Workbook
Name ______DAT10: #REF!
Name ______dat1000: #REF!
Name ______DAT11: #REF!
Name ______DAT12: #REF!
Name ______DAT3: #REF!
Name ______DAT4: #REF!
Name ______DAT5: #REF!
Name ______DAT6: #REF!
Name ______DAT7: #REF!
Name ______DAT8: #REF!
Name ______DAT9: #REF!
Name _____DAT10: #REF!
Name _____dat1000: #REF!
Name _____DAT11: #REF!
Name _____DAT12: #REF!
Name _____DAT3: #REF!
Name _____DAT4: #REF!
Name _____DAT5: #REF!
Name _____DAT6: #REF!
Name _____DAT7: #REF!
Name _____DAT8: #REF!
Name _____DAT9: #REF!
Name ____DAT10: #REF!
Name ____dat1000: #REF!
Name ____DAT11: #REF!
Name ____DAT12: #REF!
Name ____DAT3: #REF!
Name ____DAT4: #REF!
Name ____DAT5: #REF!
Name ____DAT6: #REF!
Name ____DAT7: #REF!
Name ____DAT8: #REF!
Name ____DAT9: #REF!
Name ___DAT1: #REF!
Name ___DAT10: #REF!
Name ___dat1000: #REF!
Name ___DAT11: #REF!
Name ___DAT12: #REF!
Name ___DAT2: #REF!
Name ___DAT3: #REF!
Name ___DAT4: #REF!
Name ___DAT5: #REF!
Name ___DAT6: #REF!
Name ___DAT7: #REF!
Name ___DAT8: #REF!
Name ___DAT9: #REF!
Name __DAT1: #REF!
Name __DAT10: #REF!
Name __dat1000: #REF!
Name __DAT11: #REF!
Name __DAT12: #REF!
Name __DAT2: #REF!
Name __DAT3: #REF!
Name __DAT4: #REF!
Name __DAT5: #REF!
Name __DAT6: #REF!
Name __DAT7: #REF!
Name __DAT8: #REF!
Name __DAT9: #REF!
Name _DAT1: #REF!

Sheet 減価償却費（Depreciation）
C2: Depreciation | E2: USD | I2: USD | M2: USD
A3: 部署 | C3: 減価償却費 | D3: 46113 | E3: =IF(MONTH(D3)=12,EDATE(D3,1),EDATE(D3,1)) -> 46143 | F3: =IF(MONTH(E3)=12,EDATE(E3,1),EDATE(E3,1)) -> 46174 | G3: =IF(MONTH(F3)=12,EDATE(F3,1),EDATE(F3,1)) -> 46204 | H3: =IF(MONTH(G3)=12,EDATE(G3,1),EDATE(G3,1)) -> 46235 | I3: =IF(MONTH(H3)=12,EDATE(H3,1),EDATE(H3,1)) -> 46266 | J3: =IF(MONTH(I3)=12,EDATE(I3,1),EDATE(I3,1)) -> 46296 | K3: =IF(MONTH(J3)=12,EDATE(J3,1),EDATE(J3,1)) -> 46327 | L3: =IF(MONTH(K3)=12,EDATE(K3,1),EDATE(K3,1)) -> 46357 | ... O3: =IF(MONTH(N3)=12,EDATE(N3,1),EDATE(N3,1)) -> 46447
A4: 振替総額 | C4: 建物 Building | D4: =D133 -> 324649.6 | E4: =E133 -> 324649.6 | F4: =F133 -> 324649.6 | G4: =G133 -> 324649.6 | H4: =H133 -> 324649.6 | I4: =I133 -> 324649.6 | J4: =J133 -> 324649.6 | K4: =K133 -> 324649.6 | ... O4: =O133 -> 324649.6
C5: 土地 Land | D5: =D134 -> 21912.57 | E5: =E134 -> 21912.57 | F5: =F134 -> 21912.57 | G5: =G134 -> 21912.57 | H5: =H134 -> 21912.57 | I5: =I134 -> 21912.57 | J5: =J134 -> 21912.57 | K5: =K134 -> 21912.57 | ... O5: =O134 -> 21912.57
A7: 1 | B7: 機器製造1課 | C7: 建物 Building | D7: =VLOOKUP(B8,'B&L'!$A$7:$BK$69,5,0) -> 13120.54 | E7: =VLOOKUP(B8,'B&L'!$A$7:$BK$69,10,0) -> 13142.14 | F7: =VLOOKUP(B8,'B&L'!$A$7:$BK$69,15,0) -> 12885.42 | G7: =VLOOKUP(B8,'B&L'!$A$7:$BK$69,20,0) -> 13112.58 | H7: =VLOOKUP(B8,'B&L'!$A$7:$BK$69,25,0) -> 13414.69 | I7: =VLOOKUP(B8,'B&L'!$A$7:$BK$69,30,0) -> 13414.5 | J7: =VLOOKUP(B8,'B&L'!$A$7:$BK$69,35,0) -> 13111.32 | K7: =VLOOKUP(B8,'B&L'!$A$7:$BK$69,40,0) -> 13294.21 | L7: =VLOOKUP(B8,'B&L'!$A$7:$BK$69,45,0) -> 13323.41 | M7: =VLOOKUP(B8,'B&L'!$A$7:$BK$69,50,0) -> 13484.92 | N7: =VLOOKUP(B8,'B&L'!$A$7:$BK$69,55,0) -> 14223.59 | O7: =VLOOKUP(B8,'B&L'!$A$7:$BK$69,60,0) -> 13277.16
B8: 1412000004 | C8: 土地 Land | D8: =VLOOKUP(B8,'B&L'!$A$7:$BK$69,6,0) -> 885.58 | E8: =VLOOKUP(B8,'B&L'!$A$7:$BK$69,11,0) -> 887.04 | F8: =VLOOKUP(B8,'B&L'!$A$7:$BK$69,16,0) -> 869.72 | G8: =VLOOKUP(B8,'B&L'!$A$7:$BK$69,21,0) -> 885.05 | H8: =VLOOKUP(B8,'B&L'!$A$7:$BK$69,26,0) -> 905.44 | I8: =VLOOKUP(B8,'B&L'!$A$7:$BK$69,31,0) -> 905.43 | J8: =VLOOKUP(B8,'B&L'!$A$7:$BK$69,36,0) -> 884.96 | K8: =VLOOKUP(B8,'B&L'!$A$7:$BK$69,41,0) -> 897.31 | L8: =VLOOKUP(B8,'B&L'!$A$7:$BK$69,46,0) -> 899.28 | M8: =VLOOKUP(B8,'B&L'!$A$7:$BK$69,51,0) -> 910.18 | N8: =VLOOKUP(B8,'B&L'!$A$7:$BK$69,56,0) -> 960.04 | O8: =VLOOKUP(B8,'B&L'!$A$7:$BK$69,61,0) -> 896.16
A9: 2 | B9: 機器製造2課 | C9: 建物 Building | D9: =VLOOKUP(B10,'B&L'!$A$7:$BK$69,5,0) -> 17807.79 | E9: =VLOOKUP(B10,'B&L'!$A$7:$BK$69,10,0) -> 17919.89 | F9: =VLOOKUP(B10,'B&L'!$A$7:$BK$69,15,0) -> 17978.32 | G9: =VLOOKUP(B10,'B&L'!$A$7:$BK$69,20,0) -> 17998.68 | H9: =VLOOKUP(B10,'B&L'!$A$7:$BK$69,25,0) -> 17958.43 | I9: =VLOOKUP(B10,'B&L'!$A$7:$BK$69,30,0) -> 17963.93 | J9: =VLOOKUP(B10,'B&L'!$A$7:$BK$69,35,0) -> 17945.57 | K9: =VLOOKUP(B10,'B&L'!$A$7:$BK$69,40,0) -> 17916.4 | L9: =VLOOKUP(B10,'B&L'!$A$7:$BK$69,45,0) -> 17802.57 | M9: =VLOOKUP(B10,'B&L'!$A$7:$BK$69,50,0) -> 17884.69 | N9: =VLOOKUP(B10,'B&L'!$A$7:$BK$69,55,0) -> 18164.77 | O9: =VLOOKUP(B10,'B&L'!$A$7:$BK$69,60,0) -> 17840.02
B10: 1412000005 | C10: 土地 Land | D10: =VLOOKUP(B10,'B&L'!$A$7:$BK$69,6,0) -> 1201.96 | E10: =VLOOKUP(B10,'B&L'!$A$7:$BK$69,11,0) -> 1209.52 | F10: =VLOOKUP(B10,'B&L'!$A$7:$BK$69,16,0) -> 1213.47 | G10: =VLOOKUP(B10,'B&L'!$A$7:$BK$69,21,0) -> 1214.84 | H10: =VLOOKUP(B10,'B&L'!$A$7:$BK$69,26,0) -> 1212.12 | I10: =VLOOKUP(B10,'B&L'!$A$7:$BK$69,31,0) -> 1212.49 | J10: =VLOOKUP(B10,'B&L'!$A$7:$BK$69,36,0) -> 1211.26 | K10: =VLOOKUP(B10,'B&L'!$A$7:$BK$69,41,0) -> 1209.29 | L10: =VLOOKUP(B10,'B&L'!$A$7:$BK$69,46,0) -> 1201.6 | M10: =VLOOKUP(B10,'B&L'!$A$7:$BK$69,51,0) -> 1207.15 | N10: =VLOOKUP(B10,'B&L'!$A$7:$BK$69,56,0) -> 1226.05 | O10: =VLOOKUP(B10,'B&L'!$A$7:$BK$69,61,0) -> 1204.13
A11: 3 | B11: 機器製造管理課 | C11: 建物 Building | D11: =VLOOKUP(B12,'B&L'!$A$7:$BK$69,5,0) -> 244.52 | E11: =VLOOKUP(B12,'B&L'!$A$7:$BK$69,10,0) -> 250.28 | F11: =VLOOKUP(B12,'B&L'!$A$7:$BK$69,15,0) -> 265.57 | G11: =VLOOKUP(B12,'B&L'!$A$7:$BK$69,20,0) -> 250.31 | H11: =VLOOKUP(B12,'B&L'!$A$7:$BK$69,25,0) -> 239.84 | I11: =VLOOKUP(B12,'B&L'!$A$7:$BK$69,30,0) -> 244.06 | J11: =VLOOKUP(B12,'B&L'!$A$7:$BK$69,35,0) -> 251.25 | K11: =VLOOKUP(B12,'B&L'!$A$7:$BK$69,40,0) -> 248.2 | L11: =VLOOKUP(B12,'B&L'!$A$7:$BK$69,45,0) -> 246.25 | M11: =VLOOKUP(B12,'B&L'!$A$7:$BK$69,50,0) -> 238.68 | N11: =VLOOKUP(B12,'B&L'!$A$7:$BK$69,55,0) -> 220.76 | O11: =VLOOKUP(B12,'B&L'!$A$7:$BK$69,60,0) -> 244.54
B12: 1412000062 | C12: 土地 Land | D12: =VLOOKUP(B12,'B&L'!$A$7:$BK$69,6,0) -> 16.5 | E12: =VLOOKUP(B12,'B&L'!$A$7:$BK$69,11,0) -> 16.89 | F12: =VLOOKUP(B12,'B&L'!$A$7:$BK$69,16,0) -> 17.92 | G12: =VLOOKUP(B12,'B&L'!$A$7:$BK$69,21,0) -> 16.9 | H12: =VLOOKUP(B12,'B&L'!$A$7:$BK$69,26,0) -> 16.19 | I12: =VLOOKUP(B12,'B&L'!$A$7:$BK$69,31,0) -> 16.47 | J12: =VLOOKUP(B12,'B&L'!$A$7:$BK$69,36,0) -> 16.96 | K12: =VLOOKUP(B12,'B&L'!$A$7:$BK$69,41,0) -> 16.75 | L12: =VLOOKUP(B12,'B&L'!$A$7:$BK$69,46,0) -> 16.62 | M12: =VLOOKUP(B12,'B&L'!$A$7:$BK$69,51,0) -> 16.11 | N12: =VLOOKUP(B12,'B&L'!$A$7:$BK$69,56,0) -> 14.9 | O12: =VLOOKUP(B12,'B&L'!$A$7:$BK$69,61,0) -> 16.51
A13: 4 | B13: RPS製造課 | C13: 建物 Building | D13: =VLOOKUP(B14,'B&L'!$A$7:$BK$69,5,0) -> 6380.12 | E13: =VLOOKUP(B14,'B&L'!$A$7:$BK$69,10,0) -> 6380.12 | F13: =VLOOKUP(B14,'B&L'!$A$7:$BK$69,15,0) -> 6380.12 | G13: =VLOOKUP(B14,'B&L'!$A$7:$BK$69,20,0) -> 6380.12 | H13: =VLOOKUP(B14,'B&L'!$A$7:$BK$69,25,0) -> 6380.12 | I13: =VLOOKUP(B14,'B&L'!$A$7:$BK$69,30,0) -> 6380.12 | J13: =VLOOKUP(B14,'B&L'!$A$7:$BK$69,35,0) -> 6380.12 | K13: =VLOOKUP(B14,'B&L'!$A$7:$BK$69,40,0) -> 6380.12 | L13: =VLOOKUP(B14,'B&L'!$A$7:$BK$69,45,0) -> 6380.12 | M13: =VLOOKUP(B14,'B&L'!$A$7:$BK$69,50,0) -> 6380.12 | N13: =VLOOKUP(B14,'B&L'!$A$7:$BK$69,55,0) -> 6380.12 | O13: =VLOOKUP(B14,'B&L'!$A$7:$BK$69,60,0) -> 6380.12
B14: 1412000066 | C14: 土地 Land | D14: =VLOOKUP(B14,'B&L'!$A$7:$BK$69,6,0) -> 430.63 | E14: =VLOOKUP(B14,'B&L'!$A$7:$BK$69,11,0) -> 430.63 | F14: =VLOOKUP(B14,'B&L'!$A$7:$BK$69,16,0) -> 430.63 | G14: =VLOOKUP(B14,'B&L'!$A$7:$BK$69,21,0) -> 430.63 | H14: =VLOOKUP(B14,'B&L'!$A$7:$BK$69,26,0) -> 430.63 | I14: =VLOOKUP(B14,'B&L'!$A$7:$BK$69,31,0) -> 430.63 | J14: =VLOOKUP(B14,'B&L'!$A$7:$BK$69,36,0) -> 430.63 | K14: =VLOOKUP(B14,'B&L'!$A$7:$BK$69,41,0) -> 430.63 | L14: =VLOOKUP(B14,'B&L'!$A$7:$BK$69,46,0) -> 430.63 | M14: =VLOOKUP(B14,'B&L'!$A$7:$BK$69,51,0) -> 430.63 | N14: =VLOOKUP(B14,'B&L'!$A$7:$BK$69,56,0) -> 430.63 | O14: =VLOOKUP(B14,'B&L'!$A$7:$BK$69,61,0) -> 430.63
A15: 5 | B15: 機器製造3課 | C15: 建物 Building | D15: =VLOOKUP(B16,'B&L'!$A$7:$BK$69,5,0) -> 47907.49 | E15: =VLOOKUP(B16,'B&L'!$A$7:$BK$69,10,0) -> 47628 | F15: =VLOOKUP(B16,'B&L'!$A$7:$BK$69,15,0) -> 47217.51 | G15: =VLOOKUP(B16,'B&L'!$A$7:$BK$69,20,0) -> 47502.29 | H15: =VLOOKUP(B16,'B&L'!$A$7:$BK$69,25,0) -> 47724.65 | I15: =VLOOKUP(B16,'B&L'!$A$7:$BK$69,30,0) -> 47612.51 | J15: =VLOOKUP(B16,'B&L'!$A$7:$BK$69,35,0) -> 47402.45 | K15: =VLOOKUP(B16,'B&L'!$A$7:$BK$69,40,0) -> 47494.1 | L15: =VLOOKUP(B16,'B&L'!$A$7:$BK$69,45,0) -> 47651.73 | M15: =VLOOKUP(B16,'B&L'!$A$7:$BK$69,50,0) -> 47742.78 | N15: =VLOOKUP(B16,'B&L'!$A$7:$BK$69,55,0) -> 47858.19 | O15: =VLOOKUP(B16,'B&L'!$A$7:$BK$69,60,0) -> 47661.03
B16: 1412000081 | C16: 土地 Land | D16: =VLOOKUP(B16,'B&L'!$A$7:$BK$69,6,0) -> 3233.57 | E16: =VLOOKUP(B16,'B&L'!$A$7:$BK$69,11,0) -> 3214.7 | F16: =VLOOKUP(B16,'B&L'!$A$7:$BK$69,16,0) -> 3187 | G16: =VLOOKUP(B16,'B&L'!$A$7:$BK$69,21,0) -> 3206.22 | H16: =VLOOKUP(B16,'B&L'!$A$7:$BK$69,26,0) -> 3221.23 | I16: =VLOOKUP(B16,'B&L'!$A$7:$BK$69,31,0) -> 3213.66 | J16: =VLOOKUP(B16,'B&L'!$A$7:$BK$69,36,0) -> 3199.48 | K16: =VLOOKUP(B16,'B&L'!$A$7:$BK$69,41,0) -> 3205.66 | L16: =VLOOKUP(B16,'B&L'!$A$7:$BK$69,46,0) -> 3216.3 | M16: =VLOOKUP(B16,'B&L'!$A$7:$BK$69,51,0) -> 3222.45 | N16: =VLOOKUP(B16,'B&L'!$A$7:$BK$69,56,0) -> 3230.24 | O16: =VLOOKUP(B16,'B&L'!$A$7:$BK$69,61,0) -> 3216.93
A17: 6 | B17: 電工製造課 | C17: 建物 Building | D17: =VLOOKUP(B18,'B&L'!$A$7:$BK$69,5,0) -> 5396.22 | E17: =VLOOKUP(B18,'B&L'!$A$7:$BK$69,10,0) -> 5395.95 | F17: =VLOOKUP(B18,'B&L'!$A$7:$BK$69,15,0) -> 5409.44 | G17: =VLOOKUP(B18,'B&L'!$A$7:$BK$69,20,0) -> 5396.13 | H17: =VLOOKUP(B18,'B&L'!$A$7:$BK$69,25,0) -> 5382.73 | I17: =VLOOKUP(B18,'B&L'!$A$7:$BK$69,30,0) -> 5384.14 | J17: =VLOOKUP(B18,'B&L'!$A$7:$BK$69,35,0) -> 5398.11 | K17: =VLOOKUP(B18,'B&L'!$A$7:$BK$69,40,0) -> 5389.64 | L17: =VLOOKUP(B18,'B&L'!$A$7:$BK$69,45,0) -> 5388.28 | M17: =VLOOKUP(B18,'B&L'!$A$7:$BK$69,50,0) -> 5369.23 | N17: =VLOOKUP(B18,'B&L'!$A$7:$BK$69,55,0) -> 5336.15 | O17: =VLOOKUP(B18,'B&L'!$A$7:$BK$69,60,0) -> 5379.14
B18: 1412000098 | C18: 土地 Land | D18: =VLOOKUP(B18,'B&L'!$A$7:$BK$69,6,0) -> 364.22 | E18: =VLOOKUP(B18,'B&L'!$A$7:$BK$69,11,0) -> 364.21 | F18: =VLOOKUP(B18,'B&L'!$A$7:$BK$69,16,0) -> 365.12 | G18: =VLOOKUP(B18,'B&L'!$A$7:$BK$69,21,0) -> 364.22 | H18: =VLOOKUP(B18,'B&L'!$A$7:$BK$69,26,0) -> 363.31 | I18: =VLOOKUP(B18,'B&L'!$A$7:$BK$69,31,0) -> 363.41 | J18: =VLOOKUP(B18,'B&L'!$A$7:$BK$69,36,0) -> 364.35 | K18: =VLOOKUP(B18,'B&L'!$A$7:$BK$69,41,0) -> 363.78 | L18: =VLOOKUP(B18,'B&L'!$A$7:$BK$69,46,0) -> 363.69 | M18: =VLOOKUP(B18,'B&L'!$A$7:$BK$69,51,0) -> 362.4 | N18: =VLOOKUP(B18,'B&L'!$A$7:$BK$69,56,0) -> 360.17 | O18: =VLOOKUP(B18,'B&L'!$A$7:$BK$69,61,0) -> 363.07
A19: 7 | B19: トナー製造課 | C19: 建物 Building | D19: =VLOOKUP(B20,'B&L'!$A$7:$BK$69,5,0) -> 9615.17 | E19: =VLOOKUP(B20,'B&L'!$A$7:$BK$69,10,0) -> 9671.62 | F19: =VLOOKUP(B20,'B&L'!$A$7:$BK$69,15,0) -> 9804.64 | G19: =VLOOKUP(B20,'B&L'!$A$7:$BK$69,20,0) -> 9678.64 | H19: =VLOOKUP(B20,'B&L'!$A$7:$BK$69,25,0) -> 9616.83 | I19: =VLOOKUP(B20,'B&L'!$A$7:$BK$69,30,0) -> 9655.23 | J19: =VLOOKUP(B20,'B&L'!$A$7:$BK$69,35,0) -> 9801.82 | K19: =VLOOKUP(B20,'B&L'!$A$7:$BK$69,40,0) -> 9771.68 | L19: =VLOOKUP(B20,'B&L'!$A$7:$BK$69,45,0) -> 9752.37 | M19: =VLOOKUP(B20,'B&L'!$A$7:$BK$69,50,0) -> 9677.42 | N19: =VLOOKUP(B20,'B&L'!$A$7:$BK$69,55,0) -> 9500 | O19: =VLOOKUP(B20,'B&L'!$A$7:$BK$69,60,0) -> 9735.43
B20: 1412000034 | C20: 土地 Land | D20: =VLOOKUP(B20,'B&L'!$A$7:$BK$69,6,0) -> 648.99 | E20: =VLOOKUP(B20,'B&L'!$A$7:$BK$69,11,0) -> 652.8 | F20: =VLOOKUP(B20,'B&L'!$A$7:$BK$69,16,0) -> 661.77 | G20: =VLOOKUP(B20,'B&L'!$A$7:$BK$69,21,0) -> 653.27 | H20: =VLOOKUP(B20,'B&L'!$A$7:$BK$69,26,0) -> 649.1 | I20: =VLOOKUP(B20,'B&L'!$A$7:$BK$69,31,0) -> 651.69 | J20: =VLOOKUP(B20,'B&L'!$A$7:$BK$69,36,0) -> 661.58 | K20: =VLOOKUP(B20,'B&L'!$A$7:$BK$69,41,0) -> 659.55 | L20: =VLOOKUP(B20,'B&L'!$A$7:$BK$69,46,0) -> 658.25 | M20: =VLOOKUP(B20,'B&L'!$A$7:$BK$69,51,0) -> 653.19 | N20: =VLOOKUP(B20,'B&L'!$A$7:$BK$69,56,0) -> 641.21 | O20: =VLOOKUP(B20,'B&L'!$A$7:$BK$69,61,0) -> 657.1
A21: 8 | B21: トナー生産技術 | C21: 建物 Building | D21: =VLOOKUP(B22,'B&L'!$A$7:$BK$69,5,0) -> 303.31 | E21: =VLOOKUP(B22,'B&L'!$A$7:$BK$69,10,0) -> 307.92 | F21: =VLOOKUP(B22,'B&L'!$A$7:$BK$69,15,0) -> 320.15 | G21: =VLOOKUP(B22,'B&L'!$A$7:$BK$69,20,0) -> 307.95 | H21: =VLOOKUP(B22,'B&L'!$A$7:$BK$69,25,0) -> 299.57 | I21: =VLOOKUP(B22,'B&L'!$A$7:$BK$69,30,0) -> 302.94 | J21: =VLOOKUP(B22,'B&L'!$A$7:$BK$69,35,0) -> 308.69 | K21: =VLOOKUP(B22,'B&L'!$A$7:$BK$69,40,0) -> 306.26 | L21: =VLOOKUP(B22,'B&L'!$A$7:$BK$69,45,0) -> 304.7 | M21: =VLOOKUP(B22,'B&L'!$A$7:$BK$69,50,0) -> 298.64 | N21: =VLOOKUP(B22,'B&L'!$A$7:$BK$69,55,0) -> 284.3 | O21: =VLOOKUP(B22,'B&L'!$A$7:$BK$69,60,0) -> 303.33
B22: 1412000048 | C22: 土地 Land | D22: =VLOOKUP(B22,'B&L'!$A$7:$BK$69,6,0) -> 20.47 | E22: =VLOOKUP(B22,'B&L'!$A$7:$BK$69,11,0) -> 20.78 | F22: =VLOOKUP(B22,'B&L'!$A$7:$BK$69,16,0) -> 21.61 | G22: =VLOOKUP(B22,'B&L'!$A$7:$BK$69,21,0) -> 20.79 | H22: =VLOOKUP(B22,'B&L'!$A$7:$BK$69,26,0) -> 20.22 | I22: =VLOOKUP(B22,'B&L'!$A$7:$BK$69,31,0) -> 20.45 | J22: =VLOOKUP(B22,'B&L'!$A$7:$BK$69,36,0) -> 20.84 | K22: =VLOOKUP(B22,'B&L'!$A$7:$BK$69,41,0) -> 20.67 | L22: =VLOOKUP(B22,'B&L'!$A$7:$BK$69,46,0) -> 20.57 | M22: =VLOOKUP(B22,'B&L'!$A$7:$BK$69,51,0) -> 20.16 | N22: =VLOOKUP(B22,'B&L'!$A$7:$BK$69,56,0) -> 19.19 | O22: =VLOOKUP(B22,'B&L'!$A$7:$BK$69,61,0) -> 20.47
A23: 9 | B23: トナー品質管理課 | C23: 建物 Building | D23: =VLOOKUP(B24,'B&L'!$A$7:$BK$69,5,0) -> 202.25 | E23: =VLOOKUP(B24,'B&L'!$A$7:$BK$69,10,0) -> 206.67 | F23: =VLOOKUP(B24,'B&L'!$A$7:$BK$69,15,0) -> 218.39 | G23: =VLOOKUP(B24,'B&L'!$A$7:$BK$69,20,0) -> 206.69 | H23: =VLOOKUP(B24,'B&L'!$A$7:$BK$69,25,0) -> 201.66 | I23: =VLOOKUP(B24,'B&L'!$A$7:$BK$69,30,0) -> 205.04 | J23: =VLOOKUP(B24,'B&L'!$A$7:$BK$69,35,0) -> 210.79 | K23: =VLOOKUP(B24,'B&L'!$A$7:$BK$69,40,0) -> 208.35 | L23: =VLOOKUP(B24,'B&L'!$A$7:$BK$69,45,0) -> 206.79 | M23: =VLOOKUP(B24,'B&L'!$A$7:$BK$69,50,0) -> 200.74 | N23: =VLOOKUP(B24,'B&L'!$A$7:$BK$69,55,0) -> 186.4 | O23: =VLOOKUP(B24,'B&L'!$A$7:$BK$69,60,0) -> 205.42
B24: 1412000055 | C24: 土地 Land | D24: =VLOOKUP(B24,'B&L'!$A$7:$BK$69,6,0) -> 13.65 | E24: =VLOOKUP(B24,'B&L'!$A$7:$BK$69,11,0) -> 13.95 | F24: =VLOOKUP(B24,'B&L'!$A$7:$BK$69,16,0) -> 14.74 | G24: =VLOOKUP(B24,'B&L'!$A$7:$BK$69,21,0) -> 13.95 | H24: =VLOOKUP(B24,'B&L'!$A$7:$BK$69,26,0) -> 13.61 | I24: =VLOOKUP(B24,'B&L'!$A$7:$BK$69,31,0) -> 13.84 | J24: =VLOOKUP(B24,'B&L'!$A$7:$BK$69,36,0) -> 14.23 | K24: =VLOOKUP(B24,'B&L'!$A$7:$BK$69,41,0) -> 14.06 | L24: =VLOOKUP(B24,'B&L'!$A$7:$BK$69,46,0) -> 13.96 | M24: =VLOOKUP(B24,'B&L'!$A$7:$BK$69,51,0) -> 13.55 | N24: =VLOOKUP(B24,'B&L'!$A$7:$BK$69,56,0) -> 12.58 | O24: =VLOOKUP(B24,'B&L'!$A$7:$BK$69,61,0) -> 13.87
A25: 10 | B25: トナー製造管理課 | C25: 建物 Building | D25: =VLOOKUP(B26,'B&L'!$A$7:$BK$69,5,0) -> 37.77 | E25: =VLOOKUP(B26,'B&L'!$A$7:$BK$69,10,0) -> 36.34 | F25: =VLOOKUP(B26,'B&L'!$A$7:$BK$69,15,0) -> 40.92 | G25: =VLOOKUP(B26,'B&L'!$A$7:$BK$69,20,0) -> 43.05 | H25: =VLOOKUP(B26,'B&L'!$A$7:$BK$69,25,0) -> 39.21 | I25: =VLOOKUP(B26,'B&L'!$A$7:$BK$69,30,0) -> 47.04 | J25: =VLOOKUP(B26,'B&L'!$A$7:$BK$69,35,0) -> 46.78 | K25: =VLOOKUP(B26,'B&L'!$A$7:$BK$69,40,0) -> 45.56 | L25: =VLOOKUP(B26,'B&L'!$A$7:$BK$69,45,0) -> 41.56 | M25: =VLOOKUP(B26,'B&L'!$A$7:$BK$69,50,0) -> 38.79 | N25: =VLOOKUP(B26,'B&L'!$A$7:$BK$69,55,0) -> 29.85 | O25: =VLOOKUP(B26,'B&L'!$A$7:$BK$69,60,0) -> 37.78
B26: 1412000063 | C26: 土地 Land | D26: =VLOOKUP(B26,'B&L'!$A$7:$BK$69,6,0) -> 2.55 | E26: =VLOOKUP(B26,'B&L'!$A$7:$BK$69,11,0) -> 2.45 | F26: =VLOOKUP(B26,'B&L'!$A$7:$BK$69,16,0) -> 2.76 | G26: =VLOOKUP(B26,'B&L'!$A$7:$BK$69,21,0) -> 2.91 | H26: =VLOOKUP(B26,'B&L'!$A$7:$BK$69,26,0) -> 2.65 | I26: =VLOOKUP(B26,'B&L'!$A$7:$BK$69,31,0) -> 3.18 | J26: =VLOOKUP(B26,'B&L'!$A$7:$BK$69,36,0) -> 3.16 | K26: =VLOOKUP(B26,'B&L'!$A$7:$BK$69,41,0) -> 3.08 | L26: =VLOOKUP(B26,'B&L'!$A$7:$BK$69,46,0) -> 2.81 | M26: =VLOOKUP(B26,'B&L'!$A$7:$BK$69,51,0) -> 2.62 | N26: =VLOOKUP(B26,'B&L'!$A$7:$BK$69,56,0) -> 2.01 | O26: =VLOOKUP(B26,'B&L'!$A$7:$BK$69,61,0) -> 2.55
A27: 11 | B27: 金型技術課 | C27: 建物 Building | D27: =VLOOKUP(B28,'B&L'!$A$7:$BK$69,5,0) -> 1618.4 | E27: =VLOOKUP(B28,'B&L'!$A$7:$BK$69,10,0) -> 1626.59 | F27: =VLOOKUP(B28,'B&L'!$A$7:$BK$69,15,0) -> 1634.58 | G27: =VLOOKUP(B28,'B&L'!$A$7:$BK$69,20,0) -> 1626.7 | H27: =VLOOKUP(B28,'B&L'!$A$7:$BK$69,25,0) -> 1618.77 | I27: =VLOOKUP(B28,'B&L'!$A$7:$BK$69,30,0) -> 1619.6 | J27: =VLOOKUP(B28,'B&L'!$A$7:$BK$69,35,0) -> 1627.87 | K27: =VLOOKUP(B28,'B&L'!$A$7:$BK$69,40,0) -> 1622.86 | L27: =VLOOKUP(B28,'B&L'!$A$7:$BK$69,45,0) -> 1622.05 | M27: =VLOOKUP(B28,'B&L'!$A$7:$BK$69,50,0) -> 1617.63 | N27: =VLOOKUP(B28,'B&L'!$A$7:$BK$69,55,0) -> 1596.78 | O27: =VLOOKUP(B28,'B&L'!$A$7:$BK$69,60,0) -> 1623.88
B28: 1412000044 | C28: 土地 Land | D28: =VLOOKUP(B28,'B&L'!$A$7:$BK$69,6,0) -> 109.24 | E28: =VLOOKUP(B28,'B&L'!$A$7:$BK$69,11,0) -> 109.79 | F28: =VLOOKUP(B28,'B&L'!$A$7:$BK$69,16,0) -> 110.33 | G28: =VLOOKUP(B28,'B&L'!$A$7:$BK$69,21,0) -> 109.8 | H28: =VLOOKUP(B28,'B&L'!$A$7:$BK$69,26,0) -> 109.26 | I28: =VLOOKUP(B28,'B&L'!$A$7:$BK$69,31,0) -> 109.32 | J28: =VLOOKUP(B28,'B&L'!$A$7:$BK$69,36,0) -> 109.88 | K28: =VLOOKUP(B28,'B&L'!$A$7:$BK$69,41,0) -> 109.54 | L28: =VLOOKUP(B28,'B&L'!$A$7:$BK$69,46,0) -> 109.48 | M28: =VLOOKUP(B28,'B&L'!$A$7:$BK$69,51,0) -> 109.18 | N28: =VLOOKUP(B28,'B&L'!$A$7:$BK$69,56,0) -> 107.78 | O28: =VLOOKUP(B28,'B&L'!$A$7:$BK$69,61,0) -> 109.61
A29: 12 | B29: 部品製造管理課 | C29: 建物 Building | D29: =VLOOKUP(B30,'B&L'!$A$7:$BK$69,5,0) -> 110.03 | E29: =VLOOKUP(B30,'B&L'!$A$7:$BK$69,10,0) -> 109.98 | F29: =VLOOKUP(B30,'B&L'!$A$7:$BK$69,15,0) -> 112.19 | G29: =VLOOKUP(B30,'B&L'!$A$7:$BK$69,20,0) -> 110.01 | H29: =VLOOKUP(B30,'B&L'!$A$7:$BK$69,25,0) -> 107.83 | I29: =VLOOKUP(B30,'B&L'!$A$7:$BK$69,30,0) -> 108.06 | J29: =VLOOKUP(B30,'B&L'!$A$7:$BK$69,35,0) -> 110.34 | K29: =VLOOKUP(B30,'B&L'!$A$7:$BK$69,40,0) -> 108.95 | L29: =VLOOKUP(B30,'B&L'!$A$7:$BK$69,45,0) -> 108.73 | M29: =VLOOKUP(B30,'B&L'!$A$7:$BK$69,50,0) -> 107.51 | N29: =VLOOKUP(B30,'B&L'!$A$7:$BK$69,55,0) -> 101.76 | O29: =VLOOKUP(B30,'B&L'!$A$7:$BK$69,60,0) -> 109.24
B30: 1412000087 | C30: 土地 Land | D30: =VLOOKUP(B30,'B&L'!$A$7:$BK$69,6,0) -> 7.43 | E30: =VLOOKUP(B30,'B&L'!$A$7:$BK$69,11,0) -> 7.42 | F30: =VLOOKUP(B30,'B&L'!$A$7:$BK$69,16,0) -> 7.57 | G30: =VLOOKUP(B30,'B&L'!$A$7:$BK$69,21,0) -> 7.43 | H30: =VLOOKUP(B30,'B&L'!$A$7:$BK$69,26,0) -> 7.28 | I30: =VLOOKUP(B30,'B&L'!$A$7:$BK$69,31,0) -> 7.29 | J30: =VLOOKUP(B30,'B&L'!$A$7:$BK$69,36,0) -> 7.45 | K30: =VLOOKUP(B30,'B&L'!$A$7:$BK$69,41,0) -> 7.35 | L30: =VLOOKUP(B30,'B&L'!$A$7:$BK$69,46,0) -> 7.34 | M30: =VLOOKUP(B30,'B&L'!$A$7:$BK$69,51,0) -> 7.26 | N30: =VLOOKUP(B30,'B&L'!$A$7:$BK$69,56,0) -> 6.87 | O30: =VLOOKUP(B30,'B&L'!$A$7:$BK$69,61,0) -> 7.37
A31: 13 | B31: 品質管理課 | C31: 建物 Building | D31: =VLOOKUP(B32,'B&L'!$A$7:$BK$69,5,0) -> 364.57 | E31: =VLOOKUP(B32,'B&L'!$A$7:$BK$69,10,0) -> 364.43 | F31: =VLOOKUP(B32,'B&L'!$A$7:$BK$69,15,0) -> 371.04 | G31: =VLOOKUP(B32,'B&L'!$A$7:$BK$69,20,0) -> 364.52 | H31: =VLOOKUP(B32,'B&L'!$A$7:$BK$69,25,0) -> 357.96 | I31: =VLOOKUP(B32,'B&L'!$A$7:$BK$69,30,0) -> 358.65 | J31: =VLOOKUP(B32,'B&L'!$A$7:$BK$69,35,0) -> 365.49 | K31: =VLOOKUP(B32,'B&L'!$A$7:$BK$69,40,0) -> 361.34 | L31: =VLOOKUP(B32,'B&L'!$A$7:$BK$69,45,0) -> 360.68 | M31: =VLOOKUP(B32,'B&L'!$A$7:$BK$69,50,0) -> 357.02 | N31: =VLOOKUP(B32,'B&L'!$A$7:$BK$69,55,0) -> 339.76 | O31: =VLOOKUP(B32,'B&L'!$A$7:$BK$69,60,0) -> 362.19
B32: 1412000088 | C32: 土地 Land | D32: =VLOOKUP(B32,'B&L'!$A$7:$BK$69,6,0) -> 24.61 | E32: =VLOOKUP(B32,'B&L'!$A$7:$BK$69,11,0) -> 24.6 | F32: =VLOOKUP(B32,'B&L'!$A$7:$BK$69,16,0) -> 25.04 | G32: =VLOOKUP(B32,'B&L'!$A$7:$BK$69,21,0) -> 24.6 | H32: =VLOOKUP(B32,'B&L'!$A$7:$BK$69,26,0) -> 24.16 | I32: =VLOOKUP(B32,'B&L'!$A$7:$BK$69,31,0) -> 24.21 | J32: =VLOOKUP(B32,'B&L'!$A$7:$BK$69,36,0) -> 24.67 | K32: =VLOOKUP(B32,'B&L'!$A$7:$BK$69,41,0) -> 24.39 | L32: =VLOOKUP(B32,'B&L'!$A$7:$BK$69,46,0) -> 24.34 | M32: =VLOOKUP(B32,'B&L'!$A$7:$BK$69,51,0) -> 24.1 | N32: =VLOOKUP(B32,'B&L'!$A$7:$BK$69,56,0) -> 22.93 | O32: =VLOOKUP(B32,'B&L'!$A$7:$BK$69,61,0) -> 24.45
A33: 14 | B33: 部品製造課 | C33: 建物 Building | D33: =VLOOKUP(B34,'B&L'!$A$7:$BK$69,5,0) -> 11479.77 | E33: =VLOOKUP(B34,'B&L'!$A$7:$BK$69,10,0) -> 11474.95 | F33: =VLOOKUP(B34,'B&L'!$A$7:$BK$69,15,0) -> 11502.72 | G33: =VLOOKUP(B34,'B&L'!$A$7:$BK$69,20,0) -> 11467.04 | H33: =VLOOKUP(B34,'B&L'!$A$7:$BK$69,25,0) -> 11431.69 | I33: =VLOOKUP(B34,'B&L'!$A$7:$BK$69,30,0) -> 11438.89 | J33: =VLOOKUP(B34,'B&L'!$A$7:$BK$69,35,0) -> 11475.9 | K33: =VLOOKUP(B34,'B&L'!$A$7:$BK$69,40,0) -> 11459.89 | L33: =VLOOKUP(B34,'B&L'!$A$7:$BK$69,45,0) -> 11460.65 | M33: =VLOOKUP(B34,'B&L'!$A$7:$BK$69,50,0) -> 11442.67 | N33: =VLOOKUP(B34,'B&L'!$A$7:$BK$69,55,0) -> 11357.81 | O33: =VLOOKUP(B34,'B&L'!$A$7:$BK$69,60,0) -> 11468.08
B34: 1412000056 | C34: 土地 Land | D34: =VLOOKUP(B34,'B&L'!$A$7:$BK$69,6,0) -> 774.84 | E34: =VLOOKUP(B34,'B&L'!$A$7:$BK$69,11,0) -> 774.51 | F34: =VLOOKUP(B34,'B&L'!$A$7:$BK$69,16,0) -> 776.39 | G34: =VLOOKUP(B34,'B&L'!$A$7:$BK$69,21,0) -> 773.98 | H34: =VLOOKUP(B34,'B&L'!$A$7:$BK$69,26,0) -> 771.59 | I34: =VLOOKUP(B34,'B&L'!$A$7:$BK$69,31,0) -> 772.08 | J34: =VLOOKUP(B34,'B&L'!$A$7:$BK$69,36,0) -> 774.58 | K34: =VLOOKUP(B34,'B&L'!$A$7:$BK$69,41,0) -> 773.5 | L34: =VLOOKUP(B34,'B&L'!$A$7:$BK$69,46,0) -> 773.55 | M34: =VLOOKUP(B34,'B&L'!$A$7:$BK$69,51,0) -> 772.34 | N34: =VLOOKUP(B34,'B&L'!$A$7:$BK$69,56,0) -> 766.61 | O34: =VLOOKUP(B34,'B&L'!$A$7:$BK$69,61,0) -> 774.05
A35: 15 | B35: 部品技術課 | C35: 建物 Building | D35: =VLOOKUP(B36,'B&L'!$A$7:$BK$69,5,0) -> 285.47 | E35: =VLOOKUP(B36,'B&L'!$A$7:$BK$69,10,0) -> 285.26 | F35: =VLOOKUP(B36,'B&L'!$A$7:$BK$69,15,0) -> 285.76 | G35: =VLOOKUP(B36,'B&L'!$A$7:$BK$69,20,0) -> 285.08 | H35: =VLOOKUP(B36,'B&L'!$A$7:$BK$69,25,0) -> 296.95 | I35: =VLOOKUP(B36,'B&L'!$A$7:$BK$69,30,0) -> 297.07 | J35: =VLOOKUP(B36,'B&L'!$A$7:$BK$69,35,0) -> 297.43 | K35: =VLOOKUP(B36,'B&L'!$A$7:$BK$69,40,0) -> 297.25 | L35: =VLOOKUP(B36,'B&L'!$A$7:$BK$69,45,0) -> 303.31 | M35: =VLOOKUP(B36,'B&L'!$A$7:$BK$69,50,0) -> 303 | N35: =VLOOKUP(B36,'B&L'!$A$7:$BK$69,55,0) -> 302.02 | O35: =VLOOKUP(B36,'B&L'!$A$7:$BK$69,60,0) -> 303.29
B36: 1412000080 | C36: 土地 Land | D36: =VLOOKUP(B36,'B&L'!$A$7:$BK$69,6,0) -> 19.27 | E36: =VLOOKUP(B36,'B&L'!$A$7:$BK$69,11,0) -> 19.25 | F36: =VLOOKUP(B36,'B&L'!$A$7:$BK$69,16,0) -> 19.29 | G36: =VLOOKUP(B36,'B&L'!$A$7:$BK$69,21,0) -> 19.24 | H36: =VLOOKUP(B36,'B&L'!$A$7:$BK$69,26,0) -> 20.04 | I36: =VLOOKUP(B36,'B&L'!$A$7:$BK$69,31,0) -> 20.05 | J36: =VLOOKUP(B36,'B&L'!$A$7:$BK$69,36,0) -> 20.08 | K36: =VLOOKUP(B36,'B&L'!$A$7:$BK$69,41,0) -> 20.06 | L36: =VLOOKUP(B36,'B&L'!$A$7:$BK$69,46,0) -> 20.47 | M36: =VLOOKUP(B36,'B&L'!$A$7:$BK$69,51,0) -> 20.45 | N36: =VLOOKUP(B36,'B&L'!$A$7:$BK$69,56,0) -> 20.38 | O36: =VLOOKUP(B36,'B&L'!$A$7:$BK$69,61,0) -> 20.47
A37: 16 | B37: 工程品質管理1課 | C37: 建物 Building | D37: =VLOOKUP(B38,'B&L'!$A$7:$BK$69,5,0) -> 515.11 | E37: =VLOOKUP(B38,'B&L'!$A$7:$BK$69,10,0) -> 517.01 | F37: =VLOOKUP(B38,'B&L'!$A$7:$BK$69,15,0) -> 528.79 | G37: =VLOOKUP(B38,'B&L'!$A$7:$BK$69,20,0) -> 537.95 | H37: =VLOOKUP(B38,'B&L'!$A$7:$BK$69,25,0) -> 527.24 | I37: =VLOOKUP(B38,'B&L'!$A$7:$BK$69,30,0) -> 529.92 | J37: =VLOOKUP(B38,'B&L'!$A$7:$BK$69,35,0) -> 547.65 | K37: =VLOOKUP(B38,'B&L'!$A$7:$BK$69,40,0) -> 542.32 | L37: =VLOOKUP(B38,'B&L'!$A$7:$BK$69,45,0) -> 540.74 | M37: =VLOOKUP(B38,'B&L'!$A$7:$BK$69,50,0) -> 533.6 | N37: =VLOOKUP(B38,'B&L'!$A$7:$BK$69,55,0) -> 508.82 | O37: =VLOOKUP(B38,'B&L'!$A$7:$BK$69,60,0) -> 541.27
B38: 1412000053 | C38: 土地 Land | D38: =VLOOKUP(B38,'B&L'!$A$7:$BK$69,6,0) -> 34.77 | E38: =VLOOKUP(B38,'B&L'!$A$7:$BK$69,11,0) -> 34.9 | F38: =VLOOKUP(B38,'B&L'!$A$7:$BK$69,16,0) -> 35.69 | G38: =VLOOKUP(B38,'B&L'!$A$7:$BK$69,21,0) -> 36.31 | H38: =VLOOKUP(B38,'B&L'!$A$7:$BK$69,26,0) -> 35.59 | I38: =VLOOKUP(B38,'B&L'!$A$7:$BK$69,31,0) -> 35.77 | J38: =VLOOKUP(B38,'B&L'!$A$7:$BK$69,36,0) -> 36.96 | K38: =VLOOKUP(B38,'B&L'!$A$7:$BK$69,41,0) -> 36.6 | L38: =VLOOKUP(B38,'B&L'!$A$7:$BK$69,46,0) -> 36.5 | M38: =VLOOKUP(B38,'B&L'!$A$7:$BK$69,51,0) -> 36.02 | N38: =VLOOKUP(B38,'B&L'!$A$7:$BK$69,56,0) -> 34.34 | O38: =VLOOKUP(B38,'B&L'!$A$7:$BK$69,61,0) -> 36.53
A39: 17 | B39: 工程品質管理2課 | C39: 建物 Building | D39: =VLOOKUP(B40,'B&L'!$A$7:$BK$69,5,0) -> 1356.41 | E39: =VLOOKUP(B40,'B&L'!$A$7:$BK$69,10,0) -> 1357.9 | F39: =VLOOKUP(B40,'B&L'!$A$7:$BK$69,15,0) -> 1404.02 | G39: =VLOOKUP(B40,'B&L'!$A$7:$BK$69,20,0) -> 1358.44 | H39: =VLOOKUP(B40,'B&L'!$A$7:$BK$69,25,0) -> 1315.31 | I39: =VLOOKUP(B40,'B&L'!$A$7:$BK$69,30,0) -> 1321.6 | J39: =VLOOKUP(B40,'B&L'!$A$7:$BK$69,35,0) -> 1364.46 | K39: =VLOOKUP(B40,'B&L'!$A$7:$BK$69,40,0) -> 1339.22 | L39: =VLOOKUP(B40,'B&L'!$A$7:$BK$69,45,0) -> 1334.34 | M39: =VLOOKUP(B40,'B&L'!$A$7:$BK$69,50,0) -> 1309.33 | N39: =VLOOKUP(B40,'B&L'!$A$7:$BK$69,55,0) -> 1201.37 | O39: =VLOOKUP(B40,'B&L'!$A$7:$BK$69,60,0) -> 1341.93
B40: 1412000104 | C40: 土地 Land | D40: =VLOOKUP(B40,'B&L'!$A$7:$BK$69,6,0) -> 91.55 | E40: =VLOOKUP(B40,'B&L'!$A$7:$BK$69,11,0) -> 91.65 | F40: =VLOOKUP(B40,'B&L'!$A$7:$BK$69,16,0) -> 94.77 | G40: =VLOOKUP(B40,'B&L'!$A$7:$BK$69,21,0) -> 91.69 | H40: =VLOOKUP(B40,'B&L'!$A$7:$BK$69,26,0) -> 88.78 | I40: =VLOOKUP(B40,'B&L'!$A$7:$BK$69,31,0) -> 89.2 | J40: =VLOOKUP(B40,'B&L'!$A$7:$BK$69,36,0) -> 92.1 | K40: =VLOOKUP(B40,'B&L'!$A$7:$BK$69,41,0) -> 90.39 | L40: =VLOOKUP(B40,'B&L'!$A$7:$BK$69,46,0) -> 90.06 | M40: =VLOOKUP(B40,'B&L'!$A$7:$BK$69,51,0) -> 88.37 | N40: =VLOOKUP(B40,'B&L'!$A$7:$BK$69,56,0) -> 81.09 | O40: =VLOOKUP(B40,'B&L'!$A$7:$BK$69,61,0) -> 90.58
A41: 18 | B41: 工程品質管理3課 | C41: 建物 Building | D41: =VLOOKUP(B42,'B&L'!$A$7:$BK$69,5,0) -> 319.76 | E41: =VLOOKUP(B42,'B&L'!$A$7:$BK$69,10,0) -> 320.2 | F41: =VLOOKUP(B42,'B&L'!$A$7:$BK$69,15,0) -> 326.64 | G41: =VLOOKUP(B42,'B&L'!$A$7:$BK$69,20,0) -> 320.26 | H41: =VLOOKUP(B42,'B&L'!$A$7:$BK$69,25,0) -> 314.49 | I41: =VLOOKUP(B42,'B&L'!$A$7:$BK$69,30,0) -> 315.51 | J41: =VLOOKUP(B42,'B&L'!$A$7:$BK$69,35,0) -> 321.03 | K41: =VLOOKUP(B42,'B&L'!$A$7:$BK$69,40,0) -> 317.86 | L41: =VLOOKUP(B42,'B&L'!$A$7:$BK$69,45,0) -> 317.16 | M41: =VLOOKUP(B42,'B&L'!$A$7:$BK$69,50,0) -> 313.71 | N41: =VLOOKUP(B42,'B&L'!$A$7:$BK$69,55,0) -> 299.81 | O41: =VLOOKUP(B42,'B&L'!$A$7:$BK$69,60,0) -> 317.94
B42: 1412000105 | C42: 土地 Land | D42: =VLOOKUP(B42,'B&L'!$A$7:$BK$69,6,0) -> 21.58 | E42: =VLOOKUP(B42,'B&L'!$A$7:$BK$69,11,0) -> 21.61 | F42: =VLOOKUP(B42,'B&L'!$A$7:$BK$69,16,0) -> 22.05 | G42: =VLOOKUP(B42,'B&L'!$A$7:$BK$69,21,0) -> 21.62 | H42: =VLOOKUP(B42,'B&L'!$A$7:$BK$69,26,0) -> 21.23 | I42: =VLOOKUP(B42,'B&L'!$A$7:$BK$69,31,0) -> 21.3 | J42: =VLOOKUP(B42,'B&L'!$A$7:$BK$69,36,0) -> 21.67 | K42: =VLOOKUP(B42,'B&L'!$A$7:$BK$69,41,0) -> 21.45 | L42: =VLOOKUP(B42,'B&L'!$A$7:$BK$69,46,0) -> 21.41 | M42: =VLOOKUP(B42,'B&L'!$A$7:$BK$69,51,0) -> 21.17 | N42: =VLOOKUP(B42,'B&L'!$A$7:$BK$69,56,0) -> 20.24 | O42: =VLOOKUP(B42,'B&L'!$A$7:$BK$69,61,0) -> 21.46
A43: 19 | B43: 工程品質管理4課 | C43: 建物 Building | D43: =VLOOKUP(B44,'B&L'!$A$7:$BK$69,5,0) -> 107.26 | E43: =VLOOKUP(B44,'B&L'!$A$7:$BK$69,10,0) -> 117.36 | F43: =VLOOKUP(B44,'B&L'!$A$7:$BK$69,15,0) -> 124.5 | G43: =VLOOKUP(B44,'B&L'!$A$7:$BK$69,20,0) -> 117.38 | H43: =VLOOKUP(B44,'B&L'!$A$7:$BK$69,25,0) -> 112.49 | I43: =VLOOKUP(B44,'B&L'!$A$7:$BK$69,30,0) -> 114.46 | J43: =VLOOKUP(B44,'B&L'!$A$7:$BK$69,35,0) -> 117.81 | K43: =VLOOKUP(B44,'B&L'!$A$7:$BK$69,40,0) -> 116.39 | L43: =VLOOKUP(B44,'B&L'!$A$7:$BK$69,45,0) -> 115.48 | M43: =VLOOKUP(B44,'B&L'!$A$7:$BK$69,50,0) -> 111.95 | N43: =VLOOKUP(B44,'B&L'!$A$7:$BK$69,55,0) -> 103.59 | O43: =VLOOKUP(B44,'B&L'!$A$7:$BK$69,60,0) -> 114.69
B44: 1412000075 | C44: 土地 Land | D44: =VLOOKUP(B44,'B&L'!$A$7:$BK$69,6,0) -> 7.24 | E44: =VLOOKUP(B44,'B&L'!$A$7:$BK$69,11,0) -> 7.92 | F44: =VLOOKUP(B44,'B&L'!$A$7:$BK$69,16,0) -> 8.4 | G44: =VLOOKUP(B44,'B&L'!$A$7:$BK$69,21,0) -> 7.92 | H44: =VLOOKUP(B44,'B&L'!$A$7:$BK$69,26,0) -> 7.59 | I44: =VLOOKUP(B44,'B&L'!$A$7:$BK$69,31,0) -> 7.73 | J44: =VLOOKUP(B44,'B&L'!$A$7:$BK$69,36,0) -> 7.95 | K44: =VLOOKUP(B44,'B&L'!$A$7:$BK$69,41,0) -> 7.86 | L44: =VLOOKUP(B44,'B&L'!$A$7:$BK$69,46,0) -> 7.79 | M44: =VLOOKUP(B44,'B&L'!$A$7:$BK$69,51,0) -> 7.56 | N44: =VLOOKUP(B44,'B&L'!$A$7:$BK$69,56,0) -> 6.99 | O44: =VLOOKUP(B44,'B&L'!$A$7:$BK$69,61,0) -> 7.74
A45: 20 | B45: 生産管理課 | C45: 建物 Building | D45: =VLOOKUP(B46,'B&L'!$A$7:$BK$69,5,0) -> 82.51 | E45: =VLOOKUP(B46,'B&L'!$A$7:$BK$69,10,0) -> 83.83 | F45: =VLOOKUP(B46,'B&L'!$A$7:$BK$69,15,0) -> 88.93 | G45: =VLOOKUP(B46,'B&L'!$A$7:$BK$69,20,0) -> 83.84 | H45: =VLOOKUP(B46,'B&L'!$A$7:$BK$69,25,0) -> 80.35 | I45: =VLOOKUP(B46,'B&L'!$A$7:$BK$69,30,0) -> 81.76 | J45: =VLOOKUP(B46,'B&L'!$A$7:$BK$69,35,0) -> 84.15 | K45: =VLOOKUP(B46,'B&L'!$A$7:$BK$69,40,0) -> 83.14 | L45: =VLOOKUP(B46,'B&L'!$A$7:$BK$69,45,0) -> 82.49 | M45: =VLOOKUP(B46,'B&L'!$A$7:$BK$69,50,0) -> 79.96 | N45: =VLOOKUP(B46,'B&L'!$A$7:$BK$69,55,0) -> 73.99 | O45: =VLOOKUP(B46,'B&L'!$A$7:$BK$69,60,0) -> 81.92
B46: 1412000008 | C46: 土地 Land | D46: =VLOOKUP(B46,'B&L'!$A$7:$BK$69,6,0) -> 5.57 | E46: =VLOOKUP(B46,'B&L'!$A$7:$BK$69,11,0) -> 5.66 | F46: =VLOOKUP(B46,'B&L'!$A$7:$BK$69,16,0) -> 6 | G46: =VLOOKUP(B46,'B&L'!$A$7:$BK$69,21,0) -> 5.66 | H46: =VLOOKUP(B46,'B&L'!$A$7:$BK$69,26,0) -> 5.42 | I46: =VLOOKUP(B46,'B&L'!$A$7:$BK$69,31,0) -> 5.52 | J46: =VLOOKUP(B46,'B&L'!$A$7:$BK$69,36,0) -> 5.68 | K46: =VLOOKUP(B46,'B&L'!$A$7:$BK$69,41,0) -> 5.61 | L46: =VLOOKUP(B46,'B&L'!$A$7:$BK$69,46,0) -> 5.57 | M46: =VLOOKUP(B46,'B&L'!$A$7:$BK$69,51,0) -> 5.4 | N46: =VLOOKUP(B46,'B&L'!$A$7:$BK$69,56,0) -> 4.99 | O46: =VLOOKUP(B46,'B&L'!$A$7:$BK$69,61,0) -> 5.53
A47: 21 | B47: 採算管理課 | C47: 建物 Building | D47: =VLOOKUP(B48,'B&L'!$A$7:$BK$69,5,0) -> 49.51 | E47: =VLOOKUP(B48,'B&L'!$A$7:$BK$69,10,0) -> 50.3 | F47: =VLOOKUP(B48,'B&L'!$A$7:$BK$69,15,0) -> 53.36 | G47: =VLOOKUP(B48,'B&L'!$A$7:$BK$69,20,0) -> 50.31 | H47: =VLOOKUP(B48,'B&L'!$A$7:$BK$69,25,0) -> 48.21 | I47: =VLOOKUP(B48,'B&L'!$A$7:$BK$69,30,0) -> 49.05 | J47: =VLOOKUP(B48,'B&L'!$A$7:$BK$69,35,0) -> 50.49 | K47: =VLOOKUP(B48,'B&L'!$A$7:$BK$69,40,0) -> 49.88 | L47: =VLOOKUP(B48,'B&L'!$A$7:$BK$69,45,0) -> 49.49 | M47: =VLOOKUP(B48,'B&L'!$A$7:$BK$69,50,0) -> 47.98 | N47: =VLOOKUP(B48,'B&L'!$A$7:$BK$69,55,0) -> 44.39 | O47: =VLOOKUP(B48,'B&L'!$A$7:$BK$69,60,0) -> 49.15
B48: 1412000010 | C48: 土地 Land | D48: =VLOOKUP(B48,'B&L'!$A$7:$BK$69,6,0) -> 3.34 | E48: =VLOOKUP(B48,'B&L'!$A$7:$BK$69,11,0) -> 3.39 | F48: =VLOOKUP(B48,'B&L'!$A$7:$BK$69,16,0) -> 3.6 | G48: =VLOOKUP(B48,'B&L'!$A$7:$BK$69,21,0) -> 3.4 | H48: =VLOOKUP(B48,'B&L'!$A$7:$BK$69,26,0) -> 3.25 | I48: =VLOOKUP(B48,'B&L'!$A$7:$BK$69,31,0) -> 3.31 | J48: =VLOOKUP(B48,'B&L'!$A$7:$BK$69,36,0) -> 3.41 | K48: =VLOOKUP(B48,'B&L'!$A$7:$BK$69,41,0) -> 3.37 | L48: =VLOOKUP(B48,'B&L'!$A$7:$BK$69,46,0) -> 3.34 | M48: =VLOOKUP(B48,'B&L'!$A$7:$BK$69,51,0) -> 3.24 | N48: =VLOOKUP(B48,'B&L'!$A$7:$BK$69,56,0) -> 3 | O48: =VLOOKUP(B48,'B&L'!$A$7:$BK$69,61,0) -> 3.32
A49: 22 | B49: OC課 | C49: 建物 Building | D49: =VLOOKUP(B50,'B&L'!$A$7:$BK$69,5,0) -> 41.25 | E49: =VLOOKUP(B50,'B&L'!$A$7:$BK$69,10,0) -> 41.92 | F49: =VLOOKUP(B50,'B&L'!$A$7:$BK$69,15,0) -> 44.46 | G49: =VLOOKUP(B50,'B&L'!$A$7:$BK$69,20,0) -> 41.92 | H49: =VLOOKUP(B50,'B&L'!$A$7:$BK$69,25,0) -> 40.18 | I49: =VLOOKUP(B50,'B&L'!$A$7:$BK$69,30,0) -> 40.88 | J49: =VLOOKUP(B50,'B&L'!$A$7:$BK$69,35,0) -> 42.08 | K49: =VLOOKUP(B50,'B&L'!$A$7:$BK$69,40,0) -> 41.57 | L49: =VLOOKUP(B50,'B&L'!$A$7:$BK$69,45,0) -> 41.24 | M49: =VLOOKUP(B50,'B&L'!$A$7:$BK$69,50,0) -> 39.98 | N49: =VLOOKUP(B50,'B&L'!$A$7:$BK$69,55,0) -> 37 | O49: =VLOOKUP(B50,'B&L'!$A$7:$BK$69,60,0) -> 40.96
B50: 1412000094 | C50: 土地 Land | D50: =VLOOKUP(B50,'B&L'!$A$7:$BK$69,6,0) -> 2.78 | E50: =VLOOKUP(B50,'B&L'!$A$7:$BK$69,11,0) -> 2.83 | F50: =VLOOKUP(B50,'B&L'!$A$7:$BK$69,16,0) -> 3 | G50: =VLOOKUP(B50,'B&L'!$A$7:$BK$69,21,0) -> 2.83 | H50: =VLOOKUP(B50,'B&L'!$A$7:$BK$69,26,0) -> 2.71 | I50: =VLOOKUP(B50,'B&L'!$A$7:$BK$69,31,0) -> 2.76 | J50: =VLOOKUP(B50,'B&L'!$A$7:$BK$69,36,0) -> 2.84 | K50: =VLOOKUP(B50,'B&L'!$A$7:$BK$69,41,0) -> 2.81 | L50: =VLOOKUP(B50,'B&L'!$A$7:$BK$69,46,0) -> 2.78 | M50: =VLOOKUP(B50,'B&L'!$A$7:$BK$69,51,0) -> 2.7 | N50: =VLOOKUP(B50,'B&L'!$A$7:$BK$69,56,0) -> 2.5 | O50: =VLOOKUP(B50,'B&L'!$A$7:$BK$69,61,0) -> 2.76
A51: 23 | B51: マスター管理課 | C51: 建物 Building | D51: =VLOOKUP(B52,'B&L'!$A$7:$BK$69,5,0) -> 115.51 | E51: =VLOOKUP(B52,'B&L'!$A$7:$BK$69,10,0) -> 117.36 | F51: =VLOOKUP(B52,'B&L'!$A$7:$BK$69,15,0) -> 124.5 | G51: =VLOOKUP(B52,'B&L'!$A$7:$BK$69,20,0) -> 117.38 | H51: =VLOOKUP(B52,'B&L'!$A$7:$BK$69,25,0) -> 112.49 | I51: =VLOOKUP(B52,'B&L'!$A$7:$BK$69,30,0) -> 114.46 | J51: =VLOOKUP(B52,'B&L'!$A$7:$BK$69,35,0) -> 117.81 | K51: =VLOOKUP(B52,'B&L'!$A$7:$BK$69,40,0) -> 116.39 | L51: =VLOOKUP(B52,'B&L'!$A$7:$BK$69,45,0) -> 115.48 | M51: =VLOOKUP(B52,'B&L'!$A$7:$BK$69,50,0) -> 111.95 | N51: =VLOOKUP(B52,'B&L'!$A$7:$BK$69,55,0) -> 103.59 | O51: =VLOOKUP(B52,'B&L'!$A$7:$BK$69,60,0) -> 114.69
B52: 1412000054 | C52: 土地 Land | D52: =VLOOKUP(B52,'B&L'!$A$7:$BK$69,6,0) -> 7.8 | E52: =VLOOKUP(B52,'B&L'!$A$7:$BK$69,11,0) -> 7.92 | F52: =VLOOKUP(B52,'B&L'!$A$7:$BK$69,16,0) -> 8.4 | G52: =VLOOKUP(B52,'B&L'!$A$7:$BK$69,21,0) -> 7.92 | H52: =VLOOKUP(B52,'B&L'!$A$7:$BK$69,26,0) -> 7.59 | I52: =VLOOKUP(B52,'B&L'!$A$7:$BK$69,31,0) -> 7.73 | J52: =VLOOKUP(B52,'B&L'!$A$7:$BK$69,36,0) -> 7.95 | K52: =VLOOKUP(B52,'B&L'!$A$7:$BK$69,41,0) -> 7.86 | L52: =VLOOKUP(B52,'B&L'!$A$7:$BK$69,46,0) -> 7.79 | M52: =VLOOKUP(B52,'B&L'!$A$7:$BK$69,51,0) -> 7.56 | N52: =VLOOKUP(B52,'B&L'!$A$7:$BK$69,56,0) -> 6.99 | O52: =VLOOKUP(B52,'B&L'!$A$7:$BK$69,61,0) -> 7.74
A53: 24 | B53: 部品管理1課 | C53: 建物 Building | D53: =VLOOKUP(B54,'B&L'!$A$7:$BK$69,5,0) -> 30651.3 | E53: =VLOOKUP(B54,'B&L'!$A$7:$BK$69,10,0) -> 30651.11 | F53: =VLOOKUP(B54,'B&L'!$A$7:$BK$69,15,0) -> 30681.83 | G53: =VLOOKUP(B54,'B&L'!$A$7:$BK$69,20,0) -> 30647.34 | H53: =VLOOKUP(B54,'B&L'!$A$7:$BK$69,25,0) -> 30590.28 | I53: =VLOOKUP(B54,'B&L'!$A$7:$BK$69,30,0) -> 30589.59 | J53: =VLOOKUP(B54,'B&L'!$A$7:$BK$69,35,0) -> 30613.76 | K53: =VLOOKUP(B54,'B&L'!$A$7:$BK$69,40,0) -> 30596.86 | L53: =VLOOKUP(B54,'B&L'!$A$7:$BK$69,45,0) -> 30594 | M53: =VLOOKUP(B54,'B&L'!$A$7:$BK$69,50,0) -> 30578.61 | N53: =VLOOKUP(B54,'B&L'!$A$7:$BK$69,55,0) -> 30507.78 | O53: =VLOOKUP(B54,'B&L'!$A$7:$BK$69,60,0) -> 30595.8
B54: 1412000036 | C54: 土地 Land | D54: =VLOOKUP(B54,'B&L'!$A$7:$BK$69,6,0) -> 2068.84 | E54: =VLOOKUP(B54,'B&L'!$A$7:$BK$69,11,0) -> 2068.83 | F54: =VLOOKUP(B54,'B&L'!$A$7:$BK$69,16,0) -> 2070.9 | G54: =VLOOKUP(B54,'B&L'!$A$7:$BK$69,21,0) -> 2068.57 | H54: =VLOOKUP(B54,'B&L'!$A$7:$BK$69,26,0) -> 2064.72 | I54: =VLOOKUP(B54,'B&L'!$A$7:$BK$69,31,0) -> 2064.68 | J54: =VLOOKUP(B54,'B&L'!$A$7:$BK$69,36,0) -> 2066.31 | K54: =VLOOKUP(B54,'B&L'!$A$7:$BK$69,41,0) -> 2065.17 | L54: =VLOOKUP(B54,'B&L'!$A$7:$BK$69,46,0) -> 2064.97 | M54: =VLOOKUP(B54,'B&L'!$A$7:$BK$69,51,0) -> 2063.94 | N54: =VLOOKUP(B54,'B&L'!$A$7:$BK$69,56,0) -> 2059.16 | O54: =VLOOKUP(B54,'B&L'!$A$7:$BK$69,61,0) -> 2065.1
A55: 25 | B55: 部品管理2課 | C55: 建物 Building | D55: =VLOOKUP(B56,'B&L'!$A$7:$BK$69,5,0) -> 51406.91 | E55: =VLOOKUP(B56,'B&L'!$A$7:$BK$69,10,0) -> 51402.36 | F55: =VLOOKUP(B56,'B&L'!$A$7:$BK$69,15,0) -> 51464.1 | G55: =VLOOKUP(B56,'B&L'!$A$7:$BK$69,20,0) -> 51394.85 | H55: =VLOOKUP(B56,'B&L'!$A$7:$BK$69,25,0) -> 51330.71 | I55: =VLOOKUP(B56,'B&L'!$A$7:$BK$69,30,0) -> 51322.46 | J55: =VLOOKUP(B56,'B&L'!$A$7:$BK$69,35,0) -> 51383.03 | K55: =VLOOKUP(B56,'B&L'!$A$7:$BK$69,40,0) -> 51340.21 | L55: =VLOOKUP(B56,'B&L'!$A$7:$BK$69,45,0) -> 51329.61 | M55: =VLOOKUP(B56,'B&L'!$A$7:$BK$69,50,0) -> 51290.71 | N55: =VLOOKUP(B56,'B&L'!$A$7:$BK$69,55,0) -> 51130.29 | O55: =VLOOKUP(B56,'B&L'!$A$7:$BK$69,60,0) -> 51334.78
B56: 1412000103 | C56: 土地 Land | D56: =VLOOKUP(B56,'B&L'!$A$7:$BK$69,6,0) -> 3469.76 | E56: =VLOOKUP(B56,'B&L'!$A$7:$BK$69,11,0) -> 3469.46 | F56: =VLOOKUP(B56,'B&L'!$A$7:$BK$69,16,0) -> 3473.62 | G56: =VLOOKUP(B56,'B&L'!$A$7:$BK$69,21,0) -> 3468.95 | H56: =VLOOKUP(B56,'B&L'!$A$7:$BK$69,26,0) -> 3464.62 | I56: =VLOOKUP(B56,'B&L'!$A$7:$BK$69,31,0) -> 3464.06 | J56: =VLOOKUP(B56,'B&L'!$A$7:$BK$69,36,0) -> 3468.15 | K56: =VLOOKUP(B56,'B&L'!$A$7:$BK$69,41,0) -> 3465.26 | L56: =VLOOKUP(B56,'B&L'!$A$7:$BK$69,46,0) -> 3464.55 | M56: =VLOOKUP(B56,'B&L'!$A$7:$BK$69,51,0) -> 3461.92 | N56: =VLOOKUP(B56,'B&L'!$A$7:$BK$69,56,0) -> 3451.09 | O56: =VLOOKUP(B56,'B&L'!$A$7:$BK$69,61,0) -> 3464.9
A57: 26 | B57: 製品管理課 | C57: 建物 Building | D57: =VLOOKUP(B58,'B&L'!$A$7:$BK$69,5,0) -> 36364.5 | E57: =VLOOKUP(B58,'B&L'!$A$7:$BK$69,10,0) -> 36365.3 | F57: =VLOOKUP(B58,'B&L'!$A$7:$BK$69,15,0) -> 36381.26 | G57: =VLOOKUP(B58,'B&L'!$A$7:$BK$69,20,0) -> 36361.28 | H57: =VLOOKUP(B58,'B&L'!$A$7:$BK$69,25,0) -> 36350.84 | I57: =VLOOKUP(B58,'B&L'!$A$7:$BK$69,30,0) -> 36349.28 | J57: =VLOOKUP(B58,'B&L'!$A$7:$BK$69,35,0) -> 36363.2 | K57: =VLOOKUP(B58,'B&L'!$A$7:$BK$69,40,0) -> 36355.12 | L57: =VLOOKUP(B58,'B&L'!$A$7:$BK$69,45,0) -> 36349.4 | M57: =VLOOKUP(B58,'B&L'!$A$7:$BK$69,50,0) -> 36341.11 | N57: =VLOOKUP(B58,'B&L'!$A$7:$BK$69,55,0) -> 36306.77 | O57: =VLOOKUP(B58,'B&L'!$A$7:$BK$69,60,0) -> 36347.45
B58: 1412000072 | C58: 土地 Land | D58: =VLOOKUP(B58,'B&L'!$A$7:$BK$69,6,0) -> 2454.46 | E58: =VLOOKUP(B58,'B&L'!$A$7:$BK$69,11,0) -> 2454.51 | F58: =VLOOKUP(B58,'B&L'!$A$7:$BK$69,16,0) -> 2455.59 | G58: =VLOOKUP(B58,'B&L'!$A$7:$BK$69,21,0) -> 2454.24 | H58: =VLOOKUP(B58,'B&L'!$A$7:$BK$69,26,0) -> 2453.54 | I58: =VLOOKUP(B58,'B&L'!$A$7:$BK$69,31,0) -> 2453.43 | J58: =VLOOKUP(B58,'B&L'!$A$7:$BK$69,36,0) -> 2454.37 | K58: =VLOOKUP(B58,'B&L'!$A$7:$BK$69,41,0) -> 2453.83 | L58: =VLOOKUP(B58,'B&L'!$A$7:$BK$69,46,0) -> 2453.44 | M58: =VLOOKUP(B58,'B&L'!$A$7:$BK$69,51,0) -> 2452.88 | N58: =VLOOKUP(B58,'B&L'!$A$7:$BK$69,56,0) -> 2450.56 | O58: =VLOOKUP(B58,'B&L'!$A$7:$BK$69,61,0) -> 2453.31
A59: 27 | B59: 物流管理課 | C59: 建物 Building | D59: =VLOOKUP(B60,'B&L'!$A$7:$BK$69,5,0) -> 123.76 | E59: =VLOOKUP(B60,'B&L'!$A$7:$BK$69,10,0) -> 125.75 | F59: =VLOOKUP(B60,'B&L'!$A$7:$BK$69,15,0) -> 133.39 | G59: =VLOOKUP(B60,'B&L'!$A$7:$BK$69,20,0) -> 125.76 | H59: =VLOOKUP(B60,'B&L'!$A$7:$BK$69,25,0) -> 120.53 | I59: =VLOOKUP(B60,'B&L'!$A$7:$BK$69,30,0) -> 122.64 | J59: =VLOOKUP(B60,'B&L'!$A$7:$BK$69,35,0) -> 126.23 | K59: =VLOOKUP(B60,'B&L'!$A$7:$BK$69,40,0) -> 124.71 | L59: =VLOOKUP(B60,'B&L'!$A$7:$BK$69,45,0) -> 123.73 | M59: =VLOOKUP(B60,'B&L'!$A$7:$BK$69,50,0) -> 119.95 | N59: =VLOOKUP(B60,'B&L'!$A$7:$BK$69,55,0) -> 110.99 | O59: =VLOOKUP(B60,'B&L'!$A$7:$BK$69,60,0) -> 122.88
B60: 1412000073 | C60: 土地 Land | D60: =VLOOKUP(B60,'B&L'!$A$7:$BK$69,6,0) -> 8.35 | E60: =VLOOKUP(B60,'B&L'!$A$7:$BK$69,11,0) -> 8.49 | F60: =VLOOKUP(B60,'B&L'!$A$7:$BK$69,16,0) -> 9 | G60: =VLOOKUP(B60,'B&L'!$A$7:$BK$69,21,0) -> 8.49 | H60: =VLOOKUP(B60,'B&L'!$A$7:$BK$69,26,0) -> 8.14 | I60: =VLOOKUP(B60,'B&L'!$A$7:$BK$69,31,0) -> 8.28 | J60: =VLOOKUP(B60,'B&L'!$A$7:$BK$69,36,0) -> 8.52 | K60: =VLOOKUP(B60,'B&L'!$A$7:$BK$69,41,0) -> 8.42 | L60: =VLOOKUP(B60,'B&L'!$A$7:$BK$69,46,0) -> 8.35 | M60: =VLOOKUP(B60,'B&L'!$A$7:$BK$69,51,0) -> 8.1 | N60: =VLOOKUP(B60,'B&L'!$A$7:$BK$69,56,0) -> 7.49 | O60: =VLOOKUP(B60,'B&L'!$A$7:$BK$69,61,0) -> 8.29
A61: 28 | B61: メカ製造技術1課 | C61: 建物 Building | D61: =VLOOKUP(B62,'B&L'!$A$7:$BK$69,5,0) -> 244.09 | E61: =VLOOKUP(B62,'B&L'!$A$7:$BK$69,10,0) -> 245.37 | F61: =VLOOKUP(B62,'B&L'!$A$7:$BK$69,15,0) -> 283.68 | G61: =VLOOKUP(B62,'B&L'!$A$7:$BK$69,20,0) -> 275.75 | H61: =VLOOKUP(B62,'B&L'!$A$7:$BK$69,25,0) -> 266.32 | I61: =VLOOKUP(B62,'B&L'!$A$7:$BK$69,30,0) -> 270.12 | J61: =VLOOKUP(B62,'B&L'!$A$7:$BK$69,35,0) -> 276.59 | K61: =VLOOKUP(B62,'B&L'!$A$7:$BK$69,40,0) -> 273.85 | L61: =VLOOKUP(B62,'B&L'!$A$7:$BK$69,45,0) -> 272.09 | M61: =VLOOKUP(B62,'B&L'!$A$7:$BK$69,50,0) -> 271.55 | N61: =VLOOKUP(B62,'B&L'!$A$7:$BK$69,55,0) -> 254.83 | O61: =VLOOKUP(B62,'B&L'!$A$7:$BK$69,60,0) -> 277.02
B62: 1412000006 | C62: 土地 Land | D62: =VLOOKUP(B62,'B&L'!$A$7:$BK$69,6,0) -> 16.48 | E62: =VLOOKUP(B62,'B&L'!$A$7:$BK$69,11,0) -> 16.56 | F62: =VLOOKUP(B62,'B&L'!$A$7:$BK$69,16,0) -> 19.15 | G62: =VLOOKUP(B62,'B&L'!$A$7:$BK$69,21,0) -> 18.61 | H62: =VLOOKUP(B62,'B&L'!$A$7:$BK$69,26,0) -> 17.98 | I62: =VLOOKUP(B62,'B&L'!$A$7:$BK$69,31,0) -> 18.23 | J62: =VLOOKUP(B62,'B&L'!$A$7:$BK$69,36,0) -> 18.67 | K62: =VLOOKUP(B62,'B&L'!$A$7:$BK$69,41,0) -> 18.48 | L62: =VLOOKUP(B62,'B&L'!$A$7:$BK$69,46,0) -> 18.37 | M62: =VLOOKUP(B62,'B&L'!$A$7:$BK$69,51,0) -> 18.33 | N62: =VLOOKUP(B62,'B&L'!$A$7:$BK$69,56,0) -> 17.2 | O62: =VLOOKUP(B62,'B&L'!$A$7:$BK$69,61,0) -> 18.7
A63: 29 | B63: メカ製造技術2課 | C63: 建物 Building | D63: =VLOOKUP(B64,'B&L'!$A$7:$BK$69,5,0) -> 207.78 | E63: =VLOOKUP(B64,'B&L'!$A$7:$BK$69,10,0) -> 209 | F63: =VLOOKUP(B64,'B&L'!$A$7:$BK$69,15,0) -> 229.61 | G63: =VLOOKUP(B64,'B&L'!$A$7:$BK$69,20,0) -> 215.38 | H63: =VLOOKUP(B64,'B&L'!$A$7:$BK$69,25,0) -> 207.34 | I63: =VLOOKUP(B64,'B&L'!$A$7:$BK$69,30,0) -> 210.58 | J63: =VLOOKUP(B64,'B&L'!$A$7:$BK$69,35,0) -> 216.09 | K63: =VLOOKUP(B64,'B&L'!$A$7:$BK$69,40,0) -> 213.76 | L63: =VLOOKUP(B64,'B&L'!$A$7:$BK$69,45,0) -> 212.26 | M63: =VLOOKUP(B64,'B&L'!$A$7:$BK$69,50,0) -> 205.23 | N63: =VLOOKUP(B64,'B&L'!$A$7:$BK$69,55,0) -> 191.49 | O63: =VLOOKUP(B64,'B&L'!$A$7:$BK$69,60,0) -> 209.72
B64: 1412000089 | C64: 土地 Land | D64: =VLOOKUP(B64,'B&L'!$A$7:$BK$69,6,0) -> 14.02 | E64: =VLOOKUP(B64,'B&L'!$A$7:$BK$69,11,0) -> 14.11 | F64: =VLOOKUP(B64,'B&L'!$A$7:$BK$69,16,0) -> 15.5 | G64: =VLOOKUP(B64,'B&L'!$A$7:$BK$69,21,0) -> 14.54 | H64: =VLOOKUP(B64,'B&L'!$A$7:$BK$69,26,0) -> 13.99 | I64: =VLOOKUP(B64,'B&L'!$A$7:$BK$69,31,0) -> 14.21 | J64: =VLOOKUP(B64,'B&L'!$A$7:$BK$69,36,0) -> 14.59 | K64: =VLOOKUP(B64,'B&L'!$A$7:$BK$69,41,0) -> 14.43 | L64: =VLOOKUP(B64,'B&L'!$A$7:$BK$69,46,0) -> 14.33 | M64: =VLOOKUP(B64,'B&L'!$A$7:$BK$69,51,0) -> 13.85 | N64: =VLOOKUP(B64,'B&L'!$A$7:$BK$69,56,0) -> 12.92 | O64: =VLOOKUP(B64,'B&L'!$A$7:$BK$69,61,0) -> 14.16
A65: 30 | B65: 電気製造技術課 | C65: 建物 Building | D65: =VLOOKUP(B66,'B&L'!$A$7:$BK$69,5,0) -> 293.02 | E65: =VLOOKUP(B66,'B&L'!$A$7:$BK$69,10,0) -> 294.07 | F65: =VLOOKUP(B66,'B&L'!$A$7:$BK$69,15,0) -> 296.68 | G65: =VLOOKUP(B66,'B&L'!$A$7:$BK$69,20,0) -> 293.7 | H65: =VLOOKUP(B66,'B&L'!$A$7:$BK$69,25,0) -> 287.07 | I65: =VLOOKUP(B66,'B&L'!$A$7:$BK$69,30,0) -> 289.74 | J65: =VLOOKUP(B66,'B&L'!$A$7:$BK$69,35,0) -> 294.29 | K65: =VLOOKUP(B66,'B&L'!$A$7:$BK$69,40,0) -> 292.36 | L65: =VLOOKUP(B66,'B&L'!$A$7:$BK$69,45,0) -> 291.13 | M65: =VLOOKUP(B66,'B&L'!$A$7:$BK$69,50,0) -> 285.32 | N65: =VLOOKUP(B66,'B&L'!$A$7:$BK$69,55,0) -> 273.97 | O65: =VLOOKUP(B66,'B&L'!$A$7:$BK$69,60,0) -> 289.03
B66: 1412000040 | C66: 土地 Land | D66: =VLOOKUP(B66,'B&L'!$A$7:$BK$69,6,0) -> 19.78 | E66: =VLOOKUP(B66,'B&L'!$A$7:$BK$69,11,0) -> 19.85 | F66: =VLOOKUP(B66,'B&L'!$A$7:$BK$69,16,0) -> 20.03 | G66: =VLOOKUP(B66,'B&L'!$A$7:$BK$69,21,0) -> 19.82 | H66: =VLOOKUP(B66,'B&L'!$A$7:$BK$69,26,0) -> 19.38 | I66: =VLOOKUP(B66,'B&L'!$A$7:$BK$69,31,0) -> 19.56 | J66: =VLOOKUP(B66,'B&L'!$A$7:$BK$69,36,0) -> 19.86 | K66: =VLOOKUP(B66,'B&L'!$A$7:$BK$69,41,0) -> 19.73 | L66: =VLOOKUP(B66,'B&L'!$A$7:$BK$69,46,0) -> 19.65 | M66: =VLOOKUP(B66,'B&L'!$A$7:$BK$69,51,0) -> 19.26 | N66: =VLOOKUP(B66,'B&L'!$A$7:$BK$69,56,0) -> 18.49 | O66: =VLOOKUP(B66,'B&L'!$A$7:$BK$69,61,0) -> 19.51
A67: 31 | B67: 製造システム開発課 | C67: 建物 Building | D67: =VLOOKUP(B68,'B&L'!$A$7:$BK$69,5,0) -> 122.05 | E67: =VLOOKUP(B68,'B&L'!$A$7:$BK$69,10,0) -> 122.69 | F67: =VLOOKUP(B68,'B&L'!$A$7:$BK$69,15,0) -> 124.29 | G67: =VLOOKUP(B68,'B&L'!$A$7:$BK$69,20,0) -> 117.48 | H67: =VLOOKUP(B68,'B&L'!$A$7:$BK$69,25,0) -> 113.64 | I67: =VLOOKUP(B68,'B&L'!$A$7:$BK$69,30,0) -> 115.19 | J67: =VLOOKUP(B68,'B&L'!$A$7:$BK$69,35,0) -> 117.82 | K67: =VLOOKUP(B68,'B&L'!$A$7:$BK$69,40,0) -> 116.7 | L67: =VLOOKUP(B68,'B&L'!$A$7:$BK$69,45,0) -> 115.99 | M67: =VLOOKUP(B68,'B&L'!$A$7:$BK$69,50,0) -> 112.63 | N67: =VLOOKUP(B68,'B&L'!$A$7:$BK$69,55,0) -> 106.05 | O67: =VLOOKUP(B68,'B&L'!$A$7:$BK$69,60,0) -> 114.77
B68: 1412000039 | C68: 土地 Land | D68: =VLOOKUP(B68,'B&L'!$A$7:$BK$69,6,0) -> 8.24 | E68: =VLOOKUP(B68,'B&L'!$A$7:$BK$69,11,0) -> 8.28 | F68: =VLOOKUP(B68,'B&L'!$A$7:$BK$69,16,0) -> 8.39 | G68: =VLOOKUP(B68,'B&L'!$A$7:$BK$69,21,0) -> 7.93 | H68: =VLOOKUP(B68,'B&L'!$A$7:$BK$69,26,0) -> 7.67 | I68: =VLOOKUP(B68,'B&L'!$A$7:$BK$69,31,0) -> 7.77 | J68: =VLOOKUP(B68,'B&L'!$A$7:$BK$69,36,0) -> 7.95 | K68: =VLOOKUP(B68,'B&L'!$A$7:$BK$69,41,0) -> 7.88 | L68: =VLOOKUP(B68,'B&L'!$A$7:$BK$69,46,0) -> 7.83 | M68: =VLOOKUP(B68,'B&L'!$A$7:$BK$69,51,0) -> 7.6 | N68: =VLOOKUP(B68,'B&L'!$A$7:$BK$69,56,0) -> 7.16 | O68: =VLOOKUP(B68,'B&L'!$A$7:$BK$69,61,0) -> 7.75
A69: 32 | B69: 製造技術管理課 | C69: 建物 Building | D69: =VLOOKUP(B70,'B&L'!$A$7:$BK$69,5,0) -> 87.75 | E69: =VLOOKUP(B70,'B&L'!$A$7:$BK$69,10,0) -> 105.42 | F69: =VLOOKUP(B70,'B&L'!$A$7:$BK$69,15,0) -> 106.73 | G69: =VLOOKUP(B70,'B&L'!$A$7:$BK$69,20,0) -> 101.16 | H69: =VLOOKUP(B70,'B&L'!$A$7:$BK$69,25,0) -> 98.02 | I69: =VLOOKUP(B70,'B&L'!$A$7:$BK$69,30,0) -> 99.29 | J69: =VLOOKUP(B70,'B&L'!$A$7:$BK$69,35,0) -> 101.44 | K69: =VLOOKUP(B70,'B&L'!$A$7:$BK$69,40,0) -> 100.53 | L69: =VLOOKUP(B70,'B&L'!$A$7:$BK$69,45,0) -> 99.94 | M69: =VLOOKUP(B70,'B&L'!$A$7:$BK$69,50,0) -> 97.19 | N69: =VLOOKUP(B70,'B&L'!$A$7:$BK$69,55,0) -> 91.82 | O69: =VLOOKUP(B70,'B&L'!$A$7:$BK$69,60,0) -> 98.95
B70: 14120000AB | C70: 土地 Land | D70: =VLOOKUP(B70,'B&L'!$A$7:$BK$69,6,0) -> 5.92 | E70: =VLOOKUP(B70,'B&L'!$A$7:$BK$69,11,0) -> 7.12 | F70: =VLOOKUP(B70,'B&L'!$A$7:$BK$69,16,0) -> 7.2 | G70: =VLOOKUP(B70,'B&L'!$A$7:$BK$69,21,0) -> 6.83 | H70: =VLOOKUP(B70,'B&L'!$A$7:$BK$69,26,0) -> 6.62 | I70: =VLOOKUP(B70,'B&L'!$A$7:$BK$69,31,0) -> 6.7 | J70: =VLOOKUP(B70,'B&L'!$A$7:$BK$69,36,0) -> 6.85 | K70: =VLOOKUP(B70,'B&L'!$A$7:$BK$69,41,0) -> 6.79 | L70: =VLOOKUP(B70,'B&L'!$A$7:$BK$69,46,0) -> 6.75 | M70: =VLOOKUP(B70,'B&L'!$A$7:$BK$69,51,0) -> 6.56 | N70: =VLOOKUP(B70,'B&L'!$A$7:$BK$69,56,0) -> 6.2 | O70: =VLOOKUP(B70,'B&L'!$A$7:$BK$69,61,0) -> 6.68
A71: 33 | B71: 部品検査課 1 | C71: 建物 Building | D71: =VLOOKUP(B72,'B&L'!$A$7:$BK$69,5,0) -> 1423.45 | E71: =VLOOKUP(B72,'B&L'!$A$7:$BK$69,10,0) -> 1422.89 | F71: =VLOOKUP(B72,'B&L'!$A$7:$BK$69,15,0) -> 1450.7 | G71: =VLOOKUP(B72,'B&L'!$A$7:$BK$69,20,0) -> 1444.13 | H71: =VLOOKUP(B72,'B&L'!$A$7:$BK$69,25,0) -> 1415.14 | I71: =VLOOKUP(B72,'B&L'!$A$7:$BK$69,30,0) -> 1418.18 | J71: =VLOOKUP(B72,'B&L'!$A$7:$BK$69,35,0) -> 1448.41 | K71: =VLOOKUP(B72,'B&L'!$A$7:$BK$69,40,0) -> 1430.09 | L71: =VLOOKUP(B72,'B&L'!$A$7:$BK$69,45,0) -> 1427.14 | M71: =VLOOKUP(B72,'B&L'!$A$7:$BK$69,50,0) -> 1410.99 | N71: =VLOOKUP(B72,'B&L'!$A$7:$BK$69,55,0) -> 1334.76 | O71: =VLOOKUP(B72,'B&L'!$A$7:$BK$69,60,0) -> 1433.82
B72: 1412000013 | C72: 土地 Land | D72: =VLOOKUP(B72,'B&L'!$A$7:$BK$69,6,0) -> 96.08 | E72: =VLOOKUP(B72,'B&L'!$A$7:$BK$69,11,0) -> 96.04 | F72: =VLOOKUP(B72,'B&L'!$A$7:$BK$69,16,0) -> 97.92 | G72: =VLOOKUP(B72,'B&L'!$A$7:$BK$69,21,0) -> 97.47 | H72: =VLOOKUP(B72,'B&L'!$A$7:$BK$69,26,0) -> 95.52 | I72: =VLOOKUP(B72,'B&L'!$A$7:$BK$69,31,0) -> 95.72 | J72: =VLOOKUP(B72,'B&L'!$A$7:$BK$69,36,0) -> 97.76 | K72: =VLOOKUP(B72,'B&L'!$A$7:$BK$69,41,0) -> 96.53 | L72: =VLOOKUP(B72,'B&L'!$A$7:$BK$69,46,0) -> 96.33 | M72: =VLOOKUP(B72,'B&L'!$A$7:$BK$69,51,0) -> 95.24 | N72: =VLOOKUP(B72,'B&L'!$A$7:$BK$69,56,0) -> 90.09 | O72: =VLOOKUP(B72,'B&L'!$A$7:$BK$69,61,0) -> 96.78
A73: 34 | B73: 部品検査課 2 | C73: 建物 Building | D73: =VLOOKUP(B74,'B&L'!$A$7:$BK$69,5,0) -> 1024.19 | E73: =VLOOKUP(B74,'B&L'!$A$7:$BK$69,10,0) -> 1023.94 | F73: =VLOOKUP(B74,'B&L'!$A$7:$BK$69,15,0) -> 1036.61 | G73: =VLOOKUP(B74,'B&L'!$A$7:$BK$69,20,0) -> 1032.46 | H73: =VLOOKUP(B74,'B&L'!$A$7:$BK$69,25,0) -> 1019.33 | I73: =VLOOKUP(B74,'B&L'!$A$7:$BK$69,30,0) -> 1020.71 | J73: =VLOOKUP(B74,'B&L'!$A$7:$BK$69,35,0) -> 1034.4 | K73: =VLOOKUP(B74,'B&L'!$A$7:$BK$69,40,0) -> 1026.1 | L73: =VLOOKUP(B74,'B&L'!$A$7:$BK$69,45,0) -> 1024.77 | M73: =VLOOKUP(B74,'B&L'!$A$7:$BK$69,50,0) -> 1017.45 | N73: =VLOOKUP(B74,'B&L'!$A$7:$BK$69,55,0) -> 982.93 | O73: =VLOOKUP(B74,'B&L'!$A$7:$BK$69,60,0) -> 1027.79
B74: 1412000092 | C74: 土地 Land | D74: =VLOOKUP(B74,'B&L'!$A$7:$BK$69,6,0) -> 69.13 | E74: =VLOOKUP(B74,'B&L'!$A$7:$BK$69,11,0) -> 69.11 | F74: =VLOOKUP(B74,'B&L'!$A$7:$BK$69,16,0) -> 69.97 | G74: =VLOOKUP(B74,'B&L'!$A$7:$BK$69,21,0) -> 69.69 | H74: =VLOOKUP(B74,'B&L'!$A$7:$BK$69,26,0) -> 68.8 | I74: =VLOOKUP(B74,'B&L'!$A$7:$BK$69,31,0) -> 68.89 | J74: =VLOOKUP(B74,'B&L'!$A$7:$BK$69,36,0) -> 69.82 | K74: =VLOOKUP(B74,'B&L'!$A$7:$BK$69,41,0) -> 69.26 | L74: =VLOOKUP(B74,'B&L'!$A$7:$BK$69,46,0) -> 69.17 | M74: =VLOOKUP(B74,'B&L'!$A$7:$BK$69,51,0) -> 68.67 | N74: =VLOOKUP(B74,'B&L'!$A$7:$BK$69,56,0) -> 66.34 | O74: =VLOOKUP(B74,'B&L'!$A$7:$BK$69,61,0) -> 69.37
A75: 35 | B75: 外製管理課 | C75: 建物 Building | D75: =VLOOKUP(B76,'B&L'!$A$7:$BK$69,5,0) -> 487.99 | E75: =VLOOKUP(B76,'B&L'!$A$7:$BK$69,10,0) -> 499.69 | F75: =VLOOKUP(B76,'B&L'!$A$7:$BK$69,15,0) -> 513.96 | G75: =VLOOKUP(B76,'B&L'!$A$7:$BK$69,20,0) -> 499.72 | H75: =VLOOKUP(B76,'B&L'!$A$7:$BK$69,25,0) -> 489.94 | I75: =VLOOKUP(B76,'B&L'!$A$7:$BK$69,30,0) -> 493.88 | J75: =VLOOKUP(B76,'B&L'!$A$7:$BK$69,35,0) -> 500.59 | K75: =VLOOKUP(B76,'B&L'!$A$7:$BK$69,40,0) -> 497.75 | L75: =VLOOKUP(B76,'B&L'!$A$7:$BK$69,45,0) -> 495.93 | M75: =VLOOKUP(B76,'B&L'!$A$7:$BK$69,50,0) -> 488.86 | N75: =VLOOKUP(B76,'B&L'!$A$7:$BK$69,55,0) -> 472.14 | O75: =VLOOKUP(B76,'B&L'!$A$7:$BK$69,60,0) -> 494.33
B76: 1412000035 | C76: 土地 Land | D76: =VLOOKUP(B76,'B&L'!$A$7:$BK$69,6,0) -> 32.94 | E76: =VLOOKUP(B76,'B&L'!$A$7:$BK$69,11,0) -> 33.73 | F76: =VLOOKUP(B76,'B&L'!$A$7:$BK$69,16,0) -> 34.69 | G76: =VLOOKUP(B76,'B&L'!$A$7:$BK$69,21,0) -> 33.73 | H76: =VLOOKUP(B76,'B&L'!$A$7:$BK$69,26,0) -> 33.07 | I76: =VLOOKUP(B76,'B&L'!$A$7:$BK$69,31,0) -> 33.34 | J76: =VLOOKUP(B76,'B&L'!$A$7:$BK$69,36,0) -> 33.79 | K76: =VLOOKUP(B76,'B&L'!$A$7:$BK$69,41,0) -> 33.6 | L76: =VLOOKUP(B76,'B&L'!$A$7:$BK$69,46,0) -> 33.47 | M76: =VLOOKUP(B76,'B&L'!$A$7:$BK$69,51,0) -> 33 | N76: =VLOOKUP(B76,'B&L'!$A$7:$BK$69,56,0) -> 31.87 | O76: =VLOOKUP(B76,'B&L'!$A$7:$BK$69,61,0) -> 33.37
A77: 36 | B77: 生産技術1課 | C77: 建物 Building | D77: =VLOOKUP(B78,'B&L'!$A$7:$BK$69,5,0) -> 486.97 | E77: =VLOOKUP(B78,'B&L'!$A$7:$BK$69,10,0) -> 496.83 | F77: =VLOOKUP(B78,'B&L'!$A$7:$BK$69,15,0) -> 497.26 | G77: =VLOOKUP(B78,'B&L'!$A$7:$BK$69,20,0) -> 491.45 | H77: =VLOOKUP(B78,'B&L'!$A$7:$BK$69,25,0) -> 490.78 | I77: =VLOOKUP(B78,'B&L'!$A$7:$BK$69,30,0) -> 490.89 | J77: =VLOOKUP(B78,'B&L'!$A$7:$BK$69,35,0) -> 491.17 | K77: =VLOOKUP(B78,'B&L'!$A$7:$BK$69,40,0) -> 491.03 | L77: =VLOOKUP(B78,'B&L'!$A$7:$BK$69,45,0) -> 490.82 | M77: =VLOOKUP(B78,'B&L'!$A$7:$BK$69,50,0) -> 490.58 | N77: =VLOOKUP(B78,'B&L'!$A$7:$BK$69,55,0) -> 489.82 | O77: =VLOOKUP(B78,'B&L'!$A$7:$BK$69,60,0) -> 490.81
B78: 1412000016 | C78: 土地 Land | D78: =VLOOKUP(B78,'B&L'!$A$7:$BK$69,6,0) -> 32.87 | E78: =VLOOKUP(B78,'B&L'!$A$7:$BK$69,11,0) -> 33.53 | F78: =VLOOKUP(B78,'B&L'!$A$7:$BK$69,16,0) -> 33.56 | G78: =VLOOKUP(B78,'B&L'!$A$7:$BK$69,21,0) -> 33.17 | H78: =VLOOKUP(B78,'B&L'!$A$7:$BK$69,26,0) -> 33.13 | I78: =VLOOKUP(B78,'B&L'!$A$7:$BK$69,31,0) -> 33.13 | J78: =VLOOKUP(B78,'B&L'!$A$7:$BK$69,36,0) -> 33.15 | K78: =VLOOKUP(B78,'B&L'!$A$7:$BK$69,41,0) -> 33.14 | L78: =VLOOKUP(B78,'B&L'!$A$7:$BK$69,46,0) -> 33.13 | M78: =VLOOKUP(B78,'B&L'!$A$7:$BK$69,51,0) -> 33.11 | N78: =VLOOKUP(B78,'B&L'!$A$7:$BK$69,56,0) -> 33.06 | O78: =VLOOKUP(B78,'B&L'!$A$7:$BK$69,61,0) -> 33.13
A79: 37 | B79: 生産技術2課 | C79: 建物 Building | D79: =VLOOKUP(B80,'B&L'!$A$7:$BK$69,5,0) -> 339.53 | E79: =VLOOKUP(B80,'B&L'!$A$7:$BK$69,10,0) -> 353.12 | F79: =VLOOKUP(B80,'B&L'!$A$7:$BK$69,15,0) -> 353.41 | G79: =VLOOKUP(B80,'B&L'!$A$7:$BK$69,20,0) -> 349.53 | H79: =VLOOKUP(B80,'B&L'!$A$7:$BK$69,25,0) -> 349.09 | I79: =VLOOKUP(B80,'B&L'!$A$7:$BK$69,30,0) -> 349.16 | J79: =VLOOKUP(B80,'B&L'!$A$7:$BK$69,35,0) -> 349.35 | K79: =VLOOKUP(B80,'B&L'!$A$7:$BK$69,40,0) -> 349.25 | L79: =VLOOKUP(B80,'B&L'!$A$7:$BK$69,45,0) -> 349.11 | M79: =VLOOKUP(B80,'B&L'!$A$7:$BK$69,50,0) -> 348.95 | N79: =VLOOKUP(B80,'B&L'!$A$7:$BK$69,55,0) -> 348.45 | O79: =VLOOKUP(B80,'B&L'!$A$7:$BK$69,60,0) -> 349.11
B80: 1412000069 | C80: 土地 Land | D80: =VLOOKUP(B80,'B&L'!$A$7:$BK$69,6,0) -> 22.92 | E80: =VLOOKUP(B80,'B&L'!$A$7:$BK$69,11,0) -> 23.83 | F80: =VLOOKUP(B80,'B&L'!$A$7:$BK$69,16,0) -> 23.85 | G80: =VLOOKUP(B80,'B&L'!$A$7:$BK$69,21,0) -> 23.59 | H80: =VLOOKUP(B80,'B&L'!$A$7:$BK$69,26,0) -> 23.56 | I80: =VLOOKUP(B80,'B&L'!$A$7:$BK$69,31,0) -> 23.57 | J80: =VLOOKUP(B80,'B&L'!$A$7:$BK$69,36,0) -> 23.58 | K80: =VLOOKUP(B80,'B&L'!$A$7:$BK$69,41,0) -> 23.57 | L80: =VLOOKUP(B80,'B&L'!$A$7:$BK$69,46,0) -> 23.56 | M80: =VLOOKUP(B80,'B&L'!$A$7:$BK$69,51,0) -> 23.55 | N80: =VLOOKUP(B80,'B&L'!$A$7:$BK$69,56,0) -> 23.52 | O80: =VLOOKUP(B80,'B&L'!$A$7:$BK$69,61,0) -> 23.56
A81: 38 | B81: 生産技術3課 | C81: 建物 Building | D81: =VLOOKUP(B82,'B&L'!$A$7:$BK$69,5,0) -> 508.03 | E81: =VLOOKUP(B82,'B&L'!$A$7:$BK$69,10,0) -> 496.83 | F81: =VLOOKUP(B82,'B&L'!$A$7:$BK$69,15,0) -> 497.26 | G81: =VLOOKUP(B82,'B&L'!$A$7:$BK$69,20,0) -> 511.72 | H81: =VLOOKUP(B82,'B&L'!$A$7:$BK$69,25,0) -> 511.02 | I81: =VLOOKUP(B82,'B&L'!$A$7:$BK$69,30,0) -> 511.13 | J81: =VLOOKUP(B82,'B&L'!$A$7:$BK$69,35,0) -> 511.43 | K81: =VLOOKUP(B82,'B&L'!$A$7:$BK$69,40,0) -> 511.28 | L81: =VLOOKUP(B82,'B&L'!$A$7:$BK$69,45,0) -> 511.06 | M81: =VLOOKUP(B82,'B&L'!$A$7:$BK$69,50,0) -> 510.81 | N81: =VLOOKUP(B82,'B&L'!$A$7:$BK$69,55,0) -> 510.02 | O81: =VLOOKUP(B82,'B&L'!$A$7:$BK$69,60,0) -> 511.05
B82: 1412000084 | C82: 土地 Land | D82: =VLOOKUP(B82,'B&L'!$A$7:$BK$69,6,0) -> 34.29 | E82: =VLOOKUP(B82,'B&L'!$A$7:$BK$69,11,0) -> 33.53 | F82: =VLOOKUP(B82,'B&L'!$A$7:$BK$69,16,0) -> 33.56 | G82: =VLOOKUP(B82,'B&L'!$A$7:$BK$69,21,0) -> 34.54 | H82: =VLOOKUP(B82,'B&L'!$A$7:$BK$69,26,0) -> 34.49 | I82: =VLOOKUP(B82,'B&L'!$A$7:$BK$69,31,0) -> 34.5 | J82: =VLOOKUP(B82,'B&L'!$A$7:$BK$69,36,0) -> 34.52 | K82: =VLOOKUP(B82,'B&L'!$A$7:$BK$69,41,0) -> 34.51 | L82: =VLOOKUP(B82,'B&L'!$A$7:$BK$69,46,0) -> 34.49 | M82: =VLOOKUP(B82,'B&L'!$A$7:$BK$69,51,0) -> 34.48 | N82: =VLOOKUP(B82,'B&L'!$A$7:$BK$69,56,0) -> 34.42 | O82: =VLOOKUP(B82,'B&L'!$A$7:$BK$69,61,0) -> 34.49
A83: 39 | B83: MD1課 | C83: 建物 Building | D83: =VLOOKUP(B84,'B&L'!$A$7:$BK$69,5,0) -> 246.2 | E83: =VLOOKUP(B84,'B&L'!$A$7:$BK$69,10,0) -> 246.29 | F83: =VLOOKUP(B84,'B&L'!$A$7:$BK$69,15,0) -> 245.4 | G83: =VLOOKUP(B84,'B&L'!$A$7:$BK$69,20,0) -> 243.34 | H83: =VLOOKUP(B84,'B&L'!$A$7:$BK$69,25,0) -> 243.08 | I83: =VLOOKUP(B84,'B&L'!$A$7:$BK$69,30,0) -> 272.59 | J83: =VLOOKUP(B84,'B&L'!$A$7:$BK$69,35,0) -> 262.4 | K83: =VLOOKUP(B84,'B&L'!$A$7:$BK$69,40,0) -> 262.29 | L83: =VLOOKUP(B84,'B&L'!$A$7:$BK$69,45,0) -> 262.66 | M83: =VLOOKUP(B84,'B&L'!$A$7:$BK$69,50,0) -> 262.47 | N83: =VLOOKUP(B84,'B&L'!$A$7:$BK$69,55,0) -> 258.39 | O83: =VLOOKUP(B84,'B&L'!$A$7:$BK$69,60,0) -> 262.65
B84: 1412000050 | C84: 土地 Land | D84: =VLOOKUP(B84,'B&L'!$A$7:$BK$69,6,0) -> 16.62 | E84: =VLOOKUP(B84,'B&L'!$A$7:$BK$69,11,0) -> 16.62 | F84: =VLOOKUP(B84,'B&L'!$A$7:$BK$69,16,0) -> 16.56 | G84: =VLOOKUP(B84,'B&L'!$A$7:$BK$69,21,0) -> 16.42 | H84: =VLOOKUP(B84,'B&L'!$A$7:$BK$69,26,0) -> 16.41 | I84: =VLOOKUP(B84,'B&L'!$A$7:$BK$69,31,0) -> 18.4 | J84: =VLOOKUP(B84,'B&L'!$A$7:$BK$69,36,0) -> 17.71 | K84: =VLOOKUP(B84,'B&L'!$A$7:$BK$69,41,0) -> 17.7 | L84: =VLOOKUP(B84,'B&L'!$A$7:$BK$69,46,0) -> 17.73 | M84: =VLOOKUP(B84,'B&L'!$A$7:$BK$69,51,0) -> 17.72 | N84: =VLOOKUP(B84,'B&L'!$A$7:$BK$69,56,0) -> 17.44 | O84: =VLOOKUP(B84,'B&L'!$A$7:$BK$69,61,0) -> 17.73
A85: 40 | B85: MD2課 | C85: 建物 Building | D85: =VLOOKUP(B86,'B&L'!$A$7:$BK$69,5,0) -> 180.54 | E85: =VLOOKUP(B86,'B&L'!$A$7:$BK$69,10,0) -> 180.61 | F85: =VLOOKUP(B86,'B&L'!$A$7:$BK$69,15,0) -> 179.96 | G85: =VLOOKUP(B86,'B&L'!$A$7:$BK$69,20,0) -> 178.45 | H85: =VLOOKUP(B86,'B&L'!$A$7:$BK$69,25,0) -> 178.26 | I85: =VLOOKUP(B86,'B&L'!$A$7:$BK$69,30,0) -> 166.58 | J85: =VLOOKUP(B86,'B&L'!$A$7:$BK$69,35,0) -> 169.79 | K85: =VLOOKUP(B86,'B&L'!$A$7:$BK$69,40,0) -> 169.71 | L85: =VLOOKUP(B86,'B&L'!$A$7:$BK$69,45,0) -> 169.96 | M85: =VLOOKUP(B86,'B&L'!$A$7:$BK$69,50,0) -> 169.83 | N85: =VLOOKUP(B86,'B&L'!$A$7:$BK$69,55,0) -> 167.2 | O85: =VLOOKUP(B86,'B&L'!$A$7:$BK$69,60,0) -> 169.95
B86: 1412000077 | C86: 土地 Land | D86: =VLOOKUP(B86,'B&L'!$A$7:$BK$69,6,0) -> 12.19 | E86: =VLOOKUP(B86,'B&L'!$A$7:$BK$69,11,0) -> 12.19 | F86: =VLOOKUP(B86,'B&L'!$A$7:$BK$69,16,0) -> 12.15 | G86: =VLOOKUP(B86,'B&L'!$A$7:$BK$69,21,0) -> 12.04 | H86: =VLOOKUP(B86,'B&L'!$A$7:$BK$69,26,0) -> 12.03 | I86: =VLOOKUP(B86,'B&L'!$A$7:$BK$69,31,0) -> 11.24 | J86: =VLOOKUP(B86,'B&L'!$A$7:$BK$69,36,0) -> 11.46 | K86: =VLOOKUP(B86,'B&L'!$A$7:$BK$69,41,0) -> 11.46 | L86: =VLOOKUP(B86,'B&L'!$A$7:$BK$69,46,0) -> 11.47 | M86: =VLOOKUP(B86,'B&L'!$A$7:$BK$69,51,0) -> 11.46 | N86: =VLOOKUP(B86,'B&L'!$A$7:$BK$69,56,0) -> 11.29 | O86: =VLOOKUP(B86,'B&L'!$A$7:$BK$69,61,0) -> 11.47
A87: 41 | B87: MD3課 | C87: 建物 Building | D87: =VLOOKUP(B88,'B&L'!$A$7:$BK$69,5,0) -> 164.13 | E87: =VLOOKUP(B88,'B&L'!$A$7:$BK$69,10,0) -> 164.19 | F87: =VLOOKUP(B88,'B&L'!$A$7:$BK$69,15,0) -> 163.6 | G87: =VLOOKUP(B88,'B&L'!$A$7:$BK$69,20,0) -> 162.23 | H87: =VLOOKUP(B88,'B&L'!$A$7:$BK$69,25,0) -> 162.06 | I87: =VLOOKUP(B88,'B&L'!$A$7:$BK$69,30,0) -> 151.44 | J87: =VLOOKUP(B88,'B&L'!$A$7:$BK$69,35,0) -> 154.35 | K87: =VLOOKUP(B88,'B&L'!$A$7:$BK$69,40,0) -> 154.29 | L87: =VLOOKUP(B88,'B&L'!$A$7:$BK$69,45,0) -> 154.51 | M87: =VLOOKUP(B88,'B&L'!$A$7:$BK$69,50,0) -> 154.39 | N87: =VLOOKUP(B88,'B&L'!$A$7:$BK$69,55,0) -> 152 | O87: =VLOOKUP(B88,'B&L'!$A$7:$BK$69,60,0) -> 139.05
B88: 1412000083 | C88: 土地 Land | D88: =VLOOKUP(B88,'B&L'!$A$7:$BK$69,6,0) -> 11.08 | E88: =VLOOKUP(B88,'B&L'!$A$7:$BK$69,11,0) -> 11.08 | F88: =VLOOKUP(B88,'B&L'!$A$7:$BK$69,16,0) -> 11.04 | G88: =VLOOKUP(B88,'B&L'!$A$7:$BK$69,21,0) -> 10.95 | H88: =VLOOKUP(B88,'B&L'!$A$7:$BK$69,26,0) -> 10.94 | I88: =VLOOKUP(B88,'B&L'!$A$7:$BK$69,31,0) -> 10.22 | J88: =VLOOKUP(B88,'B&L'!$A$7:$BK$69,36,0) -> 10.42 | K88: =VLOOKUP(B88,'B&L'!$A$7:$BK$69,41,0) -> 10.41 | L88: =VLOOKUP(B88,'B&L'!$A$7:$BK$69,46,0) -> 10.43 | M88: =VLOOKUP(B88,'B&L'!$A$7:$BK$69,51,0) -> 10.42 | N88: =VLOOKUP(B88,'B&L'!$A$7:$BK$69,56,0) -> 10.26 | O88: =VLOOKUP(B88,'B&L'!$A$7:$BK$69,61,0) -> 9.39
A89: 42 | B89: MD4課 | C89: 建物 Building | D89: =VLOOKUP(B90,'B&L'!$A$7:$BK$69,5,0) -> 164.13 | E89: =VLOOKUP(B90,'B&L'!$A$7:$BK$69,10,0) -> 164.19 | F89: =VLOOKUP(B90,'B&L'!$A$7:$BK$69,15,0) -> 163.6 | G89: =VLOOKUP(B90,'B&L'!$A$7:$BK$69,20,0) -> 178.45 | H89: =VLOOKUP(B90,'B&L'!$A$7:$BK$69,25,0) -> 178.26 | I89: =VLOOKUP(B90,'B&L'!$A$7:$BK$69,30,0) -> 166.58 | J89: =VLOOKUP(B90,'B&L'!$A$7:$BK$69,35,0) -> 169.79 | K89: =VLOOKUP(B90,'B&L'!$A$7:$BK$69,40,0) -> 169.71 | L89: =VLOOKUP(B90,'B&L'!$A$7:$BK$69,45,0) -> 169.96 | M89: =VLOOKUP(B90,'B&L'!$A$7:$BK$69,50,0) -> 169.83 | N89: =VLOOKUP(B90,'B&L'!$A$7:$BK$69,55,0) -> 167.2 | O89: =VLOOKUP(B90,'B&L'!$A$7:$BK$69,60,0) -> 169.95
B90: 1412000099 | C90: 土地 Land | D90: =VLOOKUP(B90,'B&L'!$A$7:$BK$69,6,0) -> 11.08 | E90: =VLOOKUP(B90,'B&L'!$A$7:$BK$69,11,0) -> 11.08 | F90: =VLOOKUP(B90,'B&L'!$A$7:$BK$69,16,0) -> 11.04 | G90: =VLOOKUP(B90,'B&L'!$A$7:$BK$69,21,0) -> 12.04 | H90: =VLOOKUP(B90,'B&L'!$A$7:$BK$69,26,0) -> 12.03 | I90: =VLOOKUP(B90,'B&L'!$A$7:$BK$69,31,0) -> 11.24 | J90: =VLOOKUP(B90,'B&L'!$A$7:$BK$69,36,0) -> 11.46 | K90: =VLOOKUP(B90,'B&L'!$A$7:$BK$69,41,0) -> 11.46 | L90: =VLOOKUP(B90,'B&L'!$A$7:$BK$69,46,0) -> 11.47 | M90: =VLOOKUP(B90,'B&L'!$A$7:$BK$69,51,0) -> 11.46 | N90: =VLOOKUP(B90,'B&L'!$A$7:$BK$69,56,0) -> 11.29 | O90: =VLOOKUP(B90,'B&L'!$A$7:$BK$69,61,0) -> 11.47
A91: 43 | B91: MD5課 | C91: 建物 Building | D91: =VLOOKUP(B92,'B&L'!$A$7:$BK$69,5,0) -> 131.31 | E91: =VLOOKUP(B92,'B&L'!$A$7:$BK$69,10,0) -> 131.35 | F91: =VLOOKUP(B92,'B&L'!$A$7:$BK$69,15,0) -> 130.88 | G91: =VLOOKUP(B92,'B&L'!$A$7:$BK$69,20,0) -> 129.78 | H91: =VLOOKUP(B92,'B&L'!$A$7:$BK$69,25,0) -> 129.64 | I91: =VLOOKUP(B92,'B&L'!$A$7:$BK$69,30,0) -> 121.15 | J91: =VLOOKUP(B92,'B&L'!$A$7:$BK$69,35,0) -> 123.48 | K91: =VLOOKUP(B92,'B&L'!$A$7:$BK$69,40,0) -> 123.43 | L91: =VLOOKUP(B92,'B&L'!$A$7:$BK$69,45,0) -> 123.61 | M91: =VLOOKUP(B92,'B&L'!$A$7:$BK$69,50,0) -> 123.51 | N91: =VLOOKUP(B92,'B&L'!$A$7:$BK$69,55,0) -> 136.8 | O91: =VLOOKUP(B92,'B&L'!$A$7:$BK$69,60,0) -> 154.5
B92: 1412000100 | C92: 土地 Land | D92: =VLOOKUP(B92,'B&L'!$A$7:$BK$69,6,0) -> 8.86 | E92: =VLOOKUP(B92,'B&L'!$A$7:$BK$69,11,0) -> 8.87 | F92: =VLOOKUP(B92,'B&L'!$A$7:$BK$69,16,0) -> 8.83 | G92: =VLOOKUP(B92,'B&L'!$A$7:$BK$69,21,0) -> 8.76 | H92: =VLOOKUP(B92,'B&L'!$A$7:$BK$69,26,0) -> 8.75 | I92: =VLOOKUP(B92,'B&L'!$A$7:$BK$69,31,0) -> 8.18 | J92: =VLOOKUP(B92,'B&L'!$A$7:$BK$69,36,0) -> 8.33 | K92: =VLOOKUP(B92,'B&L'!$A$7:$BK$69,41,0) -> 8.33 | L92: =VLOOKUP(B92,'B&L'!$A$7:$BK$69,46,0) -> 8.34 | M92: =VLOOKUP(B92,'B&L'!$A$7:$BK$69,51,0) -> 8.34 | N92: =VLOOKUP(B92,'B&L'!$A$7:$BK$69,56,0) -> 9.23 | O92: =VLOOKUP(B92,'B&L'!$A$7:$BK$69,61,0) -> 10.43
A93: 44 | B93: EI1課 | C93: 建物 Building | D93: =VLOOKUP(B94,'B&L'!$A$7:$BK$69,5,0) -> 147.72 | E93: =VLOOKUP(B94,'B&L'!$A$7:$BK$69,10,0) -> 147.77 | F93: =VLOOKUP(B94,'B&L'!$A$7:$BK$69,15,0) -> 147.24 | G93: =VLOOKUP(B94,'B&L'!$A$7:$BK$69,20,0) -> 146 | H93: =VLOOKUP(B94,'B&L'!$A$7:$BK$69,25,0) -> 145.85 | I93: =VLOOKUP(B94,'B&L'!$A$7:$BK$69,30,0) -> 181.73 | J93: =VLOOKUP(B94,'B&L'!$A$7:$BK$69,35,0) -> 169.79 | K93: =VLOOKUP(B94,'B&L'!$A$7:$BK$69,40,0) -> 169.71 | L93: =VLOOKUP(B94,'B&L'!$A$7:$BK$69,45,0) -> 169.96 | M93: =VLOOKUP(B94,'B&L'!$A$7:$BK$69,50,0) -> 169.83 | N93: =VLOOKUP(B94,'B&L'!$A$7:$BK$69,55,0) -> 167.2 | O93: =VLOOKUP(B94,'B&L'!$A$7:$BK$69,60,0) -> 169.95
B94: 1412000057 | C94: 土地 Land | D94: =VLOOKUP(B94,'B&L'!$A$7:$BK$69,6,0) -> 9.97 | E94: =VLOOKUP(B94,'B&L'!$A$7:$BK$69,11,0) -> 9.97 | F94: =VLOOKUP(B94,'B&L'!$A$7:$BK$69,16,0) -> 9.94 | G94: =VLOOKUP(B94,'B&L'!$A$7:$BK$69,21,0) -> 9.85 | H94: =VLOOKUP(B94,'B&L'!$A$7:$BK$69,26,0) -> 9.84 | I94: =VLOOKUP(B94,'B&L'!$A$7:$BK$69,31,0) -> 12.27 | J94: =VLOOKUP(B94,'B&L'!$A$7:$BK$69,36,0) -> 11.46 | K94: =VLOOKUP(B94,'B&L'!$A$7:$BK$69,41,0) -> 11.46 | L94: =VLOOKUP(B94,'B&L'!$A$7:$BK$69,46,0) -> 11.47 | M94: =VLOOKUP(B94,'B&L'!$A$7:$BK$69,51,0) -> 11.46 | N94: =VLOOKUP(B94,'B&L'!$A$7:$BK$69,56,0) -> 11.29 | O94: =VLOOKUP(B94,'B&L'!$A$7:$BK$69,61,0) -> 11.47
A95: 45 | B95: EI2課 | C95: 建物 Building | D95: =VLOOKUP(B96,'B&L'!$A$7:$BK$69,5,0) -> 213.37 | E95: =VLOOKUP(B96,'B&L'!$A$7:$BK$69,10,0) -> 213.45 | F95: =VLOOKUP(B96,'B&L'!$A$7:$BK$69,15,0) -> 212.68 | G95: =VLOOKUP(B96,'B&L'!$A$7:$BK$69,20,0) -> 210.89 | H95: =VLOOKUP(B96,'B&L'!$A$7:$BK$69,25,0) -> 210.67 | I95: =VLOOKUP(B96,'B&L'!$A$7:$BK$69,30,0) -> 196.87 | J95: =VLOOKUP(B96,'B&L'!$A$7:$BK$69,35,0) -> 200.66 | K95: =VLOOKUP(B96,'B&L'!$A$7:$BK$69,40,0) -> 200.57 | L95: =VLOOKUP(B96,'B&L'!$A$7:$BK$69,45,0) -> 200.86 | M95: =VLOOKUP(B96,'B&L'!$A$7:$BK$69,50,0) -> 200.71 | N95: =VLOOKUP(B96,'B&L'!$A$7:$BK$69,55,0) -> 197.6 | O95: =VLOOKUP(B96,'B&L'!$A$7:$BK$69,60,0) -> 185.4
B96: 1412000101 | C96: 土地 Land | D96: =VLOOKUP(B96,'B&L'!$A$7:$BK$69,6,0) -> 14.4 | E96: =VLOOKUP(B96,'B&L'!$A$7:$BK$69,11,0) -> 14.41 | F96: =VLOOKUP(B96,'B&L'!$A$7:$BK$69,16,0) -> 14.36 | G96: =VLOOKUP(B96,'B&L'!$A$7:$BK$69,21,0) -> 14.23 | H96: =VLOOKUP(B96,'B&L'!$A$7:$BK$69,26,0) -> 14.22 | I96: =VLOOKUP(B96,'B&L'!$A$7:$BK$69,31,0) -> 13.29 | J96: =VLOOKUP(B96,'B&L'!$A$7:$BK$69,36,0) -> 13.54 | K96: =VLOOKUP(B96,'B&L'!$A$7:$BK$69,41,0) -> 13.54 | L96: =VLOOKUP(B96,'B&L'!$A$7:$BK$69,46,0) -> 13.56 | M96: =VLOOKUP(B96,'B&L'!$A$7:$BK$69,51,0) -> 13.55 | N96: =VLOOKUP(B96,'B&L'!$A$7:$BK$69,56,0) -> 13.34 | O96: =VLOOKUP(B96,'B&L'!$A$7:$BK$69,61,0) -> 12.51
A97: 46 | B97: ESD1課 | C97: 建物 Building | D97: =VLOOKUP(B98,'B&L'!$A$7:$BK$69,5,0) -> 213.37 | E97: =VLOOKUP(B98,'B&L'!$A$7:$BK$69,10,0) -> 213.45 | F97: =VLOOKUP(B98,'B&L'!$A$7:$BK$69,15,0) -> 212.68 | G97: =VLOOKUP(B98,'B&L'!$A$7:$BK$69,20,0) -> 210.89 | H97: =VLOOKUP(B98,'B&L'!$A$7:$BK$69,25,0) -> 210.67 | I97: =VLOOKUP(B98,'B&L'!$A$7:$BK$69,30,0) -> 257.45 | J97: =VLOOKUP(B98,'B&L'!$A$7:$BK$69,35,0) -> 246.97 | K97: =VLOOKUP(B98,'B&L'!$A$7:$BK$69,40,0) -> 246.86 | L97: =VLOOKUP(B98,'B&L'!$A$7:$BK$69,45,0) -> 247.21 | M97: =VLOOKUP(B98,'B&L'!$A$7:$BK$69,50,0) -> 247.03 | N97: =VLOOKUP(B98,'B&L'!$A$7:$BK$69,55,0) -> 243.2 | O97: =VLOOKUP(B98,'B&L'!$A$7:$BK$69,60,0) -> 247.2
B98: 1412000078 | C98: 土地 Land | D98: =VLOOKUP(B98,'B&L'!$A$7:$BK$69,6,0) -> 14.4 | E98: =VLOOKUP(B98,'B&L'!$A$7:$BK$69,11,0) -> 14.41 | F98: =VLOOKUP(B98,'B&L'!$A$7:$BK$69,16,0) -> 14.36 | G98: =VLOOKUP(B98,'B&L'!$A$7:$BK$69,21,0) -> 14.23 | H98: =VLOOKUP(B98,'B&L'!$A$7:$BK$69,26,0) -> 14.22 | I98: =VLOOKUP(B98,'B&L'!$A$7:$BK$69,31,0) -> 17.38 | J98: =VLOOKUP(B98,'B&L'!$A$7:$BK$69,36,0) -> 16.67 | K98: =VLOOKUP(B98,'B&L'!$A$7:$BK$69,41,0) -> 16.66 | L98: =VLOOKUP(B98,'B&L'!$A$7:$BK$69,46,0) -> 16.69 | M98: =VLOOKUP(B98,'B&L'!$A$7:$BK$69,51,0) -> 16.67 | N98: =VLOOKUP(B98,'B&L'!$A$7:$BK$69,56,0) -> 16.41 | O98: =VLOOKUP(B98,'B&L'!$A$7:$BK$69,61,0) -> 16.69
A99: 47 | B99: ESD2課 | C99: 建物 Building | D99: =VLOOKUP(B100,'B&L'!$A$7:$BK$69,5,0) -> 229.78 | E99: =VLOOKUP(B100,'B&L'!$A$7:$BK$69,10,0) -> 229.87 | F99: =VLOOKUP(B100,'B&L'!$A$7:$BK$69,15,0) -> 229.04 | G99: =VLOOKUP(B100,'B&L'!$A$7:$BK$69,20,0) -> 227.12 | H99: =VLOOKUP(B100,'B&L'!$A$7:$BK$69,25,0) -> 226.88 | I99: =VLOOKUP(B100,'B&L'!$A$7:$BK$69,30,0) -> 212.01 | J99: =VLOOKUP(B100,'B&L'!$A$7:$BK$69,35,0) -> 216.1 | K99: =VLOOKUP(B100,'B&L'!$A$7:$BK$69,40,0) -> 216 | L99: =VLOOKUP(B100,'B&L'!$A$7:$BK$69,45,0) -> 216.31 | M99: =VLOOKUP(B100,'B&L'!$A$7:$BK$69,50,0) -> 216.15 | N99: =VLOOKUP(B100,'B&L'!$A$7:$BK$69,55,0) -> 228 | O99: =VLOOKUP(B100,'B&L'!$A$7:$BK$69,60,0) -> 216.3
B100: 1412000096 | C100: 土地 Land | D100: =VLOOKUP(B100,'B&L'!$A$7:$BK$69,6,0) -> 15.51 | E100: =VLOOKUP(B100,'B&L'!$A$7:$BK$69,11,0) -> 15.52 | F100: =VLOOKUP(B100,'B&L'!$A$7:$BK$69,16,0) -> 15.46 | G100: =VLOOKUP(B100,'B&L'!$A$7:$BK$69,21,0) -> 15.33 | H100: =VLOOKUP(B100,'B&L'!$A$7:$BK$69,26,0) -> 15.31 | I100: =VLOOKUP(B100,'B&L'!$A$7:$BK$69,31,0) -> 14.31 | J100: =VLOOKUP(B100,'B&L'!$A$7:$BK$69,36,0) -> 14.59 | K100: =VLOOKUP(B100,'B&L'!$A$7:$BK$69,41,0) -> 14.58 | L100: =VLOOKUP(B100,'B&L'!$A$7:$BK$69,46,0) -> 14.6 | M100: =VLOOKUP(B100,'B&L'!$A$7:$BK$69,51,0) -> 14.59 | N100: =VLOOKUP(B100,'B&L'!$A$7:$BK$69,56,0) -> 15.39 | O100: =VLOOKUP(B100,'B&L'!$A$7:$BK$69,61,0) -> 14.6
A101: 48 | B101: 品質保証課 | C101: 建物 Building | D101: =VLOOKUP(B102,'B&L'!$A$7:$BK$69,5,0) -> 866.9 | E101: =VLOOKUP(B102,'B&L'!$A$7:$BK$69,10,0) -> 877.66 | F101: =VLOOKUP(B102,'B&L'!$A$7:$BK$69,15,0) -> 887.34 | G101: =VLOOKUP(B102,'B&L'!$A$7:$BK$69,20,0) -> 877.68 | H101: =VLOOKUP(B102,'B&L'!$A$7:$BK$69,25,0) -> 871.05 | I101: =VLOOKUP(B102,'B&L'!$A$7:$BK$69,30,0) -> 873.72 | J101: =VLOOKUP(B102,'B&L'!$A$7:$BK$69,35,0) -> 878.27 | K101: =VLOOKUP(B102,'B&L'!$A$7:$BK$69,40,0) -> 876.35 | L101: =VLOOKUP(B102,'B&L'!$A$7:$BK$69,45,0) -> 875.11 | M101: =VLOOKUP(B102,'B&L'!$A$7:$BK$69,50,0) -> 870.32 | N101: =VLOOKUP(B102,'B&L'!$A$7:$BK$69,55,0) -> 858.97 | O101: =VLOOKUP(B102,'B&L'!$A$7:$BK$69,60,0) -> 874.03
B102: 1412000018 | C102: 土地 Land | D102: =VLOOKUP(B102,'B&L'!$A$7:$BK$69,6,0) -> 58.51 | E102: =VLOOKUP(B102,'B&L'!$A$7:$BK$69,11,0) -> 59.24 | F102: =VLOOKUP(B102,'B&L'!$A$7:$BK$69,16,0) -> 59.89 | G102: =VLOOKUP(B102,'B&L'!$A$7:$BK$69,21,0) -> 59.24 | H102: =VLOOKUP(B102,'B&L'!$A$7:$BK$69,26,0) -> 58.79 | I102: =VLOOKUP(B102,'B&L'!$A$7:$BK$69,31,0) -> 58.97 | J102: =VLOOKUP(B102,'B&L'!$A$7:$BK$69,36,0) -> 59.28 | K102: =VLOOKUP(B102,'B&L'!$A$7:$BK$69,41,0) -> 59.15 | L102: =VLOOKUP(B102,'B&L'!$A$7:$BK$69,46,0) -> 59.07 | M102: =VLOOKUP(B102,'B&L'!$A$7:$BK$69,51,0) -> 58.74 | N102: =VLOOKUP(B102,'B&L'!$A$7:$BK$69,56,0) -> 57.98 | O102: =VLOOKUP(B102,'B&L'!$A$7:$BK$69,61,0) -> 58.99
...

Sheet 固定資産金利（Interest）
C2: Interest | E2: USD | I2: USD
A3: 部署 | C3: 固定資産金利 | D3: 46113 | E3: =IF(MONTH(D3)=12,EDATE(D3,1),EDATE(D3,1)) -> 46143 | F3: =IF(MONTH(E3)=12,EDATE(E3,1),EDATE(E3,1)) -> 46174 | G3: =IF(MONTH(F3)=12,EDATE(F3,1),EDATE(F3,1)) -> 46204 | H3: =IF(MONTH(G3)=12,EDATE(G3,1),EDATE(G3,1)) -> 46235 | I3: =IF(MONTH(H3)=12,EDATE(H3,1),EDATE(H3,1)) -> 46266 | J3: =IF(MONTH(I3)=12,EDATE(I3,1),EDATE(I3,1)) -> 46296 | K3: =IF(MONTH(J3)=12,EDATE(J3,1),EDATE(J3,1)) -> 46327 | L3: =IF(MONTH(K3)=12,EDATE(K3,1),EDATE(K3,1)) -> 46357 | ... O3: =IF(MONTH(N3)=12,EDATE(N3,1),EDATE(N3,1)) -> 46447
A4: 振替総額 | C4: 建物 Building | D4: =D133 -> 208679.16 | E4: =E133 -> 196991.77 | F4: =F133 -> 196991.77 | G4: =G133 -> 196991.77 | H4: =H133 -> 196991.77 | I4: =I133 -> 196991.77 | J4: =J133 -> 196991.77 | K4: =K133 -> 196991.77 | ... O4: =O133 -> 196991.77
C5: 土地 Land | D5: =D134 -> 26458.43 | E5: =E134 -> 25669.57 | F5: =F134 -> 25669.57 | G5: =G134 -> 25669.57 | H5: =H134 -> 25669.57 | I5: =I134 -> 25669.57 | J5: =J134 -> 25669.57 | K5: =K134 -> 25669.57 | ... O5: =O134 -> 25669.57
A7: 1 | B7: 機器製造1課 | C7: 建物 Building | D7: =VLOOKUP(B8,'B&L'!$A$7:$BK$69,7,0) -> 8433.66 | E7: =VLOOKUP(B8,'B&L'!$A$7:$BK$69,12,0) -> 7974.42 | F7: =VLOOKUP(B8,'B&L'!$A$7:$BK$69,17,0) -> 7818.65 | G7: =VLOOKUP(B8,'B&L'!$A$7:$BK$69,22,0) -> 7956.49 | H7: =VLOOKUP(B8,'B&L'!$A$7:$BK$69,27,0) -> 8139.8 | I7: =VLOOKUP(B8,'B&L'!$A$7:$BK$69,32,0) -> 8139.69 | J7: =VLOOKUP(B8,'B&L'!$A$7:$BK$69,37,0) -> 7955.72 | K7: =VLOOKUP(B8,'B&L'!$A$7:$BK$69,42,0) -> 8066.7 | L7: =VLOOKUP(B8,'B&L'!$A$7:$BK$69,47,0) -> 8084.42 | M7: =VLOOKUP(B8,'B&L'!$A$7:$BK$69,52,0) -> 8182.42 | N7: =VLOOKUP(B8,'B&L'!$A$7:$BK$69,57,0) -> 8630.63 | O7: =VLOOKUP(B8,'B&L'!$A$7:$BK$69,62,0) -> 8056.35
B8: 1412000004 | C8: 土地 Land | D8: =VLOOKUP(B8,'B&L'!$A$7:$BK$69,8,0) -> 1069.3 | E8: =VLOOKUP(B8,'B&L'!$A$7:$BK$69,13,0) -> 1039.13 | F8: =VLOOKUP(B8,'B&L'!$A$7:$BK$69,18,0) -> 1018.83 | G8: =VLOOKUP(B8,'B&L'!$A$7:$BK$69,23,0) -> 1036.79 | H8: =VLOOKUP(B8,'B&L'!$A$7:$BK$69,28,0) -> 1060.68 | I8: =VLOOKUP(B8,'B&L'!$A$7:$BK$69,33,0) -> 1060.67 | J8: =VLOOKUP(B8,'B&L'!$A$7:$BK$69,38,0) -> 1036.69 | K8: =VLOOKUP(B8,'B&L'!$A$7:$BK$69,43,0) -> 1051.15 | L8: =VLOOKUP(B8,'B&L'!$A$7:$BK$69,48,0) -> 1053.46 | M8: =VLOOKUP(B8,'B&L'!$A$7:$BK$69,53,0) -> 1066.23 | N8: =VLOOKUP(B8,'B&L'!$A$7:$BK$69,58,0) -> 1124.64 | O8: =VLOOKUP(B8,'B&L'!$A$7:$BK$69,63,0) -> 1049.81
A9: 2 | B9: 機器製造2課 | C9: 建物 Building | D9: =VLOOKUP(B10,'B&L'!$A$7:$BK$69,7,0) -> 11446.54 | E9: =VLOOKUP(B10,'B&L'!$A$7:$BK$69,12,0) -> 10873.48 | F9: =VLOOKUP(B10,'B&L'!$A$7:$BK$69,17,0) -> 10908.94 | G9: =VLOOKUP(B10,'B&L'!$A$7:$BK$69,22,0) -> 10921.29 | H9: =VLOOKUP(B10,'B&L'!$A$7:$BK$69,27,0) -> 10896.86 | I9: =VLOOKUP(B10,'B&L'!$A$7:$BK$69,32,0) -> 10900.2 | J9: =VLOOKUP(B10,'B&L'!$A$7:$BK$69,37,0) -> 10889.06 | K9: =VLOOKUP(B10,'B&L'!$A$7:$BK$69,42,0) -> 10871.36 | L9: =VLOOKUP(B10,'B&L'!$A$7:$BK$69,47,0) -> 10802.29 | M9: =VLOOKUP(B10,'B&L'!$A$7:$BK$69,52,0) -> 10852.12 | N9: =VLOOKUP(B10,'B&L'!$A$7:$BK$69,57,0) -> 11022.07 | O9: =VLOOKUP(B10,'B&L'!$A$7:$BK$69,62,0) -> 10825.02
B10: 1412000005 | C10: 土地 Land | D10: =VLOOKUP(B10,'B&L'!$A$7:$BK$69,8,0) -> 1451.31 | E10: =VLOOKUP(B10,'B&L'!$A$7:$BK$69,13,0) -> 1416.9 | F10: =VLOOKUP(B10,'B&L'!$A$7:$BK$69,18,0) -> 1421.52 | G10: =VLOOKUP(B10,'B&L'!$A$7:$BK$69,23,0) -> 1423.13 | H10: =VLOOKUP(B10,'B&L'!$A$7:$BK$69,28,0) -> 1419.95 | I10: =VLOOKUP(B10,'B&L'!$A$7:$BK$69,33,0) -> 1420.38 | J10: =VLOOKUP(B10,'B&L'!$A$7:$BK$69,38,0) -> 1418.93 | K10: =VLOOKUP(B10,'B&L'!$A$7:$BK$69,43,0) -> 1416.62 | L10: =VLOOKUP(B10,'B&L'!$A$7:$BK$69,48,0) -> 1407.62 | M10: =VLOOKUP(B10,'B&L'!$A$7:$BK$69,53,0) -> 1414.12 | N10: =VLOOKUP(B10,'B&L'!$A$7:$BK$69,58,0) -> 1436.26 | O10: =VLOOKUP(B10,'B&L'!$A$7:$BK$69,63,0) -> 1410.58
A11: 3 | B11: 機器製造管理課 | C11: 建物 Building | D11: =VLOOKUP(B12,'B&L'!$A$7:$BK$69,7,0) -> 157.17 | E11: =VLOOKUP(B12,'B&L'!$A$7:$BK$69,12,0) -> 151.86 | F11: =VLOOKUP(B12,'B&L'!$A$7:$BK$69,17,0) -> 161.14 | G11: =VLOOKUP(B12,'B&L'!$A$7:$BK$69,22,0) -> 151.89 | H11: =VLOOKUP(B12,'B&L'!$A$7:$BK$69,27,0) -> 145.53 | I11: =VLOOKUP(B12,'B&L'!$A$7:$BK$69,32,0) -> 148.09 | J11: =VLOOKUP(B12,'B&L'!$A$7:$BK$69,37,0) -> 152.45 | K11: =VLOOKUP(B12,'B&L'!$A$7:$BK$69,42,0) -> 150.6 | L11: =VLOOKUP(B12,'B&L'!$A$7:$BK$69,47,0) -> 149.42 | M11: =VLOOKUP(B12,'B&L'!$A$7:$BK$69,52,0) -> 144.83 | N11: =VLOOKUP(B12,'B&L'!$A$7:$BK$69,57,0) -> 133.95 | O11: =VLOOKUP(B12,'B&L'!$A$7:$BK$69,62,0) -> 148.38
B12: 1412000062 | C12: 土地 Land | D12: =VLOOKUP(B12,'B&L'!$A$7:$BK$69,8,0) -> 19.93 | E12: =VLOOKUP(B12,'B&L'!$A$7:$BK$69,13,0) -> 19.79 | F12: =VLOOKUP(B12,'B&L'!$A$7:$BK$69,18,0) -> 21 | G12: =VLOOKUP(B12,'B&L'!$A$7:$BK$69,23,0) -> 19.79 | H12: =VLOOKUP(B12,'B&L'!$A$7:$BK$69,28,0) -> 18.96 | I12: =VLOOKUP(B12,'B&L'!$A$7:$BK$69,33,0) -> 19.3 | J12: =VLOOKUP(B12,'B&L'!$A$7:$BK$69,38,0) -> 19.87 | K12: =VLOOKUP(B12,'B&L'!$A$7:$BK$69,43,0) -> 19.62 | L12: =VLOOKUP(B12,'B&L'!$A$7:$BK$69,48,0) -> 19.47 | M12: =VLOOKUP(B12,'B&L'!$A$7:$BK$69,53,0) -> 18.87 | N12: =VLOOKUP(B12,'B&L'!$A$7:$BK$69,58,0) -> 17.46 | O12: =VLOOKUP(B12,'B&L'!$A$7:$BK$69,63,0) -> 19.34
A13: 4 | B13: RPS製造課 | C13: 建物 Building | D13: =VLOOKUP(B14,'B&L'!$A$7:$BK$69,7,0) -> 4101.03 | E13: =VLOOKUP(B14,'B&L'!$A$7:$BK$69,12,0) -> 3871.34 | F13: =VLOOKUP(B14,'B&L'!$A$7:$BK$69,17,0) -> 3871.34 | G13: =VLOOKUP(B14,'B&L'!$A$7:$BK$69,22,0) -> 3871.34 | H13: =VLOOKUP(B14,'B&L'!$A$7:$BK$69,27,0) -> 3871.34 | I13: =VLOOKUP(B14,'B&L'!$A$7:$BK$69,32,0) -> 3871.34 | J13: =VLOOKUP(B14,'B&L'!$A$7:$BK$69,37,0) -> 3871.34 | K13: =VLOOKUP(B14,'B&L'!$A$7:$BK$69,42,0) -> 3871.34 | L13: =VLOOKUP(B14,'B&L'!$A$7:$BK$69,47,0) -> 3871.34 | M13: =VLOOKUP(B14,'B&L'!$A$7:$BK$69,52,0) -> 3871.34 | N13: =VLOOKUP(B14,'B&L'!$A$7:$BK$69,57,0) -> 3871.34 | O13: =VLOOKUP(B14,'B&L'!$A$7:$BK$69,62,0) -> 3871.34
B14: 1412000066 | C14: 土地 Land | D14: =VLOOKUP(B14,'B&L'!$A$7:$BK$69,8,0) -> 519.97 | E14: =VLOOKUP(B14,'B&L'!$A$7:$BK$69,13,0) -> 504.47 | F14: =VLOOKUP(B14,'B&L'!$A$7:$BK$69,18,0) -> 504.47 | G14: =VLOOKUP(B14,'B&L'!$A$7:$BK$69,23,0) -> 504.47 | H14: =VLOOKUP(B14,'B&L'!$A$7:$BK$69,28,0) -> 504.47 | I14: =VLOOKUP(B14,'B&L'!$A$7:$BK$69,33,0) -> 504.47 | J14: =VLOOKUP(B14,'B&L'!$A$7:$BK$69,38,0) -> 504.47 | K14: =VLOOKUP(B14,'B&L'!$A$7:$BK$69,43,0) -> 504.47 | L14: =VLOOKUP(B14,'B&L'!$A$7:$BK$69,48,0) -> 504.47 | M14: =VLOOKUP(B14,'B&L'!$A$7:$BK$69,53,0) -> 504.47 | N14: =VLOOKUP(B14,'B&L'!$A$7:$BK$69,58,0) -> 504.47 | O14: =VLOOKUP(B14,'B&L'!$A$7:$BK$69,63,0) -> 504.47
A15: 5 | B15: 機器製造3課 | C15: 建物 Building | D15: =VLOOKUP(B16,'B&L'!$A$7:$BK$69,7,0) -> 30794.11 | E15: =VLOOKUP(B16,'B&L'!$A$7:$BK$69,12,0) -> 28899.84 | F15: =VLOOKUP(B16,'B&L'!$A$7:$BK$69,17,0) -> 28650.77 | G15: =VLOOKUP(B16,'B&L'!$A$7:$BK$69,22,0) -> 28823.57 | H15: =VLOOKUP(B16,'B&L'!$A$7:$BK$69,27,0) -> 28958.5 | I15: =VLOOKUP(B16,'B&L'!$A$7:$BK$69,32,0) -> 28890.45 | J15: =VLOOKUP(B16,'B&L'!$A$7:$BK$69,37,0) -> 28762.99 | K15: =VLOOKUP(B16,'B&L'!$A$7:$BK$69,42,0) -> 28818.6 | L15: =VLOOKUP(B16,'B&L'!$A$7:$BK$69,47,0) -> 28914.25 | M15: =VLOOKUP(B16,'B&L'!$A$7:$BK$69,52,0) -> 28969.5 | N15: =VLOOKUP(B16,'B&L'!$A$7:$BK$69,57,0) -> 29039.52 | O15: =VLOOKUP(B16,'B&L'!$A$7:$BK$69,62,0) -> 28919.89
B16: 1412000081 | C16: 土地 Land | D16: =VLOOKUP(B16,'B&L'!$A$7:$BK$69,8,0) -> 3904.38 | E16: =VLOOKUP(B16,'B&L'!$A$7:$BK$69,13,0) -> 3765.88 | F16: =VLOOKUP(B16,'B&L'!$A$7:$BK$69,18,0) -> 3733.42 | G16: =VLOOKUP(B16,'B&L'!$A$7:$BK$69,23,0) -> 3755.94 | H16: =VLOOKUP(B16,'B&L'!$A$7:$BK$69,28,0) -> 3773.52 | I16: =VLOOKUP(B16,'B&L'!$A$7:$BK$69,33,0) -> 3764.65 | J16: =VLOOKUP(B16,'B&L'!$A$7:$BK$69,38,0) -> 3748.04 | K16: =VLOOKUP(B16,'B&L'!$A$7:$BK$69,43,0) -> 3755.29 | L16: =VLOOKUP(B16,'B&L'!$A$7:$BK$69,48,0) -> 3767.75 | M16: =VLOOKUP(B16,'B&L'!$A$7:$BK$69,53,0) -> 3774.95 | N16: =VLOOKUP(B16,'B&L'!$A$7:$BK$69,58,0) -> 3784.08 | O16: =VLOOKUP(B16,'B&L'!$A$7:$BK$69,63,0) -> 3768.49
A17: 6 | B17: 電工製造課 | C17: 建物 Building | D17: =VLOOKUP(B18,'B&L'!$A$7:$BK$69,7,0) -> 3468.6 | E17: =VLOOKUP(B18,'B&L'!$A$7:$BK$69,12,0) -> 3274.17 | F17: =VLOOKUP(B18,'B&L'!$A$7:$BK$69,17,0) -> 3282.36 | G17: =VLOOKUP(B18,'B&L'!$A$7:$BK$69,22,0) -> 3274.28 | H17: =VLOOKUP(B18,'B&L'!$A$7:$BK$69,27,0) -> 3266.15 | I17: =VLOOKUP(B18,'B&L'!$A$7:$BK$69,32,0) -> 3267 | J17: =VLOOKUP(B18,'B&L'!$A$7:$BK$69,37,0) -> 3275.48 | K17: =VLOOKUP(B18,'B&L'!$A$7:$BK$69,42,0) -> 3270.34 | L17: =VLOOKUP(B18,'B&L'!$A$7:$BK$69,47,0) -> 3269.51 | M17: =VLOOKUP(B18,'B&L'!$A$7:$BK$69,52,0) -> 3257.96 | N17: =VLOOKUP(B18,'B&L'!$A$7:$BK$69,57,0) -> 3237.89 | O17: =VLOOKUP(B18,'B&L'!$A$7:$BK$69,62,0) -> 3263.97
B18: 1412000098 | C18: 土地 Land | D18: =VLOOKUP(B18,'B&L'!$A$7:$BK$69,8,0) -> 439.78 | E18: =VLOOKUP(B18,'B&L'!$A$7:$BK$69,13,0) -> 426.65 | F18: =VLOOKUP(B18,'B&L'!$A$7:$BK$69,18,0) -> 427.72 | G18: =VLOOKUP(B18,'B&L'!$A$7:$BK$69,23,0) -> 426.66 | H18: =VLOOKUP(B18,'B&L'!$A$7:$BK$69,28,0) -> 425.6 | I18: =VLOOKUP(B18,'B&L'!$A$7:$BK$69,33,0) -> 425.72 | J18: =VLOOKUP(B18,'B&L'!$A$7:$BK$69,38,0) -> 426.82 | K18: =VLOOKUP(B18,'B&L'!$A$7:$BK$69,43,0) -> 426.15 | L18: =VLOOKUP(B18,'B&L'!$A$7:$BK$69,48,0) -> 426.04 | M18: =VLOOKUP(B18,'B&L'!$A$7:$BK$69,53,0) -> 424.54 | N18: =VLOOKUP(B18,'B&L'!$A$7:$BK$69,58,0) -> 421.92 | O18: =VLOOKUP(B18,'B&L'!$A$7:$BK$69,63,0) -> 425.32
A19: 7 | B19: トナー製造課 | C19: 建物 Building | D19: =VLOOKUP(B20,'B&L'!$A$7:$BK$69,7,0) -> 6180.47 | E19: =VLOOKUP(B20,'B&L'!$A$7:$BK$69,12,0) -> 5868.57 | F19: =VLOOKUP(B20,'B&L'!$A$7:$BK$69,17,0) -> 5949.28 | G19: =VLOOKUP(B20,'B&L'!$A$7:$BK$69,22,0) -> 5872.83 | H19: =VLOOKUP(B20,'B&L'!$A$7:$BK$69,27,0) -> 5835.32 | I19: =VLOOKUP(B20,'B&L'!$A$7:$BK$69,32,0) -> 5858.63 | J19: =VLOOKUP(B20,'B&L'!$A$7:$BK$69,37,0) -> 5947.58 | K19: =VLOOKUP(B20,'B&L'!$A$7:$BK$69,42,0) -> 5929.29 | L19: =VLOOKUP(B20,'B&L'!$A$7:$BK$69,47,0) -> 5917.57 | M19: =VLOOKUP(B20,'B&L'!$A$7:$BK$69,52,0) -> 5872.09 | N19: =VLOOKUP(B20,'B&L'!$A$7:$BK$69,57,0) -> 5764.43 | O19: =VLOOKUP(B20,'B&L'!$A$7:$BK$69,62,0) -> 5907.29
B20: 1412000034 | C20: 土地 Land | D20: =VLOOKUP(B20,'B&L'!$A$7:$BK$69,8,0) -> 783.62 | E20: =VLOOKUP(B20,'B&L'!$A$7:$BK$69,13,0) -> 764.72 | F20: =VLOOKUP(B20,'B&L'!$A$7:$BK$69,18,0) -> 775.24 | G20: =VLOOKUP(B20,'B&L'!$A$7:$BK$69,23,0) -> 765.28 | H20: =VLOOKUP(B20,'B&L'!$A$7:$BK$69,28,0) -> 760.39 | I20: =VLOOKUP(B20,'B&L'!$A$7:$BK$69,33,0) -> 763.43 | J20: =VLOOKUP(B20,'B&L'!$A$7:$BK$69,38,0) -> 775.02 | K20: =VLOOKUP(B20,'B&L'!$A$7:$BK$69,43,0) -> 772.63 | L20: =VLOOKUP(B20,'B&L'!$A$7:$BK$69,48,0) -> 771.11 | M20: =VLOOKUP(B20,'B&L'!$A$7:$BK$69,53,0) -> 765.18 | N20: =VLOOKUP(B20,'B&L'!$A$7:$BK$69,58,0) -> 751.15 | O20: =VLOOKUP(B20,'B&L'!$A$7:$BK$69,63,0) -> 769.77
A21: 8 | B21: トナー生産技術 | C21: 建物 Building | D21: =VLOOKUP(B22,'B&L'!$A$7:$BK$69,7,0) -> 194.96 | E21: =VLOOKUP(B22,'B&L'!$A$7:$BK$69,12,0) -> 186.84 | F21: =VLOOKUP(B22,'B&L'!$A$7:$BK$69,17,0) -> 194.26 | G21: =VLOOKUP(B22,'B&L'!$A$7:$BK$69,22,0) -> 186.86 | H21: =VLOOKUP(B22,'B&L'!$A$7:$BK$69,27,0) -> 181.77 | I21: =VLOOKUP(B22,'B&L'!$A$7:$BK$69,32,0) -> 183.82 | J21: =VLOOKUP(B22,'B&L'!$A$7:$BK$69,37,0) -> 187.31 | K21: =VLOOKUP(B22,'B&L'!$A$7:$BK$69,42,0) -> 185.83 | L21: =VLOOKUP(B22,'B&L'!$A$7:$BK$69,47,0) -> 184.89 | M21: =VLOOKUP(B22,'B&L'!$A$7:$BK$69,52,0) -> 181.21 | N21: =VLOOKUP(B22,'B&L'!$A$7:$BK$69,57,0) -> 172.51 | O21: =VLOOKUP(B22,'B&L'!$A$7:$BK$69,62,0) -> 184.06
B22: 1412000048 | C22: 土地 Land | D22: =VLOOKUP(B22,'B&L'!$A$7:$BK$69,8,0) -> 24.72 | E22: =VLOOKUP(B22,'B&L'!$A$7:$BK$69,13,0) -> 24.35 | F22: =VLOOKUP(B22,'B&L'!$A$7:$BK$69,18,0) -> 25.31 | G22: =VLOOKUP(B22,'B&L'!$A$7:$BK$69,23,0) -> 24.35 | H22: =VLOOKUP(B22,'B&L'!$A$7:$BK$69,28,0) -> 23.69 | I22: =VLOOKUP(B22,'B&L'!$A$7:$BK$69,33,0) -> 23.95 | J22: =VLOOKUP(B22,'B&L'!$A$7:$BK$69,38,0) -> 24.41 | K22: =VLOOKUP(B22,'B&L'!$A$7:$BK$69,43,0) -> 24.22 | L22: =VLOOKUP(B22,'B&L'!$A$7:$BK$69,48,0) -> 24.09 | M22: =VLOOKUP(B22,'B&L'!$A$7:$BK$69,53,0) -> 23.61 | N22: =VLOOKUP(B22,'B&L'!$A$7:$BK$69,58,0) -> 22.48 | O22: =VLOOKUP(B22,'B&L'!$A$7:$BK$69,63,0) -> 23.98
A23: 9 | B23: トナー品質管理課 | C23: 建物 Building | D23: =VLOOKUP(B24,'B&L'!$A$7:$BK$69,7,0) -> 130 | E23: =VLOOKUP(B24,'B&L'!$A$7:$BK$69,12,0) -> 125.4 | F23: =VLOOKUP(B24,'B&L'!$A$7:$BK$69,17,0) -> 132.51 | G23: =VLOOKUP(B24,'B&L'!$A$7:$BK$69,22,0) -> 125.42 | H23: =VLOOKUP(B24,'B&L'!$A$7:$BK$69,27,0) -> 122.37 | I23: =VLOOKUP(B24,'B&L'!$A$7:$BK$69,32,0) -> 124.41 | J23: =VLOOKUP(B24,'B&L'!$A$7:$BK$69,37,0) -> 127.9 | K23: =VLOOKUP(B24,'B&L'!$A$7:$BK$69,42,0) -> 126.43 | L23: =VLOOKUP(B24,'B&L'!$A$7:$BK$69,47,0) -> 125.48 | M23: =VLOOKUP(B24,'B&L'!$A$7:$BK$69,52,0) -> 121.8 | N23: =VLOOKUP(B24,'B&L'!$A$7:$BK$69,57,0) -> 113.1 | O23: =VLOOKUP(B24,'B&L'!$A$7:$BK$69,62,0) -> 124.65
B24: 1412000055 | C24: 土地 Land | D24: =VLOOKUP(B24,'B&L'!$A$7:$BK$69,8,0) -> 16.48 | E24: =VLOOKUP(B24,'B&L'!$A$7:$BK$69,13,0) -> 16.34 | F24: =VLOOKUP(B24,'B&L'!$A$7:$BK$69,18,0) -> 17.27 | G24: =VLOOKUP(B24,'B&L'!$A$7:$BK$69,23,0) -> 16.34 | H24: =VLOOKUP(B24,'B&L'!$A$7:$BK$69,28,0) -> 15.95 | I24: =VLOOKUP(B24,'B&L'!$A$7:$BK$69,33,0) -> 16.21 | J24: =VLOOKUP(B24,'B&L'!$A$7:$BK$69,38,0) -> 16.67 | K24: =VLOOKUP(B24,'B&L'!$A$7:$BK$69,43,0) -> 16.47 | L24: =VLOOKUP(B24,'B&L'!$A$7:$BK$69,48,0) -> 16.35 | M24: =VLOOKUP(B24,'B&L'!$A$7:$BK$69,53,0) -> 15.87 | N24: =VLOOKUP(B24,'B&L'!$A$7:$BK$69,58,0) -> 14.74 | O24: =VLOOKUP(B24,'B&L'!$A$7:$BK$69,63,0) -> 16.24
A25: 10 | B25: トナー製造管理課 | C25: 建物 Building | D25: =VLOOKUP(B26,'B&L'!$A$7:$BK$69,7,0) -> 24.28 | E25: =VLOOKUP(B26,'B&L'!$A$7:$BK$69,12,0) -> 22.05 | F25: =VLOOKUP(B26,'B&L'!$A$7:$BK$69,17,0) -> 24.83 | G25: =VLOOKUP(B26,'B&L'!$A$7:$BK$69,22,0) -> 26.12 | H25: =VLOOKUP(B26,'B&L'!$A$7:$BK$69,27,0) -> 23.79 | I25: =VLOOKUP(B26,'B&L'!$A$7:$BK$69,32,0) -> 28.55 | J25: =VLOOKUP(B26,'B&L'!$A$7:$BK$69,37,0) -> 28.38 | K25: =VLOOKUP(B26,'B&L'!$A$7:$BK$69,42,0) -> 27.64 | L25: =VLOOKUP(B26,'B&L'!$A$7:$BK$69,47,0) -> 25.22 | M25: =VLOOKUP(B26,'B&L'!$A$7:$BK$69,52,0) -> 23.53 | N25: =VLOOKUP(B26,'B&L'!$A$7:$BK$69,57,0) -> 18.11 | O25: =VLOOKUP(B26,'B&L'!$A$7:$BK$69,62,0) -> 22.92
B26: 1412000063 | C26: 土地 Land | D26: =VLOOKUP(B26,'B&L'!$A$7:$BK$69,8,0) -> 3.08 | E26: =VLOOKUP(B26,'B&L'!$A$7:$BK$69,13,0) -> 2.87 | F26: =VLOOKUP(B26,'B&L'!$A$7:$BK$69,18,0) -> 3.24 | G26: =VLOOKUP(B26,'B&L'!$A$7:$BK$69,23,0) -> 3.4 | H26: =VLOOKUP(B26,'B&L'!$A$7:$BK$69,28,0) -> 3.1 | I26: =VLOOKUP(B26,'B&L'!$A$7:$BK$69,33,0) -> 3.72 | J26: =VLOOKUP(B26,'B&L'!$A$7:$BK$69,38,0) -> 3.7 | K26: =VLOOKUP(B26,'B&L'!$A$7:$BK$69,43,0) -> 3.6 | L26: =VLOOKUP(B26,'B&L'!$A$7:$BK$69,48,0) -> 3.29 | M26: =VLOOKUP(B26,'B&L'!$A$7:$BK$69,53,0) -> 3.07 | N26: =VLOOKUP(B26,'B&L'!$A$7:$BK$69,58,0) -> 2.36 | O26: =VLOOKUP(B26,'B&L'!$A$7:$BK$69,63,0) -> 2.99
A27: 11 | B27: 金型技術課 | C27: 建物 Building | D27: =VLOOKUP(B28,'B&L'!$A$7:$BK$69,7,0) -> 1040.28 | E27: =VLOOKUP(B28,'B&L'!$A$7:$BK$69,12,0) -> 986.99 | F27: =VLOOKUP(B28,'B&L'!$A$7:$BK$69,17,0) -> 991.83 | G27: =VLOOKUP(B28,'B&L'!$A$7:$BK$69,22,0) -> 987.05 | H27: =VLOOKUP(B28,'B&L'!$A$7:$BK$69,27,0) -> 982.24 | I27: =VLOOKUP(B28,'B&L'!$A$7:$BK$69,32,0) -> 982.75 | J27: =VLOOKUP(B28,'B&L'!$A$7:$BK$69,37,0) -> 987.77 | K27: =VLOOKUP(B28,'B&L'!$A$7:$BK$69,42,0) -> 984.72 | L27: =VLOOKUP(B28,'B&L'!$A$7:$BK$69,47,0) -> 984.23 | M27: =VLOOKUP(B28,'B&L'!$A$7:$BK$69,52,0) -> 981.55 | N27: =VLOOKUP(B28,'B&L'!$A$7:$BK$69,57,0) -> 968.9 | O27: =VLOOKUP(B28,'B&L'!$A$7:$BK$69,62,0) -> 985.34
B28: 1412000044 | C28: 土地 Land | D28: =VLOOKUP(B28,'B&L'!$A$7:$BK$69,8,0) -> 131.9 | E28: =VLOOKUP(B28,'B&L'!$A$7:$BK$69,13,0) -> 128.61 | F28: =VLOOKUP(B28,'B&L'!$A$7:$BK$69,18,0) -> 129.24 | G28: =VLOOKUP(B28,'B&L'!$A$7:$BK$69,23,0) -> 128.62 | H28: =VLOOKUP(B28,'B&L'!$A$7:$BK$69,28,0) -> 127.99 | I28: =VLOOKUP(B28,'B&L'!$A$7:$BK$69,33,0) -> 128.06 | J28: =VLOOKUP(B28,'B&L'!$A$7:$BK$69,38,0) -> 128.71 | K28: =VLOOKUP(B28,'B&L'!$A$7:$BK$69,43,0) -> 128.32 | L28: =VLOOKUP(B28,'B&L'!$A$7:$BK$69,48,0) -> 128.25 | M28: =VLOOKUP(B28,'B&L'!$A$7:$BK$69,53,0) -> 127.9 | N28: =VLOOKUP(B28,'B&L'!$A$7:$BK$69,58,0) -> 126.25 | O28: =VLOOKUP(B28,'B&L'!$A$7:$BK$69,63,0) -> 128.4
A29: 12 | B29: 部品製造管理課 | C29: 建物 Building | D29: =VLOOKUP(B30,'B&L'!$A$7:$BK$69,7,0) -> 70.72 | E29: =VLOOKUP(B30,'B&L'!$A$7:$BK$69,12,0) -> 66.74 | F29: =VLOOKUP(B30,'B&L'!$A$7:$BK$69,17,0) -> 68.07 | G29: =VLOOKUP(B30,'B&L'!$A$7:$BK$69,22,0) -> 66.75 | H29: =VLOOKUP(B30,'B&L'!$A$7:$BK$69,27,0) -> 65.43 | I29: =VLOOKUP(B30,'B&L'!$A$7:$BK$69,32,0) -> 65.57 | J29: =VLOOKUP(B30,'B&L'!$A$7:$BK$69,37,0) -> 66.95 | K29: =VLOOKUP(B30,'B&L'!$A$7:$BK$69,42,0) -> 66.11 | L29: =VLOOKUP(B30,'B&L'!$A$7:$BK$69,47,0) -> 65.98 | M29: =VLOOKUP(B30,'B&L'!$A$7:$BK$69,52,0) -> 65.24 | N29: =VLOOKUP(B30,'B&L'!$A$7:$BK$69,57,0) -> 61.75 | O29: =VLOOKUP(B30,'B&L'!$A$7:$BK$69,62,0) -> 66.28
B30: 1412000087 | C30: 土地 Land | D30: =VLOOKUP(B30,'B&L'!$A$7:$BK$69,8,0) -> 8.97 | E30: =VLOOKUP(B30,'B&L'!$A$7:$BK$69,13,0) -> 8.7 | F30: =VLOOKUP(B30,'B&L'!$A$7:$BK$69,18,0) -> 8.87 | G30: =VLOOKUP(B30,'B&L'!$A$7:$BK$69,23,0) -> 8.7 | H30: =VLOOKUP(B30,'B&L'!$A$7:$BK$69,28,0) -> 8.53 | I30: =VLOOKUP(B30,'B&L'!$A$7:$BK$69,33,0) -> 8.54 | J30: =VLOOKUP(B30,'B&L'!$A$7:$BK$69,38,0) -> 8.72 | K30: =VLOOKUP(B30,'B&L'!$A$7:$BK$69,43,0) -> 8.61 | L30: =VLOOKUP(B30,'B&L'!$A$7:$BK$69,48,0) -> 8.6 | M30: =VLOOKUP(B30,'B&L'!$A$7:$BK$69,53,0) -> 8.5 | N30: =VLOOKUP(B30,'B&L'!$A$7:$BK$69,58,0) -> 8.05 | O30: =VLOOKUP(B30,'B&L'!$A$7:$BK$69,63,0) -> 8.64
A31: 13 | B31: 品質管理課 | C31: 建物 Building | D31: =VLOOKUP(B32,'B&L'!$A$7:$BK$69,7,0) -> 234.34 | E31: =VLOOKUP(B32,'B&L'!$A$7:$BK$69,12,0) -> 221.13 | F31: =VLOOKUP(B32,'B&L'!$A$7:$BK$69,17,0) -> 225.14 | G31: =VLOOKUP(B32,'B&L'!$A$7:$BK$69,22,0) -> 221.19 | H31: =VLOOKUP(B32,'B&L'!$A$7:$BK$69,27,0) -> 217.2 | I31: =VLOOKUP(B32,'B&L'!$A$7:$BK$69,32,0) -> 217.62 | J31: =VLOOKUP(B32,'B&L'!$A$7:$BK$69,37,0) -> 221.78 | K31: =VLOOKUP(B32,'B&L'!$A$7:$BK$69,42,0) -> 219.26 | L31: =VLOOKUP(B32,'B&L'!$A$7:$BK$69,47,0) -> 218.85 | M31: =VLOOKUP(B32,'B&L'!$A$7:$BK$69,52,0) -> 216.63 | N31: =VLOOKUP(B32,'B&L'!$A$7:$BK$69,57,0) -> 206.16 | O31: =VLOOKUP(B32,'B&L'!$A$7:$BK$69,62,0) -> 219.77
B32: 1412000088 | C32: 土地 Land | D32: =VLOOKUP(B32,'B&L'!$A$7:$BK$69,8,0) -> 29.71 | E32: =VLOOKUP(B32,'B&L'!$A$7:$BK$69,13,0) -> 28.82 | F32: =VLOOKUP(B32,'B&L'!$A$7:$BK$69,18,0) -> 29.34 | G32: =VLOOKUP(B32,'B&L'!$A$7:$BK$69,23,0) -> 28.82 | H32: =VLOOKUP(B32,'B&L'!$A$7:$BK$69,28,0) -> 28.3 | I32: =VLOOKUP(B32,'B&L'!$A$7:$BK$69,33,0) -> 28.36 | J32: =VLOOKUP(B32,'B&L'!$A$7:$BK$69,38,0) -> 28.9 | K32: =VLOOKUP(B32,'B&L'!$A$7:$BK$69,43,0) -> 28.57 | L32: =VLOOKUP(B32,'B&L'!$A$7:$BK$69,48,0) -> 28.52 | M32: =VLOOKUP(B32,'B&L'!$A$7:$BK$69,53,0) -> 28.23 | N32: =VLOOKUP(B32,'B&L'!$A$7:$BK$69,58,0) -> 26.86 | O32: =VLOOKUP(B32,'B&L'!$A$7:$BK$69,63,0) -> 28.64
A33: 14 | B33: 部品製造課 | C33: 建物 Building | D33: =VLOOKUP(B34,'B&L'!$A$7:$BK$69,7,0) -> 7379 | E33: =VLOOKUP(B34,'B&L'!$A$7:$BK$69,12,0) -> 6962.8 | F33: =VLOOKUP(B34,'B&L'!$A$7:$BK$69,17,0) -> 6979.65 | G33: =VLOOKUP(B34,'B&L'!$A$7:$BK$69,22,0) -> 6958 | H33: =VLOOKUP(B34,'B&L'!$A$7:$BK$69,27,0) -> 6936.55 | I33: =VLOOKUP(B34,'B&L'!$A$7:$BK$69,32,0) -> 6940.92 | J33: =VLOOKUP(B34,'B&L'!$A$7:$BK$69,37,0) -> 6963.38 | K33: =VLOOKUP(B34,'B&L'!$A$7:$BK$69,42,0) -> 6953.66 | L33: =VLOOKUP(B34,'B&L'!$A$7:$BK$69,47,0) -> 6954.12 | M33: =VLOOKUP(B34,'B&L'!$A$7:$BK$69,52,0) -> 6943.21 | N33: =VLOOKUP(B34,'B&L'!$A$7:$BK$69,57,0) -> 6891.72 | O33: =VLOOKUP(B34,'B&L'!$A$7:$BK$69,62,0) -> 6958.63
B34: 1412000056 | C34: 土地 Land | D34: =VLOOKUP(B34,'B&L'!$A$7:$BK$69,8,0) -> 935.58 | E34: =VLOOKUP(B34,'B&L'!$A$7:$BK$69,13,0) -> 907.31 | F34: =VLOOKUP(B34,'B&L'!$A$7:$BK$69,18,0) -> 909.5 | G34: =VLOOKUP(B34,'B&L'!$A$7:$BK$69,23,0) -> 906.68 | H34: =VLOOKUP(B34,'B&L'!$A$7:$BK$69,28,0) -> 903.89 | I34: =VLOOKUP(B34,'B&L'!$A$7:$BK$69,33,0) -> 904.46 | J34: =VLOOKUP(B34,'B&L'!$A$7:$BK$69,38,0) -> 907.38 | K34: =VLOOKUP(B34,'B&L'!$A$7:$BK$69,43,0) -> 906.12 | L34: =VLOOKUP(B34,'B&L'!$A$7:$BK$69,48,0) -> 906.18 | M34: =VLOOKUP(B34,'B&L'!$A$7:$BK$69,53,0) -> 904.76 | N34: =VLOOKUP(B34,'B&L'!$A$7:$BK$69,58,0) -> 898.05 | O34: =VLOOKUP(B34,'B&L'!$A$7:$BK$69,63,0) -> 906.76
A35: 15 | B35: 部品技術課 | C35: 建物 Building | D35: =VLOOKUP(B36,'B&L'!$A$7:$BK$69,7,0) -> 183.49 | E35: =VLOOKUP(B36,'B&L'!$A$7:$BK$69,12,0) -> 173.09 | F35: =VLOOKUP(B36,'B&L'!$A$7:$BK$69,17,0) -> 173.39 | G35: =VLOOKUP(B36,'B&L'!$A$7:$BK$69,22,0) -> 172.98 | H35: =VLOOKUP(B36,'B&L'!$A$7:$BK$69,27,0) -> 180.18 | I35: =VLOOKUP(B36,'B&L'!$A$7:$BK$69,32,0) -> 180.26 | J35: =VLOOKUP(B36,'B&L'!$A$7:$BK$69,37,0) -> 180.47 | K35: =VLOOKUP(B36,'B&L'!$A$7:$BK$69,42,0) -> 180.37 | L35: =VLOOKUP(B36,'B&L'!$A$7:$BK$69,47,0) -> 184.04 | M35: =VLOOKUP(B36,'B&L'!$A$7:$BK$69,52,0) -> 183.85 | N35: =VLOOKUP(B36,'B&L'!$A$7:$BK$69,57,0) -> 183.26 | O35: =VLOOKUP(B36,'B&L'!$A$7:$BK$69,62,0) -> 184.03
B36: 1412000080 | C36: 土地 Land | D36: =VLOOKUP(B36,'B&L'!$A$7:$BK$69,8,0) -> 23.26 | E36: =VLOOKUP(B36,'B&L'!$A$7:$BK$69,13,0) -> 22.56 | F36: =VLOOKUP(B36,'B&L'!$A$7:$BK$69,18,0) -> 22.59 | G36: =VLOOKUP(B36,'B&L'!$A$7:$BK$69,23,0) -> 22.54 | H36: =VLOOKUP(B36,'B&L'!$A$7:$BK$69,28,0) -> 23.48 | I36: =VLOOKUP(B36,'B&L'!$A$7:$BK$69,33,0) -> 23.49 | J36: =VLOOKUP(B36,'B&L'!$A$7:$BK$69,38,0) -> 23.52 | K36: =VLOOKUP(B36,'B&L'!$A$7:$BK$69,43,0) -> 23.5 | L36: =VLOOKUP(B36,'B&L'!$A$7:$BK$69,48,0) -> 23.98 | M36: =VLOOKUP(B36,'B&L'!$A$7:$BK$69,53,0) -> 23.96 | N36: =VLOOKUP(B36,'B&L'!$A$7:$BK$69,58,0) -> 23.88 | O36: =VLOOKUP(B36,'B&L'!$A$7:$BK$69,63,0) -> 23.98
A37: 16 | B37: 工程品質管理1課 | C37: 建物 Building | D37: =VLOOKUP(B38,'B&L'!$A$7:$BK$69,7,0) -> 331.11 | E37: =VLOOKUP(B38,'B&L'!$A$7:$BK$69,12,0) -> 313.71 | F37: =VLOOKUP(B38,'B&L'!$A$7:$BK$69,17,0) -> 320.86 | G37: =VLOOKUP(B38,'B&L'!$A$7:$BK$69,22,0) -> 326.42 | H37: =VLOOKUP(B38,'B&L'!$A$7:$BK$69,27,0) -> 319.92 | I37: =VLOOKUP(B38,'B&L'!$A$7:$BK$69,32,0) -> 321.55 | J37: =VLOOKUP(B38,'B&L'!$A$7:$BK$69,37,0) -> 332.3 | K37: =VLOOKUP(B38,'B&L'!$A$7:$BK$69,42,0) -> 329.07 | L37: =VLOOKUP(B38,'B&L'!$A$7:$BK$69,47,0) -> 328.11 | M37: =VLOOKUP(B38,'B&L'!$A$7:$BK$69,52,0) -> 323.78 | N37: =VLOOKUP(B38,'B&L'!$A$7:$BK$69,57,0) -> 308.74 | O37: =VLOOKUP(B38,'B&L'!$A$7:$BK$69,62,0) -> 328.43
B38: 1412000053 | C38: 土地 Land | D38: =VLOOKUP(B38,'B&L'!$A$7:$BK$69,8,0) -> 41.98 | E38: =VLOOKUP(B38,'B&L'!$A$7:$BK$69,13,0) -> 40.88 | F38: =VLOOKUP(B38,'B&L'!$A$7:$BK$69,18,0) -> 41.81 | G38: =VLOOKUP(B38,'B&L'!$A$7:$BK$69,23,0) -> 42.53 | H38: =VLOOKUP(B38,'B&L'!$A$7:$BK$69,28,0) -> 41.69 | I38: =VLOOKUP(B38,'B&L'!$A$7:$BK$69,33,0) -> 41.9 | J38: =VLOOKUP(B38,'B&L'!$A$7:$BK$69,38,0) -> 43.3 | K38: =VLOOKUP(B38,'B&L'!$A$7:$BK$69,43,0) -> 42.88 | L38: =VLOOKUP(B38,'B&L'!$A$7:$BK$69,48,0) -> 42.76 | M38: =VLOOKUP(B38,'B&L'!$A$7:$BK$69,53,0) -> 42.19 | N38: =VLOOKUP(B38,'B&L'!$A$7:$BK$69,58,0) -> 40.23 | O38: =VLOOKUP(B38,'B&L'!$A$7:$BK$69,63,0) -> 42.8
A39: 17 | B39: 工程品質管理2課 | C39: 建物 Building | D39: =VLOOKUP(B40,'B&L'!$A$7:$BK$69,7,0) -> 871.88 | E39: =VLOOKUP(B40,'B&L'!$A$7:$BK$69,12,0) -> 823.95 | F39: =VLOOKUP(B40,'B&L'!$A$7:$BK$69,17,0) -> 851.93 | G39: =VLOOKUP(B40,'B&L'!$A$7:$BK$69,22,0) -> 824.28 | H39: =VLOOKUP(B40,'B&L'!$A$7:$BK$69,27,0) -> 798.11 | I39: =VLOOKUP(B40,'B&L'!$A$7:$BK$69,32,0) -> 801.92 | J39: =VLOOKUP(B40,'B&L'!$A$7:$BK$69,37,0) -> 827.93 | K39: =VLOOKUP(B40,'B&L'!$A$7:$BK$69,42,0) -> 812.62 | L39: =VLOOKUP(B40,'B&L'!$A$7:$BK$69,47,0) -> 809.65 | M39: =VLOOKUP(B40,'B&L'!$A$7:$BK$69,52,0) -> 794.48 | N39: =VLOOKUP(B40,'B&L'!$A$7:$BK$69,57,0) -> 728.97 | O39: =VLOOKUP(B40,'B&L'!$A$7:$BK$69,62,0) -> 814.26
B40: 1412000104 | C40: 土地 Land | D40: =VLOOKUP(B40,'B&L'!$A$7:$BK$69,8,0) -> 110.55 | E40: =VLOOKUP(B40,'B&L'!$A$7:$BK$69,13,0) -> 107.37 | F40: =VLOOKUP(B40,'B&L'!$A$7:$BK$69,18,0) -> 111.01 | G40: =VLOOKUP(B40,'B&L'!$A$7:$BK$69,23,0) -> 107.41 | H40: =VLOOKUP(B40,'B&L'!$A$7:$BK$69,28,0) -> 104 | I40: =VLOOKUP(B40,'B&L'!$A$7:$BK$69,33,0) -> 104.5 | J40: =VLOOKUP(B40,'B&L'!$A$7:$BK$69,38,0) -> 107.89 | K40: =VLOOKUP(B40,'B&L'!$A$7:$BK$69,43,0) -> 105.89 | L40: =VLOOKUP(B40,'B&L'!$A$7:$BK$69,48,0) -> 105.5 | M40: =VLOOKUP(B40,'B&L'!$A$7:$BK$69,53,0) -> 103.53 | N40: =VLOOKUP(B40,'B&L'!$A$7:$BK$69,58,0) -> 94.99 | O40: =VLOOKUP(B40,'B&L'!$A$7:$BK$69,63,0) -> 106.1
A41: 18 | B41: 工程品質管理3課 | C41: 建物 Building | D41: =VLOOKUP(B42,'B&L'!$A$7:$BK$69,7,0) -> 205.54 | E41: =VLOOKUP(B42,'B&L'!$A$7:$BK$69,12,0) -> 194.29 | F41: =VLOOKUP(B42,'B&L'!$A$7:$BK$69,17,0) -> 198.2 | G41: =VLOOKUP(B42,'B&L'!$A$7:$BK$69,22,0) -> 194.33 | H41: =VLOOKUP(B42,'B&L'!$A$7:$BK$69,27,0) -> 190.83 | I41: =VLOOKUP(B42,'B&L'!$A$7:$BK$69,32,0) -> 191.45 | J41: =VLOOKUP(B42,'B&L'!$A$7:$BK$69,37,0) -> 194.8 | K41: =VLOOKUP(B42,'B&L'!$A$7:$BK$69,42,0) -> 192.87 | L41: =VLOOKUP(B42,'B&L'!$A$7:$BK$69,47,0) -> 192.45 | M41: =VLOOKUP(B42,'B&L'!$A$7:$BK$69,52,0) -> 190.35 | N41: =VLOOKUP(B42,'B&L'!$A$7:$BK$69,57,0) -> 181.92 | O41: =VLOOKUP(B42,'B&L'!$A$7:$BK$69,62,0) -> 192.92
B42: 1412000105 | C42: 土地 Land | D42: =VLOOKUP(B42,'B&L'!$A$7:$BK$69,8,0) -> 26.06 | E42: =VLOOKUP(B42,'B&L'!$A$7:$BK$69,13,0) -> 25.32 | F42: =VLOOKUP(B42,'B&L'!$A$7:$BK$69,18,0) -> 25.83 | G42: =VLOOKUP(B42,'B&L'!$A$7:$BK$69,23,0) -> 25.32 | H42: =VLOOKUP(B42,'B&L'!$A$7:$BK$69,28,0) -> 24.87 | I42: =VLOOKUP(B42,'B&L'!$A$7:$BK$69,33,0) -> 24.95 | J42: =VLOOKUP(B42,'B&L'!$A$7:$BK$69,38,0) -> 25.38 | K42: =VLOOKUP(B42,'B&L'!$A$7:$BK$69,43,0) -> 25.13 | L42: =VLOOKUP(B42,'B&L'!$A$7:$BK$69,48,0) -> 25.08 | M42: =VLOOKUP(B42,'B&L'!$A$7:$BK$69,53,0) -> 24.8 | N42: =VLOOKUP(B42,'B&L'!$A$7:$BK$69,58,0) -> 23.71 | O42: =VLOOKUP(B42,'B&L'!$A$7:$BK$69,63,0) -> 25.14
A43: 19 | B43: 工程品質管理4課 | C43: 建物 Building | D43: =VLOOKUP(B44,'B&L'!$A$7:$BK$69,7,0) -> 68.95 | E43: =VLOOKUP(B44,'B&L'!$A$7:$BK$69,12,0) -> 71.21 | F43: =VLOOKUP(B44,'B&L'!$A$7:$BK$69,17,0) -> 75.54 | G43: =VLOOKUP(B44,'B&L'!$A$7:$BK$69,22,0) -> 71.22 | H43: =VLOOKUP(B44,'B&L'!$A$7:$BK$69,27,0) -> 68.26 | I43: =VLOOKUP(B44,'B&L'!$A$7:$BK$69,32,0) -> 69.45 | J43: =VLOOKUP(B44,'B&L'!$A$7:$BK$69,37,0) -> 71.49 | K43: =VLOOKUP(B44,'B&L'!$A$7:$BK$69,42,0) -> 70.63 | L43: =VLOOKUP(B44,'B&L'!$A$7:$BK$69,47,0) -> 70.07 | M43: =VLOOKUP(B44,'B&L'!$A$7:$BK$69,52,0) -> 67.93 | N43: =VLOOKUP(B44,'B&L'!$A$7:$BK$69,57,0) -> 62.86 | O43: =VLOOKUP(B44,'B&L'!$A$7:$BK$69,62,0) -> 69.59
B44: 1412000075 | C44: 土地 Land | D44: =VLOOKUP(B44,'B&L'!$A$7:$BK$69,8,0) -> 8.74 | E44: =VLOOKUP(B44,'B&L'!$A$7:$BK$69,13,0) -> 9.28 | F44: =VLOOKUP(B44,'B&L'!$A$7:$BK$69,18,0) -> 9.84 | G44: =VLOOKUP(B44,'B&L'!$A$7:$BK$69,23,0) -> 9.28 | H44: =VLOOKUP(B44,'B&L'!$A$7:$BK$69,28,0) -> 8.89 | I44: =VLOOKUP(B44,'B&L'!$A$7:$BK$69,33,0) -> 9.05 | J44: =VLOOKUP(B44,'B&L'!$A$7:$BK$69,38,0) -> 9.32 | K44: =VLOOKUP(B44,'B&L'!$A$7:$BK$69,43,0) -> 9.2 | L44: =VLOOKUP(B44,'B&L'!$A$7:$BK$69,48,0) -> 9.13 | M44: =VLOOKUP(B44,'B&L'!$A$7:$BK$69,53,0) -> 8.85 | N44: =VLOOKUP(B44,'B&L'!$A$7:$BK$69,58,0) -> 8.19 | O44: =VLOOKUP(B44,'B&L'!$A$7:$BK$69,63,0) -> 9.07
A45: 20 | B45: 生産管理課 | C45: 建物 Building | D45: =VLOOKUP(B46,'B&L'!$A$7:$BK$69,7,0) -> 53.04 | E45: =VLOOKUP(B46,'B&L'!$A$7:$BK$69,12,0) -> 50.87 | F45: =VLOOKUP(B46,'B&L'!$A$7:$BK$69,17,0) -> 53.96 | G45: =VLOOKUP(B46,'B&L'!$A$7:$BK$69,22,0) -> 50.87 | H45: =VLOOKUP(B46,'B&L'!$A$7:$BK$69,27,0) -> 48.76 | I45: =VLOOKUP(B46,'B&L'!$A$7:$BK$69,32,0) -> 49.61 | J45: =VLOOKUP(B46,'B&L'!$A$7:$BK$69,37,0) -> 51.06 | K45: =VLOOKUP(B46,'B&L'!$A$7:$BK$69,42,0) -> 50.45 | L45: =VLOOKUP(B46,'B&L'!$A$7:$BK$69,47,0) -> 50.05 | M45: =VLOOKUP(B46,'B&L'!$A$7:$BK$69,52,0) -> 48.52 | N45: =VLOOKUP(B46,'B&L'!$A$7:$BK$69,57,0) -> 44.9 | O45: =VLOOKUP(B46,'B&L'!$A$7:$BK$69,62,0) -> 49.71
B46: 1412000008 | C46: 土地 Land | D46: =VLOOKUP(B46,'B&L'!$A$7:$BK$69,8,0) -> 6.72 | E46: =VLOOKUP(B46,'B&L'!$A$7:$BK$69,13,0) -> 6.63 | F46: =VLOOKUP(B46,'B&L'!$A$7:$BK$69,18,0) -> 7.03 | G46: =VLOOKUP(B46,'B&L'!$A$7:$BK$69,23,0) -> 6.63 | H46: =VLOOKUP(B46,'B&L'!$A$7:$BK$69,28,0) -> 6.35 | I46: =VLOOKUP(B46,'B&L'!$A$7:$BK$69,33,0) -> 6.46 | J46: =VLOOKUP(B46,'B&L'!$A$7:$BK$69,38,0) -> 6.65 | K46: =VLOOKUP(B46,'B&L'!$A$7:$BK$69,43,0) -> 6.57 | L46: =VLOOKUP(B46,'B&L'!$A$7:$BK$69,48,0) -> 6.52 | M46: =VLOOKUP(B46,'B&L'!$A$7:$BK$69,53,0) -> 6.32 | N46: =VLOOKUP(B46,'B&L'!$A$7:$BK$69,58,0) -> 5.85 | O46: =VLOOKUP(B46,'B&L'!$A$7:$BK$69,63,0) -> 6.48
A47: 21 | B47: 採算管理課 | C47: 建物 Building | D47: =VLOOKUP(B48,'B&L'!$A$7:$BK$69,7,0) -> 31.82 | E47: =VLOOKUP(B48,'B&L'!$A$7:$BK$69,12,0) -> 30.52 | F47: =VLOOKUP(B48,'B&L'!$A$7:$BK$69,17,0) -> 32.38 | G47: =VLOOKUP(B48,'B&L'!$A$7:$BK$69,22,0) -> 30.52 | H47: =VLOOKUP(B48,'B&L'!$A$7:$BK$69,27,0) -> 29.25 | I47: =VLOOKUP(B48,'B&L'!$A$7:$BK$69,32,0) -> 29.77 | J47: =VLOOKUP(B48,'B&L'!$A$7:$BK$69,37,0) -> 30.64 | K47: =VLOOKUP(B48,'B&L'!$A$7:$BK$69,42,0) -> 30.27 | L47: =VLOOKUP(B48,'B&L'!$A$7:$BK$69,47,0) -> 30.03 | M47: =VLOOKUP(B48,'B&L'!$A$7:$BK$69,52,0) -> 29.11 | N47: =VLOOKUP(B48,'B&L'!$A$7:$BK$69,57,0) -> 26.94 | O47: =VLOOKUP(B48,'B&L'!$A$7:$BK$69,62,0) -> 29.82
B48: 1412000010 | C48: 土地 Land | D48: =VLOOKUP(B48,'B&L'!$A$7:$BK$69,8,0) -> 4.03 | E48: =VLOOKUP(B48,'B&L'!$A$7:$BK$69,13,0) -> 3.98 | F48: =VLOOKUP(B48,'B&L'!$A$7:$BK$69,18,0) -> 4.22 | G48: =VLOOKUP(B48,'B&L'!$A$7:$BK$69,23,0) -> 3.98 | H48: =VLOOKUP(B48,'B&L'!$A$7:$BK$69,28,0) -> 3.81 | I48: =VLOOKUP(B48,'B&L'!$A$7:$BK$69,33,0) -> 3.88 | J48: =VLOOKUP(B48,'B&L'!$A$7:$BK$69,38,0) -> 3.99 | K48: =VLOOKUP(B48,'B&L'!$A$7:$BK$69,43,0) -> 3.94 | L48: =VLOOKUP(B48,'B&L'!$A$7:$BK$69,48,0) -> 3.91 | M48: =VLOOKUP(B48,'B&L'!$A$7:$BK$69,53,0) -> 3.79 | N48: =VLOOKUP(B48,'B&L'!$A$7:$BK$69,58,0) -> 3.51 | O48: =VLOOKUP(B48,'B&L'!$A$7:$BK$69,63,0) -> 3.89
A49: 22 | B49: OC課 | C49: 建物 Building | D49: =VLOOKUP(B50,'B&L'!$A$7:$BK$69,7,0) -> 26.52 | E49: =VLOOKUP(B50,'B&L'!$A$7:$BK$69,12,0) -> 25.43 | F49: =VLOOKUP(B50,'B&L'!$A$7:$BK$69,17,0) -> 26.98 | G49: =VLOOKUP(B50,'B&L'!$A$7:$BK$69,22,0) -> 25.44 | H49: =VLOOKUP(B50,'B&L'!$A$7:$BK$69,27,0) -> 24.38 | I49: =VLOOKUP(B50,'B&L'!$A$7:$BK$69,32,0) -> 24.8 | J49: =VLOOKUP(B50,'B&L'!$A$7:$BK$69,37,0) -> 25.53 | K49: =VLOOKUP(B50,'B&L'!$A$7:$BK$69,42,0) -> 25.22 | L49: =VLOOKUP(B50,'B&L'!$A$7:$BK$69,47,0) -> 25.03 | M49: =VLOOKUP(B50,'B&L'!$A$7:$BK$69,52,0) -> 24.26 | N49: =VLOOKUP(B50,'B&L'!$A$7:$BK$69,57,0) -> 22.45 | O49: =VLOOKUP(B50,'B&L'!$A$7:$BK$69,62,0) -> 24.85
B50: 1412000094 | C50: 土地 Land | D50: =VLOOKUP(B50,'B&L'!$A$7:$BK$69,8,0) -> 3.36 | E50: =VLOOKUP(B50,'B&L'!$A$7:$BK$69,13,0) -> 3.31 | F50: =VLOOKUP(B50,'B&L'!$A$7:$BK$69,18,0) -> 3.52 | G50: =VLOOKUP(B50,'B&L'!$A$7:$BK$69,23,0) -> 3.31 | H50: =VLOOKUP(B50,'B&L'!$A$7:$BK$69,28,0) -> 3.18 | I50: =VLOOKUP(B50,'B&L'!$A$7:$BK$69,33,0) -> 3.23 | J50: =VLOOKUP(B50,'B&L'!$A$7:$BK$69,38,0) -> 3.33 | K50: =VLOOKUP(B50,'B&L'!$A$7:$BK$69,43,0) -> 3.29 | L50: =VLOOKUP(B50,'B&L'!$A$7:$BK$69,48,0) -> 3.26 | M50: =VLOOKUP(B50,'B&L'!$A$7:$BK$69,53,0) -> 3.16 | N50: =VLOOKUP(B50,'B&L'!$A$7:$BK$69,58,0) -> 2.93 | O50: =VLOOKUP(B50,'B&L'!$A$7:$BK$69,63,0) -> 3.24
A51: 23 | B51: マスター管理課 | C51: 建物 Building | D51: =VLOOKUP(B52,'B&L'!$A$7:$BK$69,7,0) -> 74.25 | E51: =VLOOKUP(B52,'B&L'!$A$7:$BK$69,12,0) -> 71.21 | F51: =VLOOKUP(B52,'B&L'!$A$7:$BK$69,17,0) -> 75.54 | G51: =VLOOKUP(B52,'B&L'!$A$7:$BK$69,22,0) -> 71.22 | H51: =VLOOKUP(B52,'B&L'!$A$7:$BK$69,27,0) -> 68.26 | I51: =VLOOKUP(B52,'B&L'!$A$7:$BK$69,32,0) -> 69.45 | J51: =VLOOKUP(B52,'B&L'!$A$7:$BK$69,37,0) -> 71.49 | K51: =VLOOKUP(B52,'B&L'!$A$7:$BK$69,42,0) -> 70.63 | L51: =VLOOKUP(B52,'B&L'!$A$7:$BK$69,47,0) -> 70.07 | M51: =VLOOKUP(B52,'B&L'!$A$7:$BK$69,52,0) -> 67.93 | N51: =VLOOKUP(B52,'B&L'!$A$7:$BK$69,57,0) -> 62.86 | O51: =VLOOKUP(B52,'B&L'!$A$7:$BK$69,62,0) -> 69.59
B52: 1412000054 | C52: 土地 Land | D52: =VLOOKUP(B52,'B&L'!$A$7:$BK$69,8,0) -> 9.41 | E52: =VLOOKUP(B52,'B&L'!$A$7:$BK$69,13,0) -> 9.28 | F52: =VLOOKUP(B52,'B&L'!$A$7:$BK$69,18,0) -> 9.84 | G52: =VLOOKUP(B52,'B&L'!$A$7:$BK$69,23,0) -> 9.28 | H52: =VLOOKUP(B52,'B&L'!$A$7:$BK$69,28,0) -> 8.89 | I52: =VLOOKUP(B52,'B&L'!$A$7:$BK$69,33,0) -> 9.05 | J52: =VLOOKUP(B52,'B&L'!$A$7:$BK$69,38,0) -> 9.32 | K52: =VLOOKUP(B52,'B&L'!$A$7:$BK$69,43,0) -> 9.2 | L52: =VLOOKUP(B52,'B&L'!$A$7:$BK$69,48,0) -> 9.13 | M52: =VLOOKUP(B52,'B&L'!$A$7:$BK$69,53,0) -> 8.85 | N52: =VLOOKUP(B52,'B&L'!$A$7:$BK$69,58,0) -> 8.19 | O52: =VLOOKUP(B52,'B&L'!$A$7:$BK$69,63,0) -> 9.07
A53: 24 | B53: 部品管理1課 | C53: 建物 Building | D53: =VLOOKUP(B54,'B&L'!$A$7:$BK$69,7,0) -> 19702.13 | E53: =VLOOKUP(B54,'B&L'!$A$7:$BK$69,12,0) -> 18598.56 | F53: =VLOOKUP(B54,'B&L'!$A$7:$BK$69,17,0) -> 18617.2 | G53: =VLOOKUP(B54,'B&L'!$A$7:$BK$69,22,0) -> 18596.28 | H53: =VLOOKUP(B54,'B&L'!$A$7:$BK$69,27,0) -> 18561.66 | I53: =VLOOKUP(B54,'B&L'!$A$7:$BK$69,32,0) -> 18561.23 | J53: =VLOOKUP(B54,'B&L'!$A$7:$BK$69,37,0) -> 18575.9 | K53: =VLOOKUP(B54,'B&L'!$A$7:$BK$69,42,0) -> 18565.65 | L53: =VLOOKUP(B54,'B&L'!$A$7:$BK$69,47,0) -> 18563.91 | M53: =VLOOKUP(B54,'B&L'!$A$7:$BK$69,52,0) -> 18554.57 | N53: =VLOOKUP(B54,'B&L'!$A$7:$BK$69,57,0) -> 18511.6 | O53: =VLOOKUP(B54,'B&L'!$A$7:$BK$69,62,0) -> 18565
B54: 1412000036 | C54: 土地 Land | D54: =VLOOKUP(B54,'B&L'!$A$7:$BK$69,8,0) -> 2498.03 | E54: =VLOOKUP(B54,'B&L'!$A$7:$BK$69,13,0) -> 2423.54 | F54: =VLOOKUP(B54,'B&L'!$A$7:$BK$69,18,0) -> 2425.97 | G54: =VLOOKUP(B54,'B&L'!$A$7:$BK$69,23,0) -> 2423.24 | H54: =VLOOKUP(B54,'B&L'!$A$7:$BK$69,28,0) -> 2418.73 | I54: =VLOOKUP(B54,'B&L'!$A$7:$BK$69,33,0) -> 2418.67 | J54: =VLOOKUP(B54,'B&L'!$A$7:$BK$69,38,0) -> 2420.59 | K54: =VLOOKUP(B54,'B&L'!$A$7:$BK$69,43,0) -> 2419.25 | L54: =VLOOKUP(B54,'B&L'!$A$7:$BK$69,48,0) -> 2419.02 | M54: =VLOOKUP(B54,'B&L'!$A$7:$BK$69,53,0) -> 2417.81 | N54: =VLOOKUP(B54,'B&L'!$A$7:$BK$69,58,0) -> 2412.21 | O54: =VLOOKUP(B54,'B&L'!$A$7:$BK$69,63,0) -> 2419.16
A55: 25 | B55: 部品管理2課 | C55: 建物 Building | D55: =VLOOKUP(B56,'B&L'!$A$7:$BK$69,7,0) -> 33043.47 | E55: =VLOOKUP(B56,'B&L'!$A$7:$BK$69,12,0) -> 31190.07 | F55: =VLOOKUP(B56,'B&L'!$A$7:$BK$69,17,0) -> 31227.53 | G55: =VLOOKUP(B56,'B&L'!$A$7:$BK$69,22,0) -> 31185.51 | H55: =VLOOKUP(B56,'B&L'!$A$7:$BK$69,27,0) -> 31146.59 | I55: =VLOOKUP(B56,'B&L'!$A$7:$BK$69,32,0) -> 31141.58 | J55: =VLOOKUP(B56,'B&L'!$A$7:$BK$69,37,0) -> 31178.34 | K55: =VLOOKUP(B56,'B&L'!$A$7:$BK$69,42,0) -> 31152.35 | L55: =VLOOKUP(B56,'B&L'!$A$7:$BK$69,47,0) -> 31145.92 | M55: =VLOOKUP(B56,'B&L'!$A$7:$BK$69,52,0) -> 31122.31 | N55: =VLOOKUP(B56,'B&L'!$A$7:$BK$69,57,0) -> 31024.98 | O55: =VLOOKUP(B56,'B&L'!$A$7:$BK$69,62,0) -> 31149.06
B56: 1412000103 | C56: 土地 Land | D56: =VLOOKUP(B56,'B&L'!$A$7:$BK$69,8,0) -> 4189.58 | E56: =VLOOKUP(B56,'B&L'!$A$7:$BK$69,13,0) -> 4064.31 | F56: =VLOOKUP(B56,'B&L'!$A$7:$BK$69,18,0) -> 4069.19 | G56: =VLOOKUP(B56,'B&L'!$A$7:$BK$69,23,0) -> 4063.72 | H56: =VLOOKUP(B56,'B&L'!$A$7:$BK$69,28,0) -> 4058.64 | I56: =VLOOKUP(B56,'B&L'!$A$7:$BK$69,33,0) -> 4057.99 | J56: =VLOOKUP(B56,'B&L'!$A$7:$BK$69,38,0) -> 4062.78 | K56: =VLOOKUP(B56,'B&L'!$A$7:$BK$69,43,0) -> 4059.4 | L56: =VLOOKUP(B56,'B&L'!$A$7:$BK$69,48,0) -> 4058.56 | M56: =VLOOKUP(B56,'B&L'!$A$7:$BK$69,53,0) -> 4055.48 | N56: =VLOOKUP(B56,'B&L'!$A$7:$BK$69,58,0) -> 4042.8 | O56: =VLOOKUP(B56,'B&L'!$A$7:$BK$69,63,0) -> 4058.97
A57: 26 | B57: 製品管理課 | C57: 建物 Building | D57: =VLOOKUP(B58,'B&L'!$A$7:$BK$69,7,0) -> 23374.47 | E57: =VLOOKUP(B58,'B&L'!$A$7:$BK$69,12,0) -> 22065.84 | F57: =VLOOKUP(B58,'B&L'!$A$7:$BK$69,17,0) -> 22075.52 | G57: =VLOOKUP(B58,'B&L'!$A$7:$BK$69,22,0) -> 22063.4 | H57: =VLOOKUP(B58,'B&L'!$A$7:$BK$69,27,0) -> 22057.06 | I57: =VLOOKUP(B58,'B&L'!$A$7:$BK$69,32,0) -> 22056.11 | J57: =VLOOKUP(B58,'B&L'!$A$7:$BK$69,37,0) -> 22064.56 | K57: =VLOOKUP(B58,'B&L'!$A$7:$BK$69,42,0) -> 22059.66 | L57: =VLOOKUP(B58,'B&L'!$A$7:$BK$69,47,0) -> 22056.19 | M57: =VLOOKUP(B58,'B&L'!$A$7:$BK$69,52,0) -> 22051.16 | N57: =VLOOKUP(B58,'B&L'!$A$7:$BK$69,57,0) -> 22030.32 | O57: =VLOOKUP(B58,'B&L'!$A$7:$BK$69,62,0) -> 22055
B58: 1412000072 | C58: 土地 Land | D58: =VLOOKUP(B58,'B&L'!$A$7:$BK$69,8,0) -> 2963.65 | E58: =VLOOKUP(B58,'B&L'!$A$7:$BK$69,13,0) -> 2875.35 | F58: =VLOOKUP(B58,'B&L'!$A$7:$BK$69,18,0) -> 2876.61 | G58: =VLOOKUP(B58,'B&L'!$A$7:$BK$69,23,0) -> 2875.03 | H58: =VLOOKUP(B58,'B&L'!$A$7:$BK$69,28,0) -> 2874.21 | I58: =VLOOKUP(B58,'B&L'!$A$7:$BK$69,33,0) -> 2874.08 | J58: =VLOOKUP(B58,'B&L'!$A$7:$BK$69,38,0) -> 2875.19 | K58: =VLOOKUP(B58,'B&L'!$A$7:$BK$69,43,0) -> 2874.55 | L58: =VLOOKUP(B58,'B&L'!$A$7:$BK$69,48,0) -> 2874.09 | M58: =VLOOKUP(B58,'B&L'!$A$7:$BK$69,53,0) -> 2873.44 | N58: =VLOOKUP(B58,'B&L'!$A$7:$BK$69,58,0) -> 2870.72 | O58: =VLOOKUP(B58,'B&L'!$A$7:$BK$69,63,0) -> 2873.94
A59: 27 | B59: 物流管理課 | C59: 建物 Building | D59: =VLOOKUP(B60,'B&L'!$A$7:$BK$69,7,0) -> 79.55 | E59: =VLOOKUP(B60,'B&L'!$A$7:$BK$69,12,0) -> 76.3 | F59: =VLOOKUP(B60,'B&L'!$A$7:$BK$69,17,0) -> 80.94 | G59: =VLOOKUP(B60,'B&L'!$A$7:$BK$69,22,0) -> 76.31 | H59: =VLOOKUP(B60,'B&L'!$A$7:$BK$69,27,0) -> 73.13 | I59: =VLOOKUP(B60,'B&L'!$A$7:$BK$69,32,0) -> 74.41 | J59: =VLOOKUP(B60,'B&L'!$A$7:$BK$69,37,0) -> 76.59 | K59: =VLOOKUP(B60,'B&L'!$A$7:$BK$69,42,0) -> 75.67 | L59: =VLOOKUP(B60,'B&L'!$A$7:$BK$69,47,0) -> 75.08 | M59: =VLOOKUP(B60,'B&L'!$A$7:$BK$69,52,0) -> 72.78 | N59: =VLOOKUP(B60,'B&L'!$A$7:$BK$69,57,0) -> 67.34 | O59: =VLOOKUP(B60,'B&L'!$A$7:$BK$69,62,0) -> 74.56
B60: 1412000073 | C60: 土地 Land | D60: =VLOOKUP(B60,'B&L'!$A$7:$BK$69,8,0) -> 10.09 | E60: =VLOOKUP(B60,'B&L'!$A$7:$BK$69,13,0) -> 9.94 | F60: =VLOOKUP(B60,'B&L'!$A$7:$BK$69,18,0) -> 10.55 | G60: =VLOOKUP(B60,'B&L'!$A$7:$BK$69,23,0) -> 9.94 | H60: =VLOOKUP(B60,'B&L'!$A$7:$BK$69,28,0) -> 9.53 | I60: =VLOOKUP(B60,'B&L'!$A$7:$BK$69,33,0) -> 9.7 | J60: =VLOOKUP(B60,'B&L'!$A$7:$BK$69,38,0) -> 9.98 | K60: =VLOOKUP(B60,'B&L'!$A$7:$BK$69,43,0) -> 9.86 | L60: =VLOOKUP(B60,'B&L'!$A$7:$BK$69,48,0) -> 9.78 | M60: =VLOOKUP(B60,'B&L'!$A$7:$BK$69,53,0) -> 9.48 | N60: =VLOOKUP(B60,'B&L'!$A$7:$BK$69,58,0) -> 8.78 | O60: =VLOOKUP(B60,'B&L'!$A$7:$BK$69,63,0) -> 9.72
A61: 28 | B61: メカ製造技術1課 | C61: 建物 Building | D61: =VLOOKUP(B62,'B&L'!$A$7:$BK$69,7,0) -> 156.9 | E61: =VLOOKUP(B62,'B&L'!$A$7:$BK$69,12,0) -> 148.89 | F61: =VLOOKUP(B62,'B&L'!$A$7:$BK$69,17,0) -> 172.13 | G61: =VLOOKUP(B62,'B&L'!$A$7:$BK$69,22,0) -> 167.32 | H61: =VLOOKUP(B62,'B&L'!$A$7:$BK$69,27,0) -> 161.6 | I61: =VLOOKUP(B62,'B&L'!$A$7:$BK$69,32,0) -> 163.9 | J61: =VLOOKUP(B62,'B&L'!$A$7:$BK$69,37,0) -> 167.83 | K61: =VLOOKUP(B62,'B&L'!$A$7:$BK$69,42,0) -> 166.17 | L61: =VLOOKUP(B62,'B&L'!$A$7:$BK$69,47,0) -> 165.1 | M61: =VLOOKUP(B62,'B&L'!$A$7:$BK$69,52,0) -> 164.77 | N61: =VLOOKUP(B62,'B&L'!$A$7:$BK$69,57,0) -> 154.62 | O61: =VLOOKUP(B62,'B&L'!$A$7:$BK$69,62,0) -> 168.09
B62: 1412000006 | C62: 土地 Land | D62: =VLOOKUP(B62,'B&L'!$A$7:$BK$69,8,0) -> 19.89 | E62: =VLOOKUP(B62,'B&L'!$A$7:$BK$69,13,0) -> 19.4 | F62: =VLOOKUP(B62,'B&L'!$A$7:$BK$69,18,0) -> 22.43 | G62: =VLOOKUP(B62,'B&L'!$A$7:$BK$69,23,0) -> 21.8 | H62: =VLOOKUP(B62,'B&L'!$A$7:$BK$69,28,0) -> 21.06 | I62: =VLOOKUP(B62,'B&L'!$A$7:$BK$69,33,0) -> 21.36 | J62: =VLOOKUP(B62,'B&L'!$A$7:$BK$69,38,0) -> 21.87 | K62: =VLOOKUP(B62,'B&L'!$A$7:$BK$69,43,0) -> 21.65 | L62: =VLOOKUP(B62,'B&L'!$A$7:$BK$69,48,0) -> 21.51 | M62: =VLOOKUP(B62,'B&L'!$A$7:$BK$69,53,0) -> 21.47 | N62: =VLOOKUP(B62,'B&L'!$A$7:$BK$69,58,0) -> 20.15 | O62: =VLOOKUP(B62,'B&L'!$A$7:$BK$69,63,0) -> 21.9
A63: 29 | B63: メカ製造技術2課 | C63: 建物 Building | D63: =VLOOKUP(B64,'B&L'!$A$7:$BK$69,7,0) -> 133.56 | E63: =VLOOKUP(B64,'B&L'!$A$7:$BK$69,12,0) -> 126.82 | F63: =VLOOKUP(B64,'B&L'!$A$7:$BK$69,17,0) -> 139.32 | G63: =VLOOKUP(B64,'B&L'!$A$7:$BK$69,22,0) -> 130.69 | H63: =VLOOKUP(B64,'B&L'!$A$7:$BK$69,27,0) -> 125.81 | I63: =VLOOKUP(B64,'B&L'!$A$7:$BK$69,32,0) -> 127.78 | J63: =VLOOKUP(B64,'B&L'!$A$7:$BK$69,37,0) -> 131.12 | K63: =VLOOKUP(B64,'B&L'!$A$7:$BK$69,42,0) -> 129.7 | L63: =VLOOKUP(B64,'B&L'!$A$7:$BK$69,47,0) -> 128.8 | M63: =VLOOKUP(B64,'B&L'!$A$7:$BK$69,52,0) -> 124.53 | N63: =VLOOKUP(B64,'B&L'!$A$7:$BK$69,57,0) -> 116.19 | O63: =VLOOKUP(B64,'B&L'!$A$7:$BK$69,62,0) -> 127.25
B64: 1412000089 | C64: 土地 Land | D64: =VLOOKUP(B64,'B&L'!$A$7:$BK$69,8,0) -> 16.93 | E64: =VLOOKUP(B64,'B&L'!$A$7:$BK$69,13,0) -> 16.53 | F64: =VLOOKUP(B64,'B&L'!$A$7:$BK$69,18,0) -> 18.16 | G64: =VLOOKUP(B64,'B&L'!$A$7:$BK$69,23,0) -> 17.03 | H64: =VLOOKUP(B64,'B&L'!$A$7:$BK$69,28,0) -> 16.39 | I64: =VLOOKUP(B64,'B&L'!$A$7:$BK$69,33,0) -> 16.65 | J64: =VLOOKUP(B64,'B&L'!$A$7:$BK$69,38,0) -> 17.09 | K64: =VLOOKUP(B64,'B&L'!$A$7:$BK$69,43,0) -> 16.9 | L64: =VLOOKUP(B64,'B&L'!$A$7:$BK$69,48,0) -> 16.78 | M64: =VLOOKUP(B64,'B&L'!$A$7:$BK$69,53,0) -> 16.23 | N64: =VLOOKUP(B64,'B&L'!$A$7:$BK$69,58,0) -> 15.14 | O64: =VLOOKUP(B64,'B&L'!$A$7:$BK$69,63,0) -> 16.58
A65: 30 | B65: 電気製造技術課 | C65: 建物 Building | D65: =VLOOKUP(B66,'B&L'!$A$7:$BK$69,7,0) -> 188.35 | E65: =VLOOKUP(B66,'B&L'!$A$7:$BK$69,12,0) -> 178.43 | F65: =VLOOKUP(B66,'B&L'!$A$7:$BK$69,17,0) -> 180.02 | G65: =VLOOKUP(B66,'B&L'!$A$7:$BK$69,22,0) -> 178.21 | H65: =VLOOKUP(B66,'B&L'!$A$7:$BK$69,27,0) -> 174.19 | I65: =VLOOKUP(B66,'B&L'!$A$7:$BK$69,32,0) -> 175.81 | J65: =VLOOKUP(B66,'B&L'!$A$7:$BK$69,37,0) -> 178.57 | K65: =VLOOKUP(B66,'B&L'!$A$7:$BK$69,42,0) -> 177.4 | L65: =VLOOKUP(B66,'B&L'!$A$7:$BK$69,47,0) -> 176.65 | M65: =VLOOKUP(B66,'B&L'!$A$7:$BK$69,52,0) -> 173.13 | N65: =VLOOKUP(B66,'B&L'!$A$7:$BK$69,57,0) -> 166.24 | O65: =VLOOKUP(B66,'B&L'!$A$7:$BK$69,62,0) -> 175.38
B66: 1412000040 | C66: 土地 Land | D66: =VLOOKUP(B66,'B&L'!$A$7:$BK$69,8,0) -> 23.88 | E66: =VLOOKUP(B66,'B&L'!$A$7:$BK$69,13,0) -> 23.25 | F66: =VLOOKUP(B66,'B&L'!$A$7:$BK$69,18,0) -> 23.46 | G66: =VLOOKUP(B66,'B&L'!$A$7:$BK$69,23,0) -> 23.22 | H66: =VLOOKUP(B66,'B&L'!$A$7:$BK$69,28,0) -> 22.7 | I66: =VLOOKUP(B66,'B&L'!$A$7:$BK$69,33,0) -> 22.91 | J66: =VLOOKUP(B66,'B&L'!$A$7:$BK$69,38,0) -> 23.27 | K66: =VLOOKUP(B66,'B&L'!$A$7:$BK$69,43,0) -> 23.12 | L66: =VLOOKUP(B66,'B&L'!$A$7:$BK$69,48,0) -> 23.02 | M66: =VLOOKUP(B66,'B&L'!$A$7:$BK$69,53,0) -> 22.56 | N66: =VLOOKUP(B66,'B&L'!$A$7:$BK$69,58,0) -> 21.66 | O66: =VLOOKUP(B66,'B&L'!$A$7:$BK$69,63,0) -> 22.85
A67: 31 | B67: 製造システム開発課 | C67: 建物 Building | D67: =VLOOKUP(B68,'B&L'!$A$7:$BK$69,7,0) -> 78.45 | E67: =VLOOKUP(B68,'B&L'!$A$7:$BK$69,12,0) -> 74.44 | F67: =VLOOKUP(B68,'B&L'!$A$7:$BK$69,17,0) -> 75.42 | G67: =VLOOKUP(B68,'B&L'!$A$7:$BK$69,22,0) -> 71.28 | H67: =VLOOKUP(B68,'B&L'!$A$7:$BK$69,27,0) -> 68.95 | I67: =VLOOKUP(B68,'B&L'!$A$7:$BK$69,32,0) -> 69.89 | J67: =VLOOKUP(B68,'B&L'!$A$7:$BK$69,37,0) -> 71.49 | K67: =VLOOKUP(B68,'B&L'!$A$7:$BK$69,42,0) -> 70.81 | L67: =VLOOKUP(B68,'B&L'!$A$7:$BK$69,47,0) -> 70.38 | M67: =VLOOKUP(B68,'B&L'!$A$7:$BK$69,52,0) -> 68.34 | N67: =VLOOKUP(B68,'B&L'!$A$7:$BK$69,57,0) -> 64.35 | O67: =VLOOKUP(B68,'B&L'!$A$7:$BK$69,62,0) -> 69.64
B68: 1412000039 | C68: 土地 Land | D68: =VLOOKUP(B68,'B&L'!$A$7:$BK$69,8,0) -> 9.95 | E68: =VLOOKUP(B68,'B&L'!$A$7:$BK$69,13,0) -> 9.7 | F68: =VLOOKUP(B68,'B&L'!$A$7:$BK$69,18,0) -> 9.83 | G68: =VLOOKUP(B68,'B&L'!$A$7:$BK$69,23,0) -> 9.29 | H68: =VLOOKUP(B68,'B&L'!$A$7:$BK$69,28,0) -> 8.99 | I68: =VLOOKUP(B68,'B&L'!$A$7:$BK$69,33,0) -> 9.11 | J68: =VLOOKUP(B68,'B&L'!$A$7:$BK$69,38,0) -> 9.32 | K68: =VLOOKUP(B68,'B&L'!$A$7:$BK$69,43,0) -> 9.23 | L68: =VLOOKUP(B68,'B&L'!$A$7:$BK$69,48,0) -> 9.17 | M68: =VLOOKUP(B68,'B&L'!$A$7:$BK$69,53,0) -> 8.91 | N68: =VLOOKUP(B68,'B&L'!$A$7:$BK$69,58,0) -> 8.39 | O68: =VLOOKUP(B68,'B&L'!$A$7:$BK$69,63,0) -> 9.08
A69: 32 | B69: 製造技術管理課 | C69: 建物 Building | D69: =VLOOKUP(B70,'B&L'!$A$7:$BK$69,7,0) -> 56.41 | E69: =VLOOKUP(B70,'B&L'!$A$7:$BK$69,12,0) -> 63.97 | F69: =VLOOKUP(B70,'B&L'!$A$7:$BK$69,17,0) -> 64.76 | G69: =VLOOKUP(B70,'B&L'!$A$7:$BK$69,22,0) -> 61.38 | H69: =VLOOKUP(B70,'B&L'!$A$7:$BK$69,27,0) -> 59.48 | I69: =VLOOKUP(B70,'B&L'!$A$7:$BK$69,32,0) -> 60.24 | J69: =VLOOKUP(B70,'B&L'!$A$7:$BK$69,37,0) -> 61.55 | K69: =VLOOKUP(B70,'B&L'!$A$7:$BK$69,42,0) -> 61 | L69: =VLOOKUP(B70,'B&L'!$A$7:$BK$69,47,0) -> 60.64 | M69: =VLOOKUP(B70,'B&L'!$A$7:$BK$69,52,0) -> 58.97 | N69: =VLOOKUP(B70,'B&L'!$A$7:$BK$69,57,0) -> 55.71 | O69: =VLOOKUP(B70,'B&L'!$A$7:$BK$69,62,0) -> 60.04
B70: 14120000AB | C70: 土地 Land | D70: =VLOOKUP(B70,'B&L'!$A$7:$BK$69,8,0) -> 7.15 | E70: =VLOOKUP(B70,'B&L'!$A$7:$BK$69,13,0) -> 8.34 | F70: =VLOOKUP(B70,'B&L'!$A$7:$BK$69,18,0) -> 8.44 | G70: =VLOOKUP(B70,'B&L'!$A$7:$BK$69,23,0) -> 8 | H70: =VLOOKUP(B70,'B&L'!$A$7:$BK$69,28,0) -> 7.75 | I70: =VLOOKUP(B70,'B&L'!$A$7:$BK$69,33,0) -> 7.85 | J70: =VLOOKUP(B70,'B&L'!$A$7:$BK$69,38,0) -> 8.02 | K70: =VLOOKUP(B70,'B&L'!$A$7:$BK$69,43,0) -> 7.95 | L70: =VLOOKUP(B70,'B&L'!$A$7:$BK$69,48,0) -> 7.9 | M70: =VLOOKUP(B70,'B&L'!$A$7:$BK$69,53,0) -> 7.68 | N70: =VLOOKUP(B70,'B&L'!$A$7:$BK$69,58,0) -> 7.26 | O70: =VLOOKUP(B70,'B&L'!$A$7:$BK$69,63,0) -> 7.82
A71: 33 | B71: 部品検査課 1 | C71: 建物 Building | D71: =VLOOKUP(B72,'B&L'!$A$7:$BK$69,7,0) -> 914.97 | E71: =VLOOKUP(B72,'B&L'!$A$7:$BK$69,12,0) -> 863.38 | F71: =VLOOKUP(B72,'B&L'!$A$7:$BK$69,17,0) -> 880.26 | G71: =VLOOKUP(B72,'B&L'!$A$7:$BK$69,22,0) -> 876.27 | H71: =VLOOKUP(B72,'B&L'!$A$7:$BK$69,27,0) -> 858.68 | I71: =VLOOKUP(B72,'B&L'!$A$7:$BK$69,32,0) -> 860.53 | J71: =VLOOKUP(B72,'B&L'!$A$7:$BK$69,37,0) -> 878.87 | K71: =VLOOKUP(B72,'B&L'!$A$7:$BK$69,42,0) -> 867.75 | L71: =VLOOKUP(B72,'B&L'!$A$7:$BK$69,47,0) -> 865.96 | M71: =VLOOKUP(B72,'B&L'!$A$7:$BK$69,52,0) -> 856.16 | N71: =VLOOKUP(B72,'B&L'!$A$7:$BK$69,57,0) -> 809.91 | O71: =VLOOKUP(B72,'B&L'!$A$7:$BK$69,62,0) -> 870.01
B72: 1412000013 | C72: 土地 Land | D72: =VLOOKUP(B72,'B&L'!$A$7:$BK$69,8,0) -> 116.01 | E72: =VLOOKUP(B72,'B&L'!$A$7:$BK$69,13,0) -> 112.51 | F72: =VLOOKUP(B72,'B&L'!$A$7:$BK$69,18,0) -> 114.7 | G72: =VLOOKUP(B72,'B&L'!$A$7:$BK$69,23,0) -> 114.19 | H72: =VLOOKUP(B72,'B&L'!$A$7:$BK$69,28,0) -> 111.89 | I72: =VLOOKUP(B72,'B&L'!$A$7:$BK$69,33,0) -> 112.13 | J72: =VLOOKUP(B72,'B&L'!$A$7:$BK$69,38,0) -> 114.52 | K72: =VLOOKUP(B72,'B&L'!$A$7:$BK$69,43,0) -> 113.07 | L72: =VLOOKUP(B72,'B&L'!$A$7:$BK$69,48,0) -> 112.84 | M72: =VLOOKUP(B72,'B&L'!$A$7:$BK$69,53,0) -> 111.56 | N72: =VLOOKUP(B72,'B&L'!$A$7:$BK$69,58,0) -> 105.54 | O72: =VLOOKUP(B72,'B&L'!$A$7:$BK$69,63,0) -> 113.37
A73: 34 | B73: 部品検査課 2 | C73: 建物 Building | D73: =VLOOKUP(B74,'B&L'!$A$7:$BK$69,7,0) -> 658.33 | E73: =VLOOKUP(B74,'B&L'!$A$7:$BK$69,12,0) -> 621.31 | F73: =VLOOKUP(B74,'B&L'!$A$7:$BK$69,17,0) -> 629 | G73: =VLOOKUP(B74,'B&L'!$A$7:$BK$69,22,0) -> 626.48 | H73: =VLOOKUP(B74,'B&L'!$A$7:$BK$69,27,0) -> 618.51 | I73: =VLOOKUP(B74,'B&L'!$A$7:$BK$69,32,0) -> 619.35 | J73: =VLOOKUP(B74,'B&L'!$A$7:$BK$69,37,0) -> 627.66 | K73: =VLOOKUP(B74,'B&L'!$A$7:$BK$69,42,0) -> 622.62 | L73: =VLOOKUP(B74,'B&L'!$A$7:$BK$69,47,0) -> 621.81 | M73: =VLOOKUP(B74,'B&L'!$A$7:$BK$69,52,0) -> 617.37 | N73: =VLOOKUP(B74,'B&L'!$A$7:$BK$69,57,0) -> 596.43 | O73: =VLOOKUP(B74,'B&L'!$A$7:$BK$69,62,0) -> 623.64
B74: 1412000092 | C74: 土地 Land | D74: =VLOOKUP(B74,'B&L'!$A$7:$BK$69,8,0) -> 83.47 | E74: =VLOOKUP(B74,'B&L'!$A$7:$BK$69,13,0) -> 80.96 | F74: =VLOOKUP(B74,'B&L'!$A$7:$BK$69,18,0) -> 81.96 | G74: =VLOOKUP(B74,'B&L'!$A$7:$BK$69,23,0) -> 81.63 | H74: =VLOOKUP(B74,'B&L'!$A$7:$BK$69,28,0) -> 80.6 | I74: =VLOOKUP(B74,'B&L'!$A$7:$BK$69,33,0) -> 80.71 | J74: =VLOOKUP(B74,'B&L'!$A$7:$BK$69,38,0) -> 81.79 | K74: =VLOOKUP(B74,'B&L'!$A$7:$BK$69,43,0) -> 81.13 | L74: =VLOOKUP(B74,'B&L'!$A$7:$BK$69,48,0) -> 81.03 | M74: =VLOOKUP(B74,'B&L'!$A$7:$BK$69,53,0) -> 80.45 | N74: =VLOOKUP(B74,'B&L'!$A$7:$BK$69,58,0) -> 77.72 | O74: =VLOOKUP(B74,'B&L'!$A$7:$BK$69,63,0) -> 81.27
A75: 35 | B75: 外製管理課 | C75: 建物 Building | D75: =VLOOKUP(B76,'B&L'!$A$7:$BK$69,7,0) -> 313.67 | E75: =VLOOKUP(B76,'B&L'!$A$7:$BK$69,12,0) -> 303.2 | F75: =VLOOKUP(B76,'B&L'!$A$7:$BK$69,17,0) -> 311.86 | G75: =VLOOKUP(B76,'B&L'!$A$7:$BK$69,22,0) -> 303.22 | H75: =VLOOKUP(B76,'B&L'!$A$7:$BK$69,27,0) -> 297.29 | I75: =VLOOKUP(B76,'B&L'!$A$7:$BK$69,32,0) -> 299.68 | J75: =VLOOKUP(B76,'B&L'!$A$7:$BK$69,37,0) -> 303.75 | K75: =VLOOKUP(B76,'B&L'!$A$7:$BK$69,42,0) -> 302.03 | L75: =VLOOKUP(B76,'B&L'!$A$7:$BK$69,47,0) -> 300.92 | M75: =VLOOKUP(B76,'B&L'!$A$7:$BK$69,52,0) -> 296.63 | N75: =VLOOKUP(B76,'B&L'!$A$7:$BK$69,57,0) -> 286.48 | O75: =VLOOKUP(B76,'B&L'!$A$7:$BK$69,62,0) -> 299.95
B76: 1412000035 | C76: 土地 Land | D76: =VLOOKUP(B76,'B&L'!$A$7:$BK$69,8,0) -> 39.77 | E76: =VLOOKUP(B76,'B&L'!$A$7:$BK$69,13,0) -> 39.51 | F76: =VLOOKUP(B76,'B&L'!$A$7:$BK$69,18,0) -> 40.64 | G76: =VLOOKUP(B76,'B&L'!$A$7:$BK$69,23,0) -> 39.51 | H76: =VLOOKUP(B76,'B&L'!$A$7:$BK$69,28,0) -> 38.74 | I76: =VLOOKUP(B76,'B&L'!$A$7:$BK$69,33,0) -> 39.05 | J76: =VLOOKUP(B76,'B&L'!$A$7:$BK$69,38,0) -> 39.58 | K76: =VLOOKUP(B76,'B&L'!$A$7:$BK$69,43,0) -> 39.36 | L76: =VLOOKUP(B76,'B&L'!$A$7:$BK$69,48,0) -> 39.21 | M76: =VLOOKUP(B76,'B&L'!$A$7:$BK$69,53,0) -> 38.65 | N76: =VLOOKUP(B76,'B&L'!$A$7:$BK$69,58,0) -> 37.33 | O76: =VLOOKUP(B76,'B&L'!$A$7:$BK$69,63,0) -> 39.09
A77: 36 | B77: 生産技術1課 | C77: 建物 Building | D77: =VLOOKUP(B78,'B&L'!$A$7:$BK$69,7,0) -> 313.02 | E77: =VLOOKUP(B78,'B&L'!$A$7:$BK$69,12,0) -> 301.47 | F77: =VLOOKUP(B78,'B&L'!$A$7:$BK$69,17,0) -> 301.73 | G77: =VLOOKUP(B78,'B&L'!$A$7:$BK$69,22,0) -> 298.2 | H77: =VLOOKUP(B78,'B&L'!$A$7:$BK$69,27,0) -> 297.8 | I77: =VLOOKUP(B78,'B&L'!$A$7:$BK$69,32,0) -> 297.86 | J77: =VLOOKUP(B78,'B&L'!$A$7:$BK$69,37,0) -> 298.03 | K77: =VLOOKUP(B78,'B&L'!$A$7:$BK$69,42,0) -> 297.95 | L77: =VLOOKUP(B78,'B&L'!$A$7:$BK$69,47,0) -> 297.82 | M77: =VLOOKUP(B78,'B&L'!$A$7:$BK$69,52,0) -> 297.68 | N77: =VLOOKUP(B78,'B&L'!$A$7:$BK$69,57,0) -> 297.21 | O77: =VLOOKUP(B78,'B&L'!$A$7:$BK$69,62,0) -> 297.81
B78: 1412000016 | C78: 土地 Land | D78: =VLOOKUP(B78,'B&L'!$A$7:$BK$69,8,0) -> 39.69 | E78: =VLOOKUP(B78,'B&L'!$A$7:$BK$69,13,0) -> 39.28 | F78: =VLOOKUP(B78,'B&L'!$A$7:$BK$69,18,0) -> 39.32 | G78: =VLOOKUP(B78,'B&L'!$A$7:$BK$69,23,0) -> 38.86 | H78: =VLOOKUP(B78,'B&L'!$A$7:$BK$69,28,0) -> 38.81 | I78: =VLOOKUP(B78,'B&L'!$A$7:$BK$69,33,0) -> 38.81 | J78: =VLOOKUP(B78,'B&L'!$A$7:$BK$69,38,0) -> 38.84 | K78: =VLOOKUP(B78,'B&L'!$A$7:$BK$69,43,0) -> 38.82 | L78: =VLOOKUP(B78,'B&L'!$A$7:$BK$69,48,0) -> 38.81 | M78: =VLOOKUP(B78,'B&L'!$A$7:$BK$69,53,0) -> 38.79 | N78: =VLOOKUP(B78,'B&L'!$A$7:$BK$69,58,0) -> 38.73 | O78: =VLOOKUP(B78,'B&L'!$A$7:$BK$69,63,0) -> 38.81
A79: 37 | B79: 生産技術2課 | C79: 建物 Building | D79: =VLOOKUP(B80,'B&L'!$A$7:$BK$69,7,0) -> 218.24 | E79: =VLOOKUP(B80,'B&L'!$A$7:$BK$69,12,0) -> 214.27 | F79: =VLOOKUP(B80,'B&L'!$A$7:$BK$69,17,0) -> 214.44 | G79: =VLOOKUP(B80,'B&L'!$A$7:$BK$69,22,0) -> 212.09 | H79: =VLOOKUP(B80,'B&L'!$A$7:$BK$69,27,0) -> 211.82 | I79: =VLOOKUP(B80,'B&L'!$A$7:$BK$69,32,0) -> 211.86 | J79: =VLOOKUP(B80,'B&L'!$A$7:$BK$69,37,0) -> 211.98 | K79: =VLOOKUP(B80,'B&L'!$A$7:$BK$69,42,0) -> 211.92 | L79: =VLOOKUP(B80,'B&L'!$A$7:$BK$69,47,0) -> 211.84 | M79: =VLOOKUP(B80,'B&L'!$A$7:$BK$69,52,0) -> 211.74 | N79: =VLOOKUP(B80,'B&L'!$A$7:$BK$69,57,0) -> 211.43 | O79: =VLOOKUP(B80,'B&L'!$A$7:$BK$69,62,0) -> 211.83
B80: 1412000069 | C80: 土地 Land | D80: =VLOOKUP(B80,'B&L'!$A$7:$BK$69,8,0) -> 27.67 | E80: =VLOOKUP(B80,'B&L'!$A$7:$BK$69,13,0) -> 27.92 | F80: =VLOOKUP(B80,'B&L'!$A$7:$BK$69,18,0) -> 27.94 | G80: =VLOOKUP(B80,'B&L'!$A$7:$BK$69,23,0) -> 27.64 | H80: =VLOOKUP(B80,'B&L'!$A$7:$BK$69,28,0) -> 27.6 | I80: =VLOOKUP(B80,'B&L'!$A$7:$BK$69,33,0) -> 27.61 | J80: =VLOOKUP(B80,'B&L'!$A$7:$BK$69,38,0) -> 27.62 | K80: =VLOOKUP(B80,'B&L'!$A$7:$BK$69,43,0) -> 27.61 | L80: =VLOOKUP(B80,'B&L'!$A$7:$BK$69,48,0) -> 27.6 | M80: =VLOOKUP(B80,'B&L'!$A$7:$BK$69,53,0) -> 27.59 | N80: =VLOOKUP(B80,'B&L'!$A$7:$BK$69,58,0) -> 27.55 | O80: =VLOOKUP(B80,'B&L'!$A$7:$BK$69,63,0) -> 27.6
A81: 38 | B81: 生産技術3課 | C81: 建物 Building | D81: =VLOOKUP(B82,'B&L'!$A$7:$BK$69,7,0) -> 326.56 | E81: =VLOOKUP(B82,'B&L'!$A$7:$BK$69,12,0) -> 301.47 | F81: =VLOOKUP(B82,'B&L'!$A$7:$BK$69,17,0) -> 301.73 | G81: =VLOOKUP(B82,'B&L'!$A$7:$BK$69,22,0) -> 310.5 | H81: =VLOOKUP(B82,'B&L'!$A$7:$BK$69,27,0) -> 310.08 | I81: =VLOOKUP(B82,'B&L'!$A$7:$BK$69,32,0) -> 310.15 | J81: =VLOOKUP(B82,'B&L'!$A$7:$BK$69,37,0) -> 310.33 | K81: =VLOOKUP(B82,'B&L'!$A$7:$BK$69,42,0) -> 310.24 | L81: =VLOOKUP(B82,'B&L'!$A$7:$BK$69,47,0) -> 310.11 | M81: =VLOOKUP(B82,'B&L'!$A$7:$BK$69,52,0) -> 309.95 | N81: =VLOOKUP(B82,'B&L'!$A$7:$BK$69,57,0) -> 309.47 | O81: =VLOOKUP(B82,'B&L'!$A$7:$BK$69,62,0) -> 310.1
B82: 1412000084 | C82: 土地 Land | D82: =VLOOKUP(B82,'B&L'!$A$7:$BK$69,8,0) -> 41.4 | E82: =VLOOKUP(B82,'B&L'!$A$7:$BK$69,13,0) -> 39.28 | F82: =VLOOKUP(B82,'B&L'!$A$7:$BK$69,18,0) -> 39.32 | G82: =VLOOKUP(B82,'B&L'!$A$7:$BK$69,23,0) -> 40.46 | H82: =VLOOKUP(B82,'B&L'!$A$7:$BK$69,28,0) -> 40.41 | I82: =VLOOKUP(B82,'B&L'!$A$7:$BK$69,33,0) -> 40.41 | J82: =VLOOKUP(B82,'B&L'!$A$7:$BK$69,38,0) -> 40.44 | K82: =VLOOKUP(B82,'B&L'!$A$7:$BK$69,43,0) -> 40.43 | L82: =VLOOKUP(B82,'B&L'!$A$7:$BK$69,48,0) -> 40.41 | M82: =VLOOKUP(B82,'B&L'!$A$7:$BK$69,53,0) -> 40.39 | N82: =VLOOKUP(B82,'B&L'!$A$7:$BK$69,58,0) -> 40.33 | O82: =VLOOKUP(B82,'B&L'!$A$7:$BK$69,63,0) -> 40.41
A83: 39 | B83: MD1課 | C83: 建物 Building | D83: =VLOOKUP(B84,'B&L'!$A$7:$BK$69,7,0) -> 158.25 | E83: =VLOOKUP(B84,'B&L'!$A$7:$BK$69,12,0) -> 149.44 | F83: =VLOOKUP(B84,'B&L'!$A$7:$BK$69,17,0) -> 148.9 | G83: =VLOOKUP(B84,'B&L'!$A$7:$BK$69,22,0) -> 147.65 | H83: =VLOOKUP(B84,'B&L'!$A$7:$BK$69,27,0) -> 147.5 | I83: =VLOOKUP(B84,'B&L'!$A$7:$BK$69,32,0) -> 165.4 | J83: =VLOOKUP(B84,'B&L'!$A$7:$BK$69,37,0) -> 159.22 | K83: =VLOOKUP(B84,'B&L'!$A$7:$BK$69,42,0) -> 159.15 | L83: =VLOOKUP(B84,'B&L'!$A$7:$BK$69,47,0) -> 159.38 | M83: =VLOOKUP(B84,'B&L'!$A$7:$BK$69,52,0) -> 159.26 | N83: =VLOOKUP(B84,'B&L'!$A$7:$BK$69,57,0) -> 156.79 | O83: =VLOOKUP(B84,'B&L'!$A$7:$BK$69,62,0) -> 159.37
B84: 1412000050 | C84: 土地 Land | D84: =VLOOKUP(B84,'B&L'!$A$7:$BK$69,8,0) -> 20.06 | E84: =VLOOKUP(B84,'B&L'!$A$7:$BK$69,13,0) -> 19.47 | F84: =VLOOKUP(B84,'B&L'!$A$7:$BK$69,18,0) -> 19.4 | G84: =VLOOKUP(B84,'B&L'!$A$7:$BK$69,23,0) -> 19.24 | H84: =VLOOKUP(B84,'B&L'!$A$7:$BK$69,28,0) -> 19.22 | I84: =VLOOKUP(B84,'B&L'!$A$7:$BK$69,33,0) -> 21.55 | J84: =VLOOKUP(B84,'B&L'!$A$7:$BK$69,38,0) -> 20.75 | K84: =VLOOKUP(B84,'B&L'!$A$7:$BK$69,43,0) -> 20.74 | L84: =VLOOKUP(B84,'B&L'!$A$7:$BK$69,48,0) -> 20.77 | M84: =VLOOKUP(B84,'B&L'!$A$7:$BK$69,53,0) -> 20.75 | N84: =VLOOKUP(B84,'B&L'!$A$7:$BK$69,58,0) -> 20.43 | O84: =VLOOKUP(B84,'B&L'!$A$7:$BK$69,63,0) -> 20.77
A85: 40 | B85: MD2課 | C85: 建物 Building | D85: =VLOOKUP(B86,'B&L'!$A$7:$BK$69,7,0) -> 116.05 | E85: =VLOOKUP(B86,'B&L'!$A$7:$BK$69,12,0) -> 109.59 | F85: =VLOOKUP(B86,'B&L'!$A$7:$BK$69,17,0) -> 109.2 | G85: =VLOOKUP(B86,'B&L'!$A$7:$BK$69,22,0) -> 108.28 | H85: =VLOOKUP(B86,'B&L'!$A$7:$BK$69,27,0) -> 108.17 | I85: =VLOOKUP(B86,'B&L'!$A$7:$BK$69,32,0) -> 101.08 | J85: =VLOOKUP(B86,'B&L'!$A$7:$BK$69,37,0) -> 103.03 | K85: =VLOOKUP(B86,'B&L'!$A$7:$BK$69,42,0) -> 102.98 | L85: =VLOOKUP(B86,'B&L'!$A$7:$BK$69,47,0) -> 103.13 | M85: =VLOOKUP(B86,'B&L'!$A$7:$BK$69,52,0) -> 103.05 | N85: =VLOOKUP(B86,'B&L'!$A$7:$BK$69,57,0) -> 101.45 | O85: =VLOOKUP(B86,'B&L'!$A$7:$BK$69,62,0) -> 103.12
B86: 1412000077 | C86: 土地 Land | D86: =VLOOKUP(B86,'B&L'!$A$7:$BK$69,8,0) -> 14.71 | E86: =VLOOKUP(B86,'B&L'!$A$7:$BK$69,13,0) -> 14.28 | F86: =VLOOKUP(B86,'B&L'!$A$7:$BK$69,18,0) -> 14.23 | G86: =VLOOKUP(B86,'B&L'!$A$7:$BK$69,23,0) -> 14.11 | H86: =VLOOKUP(B86,'B&L'!$A$7:$BK$69,28,0) -> 14.09 | I86: =VLOOKUP(B86,'B&L'!$A$7:$BK$69,33,0) -> 13.17 | J86: =VLOOKUP(B86,'B&L'!$A$7:$BK$69,38,0) -> 13.42 | K86: =VLOOKUP(B86,'B&L'!$A$7:$BK$69,43,0) -> 13.42 | L86: =VLOOKUP(B86,'B&L'!$A$7:$BK$69,48,0) -> 13.44 | M86: =VLOOKUP(B86,'B&L'!$A$7:$BK$69,53,0) -> 13.43 | N86: =VLOOKUP(B86,'B&L'!$A$7:$BK$69,58,0) -> 13.22 | O86: =VLOOKUP(B86,'B&L'!$A$7:$BK$69,63,0) -> 13.44
A87: 41 | B87: MD3課 | C87: 建物 Building | D87: =VLOOKUP(B88,'B&L'!$A$7:$BK$69,7,0) -> 105.5 | E87: =VLOOKUP(B88,'B&L'!$A$7:$BK$69,12,0) -> 99.63 | F87: =VLOOKUP(B88,'B&L'!$A$7:$BK$69,17,0) -> 99.27 | G87: =VLOOKUP(B88,'B&L'!$A$7:$BK$69,22,0) -> 98.44 | H87: =VLOOKUP(B88,'B&L'!$A$7:$BK$69,27,0) -> 98.33 | I87: =VLOOKUP(B88,'B&L'!$A$7:$BK$69,32,0) -> 91.89 | J87: =VLOOKUP(B88,'B&L'!$A$7:$BK$69,37,0) -> 93.66 | K87: =VLOOKUP(B88,'B&L'!$A$7:$BK$69,42,0) -> 93.62 | L87: =VLOOKUP(B88,'B&L'!$A$7:$BK$69,47,0) -> 93.75 | M87: =VLOOKUP(B88,'B&L'!$A$7:$BK$69,52,0) -> 93.68 | N87: =VLOOKUP(B88,'B&L'!$A$7:$BK$69,57,0) -> 92.23 | O87: =VLOOKUP(B88,'B&L'!$A$7:$BK$69,62,0) -> 84.37
B88: 1412000083 | C88: 土地 Land | D88: =VLOOKUP(B88,'B&L'!$A$7:$BK$69,8,0) -> 13.38 | E88: =VLOOKUP(B88,'B&L'!$A$7:$BK$69,13,0) -> 12.98 | F88: =VLOOKUP(B88,'B&L'!$A$7:$BK$69,18,0) -> 12.94 | G88: =VLOOKUP(B88,'B&L'!$A$7:$BK$69,23,0) -> 12.83 | H88: =VLOOKUP(B88,'B&L'!$A$7:$BK$69,28,0) -> 12.81 | I88: =VLOOKUP(B88,'B&L'!$A$7:$BK$69,33,0) -> 11.97 | J88: =VLOOKUP(B88,'B&L'!$A$7:$BK$69,38,0) -> 12.2 | K88: =VLOOKUP(B88,'B&L'!$A$7:$BK$69,43,0) -> 12.2 | L88: =VLOOKUP(B88,'B&L'!$A$7:$BK$69,48,0) -> 12.22 | M88: =VLOOKUP(B88,'B&L'!$A$7:$BK$69,53,0) -> 12.21 | N88: =VLOOKUP(B88,'B&L'!$A$7:$BK$69,58,0) -> 12.02 | O88: =VLOOKUP(B88,'B&L'!$A$7:$BK$69,63,0) -> 10.99
A89: 42 | B89: MD4課 | C89: 建物 Building | D89: =VLOOKUP(B90,'B&L'!$A$7:$BK$69,7,0) -> 105.5 | E89: =VLOOKUP(B90,'B&L'!$A$7:$BK$69,12,0) -> 99.63 | F89: =VLOOKUP(B90,'B&L'!$A$7:$BK$69,17,0) -> 99.27 | G89: =VLOOKUP(B90,'B&L'!$A$7:$BK$69,22,0) -> 108.28 | H89: =VLOOKUP(B90,'B&L'!$A$7:$BK$69,27,0) -> 108.17 | I89: =VLOOKUP(B90,'B&L'!$A$7:$BK$69,32,0) -> 101.08 | J89: =VLOOKUP(B90,'B&L'!$A$7:$BK$69,37,0) -> 103.03 | K89: =VLOOKUP(B90,'B&L'!$A$7:$BK$69,42,0) -> 102.98 | L89: =VLOOKUP(B90,'B&L'!$A$7:$BK$69,47,0) -> 103.13 | M89: =VLOOKUP(B90,'B&L'!$A$7:$BK$69,52,0) -> 103.05 | N89: =VLOOKUP(B90,'B&L'!$A$7:$BK$69,57,0) -> 101.45 | O89: =VLOOKUP(B90,'B&L'!$A$7:$BK$69,62,0) -> 103.12
B90: 1412000099 | C90: 土地 Land | D90: =VLOOKUP(B90,'B&L'!$A$7:$BK$69,8,0) -> 13.38 | E90: =VLOOKUP(B90,'B&L'!$A$7:$BK$69,13,0) -> 12.98 | F90: =VLOOKUP(B90,'B&L'!$A$7:$BK$69,18,0) -> 12.94 | G90: =VLOOKUP(B90,'B&L'!$A$7:$BK$69,23,0) -> 14.11 | H90: =VLOOKUP(B90,'B&L'!$A$7:$BK$69,28,0) -> 14.09 | I90: =VLOOKUP(B90,'B&L'!$A$7:$BK$69,33,0) -> 13.17 | J90: =VLOOKUP(B90,'B&L'!$A$7:$BK$69,38,0) -> 13.42 | K90: =VLOOKUP(B90,'B&L'!$A$7:$BK$69,43,0) -> 13.42 | L90: =VLOOKUP(B90,'B&L'!$A$7:$BK$69,48,0) -> 13.44 | M90: =VLOOKUP(B90,'B&L'!$A$7:$BK$69,53,0) -> 13.43 | N90: =VLOOKUP(B90,'B&L'!$A$7:$BK$69,58,0) -> 13.22 | O90: =VLOOKUP(B90,'B&L'!$A$7:$BK$69,63,0) -> 13.44
A91: 43 | B91: MD5課 | C91: 建物 Building | D91: =VLOOKUP(B92,'B&L'!$A$7:$BK$69,7,0) -> 84.4 | E91: =VLOOKUP(B92,'B&L'!$A$7:$BK$69,12,0) -> 79.7 | F91: =VLOOKUP(B92,'B&L'!$A$7:$BK$69,17,0) -> 79.42 | G91: =VLOOKUP(B92,'B&L'!$A$7:$BK$69,22,0) -> 78.75 | H91: =VLOOKUP(B92,'B&L'!$A$7:$BK$69,27,0) -> 78.67 | I91: =VLOOKUP(B92,'B&L'!$A$7:$BK$69,32,0) -> 73.51 | J91: =VLOOKUP(B92,'B&L'!$A$7:$BK$69,37,0) -> 74.93 | K91: =VLOOKUP(B92,'B&L'!$A$7:$BK$69,42,0) -> 74.89 | L91: =VLOOKUP(B92,'B&L'!$A$7:$BK$69,47,0) -> 75 | M91: =VLOOKUP(B92,'B&L'!$A$7:$BK$69,52,0) -> 74.95 | N91: =VLOOKUP(B92,'B&L'!$A$7:$BK$69,57,0) -> 83.01 | O91: =VLOOKUP(B92,'B&L'!$A$7:$BK$69,62,0) -> 93.75
B92: 1412000100 | C92: 土地 Land | D92: =VLOOKUP(B92,'B&L'!$A$7:$BK$69,8,0) -> 10.7 | E92: =VLOOKUP(B92,'B&L'!$A$7:$BK$69,13,0) -> 10.39 | F92: =VLOOKUP(B92,'B&L'!$A$7:$BK$69,18,0) -> 10.35 | G92: =VLOOKUP(B92,'B&L'!$A$7:$BK$69,23,0) -> 10.26 | H92: =VLOOKUP(B92,'B&L'!$A$7:$BK$69,28,0) -> 10.25 | I92: =VLOOKUP(B92,'B&L'!$A$7:$BK$69,33,0) -> 9.58 | J92: =VLOOKUP(B92,'B&L'!$A$7:$BK$69,38,0) -> 9.76 | K92: =VLOOKUP(B92,'B&L'!$A$7:$BK$69,43,0) -> 9.76 | L92: =VLOOKUP(B92,'B&L'!$A$7:$BK$69,48,0) -> 9.77 | M92: =VLOOKUP(B92,'B&L'!$A$7:$BK$69,53,0) -> 9.77 | N92: =VLOOKUP(B92,'B&L'!$A$7:$BK$69,58,0) -> 10.82 | O92: =VLOOKUP(B92,'B&L'!$A$7:$BK$69,63,0) -> 12.22
A93: 44 | B93: EI1課 | C93: 建物 Building | D93: =VLOOKUP(B94,'B&L'!$A$7:$BK$69,7,0) -> 94.95 | E93: =VLOOKUP(B94,'B&L'!$A$7:$BK$69,12,0) -> 89.67 | F93: =VLOOKUP(B94,'B&L'!$A$7:$BK$69,17,0) -> 89.34 | G93: =VLOOKUP(B94,'B&L'!$A$7:$BK$69,22,0) -> 88.59 | H93: =VLOOKUP(B94,'B&L'!$A$7:$BK$69,27,0) -> 88.5 | I93: =VLOOKUP(B94,'B&L'!$A$7:$BK$69,32,0) -> 110.27 | J93: =VLOOKUP(B94,'B&L'!$A$7:$BK$69,37,0) -> 103.03 | K93: =VLOOKUP(B94,'B&L'!$A$7:$BK$69,42,0) -> 102.98 | L93: =VLOOKUP(B94,'B&L'!$A$7:$BK$69,47,0) -> 103.13 | M93: =VLOOKUP(B94,'B&L'!$A$7:$BK$69,52,0) -> 103.09 | N93: =VLOOKUP(B94,'B&L'!$A$7:$BK$69,57,0) -> 101.45 | O93: =VLOOKUP(B94,'B&L'!$A$7:$BK$69,62,0) -> 103.12
B94: 1412000057 | C94: 土地 Land | D94: =VLOOKUP(B94,'B&L'!$A$7:$BK$69,8,0) -> 12.04 | E94: =VLOOKUP(B94,'B&L'!$A$7:$BK$69,13,0) -> 11.68 | F94: =VLOOKUP(B94,'B&L'!$A$7:$BK$69,18,0) -> 11.64 | G94: =VLOOKUP(B94,'B&L'!$A$7:$BK$69,23,0) -> 11.54 | H94: =VLOOKUP(B94,'B&L'!$A$7:$BK$69,28,0) -> 11.53 | I94: =VLOOKUP(B94,'B&L'!$A$7:$BK$69,33,0) -> 14.37 | J94: =VLOOKUP(B94,'B&L'!$A$7:$BK$69,38,0) -> 13.42 | K94: =VLOOKUP(B94,'B&L'!$A$7:$BK$69,43,0) -> 13.42 | L94: =VLOOKUP(B94,'B&L'!$A$7:$BK$69,48,0) -> 13.44 | M94: =VLOOKUP(B94,'B&L'!$A$7:$BK$69,53,0) -> 13.43 | N94: =VLOOKUP(B94,'B&L'!$A$7:$BK$69,58,0) -> 13.22 | O94: =VLOOKUP(B94,'B&L'!$A$7:$BK$69,63,0) -> 13.44
A95: 45 | B95: EI2課 | C95: 建物 Building | D95: =VLOOKUP(B96,'B&L'!$A$7:$BK$69,7,0) -> 137.15 | E95: =VLOOKUP(B96,'B&L'!$A$7:$BK$69,12,0) -> 129.52 | F95: =VLOOKUP(B96,'B&L'!$A$7:$BK$69,17,0) -> 129.05 | G95: =VLOOKUP(B96,'B&L'!$A$7:$BK$69,22,0) -> 127.97 | H95: =VLOOKUP(B96,'B&L'!$A$7:$BK$69,27,0) -> 127.83 | I95: =VLOOKUP(B96,'B&L'!$A$7:$BK$69,32,0) -> 119.46 | J95: =VLOOKUP(B96,'B&L'!$A$7:$BK$69,37,0) -> 121.76 | K95: =VLOOKUP(B96,'B&L'!$A$7:$BK$69,42,0) -> 121.7 | L95: =VLOOKUP(B96,'B&L'!$A$7:$BK$69,47,0) -> 121.88 | M95: =VLOOKUP(B96,'B&L'!$A$7:$BK$69,52,0) -> 121.79 | N95: =VLOOKUP(B96,'B&L'!$A$7:$BK$69,57,0) -> 119.9 | O95: =VLOOKUP(B96,'B&L'!$A$7:$BK$69,62,0) -> 112.5
B96: 1412000101 | C96: 土地 Land | D96: =VLOOKUP(B96,'B&L'!$A$7:$BK$69,8,0) -> 17.39 | E96: =VLOOKUP(B96,'B&L'!$A$7:$BK$69,13,0) -> 16.88 | F96: =VLOOKUP(B96,'B&L'!$A$7:$BK$69,18,0) -> 16.82 | G96: =VLOOKUP(B96,'B&L'!$A$7:$BK$69,23,0) -> 16.68 | H96: =VLOOKUP(B96,'B&L'!$A$7:$BK$69,28,0) -> 16.66 | I96: =VLOOKUP(B96,'B&L'!$A$7:$BK$69,33,0) -> 15.57 | J96: =VLOOKUP(B96,'B&L'!$A$7:$BK$69,38,0) -> 15.87 | K96: =VLOOKUP(B96,'B&L'!$A$7:$BK$69,43,0) -> 15.86 | L96: =VLOOKUP(B96,'B&L'!$A$7:$BK$69,48,0) -> 15.88 | M96: =VLOOKUP(B96,'B&L'!$A$7:$BK$69,53,0) -> 15.87 | N96: =VLOOKUP(B96,'B&L'!$A$7:$BK$69,58,0) -> 15.62 | O96: =VLOOKUP(B96,'B&L'!$A$7:$BK$69,63,0) -> 14.66
A97: 46 | B97: ESD1課 | C97: 建物 Building | D97: =VLOOKUP(B98,'B&L'!$A$7:$BK$69,7,0) -> 137.15 | E97: =VLOOKUP(B98,'B&L'!$A$7:$BK$69,12,0) -> 129.52 | F97: =VLOOKUP(B98,'B&L'!$A$7:$BK$69,17,0) -> 129.05 | G97: =VLOOKUP(B98,'B&L'!$A$7:$BK$69,22,0) -> 127.97 | H97: =VLOOKUP(B98,'B&L'!$A$7:$BK$69,27,0) -> 127.83 | I97: =VLOOKUP(B98,'B&L'!$A$7:$BK$69,32,0) -> 156.21 | J97: =VLOOKUP(B98,'B&L'!$A$7:$BK$69,37,0) -> 149.85 | K97: =VLOOKUP(B98,'B&L'!$A$7:$BK$69,42,0) -> 149.79 | L97: =VLOOKUP(B98,'B&L'!$A$7:$BK$69,47,0) -> 150 | M97: =VLOOKUP(B98,'B&L'!$A$7:$BK$69,52,0) -> 149.89 | N97: =VLOOKUP(B98,'B&L'!$A$7:$BK$69,57,0) -> 147.57 | O97: =VLOOKUP(B98,'B&L'!$A$7:$BK$69,62,0) -> 150
B98: 1412000078 | C98: 土地 Land | D98: =VLOOKUP(B98,'B&L'!$A$7:$BK$69,8,0) -> 17.39 | E98: =VLOOKUP(B98,'B&L'!$A$7:$BK$69,13,0) -> 16.88 | F98: =VLOOKUP(B98,'B&L'!$A$7:$BK$69,18,0) -> 16.82 | G98: =VLOOKUP(B98,'B&L'!$A$7:$BK$69,23,0) -> 16.68 | H98: =VLOOKUP(B98,'B&L'!$A$7:$BK$69,28,0) -> 16.66 | I98: =VLOOKUP(B98,'B&L'!$A$7:$BK$69,33,0) -> 20.36 | J98: =VLOOKUP(B98,'B&L'!$A$7:$BK$69,38,0) -> 19.53 | K98: =VLOOKUP(B98,'B&L'!$A$7:$BK$69,43,0) -> 19.52 | L98: =VLOOKUP(B98,'B&L'!$A$7:$BK$69,48,0) -> 19.55 | M98: =VLOOKUP(B98,'B&L'!$A$7:$BK$69,53,0) -> 19.53 | N98: =VLOOKUP(B98,'B&L'!$A$7:$BK$69,58,0) -> 19.23 | O98: =VLOOKUP(B98,'B&L'!$A$7:$BK$69,63,0) -> 19.55
A99: 47 | B99: ESD2課 | C99: 建物 Building | D99: =VLOOKUP(B100,'B&L'!$A$7:$BK$69,7,0) -> 147.7 | E99: =VLOOKUP(B100,'B&L'!$A$7:$BK$69,12,0) -> 139.48 | F99: =VLOOKUP(B100,'B&L'!$A$7:$BK$69,17,0) -> 138.98 | G99: =VLOOKUP(B100,'B&L'!$A$7:$BK$69,22,0) -> 137.81 | H99: =VLOOKUP(B100,'B&L'!$A$7:$BK$69,27,0) -> 137.67 | I99: =VLOOKUP(B100,'B&L'!$A$7:$BK$69,32,0) -> 128.65 | J99: =VLOOKUP(B100,'B&L'!$A$7:$BK$69,37,0) -> 131.12 | K99: =VLOOKUP(B100,'B&L'!$A$7:$BK$69,42,0) -> 131.07 | L99: =VLOOKUP(B100,'B&L'!$A$7:$BK$69,47,0) -> 131.25 | M99: =VLOOKUP(B100,'B&L'!$A$7:$BK$69,52,0) -> 131.16 | N99: =VLOOKUP(B100,'B&L'!$A$7:$BK$69,57,0) -> 138.34 | O99: =VLOOKUP(B100,'B&L'!$A$7:$BK$69,62,0) -> 131.25
B100: 1412000096 | C100: 土地 Land | D100: =VLOOKUP(B100,'B&L'!$A$7:$BK$69,8,0) -> 18.73 | E100: =VLOOKUP(B100,'B&L'!$A$7:$BK$69,13,0) -> 18.18 | F100: =VLOOKUP(B100,'B&L'!$A$7:$BK$69,18,0) -> 18.11 | G100: =VLOOKUP(B100,'B&L'!$A$7:$BK$69,23,0) -> 17.96 | H100: =VLOOKUP(B100,'B&L'!$A$7:$BK$69,28,0) -> 17.94 | I100: =VLOOKUP(B100,'B&L'!$A$7:$BK$69,33,0) -> 16.76 | J100: =VLOOKUP(B100,'B&L'!$A$7:$BK$69,38,0) -> 17.09 | K100: =VLOOKUP(B100,'B&L'!$A$7:$BK$69,43,0) -> 17.08 | L100: =VLOOKUP(B100,'B&L'!$A$7:$BK$69,48,0) -> 17.1 | M100: =VLOOKUP(B100,'B&L'!$A$7:$BK$69,53,0) -> 17.09 | N100: =VLOOKUP(B100,'B&L'!$A$7:$BK$69,58,0) -> 18.03 | O100: =VLOOKUP(B100,'B&L'!$A$7:$BK$69,63,0) -> 17.1
A101: 48 | B101: 品質保証課 | C101: 建物 Building | D101: =VLOOKUP(B102,'B&L'!$A$7:$BK$69,7,0) -> 557.23 | E101: =VLOOKUP(B102,'B&L'!$A$7:$BK$69,12,0) -> 532.55 | F101: =VLOOKUP(B102,'B&L'!$A$7:$BK$69,17,0) -> 538.42 | G101: =VLOOKUP(B102,'B&L'!$A$7:$BK$69,22,0) -> 532.56 | H101: =VLOOKUP(B102,'B&L'!$A$7:$BK$69,27,0) -> 528.54 | I101: =VLOOKUP(B102,'B&L'!$A$7:$BK$69,32,0) -> 530.16 | J101: =VLOOKUP(B102,'B&L'!$A$7:$BK$69,37,0) -> 532.92 | K101: =VLOOKUP(B102,'B&L'!$A$7:$BK$69,42,0) -> 531.75 | L101: =VLOOKUP(B102,'B&L'!$A$7:$BK$69,47,0) -> 531 | M101: =VLOOKUP(B102,'B&L'!$A$7:$BK$69,52,0) -> 528.09 | N101: =VLOOKUP(B102,'B&L'!$A$7:$BK$69,57,0) -> 521.21 | O101: =VLOOKUP(B102,'B&L'!$A$7:$BK$69,62,0) -> 530.34
B102: 1412000018 | C102: 土地 Land | D102: =VLOOKUP(B102,'B&L'!$A$7:$BK$69,8,0) -> 70.65 | E102: =VLOOKUP(B102,'B&L'!$A$7:$BK$69,13,0) -> 69.4 | F102: =VLOOKUP(B102,'B&L'!$A$7:$BK$69,18,0) -> 70.16 | G102: =VLOOKUP(B102,'B&L'!$A$7:$BK$69,23,0) -> 69.4 | H102: =VLOOKUP(B102,'B&L'!$A$7:$BK$69,28,0) -> 68.87 | I102: =VLOOKUP(B102,'B&L'!$A$7:$BK$69,33,0) -> 69.08 | J102: =VLOOKUP(B102,'B&L'!$A$7:$BK$69,38,0) -> 69.44 | K102: =VLOOKUP(B102,'B&L'!$A$7:$BK$69,43,0) -> 69.29 | L102: =VLOOKUP(B102,'B&L'!$A$7:$BK$69,48,0) -> 69.19 | M102: =VLOOKUP(B102,'B&L'!$A$7:$BK$69,53,0) -> 68.81 | N102: =VLOOKUP(B102,'B&L'!$A$7:$BK$69,58,0) -> 67.92 | O102: =VLOOKUP(B102,'B&L'!$A$7:$BK$69,63,0) -> 69.11
...

Sheet 水道光熱費（Electric & Water）
F2: VND | J2: VND | M2: VND
B3: 部署 | C3: 水道光熱費 | D3: 46113 | E3: =IF(MONTH(D3)=12,EDATE(D3,1),EDATE(D3,1)) -> 46143 | F3: =IF(MONTH(E3)=12,EDATE(E3,1),EDATE(E3,1)) -> 46174 | G3: =IF(MONTH(F3)=12,EDATE(F3,1),EDATE(F3,1)) -> 46204 | H3: =IF(MONTH(G3)=12,EDATE(G3,1),EDATE(G3,1)) -> 46235 | I3: =IF(MONTH(H3)=12,EDATE(H3,1),EDATE(H3,1)) -> 46266 | J3: =IF(MONTH(I3)=12,EDATE(I3,1),EDATE(I3,1)) -> 46296 | K3: =IF(MONTH(J3)=12,EDATE(J3,1),EDATE(J3,1)) -> 46327 | L3: =IF(MONTH(K3)=12,EDATE(K3,1),EDATE(K3,1)) -> 46357 | ... O3: =IF(MONTH(N3)=12,EDATE(N3,1),EDATE(N3,1)) -> 46447
B4: 振替総額 | C4: 電気代 Electric | D4: =D132 -> 2389607989 | E4: =E132 -> 2341505283 | F4: =F132 -> 2662705192 | G4: =G132 -> 2890515886 | H4: =H132 -> 3008051207 | I4: =I132 -> 2667455145 | J4: =J132 -> 2398897481 | K4: =K132 -> 2375784802 | ... O4: =O132 -> 2249588940
C5: 水道代 Water | D5: =D133 -> 168200000 | E5: =E133 -> 178572000 | F5: =F133 -> 194100000 | G5: =G133 -> 297620000 | H5: =H133 -> 271740000 | I5: =I133 -> 270446000 | J5: =J133 -> 251036000 | K5: =K133 -> 194100000 | ... O5: =O133 -> 194100000
A6: 1 | B6: 機器製造1課 | C6: 電気代 Electric | D6: =VLOOKUP(B7,'E&W'!$A$7:$P$69,7,0) -> 217557171 | E6: =VLOOKUP(B7,'E&W'!$A$7:$P$69,9,0) -> 195546170 | F6: =VLOOKUP(B7,'E&W'!$A$7:$P$69,11,0) -> 216687222 | G6: =VLOOKUP(B7,'E&W'!$A$7:$P$69,13,0) -> 233958853 | H6: =VLOOKUP(B7,'E&W'!$A$7:$P$69,15,0) -> 239911156 | I6: =VLOOKUP(B7,'E&W'!$A$7:$AD$69,17,0) -> 224873351 | J6: =VLOOKUP(B7,'E&W'!$A$7:$AD$69,19,0) -> 198924667 | K6: =VLOOKUP(B7,'E&W'!$A$7:$AD$69,21,0) -> 192388076 | L6: =VLOOKUP(B7,'E&W'!$A$7:$AD$69,23,0) -> 172751094 | M6: =VLOOKUP(B7,'E&W'!$A$7:$AD$69,25,0) -> 223709328 | N6: =VLOOKUP(B7,'E&W'!$A$7:$AD$69,27,0) -> 222227053 | O6: =VLOOKUP(B7,'E&W'!$A$7:$AD$69,29,0) -> 205654872
B7: 1412000004 | C7: 水道代 Water | D7: =VLOOKUP(B7,'E&W'!$A$7:$P$69,8,0) -> 29926417 | E7: =VLOOKUP(B7,'E&W'!$A$7:$P$69,10,0) -> 32802865 | F7: =VLOOKUP(B7,'E&W'!$A$7:$P$69,12,0) -> 34177076 | G7: =VLOOKUP(B7,'E&W'!$A$7:$P$69,14,0) -> 54224430 | H7: =VLOOKUP(B7,'E&W'!$A$7:$P$69,16,0) -> 52664895 | I7: =VLOOKUP(B7,'E&W'!$A$7:$AD$69,18,0) -> 53168533 | J7: =VLOOKUP(B7,'E&W'!$A$7:$AD$69,20,0) -> 45556371 | K7: =VLOOKUP(B7,'E&W'!$A$7:$AD$69,22,0) -> 37212998 | L7: =VLOOKUP(B7,'E&W'!$A$7:$AD$69,24,0) -> 37043358 | M7: =VLOOKUP(B7,'E&W'!$A$7:$AD$69,26,0) -> 35623360 | N7: =VLOOKUP(B7,'E&W'!$A$7:$AD$69,28,0) -> 39263637 | O7: =VLOOKUP(B7,'E&W'!$A$7:$AD$69,30,0) -> 36261546
A8: 2 | B8: 機器製造2課 | C8: 電気代 Electric | D8: =VLOOKUP(B9,'E&W'!$A$7:$P$69,7,0) -> 145656656 | E8: =VLOOKUP(B9,'E&W'!$A$7:$P$69,9,0) -> 125903402 | F8: =VLOOKUP(B9,'E&W'!$A$7:$P$69,11,0) -> 138835031 | G8: =VLOOKUP(B9,'E&W'!$A$7:$P$69,13,0) -> 147155898 | H8: =VLOOKUP(B9,'E&W'!$A$7:$P$69,15,0) -> 153790158 | I8: =VLOOKUP(B9,'E&W'!$A$7:$AD$69,17,0) -> 134570184 | J8: =VLOOKUP(B9,'E&W'!$A$7:$AD$69,19,0) -> 120271965 | K8: =VLOOKUP(B9,'E&W'!$A$7:$AD$69,21,0) -> 129168668 | L8: =VLOOKUP(B9,'E&W'!$A$7:$AD$69,23,0) -> 137246842 | M8: =VLOOKUP(B9,'E&W'!$A$7:$AD$69,25,0) -> 160269338 | N8: =VLOOKUP(B9,'E&W'!$A$7:$AD$69,27,0) -> 159326628 | O8: =VLOOKUP(B9,'E&W'!$A$7:$AD$69,29,0) -> 160608544
B9: 1412000005 | C9: 水道代 Water | D9: =VLOOKUP(B9,'E&W'!$A$7:$P$69,8,0) -> 43433030 | E9: =VLOOKUP(B9,'E&W'!$A$7:$P$69,10,0) -> 45693141 | F9: =VLOOKUP(B9,'E&W'!$A$7:$P$69,12,0) -> 47491343 | G9: =VLOOKUP(B9,'E&W'!$A$7:$P$69,14,0) -> 77356625 | H9: =VLOOKUP(B9,'E&W'!$A$7:$P$69,16,0) -> 72527343 | I9: =VLOOKUP(B9,'E&W'!$A$7:$AD$69,18,0) -> 70569143 | J9: =VLOOKUP(B9,'E&W'!$A$7:$AD$69,20,0) -> 64322875 | K9: =VLOOKUP(B9,'E&W'!$A$7:$AD$69,22,0) -> 49503841 | L9: =VLOOKUP(B9,'E&W'!$A$7:$AD$69,24,0) -> 48410454 | M9: =VLOOKUP(B9,'E&W'!$A$7:$AD$69,26,0) -> 47706660 | N9: =VLOOKUP(B9,'E&W'!$A$7:$AD$69,28,0) -> 48929597 | O9: =VLOOKUP(B9,'E&W'!$A$7:$AD$69,30,0) -> 49893202
A10: 3 | B10: 機器製造管理課 | C10: 電気代 Electric | D10: =VLOOKUP(B11,'E&W'!$A$7:$P$69,7,0) -> 1006022 | E10: =VLOOKUP(B11,'E&W'!$A$7:$P$69,9,0) -> 790110 | F10: =VLOOKUP(B11,'E&W'!$A$7:$P$69,11,0) -> 727029 | G10: =VLOOKUP(B11,'E&W'!$A$7:$P$69,13,0) -> 769064 | H10: =VLOOKUP(B11,'E&W'!$A$7:$P$69,15,0) -> 810421 | I10: =VLOOKUP(B11,'E&W'!$A$7:$AD$69,17,0) -> 764773 | J10: =VLOOKUP(B11,'E&W'!$A$7:$AD$69,19,0) -> 692555 | K10: =VLOOKUP(B11,'E&W'!$A$7:$AD$69,21,0) -> 755120 | L10: =VLOOKUP(B11,'E&W'!$A$7:$AD$69,23,0) -> 911565 | M10: =VLOOKUP(B11,'E&W'!$A$7:$AD$69,25,0) -> 1096034 | N10: =VLOOKUP(B11,'E&W'!$A$7:$AD$69,27,0) -> 1112669 | O10: =VLOOKUP(B11,'E&W'!$A$7:$AD$69,29,0) -> 1045056
B11: 1412000062 | C11: 水道代 Water | D11: =VLOOKUP(B11,'E&W'!$A$7:$P$69,8,0) -> 882785 | E11: =VLOOKUP(B11,'E&W'!$A$7:$P$69,10,0) -> 961961 | F11: =VLOOKUP(B11,'E&W'!$A$7:$P$69,12,0) -> 1137971 | G11: =VLOOKUP(B11,'E&W'!$A$7:$P$69,14,0) -> 1602693 | H11: =VLOOKUP(B11,'E&W'!$A$7:$P$69,16,0) -> 1357343 | I11: =VLOOKUP(B11,'E&W'!$A$7:$AD$69,18,0) -> 1381001 | J11: =VLOOKUP(B11,'E&W'!$A$7:$AD$69,20,0) -> 1359892 | K11: =VLOOKUP(B11,'E&W'!$A$7:$AD$69,22,0) -> 1021400 | L11: =VLOOKUP(B11,'E&W'!$A$7:$AD$69,24,0) -> 1002979 | M11: =VLOOKUP(B11,'E&W'!$A$7:$AD$69,26,0) -> 895059 | N11: =VLOOKUP(B11,'E&W'!$A$7:$AD$69,28,0) -> 692074 | O11: =VLOOKUP(B11,'E&W'!$A$7:$AD$69,30,0) -> 1007265
A12: 4 | B12: RPS製造課 | C12: 電気代 Electric | D12: =VLOOKUP(B13,'E&W'!$A$7:$P$69,7,0) -> 8660259 | E12: =VLOOKUP(B13,'E&W'!$A$7:$P$69,9,0) -> 9557487 | F12: =VLOOKUP(B13,'E&W'!$A$7:$P$69,11,0) -> 15187227 | G12: =VLOOKUP(B13,'E&W'!$A$7:$P$69,13,0) -> 16298009 | H12: =VLOOKUP(B13,'E&W'!$A$7:$P$69,15,0) -> 17082503 | I12: =VLOOKUP(B13,'E&W'!$A$7:$AD$69,17,0) -> 13771437 | J12: =VLOOKUP(B13,'E&W'!$A$7:$AD$69,19,0) -> 11786489 | K12: =VLOOKUP(B13,'E&W'!$A$7:$AD$69,21,0) -> 11009413 | L12: =VLOOKUP(B13,'E&W'!$A$7:$AD$69,23,0) -> 8888349 | M12: =VLOOKUP(B13,'E&W'!$A$7:$AD$69,25,0) -> 7686171 | N12: =VLOOKUP(B13,'E&W'!$A$7:$AD$69,27,0) -> 6901292 | O12: =VLOOKUP(B13,'E&W'!$A$7:$AD$69,29,0) -> 6900755
B13: 1412000066 | C13: 水道代 Water | D13: =VLOOKUP(B13,'E&W'!$A$7:$P$69,8,0) -> 0 | E13: =VLOOKUP(B13,'E&W'!$A$7:$P$69,10,0) -> 0 | F13: =VLOOKUP(B13,'E&W'!$A$7:$P$69,12,0) -> 0 | G13: =VLOOKUP(B13,'E&W'!$A$7:$P$69,14,0) -> 0 | H13: =VLOOKUP(B13,'E&W'!$A$7:$P$69,16,0) -> 0 | I13: =VLOOKUP(B13,'E&W'!$A$7:$AD$69,18,0) -> 0 | J13: =VLOOKUP(B13,'E&W'!$A$7:$AD$69,20,0) -> 0 | K13: =VLOOKUP(B13,'E&W'!$A$7:$AD$69,22,0) -> 0 | L13: =VLOOKUP(B13,'E&W'!$A$7:$AD$69,24,0) -> 0 | M13: =VLOOKUP(B13,'E&W'!$A$7:$AD$69,26,0) -> 0 | N13: =VLOOKUP(B13,'E&W'!$A$7:$AD$69,28,0) -> 0 | O13: =VLOOKUP(B13,'E&W'!$A$7:$AD$69,30,0) -> 0
A14: 5 | B14: 機器製造3課 | C14: 電気代 Electric | D14: =VLOOKUP(B15,'E&W'!$A$7:$P$69,7,0) -> 207136304 | E14: =VLOOKUP(B15,'E&W'!$A$7:$P$69,9,0) -> 205029766 | F14: =VLOOKUP(B15,'E&W'!$A$7:$P$69,11,0) -> 233767130 | G14: =VLOOKUP(B15,'E&W'!$A$7:$P$69,13,0) -> 244248329 | H14: =VLOOKUP(B15,'E&W'!$A$7:$P$69,15,0) -> 263505172 | I14: =VLOOKUP(B15,'E&W'!$A$7:$AD$69,17,0) -> 229805941 | J14: =VLOOKUP(B15,'E&W'!$A$7:$AD$69,19,0) -> 202139773 | K14: =VLOOKUP(B15,'E&W'!$A$7:$AD$69,21,0) -> 205410262 | L14: =VLOOKUP(B15,'E&W'!$A$7:$AD$69,23,0) -> 211450047 | M14: =VLOOKUP(B15,'E&W'!$A$7:$AD$69,25,0) -> 193612701 | N14: =VLOOKUP(B15,'E&W'!$A$7:$AD$69,27,0) -> 214847892 | O14: =VLOOKUP(B15,'E&W'!$A$7:$AD$69,29,0) -> 219383962
B15: 1412000081 | C15: 水道代 Water | D15: =VLOOKUP(B15,'E&W'!$A$7:$P$69,8,0) -> 37282960 | E15: =VLOOKUP(B15,'E&W'!$A$7:$P$69,10,0) -> 37067558 | F15: =VLOOKUP(B15,'E&W'!$A$7:$P$69,12,0) -> 37628923 | G15: =VLOOKUP(B15,'E&W'!$A$7:$P$69,14,0) -> 59833854 | H15: =VLOOKUP(B15,'E&W'!$A$7:$P$69,16,0) -> 56329720 | I15: =VLOOKUP(B15,'E&W'!$A$7:$AD$69,18,0) -> 54595567 | J15: =VLOOKUP(B15,'E&W'!$A$7:$AD$69,20,0) -> 49409397 | K15: =VLOOKUP(B15,'E&W'!$A$7:$AD$69,22,0) -> 38472724 | L15: =VLOOKUP(B15,'E&W'!$A$7:$AD$69,24,0) -> 39751402 | M15: =VLOOKUP(B15,'E&W'!$A$7:$AD$69,26,0) -> 37592490 | N15: =VLOOKUP(B15,'E&W'!$A$7:$AD$69,28,0) -> 33427150 | O15: =VLOOKUP(B15,'E&W'!$A$7:$AD$69,30,0) -> 40290607
A16: 6 | B16: 電工製造課 | C16: 電気代 Electric | D16: =VLOOKUP(B17,'E&W'!$A$7:$P$69,7,0) -> 14605850 | E16: =VLOOKUP(B17,'E&W'!$A$7:$P$69,9,0) -> 15646037 | F16: =VLOOKUP(B17,'E&W'!$A$7:$P$69,11,0) -> 19795032 | G16: =VLOOKUP(B17,'E&W'!$A$7:$P$69,13,0) -> 24881242 | H16: =VLOOKUP(B17,'E&W'!$A$7:$P$69,15,0) -> 24880553 | I16: =VLOOKUP(B17,'E&W'!$A$7:$AD$69,17,0) -> 25397094 | J16: =VLOOKUP(B17,'E&W'!$A$7:$AD$69,19,0) -> 18957781 | K16: =VLOOKUP(B17,'E&W'!$A$7:$AD$69,21,0) -> 16413961 | L16: =VLOOKUP(B17,'E&W'!$A$7:$AD$69,23,0) -> 13441741 | M16: =VLOOKUP(B17,'E&W'!$A$7:$AD$69,25,0) -> 11448663 | N16: =VLOOKUP(B17,'E&W'!$A$7:$AD$69,27,0) -> 11803536 | O16: =VLOOKUP(B17,'E&W'!$A$7:$AD$69,29,0) -> 12715104
B17: 1412000098 | C17: 水道代 Water | D17: =VLOOKUP(B17,'E&W'!$A$7:$P$69,8,0) -> 1441882 | E17: =VLOOKUP(B17,'E&W'!$A$7:$P$69,10,0) -> 1571203 | F17: =VLOOKUP(B17,'E&W'!$A$7:$P$69,12,0) -> 1858687 | G17: =VLOOKUP(B17,'E&W'!$A$7:$P$69,14,0) -> 2617731 | H17: =VLOOKUP(B17,'E&W'!$A$7:$P$69,16,0) -> 2216993 | I17: =VLOOKUP(B17,'E&W'!$A$7:$AD$69,18,0) -> 2255635 | J17: =VLOOKUP(B17,'E&W'!$A$7:$AD$69,20,0) -> 2221156 | K17: =VLOOKUP(B17,'E&W'!$A$7:$AD$69,22,0) -> 1668286 | L17: =VLOOKUP(B17,'E&W'!$A$7:$AD$69,24,0) -> 1638199 | M17: =VLOOKUP(B17,'E&W'!$A$7:$AD$69,26,0) -> 1372424 | N17: =VLOOKUP(B17,'E&W'!$A$7:$AD$69,28,0) -> 1061179 | O17: =VLOOKUP(B17,'E&W'!$A$7:$AD$69,30,0) -> 1544473
A18: 7 | B18: トナー製造課 | C18: 電気代 Electric | D18: =VLOOKUP(B19,'E&W'!$A$7:$P$69,7,0) -> 163038029 | E18: =VLOOKUP(B19,'E&W'!$A$7:$P$69,9,0) -> 164531905 | F18: =VLOOKUP(B19,'E&W'!$A$7:$P$69,11,0) -> 177726638 | G18: =VLOOKUP(B19,'E&W'!$A$7:$P$69,13,0) -> 199855801 | H18: =VLOOKUP(B19,'E&W'!$A$7:$P$69,15,0) -> 196958068 | I18: =VLOOKUP(B19,'E&W'!$A$7:$AD$69,17,0) -> 175801510 | J18: =VLOOKUP(B19,'E&W'!$A$7:$AD$69,19,0) -> 156730616 | K18: =VLOOKUP(B19,'E&W'!$A$7:$AD$69,21,0) -> 156194483 | L18: =VLOOKUP(B19,'E&W'!$A$7:$AD$69,23,0) -> 123504928 | M18: =VLOOKUP(B19,'E&W'!$A$7:$AD$69,25,0) -> 149215972 | N18: =VLOOKUP(B19,'E&W'!$A$7:$AD$69,27,0) -> 155458919 | O18: =VLOOKUP(B19,'E&W'!$A$7:$AD$69,29,0) -> 145990387
B19: 1412000034 | C19: 水道代 Water | D19: =VLOOKUP(B19,'E&W'!$A$7:$P$69,8,0) -> 7621379 | E19: =VLOOKUP(B19,'E&W'!$A$7:$P$69,10,0) -> 8369059 | F19: =VLOOKUP(B19,'E&W'!$A$7:$P$69,12,0) -> 9900352 | G19: =VLOOKUP(B19,'E&W'!$A$7:$P$69,14,0) -> 14050271 | H19: =VLOOKUP(B19,'E&W'!$A$7:$P$69,16,0) -> 12351818 | I19: =VLOOKUP(B19,'E&W'!$A$7:$AD$69,18,0) -> 12567108 | J19: =VLOOKUP(B19,'E&W'!$A$7:$AD$69,20,0) -> 13462927 | K19: =VLOOKUP(B19,'E&W'!$A$7:$AD$69,22,0) -> 10111858 | L19: =VLOOKUP(B19,'E&W'!$A$7:$AD$69,24,0) -> 9929492 | M19: =VLOOKUP(B19,'E&W'!$A$7:$AD$69,26,0) -> 8861087 | N19: =VLOOKUP(B19,'E&W'!$A$7:$AD$69,28,0) -> 6851528 | O19: =VLOOKUP(B19,'E&W'!$A$7:$AD$69,30,0) -> 9971925
A20: 8 | B20: トナー生産技術 | C20: 電気代 Electric | D20: =VLOOKUP(B21,'E&W'!$A$7:$P$69,7,0) -> 1268149 | E20: =VLOOKUP(B21,'E&W'!$A$7:$P$69,9,0) -> 2147688 | F20: =VLOOKUP(B21,'E&W'!$A$7:$P$69,11,0) -> 2627580 | G20: =VLOOKUP(B21,'E&W'!$A$7:$P$69,13,0) -> 4049509 | H20: =VLOOKUP(B21,'E&W'!$A$7:$P$69,15,0) -> 3899166 | I20: =VLOOKUP(B21,'E&W'!$A$7:$AD$69,17,0) -> 3539639 | J20: =VLOOKUP(B21,'E&W'!$A$7:$AD$69,19,0) -> 2851950 | K20: =VLOOKUP(B21,'E&W'!$A$7:$AD$69,21,0) -> 2226285 | L20: =VLOOKUP(B21,'E&W'!$A$7:$AD$69,23,0) -> 906721 | M20: =VLOOKUP(B21,'E&W'!$A$7:$AD$69,25,0) -> 1421372 | N20: =VLOOKUP(B21,'E&W'!$A$7:$AD$69,27,0) -> 1065726 | O20: =VLOOKUP(B21,'E&W'!$A$7:$AD$69,29,0) -> 753239
B21: 1412000048 | C21: 水道代 Water | D21: =VLOOKUP(B21,'E&W'!$A$7:$P$69,8,0) -> 706228 | E21: =VLOOKUP(B21,'E&W'!$A$7:$P$69,10,0) -> 769569 | F21: =VLOOKUP(B21,'E&W'!$A$7:$P$69,12,0) -> 910377 | G21: =VLOOKUP(B21,'E&W'!$A$7:$P$69,14,0) -> 1282154 | H21: =VLOOKUP(B21,'E&W'!$A$7:$P$69,16,0) -> 1085874 | I21: =VLOOKUP(B21,'E&W'!$A$7:$AD$69,18,0) -> 1104801 | J21: =VLOOKUP(B21,'E&W'!$A$7:$AD$69,20,0) -> 1087913 | K21: =VLOOKUP(B21,'E&W'!$A$7:$AD$69,22,0) -> 817120 | L21: =VLOOKUP(B21,'E&W'!$A$7:$AD$69,24,0) -> 802383 | M21: =VLOOKUP(B21,'E&W'!$A$7:$AD$69,26,0) -> 716047 | N21: =VLOOKUP(B21,'E&W'!$A$7:$AD$69,28,0) -> 553659 | O21: =VLOOKUP(B21,'E&W'!$A$7:$AD$69,30,0) -> 805812
A22: 9 | B22: トナー品質管理課 | C22: 電気代 Electric | D22: =VLOOKUP(B23,'E&W'!$A$7:$P$69,7,0) -> 890062 | E22: =VLOOKUP(B23,'E&W'!$A$7:$P$69,9,0) -> 1507373 | F22: =VLOOKUP(B23,'E&W'!$A$7:$P$69,11,0) -> 1844190 | G22: =VLOOKUP(B23,'E&W'!$A$7:$P$69,13,0) -> 2842183 | H22: =VLOOKUP(B23,'E&W'!$A$7:$P$69,15,0) -> 2736663 | I22: =VLOOKUP(B23,'E&W'!$A$7:$AD$69,17,0) -> 2484326 | J22: =VLOOKUP(B23,'E&W'!$A$7:$AD$69,19,0) -> 2001666 | K22: =VLOOKUP(B23,'E&W'!$A$7:$AD$69,21,0) -> 1562538 | L22: =VLOOKUP(B23,'E&W'!$A$7:$AD$69,23,0) -> 636390 | M22: =VLOOKUP(B23,'E&W'!$A$7:$AD$69,25,0) -> 997602 | N22: =VLOOKUP(B23,'E&W'!$A$7:$AD$69,27,0) -> 747989 | O22: =VLOOKUP(B23,'E&W'!$A$7:$AD$69,29,0) -> 528668
B23: 1412000055 | C23: 水道代 Water | D23: =VLOOKUP(B23,'E&W'!$A$7:$P$69,8,0) -> 676802 | E23: =VLOOKUP(B23,'E&W'!$A$7:$P$69,10,0) -> 737503 | F23: =VLOOKUP(B23,'E&W'!$A$7:$P$69,12,0) -> 872445 | G23: =VLOOKUP(B23,'E&W'!$A$7:$P$69,14,0) -> 1228731 | H23: =VLOOKUP(B23,'E&W'!$A$7:$P$69,16,0) -> 1085874 | I23: =VLOOKUP(B23,'E&W'!$A$7:$AD$69,18,0) -> 1104801 | J23: =VLOOKUP(B23,'E&W'!$A$7:$AD$69,20,0) -> 1087913 | K23: =VLOOKUP(B23,'E&W'!$A$7:$AD$69,22,0) -> 817120 | L23: =VLOOKUP(B23,'E&W'!$A$7:$AD$69,24,0) -> 802383 | M23: =VLOOKUP(B23,'E&W'!$A$7:$AD$69,26,0) -> 716047 | N23: =VLOOKUP(B23,'E&W'!$A$7:$AD$69,28,0) -> 553659 | O23: =VLOOKUP(B23,'E&W'!$A$7:$AD$69,30,0) -> 805812
A24: 10 | B24: トナー製造管理課 | C24: 電気代 Electric | D24: =VLOOKUP(B25,'E&W'!$A$7:$P$69,7,0) -> 67886 | E24: =VLOOKUP(B25,'E&W'!$A$7:$P$69,9,0) -> 114969 | F24: =VLOOKUP(B25,'E&W'!$A$7:$P$69,11,0) -> 140659 | G24: =VLOOKUP(B25,'E&W'!$A$7:$P$69,13,0) -> 216777 | H24: =VLOOKUP(B25,'E&W'!$A$7:$P$69,15,0) -> 208729 | I24: =VLOOKUP(B25,'E&W'!$A$7:$AD$69,17,0) -> 189483 | J24: =VLOOKUP(B25,'E&W'!$A$7:$AD$69,19,0) -> 152669 | K24: =VLOOKUP(B25,'E&W'!$A$7:$AD$69,21,0) -> 119177 | L24: =VLOOKUP(B25,'E&W'!$A$7:$AD$69,23,0) -> 48538 | M24: =VLOOKUP(B25,'E&W'!$A$7:$AD$69,25,0) -> 76088 | N24: =VLOOKUP(B25,'E&W'!$A$7:$AD$69,27,0) -> 57050 | O24: =VLOOKUP(B25,'E&W'!$A$7:$AD$69,29,0) -> 40322
B25: 1412000063 | C25: 水道代 Water | D25: =VLOOKUP(B25,'E&W'!$A$7:$P$69,8,0) -> 294262 | E25: =VLOOKUP(B25,'E&W'!$A$7:$P$69,10,0) -> 288588 | F25: =VLOOKUP(B25,'E&W'!$A$7:$P$69,12,0) -> 341391 | G25: =VLOOKUP(B25,'E&W'!$A$7:$P$69,14,0) -> 587654 | H25: =VLOOKUP(B25,'E&W'!$A$7:$P$69,16,0) -> 497692 | I25: =VLOOKUP(B25,'E&W'!$A$7:$AD$69,18,0) -> 598434 | J25: =VLOOKUP(B25,'E&W'!$A$7:$AD$69,20,0) -> 543957 | K25: =VLOOKUP(B25,'E&W'!$A$7:$AD$69,22,0) -> 408560 | L25: =VLOOKUP(B25,'E&W'!$A$7:$AD$69,24,0) -> 367759 | M25: =VLOOKUP(B25,'E&W'!$A$7:$AD$69,26,0) -> 328188 | N25: =VLOOKUP(B25,'E&W'!$A$7:$AD$69,28,0) -> 230691 | O25: =VLOOKUP(B25,'E&W'!$A$7:$AD$69,30,0) -> 335755
A26: 11 | B26: 金型技術課 | C26: 電気代 Electric | D26: =VLOOKUP(B27,'E&W'!$A$7:$P$69,7,0) -> 101616030 | E26: =VLOOKUP(B27,'E&W'!$A$7:$P$69,9,0) -> 113805039 | F26: =VLOOKUP(B27,'E&W'!$A$7:$P$69,11,0) -> 107257894 | G26: =VLOOKUP(B27,'E&W'!$A$7:$P$69,13,0) -> 117258007 | H26: =VLOOKUP(B27,'E&W'!$A$7:$P$69,15,0) -> 126486080 | I26: =VLOOKUP(B27,'E&W'!$A$7:$AD$69,17,0) -> 121354856 | J26: =VLOOKUP(B27,'E&W'!$A$7:$AD$69,19,0) -> 122584302 | K26: =VLOOKUP(B27,'E&W'!$A$7:$AD$69,21,0) -> 126713377 | L26: =VLOOKUP(B27,'E&W'!$A$7:$AD$69,23,0) -> 125096913 | M26: =VLOOKUP(B27,'E&W'!$A$7:$AD$69,25,0) -> 82644829 | N26: =VLOOKUP(B27,'E&W'!$A$7:$AD$69,27,0) -> 90594618 | O26: =VLOOKUP(B27,'E&W'!$A$7:$AD$69,29,0) -> 97309562
B27: 1412000044 | C27: 水道代 Water | D27: =VLOOKUP(B27,'E&W'!$A$7:$P$69,8,0) -> 794507 | E27: =VLOOKUP(B27,'E&W'!$A$7:$P$69,10,0) -> 929895 | F27: =VLOOKUP(B27,'E&W'!$A$7:$P$69,12,0) -> 1100039 | G27: =VLOOKUP(B27,'E&W'!$A$7:$P$69,14,0) -> 1549269 | H27: =VLOOKUP(B27,'E&W'!$A$7:$P$69,16,0) -> 1312098 | I27: =VLOOKUP(B27,'E&W'!$A$7:$AD$69,18,0) -> 1334967 | J27: =VLOOKUP(B27,'E&W'!$A$7:$AD$69,20,0) -> 1314562 | K27: =VLOOKUP(B27,'E&W'!$A$7:$AD$69,22,0) -> 987353 | L27: =VLOOKUP(B27,'E&W'!$A$7:$AD$69,24,0) -> 969546 | M27: =VLOOKUP(B27,'E&W'!$A$7:$AD$69,26,0) -> 865224 | N27: =VLOOKUP(B27,'E&W'!$A$7:$AD$69,28,0) -> 669004 | O27: =VLOOKUP(B27,'E&W'!$A$7:$AD$69,30,0) -> 973690
A28: 12 | B28: 部品製造管理課 | C28: 電気代 Electric | D28: =VLOOKUP(B29,'E&W'!$A$7:$P$69,7,0) -> 2937106 | E28: =VLOOKUP(B29,'E&W'!$A$7:$P$69,9,0) -> 3168420 | F28: =VLOOKUP(B29,'E&W'!$A$7:$P$69,11,0) -> 3077032 | G28: =VLOOKUP(B29,'E&W'!$A$7:$P$69,13,0) -> 3445750 | H28: =VLOOKUP(B29,'E&W'!$A$7:$P$69,15,0) -> 3679975 | I28: =VLOOKUP(B29,'E&W'!$A$7:$AD$69,17,0) -> 3185027 | J28: =VLOOKUP(B29,'E&W'!$A$7:$AD$69,19,0) -> 3250987 | K28: =VLOOKUP(B29,'E&W'!$A$7:$AD$69,21,0) -> 3166221 | L28: =VLOOKUP(B29,'E&W'!$A$7:$AD$69,23,0) -> 2565034 | M28: =VLOOKUP(B29,'E&W'!$A$7:$AD$69,25,0) -> 2438434 | N28: =VLOOKUP(B29,'E&W'!$A$7:$AD$69,27,0) -> 2752358 | O28: =VLOOKUP(B29,'E&W'!$A$7:$AD$69,29,0) -> 2726879
B29: 1412000087 | C29: 水道代 Water | D29: =VLOOKUP(B29,'E&W'!$A$7:$P$69,8,0) -> 235409 | E29: =VLOOKUP(B29,'E&W'!$A$7:$P$69,10,0) -> 256523 | F29: =VLOOKUP(B29,'E&W'!$A$7:$P$69,12,0) -> 303459 | G29: =VLOOKUP(B29,'E&W'!$A$7:$P$69,14,0) -> 427385 | H29: =VLOOKUP(B29,'E&W'!$A$7:$P$69,16,0) -> 361958 | I29: =VLOOKUP(B29,'E&W'!$A$7:$AD$69,18,0) -> 368267 | J29: =VLOOKUP(B29,'E&W'!$A$7:$AD$69,20,0) -> 362638 | K29: =VLOOKUP(B29,'E&W'!$A$7:$AD$69,22,0) -> 272373 | L29: =VLOOKUP(B29,'E&W'!$A$7:$AD$69,24,0) -> 267461 | M29: =VLOOKUP(B29,'E&W'!$A$7:$AD$69,26,0) -> 238682 | N29: =VLOOKUP(B29,'E&W'!$A$7:$AD$69,28,0) -> 184553 | O29: =VLOOKUP(B29,'E&W'!$A$7:$AD$69,30,0) -> 268604
A30: 13 | B30: 品質管理課 | C30: 電気代 Electric | D30: =VLOOKUP(B31,'E&W'!$A$7:$P$69,7,0) -> 7735986 | E30: =VLOOKUP(B31,'E&W'!$A$7:$P$69,9,0) -> 7595144 | F30: =VLOOKUP(B31,'E&W'!$A$7:$P$69,11,0) -> 7547919 | G30: =VLOOKUP(B31,'E&W'!$A$7:$P$69,13,0) -> 7320727 | H30: =VLOOKUP(B31,'E&W'!$A$7:$P$69,15,0) -> 7162275 | I30: =VLOOKUP(B31,'E&W'!$A$7:$AD$69,17,0) -> 7224513 | J30: =VLOOKUP(B31,'E&W'!$A$7:$AD$69,19,0) -> 6425486 | K30: =VLOOKUP(B31,'E&W'!$A$7:$AD$69,21,0) -> 6882646 | L30: =VLOOKUP(B31,'E&W'!$A$7:$AD$69,23,0) -> 5018535 | M30: =VLOOKUP(B31,'E&W'!$A$7:$AD$69,25,0) -> 7359772 | N30: =VLOOKUP(B31,'E&W'!$A$7:$AD$69,27,0) -> 8176995 | O30: =VLOOKUP(B31,'E&W'!$A$7:$AD$69,29,0) -> 7314606
B31: 1412000088 | C31: 水道代 Water | D31: =VLOOKUP(B31,'E&W'!$A$7:$P$69,8,0) -> 706228 | E31: =VLOOKUP(B31,'E&W'!$A$7:$P$69,10,0) -> 769569 | F31: =VLOOKUP(B31,'E&W'!$A$7:$P$69,12,0) -> 910377 | G31: =VLOOKUP(B31,'E&W'!$A$7:$P$69,14,0) -> 1282154 | H31: =VLOOKUP(B31,'E&W'!$A$7:$P$69,16,0) -> 1085874 | I31: =VLOOKUP(B31,'E&W'!$A$7:$AD$69,18,0) -> 1104801 | J31: =VLOOKUP(B31,'E&W'!$A$7:$AD$69,20,0) -> 1087913 | K31: =VLOOKUP(B31,'E&W'!$A$7:$AD$69,22,0) -> 817120 | L31: =VLOOKUP(B31,'E&W'!$A$7:$AD$69,24,0) -> 802383 | M31: =VLOOKUP(B31,'E&W'!$A$7:$AD$69,26,0) -> 716047 | N31: =VLOOKUP(B31,'E&W'!$A$7:$AD$69,28,0) -> 553659 | O31: =VLOOKUP(B31,'E&W'!$A$7:$AD$69,30,0) -> 805812
A32: 14 | B32: 部品製造課 | C32: 電気代 Electric | D32: =VLOOKUP(B33,'E&W'!$A$7:$P$69,7,0) -> 592427614 | E32: =VLOOKUP(B33,'E&W'!$A$7:$P$69,9,0) -> 500428638 | F32: =VLOOKUP(B33,'E&W'!$A$7:$P$69,11,0) -> 500350831 | G32: =VLOOKUP(B33,'E&W'!$A$7:$P$69,13,0) -> 530470552 | H32: =VLOOKUP(B33,'E&W'!$A$7:$P$69,15,0) -> 547294097 | I32: =VLOOKUP(B33,'E&W'!$A$7:$AD$69,17,0) -> 389298659 | J32: =VLOOKUP(B33,'E&W'!$A$7:$AD$69,19,0) -> 443742553 | K32: =VLOOKUP(B33,'E&W'!$A$7:$AD$69,21,0) -> 453656082 | L32: =VLOOKUP(B33,'E&W'!$A$7:$AD$69,23,0) -> 390396333 | M32: =VLOOKUP(B33,'E&W'!$A$7:$AD$69,25,0) -> 566521629 | N32: =VLOOKUP(B33,'E&W'!$A$7:$AD$69,27,0) -> 598407118 | O32: =VLOOKUP(B33,'E&W'!$A$7:$AD$69,29,0) -> 563985078
B33: 1412000056 | C33: 水道代 Water | D33: =VLOOKUP(B33,'E&W'!$A$7:$P$69,8,0) -> 3472288 | E33: =VLOOKUP(B33,'E&W'!$A$7:$P$69,10,0) -> 3751647 | F33: =VLOOKUP(B33,'E&W'!$A$7:$P$69,12,0) -> 4400156 | G33: =VLOOKUP(B33,'E&W'!$A$7:$P$69,14,0) -> 6143655 | H33: =VLOOKUP(B33,'E&W'!$A$7:$P$69,16,0) -> 5157902 | I33: =VLOOKUP(B33,'E&W'!$A$7:$AD$69,18,0) -> 5293837 | J33: =VLOOKUP(B33,'E&W'!$A$7:$AD$69,20,0) -> 5258248 | K33: =VLOOKUP(B33,'E&W'!$A$7:$AD$69,22,0) -> 3983459 | L33: =VLOOKUP(B33,'E&W'!$A$7:$AD$69,24,0) -> 3945051 | M33: =VLOOKUP(B33,'E&W'!$A$7:$AD$69,26,0) -> 3520567 | N33: =VLOOKUP(B33,'E&W'!$A$7:$AD$69,28,0) -> 2722156 | O33: =VLOOKUP(B33,'E&W'!$A$7:$AD$69,30,0) -> 3961910
A34: 15 | B34: 部品技術課 | C34: 電気代 Electric | D34: =VLOOKUP(B35,'E&W'!$A$7:$P$69,7,0) -> 391678 | E34: =VLOOKUP(B35,'E&W'!$A$7:$P$69,9,0) -> 563787 | F34: =VLOOKUP(B35,'E&W'!$A$7:$P$69,11,0) -> 823714 | G34: =VLOOKUP(B35,'E&W'!$A$7:$P$69,13,0) -> 1182127 | H34: =VLOOKUP(B35,'E&W'!$A$7:$P$69,15,0) -> 1129362 | I34: =VLOOKUP(B35,'E&W'!$A$7:$AD$69,17,0) -> 1027823 | J34: =VLOOKUP(B35,'E&W'!$A$7:$AD$69,19,0) -> 716971 | K34: =VLOOKUP(B35,'E&W'!$A$7:$AD$69,21,0) -> 680000 | L34: =VLOOKUP(B35,'E&W'!$A$7:$AD$69,23,0) -> 575025 | M34: =VLOOKUP(B35,'E&W'!$A$7:$AD$69,25,0) -> 442483 | N34: =VLOOKUP(B35,'E&W'!$A$7:$AD$69,27,0) -> 418420 | O34: =VLOOKUP(B35,'E&W'!$A$7:$AD$69,29,0) -> 336810
B35: 1412000080 | C35: 水道代 Water | D35: =VLOOKUP(B35,'E&W'!$A$7:$P$69,8,0) -> 706228 | E35: =VLOOKUP(B35,'E&W'!$A$7:$P$69,10,0) -> 769569 | F35: =VLOOKUP(B35,'E&W'!$A$7:$P$69,12,0) -> 910377 | G35: =VLOOKUP(B35,'E&W'!$A$7:$P$69,14,0) -> 1282154 | H35: =VLOOKUP(B35,'E&W'!$A$7:$P$69,16,0) -> 1176364 | I35: =VLOOKUP(B35,'E&W'!$A$7:$AD$69,18,0) -> 1196867 | J35: =VLOOKUP(B35,'E&W'!$A$7:$AD$69,20,0) -> 1178573 | K35: =VLOOKUP(B35,'E&W'!$A$7:$AD$69,22,0) -> 885213 | L35: =VLOOKUP(B35,'E&W'!$A$7:$AD$69,24,0) -> 902681 | M35: =VLOOKUP(B35,'E&W'!$A$7:$AD$69,26,0) -> 805553 | N35: =VLOOKUP(B35,'E&W'!$A$7:$AD$69,28,0) -> 622866 | O35: =VLOOKUP(B35,'E&W'!$A$7:$AD$69,30,0) -> 906539
A36: 16 | B36: 工程品質管理1課 | C36: 電気代 Electric | D36: =VLOOKUP(B37,'E&W'!$A$7:$P$69,7,0) -> 2132140 | E36: =VLOOKUP(B37,'E&W'!$A$7:$P$69,9,0) -> 2023881 | F36: =VLOOKUP(B37,'E&W'!$A$7:$P$69,11,0) -> 1970184 | G36: =VLOOKUP(B37,'E&W'!$A$7:$P$69,13,0) -> 2192145 | H36: =VLOOKUP(B37,'E&W'!$A$7:$P$69,15,0) -> 2204081 | I36: =VLOOKUP(B37,'E&W'!$A$7:$AD$69,17,0) -> 2134874 | J36: =VLOOKUP(B37,'E&W'!$A$7:$AD$69,19,0) -> 1851504 | K36: =VLOOKUP(B37,'E&W'!$A$7:$AD$69,21,0) -> 1779961 | L36: =VLOOKUP(B37,'E&W'!$A$7:$AD$69,23,0) -> 1836753 | M36: =VLOOKUP(B37,'E&W'!$A$7:$AD$69,25,0) -> 2113805 | N36: =VLOOKUP(B37,'E&W'!$A$7:$AD$69,27,0) -> 2142741 | O36: =VLOOKUP(B37,'E&W'!$A$7:$AD$69,29,0) -> 2152242
B37: 1412000053 | C37: 水道代 Water | D37: =VLOOKUP(B37,'E&W'!$A$7:$P$69,8,0) -> 882785 | E37: =VLOOKUP(B37,'E&W'!$A$7:$P$69,10,0) -> 961961 | F37: =VLOOKUP(B37,'E&W'!$A$7:$P$69,12,0) -> 1137971 | G37: =VLOOKUP(B37,'E&W'!$A$7:$P$69,14,0) -> 1869808 | H37: =VLOOKUP(B37,'E&W'!$A$7:$P$69,16,0) -> 1583566 | I37: =VLOOKUP(B37,'E&W'!$A$7:$AD$69,18,0) -> 1611168 | J37: =VLOOKUP(B37,'E&W'!$A$7:$AD$69,20,0) -> 1677200 | K37: =VLOOKUP(B37,'E&W'!$A$7:$AD$69,22,0) -> 1259726 | L37: =VLOOKUP(B37,'E&W'!$A$7:$AD$69,24,0) -> 1237007 | M37: =VLOOKUP(B37,'E&W'!$A$7:$AD$69,26,0) -> 1103906 | N37: =VLOOKUP(B37,'E&W'!$A$7:$AD$69,28,0) -> 853557 | O37: =VLOOKUP(B37,'E&W'!$A$7:$AD$69,30,0) -> 1242294
A38: 17 | B38: 工程品質管理2課 | C38: 電気代 Electric | D38: =VLOOKUP(B39,'E&W'!$A$7:$P$69,7,0) -> 2823689 | E38: =VLOOKUP(B39,'E&W'!$A$7:$P$69,9,0) -> 2608289 | F38: =VLOOKUP(B39,'E&W'!$A$7:$P$69,11,0) -> 3070485 | G38: =VLOOKUP(B39,'E&W'!$A$7:$P$69,13,0) -> 3752959 | H38: =VLOOKUP(B39,'E&W'!$A$7:$P$69,15,0) -> 3807782 | I38: =VLOOKUP(B39,'E&W'!$A$7:$AD$69,17,0) -> 3704697 | J38: =VLOOKUP(B39,'E&W'!$A$7:$AD$69,19,0) -> 3086946 | K38: =VLOOKUP(B39,'E&W'!$A$7:$AD$69,21,0) -> 2722585 | L38: =VLOOKUP(B39,'E&W'!$A$7:$AD$69,23,0) -> 2477720 | M38: =VLOOKUP(B39,'E&W'!$A$7:$AD$69,25,0) -> 2622817 | N38: =VLOOKUP(B39,'E&W'!$A$7:$AD$69,27,0) -> 2629315 | O38: =VLOOKUP(B39,'E&W'!$A$7:$AD$69,29,0) -> 2604029
B39: 1412000104 | C39: 水道代 Water | D39: =VLOOKUP(B39,'E&W'!$A$7:$P$69,8,0) -> 4502204 | E39: =VLOOKUP(B39,'E&W'!$A$7:$P$69,10,0) -> 4906000 | F39: =VLOOKUP(B39,'E&W'!$A$7:$P$69,12,0) -> 5803654 | G39: =VLOOKUP(B39,'E&W'!$A$7:$P$69,14,0) -> 8173732 | H39: =VLOOKUP(B39,'E&W'!$A$7:$P$69,16,0) -> 6922448 | I39: =VLOOKUP(B39,'E&W'!$A$7:$AD$69,18,0) -> 7043104 | J39: =VLOOKUP(B39,'E&W'!$A$7:$AD$69,20,0) -> 6935447 | K39: =VLOOKUP(B39,'E&W'!$A$7:$AD$69,22,0) -> 5209139 | L39: =VLOOKUP(B39,'E&W'!$A$7:$AD$69,24,0) -> 5115193 | M39: =VLOOKUP(B39,'E&W'!$A$7:$AD$69,26,0) -> 4564802 | N39: =VLOOKUP(B39,'E&W'!$A$7:$AD$69,28,0) -> 3529575 | O39: =VLOOKUP(B39,'E&W'!$A$7:$AD$69,30,0) -> 5137052
A40: 18 | B40: 工程品質管理3課 | C40: 電気代 Electric | D40: =VLOOKUP(B41,'E&W'!$A$7:$P$69,7,0) -> 1175945 | E40: =VLOOKUP(B41,'E&W'!$A$7:$P$69,9,0) -> 1460384 | F40: =VLOOKUP(B41,'E&W'!$A$7:$P$69,11,0) -> 1266849 | G40: =VLOOKUP(B41,'E&W'!$A$7:$P$69,13,0) -> 1336549 | H40: =VLOOKUP(B41,'E&W'!$A$7:$P$69,15,0) -> 1258211 | I40: =VLOOKUP(B41,'E&W'!$A$7:$AD$69,17,0) -> 1249708 | J40: =VLOOKUP(B41,'E&W'!$A$7:$AD$69,19,0) -> 1083953 | K40: =VLOOKUP(B41,'E&W'!$A$7:$AD$69,21,0) -> 980997 | L40: =VLOOKUP(B41,'E&W'!$A$7:$AD$69,23,0) -> 907949 | M40: =VLOOKUP(B41,'E&W'!$A$7:$AD$69,25,0) -> 1056831 | N40: =VLOOKUP(B41,'E&W'!$A$7:$AD$69,27,0) -> 1081190 | O40: =VLOOKUP(B41,'E&W'!$A$7:$AD$69,29,0) -> 1239766
B41: 1412000105 | C41: 水道代 Water | D41: =VLOOKUP(B41,'E&W'!$A$7:$P$69,8,0) -> 588523 | E41: =VLOOKUP(B41,'E&W'!$A$7:$P$69,10,0) -> 641307 | F41: =VLOOKUP(B41,'E&W'!$A$7:$P$69,12,0) -> 758648 | G41: =VLOOKUP(B41,'E&W'!$A$7:$P$69,14,0) -> 1068462 | H41: =VLOOKUP(B41,'E&W'!$A$7:$P$69,16,0) -> 904895 | I41: =VLOOKUP(B41,'E&W'!$A$7:$AD$69,18,0) -> 920667 | J41: =VLOOKUP(B41,'E&W'!$A$7:$AD$69,20,0) -> 906594 | K41: =VLOOKUP(B41,'E&W'!$A$7:$AD$69,22,0) -> 680933 | L41: =VLOOKUP(B41,'E&W'!$A$7:$AD$69,24,0) -> 668653 | M41: =VLOOKUP(B41,'E&W'!$A$7:$AD$69,26,0) -> 596706 | N41: =VLOOKUP(B41,'E&W'!$A$7:$AD$69,28,0) -> 461382 | O41: =VLOOKUP(B41,'E&W'!$A$7:$AD$69,30,0) -> 671510
A42: 19 | B42: 工程品質管理4課 | C42: 電気代 Electric | D42: =VLOOKUP(B43,'E&W'!$A$7:$P$69,7,0) -> 1408431 | E42: =VLOOKUP(B43,'E&W'!$A$7:$P$69,9,0) -> 1106153 | F42: =VLOOKUP(B43,'E&W'!$A$7:$P$69,11,0) -> 1017840 | G42: =VLOOKUP(B43,'E&W'!$A$7:$P$69,13,0) -> 1076689 | H42: =VLOOKUP(B43,'E&W'!$A$7:$P$69,15,0) -> 1134589 | I42: =VLOOKUP(B43,'E&W'!$A$7:$AD$69,17,0) -> 1070683 | J42: =VLOOKUP(B43,'E&W'!$A$7:$AD$69,19,0) -> 969577 | K42: =VLOOKUP(B43,'E&W'!$A$7:$AD$69,21,0) -> 1057168 | L42: =VLOOKUP(B43,'E&W'!$A$7:$AD$69,23,0) -> 1276190 | M42: =VLOOKUP(B43,'E&W'!$A$7:$AD$69,25,0) -> 1534448 | N42: =VLOOKUP(B43,'E&W'!$A$7:$AD$69,27,0) -> 1557736 | O42: =VLOOKUP(B43,'E&W'!$A$7:$AD$69,29,0) -> 1463078
B43: 1412000075 | C43: 水道代 Water | D43: =VLOOKUP(B43,'E&W'!$A$7:$P$69,8,0) -> 382540 | E43: =VLOOKUP(B43,'E&W'!$A$7:$P$69,10,0) -> 448915 | F43: =VLOOKUP(B43,'E&W'!$A$7:$P$69,12,0) -> 531053 | G43: =VLOOKUP(B43,'E&W'!$A$7:$P$69,14,0) -> 747923 | H43: =VLOOKUP(B43,'E&W'!$A$7:$P$69,16,0) -> 633427 | I43: =VLOOKUP(B43,'E&W'!$A$7:$AD$69,18,0) -> 644467 | J43: =VLOOKUP(B43,'E&W'!$A$7:$AD$69,20,0) -> 634616 | K43: =VLOOKUP(B43,'E&W'!$A$7:$AD$69,22,0) -> 476653 | L43: =VLOOKUP(B43,'E&W'!$A$7:$AD$69,24,0) -> 468057 | M43: =VLOOKUP(B43,'E&W'!$A$7:$AD$69,26,0) -> 417694 | N43: =VLOOKUP(B43,'E&W'!$A$7:$AD$69,28,0) -> 322968 | O43: =VLOOKUP(B43,'E&W'!$A$7:$AD$69,30,0) -> 470057
A44: 20 | B44: 生産管理課 | C44: 電気代 Electric | D44: =VLOOKUP(B45,'E&W'!$A$7:$P$69,7,0) -> 1892497 | E44: =VLOOKUP(B45,'E&W'!$A$7:$P$69,9,0) -> 1697070 | F44: =VLOOKUP(B45,'E&W'!$A$7:$P$69,11,0) -> 1548171 | G44: =VLOOKUP(B45,'E&W'!$A$7:$P$69,13,0) -> 1665083 | H44: =VLOOKUP(B45,'E&W'!$A$7:$P$69,15,0) -> 1776206 | I44: =VLOOKUP(B45,'E&W'!$A$7:$AD$69,17,0) -> 1730953 | J44: =VLOOKUP(B45,'E&W'!$A$7:$AD$69,19,0) -> 1417376 | K44: =VLOOKUP(B45,'E&W'!$A$7:$AD$69,21,0) -> 1568216 | L44: =VLOOKUP(B45,'E&W'!$A$7:$AD$69,23,0) -> 1678744 | M44: =VLOOKUP(B45,'E&W'!$A$7:$AD$69,25,0) -> 1920136 | N44: =VLOOKUP(B45,'E&W'!$A$7:$AD$69,27,0) -> 1987771 | O44: =VLOOKUP(B45,'E&W'!$A$7:$AD$69,29,0) -> 1977773
B45: 1412000008 | C45: 水道代 Water | D45: =VLOOKUP(B45,'E&W'!$A$7:$P$69,8,0) -> 294262 | E45: =VLOOKUP(B45,'E&W'!$A$7:$P$69,10,0) -> 320654 | F45: =VLOOKUP(B45,'E&W'!$A$7:$P$69,12,0) -> 379324 | G45: =VLOOKUP(B45,'E&W'!$A$7:$P$69,14,0) -> 534231 | H45: =VLOOKUP(B45,'E&W'!$A$7:$P$69,16,0) -> 452448 | I45: =VLOOKUP(B45,'E&W'!$A$7:$AD$69,18,0) -> 460334 | J45: =VLOOKUP(B45,'E&W'!$A$7:$AD$69,20,0) -> 453297 | K45: =VLOOKUP(B45,'E&W'!$A$7:$AD$69,22,0) -> 340467 | L45: =VLOOKUP(B45,'E&W'!$A$7:$AD$69,24,0) -> 334326 | M45: =VLOOKUP(B45,'E&W'!$A$7:$AD$69,26,0) -> 298353 | N45: =VLOOKUP(B45,'E&W'!$A$7:$AD$69,28,0) -> 230691 | O45: =VLOOKUP(B45,'E&W'!$A$7:$AD$69,30,0) -> 335755
A46: 21 | B46: 採算管理課 | C46: 電気代 Electric | D46: =VLOOKUP(B47,'E&W'!$A$7:$P$69,7,0) -> 1075137 | E46: =VLOOKUP(B47,'E&W'!$A$7:$P$69,9,0) -> 970835 | F46: =VLOOKUP(B47,'E&W'!$A$7:$P$69,11,0) -> 885281 | G46: =VLOOKUP(B47,'E&W'!$A$7:$P$69,13,0) -> 952906 | H46: =VLOOKUP(B47,'E&W'!$A$7:$P$69,15,0) -> 1017098 | I46: =VLOOKUP(B47,'E&W'!$A$7:$AD$69,17,0) -> 992686 | J46: =VLOOKUP(B47,'E&W'!$A$7:$AD$69,19,0) -> 808872 | K46: =VLOOKUP(B47,'E&W'!$A$7:$AD$69,21,0) -> 895623 | L46: =VLOOKUP(B47,'E&W'!$A$7:$AD$69,23,0) -> 952553 | M46: =VLOOKUP(B47,'E&W'!$A$7:$AD$69,25,0) -> 1086320 | N46: =VLOOKUP(B47,'E&W'!$A$7:$AD$69,27,0) -> 1125902 | O46: =VLOOKUP(B47,'E&W'!$A$7:$AD$69,29,0) -> 1123960
B47: 1412000010 | C47: 水道代 Water | D47: =VLOOKUP(B47,'E&W'!$A$7:$P$69,8,0) -> 176557 | E47: =VLOOKUP(B47,'E&W'!$A$7:$P$69,10,0) -> 192392 | F47: =VLOOKUP(B47,'E&W'!$A$7:$P$69,12,0) -> 227594 | G47: =VLOOKUP(B47,'E&W'!$A$7:$P$69,14,0) -> 320539 | H47: =VLOOKUP(B47,'E&W'!$A$7:$P$69,16,0) -> 271469 | I47: =VLOOKUP(B47,'E&W'!$A$7:$AD$69,18,0) -> 276200 | J47: =VLOOKUP(B47,'E&W'!$A$7:$AD$69,20,0) -> 271978 | K47: =VLOOKUP(B47,'E&W'!$A$7:$AD$69,22,0) -> 204280 | L47: =VLOOKUP(B47,'E&W'!$A$7:$AD$69,24,0) -> 200596 | M47: =VLOOKUP(B47,'E&W'!$A$7:$AD$69,26,0) -> 179012 | N47: =VLOOKUP(B47,'E&W'!$A$7:$AD$69,28,0) -> 138415 | O47: =VLOOKUP(B47,'E&W'!$A$7:$AD$69,30,0) -> 201453
A48: 22 | B48: OC課 | C48: 電気代 Electric | D48: =VLOOKUP(B49,'E&W'!$A$7:$P$69,7,0) -> 100602 | E48: =VLOOKUP(B49,'E&W'!$A$7:$P$69,9,0) -> 79011 | F48: =VLOOKUP(B49,'E&W'!$A$7:$P$69,11,0) -> 72703 | G48: =VLOOKUP(B49,'E&W'!$A$7:$P$69,13,0) -> 76906 | H48: =VLOOKUP(B49,'E&W'!$A$7:$P$69,15,0) -> 81042 | I48: =VLOOKUP(B49,'E&W'!$A$7:$AD$69,17,0) -> 76477 | J48: =VLOOKUP(B49,'E&W'!$A$7:$AD$69,19,0) -> 69255 | K48: =VLOOKUP(B49,'E&W'!$A$7:$AD$69,21,0) -> 75512 | L48: =VLOOKUP(B49,'E&W'!$A$7:$AD$69,23,0) -> 91156 | M48: =VLOOKUP(B49,'E&W'!$A$7:$AD$69,25,0) -> 109603 | N48: =VLOOKUP(B49,'E&W'!$A$7:$AD$69,27,0) -> 111267 | O48: =VLOOKUP(B49,'E&W'!$A$7:$AD$69,29,0) -> 104506
B49: 1412000094 | C49: 水道代 Water | D49: =VLOOKUP(B49,'E&W'!$A$7:$P$69,8,0) -> 147131 | E49: =VLOOKUP(B49,'E&W'!$A$7:$P$69,10,0) -> 160327 | F49: =VLOOKUP(B49,'E&W'!$A$7:$P$69,12,0) -> 189662 | G49: =VLOOKUP(B49,'E&W'!$A$7:$P$69,14,0) -> 267115 | H49: =VLOOKUP(B49,'E&W'!$A$7:$P$69,16,0) -> 226224 | I49: =VLOOKUP(B49,'E&W'!$A$7:$AD$69,18,0) -> 230167 | J49: =VLOOKUP(B49,'E&W'!$A$7:$AD$69,20,0) -> 226649 | K49: =VLOOKUP(B49,'E&W'!$A$7:$AD$69,22,0) -> 170233 | L49: =VLOOKUP(B49,'E&W'!$A$7:$AD$69,24,0) -> 167163 | M49: =VLOOKUP(B49,'E&W'!$A$7:$AD$69,26,0) -> 149177 | N49: =VLOOKUP(B49,'E&W'!$A$7:$AD$69,28,0) -> 115346 | O49: =VLOOKUP(B49,'E&W'!$A$7:$AD$69,30,0) -> 167878
A50: 23 | B50: マスター管理課 | C50: 電気代 Electric | D50: =VLOOKUP(B51,'E&W'!$A$7:$P$69,7,0) -> 2609255 | E50: =VLOOKUP(B51,'E&W'!$A$7:$P$69,9,0) -> 2344293 | F50: =VLOOKUP(B51,'E&W'!$A$7:$P$69,11,0) -> 2138358 | G50: =VLOOKUP(B51,'E&W'!$A$7:$P$69,13,0) -> 2300354 | H50: =VLOOKUP(B51,'E&W'!$A$7:$P$69,15,0) -> 2454271 | I50: =VLOOKUP(B51,'E&W'!$A$7:$AD$69,17,0) -> 2392744 | J50: =VLOOKUP(B51,'E&W'!$A$7:$AD$69,19,0) -> 1956624 | K50: =VLOOKUP(B51,'E&W'!$A$7:$AD$69,21,0) -> 2165298 | L50: =VLOOKUP(B51,'E&W'!$A$7:$AD$69,23,0) -> 2313779 | M50: =VLOOKUP(B51,'E&W'!$A$7:$AD$69,25,0) -> 2644349 | N50: =VLOOKUP(B51,'E&W'!$A$7:$AD$69,27,0) -> 2738372 | O50: =VLOOKUP(B51,'E&W'!$A$7:$AD$69,29,0) -> 2727080
B51: 1412000054 | C51: 水道代 Water | D51: =VLOOKUP(B51,'E&W'!$A$7:$P$69,8,0) -> 411966 | E51: =VLOOKUP(B51,'E&W'!$A$7:$P$69,10,0) -> 448915 | F51: =VLOOKUP(B51,'E&W'!$A$7:$P$69,12,0) -> 531053 | G51: =VLOOKUP(B51,'E&W'!$A$7:$P$69,14,0) -> 747923 | H51: =VLOOKUP(B51,'E&W'!$A$7:$P$69,16,0) -> 633427 | I51: =VLOOKUP(B51,'E&W'!$A$7:$AD$69,18,0) -> 644467 | J51: =VLOOKUP(B51,'E&W'!$A$7:$AD$69,20,0) -> 634616 | K51: =VLOOKUP(B51,'E&W'!$A$7:$AD$69,22,0) -> 476653 | L51: =VLOOKUP(B51,'E&W'!$A$7:$AD$69,24,0) -> 468057 | M51: =VLOOKUP(B51,'E&W'!$A$7:$AD$69,26,0) -> 417694 | N51: =VLOOKUP(B51,'E&W'!$A$7:$AD$69,28,0) -> 322968 | O51: =VLOOKUP(B51,'E&W'!$A$7:$AD$69,30,0) -> 470057
A52: 24 | B52: 部品管理1課 | C52: 電気代 Electric | D52: =VLOOKUP(B53,'E&W'!$A$7:$P$69,7,0) -> 161259654 | E52: =VLOOKUP(B53,'E&W'!$A$7:$P$69,9,0) -> 184240060 | F52: =VLOOKUP(B53,'E&W'!$A$7:$P$69,11,0) -> 253069181 | G52: =VLOOKUP(B53,'E&W'!$A$7:$P$69,13,0) -> 296661048 | H52: =VLOOKUP(B53,'E&W'!$A$7:$P$69,15,0) -> 315090256 | I52: =VLOOKUP(B53,'E&W'!$A$7:$AD$69,17,0) -> 304173947 | J52: =VLOOKUP(B53,'E&W'!$A$7:$AD$69,19,0) -> 248315991 | K52: =VLOOKUP(B53,'E&W'!$A$7:$AD$69,21,0) -> 227011674 | L52: =VLOOKUP(B53,'E&W'!$A$7:$AD$69,23,0) -> 145857668 | M52: =VLOOKUP(B53,'E&W'!$A$7:$AD$69,25,0) -> 111240594 | N52: =VLOOKUP(B53,'E&W'!$A$7:$AD$69,27,0) -> 111421595 | O52: =VLOOKUP(B53,'E&W'!$A$7:$AD$69,29,0) -> 114848341
B53: 1412000036 | C53: 水道代 Water | D53: =VLOOKUP(B53,'E&W'!$A$7:$P$69,8,0) -> 3207453 | E53: =VLOOKUP(B53,'E&W'!$A$7:$P$69,10,0) -> 3495124 | F53: =VLOOKUP(B53,'E&W'!$A$7:$P$69,12,0) -> 4134630 | G53: =VLOOKUP(B53,'E&W'!$A$7:$P$69,14,0) -> 5769693 | H53: =VLOOKUP(B53,'E&W'!$A$7:$P$69,16,0) -> 4569720 | I53: =VLOOKUP(B53,'E&W'!$A$7:$AD$69,18,0) -> 4603336 | J53: =VLOOKUP(B53,'E&W'!$A$7:$AD$69,20,0) -> 4487642 | K53: =VLOOKUP(B53,'E&W'!$A$7:$AD$69,22,0) -> 3370619 | L53: =VLOOKUP(B53,'E&W'!$A$7:$AD$69,24,0) -> 3309831 | M53: =VLOOKUP(B53,'E&W'!$A$7:$AD$69,26,0) -> 2953696 | N53: =VLOOKUP(B53,'E&W'!$A$7:$AD$69,28,0) -> 2283843 | O53: =VLOOKUP(B53,'E&W'!$A$7:$AD$69,30,0) -> 3290400
A54: 25 | B54: 部品管理2課 | C54: 電気代 Electric | D54: =VLOOKUP(B55,'E&W'!$A$7:$P$69,7,0) -> 222773975 | E54: =VLOOKUP(B55,'E&W'!$A$7:$P$69,9,0) -> 235897731 | F54: =VLOOKUP(B55,'E&W'!$A$7:$P$69,11,0) -> 276218650 | G54: =VLOOKUP(B55,'E&W'!$A$7:$P$69,13,0) -> 280665744 | H54: =VLOOKUP(B55,'E&W'!$A$7:$P$69,15,0) -> 288220435 | I54: =VLOOKUP(B55,'E&W'!$A$7:$AD$69,17,0) -> 253851821 | J54: =VLOOKUP(B55,'E&W'!$A$7:$AD$69,19,0) -> 224748729 | K54: =VLOOKUP(B55,'E&W'!$A$7:$AD$69,21,0) -> 224101936 | L54: =VLOOKUP(B55,'E&W'!$A$7:$AD$69,23,0) -> 211605801 | M54: =VLOOKUP(B55,'E&W'!$A$7:$AD$69,25,0) -> 209306608 | N54: =VLOOKUP(B55,'E&W'!$A$7:$AD$69,27,0) -> 205844960 | O54: =VLOOKUP(B55,'E&W'!$A$7:$AD$69,29,0) -> 207775235
B55: 1412000103 | C55: 水道代 Water | D55: =VLOOKUP(B55,'E&W'!$A$7:$P$69,8,0) -> 7062281 | E55: =VLOOKUP(B55,'E&W'!$A$7:$P$69,10,0) -> 7663621 | F55: =VLOOKUP(B55,'E&W'!$A$7:$P$69,12,0) -> 9027907 | G55: =VLOOKUP(B55,'E&W'!$A$7:$P$69,14,0) -> 12661271 | H55: =VLOOKUP(B55,'E&W'!$A$7:$P$69,16,0) -> 10723007 | I55: =VLOOKUP(B55,'E&W'!$A$7:$AD$69,18,0) -> 10725773 | J55: =VLOOKUP(B55,'E&W'!$A$7:$AD$69,20,0) -> 10516495 | K55: =VLOOKUP(B55,'E&W'!$A$7:$AD$69,22,0) -> 7864778 | L55: =VLOOKUP(B55,'E&W'!$A$7:$AD$69,24,0) -> 7689506 | M55: =VLOOKUP(B55,'E&W'!$A$7:$AD$69,26,0) -> 6832286 | N55: =VLOOKUP(B55,'E&W'!$A$7:$AD$69,28,0) -> 5282828 | O55: =VLOOKUP(B55,'E&W'!$A$7:$AD$69,30,0) -> 7655215
A56: 26 | B56: 製品管理課 | C56: 電気代 Electric | D56: =VLOOKUP(B57,'E&W'!$A$7:$P$69,7,0) -> 163498803 | E56: =VLOOKUP(B57,'E&W'!$A$7:$P$69,9,0) -> 168181531 | F56: =VLOOKUP(B57,'E&W'!$A$7:$P$69,11,0) -> 221042029 | G56: =VLOOKUP(B57,'E&W'!$A$7:$P$69,13,0) -> 231291016 | H56: =VLOOKUP(B57,'E&W'!$A$7:$P$69,15,0) -> 237637802 | I56: =VLOOKUP(B57,'E&W'!$A$7:$AD$69,17,0) -> 214142546 | J56: =VLOOKUP(B57,'E&W'!$A$7:$AD$69,19,0) -> 184104738 | K56: =VLOOKUP(B57,'E&W'!$A$7:$AD$69,21,0) -> 181718754 | L56: =VLOOKUP(B57,'E&W'!$A$7:$AD$69,23,0) -> 153923936 | M56: =VLOOKUP(B57,'E&W'!$A$7:$AD$69,25,0) -> 140562218 | N56: =VLOOKUP(B57,'E&W'!$A$7:$AD$69,27,0) -> 139773745 | O56: =VLOOKUP(B57,'E&W'!$A$7:$AD$69,29,0) -> 142960935
B57: 1412000072 | C57: 水道代 Water | D57: =VLOOKUP(B57,'E&W'!$A$7:$P$69,8,0) -> 1559587 | E57: =VLOOKUP(B57,'E&W'!$A$7:$P$69,10,0) -> 1699464 | F57: =VLOOKUP(B57,'E&W'!$A$7:$P$69,12,0) -> 2010416 | G57: =VLOOKUP(B57,'E&W'!$A$7:$P$69,14,0) -> 2778000 | H57: =VLOOKUP(B57,'E&W'!$A$7:$P$69,16,0) -> 2397972 | I57: =VLOOKUP(B57,'E&W'!$A$7:$AD$69,18,0) -> 2393735 | J57: =VLOOKUP(B57,'E&W'!$A$7:$AD$69,20,0) -> 2357146 | K57: =VLOOKUP(B57,'E&W'!$A$7:$AD$69,22,0) -> 1770426 | L57: =VLOOKUP(B57,'E&W'!$A$7:$AD$69,24,0) -> 1705064 | M57: =VLOOKUP(B57,'E&W'!$A$7:$AD$69,26,0) -> 1521601 | N57: =VLOOKUP(B57,'E&W'!$A$7:$AD$69,28,0) -> 1176525 | O57: =VLOOKUP(B57,'E&W'!$A$7:$AD$69,30,0) -> 1678775
A58: 27 | B58: 物流管理課 | C58: 電気代 Electric | D58: =VLOOKUP(B59,'E&W'!$A$7:$P$69,7,0) -> 1207227 | E58: =VLOOKUP(B59,'E&W'!$A$7:$P$69,9,0) -> 948132 | F58: =VLOOKUP(B59,'E&W'!$A$7:$P$69,11,0) -> 872435 | G58: =VLOOKUP(B59,'E&W'!$A$7:$P$69,13,0) -> 922876 | H58: =VLOOKUP(B59,'E&W'!$A$7:$P$69,15,0) -> 972505 | I58: =VLOOKUP(B59,'E&W'!$A$7:$AD$69,17,0) -> 917728 | J58: =VLOOKUP(B59,'E&W'!$A$7:$AD$69,19,0) -> 831066 | K58: =VLOOKUP(B59,'E&W'!$A$7:$AD$69,21,0) -> 906144 | L58: =VLOOKUP(B59,'E&W'!$A$7:$AD$69,23,0) -> 1093877 | M58: =VLOOKUP(B59,'E&W'!$A$7:$AD$69,25,0) -> 1315241 | N58: =VLOOKUP(B59,'E&W'!$A$7:$AD$69,27,0) -> 1335202 | O58: =VLOOKUP(B59,'E&W'!$A$7:$AD$69,29,0) -> 1254067
B59: 1412000073 | C59: 水道代 Water | D59: =VLOOKUP(B59,'E&W'!$A$7:$P$69,8,0) -> 441393 | E59: =VLOOKUP(B59,'E&W'!$A$7:$P$69,10,0) -> 480980 | F59: =VLOOKUP(B59,'E&W'!$A$7:$P$69,12,0) -> 568986 | G59: =VLOOKUP(B59,'E&W'!$A$7:$P$69,14,0) -> 801346 | H59: =VLOOKUP(B59,'E&W'!$A$7:$P$69,16,0) -> 678671 | I59: =VLOOKUP(B59,'E&W'!$A$7:$AD$69,18,0) -> 690500 | J59: =VLOOKUP(B59,'E&W'!$A$7:$AD$69,20,0) -> 679946 | K59: =VLOOKUP(B59,'E&W'!$A$7:$AD$69,22,0) -> 510700 | L59: =VLOOKUP(B59,'E&W'!$A$7:$AD$69,24,0) -> 501490 | M59: =VLOOKUP(B59,'E&W'!$A$7:$AD$69,26,0) -> 447530 | N59: =VLOOKUP(B59,'E&W'!$A$7:$AD$69,28,0) -> 346037 | O59: =VLOOKUP(B59,'E&W'!$A$7:$AD$69,30,0) -> 503633
A60: 28 | B60: メカ製造技術1課 | C60: 電気代 Electric | D60: =VLOOKUP(B61,'E&W'!$A$7:$P$69,7,0) -> 932009 | E60: =VLOOKUP(B61,'E&W'!$A$7:$P$69,9,0) -> 1158252 | F60: =VLOOKUP(B61,'E&W'!$A$7:$P$69,11,0) -> 1702420 | G60: =VLOOKUP(B61,'E&W'!$A$7:$P$69,13,0) -> 2125161 | H60: =VLOOKUP(B61,'E&W'!$A$7:$P$69,15,0) -> 2211909 | I60: =VLOOKUP(B61,'E&W'!$A$7:$AD$69,17,0) -> 2026479 | J60: =VLOOKUP(B61,'E&W'!$A$7:$AD$69,19,0) -> 1790128 | K60: =VLOOKUP(B61,'E&W'!$A$7:$AD$69,21,0) -> 1500861 | L60: =VLOOKUP(B61,'E&W'!$A$7:$AD$69,23,0) -> 1070755 | M60: =VLOOKUP(B61,'E&W'!$A$7:$AD$69,25,0) -> 923989 | N60: =VLOOKUP(B61,'E&W'!$A$7:$AD$69,27,0) -> 842827 | O60: =VLOOKUP(B61,'E&W'!$A$7:$AD$69,29,0) -> 821816
B61: 1412000006 | C61: 水道代 Water | D61: =VLOOKUP(B61,'E&W'!$A$7:$P$69,8,0) -> 647376 | E61: =VLOOKUP(B61,'E&W'!$A$7:$P$69,10,0) -> 705438 | F61: =VLOOKUP(B61,'E&W'!$A$7:$P$69,12,0) -> 986242 | G61: =VLOOKUP(B61,'E&W'!$A$7:$P$69,14,0) -> 1442423 | H61: =VLOOKUP(B61,'E&W'!$A$7:$P$69,16,0) -> 1221608 | I61: =VLOOKUP(B61,'E&W'!$A$7:$AD$69,18,0) -> 1242901 | J61: =VLOOKUP(B61,'E&W'!$A$7:$AD$69,20,0) -> 1223902 | K61: =VLOOKUP(B61,'E&W'!$A$7:$AD$69,22,0) -> 919260 | L61: =VLOOKUP(B61,'E&W'!$A$7:$AD$69,24,0) -> 902681 | M61: =VLOOKUP(B61,'E&W'!$A$7:$AD$69,26,0) -> 835389 | N61: =VLOOKUP(B61,'E&W'!$A$7:$AD$69,28,0) -> 645935 | O61: =VLOOKUP(B61,'E&W'!$A$7:$AD$69,30,0) -> 940114
A62: 29 | B62: メカ製造技術2課 | C62: 電気代 Electric | D62: =VLOOKUP(B63,'E&W'!$A$7:$P$69,7,0) -> 906826 | E62: =VLOOKUP(B63,'E&W'!$A$7:$P$69,9,0) -> 1127690 | F62: =VLOOKUP(B63,'E&W'!$A$7:$P$69,11,0) -> 1581241 | G62: =VLOOKUP(B63,'E&W'!$A$7:$P$69,13,0) -> 1917798 | H62: =VLOOKUP(B63,'E&W'!$A$7:$P$69,15,0) -> 1996141 | I62: =VLOOKUP(B63,'E&W'!$A$7:$AD$69,17,0) -> 1836440 | J62: =VLOOKUP(B63,'E&W'!$A$7:$AD$69,19,0) -> 1626428 | K62: =VLOOKUP(B63,'E&W'!$A$7:$AD$69,21,0) -> 1364099 | L62: =VLOOKUP(B63,'E&W'!$A$7:$AD$69,23,0) -> 975745 | M62: =VLOOKUP(B63,'E&W'!$A$7:$AD$69,25,0) -> 825052 | N62: =VLOOKUP(B63,'E&W'!$A$7:$AD$69,27,0) -> 748518 | O62: =VLOOKUP(B63,'E&W'!$A$7:$AD$69,29,0) -> 730912
B63: 1412000089 | C63: 水道代 Water | D63: =VLOOKUP(B63,'E&W'!$A$7:$P$69,8,0) -> 617950 | E63: =VLOOKUP(B63,'E&W'!$A$7:$P$69,10,0) -> 673373 | F63: =VLOOKUP(B63,'E&W'!$A$7:$P$69,12,0) -> 872445 | G63: =VLOOKUP(B63,'E&W'!$A$7:$P$69,14,0) -> 1228731 | H63: =VLOOKUP(B63,'E&W'!$A$7:$P$69,16,0) -> 1040629 | I63: =VLOOKUP(B63,'E&W'!$A$7:$AD$69,18,0) -> 1058767 | J63: =VLOOKUP(B63,'E&W'!$A$7:$AD$69,20,0) -> 1042584 | K63: =VLOOKUP(B63,'E&W'!$A$7:$AD$69,22,0) -> 783073 | L63: =VLOOKUP(B63,'E&W'!$A$7:$AD$69,24,0) -> 768951 | M63: =VLOOKUP(B63,'E&W'!$A$7:$AD$69,26,0) -> 686212 | N63: =VLOOKUP(B63,'E&W'!$A$7:$AD$69,28,0) -> 530590 | O63: =VLOOKUP(B63,'E&W'!$A$7:$AD$69,30,0) -> 772237
A64: 30 | B64: 電気製造技術課 | C64: 電気代 Electric | D64: =VLOOKUP(B65,'E&W'!$A$7:$P$69,7,0) -> 1577160 | E64: =VLOOKUP(B65,'E&W'!$A$7:$P$69,9,0) -> 2053287 | F64: =VLOOKUP(B65,'E&W'!$A$7:$P$69,11,0) -> 2791574 | G64: =VLOOKUP(B65,'E&W'!$A$7:$P$69,13,0) -> 3290266 | H64: =VLOOKUP(B65,'E&W'!$A$7:$P$69,15,0) -> 3419370 | I64: =VLOOKUP(B65,'E&W'!$A$7:$AD$69,17,0) -> 3270194 | J64: =VLOOKUP(B65,'E&W'!$A$7:$AD$69,19,0) -> 2959172 | K64: =VLOOKUP(B65,'E&W'!$A$7:$AD$69,21,0) -> 2460327 | L64: =VLOOKUP(B65,'E&W'!$A$7:$AD$69,23,0) -> 1758044 | M64: =VLOOKUP(B65,'E&W'!$A$7:$AD$69,25,0) -> 1450135 | N64: =VLOOKUP(B65,'E&W'!$A$7:$AD$69,27,0) -> 1247404 | O64: =VLOOKUP(B65,'E&W'!$A$7:$AD$69,29,0) -> 1203521
B65: 1412000040 | C65: 水道代 Water | D65: =VLOOKUP(B65,'E&W'!$A$7:$P$69,8,0) -> 529671 | E65: =VLOOKUP(B65,'E&W'!$A$7:$P$69,10,0) -> 577177 | F65: =VLOOKUP(B65,'E&W'!$A$7:$P$69,12,0) -> 682783 | G65: =VLOOKUP(B65,'E&W'!$A$7:$P$69,14,0) -> 1015039 | H65: =VLOOKUP(B65,'E&W'!$A$7:$P$69,16,0) -> 859650 | I65: =VLOOKUP(B65,'E&W'!$A$7:$AD$69,18,0) -> 874634 | J65: =VLOOKUP(B65,'E&W'!$A$7:$AD$69,20,0) -> 861265 | K65: =VLOOKUP(B65,'E&W'!$A$7:$AD$69,22,0) -> 646887 | L65: =VLOOKUP(B65,'E&W'!$A$7:$AD$69,24,0) -> 635220 | M65: =VLOOKUP(B65,'E&W'!$A$7:$AD$69,26,0) -> 566871 | N65: =VLOOKUP(B65,'E&W'!$A$7:$AD$69,28,0) -> 438313 | O65: =VLOOKUP(B65,'E&W'!$A$7:$AD$69,30,0) -> 637935
A66: 31 | B66: 製造システム開発課 | C66: 電気代 Electric | D66: =VLOOKUP(B67,'E&W'!$A$7:$P$69,7,0) -> 501782 | E66: =VLOOKUP(B67,'E&W'!$A$7:$P$69,9,0) -> 636813 | F66: =VLOOKUP(B67,'E&W'!$A$7:$P$69,11,0) -> 857224 | G66: =VLOOKUP(B67,'E&W'!$A$7:$P$69,13,0) -> 1031307 | H66: =VLOOKUP(B67,'E&W'!$A$7:$P$69,15,0) -> 1072257 | I66: =VLOOKUP(B67,'E&W'!$A$7:$AD$69,17,0) -> 996110 | J66: =VLOOKUP(B67,'E&W'!$A$7:$AD$69,19,0) -> 886494 | K66: =VLOOKUP(B67,'E&W'!$A$7:$AD$69,21,0) -> 738237 | L66: =VLOOKUP(B67,'E&W'!$A$7:$AD$69,23,0) -> 522626 | M66: =VLOOKUP(B67,'E&W'!$A$7:$AD$69,25,0) -> 432496 | N66: =VLOOKUP(B67,'E&W'!$A$7:$AD$69,27,0) -> 385287 | O66: =VLOOKUP(B67,'E&W'!$A$7:$AD$69,29,0) -> 371606
B67: 1412000039 | C67: 水道代 Water | D67: =VLOOKUP(B67,'E&W'!$A$7:$P$69,8,0) -> 323688 | E67: =VLOOKUP(B67,'E&W'!$A$7:$P$69,10,0) -> 352719 | F67: =VLOOKUP(B67,'E&W'!$A$7:$P$69,12,0) -> 417256 | G67: =VLOOKUP(B67,'E&W'!$A$7:$P$69,14,0) -> 587654 | H67: =VLOOKUP(B67,'E&W'!$A$7:$P$69,16,0) -> 497692 | I67: =VLOOKUP(B67,'E&W'!$A$7:$AD$69,18,0) -> 506367 | J67: =VLOOKUP(B67,'E&W'!$A$7:$AD$69,20,0) -> 498627 | K67: =VLOOKUP(B67,'E&W'!$A$7:$AD$69,22,0) -> 374513 | L67: =VLOOKUP(B67,'E&W'!$A$7:$AD$69,24,0) -> 367759 | M67: =VLOOKUP(B67,'E&W'!$A$7:$AD$69,26,0) -> 328188 | N67: =VLOOKUP(B67,'E&W'!$A$7:$AD$69,28,0) -> 253760 | O67: =VLOOKUP(B67,'E&W'!$A$7:$AD$69,30,0) -> 369331
A68: 32 | B68: 製造技術管理課 | C68: 電気代 Electric | D68: =VLOOKUP(B69,'E&W'!$A$7:$P$69,7,0) -> 319390 | E68: =VLOOKUP(B69,'E&W'!$A$7:$P$69,9,0) -> 505800 | F68: =VLOOKUP(B69,'E&W'!$A$7:$P$69,11,0) -> 710738 | G68: =VLOOKUP(B69,'E&W'!$A$7:$P$69,13,0) -> 859879 | H68: =VLOOKUP(B69,'E&W'!$A$7:$P$69,15,0) -> 890108 | I68: =VLOOKUP(B69,'E&W'!$A$7:$AD$69,17,0) -> 834166 | J68: =VLOOKUP(B69,'E&W'!$A$7:$AD$69,19,0) -> 743293 | K68: =VLOOKUP(B69,'E&W'!$A$7:$AD$69,21,0) -> 600844 | L68: =VLOOKUP(B69,'E&W'!$A$7:$AD$69,23,0) -> 400293 | M68: =VLOOKUP(B69,'E&W'!$A$7:$AD$69,25,0) -> 297540 | N68: =VLOOKUP(B69,'E&W'!$A$7:$AD$69,27,0) -> 251594 | O68: =VLOOKUP(B69,'E&W'!$A$7:$AD$69,29,0) -> 224588
B69: 14120000AB | C69: 水道代 Water | D69: =VLOOKUP(B69,'E&W'!$A$7:$P$69,8,0) -> 205983 | E69: =VLOOKUP(B69,'E&W'!$A$7:$P$69,10,0) -> 288588 | F69: =VLOOKUP(B69,'E&W'!$A$7:$P$69,12,0) -> 341391 | G69: =VLOOKUP(B69,'E&W'!$A$7:$P$69,14,0) -> 480808 | H69: =VLOOKUP(B69,'E&W'!$A$7:$P$69,16,0) -> 407203 | I69: =VLOOKUP(B69,'E&W'!$A$7:$AD$69,18,0) -> 414300 | J69: =VLOOKUP(B69,'E&W'!$A$7:$AD$69,20,0) -> 407967 | K69: =VLOOKUP(B69,'E&W'!$A$7:$AD$69,22,0) -> 306420 | L69: =VLOOKUP(B69,'E&W'!$A$7:$AD$69,24,0) -> 300894 | M69: =VLOOKUP(B69,'E&W'!$A$7:$AD$69,26,0) -> 268518 | N69: =VLOOKUP(B69,'E&W'!$A$7:$AD$69,28,0) -> 207622 | O69: =VLOOKUP(B69,'E&W'!$A$7:$AD$69,30,0) -> 302180
A70: 33 | B70: 部品検査課 1 | C70: 電気代 Electric | D70: =VLOOKUP(B71,'E&W'!$A$7:$P$69,7,0) -> 5044904 | E70: =VLOOKUP(B71,'E&W'!$A$7:$P$69,9,0) -> 6313112 | F70: =VLOOKUP(B71,'E&W'!$A$7:$P$69,11,0) -> 9261809 | G70: =VLOOKUP(B71,'E&W'!$A$7:$P$69,13,0) -> 11074826 | H70: =VLOOKUP(B71,'E&W'!$A$7:$P$69,15,0) -> 11388031 | I70: =VLOOKUP(B71,'E&W'!$A$7:$AD$69,17,0) -> 11315123 | J70: =VLOOKUP(B71,'E&W'!$A$7:$AD$69,19,0) -> 9060997 | K70: =VLOOKUP(B71,'E&W'!$A$7:$AD$69,21,0) -> 8158610 | L70: =VLOOKUP(B71,'E&W'!$A$7:$AD$69,23,0) -> 5910096 | M70: =VLOOKUP(B71,'E&W'!$A$7:$AD$69,25,0) -> 5244116 | N70: =VLOOKUP(B71,'E&W'!$A$7:$AD$69,27,0) -> 5358378 | O70: =VLOOKUP(B71,'E&W'!$A$7:$AD$69,29,0) -> 4380891
B71: 1412000013 | C71: 水道代 Water | D71: =VLOOKUP(B71,'E&W'!$A$7:$P$69,8,0) -> 2972043 | E71: =VLOOKUP(B71,'E&W'!$A$7:$P$69,10,0) -> 3238602 | F71: =VLOOKUP(B71,'E&W'!$A$7:$P$69,12,0) -> 3831171 | G71: =VLOOKUP(B71,'E&W'!$A$7:$P$69,14,0) -> 5662847 | H71: =VLOOKUP(B71,'E&W'!$A$7:$P$69,16,0) -> 4795944 | I71: =VLOOKUP(B71,'E&W'!$A$7:$AD$69,18,0) -> 4879536 | J71: =VLOOKUP(B71,'E&W'!$A$7:$AD$69,20,0) -> 4804951 | K71: =VLOOKUP(B71,'E&W'!$A$7:$AD$69,22,0) -> 3608946 | L71: =VLOOKUP(B71,'E&W'!$A$7:$AD$69,24,0) -> 3543859 | M71: =VLOOKUP(B71,'E&W'!$A$7:$AD$69,26,0) -> 3162543 | N71: =VLOOKUP(B71,'E&W'!$A$7:$AD$69,28,0) -> 2445326 | O71: =VLOOKUP(B71,'E&W'!$A$7:$AD$69,30,0) -> 3559004
A72: 34 | B72: 部品検査課 2 | C72: 電気代 Electric | D72: =VLOOKUP(B73,'E&W'!$A$7:$P$69,7,0) -> 5597890 | E72: =VLOOKUP(B73,'E&W'!$A$7:$P$69,9,0) -> 5467007 | F72: =VLOOKUP(B73,'E&W'!$A$7:$P$69,11,0) -> 6010480 | G72: =VLOOKUP(B73,'E&W'!$A$7:$P$69,13,0) -> 6599482 | H72: =VLOOKUP(B73,'E&W'!$A$7:$P$69,15,0) -> 7031358 | I72: =VLOOKUP(B73,'E&W'!$A$7:$AD$69,17,0) -> 6684089 | J72: =VLOOKUP(B73,'E&W'!$A$7:$AD$69,19,0) -> 5753478 | K72: =VLOOKUP(B73,'E&W'!$A$7:$AD$69,21,0) -> 5842593 | L72: =VLOOKUP(B73,'E&W'!$A$7:$AD$69,23,0) -> 5925955 | M72: =VLOOKUP(B73,'E&W'!$A$7:$AD$69,25,0) -> 5108741 | N72: =VLOOKUP(B73,'E&W'!$A$7:$AD$69,27,0) -> 4249388 | O72: =VLOOKUP(B73,'E&W'!$A$7:$AD$69,29,0) -> 4173923
B73: 1412000092 | C73: 水道代 Water | D73: =VLOOKUP(B73,'E&W'!$A$7:$P$69,8,0) -> 1353604 | E73: =VLOOKUP(B73,'E&W'!$A$7:$P$69,10,0) -> 1475007 | F73: =VLOOKUP(B73,'E&W'!$A$7:$P$69,12,0) -> 1744890 | G73: =VLOOKUP(B73,'E&W'!$A$7:$P$69,14,0) -> 2564308 | H73: =VLOOKUP(B73,'E&W'!$A$7:$P$69,16,0) -> 2171748 | I73: =VLOOKUP(B73,'E&W'!$A$7:$AD$69,18,0) -> 2209601 | J73: =VLOOKUP(B73,'E&W'!$A$7:$AD$69,20,0) -> 2175827 | K73: =VLOOKUP(B73,'E&W'!$A$7:$AD$69,22,0) -> 1634240 | L73: =VLOOKUP(B73,'E&W'!$A$7:$AD$69,24,0) -> 1604766 | M73: =VLOOKUP(B73,'E&W'!$A$7:$AD$69,26,0) -> 1432095 | N73: =VLOOKUP(B73,'E&W'!$A$7:$AD$69,28,0) -> 1107318 | O73: =VLOOKUP(B73,'E&W'!$A$7:$AD$69,30,0) -> 1611624
A74: 35 | B74: 外製管理課 | C74: 電気代 Electric | D74: =VLOOKUP(B75,'E&W'!$A$7:$P$69,7,0) -> 1092855 | E74: =VLOOKUP(B75,'E&W'!$A$7:$P$69,9,0) -> 1399265 | F74: =VLOOKUP(B75,'E&W'!$A$7:$P$69,11,0) -> 2231952 | G74: =VLOOKUP(B75,'E&W'!$A$7:$P$69,13,0) -> 3075616 | H74: =VLOOKUP(B75,'E&W'!$A$7:$P$69,15,0) -> 3143751 | I74: =VLOOKUP(B75,'E&W'!$A$7:$AD$69,17,0) -> 2957092 | J74: =VLOOKUP(B75,'E&W'!$A$7:$AD$69,19,0) -> 2604116 | K74: =VLOOKUP(B75,'E&W'!$A$7:$AD$69,21,0) -> 2123445 | L74: =VLOOKUP(B75,'E&W'!$A$7:$AD$69,23,0) -> 1339392 | M74: =VLOOKUP(B75,'E&W'!$A$7:$AD$69,25,0) -> 1473205 | N74: =VLOOKUP(B75,'E&W'!$A$7:$AD$69,27,0) -> 1479460 | O74: =VLOOKUP(B75,'E&W'!$A$7:$AD$69,29,0) -> 1155700
B75: 1412000035 | C75: 水道代 Water | D75: =VLOOKUP(B75,'E&W'!$A$7:$P$69,8,0) -> 765080 | E75: =VLOOKUP(B75,'E&W'!$A$7:$P$69,10,0) -> 897830 | F75: =VLOOKUP(B75,'E&W'!$A$7:$P$69,12,0) -> 1062107 | G75: =VLOOKUP(B75,'E&W'!$A$7:$P$69,14,0) -> 1495846 | H75: =VLOOKUP(B75,'E&W'!$A$7:$P$69,16,0) -> 1266853 | I75: =VLOOKUP(B75,'E&W'!$A$7:$AD$69,18,0) -> 1288934 | J75: =VLOOKUP(B75,'E&W'!$A$7:$AD$69,20,0) -> 1269232 | K75: =VLOOKUP(B75,'E&W'!$A$7:$AD$69,22,0) -> 953306 | L75: =VLOOKUP(B75,'E&W'!$A$7:$AD$69,24,0) -> 936114 | M75: =VLOOKUP(B75,'E&W'!$A$7:$AD$69,26,0) -> 835389 | N75: =VLOOKUP(B75,'E&W'!$A$7:$AD$69,28,0) -> 645935 | O75: =VLOOKUP(B75,'E&W'!$A$7:$AD$69,30,0) -> 940114
A76: 36 | B76: 生産技術1課 | C76: 電気代 Electric | D76: =VLOOKUP(B77,'E&W'!$A$7:$P$69,7,0) -> 1921872 | E76: =VLOOKUP(B77,'E&W'!$A$7:$P$69,9,0) -> 2480640 | F76: =VLOOKUP(B77,'E&W'!$A$7:$P$69,11,0) -> 3515599 | G76: =VLOOKUP(B77,'E&W'!$A$7:$P$69,13,0) -> 4147708 | H76: =VLOOKUP(B77,'E&W'!$A$7:$P$69,15,0) -> 4300099 | I76: =VLOOKUP(B77,'E&W'!$A$7:$AD$69,17,0) -> 4204373 | J76: =VLOOKUP(B77,'E&W'!$A$7:$AD$69,19,0) -> 3282459 | K76: =VLOOKUP(B77,'E&W'!$A$7:$AD$69,21,0) -> 2945590 | L76: =VLOOKUP(B77,'E&W'!$A$7:$AD$69,23,0) -> 2222225 | M76: =VLOOKUP(B77,'E&W'!$A$7:$AD$69,25,0) -> 1743850 | N76: =VLOOKUP(B77,'E&W'!$A$7:$AD$69,27,0) -> 1734857 | O76: =VLOOKUP(B77,'E&W'!$A$7:$AD$69,29,0) -> 1538814
B77: 1412000016 | C77: 水道代 Water | D77: =VLOOKUP(B77,'E&W'!$A$7:$P$69,8,0) -> 588523 | E77: =VLOOKUP(B77,'E&W'!$A$7:$P$69,10,0) -> 673373 | F77: =VLOOKUP(B77,'E&W'!$A$7:$P$69,12,0) -> 796580 | G77: =VLOOKUP(B77,'E&W'!$A$7:$P$69,14,0) -> 1121885 | H77: =VLOOKUP(B77,'E&W'!$A$7:$P$69,16,0) -> 950140 | I77: =VLOOKUP(B77,'E&W'!$A$7:$AD$69,18,0) -> 966701 | J77: =VLOOKUP(B77,'E&W'!$A$7:$AD$69,20,0) -> 951924 | K77: =VLOOKUP(B77,'E&W'!$A$7:$AD$69,22,0) -> 714980 | L77: =VLOOKUP(B77,'E&W'!$A$7:$AD$69,24,0) -> 702085 | M77: =VLOOKUP(B77,'E&W'!$A$7:$AD$69,26,0) -> 626542 | N77: =VLOOKUP(B77,'E&W'!$A$7:$AD$69,28,0) -> 484451 | O77: =VLOOKUP(B77,'E&W'!$A$7:$AD$69,30,0) -> 705086
A78: 37 | B78: 生産技術2課 | C78: 電気代 Electric | D78: =VLOOKUP(B79,'E&W'!$A$7:$P$69,7,0) -> 1580420 | E78: =VLOOKUP(B79,'E&W'!$A$7:$P$69,9,0) -> 2045116 | F78: =VLOOKUP(B79,'E&W'!$A$7:$P$69,11,0) -> 2889434 | G78: =VLOOKUP(B79,'E&W'!$A$7:$P$69,13,0) -> 3306614 | H78: =VLOOKUP(B79,'E&W'!$A$7:$P$69,15,0) -> 3458336 | I78: =VLOOKUP(B79,'E&W'!$A$7:$AD$69,17,0) -> 3451986 | J78: =VLOOKUP(B79,'E&W'!$A$7:$AD$69,19,0) -> 2690258 | K78: =VLOOKUP(B79,'E&W'!$A$7:$AD$69,21,0) -> 2423945 | L78: =VLOOKUP(B79,'E&W'!$A$7:$AD$69,23,0) -> 1825765 | M78: =VLOOKUP(B79,'E&W'!$A$7:$AD$69,25,0) -> 1423782 | N78: =VLOOKUP(B79,'E&W'!$A$7:$AD$69,27,0) -> 1430877 | O78: =VLOOKUP(B79,'E&W'!$A$7:$AD$69,29,0) -> 1267888
B79: 1412000069 | C79: 水道代 Water | D79: =VLOOKUP(B79,'E&W'!$A$7:$P$69,8,0) -> 382540 | E79: =VLOOKUP(B79,'E&W'!$A$7:$P$69,10,0) -> 448915 | F79: =VLOOKUP(B79,'E&W'!$A$7:$P$69,12,0) -> 531053 | G79: =VLOOKUP(B79,'E&W'!$A$7:$P$69,14,0) -> 747923 | H79: =VLOOKUP(B79,'E&W'!$A$7:$P$69,16,0) -> 633427 | I79: =VLOOKUP(B79,'E&W'!$A$7:$AD$69,18,0) -> 644467 | J79: =VLOOKUP(B79,'E&W'!$A$7:$AD$69,20,0) -> 634616 | K79: =VLOOKUP(B79,'E&W'!$A$7:$AD$69,22,0) -> 476653 | L79: =VLOOKUP(B79,'E&W'!$A$7:$AD$69,24,0) -> 468057 | M79: =VLOOKUP(B79,'E&W'!$A$7:$AD$69,26,0) -> 417694 | N79: =VLOOKUP(B79,'E&W'!$A$7:$AD$69,28,0) -> 322968 | O79: =VLOOKUP(B79,'E&W'!$A$7:$AD$69,30,0) -> 470057
A80: 38 | B80: 生産技術3課 | C80: 電気代 Electric | D80: =VLOOKUP(B81,'E&W'!$A$7:$P$69,7,0) -> 1024356 | E80: =VLOOKUP(B81,'E&W'!$A$7:$P$69,9,0) -> 1306572 | F80: =VLOOKUP(B81,'E&W'!$A$7:$P$69,11,0) -> 1878495 | G80: =VLOOKUP(B81,'E&W'!$A$7:$P$69,13,0) -> 2643439 | H80: =VLOOKUP(B81,'E&W'!$A$7:$P$69,15,0) -> 2645540 | I80: =VLOOKUP(B81,'E&W'!$A$7:$AD$69,17,0) -> 2364643 | J80: =VLOOKUP(B81,'E&W'!$A$7:$AD$69,19,0) -> 1861202 | K80: =VLOOKUP(B81,'E&W'!$A$7:$AD$69,21,0) -> 1639454 | L80: =VLOOKUP(B81,'E&W'!$A$7:$AD$69,23,0) -> 1246019 | M80: =VLOOKUP(B81,'E&W'!$A$7:$AD$69,25,0) -> 1005928 | N80: =VLOOKUP(B81,'E&W'!$A$7:$AD$69,27,0) -> 955367 | O80: =VLOOKUP(B81,'E&W'!$A$7:$AD$69,29,0) -> 851481
B81: 1412000084 | C81: 水道代 Water | D81: =VLOOKUP(B81,'E&W'!$A$7:$P$69,8,0) -> 617950 | E81: =VLOOKUP(B81,'E&W'!$A$7:$P$69,10,0) -> 673373 | F81: =VLOOKUP(B81,'E&W'!$A$7:$P$69,12,0) -> 796580 | G81: =VLOOKUP(B81,'E&W'!$A$7:$P$69,14,0) -> 1175308 | H81: =VLOOKUP(B81,'E&W'!$A$7:$P$69,16,0) -> 995385 | I81: =VLOOKUP(B81,'E&W'!$A$7:$AD$69,18,0) -> 1012734 | J81: =VLOOKUP(B81,'E&W'!$A$7:$AD$69,20,0) -> 997254 | K81: =VLOOKUP(B81,'E&W'!$A$7:$AD$69,22,0) -> 749026 | L81: =VLOOKUP(B81,'E&W'!$A$7:$AD$69,24,0) -> 735518 | M81: =VLOOKUP(B81,'E&W'!$A$7:$AD$69,26,0) -> 656377 | N81: =VLOOKUP(B81,'E&W'!$A$7:$AD$69,28,0) -> 507521 | O81: =VLOOKUP(B81,'E&W'!$A$7:$AD$69,30,0) -> 738661
A82: 39 | B82: MD1課 | C82: 電気代 Electric | D82: =VLOOKUP(B83,'E&W'!$A$7:$P$69,7,0) -> 1417251 | E82: =VLOOKUP(B83,'E&W'!$A$7:$P$69,9,0) -> 1478138 | F82: =VLOOKUP(B83,'E&W'!$A$7:$P$69,11,0) -> 1309787 | G82: =VLOOKUP(B83,'E&W'!$A$7:$P$69,13,0) -> 1409955 | H82: =VLOOKUP(B83,'E&W'!$A$7:$P$69,15,0) -> 1525646 | I82: =VLOOKUP(B83,'E&W'!$A$7:$AD$69,17,0) -> 1694852 | J82: =VLOOKUP(B83,'E&W'!$A$7:$AD$69,19,0) -> 1202793 | K82: =VLOOKUP(B83,'E&W'!$A$7:$AD$69,21,0) -> 1389474 | L82: =VLOOKUP(B83,'E&W'!$A$7:$AD$69,23,0) -> 1348038 | M82: =VLOOKUP(B83,'E&W'!$A$7:$AD$69,25,0) -> 1426880 | N82: =VLOOKUP(B83,'E&W'!$A$7:$AD$69,27,0) -> 1491615 | O82: =VLOOKUP(B83,'E&W'!$A$7:$AD$69,29,0) -> 1626617
B83: 1412000050 | C83: 水道代 Water | D83: =VLOOKUP(B83,'E&W'!$A$7:$P$69,8,0) -> 441393 | E83: =VLOOKUP(B83,'E&W'!$A$7:$P$69,10,0) -> 480980 | F83: =VLOOKUP(B83,'E&W'!$A$7:$P$69,12,0) -> 568986 | G83: =VLOOKUP(B83,'E&W'!$A$7:$P$69,14,0) -> 801346 | H83: =VLOOKUP(B83,'E&W'!$A$7:$P$69,16,0) -> 678671 | I83: =VLOOKUP(B83,'E&W'!$A$7:$AD$69,18,0) -> 828601 | J83: =VLOOKUP(B83,'E&W'!$A$7:$AD$69,20,0) -> 770605 | K83: =VLOOKUP(B83,'E&W'!$A$7:$AD$69,22,0) -> 578793 | L83: =VLOOKUP(B83,'E&W'!$A$7:$AD$69,24,0) -> 568355 | M83: =VLOOKUP(B83,'E&W'!$A$7:$AD$69,26,0) -> 507200 | N83: =VLOOKUP(B83,'E&W'!$A$7:$AD$69,28,0) -> 392175 | O83: =VLOOKUP(B83,'E&W'!$A$7:$AD$69,30,0) -> 570784
A84: 40 | B84: MD2課 | C84: 電気代 Electric | D84: =VLOOKUP(B85,'E&W'!$A$7:$P$69,7,0) -> 1068206 | E84: =VLOOKUP(B85,'E&W'!$A$7:$P$69,9,0) -> 1119702 | F84: =VLOOKUP(B85,'E&W'!$A$7:$P$69,11,0) -> 998803 | G84: =VLOOKUP(B85,'E&W'!$A$7:$P$69,13,0) -> 1077621 | H84: =VLOOKUP(B85,'E&W'!$A$7:$P$69,15,0) -> 1167101 | I84: =VLOOKUP(B85,'E&W'!$A$7:$AD$69,17,0) -> 1115409 | J84: =VLOOKUP(B85,'E&W'!$A$7:$AD$69,19,0) -> 827017 | K84: =VLOOKUP(B85,'E&W'!$A$7:$AD$69,21,0) -> 948786 | L84: =VLOOKUP(B85,'E&W'!$A$7:$AD$69,23,0) -> 920424 | M84: =VLOOKUP(B85,'E&W'!$A$7:$AD$69,25,0) -> 965608 | N84: =VLOOKUP(B85,'E&W'!$A$7:$AD$69,27,0) -> 1003076 | O84: =VLOOKUP(B85,'E&W'!$A$7:$AD$69,29,0) -> 1097005
B85: 1412000077 | C85: 水道代 Water | D85: =VLOOKUP(B85,'E&W'!$A$7:$P$69,8,0) -> 323688 | E85: =VLOOKUP(B85,'E&W'!$A$7:$P$69,10,0) -> 352719 | F85: =VLOOKUP(B85,'E&W'!$A$7:$P$69,12,0) -> 417256 | G85: =VLOOKUP(B85,'E&W'!$A$7:$P$69,14,0) -> 587654 | H85: =VLOOKUP(B85,'E&W'!$A$7:$P$69,16,0) -> 497692 | I85: =VLOOKUP(B85,'E&W'!$A$7:$AD$69,18,0) -> 506367 | J85: =VLOOKUP(B85,'E&W'!$A$7:$AD$69,20,0) -> 498627 | K85: =VLOOKUP(B85,'E&W'!$A$7:$AD$69,22,0) -> 374513 | L85: =VLOOKUP(B85,'E&W'!$A$7:$AD$69,24,0) -> 367759 | M85: =VLOOKUP(B85,'E&W'!$A$7:$AD$69,26,0) -> 328188 | N85: =VLOOKUP(B85,'E&W'!$A$7:$AD$69,28,0) -> 253760 | O85: =VLOOKUP(B85,'E&W'!$A$7:$AD$69,30,0) -> 369331
A86: 41 | B86: MD3課 | C86: 電気代 Electric | D86: =VLOOKUP(B87,'E&W'!$A$7:$P$69,7,0) -> 872613 | E86: =VLOOKUP(B87,'E&W'!$A$7:$P$69,9,0) -> 896090 | F86: =VLOOKUP(B87,'E&W'!$A$7:$P$69,11,0) -> 777461 | G86: =VLOOKUP(B87,'E&W'!$A$7:$P$69,13,0) -> 830835 | H86: =VLOOKUP(B87,'E&W'!$A$7:$P$69,15,0) -> 896363 | I86: =VLOOKUP(B87,'E&W'!$A$7:$AD$69,17,0) -> 827775 | J86: =VLOOKUP(B87,'E&W'!$A$7:$AD$69,19,0) -> 626293 | K86: =VLOOKUP(B87,'E&W'!$A$7:$AD$69,21,0) -> 734479 | L86: =VLOOKUP(B87,'E&W'!$A$7:$AD$69,23,0) -> 712690 | M86: =VLOOKUP(B87,'E&W'!$A$7:$AD$69,25,0) -> 768787 | N86: =VLOOKUP(B87,'E&W'!$A$7:$AD$69,27,0) -> 814231 | O86: =VLOOKUP(B87,'E&W'!$A$7:$AD$69,29,0) -> 794418
B87: 1412000083 | C87: 水道代 Water | D87: =VLOOKUP(B87,'E&W'!$A$7:$P$69,8,0) -> 294262 | E87: =VLOOKUP(B87,'E&W'!$A$7:$P$69,10,0) -> 320654 | F87: =VLOOKUP(B87,'E&W'!$A$7:$P$69,12,0) -> 379324 | G87: =VLOOKUP(B87,'E&W'!$A$7:$P$69,14,0) -> 534231 | H87: =VLOOKUP(B87,'E&W'!$A$7:$P$69,16,0) -> 452448 | I87: =VLOOKUP(B87,'E&W'!$A$7:$AD$69,18,0) -> 460334 | J87: =VLOOKUP(B87,'E&W'!$A$7:$AD$69,20,0) -> 453297 | K87: =VLOOKUP(B87,'E&W'!$A$7:$AD$69,22,0) -> 340467 | L87: =VLOOKUP(B87,'E&W'!$A$7:$AD$69,24,0) -> 334326 | M87: =VLOOKUP(B87,'E&W'!$A$7:$AD$69,26,0) -> 298353 | N87: =VLOOKUP(B87,'E&W'!$A$7:$AD$69,28,0) -> 230691 | O87: =VLOOKUP(B87,'E&W'!$A$7:$AD$69,30,0) -> 302180
A88: 42 | B88: MD4課 | C88: 電気代 Electric | D88: =VLOOKUP(B89,'E&W'!$A$7:$P$69,7,0) -> 872613 | E88: =VLOOKUP(B89,'E&W'!$A$7:$P$69,9,0) -> 896090 | F88: =VLOOKUP(B89,'E&W'!$A$7:$P$69,11,0) -> 777461 | G88: =VLOOKUP(B89,'E&W'!$A$7:$P$69,13,0) -> 913918 | H88: =VLOOKUP(B89,'E&W'!$A$7:$P$69,15,0) -> 985999 | I88: =VLOOKUP(B89,'E&W'!$A$7:$AD$69,17,0) -> 910552 | J88: =VLOOKUP(B89,'E&W'!$A$7:$AD$69,19,0) -> 688922 | K88: =VLOOKUP(B89,'E&W'!$A$7:$AD$69,21,0) -> 807927 | L88: =VLOOKUP(B89,'E&W'!$A$7:$AD$69,23,0) -> 783959 | M88: =VLOOKUP(B89,'E&W'!$A$7:$AD$69,25,0) -> 845665 | N88: =VLOOKUP(B89,'E&W'!$A$7:$AD$69,27,0) -> 895654 | O88: =VLOOKUP(B89,'E&W'!$A$7:$AD$69,29,0) -> 970956
B89: 1412000099 | C89: 水道代 Water | D89: =VLOOKUP(B89,'E&W'!$A$7:$P$69,8,0) -> 294262 | E89: =VLOOKUP(B89,'E&W'!$A$7:$P$69,10,0) -> 320654 | F89: =VLOOKUP(B89,'E&W'!$A$7:$P$69,12,0) -> 379324 | G89: =VLOOKUP(B89,'E&W'!$A$7:$P$69,14,0) -> 587654 | H89: =VLOOKUP(B89,'E&W'!$A$7:$P$69,16,0) -> 497692 | I89: =VLOOKUP(B89,'E&W'!$A$7:$AD$69,18,0) -> 506367 | J89: =VLOOKUP(B89,'E&W'!$A$7:$AD$69,20,0) -> 498627 | K89: =VLOOKUP(B89,'E&W'!$A$7:$AD$69,22,0) -> 374513 | L89: =VLOOKUP(B89,'E&W'!$A$7:$AD$69,24,0) -> 367759 | M89: =VLOOKUP(B89,'E&W'!$A$7:$AD$69,26,0) -> 328188 | N89: =VLOOKUP(B89,'E&W'!$A$7:$AD$69,28,0) -> 253760 | O89: =VLOOKUP(B89,'E&W'!$A$7:$AD$69,30,0) -> 369331
A90: 43 | B90: MD5課 | C90: 電気代 Electric | D90: =VLOOKUP(B91,'E&W'!$A$7:$P$69,7,0) -> 698091 | E90: =VLOOKUP(B91,'E&W'!$A$7:$P$69,9,0) -> 716872 | F90: =VLOOKUP(B91,'E&W'!$A$7:$P$69,11,0) -> 621969 | G90: =VLOOKUP(B91,'E&W'!$A$7:$P$69,13,0) -> 664668 | H90: =VLOOKUP(B91,'E&W'!$A$7:$P$69,15,0) -> 717090 | I90: =VLOOKUP(B91,'E&W'!$A$7:$AD$69,17,0) -> 662220 | J90: =VLOOKUP(B91,'E&W'!$A$7:$AD$69,19,0) -> 501034 | K90: =VLOOKUP(B91,'E&W'!$A$7:$AD$69,21,0) -> 587583 | L90: =VLOOKUP(B91,'E&W'!$A$7:$AD$69,23,0) -> 570152 | M90: =VLOOKUP(B91,'E&W'!$A$7:$AD$69,25,0) -> 615029 | N90: =VLOOKUP(B91,'E&W'!$A$7:$AD$69,27,0) -> 732808 | O90: =VLOOKUP(B91,'E&W'!$A$7:$AD$69,29,0) -> 882687
B91: 1412000100 | C91: 水道代 Water | D91: =VLOOKUP(B91,'E&W'!$A$7:$P$69,8,0) -> 235409 | E91: =VLOOKUP(B91,'E&W'!$A$7:$P$69,10,0) -> 256523 | F91: =VLOOKUP(B91,'E&W'!$A$7:$P$69,12,0) -> 303459 | G91: =VLOOKUP(B91,'E&W'!$A$7:$P$69,14,0) -> 427385 | H91: =VLOOKUP(B91,'E&W'!$A$7:$P$69,16,0) -> 361958 | I91: =VLOOKUP(B91,'E&W'!$A$7:$AD$69,18,0) -> 368267 | J91: =VLOOKUP(B91,'E&W'!$A$7:$AD$69,20,0) -> 362638 | K91: =VLOOKUP(B91,'E&W'!$A$7:$AD$69,22,0) -> 272373 | L91: =VLOOKUP(B91,'E&W'!$A$7:$AD$69,24,0) -> 267461 | M91: =VLOOKUP(B91,'E&W'!$A$7:$AD$69,26,0) -> 238682 | N91: =VLOOKUP(B91,'E&W'!$A$7:$AD$69,28,0) -> 207622 | O91: =VLOOKUP(B91,'E&W'!$A$7:$AD$69,30,0) -> 335755
A92: 44 | B92: EI1課 | C92: 電気代 Electric | D92: =VLOOKUP(B93,'E&W'!$A$7:$P$69,7,0) -> 893684 | E92: =VLOOKUP(B93,'E&W'!$A$7:$P$69,9,0) -> 940484 | F92: =VLOOKUP(B93,'E&W'!$A$7:$P$69,11,0) -> 843311 | G92: =VLOOKUP(B93,'E&W'!$A$7:$P$69,13,0) -> 911454 | H92: =VLOOKUP(B93,'E&W'!$A$7:$P$69,15,0) -> 987828 | I92: =VLOOKUP(B93,'E&W'!$A$7:$AD$69,17,0) -> 1198187 | J92: =VLOOKUP(B93,'E&W'!$A$7:$AD$69,19,0) -> 827017 | K92: =VLOOKUP(B93,'E&W'!$A$7:$AD$69,21,0) -> 948786 | L92: =VLOOKUP(B93,'E&W'!$A$7:$AD$69,23,0) -> 920424 | M92: =VLOOKUP(B93,'E&W'!$A$7:$AD$69,25,0) -> 965608 | N92: =VLOOKUP(B93,'E&W'!$A$7:$AD$69,27,0) -> 1003076 | O92: =VLOOKUP(B93,'E&W'!$A$7:$AD$69,29,0) -> 1097005
B93: 1412000057 | C93: 水道代 Water | D93: =VLOOKUP(B93,'E&W'!$A$7:$P$69,8,0) -> 264836 | E93: =VLOOKUP(B93,'E&W'!$A$7:$P$69,10,0) -> 288588 | F93: =VLOOKUP(B93,'E&W'!$A$7:$P$69,12,0) -> 341391 | G93: =VLOOKUP(B93,'E&W'!$A$7:$P$69,14,0) -> 480808 | H93: =VLOOKUP(B93,'E&W'!$A$7:$P$69,16,0) -> 407203 | I93: =VLOOKUP(B93,'E&W'!$A$7:$AD$69,18,0) -> 552400 | J93: =VLOOKUP(B93,'E&W'!$A$7:$AD$69,20,0) -> 498627 | K93: =VLOOKUP(B93,'E&W'!$A$7:$AD$69,22,0) -> 374513 | L93: =VLOOKUP(B93,'E&W'!$A$7:$AD$69,24,0) -> 367759 | M93: =VLOOKUP(B93,'E&W'!$A$7:$AD$69,26,0) -> 328188 | N93: =VLOOKUP(B93,'E&W'!$A$7:$AD$69,28,0) -> 253760 | O93: =VLOOKUP(B93,'E&W'!$A$7:$AD$69,30,0) -> 369331
A94: 45 | B94: EI2課 | C94: 電気代 Electric | D94: =VLOOKUP(B95,'E&W'!$A$7:$P$69,7,0) -> 1134397 | E94: =VLOOKUP(B95,'E&W'!$A$7:$P$69,9,0) -> 1164916 | F94: =VLOOKUP(B95,'E&W'!$A$7:$P$69,11,0) -> 1010700 | G94: =VLOOKUP(B95,'E&W'!$A$7:$P$69,13,0) -> 1080085 | H94: =VLOOKUP(B95,'E&W'!$A$7:$P$69,15,0) -> 1165272 | I94: =VLOOKUP(B95,'E&W'!$A$7:$AD$69,17,0) -> 1076107 | J94: =VLOOKUP(B95,'E&W'!$A$7:$AD$69,19,0) -> 814180 | K94: =VLOOKUP(B95,'E&W'!$A$7:$AD$69,21,0) -> 954823 | L94: =VLOOKUP(B95,'E&W'!$A$7:$AD$69,23,0) -> 926497 | M94: =VLOOKUP(B95,'E&W'!$A$7:$AD$69,25,0) -> 999423 | N94: =VLOOKUP(B95,'E&W'!$A$7:$AD$69,27,0) -> 1058500 | O94: =VLOOKUP(B95,'E&W'!$A$7:$AD$69,29,0) -> 1059224
B95: 1412000101 | C95: 水道代 Water | D95: =VLOOKUP(B95,'E&W'!$A$7:$P$69,8,0) -> 382540 | E95: =VLOOKUP(B95,'E&W'!$A$7:$P$69,10,0) -> 416850 | F95: =VLOOKUP(B95,'E&W'!$A$7:$P$69,12,0) -> 493121 | G95: =VLOOKUP(B95,'E&W'!$A$7:$P$69,14,0) -> 694500 | H95: =VLOOKUP(B95,'E&W'!$A$7:$P$69,16,0) -> 588182 | I95: =VLOOKUP(B95,'E&W'!$A$7:$AD$69,18,0) -> 598434 | J95: =VLOOKUP(B95,'E&W'!$A$7:$AD$69,20,0) -> 589286 | K95: =VLOOKUP(B95,'E&W'!$A$7:$AD$69,22,0) -> 442607 | L95: =VLOOKUP(B95,'E&W'!$A$7:$AD$69,24,0) -> 434624 | M95: =VLOOKUP(B95,'E&W'!$A$7:$AD$69,26,0) -> 387859 | N95: =VLOOKUP(B95,'E&W'!$A$7:$AD$69,28,0) -> 299899 | O95: =VLOOKUP(B95,'E&W'!$A$7:$AD$69,30,0) -> 402906
A96: 46 | B96: ESD1課 | C96: 電気代 Electric | D96: =VLOOKUP(B97,'E&W'!$A$7:$P$69,7,0) -> 1242729 | E96: =VLOOKUP(B97,'E&W'!$A$7:$P$69,9,0) -> 1298920 | F96: =VLOOKUP(B97,'E&W'!$A$7:$P$69,11,0) -> 1154295 | G96: =VLOOKUP(B97,'E&W'!$A$7:$P$69,13,0) -> 1243788 | H96: =VLOOKUP(B97,'E&W'!$A$7:$P$69,15,0) -> 1346373 | I96: =VLOOKUP(B97,'E&W'!$A$7:$AD$69,17,0) -> 1612074 | J96: =VLOOKUP(B97,'E&W'!$A$7:$AD$69,19,0) -> 1140163 | K96: =VLOOKUP(B97,'E&W'!$A$7:$AD$69,21,0) -> 1316026 | L96: =VLOOKUP(B97,'E&W'!$A$7:$AD$69,23,0) -> 1276769 | M96: =VLOOKUP(B97,'E&W'!$A$7:$AD$69,25,0) -> 1350001 | N96: =VLOOKUP(B97,'E&W'!$A$7:$AD$69,27,0) -> 1410192 | O96: =VLOOKUP(B97,'E&W'!$A$7:$AD$69,29,0) -> 1538348
B97: 1412000078 | C97: 水道代 Water | D97: =VLOOKUP(B97,'E&W'!$A$7:$P$69,8,0) -> 382540 | E97: =VLOOKUP(B97,'E&W'!$A$7:$P$69,10,0) -> 416850 | F97: =VLOOKUP(B97,'E&W'!$A$7:$P$69,12,0) -> 493121 | G97: =VLOOKUP(B97,'E&W'!$A$7:$P$69,14,0) -> 694500 | H97: =VLOOKUP(B97,'E&W'!$A$7:$P$69,16,0) -> 588182 | I97: =VLOOKUP(B97,'E&W'!$A$7:$AD$69,18,0) -> 782567 | J97: =VLOOKUP(B97,'E&W'!$A$7:$AD$69,20,0) -> 725276 | K97: =VLOOKUP(B97,'E&W'!$A$7:$AD$69,22,0) -> 544747 | L97: =VLOOKUP(B97,'E&W'!$A$7:$AD$69,24,0) -> 534922 | M97: =VLOOKUP(B97,'E&W'!$A$7:$AD$69,26,0) -> 477365 | N97: =VLOOKUP(B97,'E&W'!$A$7:$AD$69,28,0) -> 369106 | O97: =VLOOKUP(B97,'E&W'!$A$7:$AD$69,30,0) -> 537208
A98: 47 | B98: ESD2課 | C98: 電気代 Electric | D98: =VLOOKUP(B99,'E&W'!$A$7:$P$69,7,0) -> 1329990 | E98: =VLOOKUP(B99,'E&W'!$A$7:$P$69,9,0) -> 1388529 | F98: =VLOOKUP(B99,'E&W'!$A$7:$P$69,11,0) -> 1232041 | G98: =VLOOKUP(B99,'E&W'!$A$7:$P$69,13,0) -> 1326872 | H98: =VLOOKUP(B99,'E&W'!$A$7:$P$69,15,0) -> 1436010 | I98: =VLOOKUP(B99,'E&W'!$A$7:$AD$69,17,0) -> 1363742 | J98: =VLOOKUP(B99,'E&W'!$A$7:$AD$69,19,0) -> 1014905 | K98: =VLOOKUP(B99,'E&W'!$A$7:$AD$69,21,0) -> 1169130 | L98: =VLOOKUP(B99,'E&W'!$A$7:$AD$69,23,0) -> 1134231 | M98: =VLOOKUP(B99,'E&W'!$A$7:$AD$69,25,0) -> 1196244 | N98: =VLOOKUP(B99,'E&W'!$A$7:$AD$69,27,0) -> 1328769 | O98: =VLOOKUP(B99,'E&W'!$A$7:$AD$69,29,0) -> 1361811
B99: 1412000096 | C99: 水道代 Water | D99: =VLOOKUP(B99,'E&W'!$A$7:$P$69,8,0) -> 411966 | E99: =VLOOKUP(B99,'E&W'!$A$7:$P$69,10,0) -> 448915 | F99: =VLOOKUP(B99,'E&W'!$A$7:$P$69,12,0) -> 531053 | G99: =VLOOKUP(B99,'E&W'!$A$7:$P$69,14,0) -> 747923 | H99: =VLOOKUP(B99,'E&W'!$A$7:$P$69,16,0) -> 633427 | I99: =VLOOKUP(B99,'E&W'!$A$7:$AD$69,18,0) -> 644467 | J99: =VLOOKUP(B99,'E&W'!$A$7:$AD$69,20,0) -> 634616 | K99: =VLOOKUP(B99,'E&W'!$A$7:$AD$69,22,0) -> 476653 | L99: =VLOOKUP(B99,'E&W'!$A$7:$AD$69,24,0) -> 468057 | M99: =VLOOKUP(B99,'E&W'!$A$7:$AD$69,26,0) -> 417694 | N99: =VLOOKUP(B99,'E&W'!$A$7:$AD$69,28,0) -> 346037 | O99: =VLOOKUP(B99,'E&W'!$A$7:$AD$69,30,0) -> 470057
A100: 48 | B100: 品質保証課 | C100: 電気代 Electric | D100: =VLOOKUP(B101,'E&W'!$A$7:$P$69,7,0) -> 11516532 | E100: =VLOOKUP(B101,'E&W'!$A$7:$P$69,9,0) -> 15406768 | F100: =VLOOKUP(B101,'E&W'!$A$7:$P$69,11,0) -> 13717420 | G100: =VLOOKUP(B101,'E&W'!$A$7:$P$69,13,0) -> 15155492 | H100: =VLOOKUP(B101,'E&W'!$A$7:$P$69,15,0) -> 12343574 | I100: =VLOOKUP(B101,'E&W'!$A$7:$AD$69,17,0) -> 13206708 | J100: =VLOOKUP(B101,'E&W'!$A$7:$AD$69,19,0) -> 10406026 | K100: =VLOOKUP(B101,'E&W'!$A$7:$AD$69,21,0) -> 9643859 | L100: =VLOOKUP(B101,'E&W'!$A$7:$AD$69,23,0) -> 9059803 | M100: =VLOOKUP(B101,'E&W'!$A$7:$AD$69,25,0) -> 12014577 | N100: =VLOOKUP(B101,'E&W'!$A$7:$AD$69,27,0) -> 12638580 | O100: =VLOOKUP(B101,'E&W'!$A$7:$AD$69,29,0) -> 11991376
