Workbook
Name WBS: 原価センタ!$G$2:$G$3

Sheet 採算表(USD)
B1: 組織名 | C1: ='採算表(VND)'!C1 -> MP FY2026_各予定 | N1: ='内訳ﾘｽﾄ(4～3月)'!B2 -> 25390
B2: ='採算表(VND)'!B2 -> MD2課
B4: 項目 ＼ 部門 | C4: ='採算表(VND)'!C4 -> 4 | D4: ='採算表(VND)'!D4 -> 5 | E4: ='採算表(VND)'!E4 -> 6 | F4: ='採算表(VND)'!F4 -> 7 | G4: ='採算表(VND)'!G4 -> 8 | H4: ='採算表(VND)'!H4 -> 9 | I4: ='採算表(VND)'!I4 -> 10 | J4: ='採算表(VND)'!J4 -> 11 | ... O4: ='採算表(VND)'!O4 -> 合計
B5: 総出荷 | C5: =C8+C9 -> 157155.64 | D5: =D8+D9 -> 47374.84 | E5: =E8+E9 -> 38917.66 | F5: =F8+F9 -> 42405.74 | G5: =G8+G9 -> 44162.17 | H5: =H8+H9 -> 47317.94 | I5: =I8+I9 -> 45156.41 | J5: =J8+J9 -> 69216.13 | ... O5: =O8+O9 -> 772907.41
B6: 社外出荷 | C6: =ROUNDDOWN('採算表(VND)'!C6/$N$1,2) -> 157155.64 | D6: =ROUNDDOWN('採算表(VND)'!D6/$N$1,2) -> 47374.84 | E6: =ROUNDDOWN('採算表(VND)'!E6/$N$1,2) -> 38917.66 | F6: =ROUNDDOWN('採算表(VND)'!F6/$N$1,2) -> 42405.74 | G6: =ROUNDDOWN('採算表(VND)'!G6/$N$1,2) -> 44162.17 | H6: =ROUNDDOWN('採算表(VND)'!H6/$N$1,2) -> 47317.94 | I6: =ROUNDDOWN('採算表(VND)'!I6/$N$1,2) -> 45156.41 | J6: =ROUNDDOWN('採算表(VND)'!J6/$N$1,2) -> 69216.13 | ... N6: =ROUNDDOWN('採算表(VND)'!N6/$N$1,2) -> 69864.33 | O6: =SUM(C6:N6) -> 772907.41
B7: 販売支援 | C7: =ROUNDDOWN('採算表(VND)'!C7/$N$1,2) -> 0 | D7: =ROUNDDOWN('採算表(VND)'!D7/$N$1,2) -> 0 | E7: =ROUNDDOWN('採算表(VND)'!E7/$N$1,2) -> 0 | F7: =ROUNDDOWN('採算表(VND)'!F7/$N$1,2) -> 0 | G7: =ROUNDDOWN('採算表(VND)'!G7/$N$1,2) -> 0 | H7: =ROUNDDOWN('採算表(VND)'!H7/$N$1,2) -> 0 | I7: =ROUNDDOWN('採算表(VND)'!I7/$N$1,2) -> 0 | J7: =ROUNDDOWN('採算表(VND)'!J7/$N$1,2) -> 0 | ... N7: =ROUNDDOWN('採算表(VND)'!N7/$N$1,2) -> 0 | O7: =SUM(C7:N7) -> 0
B8: 社外出荷合計 | C8: =C6+C7 -> 157155.64 | D8: =D6+D7 -> 47374.84 | E8: =E6+E7 -> 38917.66 | F8: =F6+F7 -> 42405.74 | G8: =G6+G7 -> 44162.17 | H8: =H6+H7 -> 47317.94 | I8: =I6+I7 -> 45156.41 | J8: =J6+J7 -> 69216.13 | ... O8: =O6+O7 -> 772907.41
B9: 社内売 | C9: =ROUNDDOWN('採算表(VND)'!C9/$N$1,2) -> 0 | D9: =ROUNDDOWN('採算表(VND)'!D9/$N$1,2) -> 0 | E9: =ROUNDDOWN('採算表(VND)'!E9/$N$1,2) -> 0 | F9: =ROUNDDOWN('採算表(VND)'!F9/$N$1,2) -> 0 | G9: =ROUNDDOWN('採算表(VND)'!G9/$N$1,2) -> 0 | H9: =ROUNDDOWN('採算表(VND)'!H9/$N$1,2) -> 0 | I9: =ROUNDDOWN('採算表(VND)'!I9/$N$1,2) -> 0 | J9: =ROUNDDOWN('採算表(VND)'!J9/$N$1,2) -> 0 | ... N9: =ROUNDDOWN('採算表(VND)'!N9/$N$1,2) -> 0 | O9: =SUM(C9:N9) -> 0
B10: 社内買 | C10: =ROUNDDOWN('採算表(VND)'!C10/$N$1,2) -> 0 | D10: =ROUNDDOWN('採算表(VND)'!D10/$N$1,2) -> 0 | E10: =ROUNDDOWN('採算表(VND)'!E10/$N$1,2) -> 0 | F10: =ROUNDDOWN('採算表(VND)'!F10/$N$1,2) -> 0 | G10: =ROUNDDOWN('採算表(VND)'!G10/$N$1,2) -> 0 | H10: =ROUNDDOWN('採算表(VND)'!H10/$N$1,2) -> 0 | I10: =ROUNDDOWN('採算表(VND)'!I10/$N$1,2) -> 0 | J10: =ROUNDDOWN('採算表(VND)'!J10/$N$1,2) -> 0 | ... N10: =ROUNDDOWN('採算表(VND)'!N10/$N$1,2) -> 0 | O10: =SUM(C10:N10) -> 0
B12: 総生産 | C12: =C5-C10 -> 157155.64 | D12: =D5-D10 -> 47374.84 | E12: =E5-E10 -> 38917.66 | F12: =F5-F10 -> 42405.74 | G12: =G5-G10 -> 44162.17 | H12: =H5-H10 -> 47317.94 | I12: =I5-I10 -> 45156.41 | J12: =J5-J10 -> 69216.13 | ... O12: =O5-O10 -> 772907.41
B13: 控除額 | C13: =SUM(C14:C65) -> 2526.44 | D13: =SUM(D14:D65) -> 3597.18 | E13: =SUM(E14:E65) -> 4226.84 | F13: =SUM(F14:F65) -> 3740.49 | G13: =SUM(G14:G65) -> 2300.77 | H13: =SUM(H14:H65) -> 2341.4 | I13: =SUM(I14:I65) -> 2886.68 | J13: =SUM(J14:J65) -> 2612.56 | ... O13: =SUM(O14:O65) -> 33669.15
B14: 材料費 | C14: =ROUNDUP('採算表(VND)'!C14/$N$1,2) -> 0 | D14: =ROUNDUP('採算表(VND)'!D14/$N$1,2) -> 0 | E14: =ROUNDUP('採算表(VND)'!E14/$N$1,2) -> 0 | F14: =ROUNDUP('採算表(VND)'!F14/$N$1,2) -> 0 | G14: =ROUNDUP('採算表(VND)'!G14/$N$1,2) -> 0 | H14: =ROUNDUP('採算表(VND)'!H14/$N$1,2) -> 0 | I14: =ROUNDUP('採算表(VND)'!I14/$N$1,2) -> 0 | J14: =ROUNDUP('採算表(VND)'!J14/$N$1,2) -> 0 | ... N14: =ROUNDUP('採算表(VND)'!N14/$N$1,2) -> 0 | O14: =SUM(C14:N14) -> 0
B15: 設計変更材料費 | C15: =ROUNDUP('採算表(VND)'!C15/$N$1,2) -> 0 | D15: =ROUNDUP('採算表(VND)'!D15/$N$1,2) -> 0 | E15: =ROUNDUP('採算表(VND)'!E15/$N$1,2) -> 0 | F15: =ROUNDUP('採算表(VND)'!F15/$N$1,2) -> 0 | G15: =ROUNDUP('採算表(VND)'!G15/$N$1,2) -> 0 | H15: =ROUNDUP('採算表(VND)'!H15/$N$1,2) -> 0 | I15: =ROUNDUP('採算表(VND)'!I15/$N$1,2) -> 0 | J15: =ROUNDUP('採算表(VND)'!J15/$N$1,2) -> 0 | ... N15: =ROUNDUP('採算表(VND)'!N15/$N$1,2) -> 0 | O15: =SUM(C15:N15) -> 0
B16: 仕掛仕損 | C16: =ROUNDUP('採算表(VND)'!C16/$N$1,2) -> 0 | D16: =ROUNDUP('採算表(VND)'!D16/$N$1,2) -> 0 | E16: =ROUNDUP('採算表(VND)'!E16/$N$1,2) -> 0 | F16: =ROUNDUP('採算表(VND)'!F16/$N$1,2) -> 0 | G16: =ROUNDUP('採算表(VND)'!G16/$N$1,2) -> 0 | H16: =ROUNDUP('採算表(VND)'!H16/$N$1,2) -> 0 | I16: =ROUNDUP('採算表(VND)'!I16/$N$1,2) -> 0 | J16: =ROUNDUP('採算表(VND)'!J16/$N$1,2) -> 0 | ... N16: =ROUNDUP('採算表(VND)'!N16/$N$1,2) -> 0 | O16: =SUM(C16:N16) -> 0
B17: 仕入製商品費 | C17: =ROUNDUP('採算表(VND)'!C17/$N$1,2) -> 0 | D17: =ROUNDUP('採算表(VND)'!D17/$N$1,2) -> 0 | E17: =ROUNDUP('採算表(VND)'!E17/$N$1,2) -> 0 | F17: =ROUNDUP('採算表(VND)'!F17/$N$1,2) -> 0 | G17: =ROUNDUP('採算表(VND)'!G17/$N$1,2) -> 0 | H17: =ROUNDUP('採算表(VND)'!H17/$N$1,2) -> 0 | I17: =ROUNDUP('採算表(VND)'!I17/$N$1,2) -> 0 | J17: =ROUNDUP('採算表(VND)'!J17/$N$1,2) -> 0 | ... N17: =ROUNDUP('採算表(VND)'!N17/$N$1,2) -> 0 | O17: =SUM(C17:N17) -> 0
B18: 内製品有償支給原価 | C18: =ROUNDUP('採算表(VND)'!C18/$N$1,2) -> 0 | D18: =ROUNDUP('採算表(VND)'!D18/$N$1,2) -> 0 | E18: =ROUNDUP('採算表(VND)'!E18/$N$1,2) -> 0 | F18: =ROUNDUP('採算表(VND)'!F18/$N$1,2) -> 0 | G18: =ROUNDUP('採算表(VND)'!G18/$N$1,2) -> 0 | H18: =ROUNDUP('採算表(VND)'!H18/$N$1,2) -> 0 | I18: =ROUNDUP('採算表(VND)'!I18/$N$1,2) -> 0 | J18: =ROUNDUP('採算表(VND)'!J18/$N$1,2) -> 0 | ... N18: =ROUNDUP('採算表(VND)'!N18/$N$1,2) -> 0 | O18: =SUM(C18:N18) -> 0
B19: 外注加工費 | C19: =ROUNDUP('採算表(VND)'!C19/$N$1,2) -> 0 | D19: =ROUNDUP('採算表(VND)'!D19/$N$1,2) -> 0 | E19: =ROUNDUP('採算表(VND)'!E19/$N$1,2) -> 0 | F19: =ROUNDUP('採算表(VND)'!F19/$N$1,2) -> 0 | G19: =ROUNDUP('採算表(VND)'!G19/$N$1,2) -> 0 | H19: =ROUNDUP('採算表(VND)'!H19/$N$1,2) -> 0 | I19: =ROUNDUP('採算表(VND)'!I19/$N$1,2) -> 0 | J19: =ROUNDUP('採算表(VND)'!J19/$N$1,2) -> 0 | ... N19: =ROUNDUP('採算表(VND)'!N19/$N$1,2) -> 0 | O19: =SUM(C19:N19) -> 0
B20: 減価償却費 | C20: =ROUNDUP('採算表(VND)'!C20/$N$1,2) -> 130.87 | D20: =ROUNDUP('採算表(VND)'!D20/$N$1,2) -> 130.86 | E20: =ROUNDUP('採算表(VND)'!E20/$N$1,2) -> 136.5 | F20: =ROUNDUP('採算表(VND)'!F20/$N$1,2) -> 136.92 | G20: =ROUNDUP('採算表(VND)'!G20/$N$1,2) -> 110.32 | H20: =ROUNDUP('採算表(VND)'!H20/$N$1,2) -> 109.12 | I20: =ROUNDUP('採算表(VND)'!I20/$N$1,2) -> 109.12 | J20: =ROUNDUP('採算表(VND)'!J20/$N$1,2) -> 109.12 | ... N20: =ROUNDUP('採算表(VND)'!N20/$N$1,2) -> 109.49 | O20: =SUM(C20:N20) -> 1408.56
B21: 金型償却費 | C21: =ROUNDUP('採算表(VND)'!C21/$N$1,2) -> 0 | D21: =ROUNDUP('採算表(VND)'!D21/$N$1,2) -> 0 | E21: =ROUNDUP('採算表(VND)'!E21/$N$1,2) -> 0 | F21: =ROUNDUP('採算表(VND)'!F21/$N$1,2) -> 0 | G21: =ROUNDUP('採算表(VND)'!G21/$N$1,2) -> 0 | H21: =ROUNDUP('採算表(VND)'!H21/$N$1,2) -> 0 | I21: =ROUNDUP('採算表(VND)'!I21/$N$1,2) -> 0 | J21: =ROUNDUP('採算表(VND)'!J21/$N$1,2) -> 0 | ... N21: =ROUNDUP('採算表(VND)'!N21/$N$1,2) -> 0 | O21: =SUM(C21:N21) -> 0
B22: 賃借料 | C22: =ROUNDUP('採算表(VND)'!C22/$N$1,2) -> 0 | D22: =ROUNDUP('採算表(VND)'!D22/$N$1,2) -> 0 | E22: =ROUNDUP('採算表(VND)'!E22/$N$1,2) -> 0 | F22: =ROUNDUP('採算表(VND)'!F22/$N$1,2) -> 0 | G22: =ROUNDUP('採算表(VND)'!G22/$N$1,2) -> 0 | H22: =ROUNDUP('採算表(VND)'!H22/$N$1,2) -> 0 | I22: =ROUNDUP('採算表(VND)'!I22/$N$1,2) -> 0 | J22: =ROUNDUP('採算表(VND)'!J22/$N$1,2) -> 0 | ... N22: =ROUNDUP('採算表(VND)'!N22/$N$1,2) -> 0 | O22: =SUM(C22:N22) -> 0
B23: 保険料 | C23: =ROUNDUP('採算表(VND)'!C23/$N$1,2) -> 0 | D23: =ROUNDUP('採算表(VND)'!D23/$N$1,2) -> 0 | E23: =ROUNDUP('採算表(VND)'!E23/$N$1,2) -> 0 | F23: =ROUNDUP('採算表(VND)'!F23/$N$1,2) -> 0 | G23: =ROUNDUP('採算表(VND)'!G23/$N$1,2) -> 0 | H23: =ROUNDUP('採算表(VND)'!H23/$N$1,2) -> 0 | I23: =ROUNDUP('採算表(VND)'!I23/$N$1,2) -> 0 | J23: =ROUNDUP('採算表(VND)'!J23/$N$1,2) -> 0 | ... N23: =ROUNDUP('採算表(VND)'!N23/$N$1,2) -> 0 | O23: =SUM(C23:N23) -> 0
B24: 設計委託費 | C24: =ROUNDUP('採算表(VND)'!C24/$N$1,2) -> 0 | D24: =ROUNDUP('採算表(VND)'!D24/$N$1,2) -> 0 | E24: =ROUNDUP('採算表(VND)'!E24/$N$1,2) -> 0 | F24: =ROUNDUP('採算表(VND)'!F24/$N$1,2) -> 0 | G24: =ROUNDUP('採算表(VND)'!G24/$N$1,2) -> 0 | H24: =ROUNDUP('採算表(VND)'!H24/$N$1,2) -> 0 | I24: =ROUNDUP('採算表(VND)'!I24/$N$1,2) -> 0 | J24: =ROUNDUP('採算表(VND)'!J24/$N$1,2) -> 0 | ... N24: =ROUNDUP('採算表(VND)'!N24/$N$1,2) -> 0 | O24: =SUM(C24:N24) -> 0
B25: 消耗品費 | C25: =ROUNDUP('採算表(VND)'!C25/$N$1,2) -> 6.62 | D25: =ROUNDUP('採算表(VND)'!D25/$N$1,2) -> 7.28 | E25: =ROUNDUP('採算表(VND)'!E25/$N$1,2) -> 6.95 | F25: =ROUNDUP('採算表(VND)'!F25/$N$1,2) -> 7.98 | G25: =ROUNDUP('採算表(VND)'!G25/$N$1,2) -> 7.63 | H25: =ROUNDUP('採算表(VND)'!H25/$N$1,2) -> 6.26 | I25: =ROUNDUP('採算表(VND)'!I25/$N$1,2) -> 9.72 | J25: =ROUNDUP('採算表(VND)'!J25/$N$1,2) -> 8.89 | ... N25: =ROUNDUP('採算表(VND)'!N25/$N$1,2) -> 8.49 | O25: =SUM(C25:N25) -> 93.57
... B65: 本社機構経費 | C65: =ROUNDUP('採算表(VND)'!C65/$N$1,2) -> 0 | D65: =ROUNDUP('採算表(VND)'!D65/$N$1,2) -> 0 | E65: =ROUNDUP('採算表(VND)'!E65/$N$1,2) -> 0 | F65: =ROUNDUP('採算表(VND)'!F65/$N$1,2) -> 0 | G65: =ROUNDUP('採算表(VND)'!G65/$N$1,2) -> 0 | H65: =ROUNDUP('採算表(VND)'!H65/$N$1,2) -> 0 | I65: =ROUNDUP('採算表(VND)'!I65/$N$1,2) -> 0 | J65: =ROUNDUP('採算表(VND)'!J65/$N$1,2) -> 0 | ... N65: =ROUNDUP('採算表(VND)'!N65/$N$1,2) -> 0 | O65: =SUM(C65:N65) -> 0
B66: 差引収益 | C66: =C12-C13 -> 154629.2 | D66: =IF(ISBLANK(D4),"",D12-D13) -> 43777.66 | E66: =IF(ISBLANK(E4),"",E12-E13) -> 34690.82 | F66: =IF(ISBLANK(F4),"",F12-F13) -> 38665.25 | G66: =IF(ISBLANK(G4),"",G12-G13) -> 41861.4 | H66: =IF(ISBLANK(H4),"",H12-H13) -> 44976.54 | I66: =IF(ISBLANK(I4),"",I12-I13) -> 42269.73 | J66: =IF(ISBLANK(J4),"",J12-J13) -> 66603.57 | K66: =IF(ISBLANK(K4),"",K12-K13) -> 68725.64 | ... O66: =IF(ISBLANK(O4),"",O12-O13) -> 739238.26
B67: 総時間 | C67: =C73+C79 -> 3615.5 | D67: =IF(ISBLANK(D4),"",D73+D79) -> 3441.25 | E67: =IF(ISBLANK(E4),"",E73+E79) -> 3794.75 | F67: =IF(ISBLANK(F4),"",F73+F79) -> 4197 | G67: =IF(ISBLANK(G4),"",G73+G79) -> 3661 | H67: =IF(ISBLANK(H4),"",H73+H79) -> 3480.75 | I67: =IF(ISBLANK(I4),"",I73+I79) -> 4683.25 | J67: =IF(ISBLANK(J4),"",J73+J79) -> 4082.75 | K67: =IF(ISBLANK(K4),"",K73+K79) -> 4485.25 | ... O67: =IF(ISBLANK(O4),"",O73+O79) -> 46637.75
B68: 直接部門 | C68: ='採算表(VND)'!C68 -> 2992 | D68: ='採算表(VND)'!D68 -> 2839 | E68: ='採算表(VND)'!E68 -> 3145 | F68: ='採算表(VND)'!F68 -> 3451 | G68: ='採算表(VND)'!G68 -> 2992 | H68: ='採算表(VND)'!H68 -> 2839 | I68: ='採算表(VND)'!I68 -> 3842 | J68: ='採算表(VND)'!J68 -> 3332 | ... N68: ='採算表(VND)'!N68 -> 3332 | O68: =SUM(C68:N68) -> 38207.5
B69: 部内間接部門 | C69: ='採算表(VND)'!C69 -> 0 | D69: ='採算表(VND)'!D69 -> 0 | E69: ='採算表(VND)'!E69 -> 0 | F69: ='採算表(VND)'!F69 -> 0 | G69: ='採算表(VND)'!G69 -> 0 | H69: ='採算表(VND)'!H69 -> 0 | I69: ='採算表(VND)'!I69 -> 0 | J69: ='採算表(VND)'!J69 -> 0 | ... N69: ='採算表(VND)'!N69 -> 0 | O69: =SUM(C69:N69) -> 0
B70: 部外間接部門1 | C70: ='採算表(VND)'!C70 -> 10.25 | D70: ='採算表(VND)'!D70 -> 10.5 | E70: ='採算表(VND)'!E70 -> 11.5 | F70: ='採算表(VND)'!F70 -> 16.25 | G70: ='採算表(VND)'!G70 -> 14.25 | H70: ='採算表(VND)'!H70 -> 13.5 | I70: ='採算表(VND)'!I70 -> 16.5 | J70: ='採算表(VND)'!J70 -> 14.25 | ... N70: ='採算表(VND)'!N70 -> 15 | O70: =SUM(C70:N70) -> 163.75
B71: 部外間接部門2 | C71: ='採算表(VND)'!C71 -> 19.5 | D71: ='採算表(VND)'!D71 -> 18.25 | E71: ='採算表(VND)'!E71 -> 20.75 | F71: ='採算表(VND)'!F71 -> 31.25 | G71: ='採算表(VND)'!G71 -> 27 | H71: ='採算表(VND)'!H71 -> 26.5 | I71: ='採算表(VND)'!I71 -> 32.25 | J71: ='採算表(VND)'!J71 -> 28.25 | ... N71: ='採算表(VND)'!N71 -> 28.25 | O71: =SUM(C71:N71) -> 312.5
B72: 工場間接部門 | C72: ='採算表(VND)'!C72 -> 85.25 | D72: ='採算表(VND)'!D72 -> 85.5 | E72: ='採算表(VND)'!E72 -> 89.75 | F72: ='採算表(VND)'!F72 -> 128.5 | G72: ='採算表(VND)'!G72 -> 117.25 | H72: ='採算表(VND)'!H72 -> 110 | I72: ='採算表(VND)'!I72 -> 130.25 | J72: ='採算表(VND)'!J72 -> 118.5 | ... N72: ='採算表(VND)'!N72 -> 121.25 | O72: =SUM(C72:N72) -> 1325
B73: 定時間合計 | C73: =SUM(C68:C72) -> 3107 | D73: =IF(ISBLANK(D4),"",SUM(D68:D72)) -> 2953.25 | E73: =IF(ISBLANK(E4),"",SUM(E68:E72)) -> 3267 | F73: =IF(ISBLANK(F4),"",SUM(F68:F72)) -> 3627 | G73: =IF(ISBLANK(G4),"",SUM(G68:G72)) -> 3150.5 | H73: =IF(ISBLANK(H4),"",SUM(H68:H72)) -> 2989 | I73: =IF(ISBLANK(I4),"",SUM(I68:I72)) -> 4021 | J73: =IF(ISBLANK(J4),"",SUM(J68:J72)) -> 3493 | K73: =IF(ISBLANK(K4),"",SUM(K68:K72)) -> 3847.25 | ... O73: =IF(ISBLANK(O4),"",SUM(O68:O72)) -> 40008.75
B74: 直接部門 | C74: ='採算表(VND)'!C74 -> 502 | D74: ='採算表(VND)'!D74 -> 482 | E74: ='採算表(VND)'!E74 -> 522 | F74: ='採算表(VND)'!F74 -> 562 | G74: ='採算表(VND)'!G74 -> 502 | H74: ='採算表(VND)'!H74 -> 482 | I74: ='採算表(VND)'!I74 -> 654 | J74: ='採算表(VND)'!J74 -> 582 | ... N74: ='採算表(VND)'!N74 -> 582 | O74: =SUM(C74:N74) -> 6534
B75: 部内間接部門 | C75: ='採算表(VND)'!C75 -> 0 | D75: ='採算表(VND)'!D75 -> 0 | E75: ='採算表(VND)'!E75 -> 0 | F75: ='採算表(VND)'!F75 -> 0 | G75: ='採算表(VND)'!G75 -> 0 | H75: ='採算表(VND)'!H75 -> 0 | I75: ='採算表(VND)'!I75 -> 0 | J75: ='採算表(VND)'!J75 -> 0 | ... N75: ='採算表(VND)'!N75 -> 0 | O75: =SUM(C75:N75) -> 0
B76: 部外間接部門1 | C76: ='採算表(VND)'!C76 -> 0.75 | D76: ='採算表(VND)'!D76 -> 0.75 | E76: ='採算表(VND)'!E76 -> 0.75 | F76: ='採算表(VND)'!F76 -> 1 | G76: ='採算表(VND)'!G76 -> 1 | H76: ='採算表(VND)'!H76 -> 0.75 | I76: ='採算表(VND)'!I76 -> 1 | J76: ='採算表(VND)'!J76 -> 0.75 | ... N76: ='採算表(VND)'!N76 -> 0.75 | O76: =SUM(C76:N76) -> 10
B77: 部外間接部門2 | C77: ='採算表(VND)'!C77 -> 1.25 | D77: ='採算表(VND)'!D77 -> 1.25 | E77: ='採算表(VND)'!E77 -> 1.25 | F77: ='採算表(VND)'!F77 -> 2 | G77: ='採算表(VND)'!G77 -> 2 | H77: ='採算表(VND)'!H77 -> 2 | I77: ='採算表(VND)'!I77 -> 2.25 | J77: ='採算表(VND)'!J77 -> 2 | ... N77: ='採算表(VND)'!N77 -> 2.25 | O77: =SUM(C77:N77) -> 22.25
B78: 工場間接部門 | C78: ='採算表(VND)'!C78 -> 4.5 | D78: ='採算表(VND)'!D78 -> 4 | E78: ='採算表(VND)'!E78 -> 3.75 | F78: ='採算表(VND)'!F78 -> 5 | G78: ='採算表(VND)'!G78 -> 5.5 | H78: ='採算表(VND)'!H78 -> 7 | I78: ='採算表(VND)'!I78 -> 5 | J78: ='採算表(VND)'!J78 -> 5 | ... N78: ='採算表(VND)'!N78 -> 5.5 | O78: =SUM(C78:N78) -> 62.75
B79: 残業時間合計 | C79: =SUM(C74:C78) -> 508.5 | D79: =IF(ISBLANK(D4),"",SUM(D74:D78)) -> 488 | E79: =IF(ISBLANK(E4),"",SUM(E74:E78)) -> 527.75 | F79: =IF(ISBLANK(F4),"",SUM(F74:F78)) -> 570 | G79: =IF(ISBLANK(G4),"",SUM(G74:G78)) -> 510.5 | H79: =IF(ISBLANK(H4),"",SUM(H74:H78)) -> 491.75 | I79: =IF(ISBLANK(I4),"",SUM(I74:I78)) -> 662.25 | J79: =IF(ISBLANK(J4),"",SUM(J74:J78)) -> 589.75 | K79: =IF(ISBLANK(K4),"",SUM(K74:K78)) -> 638 | ... O79: =IF(ISBLANK(O4),"",SUM(O74:O78)) -> 6629
B80: 当月時間当り | C80: =IFERROR(ROUNDDOWN(C66/C67,0),0) -> 42 | D80: =IFERROR(ROUNDDOWN(D66/D67,0),0) -> 12 | E80: =IFERROR(ROUNDDOWN(E66/E67,0),0) -> 9 | F80: =IFERROR(ROUNDDOWN(F66/F67,0),0) -> 9 | G80: =IFERROR(ROUNDDOWN(G66/G67,0),0) -> 11 | H80: =IFERROR(ROUNDDOWN(H66/H67,0),0) -> 12 | I80: =IFERROR(ROUNDDOWN(I66/I67,0),0) -> 9 | J80: =IFERROR(ROUNDDOWN(J66/J67,0),0) -> 16 | ... O80: =IFERROR(ROUNDDOWN(O66/O67,0),0) -> 15
B81: 時間当り生産高 | C81: =IFERROR(ROUNDDOWN(C12/C67,0),0) -> 43 | D81: =IFERROR(ROUNDDOWN(D12/D67,0),0) -> 13 | E81: =IFERROR(ROUNDDOWN(E12/E67,0),0) -> 10 | F81: =IFERROR(ROUNDDOWN(F12/F67,0),0) -> 10 | G81: =IFERROR(ROUNDDOWN(G12/G67,0),0) -> 12 | H81: =IFERROR(ROUNDDOWN(H12/H67,0),0) -> 13 | I81: =IFERROR(ROUNDDOWN(I12/I67,0),0) -> 9 | J81: =IFERROR(ROUNDDOWN(J12/J67,0),0) -> 16 | ... O81: =IFERROR(ROUNDDOWN(O12/O67,0),0) -> 16
B86: ■人員
B87: 出向社員(人) | C87: ='採算表(VND)'!C87 -> 9 | D87: ='採算表(VND)'!D87 -> 9 | E87: ='採算表(VND)'!E87 -> 9 | F87: ='採算表(VND)'!F87 -> 9 | G87: ='採算表(VND)'!G87 -> 9 | H87: ='採算表(VND)'!H87 -> 9 | I87: ='採算表(VND)'!I87 -> 11 | J87: ='採算表(VND)'!J87 -> 11 | ... N87: ='採算表(VND)'!N87 -> 11 | O87: =SUM(C87:N87) -> 120
B88: ローカル社員(人) | C88: ='採算表(VND)'!C88 -> 9 | D88: ='採算表(VND)'!D88 -> 9 | E88: ='採算表(VND)'!E88 -> 9 | F88: ='採算表(VND)'!F88 -> 9 | G88: ='採算表(VND)'!G88 -> 9 | H88: ='採算表(VND)'!H88 -> 9 | I88: ='採算表(VND)'!I88 -> 9 | J88: ='採算表(VND)'!J88 -> 9 | ... N88: ='採算表(VND)'!N88 -> 9 | O88: =SUM(C88:N88) -> 108
B89: 人員計 | C89: =C87+C88 -> 18 | D89: =D87+D88 -> 18 | E89: =E87+E88 -> 18 | F89: =F87+F88 -> 18 | G89: =G87+G88 -> 18 | H89: =H87+H88 -> 18 | I89: =I87+I88 -> 20 | J89: =J87+J88 -> 20 | ... O89: =O87+O88 -> 228
B91: ■定時間
B92: 出向社員定時 | C92: ='採算表(VND)'!C92 -> 1521.5 | D92: ='採算表(VND)'!D92 -> 1445 | E92: ='採算表(VND)'!E92 -> 1598 | F92: ='採算表(VND)'!F92 -> 1751 | G92: ='採算表(VND)'!G92 -> 1521.5 | H92: ='採算表(VND)'!H92 -> 1445 | I92: ='採算表(VND)'!I92 -> 2142 | J92: ='採算表(VND)'!J92 -> 1861.5 | ... N92: ='採算表(VND)'!N92 -> 1861.5 | O92: =SUM(C92:N92) -> 20408.5
B93: ローカル社員定時 | C93: ='採算表(VND)'!C93 -> 1470.5 | D93: ='採算表(VND)'!D93 -> 1394 | E93: ='採算表(VND)'!E93 -> 1547 | F93: ='採算表(VND)'!F93 -> 1700 | G93: ='採算表(VND)'!G93 -> 1470.5 | H93: ='採算表(VND)'!H93 -> 1394 | I93: ='採算表(VND)'!I93 -> 1700 | J93: ='採算表(VND)'!J93 -> 1470.5 | ... N93: ='採算表(VND)'!N93 -> 1470.5 | O93: =SUM(C93:N93) -> 17799
B94: 人員計 | C94: =C92+C93 -> 2992 | D94: =D92+D93 -> 2839 | E94: =E92+E93 -> 3145 | F94: =F92+F93 -> 3451 | G94: =G92+G93 -> 2992 | H94: =H92+H93 -> 2839 | I94: =I92+I93 -> 3842 | J94: =J92+J93 -> 3332 | ... O94: =O92+O93 -> 38207.5
B96: ■残業時間
B97: 出向社員残業 | C97: ='採算表(VND)'!C97 -> 358 | D97: ='採算表(VND)'!D97 -> 340 | E97: ='採算表(VND)'!E97 -> 376 | F97: ='採算表(VND)'!F97 -> 412 | G97: ='採算表(VND)'!G97 -> 358 | H97: ='採算表(VND)'!H97 -> 340 | I97: ='採算表(VND)'!I97 -> 504 | J97: ='採算表(VND)'!J97 -> 438 | ... N97: ='採算表(VND)'!N97 -> 438 | O97: =SUM(C97:N97) -> 4802
B98: ローカル社員残業 | C98: ='採算表(VND)'!C98 -> 144 | D98: ='採算表(VND)'!D98 -> 142 | E98: ='採算表(VND)'!E98 -> 146 | F98: ='採算表(VND)'!F98 -> 150 | G98: ='採算表(VND)'!G98 -> 144 | H98: ='採算表(VND)'!H98 -> 142 | I98: ='採算表(VND)'!I98 -> 150 | J98: ='採算表(VND)'!J98 -> 144 | ... N98: ='採算表(VND)'!N98 -> 144 | O98: =SUM(C98:N98) -> 1732
B99: 人員計 | C99: =C97+C98 -> 502 | D99: =D97+D98 -> 482 | E99: =E97+E98 -> 522 | F99: =F97+F98 -> 562 | G99: =G97+G98 -> 502 | H99: =H97+H98 -> 482 | I99: =I97+I98 -> 654 | J99: =J97+J98 -> 582 | ... O99: =O97+O98 -> 6534

Sheet 採算表(VND)
B1: 組織名 | C1: ='内訳ﾘｽﾄ(4～3月)'!A1 -> MP FY2026_各予定
B2: ='内訳ﾘｽﾄ(4～3月)'!C5 -> MD2課
C3: 2 | D3: 3 | E3: 4 | F3: 5 | G3: 6 | H3: 7 | I3: 8 | J3: 9 | K3: 10 | L3: 11 | M3: 12 | N3: 13
B4: 項目 ＼ 部門 | C4: ='内訳ﾘｽﾄ(4～3月)'!F4 -> 4 | D4: 5 | E4: 6 | F4: 7 | G4: 8 | H4: 9 | I4: 10 | J4: 11 | K4: 12 | L4: 1 | M4: 2 | N4: 3 | O4: 合計
B5: 総出荷 | C5: =C8+C9 -> 3990181700 | D5: =D8+D9 -> 1202847188 | E5: =E8+E9 -> 988119388 | F5: =F8+F9 -> 1076681739 | G5: =G8+G9 -> 1121277497 | H5: =H8+H9 -> 1201402497 | I5: =I8+I9 -> 1146521250 | J5: =J8+J9 -> 1757397541 | ... O5: =O8+O9 -> 19624119145
B6: 社外出荷 | C6: =SUMIF('内訳ﾘｽﾄ(4～3月)'!$D$26:$D$176,'採算表(VND)'!$B6,'内訳ﾘｽﾄ(4～3月)'!F$26:F$176) -> 3990181700 | D6: =SUMIF('内訳ﾘｽﾄ(4～3月)'!$D$26:$D$176,'採算表(VND)'!$B6,'内訳ﾘｽﾄ(4～3月)'!G$26:G$176) -> 1202847188 | E6: =SUMIF('内訳ﾘｽﾄ(4～3月)'!$D$26:$D$176,'採算表(VND)'!$B6,'内訳ﾘｽﾄ(4～3月)'!H$26:H$176) -> 988119388 | F6: =SUMIF('内訳ﾘｽﾄ(4～3月)'!$D$26:$D$176,'採算表(VND)'!$B6,'内訳ﾘｽﾄ(4～3月)'!I$26:I$176) -> 1076681739 | G6: =SUMIF('内訳ﾘｽﾄ(4～3月)'!$D$26:$D$176,'採算表(VND)'!$B6,'内訳ﾘｽﾄ(4～3月)'!J$26:J$176) -> 1121277497 | H6: =SUMIF('内訳ﾘｽﾄ(4～3月)'!$D$26:$D$176,'採算表(VND)'!$B6,'内訳ﾘｽﾄ(4～3月)'!K$26:K$176) -> 1201402497 | I6: =SUMIF('内訳ﾘｽﾄ(4～3月)'!$D$26:$D$176,'採算表(VND)'!$B6,'内訳ﾘｽﾄ(4～3月)'!L$26:L$176) -> 1146521250 | J6: =SUMIF('内訳ﾘｽﾄ(4～3月)'!$D$26:$D$176,'採算表(VND)'!$B6,'内訳ﾘｽﾄ(4～3月)'!M$26:M$176) -> 1757397541 | ... O6: =SUMIF('内訳ﾘｽﾄ(4～3月)'!$D$26:$D$176,'採算表(VND)'!$B6,'内訳ﾘｽﾄ(4～3月)'!R$26:R$176) -> 19624119145
B7: 販売支援 | C7: =SUMIF('内訳ﾘｽﾄ(4～3月)'!$D$26:$D$176,'採算表(VND)'!$B7,'内訳ﾘｽﾄ(4～3月)'!F$26:F$176) -> 0 | D7: =SUMIF('内訳ﾘｽﾄ(4～3月)'!$D$26:$D$176,'採算表(VND)'!$B7,'内訳ﾘｽﾄ(4～3月)'!G$26:G$176) -> 0 | E7: =SUMIF('内訳ﾘｽﾄ(4～3月)'!$D$26:$D$176,'採算表(VND)'!$B7,'内訳ﾘｽﾄ(4～3月)'!H$26:H$176) -> 0 | F7: =SUMIF('内訳ﾘｽﾄ(4～3月)'!$D$26:$D$176,'採算表(VND)'!$B7,'内訳ﾘｽﾄ(4～3月)'!I$26:I$176) -> 0 | G7: =SUMIF('内訳ﾘｽﾄ(4～3月)'!$D$26:$D$176,'採算表(VND)'!$B7,'内訳ﾘｽﾄ(4～3月)'!J$26:J$176) -> 0 | H7: =SUMIF('内訳ﾘｽﾄ(4～3月)'!$D$26:$D$176,'採算表(VND)'!$B7,'内訳ﾘｽﾄ(4～3月)'!K$26:K$176) -> 0 | I7: =SUMIF('内訳ﾘｽﾄ(4～3月)'!$D$26:$D$176,'採算表(VND)'!$B7,'内訳ﾘｽﾄ(4～3月)'!L$26:L$176) -> 0 | J7: =SUMIF('内訳ﾘｽﾄ(4～3月)'!$D$26:$D$176,'採算表(VND)'!$B7,'内訳ﾘｽﾄ(4～3月)'!M$26:M$176) -> 0 | ... O7: =SUMIF('内訳ﾘｽﾄ(4～3月)'!$D$26:$D$176,'採算表(VND)'!$B7,'内訳ﾘｽﾄ(4～3月)'!R$26:R$176) -> 0
B8: 社外出荷合計 | C8: =C6+C7 -> 3990181700 | D8: =D6+D7 -> 1202847188 | E8: =E6+E7 -> 988119388 | F8: =F6+F7 -> 1076681739 | G8: =G6+G7 -> 1121277497 | H8: =H6+H7 -> 1201402497 | I8: =I6+I7 -> 1146521250 | J8: =J6+J7 -> 1757397541 | ... O8: =O6+O7 -> 19624119145
B9: 社内売 | C9: =SUMIF('内訳ﾘｽﾄ(4～3月)'!$D$26:$D$176,'採算表(VND)'!$B9,'内訳ﾘｽﾄ(4～3月)'!F$26:F$176) -> 0 | D9: =SUMIF('内訳ﾘｽﾄ(4～3月)'!$D$26:$D$176,'採算表(VND)'!$B9,'内訳ﾘｽﾄ(4～3月)'!G$26:G$176) -> 0 | E9: =SUMIF('内訳ﾘｽﾄ(4～3月)'!$D$26:$D$176,'採算表(VND)'!$B9,'内訳ﾘｽﾄ(4～3月)'!H$26:H$176) -> 0 | F9: =SUMIF('内訳ﾘｽﾄ(4～3月)'!$D$26:$D$176,'採算表(VND)'!$B9,'内訳ﾘｽﾄ(4～3月)'!I$26:I$176) -> 0 | G9: =SUMIF('内訳ﾘｽﾄ(4～3月)'!$D$26:$D$176,'採算表(VND)'!$B9,'内訳ﾘｽﾄ(4～3月)'!J$26:J$176) -> 0 | H9: =SUMIF('内訳ﾘｽﾄ(4～3月)'!$D$26:$D$176,'採算表(VND)'!$B9,'内訳ﾘｽﾄ(4～3月)'!K$26:K$176) -> 0 | I9: =SUMIF('内訳ﾘｽﾄ(4～3月)'!$D$26:$D$176,'採算表(VND)'!$B9,'内訳ﾘｽﾄ(4～3月)'!L$26:L$176) -> 0 | J9: =SUMIF('内訳ﾘｽﾄ(4～3月)'!$D$26:$D$176,'採算表(VND)'!$B9,'内訳ﾘｽﾄ(4～3月)'!M$26:M$176) -> 0 | ... O9: =SUMIF('内訳ﾘｽﾄ(4～3月)'!$D$26:$D$176,'採算表(VND)'!$B9,'内訳ﾘｽﾄ(4～3月)'!R$26:R$176) -> 0
B10: 社内買 | C10: =SUMIF('内訳ﾘｽﾄ(4～3月)'!$D$26:$D$176,'採算表(VND)'!$B10,'内訳ﾘｽﾄ(4～3月)'!F$26:F$176) -> 0 | D10: =SUMIF('内訳ﾘｽﾄ(4～3月)'!$D$26:$D$176,'採算表(VND)'!$B10,'内訳ﾘｽﾄ(4～3月)'!G$26:G$176) -> 0 | E10: =SUMIF('内訳ﾘｽﾄ(4～3月)'!$D$26:$D$176,'採算表(VND)'!$B10,'内訳ﾘｽﾄ(4～3月)'!H$26:H$176) -> 0 | F10: =SUMIF('内訳ﾘｽﾄ(4～3月)'!$D$26:$D$176,'採算表(VND)'!$B10,'内訳ﾘｽﾄ(4～3月)'!I$26:I$176) -> 0 | G10: =SUMIF('内訳ﾘｽﾄ(4～3月)'!$D$26:$D$176,'採算表(VND)'!$B10,'内訳ﾘｽﾄ(4～3月)'!J$26:J$176) -> 0 | H10: =SUMIF('内訳ﾘｽﾄ(4～3月)'!$D$26:$D$176,'採算表(VND)'!$B10,'内訳ﾘｽﾄ(4～3月)'!K$26:K$176) -> 0 | I10: =SUMIF('内訳ﾘｽﾄ(4～3月)'!$D$26:$D$176,'採算表(VND)'!$B10,'内訳ﾘｽﾄ(4～3月)'!L$26:L$176) -> 0 | J10: =SUMIF('内訳ﾘｽﾄ(4～3月)'!$D$26:$D$176,'採算表(VND)'!$B10,'内訳ﾘｽﾄ(4～3月)'!M$26:M$176) -> 0 | ... O10: =SUMIF('内訳ﾘｽﾄ(4～3月)'!$D$26:$D$176,'採算表(VND)'!$B10,'内訳ﾘｽﾄ(4～3月)'!R$26:R$176) -> 0
B12: 総生産 | C12: =C5-C10 -> 3990181700 | D12: =D5-D10 -> 1202847188 | E12: =E5-E10 -> 988119388 | F12: =F5-F10 -> 1076681739 | G12: =G5-G10 -> 1121277497 | H12: =H5-H10 -> 1201402497 | I12: =I5-I10 -> 1146521250 | J12: =J5-J10 -> 1757397541 | ... O12: =O5-O10 -> 19624119145
B13: 控除額 | C13: =SUM(C14:C65) -> 64144401 | D13: =SUM(D14:D65) -> 91331072 | E13: =SUM(E14:E65) -> 107317573 | F13: =SUM(F14:F65) -> 94969541 | G13: =SUM(G14:G65) -> 58414822 | H13: =SUM(H14:H65) -> 59446869 | I13: =SUM(I14:I65) -> 73291663 | J13: =SUM(J14:J65) -> 66331480 | ... O13: =SUM(O14:O65) -> 854842006
B14: 材料費 | C14: =SUMIF('内訳ﾘｽﾄ(4～3月)'!$D$26:$D$176,$B14,'内訳ﾘｽﾄ(4～3月)'!F$26:F$176) -> 0 | D14: =SUMIF('内訳ﾘｽﾄ(4～3月)'!$D$26:$D$176,$B14,'内訳ﾘｽﾄ(4～3月)'!G$26:G$176) -> 0 | E14: =SUMIF('内訳ﾘｽﾄ(4～3月)'!$D$26:$D$176,$B14,'内訳ﾘｽﾄ(4～3月)'!H$26:H$176) -> 0 | F14: =SUMIF('内訳ﾘｽﾄ(4～3月)'!$D$26:$D$176,$B14,'内訳ﾘｽﾄ(4～3月)'!I$26:I$176) -> 0 | G14: =SUMIF('内訳ﾘｽﾄ(4～3月)'!$D$26:$D$176,$B14,'内訳ﾘｽﾄ(4～3月)'!J$26:J$176) -> 0 | H14: =SUMIF('内訳ﾘｽﾄ(4～3月)'!$D$26:$D$176,$B14,'内訳ﾘｽﾄ(4～3月)'!K$26:K$176) -> 0 | I14: =SUMIF('内訳ﾘｽﾄ(4～3月)'!$D$26:$D$176,$B14,'内訳ﾘｽﾄ(4～3月)'!L$26:L$176) -> 0 | J14: =SUMIF('内訳ﾘｽﾄ(4～3月)'!$D$26:$D$176,$B14,'内訳ﾘｽﾄ(4～3月)'!M$26:M$176) -> 0 | ... N14: =SUMIF('内訳ﾘｽﾄ(4～3月)'!$D$26:$D$176,$B14,'内訳ﾘｽﾄ(4～3月)'!Q$26:Q$176) -> 0 | O14: =SUMIF('内訳ﾘｽﾄ(4～3月)'!$D$26:$D$176,'採算表(VND)'!$B14,'内訳ﾘｽﾄ(4～3月)'!R$26:R$176) -> 0
B15: 設計変更材料費 | C15: =SUMIF('内訳ﾘｽﾄ(4～3月)'!$D$26:$D$176,$B15,'内訳ﾘｽﾄ(4～3月)'!F$26:F$176) -> 0 | D15: =SUMIF('内訳ﾘｽﾄ(4～3月)'!$D$26:$D$176,$B15,'内訳ﾘｽﾄ(4～3月)'!G$26:G$176) -> 0 | E15: =SUMIF('内訳ﾘｽﾄ(4～3月)'!$D$26:$D$176,$B15,'内訳ﾘｽﾄ(4～3月)'!H$26:H$176) -> 0 | F15: =SUMIF('内訳ﾘｽﾄ(4～3月)'!$D$26:$D$176,$B15,'内訳ﾘｽﾄ(4～3月)'!I$26:I$176) -> 0 | G15: =SUMIF('内訳ﾘｽﾄ(4～3月)'!$D$26:$D$176,$B15,'内訳ﾘｽﾄ(4～3月)'!J$26:J$176) -> 0 | H15: =SUMIF('内訳ﾘｽﾄ(4～3月)'!$D$26:$D$176,$B15,'内訳ﾘｽﾄ(4～3月)'!K$26:K$176) -> 0 | I15: =SUMIF('内訳ﾘｽﾄ(4～3月)'!$D$26:$D$176,$B15,'内訳ﾘｽﾄ(4～3月)'!L$26:L$176) -> 0 | J15: =SUMIF('内訳ﾘｽﾄ(4～3月)'!$D$26:$D$176,$B15,'内訳ﾘｽﾄ(4～3月)'!M$26:M$176) -> 0 | ... N15: =SUMIF('内訳ﾘｽﾄ(4～3月)'!$D$26:$D$176,$B15,'内訳ﾘｽﾄ(4～3月)'!Q$26:Q$176) -> 0 | O15: =SUMIF('内訳ﾘｽﾄ(4～3月)'!$D$26:$D$176,'採算表(VND)'!$B15,'内訳ﾘｽﾄ(4～3月)'!R$26:R$176) -> 0
B16: 仕掛仕損 | C16: =SUMIF('内訳ﾘｽﾄ(4～3月)'!$D$26:$D$176,$B16,'内訳ﾘｽﾄ(4～3月)'!F$26:F$176) -> 0 | D16: =SUMIF('内訳ﾘｽﾄ(4～3月)'!$D$26:$D$176,$B16,'内訳ﾘｽﾄ(4～3月)'!G$26:G$176) -> 0 | E16: =SUMIF('内訳ﾘｽﾄ(4～3月)'!$D$26:$D$176,$B16,'内訳ﾘｽﾄ(4～3月)'!H$26:H$176) -> 0 | F16: =SUMIF('内訳ﾘｽﾄ(4～3月)'!$D$26:$D$176,$B16,'内訳ﾘｽﾄ(4～3月)'!I$26:I$176) -> 0 | G16: =SUMIF('内訳ﾘｽﾄ(4～3月)'!$D$26:$D$176,$B16,'内訳ﾘｽﾄ(4～3月)'!J$26:J$176) -> 0 | H16: =SUMIF('内訳ﾘｽﾄ(4～3月)'!$D$26:$D$176,$B16,'内訳ﾘｽﾄ(4～3月)'!K$26:K$176) -> 0 | I16: =SUMIF('内訳ﾘｽﾄ(4～3月)'!$D$26:$D$176,$B16,'内訳ﾘｽﾄ(4～3月)'!L$26:L$176) -> 0 | J16: =SUMIF('内訳ﾘｽﾄ(4～3月)'!$D$26:$D$176,$B16,'内訳ﾘｽﾄ(4～3月)'!M$26:M$176) -> 0 | ... N16: =SUMIF('内訳ﾘｽﾄ(4～3月)'!$D$26:$D$176,$B16,'内訳ﾘｽﾄ(4～3月)'!Q$26:Q$176) -> 0 | O16: =SUMIF('内訳ﾘｽﾄ(4～3月)'!$D$26:$D$176,'採算表(VND)'!$B16,'内訳ﾘｽﾄ(4～3月)'!R$26:R$176) -> 0
B17: 仕入製商品費 | C17: =SUMIF('内訳ﾘｽﾄ(4～3月)'!$D$26:$D$176,$B17,'内訳ﾘｽﾄ(4～3月)'!F$26:F$176) -> 0 | D17: =SUMIF('内訳ﾘｽﾄ(4～3月)'!$D$26:$D$176,$B17,'内訳ﾘｽﾄ(4～3月)'!G$26:G$176) -> 0 | E17: =SUMIF('内訳ﾘｽﾄ(4～3月)'!$D$26:$D$176,$B17,'内訳ﾘｽﾄ(4～3月)'!H$26:H$176) -> 0 | F17: =SUMIF('内訳ﾘｽﾄ(4～3月)'!$D$26:$D$176,$B17,'内訳ﾘｽﾄ(4～3月)'!I$26:I$176) -> 0 | G17: =SUMIF('内訳ﾘｽﾄ(4～3月)'!$D$26:$D$176,$B17,'内訳ﾘｽﾄ(4～3月)'!J$26:J$176) -> 0 | H17: =SUMIF('内訳ﾘｽﾄ(4～3月)'!$D$26:$D$176,$B17,'内訳ﾘｽﾄ(4～3月)'!K$26:K$176) -> 0 | I17: =SUMIF('内訳ﾘｽﾄ(4～3月)'!$D$26:$D$176,$B17,'内訳ﾘｽﾄ(4～3月)'!L$26:L$176) -> 0 | J17: =SUMIF('内訳ﾘｽﾄ(4～3月)'!$D$26:$D$176,$B17,'内訳ﾘｽﾄ(4～3月)'!M$26:M$176) -> 0 | ... N17: =SUMIF('内訳ﾘｽﾄ(4～3月)'!$D$26:$D$176,$B17,'内訳ﾘｽﾄ(4～3月)'!Q$26:Q$176) -> 0 | O17: =SUMIF('内訳ﾘｽﾄ(4～3月)'!$D$26:$D$176,'採算表(VND)'!$B17,'内訳ﾘｽﾄ(4～3月)'!R$26:R$176) -> 0
B18: 内製品有償支給原価 | C18: =SUMIF('内訳ﾘｽﾄ(4～3月)'!$D$26:$D$176,$B18,'内訳ﾘｽﾄ(4～3月)'!F$26:F$176) -> 0 | D18: =SUMIF('内訳ﾘｽﾄ(4～3月)'!$D$26:$D$176,$B18,'内訳ﾘｽﾄ(4～3月)'!G$26:G$176) -> 0 | E18: =SUMIF('内訳ﾘｽﾄ(4～3月)'!$D$26:$D$176,$B18,'内訳ﾘｽﾄ(4～3月)'!H$26:H$176) -> 0 | F18: =SUMIF('内訳ﾘｽﾄ(4～3月)'!$D$26:$D$176,$B18,'内訳ﾘｽﾄ(4～3月)'!I$26:I$176) -> 0 | G18: =SUMIF('内訳ﾘｽﾄ(4～3月)'!$D$26:$D$176,$B18,'内訳ﾘｽﾄ(4～3月)'!J$26:J$176) -> 0 | H18: =SUMIF('内訳ﾘｽﾄ(4～3月)'!$D$26:$D$176,$B18,'内訳ﾘｽﾄ(4～3月)'!K$26:K$176) -> 0 | I18: =SUMIF('内訳ﾘｽﾄ(4～3月)'!$D$26:$D$176,$B18,'内訳ﾘｽﾄ(4～3月)'!L$26:L$176) -> 0 | J18: =SUMIF('内訳ﾘｽﾄ(4～3月)'!$D$26:$D$176,$B18,'内訳ﾘｽﾄ(4～3月)'!M$26:M$176) -> 0 | ... N18: =SUMIF('内訳ﾘｽﾄ(4～3月)'!$D$26:$D$176,$B18,'内訳ﾘｽﾄ(4～3月)'!Q$26:Q$176) -> 0 | O18: =SUMIF('内訳ﾘｽﾄ(4～3月)'!$D$26:$D$176,'採算表(VND)'!$B18,'内訳ﾘｽﾄ(4～3月)'!R$26:R$176) -> 0
B19: 外注加工費 | C19: =SUMIF('内訳ﾘｽﾄ(4～3月)'!$D$26:$D$176,$B19,'内訳ﾘｽﾄ(4～3月)'!F$26:F$176) -> 0 | D19: =SUMIF('内訳ﾘｽﾄ(4～3月)'!$D$26:$D$176,$B19,'内訳ﾘｽﾄ(4～3月)'!G$26:G$176) -> 0 | E19: =SUMIF('内訳ﾘｽﾄ(4～3月)'!$D$26:$D$176,$B19,'内訳ﾘｽﾄ(4～3月)'!H$26:H$176) -> 0 | F19: =SUMIF('内訳ﾘｽﾄ(4～3月)'!$D$26:$D$176,$B19,'内訳ﾘｽﾄ(4～3月)'!I$26:I$176) -> 0 | G19: =SUMIF('内訳ﾘｽﾄ(4～3月)'!$D$26:$D$176,$B19,'内訳ﾘｽﾄ(4～3月)'!J$26:J$176) -> 0 | H19: =SUMIF('内訳ﾘｽﾄ(4～3月)'!$D$26:$D$176,$B19,'内訳ﾘｽﾄ(4～3月)'!K$26:K$176) -> 0 | I19: =SUMIF('内訳ﾘｽﾄ(4～3月)'!$D$26:$D$176,$B19,'内訳ﾘｽﾄ(4～3月)'!L$26:L$176) -> 0 | J19: =SUMIF('内訳ﾘｽﾄ(4～3月)'!$D$26:$D$176,$B19,'内訳ﾘｽﾄ(4～3月)'!M$26:M$176) -> 0 | ... N19: =SUMIF('内訳ﾘｽﾄ(4～3月)'!$D$26:$D$176,$B19,'内訳ﾘｽﾄ(4～3月)'!Q$26:Q$176) -> 0 | O19: =SUMIF('内訳ﾘｽﾄ(4～3月)'!$D$26:$D$176,'採算表(VND)'!$B19,'内訳ﾘｽﾄ(4～3月)'!R$26:R$176) -> 0
B20: 減価償却費 | C20: =SUMIF('内訳ﾘｽﾄ(4～3月)'!$D$26:$D$176,$B20,'内訳ﾘｽﾄ(4～3月)'!F$26:F$176) -> 3322662 | D20: =SUMIF('内訳ﾘｽﾄ(4～3月)'!$D$26:$D$176,$B20,'内訳ﾘｽﾄ(4～3月)'!G$26:G$176) -> 3322535 | E20: =SUMIF('内訳ﾘｽﾄ(4～3月)'!$D$26:$D$176,$B20,'内訳ﾘｽﾄ(4～3月)'!H$26:H$176) -> 3465608 | F20: =SUMIF('内訳ﾘｽﾄ(4～3月)'!$D$26:$D$176,$B20,'内訳ﾘｽﾄ(4～3月)'!I$26:I$176) -> 3476271 | G20: =SUMIF('内訳ﾘｽﾄ(4～3月)'!$D$26:$D$176,$B20,'内訳ﾘｽﾄ(4～3月)'!J$26:J$176) -> 2800771 | H20: =SUMIF('内訳ﾘｽﾄ(4～3月)'!$D$26:$D$176,$B20,'内訳ﾘｽﾄ(4～3月)'!K$26:K$176) -> 2770430 | I20: =SUMIF('内訳ﾘｽﾄ(4～3月)'!$D$26:$D$176,$B20,'内訳ﾘｽﾄ(4～3月)'!L$26:L$176) -> 2770430 | J20: =SUMIF('内訳ﾘｽﾄ(4～3月)'!$D$26:$D$176,$B20,'内訳ﾘｽﾄ(4～3月)'!M$26:M$176) -> 2770430 | ... N20: =SUMIF('内訳ﾘｽﾄ(4～3月)'!$D$26:$D$176,$B20,'内訳ﾘｽﾄ(4～3月)'!Q$26:Q$176) -> 2779951 | O20: =SUMIF('内訳ﾘｽﾄ(4～3月)'!$D$26:$D$176,'採算表(VND)'!$B20,'内訳ﾘｽﾄ(4～3月)'!R$26:R$176) -> 35762320
B21: 金型償却費 | C21: =SUMIF('内訳ﾘｽﾄ(4～3月)'!$D$26:$D$176,$B21,'内訳ﾘｽﾄ(4～3月)'!F$26:F$176) -> 0 | D21: =SUMIF('内訳ﾘｽﾄ(4～3月)'!$D$26:$D$176,$B21,'内訳ﾘｽﾄ(4～3月)'!G$26:G$176) -> 0 | E21: =SUMIF('内訳ﾘｽﾄ(4～3月)'!$D$26:$D$176,$B21,'内訳ﾘｽﾄ(4～3月)'!H$26:H$176) -> 0 | F21: =SUMIF('内訳ﾘｽﾄ(4～3月)'!$D$26:$D$176,$B21,'内訳ﾘｽﾄ(4～3月)'!I$26:I$176) -> 0 | G21: =SUMIF('内訳ﾘｽﾄ(4～3月)'!$D$26:$D$176,$B21,'内訳ﾘｽﾄ(4～3月)'!J$26:J$176) -> 0 | H21: =SUMIF('内訳ﾘｽﾄ(4～3月)'!$D$26:$D$176,$B21,'内訳ﾘｽﾄ(4～3月)'!K$26:K$176) -> 0 | I21: =SUMIF('内訳ﾘｽﾄ(4～3月)'!$D$26:$D$176,$B21,'内訳ﾘｽﾄ(4～3月)'!L$26:L$176) -> 0 | J21: =SUMIF('内訳ﾘｽﾄ(4～3月)'!$D$26:$D$176,$B21,'内訳ﾘｽﾄ(4～3月)'!M$26:M$176) -> 0 | ... N21: =SUMIF('内訳ﾘｽﾄ(4～3月)'!$D$26:$D$176,$B21,'内訳ﾘｽﾄ(4～3月)'!Q$26:Q$176) -> 0 | O21: =SUMIF('内訳ﾘｽﾄ(4～3月)'!$D$26:$D$176,'採算表(VND)'!$B21,'内訳ﾘｽﾄ(4～3月)'!R$26:R$176) -> 0
B22: 賃借料 | C22: =SUMIF('内訳ﾘｽﾄ(4～3月)'!$D$26:$D$176,$B22,'内訳ﾘｽﾄ(4～3月)'!F$26:F$176) -> 0 | D22: =SUMIF('内訳ﾘｽﾄ(4～3月)'!$D$26:$D$176,$B22,'内訳ﾘｽﾄ(4～3月)'!G$26:G$176) -> 0 | E22: =SUMIF('内訳ﾘｽﾄ(4～3月)'!$D$26:$D$176,$B22,'内訳ﾘｽﾄ(4～3月)'!H$26:H$176) -> 0 | F22: =SUMIF('内訳ﾘｽﾄ(4～3月)'!$D$26:$D$176,$B22,'内訳ﾘｽﾄ(4～3月)'!I$26:I$176) -> 0 | G22: =SUMIF('内訳ﾘｽﾄ(4～3月)'!$D$26:$D$176,$B22,'内訳ﾘｽﾄ(4～3月)'!J$26:J$176) -> 0 | H22: =SUMIF('内訳ﾘｽﾄ(4～3月)'!$D$26:$D$176,$B22,'内訳ﾘｽﾄ(4～3月)'!K$26:K$176) -> 0 | I22: =SUMIF('内訳ﾘｽﾄ(4～3月)'!$D$26:$D$176,$B22,'内訳ﾘｽﾄ(4～3月)'!L$26:L$176) -> 0 | J22: =SUMIF('内訳ﾘｽﾄ(4～3月)'!$D$26:$D$176,$B22,'内訳ﾘｽﾄ(4～3月)'!M$26:M$176) -> 0 | ... N22: =SUMIF('内訳ﾘｽﾄ(4～3月)'!$D$26:$D$176,$B22,'内訳ﾘｽﾄ(4～3月)'!Q$26:Q$176) -> 0 | O22: =SUMIF('内訳ﾘｽﾄ(4～3月)'!$D$26:$D$176,'採算表(VND)'!$B22,'内訳ﾘｽﾄ(4～3月)'!R$26:R$176) -> 0
B23: 保険料 | C23: =SUMIF('内訳ﾘｽﾄ(4～3月)'!$D$26:$D$176,$B23,'内訳ﾘｽﾄ(4～3月)'!F$26:F$176) -> 0 | D23: =SUMIF('内訳ﾘｽﾄ(4～3月)'!$D$26:$D$176,$B23,'内訳ﾘｽﾄ(4～3月)'!G$26:G$176) -> 0 | E23: =SUMIF('内訳ﾘｽﾄ(4～3月)'!$D$26:$D$176,$B23,'内訳ﾘｽﾄ(4～3月)'!H$26:H$176) -> 0 | F23: =SUMIF('内訳ﾘｽﾄ(4～3月)'!$D$26:$D$176,$B23,'内訳ﾘｽﾄ(4～3月)'!I$26:I$176) -> 0 | G23: =SUMIF('内訳ﾘｽﾄ(4～3月)'!$D$26:$D$176,$B23,'内訳ﾘｽﾄ(4～3月)'!J$26:J$176) -> 0 | H23: =SUMIF('内訳ﾘｽﾄ(4～3月)'!$D$26:$D$176,$B23,'内訳ﾘｽﾄ(4～3月)'!K$26:K$176) -> 0 | I23: =SUMIF('内訳ﾘｽﾄ(4～3月)'!$D$26:$D$176,$B23,'内訳ﾘｽﾄ(4～3月)'!L$26:L$176) -> 0 | J23: =SUMIF('内訳ﾘｽﾄ(4～3月)'!$D$26:$D$176,$B23,'内訳ﾘｽﾄ(4～3月)'!M$26:M$176) -> 0 | ... N23: =SUMIF('内訳ﾘｽﾄ(4～3月)'!$D$26:$D$176,$B23,'内訳ﾘｽﾄ(4～3月)'!Q$26:Q$176) -> 0 | O23: =SUMIF('内訳ﾘｽﾄ(4～3月)'!$D$26:$D$176,'採算表(VND)'!$B23,'内訳ﾘｽﾄ(4～3月)'!R$26:R$176) -> 0
B24: 設計委託費 | C24: =SUMIF('内訳ﾘｽﾄ(4～3月)'!$D$26:$D$176,$B24,'内訳ﾘｽﾄ(4～3月)'!F$26:F$176) -> 0 | D24: =SUMIF('内訳ﾘｽﾄ(4～3月)'!$D$26:$D$176,$B24,'内訳ﾘｽﾄ(4～3月)'!G$26:G$176) -> 0 | E24: =SUMIF('内訳ﾘｽﾄ(4～3月)'!$D$26:$D$176,$B24,'内訳ﾘｽﾄ(4～3月)'!H$26:H$176) -> 0 | F24: =SUMIF('内訳ﾘｽﾄ(4～3月)'!$D$26:$D$176,$B24,'内訳ﾘｽﾄ(4～3月)'!I$26:I$176) -> 0 | G24: =SUMIF('内訳ﾘｽﾄ(4～3月)'!$D$26:$D$176,$B24,'内訳ﾘｽﾄ(4～3月)'!J$26:J$176) -> 0 | H24: =SUMIF('内訳ﾘｽﾄ(4～3月)'!$D$26:$D$176,$B24,'内訳ﾘｽﾄ(4～3月)'!K$26:K$176) -> 0 | I24: =SUMIF('内訳ﾘｽﾄ(4～3月)'!$D$26:$D$176,$B24,'内訳ﾘｽﾄ(4～3月)'!L$26:L$176) -> 0 | J24: =SUMIF('内訳ﾘｽﾄ(4～3月)'!$D$26:$D$176,$B24,'内訳ﾘｽﾄ(4～3月)'!M$26:M$176) -> 0 | ... N24: =SUMIF('内訳ﾘｽﾄ(4～3月)'!$D$26:$D$176,$B24,'内訳ﾘｽﾄ(4～3月)'!Q$26:Q$176) -> 0 | O24: =SUMIF('内訳ﾘｽﾄ(4～3月)'!$D$26:$D$176,'採算表(VND)'!$B24,'内訳ﾘｽﾄ(4～3月)'!R$26:R$176) -> 0
B25: 消耗品費 | C25: =SUMIF('内訳ﾘｽﾄ(4～3月)'!$D$26:$D$176,$B25,'内訳ﾘｽﾄ(4～3月)'!F$26:F$176) -> 167877 | D25: =SUMIF('内訳ﾘｽﾄ(4～3月)'!$D$26:$D$176,$B25,'内訳ﾘｽﾄ(4～3月)'!G$26:G$176) -> 184734 | E25: =SUMIF('内訳ﾘｽﾄ(4～3月)'!$D$26:$D$176,$B25,'内訳ﾘｽﾄ(4～3月)'!H$26:H$176) -> 176283 | F25: =SUMIF('内訳ﾘｽﾄ(4～3月)'!$D$26:$D$176,$B25,'内訳ﾘｽﾄ(4～3月)'!I$26:I$176) -> 202383 | G25: =SUMIF('内訳ﾘｽﾄ(4～3月)'!$D$26:$D$176,$B25,'内訳ﾘｽﾄ(4～3月)'!J$26:J$176) -> 193482 | H25: =SUMIF('内訳ﾘｽﾄ(4～3月)'!$D$26:$D$176,$B25,'内訳ﾘｽﾄ(4～3月)'!K$26:K$176) -> 158886 | I25: =SUMIF('内訳ﾘｽﾄ(4～3月)'!$D$26:$D$176,$B25,'内訳ﾘｽﾄ(4～3月)'!L$26:L$176) -> 246675 | J25: =SUMIF('内訳ﾘｽﾄ(4～3月)'!$D$26:$D$176,$B25,'内訳ﾘｽﾄ(4～3月)'!M$26:M$176) -> 225489 | ... N25: =SUMIF('内訳ﾘｽﾄ(4～3月)'!$D$26:$D$176,$B25,'内訳ﾘｽﾄ(4～3月)'!Q$26:Q$176) -> 215446 | O25: =SUMIF('内訳ﾘｽﾄ(4～3月)'!$D$26:$D$176,'採算表(VND)'!$B25,'内訳ﾘｽﾄ(4～3月)'!R$26:R$176) -> 2373626
... B65: 本社機構経費 | C65: =SUMIF('内訳ﾘｽﾄ(4～3月)'!$D$26:$D$176,$B65,'内訳ﾘｽﾄ(4～3月)'!F$26:F$176) -> 0 | D65: =SUMIF('内訳ﾘｽﾄ(4～3月)'!$D$26:$D$176,$B65,'内訳ﾘｽﾄ(4～3月)'!G$26:G$176) -> 0 | E65: =SUMIF('内訳ﾘｽﾄ(4～3月)'!$D$26:$D$176,$B65,'内訳ﾘｽﾄ(4～3月)'!H$26:H$176) -> 0 | F65: =SUMIF('内訳ﾘｽﾄ(4～3月)'!$D$26:$D$176,$B65,'内訳ﾘｽﾄ(4～3月)'!I$26:I$176) -> 0 | G65: =SUMIF('内訳ﾘｽﾄ(4～3月)'!$D$26:$D$176,$B65,'内訳ﾘｽﾄ(4～3月)'!J$26:J$176) -> 0 | H65: =SUMIF('内訳ﾘｽﾄ(4～3月)'!$D$26:$D$176,$B65,'内訳ﾘｽﾄ(4～3月)'!K$26:K$176) -> 0 | I65: =SUMIF('内訳ﾘｽﾄ(4～3月)'!$D$26:$D$176,$B65,'内訳ﾘｽﾄ(4～3月)'!L$26:L$176) -> 0 | J65: =SUMIF('内訳ﾘｽﾄ(4～3月)'!$D$26:$D$176,$B65,'内訳ﾘｽﾄ(4～3月)'!M$26:M$176) -> 0 | ... N65: =SUMIF('内訳ﾘｽﾄ(4～3月)'!$D$26:$D$176,$B65,'内訳ﾘｽﾄ(4～3月)'!Q$26:Q$176) -> 0 | O65: =SUMIF('内訳ﾘｽﾄ(4～3月)'!$D$26:$D$176,'採算表(VND)'!$B65,'内訳ﾘｽﾄ(4～3月)'!R$26:R$176) -> 0
B66: 差引収益 | C66: =C12-C13 -> 3926037299 | D66: =D12-D13 -> 1111516116 | E66: =E12-E13 -> 880801815 | F66: =F12-F13 -> 981712198 | G66: =G12-G13 -> 1062862675 | H66: =H12-H13 -> 1141955628 | I66: =I12-I13 -> 1073229587 | J66: =J12-J13 -> 1691066061 | ... N66: =N12-N13 -> 1721753887 | O66: =IF(ISBLANK(O4),"",O12-O13) -> 18769277139
B67: 総時間 | C67: =C73+C79 -> 3615.5 | D67: =D73+D79 -> 3441.25 | E67: =E73+E79 -> 3794.75 | F67: =F73+F79 -> 4197 | G67: =G73+G79 -> 3661 | H67: =H73+H79 -> 3480.75 | I67: =I73+I79 -> 4683.25 | J67: =J73+J79 -> 4082.75 | ... N67: =N73+N79 -> 4087 | O67: =IF(ISBLANK(O4),"",O73+O79) -> 46637.75
B68: 直接部門 | C68: =SUMIF('内訳ﾘｽﾄ(4～3月)'!$D$8:$D$15,'採算表(VND)'!$B68,'内訳ﾘｽﾄ(4～3月)'!F$8:F$15) -> 2992 | D68: =SUMIF('内訳ﾘｽﾄ(4～3月)'!$D$8:$D$15,'採算表(VND)'!$B68,'内訳ﾘｽﾄ(4～3月)'!G$8:G$15) -> 2839 | E68: =SUMIF('内訳ﾘｽﾄ(4～3月)'!$D$8:$D$15,'採算表(VND)'!$B68,'内訳ﾘｽﾄ(4～3月)'!H$8:H$15) -> 3145 | F68: =SUMIF('内訳ﾘｽﾄ(4～3月)'!$D$8:$D$15,'採算表(VND)'!$B68,'内訳ﾘｽﾄ(4～3月)'!I$8:I$15) -> 3451 | G68: =SUMIF('内訳ﾘｽﾄ(4～3月)'!$D$8:$D$15,'採算表(VND)'!$B68,'内訳ﾘｽﾄ(4～3月)'!J$8:J$15) -> 2992 | H68: =SUMIF('内訳ﾘｽﾄ(4～3月)'!$D$8:$D$15,'採算表(VND)'!$B68,'内訳ﾘｽﾄ(4～3月)'!K$8:K$15) -> 2839 | I68: =SUMIF('内訳ﾘｽﾄ(4～3月)'!$D$8:$D$15,'採算表(VND)'!$B68,'内訳ﾘｽﾄ(4～3月)'!L$8:L$15) -> 3842 | J68: =SUMIF('内訳ﾘｽﾄ(4～3月)'!$D$8:$D$15,'採算表(VND)'!$B68,'内訳ﾘｽﾄ(4～3月)'!M$8:M$15) -> 3332 | ... N68: =SUMIF('内訳ﾘｽﾄ(4～3月)'!$D$8:$D$15,'採算表(VND)'!$B68,'内訳ﾘｽﾄ(4～3月)'!Q$8:Q$15) -> 3332 | O68: =SUMIF('内訳ﾘｽﾄ(4～3月)'!$D$8:$D$15,'採算表(VND)'!$B68,'内訳ﾘｽﾄ(4～3月)'!$R$8:$R$15) -> 38207.5
B69: 部内間接部門 | C69: =IF('内訳ﾘｽﾄ(4～3月)'!$D$5="製造",SUMIF('内訳ﾘｽﾄ(4～3月)'!$D$8:$D$15,$B69,'内訳ﾘｽﾄ(4～3月)'!F$8:F$15),IF('内訳ﾘｽﾄ(4～3月)'!$D$5="部内間接",-C$68,0)) -> 0 | D69: =IF('内訳ﾘｽﾄ(4～3月)'!$D$5="製造",SUMIF('内訳ﾘｽﾄ(4～3月)'!$D$8:$D$15,$B69,'内訳ﾘｽﾄ(4～3月)'!G$8:G$15),IF('内訳ﾘｽﾄ(4～3月)'!$D$5="部内間接",-D$68,0)) -> 0 | E69: =IF('内訳ﾘｽﾄ(4～3月)'!$D$5="製造",SUMIF('内訳ﾘｽﾄ(4～3月)'!$D$8:$D$15,$B69,'内訳ﾘｽﾄ(4～3月)'!H$8:H$15),IF('内訳ﾘｽﾄ(4～3月)'!$D$5="部内間接",-E$68,0)) -> 0 | F69: =IF('内訳ﾘｽﾄ(4～3月)'!$D$5="製造",SUMIF('内訳ﾘｽﾄ(4～3月)'!$D$8:$D$15,$B69,'内訳ﾘｽﾄ(4～3月)'!I$8:I$15),IF('内訳ﾘｽﾄ(4～3月)'!$D$5="部内間接",-F$68,0)) -> 0 | G69: =IF('内訳ﾘｽﾄ(4～3月)'!$D$5="製造",SUMIF('内訳ﾘｽﾄ(4～3月)'!$D$8:$D$15,$B69,'内訳ﾘｽﾄ(4～3月)'!J$8:J$15),IF('内訳ﾘｽﾄ(4～3月)'!$D$5="部内間接",-G$68,0)) -> 0 | H69: =IF('内訳ﾘｽﾄ(4～3月)'!$D$5="製造",SUMIF('内訳ﾘｽﾄ(4～3月)'!$D$8:$D$15,$B69,'内訳ﾘｽﾄ(4～3月)'!K$8:K$15),IF('内訳ﾘｽﾄ(4～3月)'!$D$5="部内間接",-H$68,0)) -> 0 | I69: =IF('内訳ﾘｽﾄ(4～3月)'!$D$5="製造",SUMIF('内訳ﾘｽﾄ(4～3月)'!$D$8:$D$15,$B69,'内訳ﾘｽﾄ(4～3月)'!L$8:L$15),IF('内訳ﾘｽﾄ(4～3月)'!$D$5="部内間接",-I$68,0)) -> 0 | J69: =IF('内訳ﾘｽﾄ(4～3月)'!$D$5="製造",SUMIF('内訳ﾘｽﾄ(4～3月)'!$D$8:$D$15,$B69,'内訳ﾘｽﾄ(4～3月)'!M$8:M$15),IF('内訳ﾘｽﾄ(4～3月)'!$D$5="部内間接",-J$68,0)) -> 0 | ... N69: =IF('内訳ﾘｽﾄ(4～3月)'!$D$5="製造",SUMIF('内訳ﾘｽﾄ(4～3月)'!$D$8:$D$15,$B69,'内訳ﾘｽﾄ(4～3月)'!Q$8:Q$15),IF('内訳ﾘｽﾄ(4～3月)'!$D$5="部内間接",-N$68,0)) -> 0 | O69: =IF('内訳ﾘｽﾄ(4～3月)'!$D$5="部内間接",-SUM(O$68),IF('内訳ﾘｽﾄ(4～3月)'!$D$5="製造",SUMIF('内訳ﾘｽﾄ(4～3月)'!$D$8:$D$15,'採算表(VND)'!$B69,'内訳ﾘｽﾄ(4～3月)'!$R$8:$R$15),0)) -> 0
B70: 部外間接部門1 | C70: =IF('内訳ﾘｽﾄ(4～3月)'!$D$5="製造",SUMIF('内訳ﾘｽﾄ(4～3月)'!$D$8:$D$15,$B70,'内訳ﾘｽﾄ(4～3月)'!F$8:F$15),IF('内訳ﾘｽﾄ(4～3月)'!$D$5="部外間接1",-C$68,0)) -> 10.25 | D70: =IF('内訳ﾘｽﾄ(4～3月)'!$D$5="製造",SUMIF('内訳ﾘｽﾄ(4～3月)'!$D$8:$D$15,$B70,'内訳ﾘｽﾄ(4～3月)'!G$8:G$15),IF('内訳ﾘｽﾄ(4～3月)'!$D$5="部外間接1",-D$68,0)) -> 10.5 | E70: =IF('内訳ﾘｽﾄ(4～3月)'!$D$5="製造",SUMIF('内訳ﾘｽﾄ(4～3月)'!$D$8:$D$15,$B70,'内訳ﾘｽﾄ(4～3月)'!H$8:H$15),IF('内訳ﾘｽﾄ(4～3月)'!$D$5="部外間接1",-E$68,0)) -> 11.5 | F70: =IF('内訳ﾘｽﾄ(4～3月)'!$D$5="製造",SUMIF('内訳ﾘｽﾄ(4～3月)'!$D$8:$D$15,$B70,'内訳ﾘｽﾄ(4～3月)'!I$8:I$15),IF('内訳ﾘｽﾄ(4～3月)'!$D$5="部外間接1",-F$68,0)) -> 16.25 | G70: =IF('内訳ﾘｽﾄ(4～3月)'!$D$5="製造",SUMIF('内訳ﾘｽﾄ(4～3月)'!$D$8:$D$15,$B70,'内訳ﾘｽﾄ(4～3月)'!J$8:J$15),IF('内訳ﾘｽﾄ(4～3月)'!$D$5="部外間接1",-G$68,0)) -> 14.25 | H70: =IF('内訳ﾘｽﾄ(4～3月)'!$D$5="製造",SUMIF('内訳ﾘｽﾄ(4～3月)'!$D$8:$D$15,$B70,'内訳ﾘｽﾄ(4～3月)'!K$8:K$15),IF('内訳ﾘｽﾄ(4～3月)'!$D$5="部外間接1",-H$68,0)) -> 13.5 | I70: =IF('内訳ﾘｽﾄ(4～3月)'!$D$5="製造",SUMIF('内訳ﾘｽﾄ(4～3月)'!$D$8:$D$15,$B70,'内訳ﾘｽﾄ(4～3月)'!L$8:L$15),IF('内訳ﾘｽﾄ(4～3月)'!$D$5="部外間接1",-I$68,0)) -> 16.5 | J70: =IF('内訳ﾘｽﾄ(4～3月)'!$D$5="製造",SUMIF('内訳ﾘｽﾄ(4～3月)'!$D$8:$D$15,$B70,'内訳ﾘｽﾄ(4～3月)'!M$8:M$15),IF('内訳ﾘｽﾄ(4～3月)'!$D$5="部外間接1",-J$68,0)) -> 14.25 | ... N70: =IF('内訳ﾘｽﾄ(4～3月)'!$D$5="製造",SUMIF('内訳ﾘｽﾄ(4～3月)'!$D$8:$D$15,$B70,'内訳ﾘｽﾄ(4～3月)'!Q$8:Q$15),IF('内訳ﾘｽﾄ(4～3月)'!$D$5="部外間接1",-N$68,0)) -> 15 | O70: =IF('内訳ﾘｽﾄ(4～3月)'!$D$5="部外間接1",-SUM(O$68),IF('内訳ﾘｽﾄ(4～3月)'!$D$5="製造",SUMIF('内訳ﾘｽﾄ(4～3月)'!$D$8:$D$15,'採算表(VND)'!$B70,'内訳ﾘｽﾄ(4～3月)'!$R$8:$R$15),0)) -> 163.75
B71: 部外間接部門2 | C71: =IF('内訳ﾘｽﾄ(4～3月)'!$D$5="製造",SUMIF('内訳ﾘｽﾄ(4～3月)'!$D$8:$D$15,$B71,'内訳ﾘｽﾄ(4～3月)'!F$8:F$15),IF('内訳ﾘｽﾄ(4～3月)'!$D$5="部外間接2",-C$68,0)) -> 19.5 | D71: =IF('内訳ﾘｽﾄ(4～3月)'!$D$5="製造",SUMIF('内訳ﾘｽﾄ(4～3月)'!$D$8:$D$15,$B71,'内訳ﾘｽﾄ(4～3月)'!G$8:G$15),IF('内訳ﾘｽﾄ(4～3月)'!$D$5="部外間接2",-D$68,0)) -> 18.25 | E71: =IF('内訳ﾘｽﾄ(4～3月)'!$D$5="製造",SUMIF('内訳ﾘｽﾄ(4～3月)'!$D$8:$D$15,$B71,'内訳ﾘｽﾄ(4～3月)'!H$8:H$15),IF('内訳ﾘｽﾄ(4～3月)'!$D$5="部外間接2",-E$68,0)) -> 20.75 | F71: =IF('内訳ﾘｽﾄ(4～3月)'!$D$5="製造",SUMIF('内訳ﾘｽﾄ(4～3月)'!$D$8:$D$15,$B71,'内訳ﾘｽﾄ(4～3月)'!I$8:I$15),IF('内訳ﾘｽﾄ(4～3月)'!$D$5="部外間接2",-F$68,0)) -> 31.25 | G71: =IF('内訳ﾘｽﾄ(4～3月)'!$D$5="製造",SUMIF('内訳ﾘｽﾄ(4～3月)'!$D$8:$D$15,$B71,'内訳ﾘｽﾄ(4～3月)'!J$8:J$15),IF('内訳ﾘｽﾄ(4～3月)'!$D$5="部外間接2",-G$68,0)) -> 27 | H71: =IF('内訳ﾘｽﾄ(4～3月)'!$D$5="製造",SUMIF('内訳ﾘｽﾄ(4～3月)'!$D$8:$D$15,$B71,'内訳ﾘｽﾄ(4～3月)'!K$8:K$15),IF('内訳ﾘｽﾄ(4～3月)'!$D$5="部外間接2",-H$68,0)) -> 26.5 | I71: =IF('内訳ﾘｽﾄ(4～3月)'!$D$5="製造",SUMIF('内訳ﾘｽﾄ(4～3月)'!$D$8:$D$15,$B71,'内訳ﾘｽﾄ(4～3月)'!L$8:L$15),IF('内訳ﾘｽﾄ(4～3月)'!$D$5="部外間接2",-I$68,0)) -> 32.25 | J71: =IF('内訳ﾘｽﾄ(4～3月)'!$D$5="製造",SUMIF('内訳ﾘｽﾄ(4～3月)'!$D$8:$D$15,$B71,'内訳ﾘｽﾄ(4～3月)'!M$8:M$15),IF('内訳ﾘｽﾄ(4～3月)'!$D$5="部外間接2",-J$68,0)) -> 28.25 | ... N71: =IF('内訳ﾘｽﾄ(4～3月)'!$D$5="製造",SUMIF('内訳ﾘｽﾄ(4～3月)'!$D$8:$D$15,$B71,'内訳ﾘｽﾄ(4～3月)'!Q$8:Q$15),IF('内訳ﾘｽﾄ(4～3月)'!$D$5="部外間接2",-N$68,0)) -> 28.25 | O71: =IF('内訳ﾘｽﾄ(4～3月)'!$D$5="部外間接2",-SUM(O$68),IF('内訳ﾘｽﾄ(4～3月)'!$D$5="製造",SUMIF('内訳ﾘｽﾄ(4～3月)'!$D$8:$D$15,'採算表(VND)'!$B71,'内訳ﾘｽﾄ(4～3月)'!$R$8:$R$15),0)) -> 312.5
B72: 工場間接部門 | C72: =IF('内訳ﾘｽﾄ(4～3月)'!$D$5="製造",SUMIF('内訳ﾘｽﾄ(4～3月)'!$D$8:$D$15,$B72,'内訳ﾘｽﾄ(4～3月)'!F$8:F$15),IF('内訳ﾘｽﾄ(4～3月)'!$D$5="工場間接",-C$68,0)) -> 85.25 | D72: =IF('内訳ﾘｽﾄ(4～3月)'!$D$5="製造",SUMIF('内訳ﾘｽﾄ(4～3月)'!$D$8:$D$15,$B72,'内訳ﾘｽﾄ(4～3月)'!G$8:G$15),IF('内訳ﾘｽﾄ(4～3月)'!$D$5="工場間接",-D$68,0)) -> 85.5 | E72: =IF('内訳ﾘｽﾄ(4～3月)'!$D$5="製造",SUMIF('内訳ﾘｽﾄ(4～3月)'!$D$8:$D$15,$B72,'内訳ﾘｽﾄ(4～3月)'!H$8:H$15),IF('内訳ﾘｽﾄ(4～3月)'!$D$5="工場間接",-E$68,0)) -> 89.75 | F72: =IF('内訳ﾘｽﾄ(4～3月)'!$D$5="製造",SUMIF('内訳ﾘｽﾄ(4～3月)'!$D$8:$D$15,$B72,'内訳ﾘｽﾄ(4～3月)'!I$8:I$15),IF('内訳ﾘｽﾄ(4～3月)'!$D$5="工場間接",-F$68,0)) -> 128.5 | G72: =IF('内訳ﾘｽﾄ(4～3月)'!$D$5="製造",SUMIF('内訳ﾘｽﾄ(4～3月)'!$D$8:$D$15,$B72,'内訳ﾘｽﾄ(4～3月)'!J$8:J$15),IF('内訳ﾘｽﾄ(4～3月)'!$D$5="工場間接",-G$68,0)) -> 117.25 | H72: =IF('内訳ﾘｽﾄ(4～3月)'!$D$5="製造",SUMIF('内訳ﾘｽﾄ(4～3月)'!$D$8:$D$15,$B72,'内訳ﾘｽﾄ(4～3月)'!K$8:K$15),IF('内訳ﾘｽﾄ(4～3月)'!$D$5="工場間接",-H$68,0)) -> 110 | I72: =IF('内訳ﾘｽﾄ(4～3月)'!$D$5="製造",SUMIF('内訳ﾘｽﾄ(4～3月)'!$D$8:$D$15,$B72,'内訳ﾘｽﾄ(4～3月)'!L$8:L$15),IF('内訳ﾘｽﾄ(4～3月)'!$D$5="工場間接",-I$68,0)) -> 130.25 | J72: =IF('内訳ﾘｽﾄ(4～3月)'!$D$5="製造",SUMIF('内訳ﾘｽﾄ(4～3月)'!$D$8:$D$15,$B72,'内訳ﾘｽﾄ(4～3月)'!M$8:M$15),IF('内訳ﾘｽﾄ(4～3月)'!$D$5="工場間接",-J$68,0)) -> 118.5 | ... N72: =IF('内訳ﾘｽﾄ(4～3月)'!$D$5="製造",SUMIF('内訳ﾘｽﾄ(4～3月)'!$D$8:$D$15,$B72,'内訳ﾘｽﾄ(4～3月)'!Q$8:Q$15),IF('内訳ﾘｽﾄ(4～3月)'!$D$5="工場間接",-N$68,0)) -> 121.25 | O72: =IF('内訳ﾘｽﾄ(4～3月)'!$D$5="工場間接",-SUM(O$68),IF('内訳ﾘｽﾄ(4～3月)'!$D$5="製造",SUMIF('内訳ﾘｽﾄ(4～3月)'!$D$8:$D$15,'採算表(VND)'!$B72,'内訳ﾘｽﾄ(4～3月)'!$R$8:$R$15),0)) -> 1325
B73: 定時間合計 | C73: =SUM(C68:C72) -> 3107 | D73: =SUM(D68:D72) -> 2953.25 | E73: =SUM(E68:E72) -> 3267 | F73: =SUM(F68:F72) -> 3627 | G73: =SUM(G68:G72) -> 3150.5 | H73: =SUM(H68:H72) -> 2989 | I73: =SUM(I68:I72) -> 4021 | J73: =SUM(J68:J72) -> 3493 | ... N73: =SUM(N68:N72) -> 3496.5 | O73: =IF(ISBLANK(O4),"",SUM(O68:O72)) -> 40008.75
B74: 直接部門 | C74: =SUMIF('内訳ﾘｽﾄ(4～3月)'!$D$16:$D$23,'採算表(VND)'!$B74,'内訳ﾘｽﾄ(4～3月)'!F$16:F$23) -> 502 | D74: =SUMIF('内訳ﾘｽﾄ(4～3月)'!$D$16:$D$23,'採算表(VND)'!$B74,'内訳ﾘｽﾄ(4～3月)'!G$16:G$23) -> 482 | E74: =SUMIF('内訳ﾘｽﾄ(4～3月)'!$D$16:$D$23,'採算表(VND)'!$B74,'内訳ﾘｽﾄ(4～3月)'!H$16:H$23) -> 522 | F74: =SUMIF('内訳ﾘｽﾄ(4～3月)'!$D$16:$D$23,'採算表(VND)'!$B74,'内訳ﾘｽﾄ(4～3月)'!I$16:I$23) -> 562 | G74: =SUMIF('内訳ﾘｽﾄ(4～3月)'!$D$16:$D$23,'採算表(VND)'!$B74,'内訳ﾘｽﾄ(4～3月)'!J$16:J$23) -> 502 | H74: =SUMIF('内訳ﾘｽﾄ(4～3月)'!$D$16:$D$23,'採算表(VND)'!$B74,'内訳ﾘｽﾄ(4～3月)'!K$16:K$23) -> 482 | I74: =SUMIF('内訳ﾘｽﾄ(4～3月)'!$D$16:$D$23,'採算表(VND)'!$B74,'内訳ﾘｽﾄ(4～3月)'!L$16:L$23) -> 654 | J74: =SUMIF('内訳ﾘｽﾄ(4～3月)'!$D$16:$D$23,'採算表(VND)'!$B74,'内訳ﾘｽﾄ(4～3月)'!M$16:M$23) -> 582 | ... N74: =SUMIF('内訳ﾘｽﾄ(4～3月)'!$D$16:$D$23,'採算表(VND)'!$B74,'内訳ﾘｽﾄ(4～3月)'!Q$16:Q$23) -> 582 | O74: =SUMIF('内訳ﾘｽﾄ(4～3月)'!$D$16:$D$23,'採算表(VND)'!$B74,'内訳ﾘｽﾄ(4～3月)'!$R$16:$R$23) -> 6534
B75: 部内間接部門 | C75: =IF('内訳ﾘｽﾄ(4～3月)'!$D$5="製造",SUMIF('内訳ﾘｽﾄ(4～3月)'!$D$16:$D$23,$B75,'内訳ﾘｽﾄ(4～3月)'!F$16:F$23),IF('内訳ﾘｽﾄ(4～3月)'!$D$5="部内間接",-C$74,0)) -> 0 | D75: =IF('内訳ﾘｽﾄ(4～3月)'!$D$5="製造",SUMIF('内訳ﾘｽﾄ(4～3月)'!$D$16:$D$23,$B75,'内訳ﾘｽﾄ(4～3月)'!G$16:G$23),IF('内訳ﾘｽﾄ(4～3月)'!$D$5="部内間接",-D$74,0)) -> 0 | E75: =IF('内訳ﾘｽﾄ(4～3月)'!$D$5="製造",SUMIF('内訳ﾘｽﾄ(4～3月)'!$D$16:$D$23,$B75,'内訳ﾘｽﾄ(4～3月)'!H$16:H$23),IF('内訳ﾘｽﾄ(4～3月)'!$D$5="部内間接",-E$74,0)) -> 0 | F75: =IF('内訳ﾘｽﾄ(4～3月)'!$D$5="製造",SUMIF('内訳ﾘｽﾄ(4～3月)'!$D$16:$D$23,$B75,'内訳ﾘｽﾄ(4～3月)'!I$16:I$23),IF('内訳ﾘｽﾄ(4～3月)'!$D$5="部内間接",-F$74,0)) -> 0 | G75: =IF('内訳ﾘｽﾄ(4～3月)'!$D$5="製造",SUMIF('内訳ﾘｽﾄ(4～3月)'!$D$16:$D$23,$B75,'内訳ﾘｽﾄ(4～3月)'!J$16:J$23),IF('内訳ﾘｽﾄ(4～3月)'!$D$5="部内間接",-G$74,0)) -> 0 | H75: =IF('内訳ﾘｽﾄ(4～3月)'!$D$5="製造",SUMIF('内訳ﾘｽﾄ(4～3月)'!$D$16:$D$23,$B75,'内訳ﾘｽﾄ(4～3月)'!K$16:K$23),IF('内訳ﾘｽﾄ(4～3月)'!$D$5="部内間接",-H$74,0)) -> 0 | I75: =IF('内訳ﾘｽﾄ(4～3月)'!$D$5="製造",SUMIF('内訳ﾘｽﾄ(4～3月)'!$D$16:$D$23,$B75,'内訳ﾘｽﾄ(4～3月)'!L$16:L$23),IF('内訳ﾘｽﾄ(4～3月)'!$D$5="部内間接",-I$74,0)) -> 0 | J75: =IF('内訳ﾘｽﾄ(4～3月)'!$D$5="製造",SUMIF('内訳ﾘｽﾄ(4～3月)'!$D$16:$D$23,$B75,'内訳ﾘｽﾄ(4～3月)'!M$16:M$23),IF('内訳ﾘｽﾄ(4～3月)'!$D$5="部内間接",-J$74,0)) -> 0 | ... N75: =IF('内訳ﾘｽﾄ(4～3月)'!$D$5="製造",SUMIF('内訳ﾘｽﾄ(4～3月)'!$D$16:$D$23,$B75,'内訳ﾘｽﾄ(4～3月)'!Q$16:Q$23),IF('内訳ﾘｽﾄ(4～3月)'!$D$5="部内間接",-N$74,0)) -> 0 | O75: =IF('内訳ﾘｽﾄ(4～3月)'!$D$5="部内間接",-SUM(O$74),IF('内訳ﾘｽﾄ(4～3月)'!$D$5="製造",SUMIF('内訳ﾘｽﾄ(4～3月)'!$D$16:$D$23,'採算表(VND)'!$B75,'内訳ﾘｽﾄ(4～3月)'!$R$16:$R$23),0)) -> 0
B76: 部外間接部門1 | C76: =IF('内訳ﾘｽﾄ(4～3月)'!$D$5="製造",SUMIF('内訳ﾘｽﾄ(4～3月)'!$D$16:$D$23,$B76,'内訳ﾘｽﾄ(4～3月)'!F$16:F$23),IF('内訳ﾘｽﾄ(4～3月)'!$D$5="部外間接1",-C$74,0)) -> 0.75 | D76: =IF('内訳ﾘｽﾄ(4～3月)'!$D$5="製造",SUMIF('内訳ﾘｽﾄ(4～3月)'!$D$16:$D$23,$B76,'内訳ﾘｽﾄ(4～3月)'!G$16:G$23),IF('内訳ﾘｽﾄ(4～3月)'!$D$5="部外間接1",-D$74,0)) -> 0.75 | E76: =IF('内訳ﾘｽﾄ(4～3月)'!$D$5="製造",SUMIF('内訳ﾘｽﾄ(4～3月)'!$D$16:$D$23,$B76,'内訳ﾘｽﾄ(4～3月)'!H$16:H$23),IF('内訳ﾘｽﾄ(4～3月)'!$D$5="部外間接1",-E$74,0)) -> 0.75 | F76: =IF('内訳ﾘｽﾄ(4～3月)'!$D$5="製造",SUMIF('内訳ﾘｽﾄ(4～3月)'!$D$16:$D$23,$B76,'内訳ﾘｽﾄ(4～3月)'!I$16:I$23),IF('内訳ﾘｽﾄ(4～3月)'!$D$5="部外間接1",-F$74,0)) -> 1 | G76: =IF('内訳ﾘｽﾄ(4～3月)'!$D$5="製造",SUMIF('内訳ﾘｽﾄ(4～3月)'!$D$16:$D$23,$B76,'内訳ﾘｽﾄ(4～3月)'!J$16:J$23),IF('内訳ﾘｽﾄ(4～3月)'!$D$5="部外間接1",-G$74,0)) -> 1 | H76: =IF('内訳ﾘｽﾄ(4～3月)'!$D$5="製造",SUMIF('内訳ﾘｽﾄ(4～3月)'!$D$16:$D$23,$B76,'内訳ﾘｽﾄ(4～3月)'!K$16:K$23),IF('内訳ﾘｽﾄ(4～3月)'!$D$5="部外間接1",-H$74,0)) -> 0.75 | I76: =IF('内訳ﾘｽﾄ(4～3月)'!$D$5="製造",SUMIF('内訳ﾘｽﾄ(4～3月)'!$D$16:$D$23,$B76,'内訳ﾘｽﾄ(4～3月)'!L$16:L$23),IF('内訳ﾘｽﾄ(4～3月)'!$D$5="部外間接1",-I$74,0)) -> 1 | J76: =IF('内訳ﾘｽﾄ(4～3月)'!$D$5="製造",SUMIF('内訳ﾘｽﾄ(4～3月)'!$D$16:$D$23,$B76,'内訳ﾘｽﾄ(4～3月)'!M$16:M$23),IF('内訳ﾘｽﾄ(4～3月)'!$D$5="部外間接1",-J$74,0)) -> 0.75 | ... N76: =IF('内訳ﾘｽﾄ(4～3月)'!$D$5="製造",SUMIF('内訳ﾘｽﾄ(4～3月)'!$D$16:$D$23,$B76,'内訳ﾘｽﾄ(4～3月)'!Q$16:Q$23),IF('内訳ﾘｽﾄ(4～3月)'!$D$5="部外間接1",-N$74,0)) -> 0.75 | O76: =IF('内訳ﾘｽﾄ(4～3月)'!$D$5="部外間接1",-SUM(O$74),IF('内訳ﾘｽﾄ(4～3月)'!$D$5="製造",SUMIF('内訳ﾘｽﾄ(4～3月)'!$D$16:$D$23,'採算表(VND)'!$B76,'内訳ﾘｽﾄ(4～3月)'!$R$16:$R$23),0)) -> 10
B77: 部外間接部門2 | C77: =IF('内訳ﾘｽﾄ(4～3月)'!$D$5="製造",SUMIF('内訳ﾘｽﾄ(4～3月)'!$D$16:$D$23,$B77,'内訳ﾘｽﾄ(4～3月)'!F$16:F$23),IF('内訳ﾘｽﾄ(4～3月)'!$D$5="部外間接2",-C$74,0)) -> 1.25 | D77: =IF('内訳ﾘｽﾄ(4～3月)'!$D$5="製造",SUMIF('内訳ﾘｽﾄ(4～3月)'!$D$16:$D$23,$B77,'内訳ﾘｽﾄ(4～3月)'!G$16:G$23),IF('内訳ﾘｽﾄ(4～3月)'!$D$5="部外間接2",-D$74,0)) -> 1.25 | E77: =IF('内訳ﾘｽﾄ(4～3月)'!$D$5="製造",SUMIF('内訳ﾘｽﾄ(4～3月)'!$D$16:$D$23,$B77,'内訳ﾘｽﾄ(4～3月)'!H$16:H$23),IF('内訳ﾘｽﾄ(4～3月)'!$D$5="部外間接2",-E$74,0)) -> 1.25 | F77: =IF('内訳ﾘｽﾄ(4～3月)'!$D$5="製造",SUMIF('内訳ﾘｽﾄ(4～3月)'!$D$16:$D$23,$B77,'内訳ﾘｽﾄ(4～3月)'!I$16:I$23),IF('内訳ﾘｽﾄ(4～3月)'!$D$5="部外間接2",-F$74,0)) -> 2 | G77: =IF('内訳ﾘｽﾄ(4～3月)'!$D$5="製造",SUMIF('内訳ﾘｽﾄ(4～3月)'!$D$16:$D$23,$B77,'内訳ﾘｽﾄ(4～3月)'!J$16:J$23),IF('内訳ﾘｽﾄ(4～3月)'!$D$5="部外間接2",-G$74,0)) -> 2 | H77: =IF('内訳ﾘｽﾄ(4～3月)'!$D$5="製造",SUMIF('内訳ﾘｽﾄ(4～3月)'!$D$16:$D$23,$B77,'内訳ﾘｽﾄ(4～3月)'!K$16:K$23),IF('内訳ﾘｽﾄ(4～3月)'!$D$5="部外間接2",-H$74,0)) -> 2 | I77: =IF('内訳ﾘｽﾄ(4～3月)'!$D$5="製造",SUMIF('内訳ﾘｽﾄ(4～3月)'!$D$16:$D$23,$B77,'内訳ﾘｽﾄ(4～3月)'!L$16:L$23),IF('内訳ﾘｽﾄ(4～3月)'!$D$5="部外間接2",-I$74,0)) -> 2.25 | J77: =IF('内訳ﾘｽﾄ(4～3月)'!$D$5="製造",SUMIF('内訳ﾘｽﾄ(4～3月)'!$D$16:$D$23,$B77,'内訳ﾘｽﾄ(4～3月)'!M$16:M$23),IF('内訳ﾘｽﾄ(4～3月)'!$D$5="部外間接2",-J$74,0)) -> 2 | ... N77: =IF('内訳ﾘｽﾄ(4～3月)'!$D$5="製造",SUMIF('内訳ﾘｽﾄ(4～3月)'!$D$16:$D$23,$B77,'内訳ﾘｽﾄ(4～3月)'!Q$16:Q$23),IF('内訳ﾘｽﾄ(4～3月)'!$D$5="部外間接2",-N$74,0)) -> 2.25 | O77: =IF('内訳ﾘｽﾄ(4～3月)'!$D$5="部外間接2",-SUM(O$74),IF('内訳ﾘｽﾄ(4～3月)'!$D$5="製造",SUMIF('内訳ﾘｽﾄ(4～3月)'!$D$16:$D$23,'採算表(VND)'!$B77,'内訳ﾘｽﾄ(4～3月)'!$R$16:$R$23),0)) -> 22.25
B78: 工場間接部門 | C78: =IF('内訳ﾘｽﾄ(4～3月)'!$D$5="製造",SUMIF('内訳ﾘｽﾄ(4～3月)'!$D$16:$D$23,$B78,'内訳ﾘｽﾄ(4～3月)'!F$16:F$23),IF('内訳ﾘｽﾄ(4～3月)'!$D$5="工場間接",-C$74,0)) -> 4.5 | D78: =IF('内訳ﾘｽﾄ(4～3月)'!$D$5="製造",SUMIF('内訳ﾘｽﾄ(4～3月)'!$D$16:$D$23,$B78,'内訳ﾘｽﾄ(4～3月)'!G$16:G$23),IF('内訳ﾘｽﾄ(4～3月)'!$D$5="工場間接",-D$74,0)) -> 4 | E78: =IF('内訳ﾘｽﾄ(4～3月)'!$D$5="製造",SUMIF('内訳ﾘｽﾄ(4～3月)'!$D$16:$D$23,$B78,'内訳ﾘｽﾄ(4～3月)'!H$16:H$23),IF('内訳ﾘｽﾄ(4～3月)'!$D$5="工場間接",-E$74,0)) -> 3.75 | F78: =IF('内訳ﾘｽﾄ(4～3月)'!$D$5="製造",SUMIF('内訳ﾘｽﾄ(4～3月)'!$D$16:$D$23,$B78,'内訳ﾘｽﾄ(4～3月)'!I$16:I$23),IF('内訳ﾘｽﾄ(4～3月)'!$D$5="工場間接",-F$74,0)) -> 5 | G78: =IF('内訳ﾘｽﾄ(4～3月)'!$D$5="製造",SUMIF('内訳ﾘｽﾄ(4～3月)'!$D$16:$D$23,$B78,'内訳ﾘｽﾄ(4～3月)'!J$16:J$23),IF('内訳ﾘｽﾄ(4～3月)'!$D$5="工場間接",-G$74,0)) -> 5.5 | H78: =IF('内訳ﾘｽﾄ(4～3月)'!$D$5="製造",SUMIF('内訳ﾘｽﾄ(4～3月)'!$D$16:$D$23,$B78,'内訳ﾘｽﾄ(4～3月)'!K$16:K$23),IF('内訳ﾘｽﾄ(4～3月)'!$D$5="工場間接",-H$74,0)) -> 7 | I78: =IF('内訳ﾘｽﾄ(4～3月)'!$D$5="製造",SUMIF('内訳ﾘｽﾄ(4～3月)'!$D$16:$D$23,$B78,'内訳ﾘｽﾄ(4～3月)'!L$16:L$23),IF('内訳ﾘｽﾄ(4～3月)'!$D$5="工場間接",-I$74,0)) -> 5 | J78: =IF('内訳ﾘｽﾄ(4～3月)'!$D$5="製造",SUMIF('内訳ﾘｽﾄ(4～3月)'!$D$16:$D$23,$B78,'内訳ﾘｽﾄ(4～3月)'!M$16:M$23),IF('内訳ﾘｽﾄ(4～3月)'!$D$5="工場間接",-J$74,0)) -> 5 | ... N78: =IF('内訳ﾘｽﾄ(4～3月)'!$D$5="製造",SUMIF('内訳ﾘｽﾄ(4～3月)'!$D$16:$D$23,$B78,'内訳ﾘｽﾄ(4～3月)'!Q$16:Q$23),IF('内訳ﾘｽﾄ(4～3月)'!$D$5="工場間接",-N$74,0)) -> 5.5 | O78: =IF('内訳ﾘｽﾄ(4～3月)'!$D$5="工場間接",-SUM(O$74),IF('内訳ﾘｽﾄ(4～3月)'!$D$5="製造",SUMIF('内訳ﾘｽﾄ(4～3月)'!$D$16:$D$23,'採算表(VND)'!$B78,'内訳ﾘｽﾄ(4～3月)'!$R$16:$R$23),0)) -> 62.75
B79: 残業時間合計 | C79: =SUM(C74:C78) -> 508.5 | D79: =SUM(D74:D78) -> 488 | E79: =SUM(E74:E78) -> 527.75 | F79: =SUM(F74:F78) -> 570 | G79: =SUM(G74:G78) -> 510.5 | H79: =SUM(H74:H78) -> 491.75 | I79: =SUM(I74:I78) -> 662.25 | J79: =SUM(J74:J78) -> 589.75 | ... N79: =SUM(N74:N78) -> 590.5 | O79: =IF(ISBLANK(O10),"",SUM(O74:O78)) -> 6629
B80: 当月時間当り | C80: =IFERROR(ROUNDDOWN(C66/C67,0),0) -> 1085890 | D80: =IFERROR(ROUNDDOWN(D66/D67,0),0) -> 322997 | E80: =IFERROR(ROUNDDOWN(E66/E67,0),0) -> 232110 | F80: =IFERROR(ROUNDDOWN(F66/F67,0),0) -> 233908 | G80: =IFERROR(ROUNDDOWN(G66/G67,0),0) -> 290320 | H80: =IFERROR(ROUNDDOWN(H66/H67,0),0) -> 328077 | I80: =IFERROR(ROUNDDOWN(I66/I67,0),0) -> 229163 | J80: =IFERROR(ROUNDDOWN(J66/J67,0),0) -> 414197 | ... O80: =IFERROR(ROUNDDOWN(O66/O67,0),0) -> 402448
B81: 時間当り生産高 | C81: =IFERROR(ROUNDDOWN(C12/C67,0),0) -> 1103632 | D81: =IFERROR(ROUNDDOWN(D12/D67,0),0) -> 349537 | E81: =IFERROR(ROUNDDOWN(E12/E67,0),0) -> 260391 | F81: =IFERROR(ROUNDDOWN(F12/F67,0),0) -> 256536 | G81: =IFERROR(ROUNDDOWN(G12/G67,0),0) -> 306276 | H81: =IFERROR(ROUNDDOWN(H12/H67,0),0) -> 345156 | I81: =IFERROR(ROUNDDOWN(I12/I67,0),0) -> 244813 | J81: =IFERROR(ROUNDDOWN(J12/J67,0),0) -> 430444 | ... O81: =IFERROR(ROUNDDOWN(O12/O67,0),0) -> 420777
B86: ■人員
B87: 出向社員(人) | C87: =SUMIF('内訳ﾘｽﾄ(4～3月)'!$D$24:$D$25,'採算表(VND)'!$B87,'内訳ﾘｽﾄ(4～3月)'!F$24:F$25) -> 9 | D87: =SUMIF('内訳ﾘｽﾄ(4～3月)'!$D$24:$D$25,'採算表(VND)'!$B87,'内訳ﾘｽﾄ(4～3月)'!G$24:G$25) -> 9 | E87: =SUMIF('内訳ﾘｽﾄ(4～3月)'!$D$24:$D$25,'採算表(VND)'!$B87,'内訳ﾘｽﾄ(4～3月)'!H$24:H$25) -> 9 | F87: =SUMIF('内訳ﾘｽﾄ(4～3月)'!$D$24:$D$25,'採算表(VND)'!$B87,'内訳ﾘｽﾄ(4～3月)'!I$24:I$25) -> 9 | G87: =SUMIF('内訳ﾘｽﾄ(4～3月)'!$D$24:$D$25,'採算表(VND)'!$B87,'内訳ﾘｽﾄ(4～3月)'!J$24:J$25) -> 9 | H87: =SUMIF('内訳ﾘｽﾄ(4～3月)'!$D$24:$D$25,'採算表(VND)'!$B87,'内訳ﾘｽﾄ(4～3月)'!K$24:K$25) -> 9 | I87: =SUMIF('内訳ﾘｽﾄ(4～3月)'!$D$24:$D$25,'採算表(VND)'!$B87,'内訳ﾘｽﾄ(4～3月)'!L$24:L$25) -> 11 | J87: =SUMIF('内訳ﾘｽﾄ(4～3月)'!$D$24:$D$25,'採算表(VND)'!$B87,'内訳ﾘｽﾄ(4～3月)'!M$24:M$25) -> 11 | ... O87: =SUMIF('内訳ﾘｽﾄ(4～3月)'!$D$24:$D$25,'採算表(VND)'!$B87,'内訳ﾘｽﾄ(4～3月)'!R$24:R$25) -> 11
B88: ローカル社員(人) | C88: =SUMIF('内訳ﾘｽﾄ(4～3月)'!$D$24:$D$25,'採算表(VND)'!$B88,'内訳ﾘｽﾄ(4～3月)'!F$24:F$25) -> 9 | D88: =SUMIF('内訳ﾘｽﾄ(4～3月)'!$D$24:$D$25,'採算表(VND)'!$B88,'内訳ﾘｽﾄ(4～3月)'!G$24:G$25) -> 9 | E88: =SUMIF('内訳ﾘｽﾄ(4～3月)'!$D$24:$D$25,'採算表(VND)'!$B88,'内訳ﾘｽﾄ(4～3月)'!H$24:H$25) -> 9 | F88: =SUMIF('内訳ﾘｽﾄ(4～3月)'!$D$24:$D$25,'採算表(VND)'!$B88,'内訳ﾘｽﾄ(4～3月)'!I$24:I$25) -> 9 | G88: =SUMIF('内訳ﾘｽﾄ(4～3月)'!$D$24:$D$25,'採算表(VND)'!$B88,'内訳ﾘｽﾄ(4～3月)'!J$24:J$25) -> 9 | H88: =SUMIF('内訳ﾘｽﾄ(4～3月)'!$D$24:$D$25,'採算表(VND)'!$B88,'内訳ﾘｽﾄ(4～3月)'!K$24:K$25) -> 9 | I88: =SUMIF('内訳ﾘｽﾄ(4～3月)'!$D$24:$D$25,'採算表(VND)'!$B88,'内訳ﾘｽﾄ(4～3月)'!L$24:L$25) -> 9 | J88: =SUMIF('内訳ﾘｽﾄ(4～3月)'!$D$24:$D$25,'採算表(VND)'!$B88,'内訳ﾘｽﾄ(4～3月)'!M$24:M$25) -> 9 | ... O88: =SUMIF('内訳ﾘｽﾄ(4～3月)'!$D$24:$D$25,'採算表(VND)'!$B88,'内訳ﾘｽﾄ(4～3月)'!R$24:R$25) -> 9
B89: 人員計 | C89: =C87+C88 -> 18 | D89: =D87+D88 -> 18 | E89: =E87+E88 -> 18 | F89: =F87+F88 -> 18 | G89: =G87+G88 -> 18 | H89: =H87+H88 -> 18 | I89: =I87+I88 -> 20 | J89: =J87+J88 -> 20 | ... O89: =O87+O88 -> 20
B91: ■定時間
B92: 出向社員定時 | C92: =SUMIF('内訳ﾘｽﾄ(4～3月)'!$B$8:$B$15,$B92,'内訳ﾘｽﾄ(4～3月)'!F$8:F$15) -> 1521.5 | D92: =SUMIF('内訳ﾘｽﾄ(4～3月)'!$B$8:$B$15,$B92,'内訳ﾘｽﾄ(4～3月)'!G$8:G$15) -> 1445 | E92: =SUMIF('内訳ﾘｽﾄ(4～3月)'!$B$8:$B$15,$B92,'内訳ﾘｽﾄ(4～3月)'!H$8:H$15) -> 1598 | F92: =SUMIF('内訳ﾘｽﾄ(4～3月)'!$B$8:$B$15,$B92,'内訳ﾘｽﾄ(4～3月)'!I$8:I$15) -> 1751 | G92: =SUMIF('内訳ﾘｽﾄ(4～3月)'!$B$8:$B$15,$B92,'内訳ﾘｽﾄ(4～3月)'!J$8:J$15) -> 1521.5 | H92: =SUMIF('内訳ﾘｽﾄ(4～3月)'!$B$8:$B$15,$B92,'内訳ﾘｽﾄ(4～3月)'!K$8:K$15) -> 1445 | I92: =SUMIF('内訳ﾘｽﾄ(4～3月)'!$B$8:$B$15,$B92,'内訳ﾘｽﾄ(4～3月)'!L$8:L$15) -> 2142 | J92: =SUMIF('内訳ﾘｽﾄ(4～3月)'!$B$8:$B$15,$B92,'内訳ﾘｽﾄ(4～3月)'!M$8:M$15) -> 1861.5 | ... O92: =SUMIF('内訳ﾘｽﾄ(4～3月)'!$B$8:$B$15,$B92,'内訳ﾘｽﾄ(4～3月)'!R$8:R$15) -> 20408.5
B93: ローカル社員定時 | C93: =SUMIF('内訳ﾘｽﾄ(4～3月)'!$B$8:$B$15,$B93,'内訳ﾘｽﾄ(4～3月)'!F$8:F$15) -> 1470.5 | D93: =SUMIF('内訳ﾘｽﾄ(4～3月)'!$B$8:$B$15,$B93,'内訳ﾘｽﾄ(4～3月)'!G$8:G$15) -> 1394 | E93: =SUMIF('内訳ﾘｽﾄ(4～3月)'!$B$8:$B$15,$B93,'内訳ﾘｽﾄ(4～3月)'!H$8:H$15) -> 1547 | F93: =SUMIF('内訳ﾘｽﾄ(4～3月)'!$B$8:$B$15,$B93,'内訳ﾘｽﾄ(4～3月)'!I$8:I$15) -> 1700 | G93: =SUMIF('内訳ﾘｽﾄ(4～3月)'!$B$8:$B$15,$B93,'内訳ﾘｽﾄ(4～3月)'!J$8:J$15) -> 1470.5 | H93: =SUMIF('内訳ﾘｽﾄ(4～3月)'!$B$8:$B$15,$B93,'内訳ﾘｽﾄ(4～3月)'!K$8:K$15) -> 1394 | I93: =SUMIF('内訳ﾘｽﾄ(4～3月)'!$B$8:$B$15,$B93,'内訳ﾘｽﾄ(4～3月)'!L$8:L$15) -> 1700 | J93: =SUMIF('内訳ﾘｽﾄ(4～3月)'!$B$8:$B$15,$B93,'内訳ﾘｽﾄ(4～3月)'!M$8:M$15) -> 1470.5 | ... O93: =SUMIF('内訳ﾘｽﾄ(4～3月)'!$B$8:$B$15,$B93,'内訳ﾘｽﾄ(4～3月)'!R$8:R$15) -> 17799
B94: 人員計 | C94: =C92+C93 -> 2992 | D94: =D92+D93 -> 2839 | E94: =E92+E93 -> 3145 | F94: =F92+F93 -> 3451 | G94: =G92+G93 -> 2992 | H94: =H92+H93 -> 2839 | I94: =I92+I93 -> 3842 | J94: =J92+J93 -> 3332 | ... O94: =O92+O93 -> 38207.5
B96: ■残業時間
B97: 出向社員残業 | C97: =SUMIF('内訳ﾘｽﾄ(4～3月)'!$B$16:$B$23,$B97,'内訳ﾘｽﾄ(4～3月)'!F$16:F$23) -> 358 | D97: =SUMIF('内訳ﾘｽﾄ(4～3月)'!$B$16:$B$23,$B97,'内訳ﾘｽﾄ(4～3月)'!G$16:G$23) -> 340 | E97: =SUMIF('内訳ﾘｽﾄ(4～3月)'!$B$16:$B$23,$B97,'内訳ﾘｽﾄ(4～3月)'!H$16:H$23) -> 376 | F97: =SUMIF('内訳ﾘｽﾄ(4～3月)'!$B$16:$B$23,$B97,'内訳ﾘｽﾄ(4～3月)'!I$16:I$23) -> 412 | G97: =SUMIF('内訳ﾘｽﾄ(4～3月)'!$B$16:$B$23,$B97,'内訳ﾘｽﾄ(4～3月)'!J$16:J$23) -> 358 | H97: =SUMIF('内訳ﾘｽﾄ(4～3月)'!$B$16:$B$23,$B97,'内訳ﾘｽﾄ(4～3月)'!K$16:K$23) -> 340 | I97: =SUMIF('内訳ﾘｽﾄ(4～3月)'!$B$16:$B$23,$B97,'内訳ﾘｽﾄ(4～3月)'!L$16:L$23) -> 504 | J97: =SUMIF('内訳ﾘｽﾄ(4～3月)'!$B$16:$B$23,$B97,'内訳ﾘｽﾄ(4～3月)'!M$16:M$23) -> 438 | ... O97: =SUMIF('内訳ﾘｽﾄ(4～3月)'!$B$16:$B$23,$B97,'内訳ﾘｽﾄ(4～3月)'!R$16:R$23) -> 4802
B98: ローカル社員残業 | C98: =SUMIF('内訳ﾘｽﾄ(4～3月)'!$B$16:$B$23,$B98,'内訳ﾘｽﾄ(4～3月)'!F$16:F$23) -> 144 | D98: =SUMIF('内訳ﾘｽﾄ(4～3月)'!$B$16:$B$23,$B98,'内訳ﾘｽﾄ(4～3月)'!G$16:G$23) -> 142 | E98: =SUMIF('内訳ﾘｽﾄ(4～3月)'!$B$16:$B$23,$B98,'内訳ﾘｽﾄ(4～3月)'!H$16:H$23) -> 146 | F98: =SUMIF('内訳ﾘｽﾄ(4～3月)'!$B$16:$B$23,$B98,'内訳ﾘｽﾄ(4～3月)'!I$16:I$23) -> 150 | G98: =SUMIF('内訳ﾘｽﾄ(4～3月)'!$B$16:$B$23,$B98,'内訳ﾘｽﾄ(4～3月)'!J$16:J$23) -> 144 | H98: =SUMIF('内訳ﾘｽﾄ(4～3月)'!$B$16:$B$23,$B98,'内訳ﾘｽﾄ(4～3月)'!K$16:K$23) -> 142 | I98: =SUMIF('内訳ﾘｽﾄ(4～3月)'!$B$16:$B$23,$B98,'内訳ﾘｽﾄ(4～3月)'!L$16:L$23) -> 150 | J98: =SUMIF('内訳ﾘｽﾄ(4～3月)'!$B$16:$B$23,$B98,'内訳ﾘｽﾄ(4～3月)'!M$16:M$23) -> 144 | ... O98: =SUMIF('内訳ﾘｽﾄ(4～3月)'!$B$16:$B$23,$B98,'内訳ﾘｽﾄ(4～3月)'!R$16:R$23) -> 1732
B99: 人員計 | C99: =C97+C98 -> 502 | D99: =D97+D98 -> 482 | E99: =E97+E98 -> 522 | F99: =F97+F98 -> 562 | G99: =G97+G98 -> 502 | H99: =H97+H98 -> 482 | I99: =I97+I98 -> 654 | J99: =J97+J98 -> 582 | ... O99: =O97+O98 -> 6534

Sheet 内訳ﾘｽﾄ(4～3月)
A1: MP FY2026_各予定
B2: 25390 | E2: 稼働日数 | F2: =OFFSET(稼働日!$B$2,MATCH('内訳ﾘｽﾄ(4～3月)'!F4,稼働日!$A$3:$A$14,0),0) -> 20 | G2: =OFFSET(稼働日!$B$2,MATCH('内訳ﾘｽﾄ(4～3月)'!G4,稼働日!$A$3:$A$14,0),0) -> 19 | H2: =OFFSET(稼働日!$B$2,MATCH('内訳ﾘｽﾄ(4～3月)'!H4,稼働日!$A$3:$A$14,0),0) -> 21 | I2: =OFFSET(稼働日!$B$2,MATCH('内訳ﾘｽﾄ(4～3月)'!I4,稼働日!$A$3:$A$14,0),0) -> 23 | J2: =OFFSET(稼働日!$B$2,MATCH('内訳ﾘｽﾄ(4～3月)'!J4,稼働日!$A$3:$A$14,0),0) -> 20 | K2: =OFFSET(稼働日!$B$2,MATCH('内訳ﾘｽﾄ(4～3月)'!K4,稼働日!$A$3:$A$14,0),0) -> 19 | L2: =OFFSET(稼働日!$B$2,MATCH('内訳ﾘｽﾄ(4～3月)'!L4,稼働日!$A$3:$A$14,0),0) -> 23 | M2: =OFFSET(稼働日!$B$2,MATCH('内訳ﾘｽﾄ(4～3月)'!M4,稼働日!$A$3:$A$14,0),0) -> 20 | ... Q2: =OFFSET(稼働日!$B$2,MATCH('内訳ﾘｽﾄ(4～3月)'!Q4,稼働日!$A$3:$A$14,0),0) -> 20
E3: CHECK | F3: {=IF(SUM((F8:F25)-ROUNDDOWN((F8:F25)*4,0)/4)<>0,"時間➝0.25の倍数では無い",IF(SUM(ROUND((F26:F176),0)-ROUND((F26:F176),4))<>0,"経費➝小数点",IF(F5<>IF($D$5="製造",'採算表(VND)'!C13,-VLOOKUP($D$5&"経費",'採算表(VND)'!$B:$N,'採算表(VND)'!C3,0)),"経費➝NG","OK")))} -> OK | G3: {=IF(SUM((G8:G25)-ROUNDDOWN((G8:G25)*4,0)/4)<>0,"時間➝0.25の倍数では無い",IF(SUM(ROUND((G26:G176),0)-ROUND((G26:G176),4))<>0,"経費➝小数点",IF(G5<>IF($D$5="製造",'採算表(VND)'!D13,-VLOOKUP($D$5&"経費",'採算表(VND)'!$B:$N,'採算表(VND)'!D3,0)),"経費➝NG","OK")))} -> OK | H3: {=IF(SUM((H8:H25)-ROUNDDOWN((H8:H25)*4,0)/4)<>0,"時間➝0.25の倍数では無い",IF(SUM(ROUND((H26:H176),0)-ROUND((H26:H176),4))<>0,"経費➝小数点",IF(H5<>IF($D$5="製造",'採算表(VND)'!E13,-VLOOKUP($D$5&"経費",'採算表(VND)'!$B:$N,'採算表(VND)'!E3,0)),"経費➝NG","OK")))} -> OK | I3: {=IF(SUM((I8:I25)-ROUNDDOWN((I8:I25)*4,0)/4)<>0,"時間➝0.25の倍数では無い",IF(SUM(ROUND((I26:I176),0)-ROUND((I26:I176),4))<>0,"経費➝小数点",IF(I5<>IF($D$5="製造",'採算表(VND)'!F13,-VLOOKUP($D$5&"経費",'採算表(VND)'!$B:$N,'採算表(VND)'!F3,0)),"経費➝NG","OK")))} -> OK | J3: {=IF(SUM((J8:J25)-ROUNDDOWN((J8:J25)*4,0)/4)<>0,"時間➝0.25の倍数では無い",IF(SUM(ROUND((J26:J176),0)-ROUND((J26:J176),4))<>0,"経費➝小数点",IF(J5<>IF($D$5="製造",'採算表(VND)'!G13,-VLOOKUP($D$5&"経費",'採算表(VND)'!$B:$N,'採算表(VND)'!G3,0)),"経費➝NG","OK")))} -> OK | K3: {=IF(SUM((K8:K25)-ROUNDDOWN((K8:K25)*4,0)/4)<>0,"時間➝0.25の倍数では無い",IF(SUM(ROUND((K26:K176),0)-ROUND((K26:K176),4))<>0,"経費➝小数点",IF(K5<>IF($D$5="製造",'採算表(VND)'!H13,-VLOOKUP($D$5&"経費",'採算表(VND)'!$B:$N,'採算表(VND)'!H3,0)),"経費➝NG","OK")))} -> OK | L3: {=IF(SUM((L8:L25)-ROUNDDOWN((L8:L25)*4,0)/4)<>0,"時間➝0.25の倍数では無い",IF(SUM(ROUND((L26:L176),0)-ROUND((L26:L176),4))<>0,"経費➝小数点",IF(L5<>IF($D$5="製造",'採算表(VND)'!I13,-VLOOKUP($D$5&"経費",'採算表(VND)'!$B:$N,'採算表(VND)'!I3,0)),"経費➝NG","OK")))} -> OK | M3: {=IF(SUM((M8:M25)-ROUNDDOWN((M8:M25)*4,0)/4)<>0,"時間➝0.25の倍数では無い",IF(SUM(ROUND((M26:M176),0)-ROUND((M26:M176),4))<>0,"経費➝小数点",IF(M5<>IF($D$5="製造",'採算表(VND)'!J13,-VLOOKUP($D$5&"経費",'採算表(VND)'!$B:$N,'採算表(VND)'!J3,0)),"経費➝NG","OK")))} -> OK | ... Q3: {=IF(SUM((Q8:Q25)-ROUNDDOWN((Q8:Q25)*4,0)/4)<>0,"時間➝0.25の倍数では無い",IF(SUM(ROUND((Q26:Q176),0)-ROUND((Q26:Q176),4))<>0,"経費➝小数点",IF(Q5<>IF($D$5="製造",'採算表(VND)'!N13,-VLOOKUP($D$5&"経費",'採算表(VND)'!$B:$N,'採算表(VND)'!N3,0)),"経費➝NG","OK")))} -> OK
B4: 原価センター | C4: 組織名 | D4: 採算区分 | E4: 原価区分 | F4: 4 | G4: 5 | H4: 6 | I4: 7 | J4: 8 | K4: 9 | L4: 10 | M4: 11 | N4: 12 | O4: 1 | P4: 2 | Q4: 3 | R4: 合計 | S4: ※MEBIUS経費になると "V02V0800" は T列に 反映お願いします
B5: 1412000077 | C5: =VLOOKUP($B$5,原価センタ!$A:$E,2,0) -> MD2課 | D5: =VLOOKUP($B$5,原価センタ!$A:$E,4,0) -> 製造 | E5: =VLOOKUP($B$5,原価センタ!$A:$E,5,0) -> 製造 | F5: =SUM(F29:F176) -> 64144401 | G5: =SUM(G29:G176) -> 91331072 | H5: =SUM(H29:H176) -> 107317573 | I5: =SUM(I29:I176) -> 94969541 | J5: =SUM(J29:J176) -> 58414822 | K5: =SUM(K29:K176) -> 59446869 | L5: =SUM(L29:L176) -> 73291663 | M5: =SUM(M29:M176) -> 66331480 | ... R5: =SUM(R29:R176) -> 854842006
C7: 勘定科目名称 | D7: 採算科目 | E7: ﾃｰﾏｺｰﾄﾞ | F7: MP | G7: MP | H7: MP | I7: MP | J7: MP | K7: MP | L7: MP | M7: MP | N7: MP | O7: MP | P7: MP | Q7: MP | R7: MP | S7: 備考 | T7: WBS | BC7: WBS
B8: 出向社員定時 | C8: 定時間（日本社員） | D8: 直接部門 | F8: 1521.5 | G8: 1445 | H8: 1598 | I8: 1751 | J8: 1521.5 | K8: 1445 | L8: 2142 | M8: 1861.5 | N8: 2048.5 | O8: 1861.5 | P8: 1351.5 | Q8: 1861.5 | R8: =SUM(F8:Q8) -> 20408.5
B9: ローカル社員定時 | C9: 定時間（ベトナム社員） | D9: 直接部門 | F9: 1470.5 | G9: 1394 | H9: 1547 | I9: 1700 | J9: 1470.5 | K9: 1394 | L9: 1700 | M9: 1470.5 | N9: 1623.5 | O9: 1470.5 | P9: 1088 | Q9: 1470.5 | R9: =SUM(F9:Q9) -> 17799
B10: 出向社員定時 | C10: 定時間（移動分日本社員） | D10: 直接部門 | R10: =SUM(F10:Q10) -> 0
B11: ローカル社員定時 | C11: 定時間（移動分ベトナム社員） | D11: 直接部門 | R11: =SUM(F11:Q11) -> 0
C12: 定時間（部内間接部門） | D12: 部内間接部門 | F12: 0 | G12: 0 | H12: 0 | I12: 0 | J12: 0 | K12: 0 | L12: 0 | M12: 0 | N12: 0 | O12: 0 | P12: 0 | Q12: 0 | R12: =SUM(F12:Q12) -> 0 | S12: この分には間接部門から直接部門に配賦された数字
C13: 定時間（部外間接部門1） | D13: 部外間接部門1 | F13: 10.25 | G13: 10.5 | H13: 11.5 | I13: 16.25 | J13: 14.25 | K13: 13.5 | L13: 16.5 | M13: 14.25 | N13: 15.75 | O13: 15 | P13: 11 | Q13: 15 | R13: =SUM(F13:Q13) -> 163.75 | S13: この分には間接部門から直接部門に配賦された数字
C14: 定時間（部外間接部門2） | D14: 部外間接部門2 | F14: 19.5 | G14: 18.25 | H14: 20.75 | I14: 31.25 | J14: 27 | K14: 26.5 | L14: 32.25 | M14: 28.25 | N14: 31.5 | O14: 28.25 | P14: 20.75 | Q14: 28.25 | R14: =SUM(F14:Q14) -> 312.5 | S14: この分には間接部門から直接部門に配賦された数字
C15: 定時間（工場間接部門） | D15: 工場間接部門 | F15: 85.25 | G15: 85.5 | H15: 89.75 | I15: 128.5 | J15: 117.25 | K15: 110 | L15: 130.25 | M15: 118.5 | N15: 128 | O15: 120.75 | P15: 90 | Q15: 121.25 | R15: =SUM(F15:Q15) -> 1325 | S15: この分には間接部門から直接部門に配賦された数字
B16: 出向社員残業 | C16: 残業時間（日本社員） | D16: 直接部門 | F16: 358 | G16: 340 | H16: 376 | I16: 412 | J16: 358 | K16: 340 | L16: 504 | M16: 438 | N16: 482 | O16: 438 | P16: 318 | Q16: 438 | R16: =SUM(F16:Q16) -> 4802
B17: ローカル社員残業 | C17: 残業時間（ベトナム社員） | D17: 直接部門 | F17: 144 | G17: 142 | H17: 146 | I17: 150 | J17: 144 | K17: 142 | L17: 150 | M17: 144 | N17: 148 | O17: 144 | P17: 134 | Q17: 144 | R17: =SUM(F17:Q17) -> 1732 | S17: 15時間/人・月(1-12期生)で計算 係責任者は2時間のみなし残業
B18: 出向社員残業 | C18: 残業時間（移動分日本社員） | D18: 直接部門 | R18: =SUM(F18:Q18) -> 0
B19: ローカル社員残業 | C19: 残業時間（移動分ベトナム社員） | D19: 直接部門 | R19: =SUM(F19:Q19) -> 0
C20: 残業時間（部内間接部門） | D20: 部内間接部門 | F20: 0 | G20: 0 | H20: 0 | I20: 0 | J20: 0 | K20: 0 | L20: 0 | M20: 0 | N20: 0 | O20: 0 | P20: 0 | Q20: 0 | R20: =SUM(F20:Q20) -> 0 | S20: この分には間接部門から直接部門に配賦された数字
C21: 残業時間（部外間接部門1） | D21: 部外間接部門1 | F21: 0.75 | G21: 0.75 | H21: 0.75 | I21: 1 | J21: 1 | K21: 0.75 | L21: 1 | M21: 0.75 | N21: 1 | O21: 0.75 | P21: 0.75 | Q21: 0.75 | R21: =SUM(F21:Q21) -> 10 | S21: この分には間接部門から直接部門に配賦された数字
C22: 残業時間（部外間接部門2） | D22: 部外間接部門2 | F22: 1.25 | G22: 1.25 | H22: 1.25 | I22: 2 | J22: 2 | K22: 2 | L22: 2.25 | M22: 2 | N22: 2 | O22: 2.25 | P22: 1.75 | Q22: 2.25 | R22: =SUM(F22:Q22) -> 22.25 | S22: この分には間接部門から直接部門に配賦された数字
C23: 残業時間（工場間接部門） | D23: 工場間接部門 | F23: 4.5 | G23: 4 | H23: 3.75 | I23: 5 | J23: 5.5 | K23: 7 | L23: 5 | M23: 5 | N23: 5 | O23: 4.75 | P23: 7.75 | Q23: 5.5 | R23: =SUM(F23:Q23) -> 62.75 | S23: この分には間接部門から直接部門に配賦された数字
B24: 出向社員(人) | C24: 出向社員(人) | D24: 出向社員(人) | F24: 9 | G24: 9 | H24: 9 | I24: 9 | J24: 9 | K24: 9 | L24: 11 | M24: 11 | N24: 11 | O24: 11 | P24: 11 | Q24: 11 | R24: =Q24 -> 11
B25: ローカル社員(人) | C25: ローカル社員(人) | D25: ローカル社員(人) | F25: 9 | G25: 9 | H25: 9 | I25: 9 | J25: 9 | K25: 9 | L25: 9 | M25: 9 | N25: 9 | O25: 9 | P25: 9 | Q25: 9 | R25: =Q25 -> 9 | V25: 4 | W25: 5 | X25: 6 | Y25: 7 | Z25: 8 | AA25: 9 | AB25: 10 | AC25: 11 | AD25: 12 | AE25: 1 | AF25: 2 | AG25: 3
B26: 9114120002 | C26: =IFERROR(IF(VLOOKUP($B26,勘定科目!$A:$H,HLOOKUP($E$5,勘定科目!$F$1:$H$2,2,0),0)="","",VLOOKUP($B26,勘定科目!$A:$E,2,0)),"") -> 社外出荷 | D26: =IF(C26="","",VLOOKUP($B26,勘定科目!$A:$E,4,0)) -> 社外出荷 | F26: =ROUNDDOWN(V26*$B$2,0)+1 -> 3990181700 | G26: =ROUNDDOWN(W26*$B$2,0)+1 -> 1202847188 | H26: =ROUNDDOWN(X26*$B$2,0)+1 -> 988119388 | I26: =ROUNDDOWN(Y26*$B$2,0)+1 -> 1076681739 | J26: =ROUNDDOWN(Z26*$B$2,0)+1 -> 1121277497 | K26: =ROUNDDOWN(AA26*$B$2,0)+1 -> 1201402497 | L26: =ROUNDDOWN(AB26*$B$2,0)+1 -> 1146521250 | M26: =ROUNDDOWN(AC26*$B$2,0)+1 -> 1757397541 | N26: =ROUNDDOWN(AD26*$B$2,0) -> 1811655209 | O26: =ROUNDDOWN(AE26*$B$2,0)+1 -> 1803667008 | P26: =ROUNDDOWN(AF26*$B$2,0)+1 -> 1750512789 | Q26: =ROUNDDOWN(AG26*$B$2,0)+1 -> 1773855339 | R26: =SUM(F26:Q26) -> 19624119145 | S26: 総生産情報 | V26: 157155.64 | W26: 47374.84 | X26: 38917.66 | Y26: 42405.74 | Z26: 44162.17 | AA26: 47317.94 | AB26: 45156.41 | AC26: 69216.13 | AD26: 71353.1 | AE26: 71038.48 | AF26: 68944.97 | AG26: 69864.33
B27: 9114120004 | C27: =IFERROR(IF(VLOOKUP($B27,勘定科目!$A:$H,HLOOKUP($E$5,勘定科目!$F$1:$H$2,2,0),0)="","",VLOOKUP($B27,勘定科目!$A:$E,2,0)),"") -> 社内売 | D27: =IF(C27="","",VLOOKUP($B27,勘定科目!$A:$E,4,0)) -> 社内売 | F27: 0 | G27: 0 | H27: 0 | I27: 0 | K27: 0 | L27: 0 | M27: 0 | N27: 0 | O27: 0 | P27: 0 | Q27: 0 | R27: =SUM(F27:Q27) -> 0 | S27: 総生産情報
B28: 9114120014 | C28: =IFERROR(IF(VLOOKUP($B28,勘定科目!$A:$H,HLOOKUP($E$5,勘定科目!$F$1:$H$2,2,0),0)="","",VLOOKUP($B28,勘定科目!$A:$E,2,0)),"") -> 社内買 | D28: =IF(C28="","",VLOOKUP($B28,勘定科目!$A:$E,4,0)) -> 社内買 | F28: 0 | G28: 0 | H28: 0 | I28: 0 | J28: 0 | K28: 0 | L28: 0 | M28: 0 | N28: 0 | O28: 0 | P28: 0 | Q28: 0 | R28: =SUM(F28:Q28) -> 0 | S28: 総生産情報
B29: 9114120006 | C29: =IFERROR(IF(VLOOKUP($B29,勘定科目!$A:$H,HLOOKUP($E$5,勘定科目!$F$1:$H$2,2,0),0)="","",VLOOKUP($B29,勘定科目!$A:$E,2,0)),"") -> 材料費(指図出庫） | D29: =IF(C29="","",VLOOKUP($B29,勘定科目!$A:$E,4,0)) -> 材料費 | F29: 0 | G29: 0 | H29: 0 | I29: 0 | J29: 0 | K29: 0 | L29: 0 | M29: 0 | N29: 0 | O29: 0 | P29: 0 | Q29: 0 | R29: =SUM(F29:Q29) -> 0 | S29: 総生産情報
C30: =IFERROR(IF(VLOOKUP($B30,勘定科目!$A:$H,HLOOKUP($E$5,勘定科目!$F$1:$H$2,2,0),0)="","",VLOOKUP($B30,勘定科目!$A:$E,2,0)),"") | D30: =IF(C30="","",VLOOKUP($B30,勘定科目!$A:$E,4,0)) | R30: =SUM(F30:Q30) -> 0
B31: 9114120018 | C31: =IFERROR(IF(VLOOKUP($B31,勘定科目!$A:$H,HLOOKUP($E$5,勘定科目!$F$1:$H$2,2,0),0)="","",VLOOKUP($B31,勘定科目!$A:$E,2,0)),"") -> 部内間接経費 | D31: =IF(C31="","",VLOOKUP($B31,勘定科目!$A:$E,4,0)) -> 部内間接経費 | F31: 0 | G31: 0 | H31: 0 | I31: 0 | J31: 0 | K31: 0 | L31: 0 | M31: 0 | N31: 0 | O31: 0 | P31: 0 | Q31: 0 | R31: =SUM(F31:Q31) -> 0 | S31: この分には間接部門から直接部門に配賦された数字
B32: 9114120029 | C32: =IFERROR(IF(VLOOKUP($B32,勘定科目!$A:$H,HLOOKUP($E$5,勘定科目!$F$1:$H$2,2,0),0)="","",VLOOKUP($B32,勘定科目!$A:$E,2,0)),"") -> 部外間接経費1 | D32: =IF(C32="","",VLOOKUP($B32,勘定科目!$A:$E,4,0)) -> 部外間接経費1 | F32: 596622 | G32: 684802 | H32: 570040 | I32: 837357 | J32: 752849 | K32: 823913 | L32: 743120 | M32: 747959 | N32: 755474 | O32: 726734 | P32: 769311 | Q32: 735484 | R32: =SUM(F32:Q32) -> 8743665 | S32: この分には間接部門から直接部門に配賦された数字
B33: 9114120030 | C33: =IFERROR(IF(VLOOKUP($B33,勘定科目!$A:$H,HLOOKUP($E$5,勘定科目!$F$1:$H$2,2,0),0)="","",VLOOKUP($B33,勘定科目!$A:$E,2,0)),"") -> 部外間接経費2 | D33: =IF(C33="","",VLOOKUP($B33,勘定科目!$A:$E,4,0)) -> 部外間接経費2 | F33: 3642462 | G33: 1244742 | H33: 891197 | I33: 1280238 | J33: 1149370 | K33: 1033551 | L33: 1292720 | M33: 1329570 | N33: 1284126 | O33: 1004136 | P33: 1050809 | Q33: 1032782 | R33: =SUM(F33:Q33) -> 16235703 | S33: この分には間接部門から直接部門に配賦された数字
B34: 9114120021 | C34: =IFERROR(IF(VLOOKUP($B34,勘定科目!$A:$H,HLOOKUP($E$5,勘定科目!$F$1:$H$2,2,0),0)="","",VLOOKUP($B34,勘定科目!$A:$E,2,0)),"") -> 工場間接経費 | D34: =IF(C34="","",VLOOKUP($B34,勘定科目!$A:$E,4,0)) -> 工場間接経費 | F34: 43303955 | G34: 55325039 | H34: 40960083 | I34: 78671642 | J34: 43833627 | K34: 42844672 | L34: 54416406 | M34: 45844353 | N34: 45340863 | O34: 50474019 | P34: 34854992 | Q34: 35970080 | R34: =SUM(F34:Q34) -> 571839731 | S34: この分には間接部門から直接部門に配賦された数字
C35: =IFERROR(IF(VLOOKUP($B35,勘定科目!$A:$H,HLOOKUP($E$5,勘定科目!$F$1:$H$2,2,0),0)="","",VLOOKUP($B35,勘定科目!$A:$E,2,0)),"") | D35: =IF(C35="","",VLOOKUP($B35,勘定科目!$A:$E,4,0)) | R35: =SUM(F35:Q35) -> 0
C36: =IFERROR(IF(VLOOKUP($B36,勘定科目!$A:$H,HLOOKUP($E$5,勘定科目!$F$1:$H$2,2,0),0)="","",VLOOKUP($B36,勘定科目!$A:$E,2,0)),"") | D36: =IF(C36="","",VLOOKUP($B36,勘定科目!$A:$E,4,0)) | R36: =SUM(F36:Q36) -> 0
C37: =IFERROR(IF(VLOOKUP($B37,勘定科目!$A:$H,HLOOKUP($E$5,勘定科目!$F$1:$H$2,2,0),0)="","",VLOOKUP($B37,勘定科目!$A:$E,2,0)),"") | D37: =IF(C37="","",VLOOKUP($B37,勘定科目!$A:$E,4,0)) | R37: =SUM(F37:Q37) -> 0
C38: =IFERROR(IF(VLOOKUP($B38,勘定科目!$A:$H,HLOOKUP($E$5,勘定科目!$F$1:$H$2,2,0),0)="","",VLOOKUP($B38,勘定科目!$A:$E,2,0)),"") | D38: =IF(C38="","",VLOOKUP($B38,勘定科目!$A:$E,4,0)) | R38: =SUM(F38:Q38) -> 0
C39: =IFERROR(IF(VLOOKUP($B39,勘定科目!$A:$H,HLOOKUP($E$5,勘定科目!$F$1:$H$2,2,0),0)="","",VLOOKUP($B39,勘定科目!$A:$E,2,0)),"") | D39: =IF(C39="","",VLOOKUP($B39,勘定科目!$A:$E,4,0)) | R39: =SUM(F39:Q39) -> 0 | S39: 一般経費↓
B40: 5006016260 | C40: =IFERROR(IF(VLOOKUP($B40,勘定科目!$A:$H,HLOOKUP($E$5,勘定科目!$F$1:$H$2,2,0),0)="","",VLOOKUP($B40,勘定科目!$A:$E,2,0)),"") -> 減価償却費配賦（製） 建物 | D40: =IF(C40="","",VLOOKUP($B40,勘定科目!$A:$E,4,0)) -> 減価償却費 | F40: 3112560 | G40: 3112433 | H40: 3246492 | I40: 3256521 | J40: 2623676 | K40: 2595239 | L40: 2595239 | M40: 2595239 | N40: 2587241 | O40: 2586098 | P40: 2586098 | Q40: 2604125 | R40: =SUM(F40:Q40) -> 33500961 | S40: 減価償却費配賦 建物
B41: 5006016261 | C41: =IFERROR(IF(VLOOKUP($B41,勘定科目!$A:$H,HLOOKUP($E$5,勘定科目!$F$1:$H$2,2,0),0)="","",VLOOKUP($B41,勘定科目!$A:$E,2,0)),"") -> 減価償却費配賦（製） 土地使用権 | D41: =IF(C41="","",VLOOKUP($B41,勘定科目!$A:$E,4,0)) -> 減価償却費 | F41: 210102 | G41: 210102 | H41: 219116 | I41: 219750 | J41: 177095 | K41: 175191 | L41: 175191 | M41: 175191 | N41: 174683 | O41: 174556 | P41: 174556 | Q41: 175826 | R41: =SUM(F41:Q41) -> 2261359 | S41: 減価償却費配賦 土地使用権
B42: 9114120007 | C42: =IFERROR(IF(VLOOKUP($B42,勘定科目!$A:$H,HLOOKUP($E$5,勘定科目!$F$1:$H$2,2,0),0)="","",VLOOKUP($B42,勘定科目!$A:$E,2,0)),"") -> 社内金利（固定資産） | D42: =IF(C42="","",VLOOKUP($B42,勘定科目!$A:$E,4,0)) -> 固定資産金利 | F42: 2224799 | G42: 2224926 | H42: 2203598 | I42: 2210453 | J42: 1781109 | K42: 1761558 | L42: 1761558 | M42: 1761558 | N42: 1756226 | O42: 1755338 | P42: 1755338 | Q42: 1767652 | R42: =SUM(F42:Q42) -> 22964113 | S42: 固定資産金利 建物
B43: 9114120007 | C43: =IFERROR(IF(VLOOKUP($B43,勘定科目!$A:$H,HLOOKUP($E$5,勘定科目!$F$1:$H$2,2,0),0)="","",VLOOKUP($B43,勘定科目!$A:$E,2,0)),"") -> 社内金利（固定資産） | D43: =IF(C43="","",VLOOKUP($B43,勘定科目!$A:$E,4,0)) -> 固定資産金利 | F43: 268880 | G43: 268880 | H43: 272435 | I43: 273323 | J43: 220258 | K43: 217846 | L43: 217846 | M43: 217846 | N43: 217085 | O43: 217085 | P43: 217085 | Q43: 218608 | R43: =SUM(F43:Q43) -> 2827177 | S43: 固定資産金利 土地使用権
B44: 5005066281 | C44: =IFERROR(IF(VLOOKUP($B44,勘定科目!$A:$H,HLOOKUP($E$5,勘定科目!$F$1:$H$2,2,0),0)="","",VLOOKUP($B44,勘定科目!$A:$E,2,0)),"") -> 電気代（製） | D44: =IF(C44="","",VLOOKUP($B44,勘定科目!$A:$E,4,0)) -> 水道光熱費 | F44: 877127 | G44: 877127 | H44: 820435 | I44: 828796 | J44: 851382 | K44: 958528 | L44: 806256 | M44: 806256 | N44: 903813 | O44: 521474 | P44: 521474 | Q44: 524118 | R44: =SUM(F44:Q44) -> 9296786 | S44: 電気代
B45: 5005066282 | C45: =IFERROR(IF(VLOOKUP($B45,勘定科目!$A:$H,HLOOKUP($E$5,勘定科目!$F$1:$H$2,2,0),0)="","",VLOOKUP($B45,勘定科目!$A:$E,2,0)),"") -> 水道代（製） | D45: =IF(C45="","",VLOOKUP($B45,勘定科目!$A:$E,4,0)) -> 水道光熱費 | F45: 214990 | G45: 214990 | H45: 235027 | I45: 214606 | J45: 222677 | K45: 241465 | L45: 183088 | M45: 183088 | N45: 194303 | O45: 167597 | P45: 167597 | Q45: 138043 | R45: =SUM(F45:Q45) -> 2377471 | S45: 水道代
B46: 5005056281 | C46: =IFERROR(IF(VLOOKUP($B46,勘定科目!$A:$H,HLOOKUP($E$5,勘定科目!$F$1:$H$2,2,0),0)="","",VLOOKUP($B46,勘定科目!$A:$E,2,0)),"") -> ガス代（製） | D46: =IF(C46="","",VLOOKUP($B46,勘定科目!$A:$E,4,0)) -> 水道光熱費 | F46: 483345 | G46: 465075 | H46: 523557 | I46: 543051 | J46: 553626 | K46: 434007 | L46: 648164 | M46: 614691 | N46: 587818 | O46: 510785 | P46: 522126 | Q46: 601128 | R46: =SUM(F46:Q46) -> 6487373 | S46: ガス
B47: 5005016372 | C47: =IFERROR(IF(VLOOKUP($B47,勘定科目!$A:$H,HLOOKUP($E$5,勘定科目!$F$1:$H$2,2,0),0)="","",VLOOKUP($B47,勘定科目!$A:$E,2,0)),"") -> その他消耗品（製） | D47: =IF(C47="","",VLOOKUP($B47,勘定科目!$A:$E,4,0)) -> 消耗品費 | F47: 10071 | G47: 10773 | H47: 10269 | I47: 12177 | J47: 11340 | K47: 9549 | L47: 14410 | M47: 13189 | N47: 12705 | O47: 10648 | P47: 11946 | Q47: 12991 | R47: =SUM(F47:Q47) -> 140068 | S47: 手洗い洗剤
B48: 5005016372 | C48: =IFERROR(IF(VLOOKUP($B48,勘定科目!$A:$H,HLOOKUP($E$5,勘定科目!$F$1:$H$2,2,0),0)="","",VLOOKUP($B48,勘定科目!$A:$E,2,0)),"") -> その他消耗品（製） | D48: =IF(C48="","",VLOOKUP($B48,勘定科目!$A:$E,4,0)) -> 消耗品費 | F48: 157806 | G48: 173961 | H48: 166014 | I48: 190206 | J48: 182142 | K48: 149337 | L48: 232265 | M48: 212300 | N48: 202400 | O48: 172414 | P48: 192258 | Q48: 202455 | R48: =SUM(F48:Q48) -> 2233558 | S48: トイレットペーパー
B49: 5005016372 | C49: =IFERROR(IF(VLOOKUP($B49,勘定科目!$A:$H,HLOOKUP($E$5,勘定科目!$F$1:$H$2,2,0),0)="","",VLOOKUP($B49,勘定科目!$A:$E,2,0)),"") -> その他消耗品（製） | D49: =IF(C49="","",VLOOKUP($B49,勘定科目!$A:$E,4,0)) -> 消耗品費 | F49: 0 | G49: 0 | H49: 0 | I49: 0 | J49: 0 | K49: 0 | L49: 0 | M49: 0 | N49: 0 | O49: 0 | P49: 0 | Q49: 0 | R49: =SUM(F49:Q49) -> 0 | S49: アルコール 消毒
B50: 5005246286 | C50: =IFERROR(IF(VLOOKUP($B50,勘定科目!$A:$H,HLOOKUP($E$5,勘定科目!$F$1:$H$2,2,0),0)="","",VLOOKUP($B50,勘定科目!$A:$E,2,0)),"") -> その他手数料（製） | D50: =IF(C50="","",VLOOKUP($B50,勘定科目!$A:$E,4,0)) -> 手数料 | F50: 506133 | G50: 488673 | H50: 517761 | I50: 478872 | J50: 490122 | K50: 454464 | L50: 544852 | M50: 544192 | N50: 545259 | O50: 538538 | P50: 516351 | Q50: 557612 | R50: =SUM(F50:Q50) -> 6182829 | S50: 清掃費
B51: 5004086291 | C51: =IFERROR(IF(VLOOKUP($B51,勘定科目!$A:$H,HLOOKUP($E$5,勘定科目!$F$1:$H$2,2,0),0)="","",VLOOKUP($B51,勘定科目!$A:$E,2,0)),"") -> 福利厚生費（製） | D51: =IF(C51="","",VLOOKUP($B51,勘定科目!$A:$E,4,0)) -> 福利厚生費 | F51: 2100000 | G51: 2100000 | H51: 2100000 | I51: 2100000 | J51: 2100000 | K51: 2100000 | L51: 3500000 | M51: 3500000 | N51: 3500000 | O51: 3500000 | P51: 3500000 | Q51: 3500000 | R51: =SUM(F51:Q51) -> 33600000 | S51: 出向者送迎費
... B53: 5004086291 | C53: =IFERROR(IF(VLOOKUP($B53,勘定科目!$A:$H,HLOOKUP($E$5,勘定科目!$F$1:$H$2,2,0),0)="","",VLOOKUP($B53,勘定科目!$A:$E,2,0)),"") -> 福利厚生費（製） | D53: =IF(C53="","",VLOOKUP($B53,勘定科目!$A:$E,4,0)) -> 福利厚生費 | F53: 0 | G53: 0 | H53: 0 | I53: 0 | J53: 0 | K53: 0 | L53: 0 | M53: 0 | N53: 0 | O53: 0 | P53: 0 | Q53: 0 | R53: =SUM(F53:Q53) -> 0 | S53: 残業時のタクシー送迎費
B54: 5004086291 | C54: =IFERROR(IF(VLOOKUP($B54,勘定科目!$A:$H,HLOOKUP($E$5,勘定科目!$F$1:$H$2,2,0),0)="","",VLOOKUP($B54,勘定科目!$A:$E,2,0)),"") -> 福利厚生費（製） | D54: =IF(C54="","",VLOOKUP($B54,勘定科目!$A:$E,4,0)) -> 福利厚生費 | R54: =SUM(F54:Q54) -> 0 | S54: 出向者 通勤タクシー費用 （140,000*4 朝会 160,000×8 英語 固定 ＋α)
B55: 5004086291 | C55: =IFERROR(IF(VLOOKUP($B55,勘定科目!$A:$H,HLOOKUP($E$5,勘定科目!$F$1:$H$2,2,0),0)="","",VLOOKUP($B55,勘定科目!$A:$E,2,0)),"") -> 福利厚生費（製） | D55: =IF(C55="","",VLOOKUP($B55,勘定科目!$A:$E,4,0)) -> 福利厚生費 | F55: 0 | G55: 0 | H55: 0 | I55: 0 | J55: 0 | K55: 576000 | L55: 0 | M55: 0 | N55: 0 | O55: 0 | P55: 0 | Q55: 0 | R55: =SUM(F55:Q55) -> 576000 | S55: 月餅
B56: 5004086291 | C56: =IFERROR(IF(VLOOKUP($B56,勘定科目!$A:$H,HLOOKUP($E$5,勘定科目!$F$1:$H$2,2,0),0)="","",VLOOKUP($B56,勘定科目!$A:$E,2,0)),"") -> 福利厚生費（製） | D56: =IF(C56="","",VLOOKUP($B56,勘定科目!$A:$E,4,0)) -> 福利厚生費 | F56: 0 | G56: 0 | H56: 0 | I56: 0 | J56: 0 | K56: 0 | L56: 0 | M56: 0 | N56: 0 | O56: 0 | P56: 0 | Q56: 0 | R56: =SUM(F56:Q56) -> 0 | S56: 昼食代 (前月21日～当月20日を当月)
B57: 5004086291 | C57: =IFERROR(IF(VLOOKUP($B57,勘定科目!$A:$H,HLOOKUP($E$5,勘定科目!$F$1:$H$2,2,0),0)="","",VLOOKUP($B57,勘定科目!$A:$E,2,0)),"") -> 福利厚生費（製） | D57: =IF(C57="","",VLOOKUP($B57,勘定科目!$A:$E,4,0)) -> 福利厚生費 | F57: 0 | G57: 17964000 | H57: 0 | I57: 0 | J57: 0 | K57: 0 | L57: 0 | M57: 0 | N57: 0 | O57: 0 | P57: 0 | Q57: 0 | R57: =SUM(F57:Q57) -> 17964000 | S57: 社員旅行
B58: 5004086291 | C58: =IFERROR(IF(VLOOKUP($B58,勘定科目!$A:$H,HLOOKUP($E$5,勘定科目!$F$1:$H$2,2,0),0)="","",VLOOKUP($B58,勘定科目!$A:$E,2,0)),"") -> 福利厚生費（製） | D58: =IF(C58="","",VLOOKUP($B58,勘定科目!$A:$E,4,0)) -> 福利厚生費 | F58: 0 | G58: 0 | H58: 0 | I58: 0 | K58: 1206000 | L58: 0 | M58: 0 | N58: 0 | O58: 0 | P58: 0 | Q58: 0 | R58: =SUM(F58:Q58) -> 1206000 | S58: Kyoceraフェスティバル
B59: 5004086291 | C59: =IFERROR(IF(VLOOKUP($B59,勘定科目!$A:$H,HLOOKUP($E$5,勘定科目!$F$1:$H$2,2,0),0)="","",VLOOKUP($B59,勘定科目!$A:$E,2,0)),"") -> 福利厚生費（製） | D59: =IF(C59="","",VLOOKUP($B59,勘定科目!$A:$E,4,0)) -> 福利厚生費 | F59: 0 | G59: 0 | H59: 0 | I59: 0 | J59: 0 | K59: 0 | L59: 0 | M59: 1133000 | N59: 0 | O59: 0 | P59: 0 | Q59: 0 | R59: =SUM(F59:Q59) -> 1133000 | S59: 運動会
B60: 5004086291 | C60: =IFERROR(IF(VLOOKUP($B60,勘定科目!$A:$H,HLOOKUP($E$5,勘定科目!$F$1:$H$2,2,0),0)="","",VLOOKUP($B60,勘定科目!$A:$E,2,0)),"") -> 福利厚生費（製） | D60: =IF(C60="","",VLOOKUP($B60,勘定科目!$A:$E,4,0)) -> 福利厚生費 | F60: 0 | G60: 0 | H60: 0 | I60: 0 | J60: 0 | K60: 0 | L60: 0 | M60: 0 | N60: 0 | O60: 2200000 | P60: 0 | Q60: 0 | R60: =SUM(F60:Q60) -> 2200000 | S60: 忘年会補助金
B61: 5004086291 | C61: =IFERROR(IF(VLOOKUP($B61,勘定科目!$A:$H,HLOOKUP($E$5,勘定科目!$F$1:$H$2,2,0),0)="","",VLOOKUP($B61,勘定科目!$A:$E,2,0)),"") -> 福利厚生費（製） | D61: =IF(C61="","",VLOOKUP($B61,勘定科目!$A:$E,4,0)) -> 福利厚生費 | F61: 0 | G61: 0 | H61: 0 | I61: 0 | J61: 0 | K61: 0 | L61: 0 | M61: 0 | N61: 0 | O61: 0 | P61: 1100000 | Q61: 0 | R61: =SUM(F61:Q61) -> 1100000 | S61: お年玉
B62: 5004086291 | C62: =IFERROR(IF(VLOOKUP($B62,勘定科目!$A:$H,HLOOKUP($E$5,勘定科目!$F$1:$H$2,2,0),0)="","",VLOOKUP($B62,勘定科目!$A:$E,2,0)),"") -> 福利厚生費（製） | D62: =IF(C62="","",VLOOKUP($B62,勘定科目!$A:$E,4,0)) -> 福利厚生費 | F62: 163000 | G62: 163000 | H62: 163000 | I62: 0 | J62: 163000 | K62: 163000 | L62: 0 | M62: 163000 | N62: 163000 | O62: 163000 | P62: 0 | Q62: 0 | R62: =SUM(F62:Q62) -> 1304000 | S62: 誕生日会
B63: 5004086291 | C63: =IFERROR(IF(VLOOKUP($B63,勘定科目!$A:$H,HLOOKUP($E$5,勘定科目!$F$1:$H$2,2,0),0)="","",VLOOKUP($B63,勘定科目!$A:$E,2,0)),"") -> 福利厚生費（製） | D63: =IF(C63="","",VLOOKUP($B63,勘定科目!$A:$E,4,0)) -> 福利厚生費 | G63: 1800000 | R63: =SUM(F63:Q63) -> 1800000 | S63: 決起コンパ
B64: 5005246281 | C64: =IFERROR(IF(VLOOKUP($B64,勘定科目!$A:$H,HLOOKUP($E$5,勘定科目!$F$1:$H$2,2,0),0)="","",VLOOKUP($B64,勘定科目!$A:$E,2,0)),"") -> 図書印刷費（製） | D64: =IF(C64="","",VLOOKUP($B64,勘定科目!$A:$E,4,0)) -> 図書及び事務費 | F64: 0 | G64: 0 | H64: 0 | I64: 0 | J64: 0 | K64: 0 | L64: 0 | M64: 0 | N64: 8580 | O64: 0 | P64: 0 | Q64: 0 | R64: =SUM(F64:Q64) -> 8580 | S64: ポケットカレンダー
B65: 5004086291 | C65: =IFERROR(IF(VLOOKUP($B65,勘定科目!$A:$H,HLOOKUP($E$5,勘定科目!$F$1:$H$2,2,0),0)="","",VLOOKUP($B65,勘定科目!$A:$E,2,0)),"") -> 福利厚生費（製） | D65: =IF(C65="","",VLOOKUP($B65,勘定科目!$A:$E,4,0)) -> 福利厚生費 | F65: 0 | G65: 0 | H65: 0 | I65: 150000 | J65: 0 | K65: 0 | L65: 0 | M65: 0 | N65: 0 | O65: 0 | P65: 0 | Q65: 0 | R65: =SUM(F65:Q65) -> 150000 | S65: フィロソフィ論文参加賞
B66: 5004086291 | C66: =IFERROR(IF(VLOOKUP($B66,勘定科目!$A:$H,HLOOKUP($E$5,勘定科目!$F$1:$H$2,2,0),0)="","",VLOOKUP($B66,勘定科目!$A:$E,2,0)),"") -> 福利厚生費（製） | D66: =IF(C66="","",VLOOKUP($B66,勘定科目!$A:$E,4,0)) -> 福利厚生費 | F66: 0 | G66: 0 | H66: 0 | I66: 0 | J66: 0 | K66: 0 | L66: 0 | M66: 0 | N66: 1134000 | O66: 0 | P66: 0 | Q66: 0 | R66: =SUM(F66:Q66) -> 1134000 | S66: 健康診断（ローカル）男性
B67: 5004086291 | C67: =IFERROR(IF(VLOOKUP($B67,勘定科目!$A:$H,HLOOKUP($E$5,勘定科目!$F$1:$H$2,2,0),0)="","",VLOOKUP($B67,勘定科目!$A:$E,2,0)),"") -> 福利厚生費（製） | D67: =IF(C67="","",VLOOKUP($B67,勘定科目!$A:$E,4,0)) -> 福利厚生費 | F67: 0 | G67: 0 | H67: 0 | I67: 0 | J67: 0 | K67: 0 | L67: 0 | M67: 0 | N67: 0 | O67: 0 | P67: 0 | Q67: 0 | R67: =SUM(F67:Q67) -> 0 | S67: 健康診断（ローカル）女性
B68: 5005246281 | C68: =IFERROR(IF(VLOOKUP($B68,勘定科目!$A:$H,HLOOKUP($E$5,勘定科目!$F$1:$H$2,2,0),0)="","",VLOOKUP($B68,勘定科目!$A:$E,2,0)),"") -> 図書印刷費（製） | D68: =IF(C68="","",VLOOKUP($B68,勘定科目!$A:$E,4,0)) -> 図書及び事務費 | G68: 300000 | R68: =SUM(F68:Q68) -> 300000 | S68: Fukumaの名刺
C69: =IFERROR(IF(VLOOKUP($B69,勘定科目!$A:$H,HLOOKUP($E$5,勘定科目!$F$1:$H$2,2,0),0)="","",VLOOKUP($B69,勘定科目!$A:$E,2,0)),"") | D69: =IF(C69="","",VLOOKUP($B69,勘定科目!$A:$E,4,0)) | R69: =SUM(F69:Q69) -> 0 | S69: システム経費↓
B70: 5005246282 | C70: =IFERROR(IF(VLOOKUP($B70,勘定科目!$A:$H,HLOOKUP($E$5,勘定科目!$F$1:$H$2,2,0),0)="","",VLOOKUP($B70,勘定科目!$A:$E,2,0)),"") -> ＫＤＣシステム使用料（製） | D70: =IF(C70="","",VLOOKUP($B70,勘定科目!$A:$E,4,0)) -> 図書及び事務費 | F70: 1610996 | G70: 1610996 | H70: 1610996 | I70: 1610996 | J70: 1610996 | K70: 1610996 | L70: 1968995 | M70: 1968995 | N70: 1968995 | O70: 1968995 | P70: 1968995 | Q70: 1968995 | R70: =SUM(F70:Q70) -> 21479946 | S70: メール
B71: 5005246282 | C71: =IFERROR(IF(VLOOKUP($B71,勘定科目!$A:$H,HLOOKUP($E$5,勘定科目!$F$1:$H$2,2,0),0)="","",VLOOKUP($B71,勘定科目!$A:$E,2,0)),"") -> ＫＤＣシステム使用料（製） | D71: =IF(C71="","",VLOOKUP($B71,勘定科目!$A:$E,4,0)) -> 図書及び事務費 | F71: 0 | G71: 0 | H71: 0 | I71: 0 | J71: 0 | K71: 0 | L71: 0 | M71: 0 | N71: 0 | O71: 0 | P71: 0 | Q71: 0 | R71: =SUM(F71:Q71) -> 0 | S71: R3
B72: 5005246282 | C72: =IFERROR(IF(VLOOKUP($B72,勘定科目!$A:$H,HLOOKUP($E$5,勘定科目!$F$1:$H$2,2,0),0)="","",VLOOKUP($B72,勘定科目!$A:$E,2,0)),"") -> ＫＤＣシステム使用料（製） | D72: =IF(C72="","",VLOOKUP($B72,勘定科目!$A:$E,4,0)) -> 図書及び事務費 | F72: 0 | G72: 0 | H72: 0 | I72: 0 | J72: 0 | K72: 0 | L72: 0 | M72: 0 | N72: 0 | O72: 0 | P72: 0 | Q72: 0 | R72: =SUM(F72:Q72) -> 0 | S72: PLM
B73: 5005246282 | C73: =IFERROR(IF(VLOOKUP($B73,勘定科目!$A:$H,HLOOKUP($E$5,勘定科目!$F$1:$H$2,2,0),0)="","",VLOOKUP($B73,勘定科目!$A:$E,2,0)),"") -> ＫＤＣシステム使用料（製） | D73: =IF(C73="","",VLOOKUP($B73,勘定科目!$A:$E,4,0)) -> 図書及び事務費 | F73: 1191553 | G73: 1191553 | H73: 1191553 | I73: 1191553 | J73: 1191553 | K73: 1191553 | L73: 1191553 | M73: 1191553 | N73: 1191553 | O73: 1191553 | P73: 1191553 | Q73: 1191553 | R73: =SUM(F73:Q73) -> 14298636 | S73: VPS
B74: 5005246282 | C74: =IFERROR(IF(VLOOKUP($B74,勘定科目!$A:$H,HLOOKUP($E$5,勘定科目!$F$1:$H$2,2,0),0)="","",VLOOKUP($B74,勘定科目!$A:$E,2,0)),"") -> ＫＤＣシステム使用料（製） | D74: =IF(C74="","",VLOOKUP($B74,勘定科目!$A:$E,4,0)) -> 図書及び事務費 | R74: =SUM(F74:Q74) -> 0 | S74: 翻訳ツール(COTOHA)
B75: 5005246282 | C75: =IFERROR(IF(VLOOKUP($B75,勘定科目!$A:$H,HLOOKUP($E$5,勘定科目!$F$1:$H$2,2,0),0)="","",VLOOKUP($B75,勘定科目!$A:$E,2,0)),"") -> ＫＤＣシステム使用料（製） | D75: =IF(C75="","",VLOOKUP($B75,勘定科目!$A:$E,4,0)) -> 図書及び事務費 | F75: 0 | G75: 0 | H75: 0 | I75: 0 | J75: 0 | K75: 0 | L75: 0 | M75: 0 | N75: 0 | O75: 0 | P75: 0 | Q75: 0 | R75: =SUM(F75:Q75) -> 0 | S75: CAD \4,931,701/月 （新CADも含む CADユーザー追加分で予測）→FY2026～MD4課へ移動
B76: 5005246282 | C76: =IFERROR(IF(VLOOKUP($B76,勘定科目!$A:$H,HLOOKUP($E$5,勘定科目!$F$1:$H$2,2,0),0)="","",VLOOKUP($B76,勘定科目!$A:$E,2,0)),"") -> ＫＤＣシステム使用料（製） | D76: =IF(C76="","",VLOOKUP($B76,勘定科目!$A:$E,4,0)) -> 図書及び事務費 | F76: 0 | G76: 0 | H76: 0 | I76: 0 | J76: 0 | K76: 0 | L76: 0 | M76: 0 | N76: 0 | O76: 0 | P76: 0 | Q76: 0 | R76: =SUM(F76:Q76) -> 0 | S76: VPN
C77: =IFERROR(IF(VLOOKUP($B77,勘定科目!$A:$H,HLOOKUP($E$5,勘定科目!$F$1:$H$2,2,0),0)="","",VLOOKUP($B77,勘定科目!$A:$E,2,0)),"") | D77: =IF(C77="","",VLOOKUP($B77,勘定科目!$A:$E,4,0)) | R77: =SUM(F77:Q77) -> 0 | S77: 新入社員経費↓
B78: 5005246281 | C78: =IFERROR(IF(VLOOKUP($B78,勘定科目!$A:$H,HLOOKUP($E$5,勘定科目!$F$1:$H$2,2,0),0)="","",VLOOKUP($B78,勘定科目!$A:$E,2,0)),"") -> 図書印刷費（製） | D78: =IF(C78="","",VLOOKUP($B78,勘定科目!$A:$E,4,0)) -> 図書及び事務費 | R78: =SUM(F78:Q78) -> 0 | S78: 新入社員 社員証
B79: 5005246281 | C79: =IFERROR(IF(VLOOKUP($B79,勘定科目!$A:$H,HLOOKUP($E$5,勘定科目!$F$1:$H$2,2,0),0)="","",VLOOKUP($B79,勘定科目!$A:$E,2,0)),"") -> 図書印刷費（製） | D79: =IF(C79="","",VLOOKUP($B79,勘定科目!$A:$E,4,0)) -> 図書及び事務費 | R79: =SUM(F79:Q79) -> 0 | S79: 新入社員 社員証ケース
B80: 5005246288 | C80: =IFERROR(IF(VLOOKUP($B80,勘定科目!$A:$H,HLOOKUP($E$5,勘定科目!$F$1:$H$2,2,0),0)="","",VLOOKUP($B80,勘定科目!$A:$E,2,0)),"") -> 事務用品費（製） | D80: =IF(C80="","",VLOOKUP($B80,勘定科目!$A:$E,4,0)) -> 図書及び事務費 | R80: =SUM(F80:Q80) -> 0 | S80: 新入社員 Pen
B81: 5005246288 | C81: =IFERROR(IF(VLOOKUP($B81,勘定科目!$A:$H,HLOOKUP($E$5,勘定科目!$F$1:$H$2,2,0),0)="","",VLOOKUP($B81,勘定科目!$A:$E,2,0)),"") -> 事務用品費（製） | D81: =IF(C81="","",VLOOKUP($B81,勘定科目!$A:$E,4,0)) -> 図書及び事務費 | R81: =SUM(F81:Q81) -> 0 | S81: 新入社員 Note
B82: 5005246281 | C82: =IFERROR(IF(VLOOKUP($B82,勘定科目!$A:$H,HLOOKUP($E$5,勘定科目!$F$1:$H$2,2,0),0)="","",VLOOKUP($B82,勘定科目!$A:$E,2,0)),"") -> 図書印刷費（製） | D82: =IF(C82="","",VLOOKUP($B82,勘定科目!$A:$E,4,0)) -> 図書及び事務費 | R82: =SUM(F82:Q82) -> 0 | S82: 新入社員 フィロソフィ手帳
B83: 5004086291 | C83: =IFERROR(IF(VLOOKUP($B83,勘定科目!$A:$H,HLOOKUP($E$5,勘定科目!$F$1:$H$2,2,0),0)="","",VLOOKUP($B83,勘定科目!$A:$E,2,0)),"") -> 福利厚生費（製） | D83: =IF(C83="","",VLOOKUP($B83,勘定科目!$A:$E,4,0)) -> 福利厚生費 | R83: =SUM(F83:Q83) -> 0 | S83: 新入社員 採用時健康診断 （採用時）男性
B84: 5004086291 | C84: =IFERROR(IF(VLOOKUP($B84,勘定科目!$A:$H,HLOOKUP($E$5,勘定科目!$F$1:$H$2,2,0),0)="","",VLOOKUP($B84,勘定科目!$A:$E,2,0)),"") -> 福利厚生費（製） | D84: =IF(C84="","",VLOOKUP($B84,勘定科目!$A:$E,4,0)) -> 福利厚生費 | R84: =SUM(F84:Q84) -> 0 | S84: 新入社員 採用時健康診断 （採用時）女性
B85: 5004086291 | C85: =IFERROR(IF(VLOOKUP($B85,勘定科目!$A:$H,HLOOKUP($E$5,勘定科目!$F$1:$H$2,2,0),0)="","",VLOOKUP($B85,勘定科目!$A:$E,2,0)),"") -> 福利厚生費（製） | D85: =IF(C85="","",VLOOKUP($B85,勘定科目!$A:$E,4,0)) -> 福利厚生費 | R85: =SUM(F85:Q85) -> 0 | S85: 新入社員 帽子
B86: 5004086291 | C86: =IFERROR(IF(VLOOKUP($B86,勘定科目!$A:$H,HLOOKUP($E$5,勘定科目!$F$1:$H$2,2,0),0)="","",VLOOKUP($B86,勘定科目!$A:$E,2,0)),"") -> 福利厚生費（製） | D86: =IF(C86="","",VLOOKUP($B86,勘定科目!$A:$E,4,0)) -> 福利厚生費 | R86: =SUM(F86:Q86) -> 0 | S86: 新入社員 制服上着(夏服) x2枚/人
B87: 5004086291 | C87: =IFERROR(IF(VLOOKUP($B87,勘定科目!$A:$H,HLOOKUP($E$5,勘定科目!$F$1:$H$2,2,0),0)="","",VLOOKUP($B87,勘定科目!$A:$E,2,0)),"") -> 福利厚生費（製） | D87: =IF(C87="","",VLOOKUP($B87,勘定科目!$A:$E,4,0)) -> 福利厚生費 | R87: =SUM(F87:Q87) -> 0 | S87: 新入社員 制服上着(冬服) x2枚/人
B88: 5004086291 | C88: =IFERROR(IF(VLOOKUP($B88,勘定科目!$A:$H,HLOOKUP($E$5,勘定科目!$F$1:$H$2,2,0),0)="","",VLOOKUP($B88,勘定科目!$A:$E,2,0)),"") -> 福利厚生費（製） | D88: =IF(C88="","",VLOOKUP($B88,勘定科目!$A:$E,4,0)) -> 福利厚生費 | R88: =SUM(F88:Q88) -> 0 | S88: 新入社員 制服(ズボン) x2枚/人
B89: 5004086291 | C89: =IFERROR(IF(VLOOKUP($B89,勘定科目!$A:$H,HLOOKUP($E$5,勘定科目!$F$1:$H$2,2,0),0)="","",VLOOKUP($B89,勘定科目!$A:$E,2,0)),"") -> 福利厚生費（製） | D89: =IF(C89="","",VLOOKUP($B89,勘定科目!$A:$E,4,0)) -> 福利厚生費 | R89: =SUM(F89:Q89) -> 0 | S89: 新入社員 靴 男性
... B95: 5005026371 | C95: =IFERROR(IF(VLOOKUP($B95,勘定科目!$A:$H,HLOOKUP($E$5,勘定科目!$F$1:$H$2,2,0),0)="","",VLOOKUP($B95,勘定科目!$A:$E,2,0)),"") -> 消耗工具器具備品費（製） | D95: =IF(C95="","",VLOOKUP($B95,勘定科目!$A:$E,4,0)) -> 消耗工具器具備品費 | R95: =SUM(F95:Q95) -> 0 | S95: 新入社員 事務机用椅子
C96: =IFERROR(IF(VLOOKUP($B96,勘定科目!$A:$H,HLOOKUP($E$5,勘定科目!$F$1:$H$2,2,0),0)="","",VLOOKUP($B96,勘定科目!$A:$E,2,0)),"") | D96: =IF(C96="","",VLOOKUP($B96,勘定科目!$A:$E,4,0)) | R96: =SUM(F96:Q96) -> 0 | S96: INTERNSHIP↓
B97: 5005246281 | C97: =IFERROR(IF(VLOOKUP($B97,勘定科目!$A:$H,HLOOKUP($E$5,勘定科目!$F$1:$H$2,2,0),0)="","",VLOOKUP($B97,勘定科目!$A:$E,2,0)),"") -> 図書印刷費（製） | D97: =IF(C97="","",VLOOKUP($B97,勘定科目!$A:$E,4,0)) -> 図書及び事務費 | R97: =SUM(F97:Q97) -> 0 | S97: 社員証（新入社員用・再発行時、写真含む） Thẻ từ chấm công + ảnh 58000VND
B98: 5005246288 | C98: =IFERROR(IF(VLOOKUP($B98,勘定科目!$A:$H,HLOOKUP($E$5,勘定科目!$F$1:$H$2,2,0),0)="","",VLOOKUP($B98,勘定科目!$A:$E,2,0)),"") -> 事務用品費（製） | D98: =IF(C98="","",VLOOKUP($B98,勘定科目!$A:$E,4,0)) -> 図書及び事務費 | R98: =SUM(F98:Q98) -> 0 | S98: 社員証用ケース Vỏ thẻ + móc thẻ 3600VND
B99: 5005246288 | C99: =IFERROR(IF(VLOOKUP($B99,勘定科目!$A:$H,HLOOKUP($E$5,勘定科目!$F$1:$H$2,2,0),0)="","",VLOOKUP($B99,勘定科目!$A:$E,2,0)),"") -> 事務用品費（製） | D99: =IF(C99="","",VLOOKUP($B99,勘定科目!$A:$E,4,0)) -> 図書及び事務費 | R99: =SUM(F99:Q99) -> 0 | S99: ペン Bút 1名×3000VND
B100: 5005246288 | C100: =IFERROR(IF(VLOOKUP($B100,勘定科目!$A:$H,HLOOKUP($E$5,勘定科目!$F$1:$H$2,2,0),0)="","",VLOOKUP($B100,勘定科目!$A:$E,2,0)),"") -> 事務用品費（製） | D100: =IF(C100="","",VLOOKUP($B100,勘定科目!$A:$E,4,0)) -> 図書及び事務費 | R100: =SUM(F100:Q100) -> 0 | S100: ノート Số 1名×400VND
B101: 5005246281 | C101: =IFERROR(IF(VLOOKUP($B101,勘定科目!$A:$H,HLOOKUP($E$5,勘定科目!$F$1:$H$2,2,0),0)="","",VLOOKUP($B101,勘定科目!$A:$E,2,0)),"") -> 図書印刷費（製） | D101: =IF(C101="","",VLOOKUP($B101,勘定科目!$A:$E,4,0)) -> 図書及び事務費 | R101: =SUM(F101:Q101) -> 0 | S101: フィロソフィ手帳 Sổ tay philosophy I &II 1名×12,000VND
B102: 5004086291 | C102: =IFERROR(IF(VLOOKUP($B102,勘定科目!$A:$H,HLOOKUP($E$5,勘定科目!$F$1:$H$2,2,0),0)="","",VLOOKUP($B102,勘定科目!$A:$E,2,0)),"") -> 福利厚生費（製） | D102: =IF(C102="","",VLOOKUP($B102,勘定科目!$A:$E,4,0)) -> 福利厚生費 | R102: =SUM(F102:Q102) -> 0 | S102: 制服（夏） Đồng phục ngắn tay 1名×2X116,000VND
B103: 5004086291 | C103: =IFERROR(IF(VLOOKUP($B103,勘定科目!$A:$H,HLOOKUP($E$5,勘定科目!$F$1:$H$2,2,0),0)="","",VLOOKUP($B103,勘定科目!$A:$E,2,0)),"") -> 福利厚生費（製） | D103: =IF(C103="","",VLOOKUP($B103,勘定科目!$A:$E,4,0)) -> 福利厚生費 | R103: =SUM(F103:Q103) -> 0 | S103: 制服（冬） Đồng phục dài tay 142500VND
B104: 5004086291 | C104: =IFERROR(IF(VLOOKUP($B104,勘定科目!$A:$H,HLOOKUP($E$5,勘定科目!$F$1:$H$2,2,0),0)="","",VLOOKUP($B104,勘定科目!$A:$E,2,0)),"") -> 福利厚生費（製） | D104: =IF(C104="","",VLOOKUP($B104,勘定科目!$A:$E,4,0)) -> 福利厚生費 | R104: =SUM(F104:Q104) -> 0 | S104: 制服ズボン Quần 1名×116,000VND
B105: 5004086291 | C105: =IFERROR(IF(VLOOKUP($B105,勘定科目!$A:$H,HLOOKUP($E$5,勘定科目!$F$1:$H$2,2,0),0)="","",VLOOKUP($B105,勘定科目!$A:$E,2,0)),"") -> 福利厚生費（製） | D105: =IF(C105="","",VLOOKUP($B105,勘定科目!$A:$E,4,0)) -> 福利厚生費 | R105: =SUM(F105:Q105) -> 0 | S105: シューズ（男性） Giày vải nam 1名×82,000VND
B106: 5004086291 | C106: =IFERROR(IF(VLOOKUP($B106,勘定科目!$A:$H,HLOOKUP($E$5,勘定科目!$F$1:$H$2,2,0),0)="","",VLOOKUP($B106,勘定科目!$A:$E,2,0)),"") -> 福利厚生費（製） | D106: =IF(C106="","",VLOOKUP($B106,勘定科目!$A:$E,4,0)) -> 福利厚生費 | R106: =SUM(F106:Q106) -> 0 | S106: 帽子（白） Mũ trắng 1名×33,500VND
B107: 5004086291 | C107: =IFERROR(IF(VLOOKUP($B107,勘定科目!$A:$H,HLOOKUP($E$5,勘定科目!$F$1:$H$2,2,0),0)="","",VLOOKUP($B107,勘定科目!$A:$E,2,0)),"") -> 福利厚生費（製） | D107: =IF(C107="","",VLOOKUP($B107,勘定科目!$A:$E,4,0)) -> 福利厚生費 | R107: =SUM(F107:Q107) -> 0 | S107: 折りたたみ
...

Sheet 設備投資計画
B1: 設備投資金額一覧表 | D1: ='内訳ﾘｽﾄ(4～3月)'!C5 -> MD2課 | E1: (単位： VND)
B3: 部門ｺｰﾄﾞ | C3: 購入物品名 | D3: 目 的 | E3: 4 | F3: 5 | G3: 6 | H3: 7 | I3: 8 | J3: 9 | K3: 10 | L3: 11 | M3: 12 | N3: 1 | O3: 2 | P3: 3 | Q3: 償却期間 (ヶ月) | R3: 購入金額合計 | S3: WBS
R4: =SUM(E4:P4) -> 0
R5: =SUM(E5:P5) -> 0
R6: =SUM(E6:P6) -> 0
R7: =SUM(E7:P7) -> 0
R8: =SUM(E8:P8) -> 0
R9: =SUM(E9:P9) -> 0
R10: =SUM(E10:P10) -> 0
R11: =SUM(E11:P11) -> 0
R12: =SUM(E12:P12) -> 0
R13: =SUM(E13:P13) -> 0
R14: =SUM(E14:P14) -> 0
R15: =SUM(E15:P15) -> 0
... R49: =SUM(E49:P49) -> 0
D50: TOTAL | R50: =SUM(E50:P50) -> 0
B52: ＊設備投資は、30,000,000VND以上、且つ1年以上使用するものが対象となります。
B53: ＊建設仮勘定を含む、取得基準にて記入して下さい。
B54: ＊重複を避ける為、稟議起案部門にて記入して下さい。
B55: ＊リースによる設備投資を含めないで下さい。

Sheet 勘定科目
A1: Account_Code | B1: JPN (50cha) | C1: Tiếng Việt_Tên tài khoản kế toán | D1: JP_Name | E1: Tiếng Việt_Hạng mục lợi nhuận | F1: 製造 | G1: 一般 | H1: 販売 | I1: REMARK
F2: =COLUMNS($A$2:F2) -> 6 | G2: =COLUMNS($A$2:G2) -> 7 | H2: =COLUMNS($A$2:H2) -> 8
A3: 7001065118 | B3: 雑収入 | C3: Doanh thu khác | D3: 雑収入 | E3: Thu nhập khác | F3: 7001065118 | G3: 7001065118 | H3: 7001065118
A4: 7001075118 | B4: 雑収入（関係会社） | C4: Doanh thu khác | D4: 雑収入 | E4: Thu nhập khác | F4: 7001075118 | G4: 7001075118 | H4: 7001075118
A5: 7001065119 | B5: 固定資産売却勘定 | C5: Doanh thu khác | D5: 雑収入 | E5: Thu nhập khác | F5: 7001065119 | G5: 7001065119 | H5: 7001065119
A6: 5001016131 | B6: 材料仕入割戻高 | C6: Chi phí nguyên liệu, vật liệu trực tiếp | D6: 材料費 | E6: Chi phí nguyên vật liệu | F6: 5001016131 | I6: 2016年4月から追加する。
A7: 5001016134 | B7: リーフレット用材料 | C7: Chi phí nguyên liệu, vật liệu trực tiếp | D7: 材料費 | E7: Chi phí nguyên vật liệu | F7: 5001016134 | G7: 5001016134 | H7: 5001016134 | I7: 2017年1月変更。
A8: 5001016135 | B8: 不良部品材料費 | C8: Chi phí nguyên liệu, vật liệu trực tiếp | D8: 材料費 | E8: Chi phí nguyên vật liệu | F8: 5001016135 | G8: 5001016135 | H8: 5001016135
A9: 5001016136 | B9: 追加指図部品費 | C9: Chi phí nguyên liệu, vật liệu trực tiếp | D9: 材料費 | E9: Chi phí nguyên vật liệu | F9: 5001016136 | G9: 5001016136 | H9: 5001016136
A10: 5001016142 | B10: 加工中不良廃棄損 | C10: Chi phí nguyên liệu, vật liệu trực tiếp | D10: 仕掛仕損 | E10: Sản phẩm chưa hoàn thiện,hỏng | F10: 5001016142 | G10: 5001016142 | H10: 5001016142
A11: 5001016149 | B11: 金型材料仕入 | C11: Chi phí nguyên liệu, vật liệu trực tiếp | D11: 材料費 | E11: Chi phí nguyên vật liệu | F11: 5001016149 | G11: 5001016149 | H11: 5001016149 | I11: 2月から追加する。
A12: 5001016151 | B12: 生産用副資材 | C12: Chi phí nguyên liệu, vật liệu trực tiếp | D12: 材料費 | E12: Chi phí nguyên vật liệu | F12: 5001016151 | I12: 2017年1月追加。
A13: 5004046221 | B13: 雑給（直製） | C13: Chi phí nhân công trực tiếp | D13: 雑給 | E13: Chi phí nhân công trực tiếp | F13: 5004046221
A14: 5004046371 | B14: 雑給（間製） | C14: Chi phí nhân viên phân xưởng | D14: 雑給 | E14: Chi phí nhân công trực tiếp | F14: 5004046371
A15: 5005016371 | B15: 生産用消耗品費（製） | C15: Chi phí dụng cụ sản xuất | D15: 消耗品費 | E15: Chi phí hàng hóa tiêu hao | F15: 5005016371
A16: 5005016372 | B16: その他消耗品（製） | C16: Chi phí dụng cụ sản xuất | D16: 消耗品費 | E16: Chi phí hàng hóa tiêu hao | F16: 5005016372
A17: 5005016373 | B17: 生産用文房具（製造） | C17: Chi phí dụng cụ sản xuất | D17: 消耗品費 | E17: Chi phí hàng hóa tiêu hao | F17: 5005016373 | I17: 2017年1月追加。
A18: 5005026371 | B18: 消耗工具器具備品費（製） | C18: Chi phí dụng cụ sản xuất | D18: 消耗工具器具備品費 | E18: Chi phí sử dụng công cụ,đồ đạc | F18: 5005026371
A19: 5005026372 | B19: 消耗金型代（製） | C19: Chi phí dụng cụ sản xuất | D19: 消耗金型費 | E19: Chi phí tiêu hao khuôn | F19: 5005026372
A20: 5006016241 | B20: 減価償却費（製） 建物 | C20: Chi phí khấu hao TSCĐ | D20: 減価償却費 | E20: Chi phí khấu hao | F20: 5006016241
A21: 5006016242 | B21: 減価償却費（製） 機械装置 | C21: Chi phí khấu hao TSCĐ | D21: 減価償却費 | E21: Chi phí khấu hao | F21: 5006016242
A22: 5006016243 | B22: 減価償却費（製） 車輌運搬具 | C22: Chi phí khấu hao TSCĐ | D22: 減価償却費 | E22: Chi phí khấu hao | F22: 5006016243
A23: 5006016244 | B23: 減価償却費（製） 工具器具備品 | C23: Chi phí khấu hao TSCĐ | D23: 減価償却費 | E23: Chi phí khấu hao | F23: 5006016244
A24: 5006016245 | B24: 減価償却費（製） 構築物 | C24: Chi phí khấu hao TSCĐ | D24: 減価償却費 | E24: Chi phí khấu hao | F24: 5006016245
A25: 5005036246 | B25: 減価償却費（製） 金型 | C25: Chi phí khấu hao TSCĐ | D25: 金型償却費 | E25: Chi phí khấu hao khuôn | F25: 5005036246
A26: 5006016247 | B26: 減価償却費（製） その他有形固定資産 | C26: Chi phí khấu hao TSCĐ | D26: 減価償却費 | E26: Chi phí khấu hao | F26: 5006016247
A27: 5006016248 | B27: 減価償却費（製） リース建物 | C27: Chi phí khấu hao TSCĐ | D27: 減価償却費 | E27: Chi phí khấu hao | F27: 5006016248
A28: 5006016249 | B28: 減価償却費（製） リース機械装置 | C28: Chi phí khấu hao TSCĐ | D28: 減価償却費 | E28: Chi phí khấu hao | F28: 5006016249
A29: 5006016250 | B29: 減価償却費（製） リース車輌運搬具 | C29: Chi phí khấu hao TSCĐ | D29: 減価償却費 | E29: Chi phí khấu hao | F29: 5006016250
... A44: 5005046283 | B44: 年間保守料（製） | C44: Chi phi dịch vụ mua ngoài | D44: 修繕費 | E44: Chi phí sửa chữa | F44: 5005046283
A45: 5005046284 | B45: 金型修繕費（製造） | C45: Chi phi dịch vụ mua ngoài | D45: 修繕費 | E45: Chi phí sửa chữa | F45: 5005046284 | I45: 2017年1月追加。
A46: 5005066281 | B46: 電気代（製） | C46: Chi phi dịch vụ mua ngoài | D46: 水道光熱費 | E46: Chi phí Utilities(điện,nước..) | F46: 5005066281
A47: 5005066282 | B47: 水道代（製） | C47: Chi phi dịch vụ mua ngoài | D47: 水道光熱費 | E47: Chi phí Utilities(điện,nước..) | F47: 5005066282
A48: 5005056281 | B48: ガス代（製） | C48: Chi phi dịch vụ mua ngoài | D48: 水道光熱費 | E48: Chi phí Utilities(điện,nước..) | F48: 5005056281
A49: 5005076281 | B49: 通関申告費用（製） | C49: Chi phi dịch vụ mua ngoài | D49: 荷造運賃 | E49: Chi phí vận chuyển hàng hóa | F49: 5005076281
A50: 5005076282 | B50: 設備輸送費（製） | C50: Chi phi dịch vụ mua ngoài | D50: 荷造運賃 | E50: Chi phí vận chuyển hàng hóa | F50: 5005076282
A51: 5005076283 | B51: 輸入航空運賃（製） | C51: Chi phi dịch vụ mua ngoài | D51: 荷造運賃 | E51: Chi phí vận chuyển hàng hóa | F51: 5005076283
A52: 5005076284 | B52: 輸入海上運賃（製） | C52: Chi phi dịch vụ mua ngoài | D52: 荷造運賃 | E52: Chi phí vận chuyển hàng hóa | F52: 5005076284
A53: 5005076285 | B53: 空箱返却費用 | C53: Chi phi dịch vụ mua ngoài | D53: 荷造運賃 | E53: Chi phí vận chuyển hàng hóa | F53: 5005076285
A54: 5005076286 | B54: 部品集荷トラック代 | C54: Chi phi dịch vụ mua ngoài | D54: 荷造運賃 | E54: Chi phí vận chuyển hàng hóa | F54: 5005076286
A55: 5005076287 | B55: 物流保険料（製） | C55: Chi phi dịch vụ mua ngoài | D55: 荷造運賃 | E55: Chi phí vận chuyển hàng hóa | F55: 5005076287
A56: 5005076288 | B56: 梱包材料費（製） | C56: Chi phi dịch vụ mua ngoài | D56: 荷造用品費 | E56: Chi phí NVL dùng đóng gói hàng | F56: 5005076288
A57: 5005076289 | B57: クーリエ費用（製） | C57: Chi phi dịch vụ mua ngoài | D57: 荷造運賃 | E57: Chi phí vận chuyển hàng hóa | F57: 5005076289
A58: 5005076291 | B58: 外部倉庫 取扱手数料（製造） | C58: Chi phi dịch vụ mua ngoài | D58: 荷造運賃 | E58: Chi phí vận chuyển hàng hóa | F58: 5005076291 | I58: 2017年1月追加。
A59: 5005076292 | B59: 外部倉庫 保管料（製造） | C59: Chi phi dịch vụ mua ngoài | D59: 荷造運賃 | E59: Chi phí vận chuyển hàng hóa | F59: 5005076292 | I59: 2017年1月追加。
A60: 5005076293 | B60: 外部倉庫 輸送料（製造） | C60: Chi phi dịch vụ mua ngoài | D60: 荷造運賃 | E60: Chi phí vận chuyển hàng hóa | F60: 5005076293 | I60: 2017年1月追加。
A61: 5005076294 | B61: 外部物流業者 取扱手数料（製造） | C61: Chi phi dịch vụ mua ngoài | D61: 荷造運賃 | E61: Chi phí vận chuyển hàng hóa | F61: 5005076294 | I61: 2017年1月追加。
A62: 5005086281 | B62: 技術料（製） | C62: Chi phi dịch vụ mua ngoài | D62: 技術料 | E62: Phí kỹ thuật | F62: 5005086281
A63: 5005136281 | B63: 通信費（製） | C63: Chi phi dịch vụ mua ngoài | D63: 通信費 | E63: Chi phí điện thoại | F63: 5005136281
A64: 5005246281 | B64: 図書印刷費（製） | C64: Chi phi dịch vụ mua ngoài | D64: 図書及び事務費 | E64: Chi phí văn phòng | F64: 5005246281
A65: 5005246282 | B65: ＫＤＣシステム使用料（製） | C65: Chi phi dịch vụ mua ngoài | D65: 図書及び事務費 | E65: Chi phí văn phòng | F65: 5005246282
A66: 5005246283 | B66: ライセンス料（製） | C66: Chi phi dịch vụ mua ngoài | D66: 図書及び事務費 | E66: Chi phí văn phòng | F66: 5005246283
A67: 5005246284 | B67: 会費（製） | C67: Chi phi dịch vụ mua ngoài | D67: 会費及び会議費 | E67: Chi phí cuộc họp | F67: 5005246284
A68: 5005216281 | B68: 委嘱報酬・設計委託費（製） | C68: Chi phi dịch vụ mua ngoài | D68: 委嘱報酬 | E68: Thù lao ủy thác,phí hoa hồng | F68: 5005216281
A69: 5005226281 | B69: 保険料（製） | C69: Chi phi dịch vụ mua ngoài | D69: 保険料 | E69: Chi phí bảo hiểm | F69: 5005226281
A70: 5005236281 | B70: 事務所賃借料（製） | C70: Chi phi dịch vụ mua ngoài | D70: 賃借料 | E70: Chi phí thuê | F70: 5005236281
A71: 5005236282 | B71: 倉庫賃借料（製） | C71: Chi phi dịch vụ mua ngoài | D71: 賃借料 | E71: Chi phí thuê | F71: 5005236282
A72: 5005246285 | B72: 取扱手数料（製） | C72: Chi phi dịch vụ mua ngoài | D72: 手数料 | E72: Tiền dịch vụ,tiền lệ phí | F72: 5005246285
A73: 5005246286 | B73: その他手数料（製） | C73: Chi phi dịch vụ mua ngoài | D73: 手数料 | E73: Tiền dịch vụ,tiền lệ phí | F73: 5005246286
... A82: 5005186292 | B82: その他税金（製） | C82: Chi phí bằng tiền khác | D82: 公租公課 | E82: Thuế,phí công cộng | F82: 5005186292
A83: 5005196373 | B83: 試験研究用材料費 | C83: Chi phí dụng cụ sản xuất | D83: 試験研究費 | E83: Chi phí thử nghiệm,nghiên cứu | F83: 5005196373 | G83: 5005196373 | H83: 5005196373 | I83: 2月から追加する。
A84: 5005196277 | B84: 試験研究用役務費 | C84: Chi phi dịch vụ mua ngoài | D84: 試験研究費 | E84: Chi phí thử nghiệm,nghiên cứu | F84: 5005196277 | G84: 5005196277 | H84: 5005196277 | I84: 2月から追加する。
A85: 5005246291 | B85: 会議費（製） | C85: Chi phí bằng tiền khác | D85: 会費及び会議費 | E85: Chi phí cuộc họp | F85: 5005246291
A86: 5005246292 | B86: 雑費（製） | C86: Chi phí bằng tiền khác | D86: 雑費 | E86: Các loại chi phí bằng tiền khác | F86: 5005246292
A87: 5005246294 | B87: 開発費振替勘定（製） | C87: Chi phí bằng tiền khác | D87: 雑費 | E87: Các loại chi phí bằng tiền khác | F87: 5005246294 | I87: 2月から追加する→9/2015からｘから雑費になった
A88: 5005256291 | B88: 棚卸減耗費（製） | C88: Chi phí bằng tiền khác | D88: 棚卸減耗費 | E88: Chi phí hao hụt sau kiểm kê | F88: 5005256291
A89: 5101016174 | B89: 製商品仕入諸掛 | C89: Giá vốn hàng bán | D89: 仕入製商品費 | E89: Chi phí bán hàng | F89: 5101016174
A90: 5101016179 | B90: 製品品目外注加工費 | C90: Giá vốn hàng bán | D90: 外注加工費 | E90: Chi phí gia công ngoài | F90: 5101016179
A91: 5101016187 | B91: 製商品在庫廃棄損 | C91: Giá vốn hàng bán | D91: 雑損失 | E91: Tổn thất,lỗ khác | F91: 5101016187
A92: 5101016189 | B92: 金型製作収入 | C92: Doanh thu bán thành phẩm | D92: 雑収入 | E92: Thu nhập khác | F92: 5101016189 | I92: 2月から追加する。
A93: 6004046511 | B93: 雑給（販売） | C93: Chi phí nhân viên | D93: 雑給 | E93: Chi phí nhân công trực tiếp | H93: 6004046511
A94: 6003036412 | B94: 梱包材料費（販売） | C94: Chi phí vật liệu bao bì | D94: 荷造用品費 | E94: Chi phí NVL dùng đóng gói hàng | H94: 6003036412
A95: 6005016413 | B95: 消耗品費（販売） | C95: Chi phí dụng cụ đồ dùng | D95: 消耗品費 | E95: Chi phí hàng hóa tiêu hao | H95: 6005016413
A96: 6005016414 | B96: 消耗備品費（販売） | C96: Chi phí dụng cụ đồ dùng | D96: 消耗工具器具備品費 | E96: Chi phí sử dụng công cụ,đồ đạc | G96: 6005016414 | H96: 6005016414 | I96: 2017年1月追加。
A97: 6006016521 | B97: 減価償却費（販） 建物 | C97: Chi phí khấu hao TSCĐ | D97: 減価償却費 | E97: Chi phí khấu hao | H97: 6006016521
A98: 6006016522 | B98: 減価償却費（販） 機械装置 | C98: Chi phí khấu hao TSCĐ | D98: 減価償却費 | E98: Chi phí khấu hao | H98: 6006016522
A99: 6006016523 | B99: 減価償却費（販） 車輌運搬具 | C99: Chi phí khấu hao TSCĐ | D99: 減価償却費 | E99: Chi phí khấu hao | H99: 6006016523
A100: 6006016524 | B100: 減価償却費（販） 工具器具備品 | C100: Chi phí khấu hao TSCĐ | D100: 減価償却費 | E100: Chi phí khấu hao | H100: 6006016524
A101: 6006016525 | B101: 減価償却費（販） 構築物 | C101: Chi phí khấu hao TSCĐ | D101: 減価償却費 | E101: Chi phí khấu hao | H101: 6006016525
A102: 6006016526 | B102: 減価償却費（販） その他有形固定資産 | C102: Chi phí khấu hao TSCĐ | D102: 減価償却費 | E102: Chi phí khấu hao | H102: 6006016526
A103: 6006016527 | B103: 減価償却費（販） リース建物 | C103: Chi phí khấu hao TSCĐ | D103: 減価償却費 | E103: Chi phí khấu hao | H103: 6006016527
A104: 6006016528 | B104: 減価償却費（販） リース機械装置 | C104: Chi phí khấu hao TSCĐ | D104: 減価償却費 | E104: Chi phí khấu hao | H104: 6006016528
A105: 6006016529 | B105: 減価償却費（販） リース車輌運搬具 | C105: Chi phí khấu hao TSCĐ | D105: 減価償却費 | E105: Chi phí khấu hao | H105: 6006016529
A106: 6006016530 | B106: 減価償却費（販） リース工具器具備品 | C106: Chi phí khấu hao TSCĐ | D106: 減価償却費 | E106: Chi phí khấu hao | H106: 6006016530
A107: 6006016531 | B107: 減価償却費（販） リース構築物 | C107: Chi phí khấu hao TSCĐ | D107: 減価償却費 | E107: Chi phí khấu hao | H107: 6006016531
A108: 6006016532 | B108: 減価償却費（販） 土地使用権 | C108: Chi phí khấu hao TSCĐ | D108: 減価償却費 | E108: Chi phí khấu hao | H108: 6006016532
... A122: 6003036542 | B122: クーリエ費用（販売） | C122: Chi phí dịch vụ mua ngòai | D122: 荷造運賃 | E122: Chi phí vận chuyển hàng hóa | H122: 6003036542
A123: 6003036543 | B123: 輸出航空運賃（販売） | C123: Chi phí dịch vụ mua ngòai | D123: 荷造運賃 | E123: Chi phí vận chuyển hàng hóa | F123: 6003036543 | H123: 6003036543
A124: 6003036544 | B124: 輸出海上運賃（販売） | C124: Chi phí dịch vụ mua ngòai | D124: 荷造運賃 | E124: Chi phí vận chuyển hàng hóa | F124: 6003036544 | G124: 6003036544 | H124: 6003036544
A125: 6003036545 | B125: 保管延長費（販売） | C125: Chi phí dịch vụ mua ngòai | D125: 荷造運賃 | E125: Chi phí vận chuyển hàng hóa | H125: 6003036545
A126: 6003036546 | B126: 物流保険料（販売） | C126: Chi phí dịch vụ mua ngòai | D126: 荷造運賃 | E126: Chi phí vận chuyển hàng hóa | H126: 6003036546
A127: 6003036547 | B127: 梱包費用（販売） | C127: Chi phí dịch vụ mua ngòai | D127: 荷造運賃 | E127: Chi phí vận chuyển hàng hóa | H127: 6003036547
A128: 6003036548 | B128: 返品手数料（販売） | C128: Chi phí dịch vụ mua ngòai | D128: 荷造運賃 | E128: Chi phí vận chuyển hàng hóa | H128: 6003036548
A129: 6003036549 | B129: 保管料（販売） | C129: Chi phí dịch vụ mua ngòai | D129: 荷造運賃 | E129: Chi phí vận chuyển hàng hóa | H129: 6003036549
A130: 6003036550 | B130: オーバーナイト費（販売） | C130: Chi phí dịch vụ mua ngòai | D130: 荷造運賃 | E130: Chi phí vận chuyển hàng hóa | H130: 6003036550
A131: 6003036551 | B131: バンニング費（販売） | C131: Chi phí dịch vụ mua ngòai | D131: 荷造運賃 | E131: Chi phí vận chuyển hàng hóa | H131: 6003036551
A132: 6003036552 | B132: その他物流費（販売） | C132: Chi phí dịch vụ mua ngòai | D132: 荷造運賃 | E132: Chi phí vận chuyển hàng hóa | F132: 6003036552 | H132: 6003036552
A133: 6003036554 | B133: 外部倉庫 取扱手数料（販売） | C133: Chi phí dịch vụ mua ngòai | D133: 荷造運賃 | E133: Chi phí vận chuyển hàng hóa | F133: 6003036554 | G133: 6003036554 | H133: 6003036554 | I133: 2017年1月追加。
A134: 6003036555 | B134: 外部倉庫 保管料（販売） | C134: Chi phí dịch vụ mua ngòai | D134: 荷造運賃 | E134: Chi phí vận chuyển hàng hóa | F134: 6003036555 | G134: 6003036555 | H134: 6003036555 | I134: 2017年1月追加。
A135: 6003036556 | B135: 外部倉庫 輸送料（販売） | C135: Chi phí dịch vụ mua ngòai | D135: 荷造運賃 | E135: Chi phí vận chuyển hàng hóa | F135: 6003036556 | G135: 6003036556 | H135: 6003036556 | I135: 2017年1月追加。
...

Sheet 原価センタ
B1: 原価センタ | D1: 採算区分 | E1: 原価区分
A2: 1412000004 | B2: 機器製造1課 | C2: 01. | D2: 製造 | E2: 製造 | G2: V02XD800
A3: 1412000005 | B3: 機器製造2課 | C3: 02. | D3: 製造 | E3: 製造
A4: 1412000062 | B4: 機器製造管理課 | C4: 03. | D4: 部内間接 | E4: 製造
A5: 1412000034 | B5: トナー製造課 | C5: 04. | D5: 製造 | E5: 製造
A6: 1412000048 | B6: トナー生産技術課 | C6: 05. | D6: 部内間接 | E6: 製造
A7: 1412000055 | B7: トナー品質管理課 | C7: 06. | D7: 部内間接 | E7: 製造
A8: 1412000050 | B8: MD1課 | C8: 07. | D8: 製造 | E8: 製造
A9: 1412000077 | B9: MD2課 | C9: 08. | D9: 製造 | E9: 製造
A10: 1412000053 | B10: 工程品質管理1課 | C10: 09. | D10: 部内間接 | E10: 製造
A11: 1412000008 | B11: 生産管理課 | C11: 10. | D11: 部内間接 | E11: 製造
A12: 1412000010 | B12: 採算管理課 | C12: 11. | D12: 部外間接1 | E12: 製造
A13: 1412000054 | B13: マスター管理課 | C13: 12. | D13: 部外間接1 | E13: 製造
A14: 1412000036 | B14: 部品管理課 | C14: 13. | D14: 部内間接 | E14: 製造
... A58: 1412000099 | B58: MD4課 | C58: 65. | D58: 製造 | E58: 製造

Sheet 稼働日
A2: FY2026 | B2: 稼働日
A3: 4 | B3: 20
A4: 5 | B4: 19
A5: 6 | B5: 21
A6: 7 | B6: 23
A7: 8 | B7: 20
A8: 9 | B8: 19
A9: 10 | B9: 23
A10: 11 | B10: 20
A11: 12 | B11: 22
A12: 1 | B12: 20
A13: 2 | B13: 15
A14: 3 | B14: 20
