Workbook
Name WBS: 原価センタ!$G$2:$G$3

Sheet 採算表(USD)
B1: 組織名 | C1: ='採算表(VND)'!C1 -> MP FY2026_各予定 | N1: ='内訳ﾘｽﾄ(4～3月)'!B2 -> 25390
B2: ='採算表(VND)'!B2 -> 工程品質管理1課
B4: 項目 ＼ 部門 | C4: ='採算表(VND)'!C4 -> 4 | D4: ='採算表(VND)'!D4 -> 5 | E4: ='採算表(VND)'!E4 -> 6 | F4: ='採算表(VND)'!F4 -> 7 | G4: ='採算表(VND)'!G4 -> 8 | H4: ='採算表(VND)'!H4 -> 9 | I4: ='採算表(VND)'!I4 -> 10 | J4: ='採算表(VND)'!J4 -> 11 | ... O4: ='採算表(VND)'!O4 -> 合計
B5: 総出荷 | C5: =C8+C9 -> 0 | D5: =D8+D9 -> 0 | E5: =E8+E9 -> 0 | F5: =F8+F9 -> 0 | G5: =G8+G9 -> 0 | H5: =H8+H9 -> 0 | I5: =I8+I9 -> 0 | J5: =J8+J9 -> 0 | ... O5: =O8+O9 -> 0
B6: 社外出荷 | C6: =ROUNDDOWN('採算表(VND)'!C6/$N$1,2) -> 0 | D6: =ROUNDDOWN('採算表(VND)'!D6/$N$1,2) -> 0 | E6: =ROUNDDOWN('採算表(VND)'!E6/$N$1,2) -> 0 | F6: =ROUNDDOWN('採算表(VND)'!F6/$N$1,2) -> 0 | G6: =ROUNDDOWN('採算表(VND)'!G6/$N$1,2) -> 0 | H6: =ROUNDDOWN('採算表(VND)'!H6/$N$1,2) -> 0 | I6: =ROUNDDOWN('採算表(VND)'!I6/$N$1,2) -> 0 | J6: =ROUNDDOWN('採算表(VND)'!J6/$N$1,2) -> 0 | ... N6: =ROUNDDOWN('採算表(VND)'!N6/$N$1,2) -> 0 | O6: =SUM(C6:N6) -> 0
B7: 販売支援 | C7: =ROUNDDOWN('採算表(VND)'!C7/$N$1,2) -> 0 | D7: =ROUNDDOWN('採算表(VND)'!D7/$N$1,2) -> 0 | E7: =ROUNDDOWN('採算表(VND)'!E7/$N$1,2) -> 0 | F7: =ROUNDDOWN('採算表(VND)'!F7/$N$1,2) -> 0 | G7: =ROUNDDOWN('採算表(VND)'!G7/$N$1,2) -> 0 | H7: =ROUNDDOWN('採算表(VND)'!H7/$N$1,2) -> 0 | I7: =ROUNDDOWN('採算表(VND)'!I7/$N$1,2) -> 0 | J7: =ROUNDDOWN('採算表(VND)'!J7/$N$1,2) -> 0 | ... N7: =ROUNDDOWN('採算表(VND)'!N7/$N$1,2) -> 0 | O7: =SUM(C7:N7) -> 0
B8: 社外出荷合計 | C8: =C6+C7 -> 0 | D8: =D6+D7 -> 0 | E8: =E6+E7 -> 0 | F8: =F6+F7 -> 0 | G8: =G6+G7 -> 0 | H8: =H6+H7 -> 0 | I8: =I6+I7 -> 0 | J8: =J6+J7 -> 0 | ... O8: =O6+O7 -> 0
B9: 社内売 | C9: =ROUNDDOWN('採算表(VND)'!C9/$N$1,2) -> 0 | D9: =ROUNDDOWN('採算表(VND)'!D9/$N$1,2) -> 0 | E9: =ROUNDDOWN('採算表(VND)'!E9/$N$1,2) -> 0 | F9: =ROUNDDOWN('採算表(VND)'!F9/$N$1,2) -> 0 | G9: =ROUNDDOWN('採算表(VND)'!G9/$N$1,2) -> 0 | H9: =ROUNDDOWN('採算表(VND)'!H9/$N$1,2) -> 0 | I9: =ROUNDDOWN('採算表(VND)'!I9/$N$1,2) -> 0 | J9: =ROUNDDOWN('採算表(VND)'!J9/$N$1,2) -> 0 | ... N9: =ROUNDDOWN('採算表(VND)'!N9/$N$1,2) -> 0 | O9: =SUM(C9:N9) -> 0
B10: 社内買 | C10: =ROUNDDOWN('採算表(VND)'!C10/$N$1,2) -> 0 | D10: =ROUNDDOWN('採算表(VND)'!D10/$N$1,2) -> 0 | E10: =ROUNDDOWN('採算表(VND)'!E10/$N$1,2) -> 0 | F10: =ROUNDDOWN('採算表(VND)'!F10/$N$1,2) -> 0 | G10: =ROUNDDOWN('採算表(VND)'!G10/$N$1,2) -> 0 | H10: =ROUNDDOWN('採算表(VND)'!H10/$N$1,2) -> 0 | I10: =ROUNDDOWN('採算表(VND)'!I10/$N$1,2) -> 0 | J10: =ROUNDDOWN('採算表(VND)'!J10/$N$1,2) -> 0 | ... N10: =ROUNDDOWN('採算表(VND)'!N10/$N$1,2) -> 0 | O10: =SUM(C10:N10) -> 0
B12: 総生産 | C12: =C5-C10 -> 0 | D12: =D5-D10 -> 0 | E12: =E5-E10 -> 0 | F12: =F5-F10 -> 0 | G12: =G5-G10 -> 0 | H12: =H5-H10 -> 0 | I12: =I5-I10 -> 0 | J12: =J5-J10 -> 0 | ... O12: =O5-O10 -> 0
B13: 控除額 | C13: =SUM(C14:C65) -> 0.03 | D13: =SUM(D14:D65) -> 0.07 | E13: =SUM(E14:E65) -> 0.05 | F13: =SUM(F14:F65) -> 0.04 | G13: =SUM(G14:G65) -> 0.03 | H13: =SUM(H14:H65) -> 0.03 | I13: =SUM(I14:I65) -> 0.03 | J13: =SUM(J14:J65) -> 0.03 | ... O13: =SUM(O14:O65) -> 0.41
B14: 材料費 | C14: =ROUNDUP('採算表(VND)'!C14/$N$1,2) -> 0 | D14: =ROUNDUP('採算表(VND)'!D14/$N$1,2) -> 0 | E14: =ROUNDUP('採算表(VND)'!E14/$N$1,2) -> 0 | F14: =ROUNDUP('採算表(VND)'!F14/$N$1,2) -> 0 | G14: =ROUNDUP('採算表(VND)'!G14/$N$1,2) -> 0 | H14: =ROUNDUP('採算表(VND)'!H14/$N$1,2) -> 0 | I14: =ROUNDUP('採算表(VND)'!I14/$N$1,2) -> 0 | J14: =ROUNDUP('採算表(VND)'!J14/$N$1,2) -> 0 | ... N14: =ROUNDUP('採算表(VND)'!N14/$N$1,2) -> 0 | O14: =SUM(C14:N14) -> 0
B15: 設計変更材料費 | C15: =ROUNDUP('採算表(VND)'!C15/$N$1,2) -> 0 | D15: =ROUNDUP('採算表(VND)'!D15/$N$1,2) -> 0 | E15: =ROUNDUP('採算表(VND)'!E15/$N$1,2) -> 0 | F15: =ROUNDUP('採算表(VND)'!F15/$N$1,2) -> 0 | G15: =ROUNDUP('採算表(VND)'!G15/$N$1,2) -> 0 | H15: =ROUNDUP('採算表(VND)'!H15/$N$1,2) -> 0 | I15: =ROUNDUP('採算表(VND)'!I15/$N$1,2) -> 0 | J15: =ROUNDUP('採算表(VND)'!J15/$N$1,2) -> 0 | ... N15: =ROUNDUP('採算表(VND)'!N15/$N$1,2) -> 0 | O15: =SUM(C15:N15) -> 0
B16: 仕掛仕損 | C16: =ROUNDUP('採算表(VND)'!C16/$N$1,2) -> 0 | D16: =ROUNDUP('採算表(VND)'!D16/$N$1,2) -> 0 | E16: =ROUNDUP('採算表(VND)'!E16/$N$1,2) -> 0 | F16: =ROUNDUP('採算表(VND)'!F16/$N$1,2) -> 0 | G16: =ROUNDUP('採算表(VND)'!G16/$N$1,2) -> 0 | H16: =ROUNDUP('採算表(VND)'!H16/$N$1,2) -> 0 | I16: =ROUNDUP('採算表(VND)'!I16/$N$1,2) -> 0 | J16: =ROUNDUP('採算表(VND)'!J16/$N$1,2) -> 0 | ... N16: =ROUNDUP('採算表(VND)'!N16/$N$1,2) -> 0 | O16: =SUM(C16:N16) -> 0
B17: 仕入製商品費 | C17: =ROUNDUP('採算表(VND)'!C17/$N$1,2) -> 0 | D17: =ROUNDUP('採算表(VND)'!D17/$N$1,2) -> 0 | E17: =ROUNDUP('採算表(VND)'!E17/$N$1,2) -> 0 | F17: =ROUNDUP('採算表(VND)'!F17/$N$1,2) -> 0 | G17: =ROUNDUP('採算表(VND)'!G17/$N$1,2) -> 0 | H17: =ROUNDUP('採算表(VND)'!H17/$N$1,2) -> 0 | I17: =ROUNDUP('採算表(VND)'!I17/$N$1,2) -> 0 | J17: =ROUNDUP('採算表(VND)'!J17/$N$1,2) -> 0 | ... N17: =ROUNDUP('採算表(VND)'!N17/$N$1,2) -> 0 | O17: =SUM(C17:N17) -> 0
B18: 内製品有償支給原価 | C18: =ROUNDUP('採算表(VND)'!C18/$N$1,2) -> 0 | D18: =ROUNDUP('採算表(VND)'!D18/$N$1,2) -> 0 | E18: =ROUNDUP('採算表(VND)'!E18/$N$1,2) -> 0 | F18: =ROUNDUP('採算表(VND)'!F18/$N$1,2) -> 0 | G18: =ROUNDUP('採算表(VND)'!G18/$N$1,2) -> 0 | H18: =ROUNDUP('採算表(VND)'!H18/$N$1,2) -> 0 | I18: =ROUNDUP('採算表(VND)'!I18/$N$1,2) -> 0 | J18: =ROUNDUP('採算表(VND)'!J18/$N$1,2) -> 0 | ... N18: =ROUNDUP('採算表(VND)'!N18/$N$1,2) -> 0 | O18: =SUM(C18:N18) -> 0
B19: 外注加工費 | C19: =ROUNDUP('採算表(VND)'!C19/$N$1,2) -> 0 | D19: =ROUNDUP('採算表(VND)'!D19/$N$1,2) -> 0 | E19: =ROUNDUP('採算表(VND)'!E19/$N$1,2) -> 0 | F19: =ROUNDUP('採算表(VND)'!F19/$N$1,2) -> 0 | G19: =ROUNDUP('採算表(VND)'!G19/$N$1,2) -> 0 | H19: =ROUNDUP('採算表(VND)'!H19/$N$1,2) -> 0 | I19: =ROUNDUP('採算表(VND)'!I19/$N$1,2) -> 0 | J19: =ROUNDUP('採算表(VND)'!J19/$N$1,2) -> 0 | ... N19: =ROUNDUP('採算表(VND)'!N19/$N$1,2) -> 0 | O19: =SUM(C19:N19) -> 0
B20: 減価償却費 | C20: =ROUNDUP('採算表(VND)'!C20/$N$1,2) -> 2547.39 | D20: =ROUNDUP('採算表(VND)'!D20/$N$1,2) -> 2539.82 | E20: =ROUNDUP('採算表(VND)'!E20/$N$1,2) -> 2548.96 | F20: =ROUNDUP('採算表(VND)'!F20/$N$1,2) -> 2480.9 | G20: =ROUNDUP('採算表(VND)'!G20/$N$1,2) -> 1225.22 | H20: =ROUNDUP('採算表(VND)'!H20/$N$1,2) -> 1195.8 | I20: =ROUNDUP('採算表(VND)'!I20/$N$1,2) -> 1181.98 | J20: =ROUNDUP('採算表(VND)'!J20/$N$1,2) -> 1179.52 | ... N20: =ROUNDUP('採算表(VND)'!N20/$N$1,2) -> 1200.06 | O20: =SUM(C20:N20) -> 19637.07
B21: 金型償却費 | C21: =ROUNDUP('採算表(VND)'!C21/$N$1,2) -> 0 | D21: =ROUNDUP('採算表(VND)'!D21/$N$1,2) -> 0 | E21: =ROUNDUP('採算表(VND)'!E21/$N$1,2) -> 0 | F21: =ROUNDUP('採算表(VND)'!F21/$N$1,2) -> 0 | G21: =ROUNDUP('採算表(VND)'!G21/$N$1,2) -> 0 | H21: =ROUNDUP('採算表(VND)'!H21/$N$1,2) -> 0 | I21: =ROUNDUP('採算表(VND)'!I21/$N$1,2) -> 0 | J21: =ROUNDUP('採算表(VND)'!J21/$N$1,2) -> 0 | ... N21: =ROUNDUP('採算表(VND)'!N21/$N$1,2) -> 0 | O21: =SUM(C21:N21) -> 0
B22: 賃借料 | C22: =ROUNDUP('採算表(VND)'!C22/$N$1,2) -> 0 | D22: =ROUNDUP('採算表(VND)'!D22/$N$1,2) -> 0 | E22: =ROUNDUP('採算表(VND)'!E22/$N$1,2) -> 0 | F22: =ROUNDUP('採算表(VND)'!F22/$N$1,2) -> 0 | G22: =ROUNDUP('採算表(VND)'!G22/$N$1,2) -> 0 | H22: =ROUNDUP('採算表(VND)'!H22/$N$1,2) -> 0 | I22: =ROUNDUP('採算表(VND)'!I22/$N$1,2) -> 0 | J22: =ROUNDUP('採算表(VND)'!J22/$N$1,2) -> 0 | ... N22: =ROUNDUP('採算表(VND)'!N22/$N$1,2) -> 0 | O22: =SUM(C22:N22) -> 0
B23: 保険料 | C23: =ROUNDUP('採算表(VND)'!C23/$N$1,2) -> 0 | D23: =ROUNDUP('採算表(VND)'!D23/$N$1,2) -> 0 | E23: =ROUNDUP('採算表(VND)'!E23/$N$1,2) -> 0 | F23: =ROUNDUP('採算表(VND)'!F23/$N$1,2) -> 0 | G23: =ROUNDUP('採算表(VND)'!G23/$N$1,2) -> 0 | H23: =ROUNDUP('採算表(VND)'!H23/$N$1,2) -> 0 | I23: =ROUNDUP('採算表(VND)'!I23/$N$1,2) -> 0 | J23: =ROUNDUP('採算表(VND)'!J23/$N$1,2) -> 0 | ... N23: =ROUNDUP('採算表(VND)'!N23/$N$1,2) -> 0 | O23: =SUM(C23:N23) -> 0
B24: 設計委託費 | C24: =ROUNDUP('採算表(VND)'!C24/$N$1,2) -> 0 | D24: =ROUNDUP('採算表(VND)'!D24/$N$1,2) -> 0 | E24: =ROUNDUP('採算表(VND)'!E24/$N$1,2) -> 0 | F24: =ROUNDUP('採算表(VND)'!F24/$N$1,2) -> 0 | G24: =ROUNDUP('採算表(VND)'!G24/$N$1,2) -> 0 | H24: =ROUNDUP('採算表(VND)'!H24/$N$1,2) -> 0 | I24: =ROUNDUP('採算表(VND)'!I24/$N$1,2) -> 0 | J24: =ROUNDUP('採算表(VND)'!J24/$N$1,2) -> 0 | ... N24: =ROUNDUP('採算表(VND)'!N24/$N$1,2) -> 0 | O24: =SUM(C24:N24) -> 0
B25: 消耗品費 | C25: =ROUNDUP('採算表(VND)'!C25/$N$1,2) -> 531.34 | D25: =ROUNDUP('採算表(VND)'!D25/$N$1,2) -> 507.7 | E25: =ROUNDUP('採算表(VND)'!E25/$N$1,2) -> 562.17 | F25: =ROUNDUP('採算表(VND)'!F25/$N$1,2) -> 616.65 | G25: =ROUNDUP('採算表(VND)'!G25/$N$1,2) -> 39.69 | H25: =ROUNDUP('採算表(VND)'!H25/$N$1,2) -> 38.71 | I25: =ROUNDUP('採算表(VND)'!I25/$N$1,2) -> 50.84 | J25: =ROUNDUP('採算表(VND)'!J25/$N$1,2) -> 42.82 | ... N25: =ROUNDUP('採算表(VND)'!N25/$N$1,2) -> 52.02 | O25: =SUM(C25:N25) -> 2571.66
... B65: 本社機構経費 | C65: =ROUNDUP('採算表(VND)'!C65/$N$1,2) -> 0 | D65: =ROUNDUP('採算表(VND)'!D65/$N$1,2) -> 0 | E65: =ROUNDUP('採算表(VND)'!E65/$N$1,2) -> 0 | F65: =ROUNDUP('採算表(VND)'!F65/$N$1,2) -> 0 | G65: =ROUNDUP('採算表(VND)'!G65/$N$1,2) -> 0 | H65: =ROUNDUP('採算表(VND)'!H65/$N$1,2) -> 0 | I65: =ROUNDUP('採算表(VND)'!I65/$N$1,2) -> 0 | J65: =ROUNDUP('採算表(VND)'!J65/$N$1,2) -> 0 | ... N65: =ROUNDUP('採算表(VND)'!N65/$N$1,2) -> 0 | O65: =SUM(C65:N65) -> 0
B66: 差引収益 | C66: =C12-C13 -> -0.03 | D66: =IF(ISBLANK(D4),"",D12-D13) -> -0.07 | E66: =IF(ISBLANK(E4),"",E12-E13) -> -0.05 | F66: =IF(ISBLANK(F4),"",F12-F13) -> -0.04 | G66: =IF(ISBLANK(G4),"",G12-G13) -> -0.03 | H66: =IF(ISBLANK(H4),"",H12-H13) -> -0.03 | I66: =IF(ISBLANK(I4),"",I12-I13) -> -0.03 | J66: =IF(ISBLANK(J4),"",J12-J13) -> -0.03 | K66: =IF(ISBLANK(K4),"",K12-K13) -> -0.03 | ... O66: =IF(ISBLANK(O4),"",O12-O13) -> -0.41
B67: 総時間 | C67: =C73+C79 -> 0 | D67: =IF(ISBLANK(D4),"",D73+D79) -> 0 | E67: =IF(ISBLANK(E4),"",E73+E79) -> 0 | F67: =IF(ISBLANK(F4),"",F73+F79) -> 0 | G67: =IF(ISBLANK(G4),"",G73+G79) -> 0 | H67: =IF(ISBLANK(H4),"",H73+H79) -> 0 | I67: =IF(ISBLANK(I4),"",I73+I79) -> 0 | J67: =IF(ISBLANK(J4),"",J73+J79) -> 0 | K67: =IF(ISBLANK(K4),"",K73+K79) -> 0 | ... O67: =IF(ISBLANK(O4),"",O73+O79) -> 0
B68: 直接部門 | C68: ='採算表(VND)'!C68 -> 31644 | D68: ='採算表(VND)'!D68 -> 30078 | E68: ='採算表(VND)'!E68 -> 33244 | F68: ='採算表(VND)'!F68 -> 5169 | G68: ='採算表(VND)'!G68 -> 4452.5 | H68: ='採算表(VND)'!H68 -> 4253 | I68: ='採算表(VND)'!I68 -> 5904 | J68: ='採算表(VND)'!J68 -> 5134 | ... N68: ='採算表(VND)'!N68 -> 5773 | O68: =SUM(C68:N68) -> 140871.5
B69: 部内間接部門 | C69: ='採算表(VND)'!C69 -> -31644 | D69: ='採算表(VND)'!D69 -> -30078 | E69: ='採算表(VND)'!E69 -> -33244 | F69: ='採算表(VND)'!F69 -> -5169 | G69: ='採算表(VND)'!G69 -> -4452.5 | H69: ='採算表(VND)'!H69 -> -4253 | I69: ='採算表(VND)'!I69 -> -5904 | J69: ='採算表(VND)'!J69 -> -5134 | ... N69: ='採算表(VND)'!N69 -> -5773 | O69: =SUM(C69:N69) -> -140871.5
B70: 部外間接部門1 | C70: ='採算表(VND)'!C70 -> 0 | D70: ='採算表(VND)'!D70 -> 0 | E70: ='採算表(VND)'!E70 -> 0 | F70: ='採算表(VND)'!F70 -> 0 | G70: ='採算表(VND)'!G70 -> 0 | H70: ='採算表(VND)'!H70 -> 0 | I70: ='採算表(VND)'!I70 -> 0 | J70: ='採算表(VND)'!J70 -> 0 | ... N70: ='採算表(VND)'!N70 -> 0 | O70: =SUM(C70:N70) -> 0
B71: 部外間接部門2 | C71: ='採算表(VND)'!C71 -> 0 | D71: ='採算表(VND)'!D71 -> 0 | E71: ='採算表(VND)'!E71 -> 0 | F71: ='採算表(VND)'!F71 -> 0 | G71: ='採算表(VND)'!G71 -> 0 | H71: ='採算表(VND)'!H71 -> 0 | I71: ='採算表(VND)'!I71 -> 0 | J71: ='採算表(VND)'!J71 -> 0 | ... N71: ='採算表(VND)'!N71 -> 0 | O71: =SUM(C71:N71) -> 0
B72: 工場間接部門 | C72: ='採算表(VND)'!C72 -> 0 | D72: ='採算表(VND)'!D72 -> 0 | E72: ='採算表(VND)'!E72 -> 0 | F72: ='採算表(VND)'!F72 -> 0 | G72: ='採算表(VND)'!G72 -> 0 | H72: ='採算表(VND)'!H72 -> 0 | I72: ='採算表(VND)'!I72 -> 0 | J72: ='採算表(VND)'!J72 -> 0 | ... N72: ='採算表(VND)'!N72 -> 0 | O72: =SUM(C72:N72) -> 0
B73: 定時間合計 | C73: =SUM(C68:C72) -> 0 | D73: =IF(ISBLANK(D4),"",SUM(D68:D72)) -> 0 | E73: =IF(ISBLANK(E4),"",SUM(E68:E72)) -> 0 | F73: =IF(ISBLANK(F4),"",SUM(F68:F72)) -> 0 | G73: =IF(ISBLANK(G4),"",SUM(G68:G72)) -> 0 | H73: =IF(ISBLANK(H4),"",SUM(H68:H72)) -> 0 | I73: =IF(ISBLANK(I4),"",SUM(I68:I72)) -> 0 | J73: =IF(ISBLANK(J4),"",SUM(J68:J72)) -> 0 | K73: =IF(ISBLANK(K4),"",SUM(K68:K72)) -> 0 | ... O73: =IF(ISBLANK(O4),"",SUM(O68:O72)) -> 0
B74: 直接部門 | C74: ='採算表(VND)'!C74 -> 5021 | D74: ='採算表(VND)'!D74 -> 5015 | E74: ='採算表(VND)'!E74 -> 5035 | F74: ='採算表(VND)'!F74 -> 763 | G74: ='採算表(VND)'!G74 -> 735 | H74: ='採算表(VND)'!H74 -> 735 | I74: ='採算表(VND)'!I74 -> 863 | J74: ='採算表(VND)'!J74 -> 845 | ... N74: ='採算表(VND)'!N74 -> 945 | O74: =SUM(C74:N74) -> 22587
B75: 部内間接部門 | C75: ='採算表(VND)'!C75 -> -5021 | D75: ='採算表(VND)'!D75 -> -5015 | E75: ='採算表(VND)'!E75 -> -5035 | F75: ='採算表(VND)'!F75 -> -763 | G75: ='採算表(VND)'!G75 -> -735 | H75: ='採算表(VND)'!H75 -> -735 | I75: ='採算表(VND)'!I75 -> -863 | J75: ='採算表(VND)'!J75 -> -845 | ... N75: ='採算表(VND)'!N75 -> -945 | O75: =SUM(C75:N75) -> -22587
B76: 部外間接部門1 | C76: ='採算表(VND)'!C76 -> 0 | D76: ='採算表(VND)'!D76 -> 0 | E76: ='採算表(VND)'!E76 -> 0 | F76: ='採算表(VND)'!F76 -> 0 | G76: ='採算表(VND)'!G76 -> 0 | H76: ='採算表(VND)'!H76 -> 0 | I76: ='採算表(VND)'!I76 -> 0 | J76: ='採算表(VND)'!J76 -> 0 | ... N76: ='採算表(VND)'!N76 -> 0 | O76: =SUM(C76:N76) -> 0
B77: 部外間接部門2 | C77: ='採算表(VND)'!C77 -> 0 | D77: ='採算表(VND)'!D77 -> 0 | E77: ='採算表(VND)'!E77 -> 0 | F77: ='採算表(VND)'!F77 -> 0 | G77: ='採算表(VND)'!G77 -> 0 | H77: ='採算表(VND)'!H77 -> 0 | I77: ='採算表(VND)'!I77 -> 0 | J77: ='採算表(VND)'!J77 -> 0 | ... N77: ='採算表(VND)'!N77 -> 0 | O77: =SUM(C77:N77) -> 0
B78: 工場間接部門 | C78: ='採算表(VND)'!C78 -> 0 | D78: ='採算表(VND)'!D78 -> 0 | E78: ='採算表(VND)'!E78 -> 0 | F78: ='採算表(VND)'!F78 -> 0 | G78: ='採算表(VND)'!G78 -> 0 | H78: ='採算表(VND)'!H78 -> 0 | I78: ='採算表(VND)'!I78 -> 0 | J78: ='採算表(VND)'!J78 -> 0 | ... N78: ='採算表(VND)'!N78 -> 0 | O78: =SUM(C78:N78) -> 0
B79: 残業時間合計 | C79: =SUM(C74:C78) -> 0 | D79: =IF(ISBLANK(D4),"",SUM(D74:D78)) -> 0 | E79: =IF(ISBLANK(E4),"",SUM(E74:E78)) -> 0 | F79: =IF(ISBLANK(F4),"",SUM(F74:F78)) -> 0 | G79: =IF(ISBLANK(G4),"",SUM(G74:G78)) -> 0 | H79: =IF(ISBLANK(H4),"",SUM(H74:H78)) -> 0 | I79: =IF(ISBLANK(I4),"",SUM(I74:I78)) -> 0 | J79: =IF(ISBLANK(J4),"",SUM(J74:J78)) -> 0 | K79: =IF(ISBLANK(K4),"",SUM(K74:K78)) -> 0 | ... O79: =IF(ISBLANK(O4),"",SUM(O74:O78)) -> 0
B80: 当月時間当り | C80: =IFERROR(ROUNDDOWN(C66/C67,0),0) -> 0 | D80: =IFERROR(ROUNDDOWN(D66/D67,0),0) -> 0 | E80: =IFERROR(ROUNDDOWN(E66/E67,0),0) -> 0 | F80: =IFERROR(ROUNDDOWN(F66/F67,0),0) -> 0 | G80: =IFERROR(ROUNDDOWN(G66/G67,0),0) -> 0 | H80: =IFERROR(ROUNDDOWN(H66/H67,0),0) -> 0 | I80: =IFERROR(ROUNDDOWN(I66/I67,0),0) -> 0 | J80: =IFERROR(ROUNDDOWN(J66/J67,0),0) -> 0 | ... O80: =IFERROR(ROUNDDOWN(O66/O67,0),0) -> 0
B81: 時間当り生産高 | C81: =IFERROR(ROUNDDOWN(C12/C67,0),0) -> 0 | D81: =IFERROR(ROUNDDOWN(D12/D67,0),0) -> 0 | E81: =IFERROR(ROUNDDOWN(E12/E67,0),0) -> 0 | F81: =IFERROR(ROUNDDOWN(F12/F67,0),0) -> 0 | G81: =IFERROR(ROUNDDOWN(G12/G67,0),0) -> 0 | H81: =IFERROR(ROUNDDOWN(H12/H67,0),0) -> 0 | I81: =IFERROR(ROUNDDOWN(I12/I67,0),0) -> 0 | J81: =IFERROR(ROUNDDOWN(J12/J67,0),0) -> 0 | ... O81: =IFERROR(ROUNDDOWN(O12/O67,0),0) -> 0
B86: ■人員
B87: 出向社員(人) | C87: ='採算表(VND)'!C87 -> 2 | D87: ='採算表(VND)'!D87 -> 2 | E87: ='採算表(VND)'!E87 -> 2 | F87: ='採算表(VND)'!F87 -> 2 | G87: ='採算表(VND)'!G87 -> 2 | H87: ='採算表(VND)'!H87 -> 2 | I87: ='採算表(VND)'!I87 -> 2 | J87: ='採算表(VND)'!J87 -> 2 | ... N87: ='採算表(VND)'!N87 -> 2 | O87: =SUM(C87:N87) -> 24
B88: ローカル社員(人) | C88: ='採算表(VND)'!C88 -> 196 | D88: ='採算表(VND)'!D88 -> 196 | E88: ='採算表(VND)'!E88 -> 196 | F88: ='採算表(VND)'!F88 -> 26 | G88: ='採算表(VND)'!G88 -> 26 | H88: ='採算表(VND)'!H88 -> 26 | I88: ='採算表(VND)'!I88 -> 30 | J88: ='採算表(VND)'!J88 -> 30 | ... N88: ='採算表(VND)'!N88 -> 34 | O88: =SUM(C88:N88) -> 855
B89: 人員計 | C89: =C87+C88 -> 198 | D89: =D87+D88 -> 198 | E89: =E87+E88 -> 198 | F89: =F87+F88 -> 28 | G89: =G87+G88 -> 28 | H89: =H87+H88 -> 28 | I89: =I87+I88 -> 32 | J89: =J87+J88 -> 32 | ... O89: =O87+O88 -> 879
B91: ■定時間
B92: 出向社員定時 | C92: ='採算表(VND)'!C92 -> 323 | D92: ='採算表(VND)'!D92 -> 323 | E92: ='採算表(VND)'!E92 -> 357 | F92: ='採算表(VND)'!F92 -> 391 | G92: ='採算表(VND)'!G92 -> 297.5 | H92: ='採算表(VND)'!H92 -> 306 | I92: ='採算表(VND)'!I92 -> 391 | J92: ='採算表(VND)'!J92 -> 340 | ... N92: ='採算表(VND)'!N92 -> 340 | O92: =SUM(C92:N92) -> 3986.5
B93: ローカル社員定時 | C93: ='採算表(VND)'!C93 -> 31321 | D93: ='採算表(VND)'!D93 -> 29755 | E93: ='採算表(VND)'!E93 -> 32887 | F93: ='採算表(VND)'!F93 -> 4778 | G93: ='採算表(VND)'!G93 -> 4155 | H93: ='採算表(VND)'!H93 -> 3947 | I93: ='採算表(VND)'!I93 -> 5513 | J93: ='採算表(VND)'!J93 -> 4794 | ... N93: ='採算表(VND)'!N93 -> 5433 | O93: =SUM(C93:N93) -> 136885
B94: 人員計 | C94: =C92+C93 -> 31644 | D94: =D92+D93 -> 30078 | E94: =E92+E93 -> 33244 | F94: =F92+F93 -> 5169 | G94: =G92+G93 -> 4452.5 | H94: =H92+H93 -> 4253 | I94: =I92+I93 -> 5904 | J94: =J92+J93 -> 5134 | ... O94: =O92+O93 -> 140871.5
B96: ■残業時間
B97: 出向社員残業 | C97: ='採算表(VND)'!C97 -> 76 | D97: ='採算表(VND)'!D97 -> 76 | E97: ='採算表(VND)'!E97 -> 84 | F97: ='採算表(VND)'!F97 -> 92 | G97: ='採算表(VND)'!G97 -> 70 | H97: ='採算表(VND)'!H97 -> 72 | I97: ='採算表(VND)'!I97 -> 92 | J97: ='採算表(VND)'!J97 -> 80 | ... N97: ='採算表(VND)'!N97 -> 80 | O97: =SUM(C97:N97) -> 938
B98: ローカル社員残業 | C98: ='採算表(VND)'!C98 -> 4945 | D98: ='採算表(VND)'!D98 -> 4939 | E98: ='採算表(VND)'!E98 -> 4951 | F98: ='採算表(VND)'!F98 -> 671 | G98: ='採算表(VND)'!G98 -> 665 | H98: ='採算表(VND)'!H98 -> 663 | I98: ='採算表(VND)'!I98 -> 771 | J98: ='採算表(VND)'!J98 -> 765 | ... N98: ='採算表(VND)'!N98 -> 865 | O98: =SUM(C98:N98) -> 21649
B99: 人員計 | C99: =C97+C98 -> 5021 | D99: =D97+D98 -> 5015 | E99: =E97+E98 -> 5035 | F99: =F97+F98 -> 763 | G99: =G97+G98 -> 735 | H99: =H97+H98 -> 735 | I99: =I97+I98 -> 863 | J99: =J97+J98 -> 845 | ... O99: =O97+O98 -> 22587

Sheet 採算表(VND)
B1: 組織名 | C1: ='内訳ﾘｽﾄ(4～3月)'!A1 -> MP FY2026_各予定
B2: ='内訳ﾘｽﾄ(4～3月)'!C5 -> 工程品質管理1課
C3: 2 | D3: 3 | E3: 4 | F3: 5 | G3: 6 | H3: 7 | I3: 8 | J3: 9 | K3: 10 | L3: 11 | M3: 12 | N3: 13
B4: 項目 ＼ 部門 | C4: ='内訳ﾘｽﾄ(4～3月)'!F4 -> 4 | D4: 5 | E4: 6 | F4: 7 | G4: 8 | H4: 9 | I4: 10 | J4: 11 | K4: 12 | L4: 1 | M4: 2 | N4: 3 | O4: 合計
B5: 総出荷 | C5: =C8+C9 -> 0 | D5: =D8+D9 -> 0 | E5: =E8+E9 -> 0 | F5: =F8+F9 -> 0 | G5: =G8+G9 -> 0 | H5: =H8+H9 -> 0 | I5: =I8+I9 -> 0 | J5: =J8+J9 -> 0 | ... O5: =O8+O9 -> 0
B6: 社外出荷 | C6: =SUMIF('内訳ﾘｽﾄ(4～3月)'!$D$26:$D$1004,'採算表(VND)'!$B6,'内訳ﾘｽﾄ(4～3月)'!F$26:F$1004) -> 0 | D6: =SUMIF('内訳ﾘｽﾄ(4～3月)'!$D$26:$D$1004,'採算表(VND)'!$B6,'内訳ﾘｽﾄ(4～3月)'!G$26:G$1004) -> 0 | E6: =SUMIF('内訳ﾘｽﾄ(4～3月)'!$D$26:$D$1004,'採算表(VND)'!$B6,'内訳ﾘｽﾄ(4～3月)'!H$26:H$1004) -> 0 | F6: =SUMIF('内訳ﾘｽﾄ(4～3月)'!$D$26:$D$1004,'採算表(VND)'!$B6,'内訳ﾘｽﾄ(4～3月)'!I$26:I$1004) -> 0 | G6: =SUMIF('内訳ﾘｽﾄ(4～3月)'!$D$26:$D$1004,'採算表(VND)'!$B6,'内訳ﾘｽﾄ(4～3月)'!J$26:J$1004) -> 0 | H6: =SUMIF('内訳ﾘｽﾄ(4～3月)'!$D$26:$D$1004,'採算表(VND)'!$B6,'内訳ﾘｽﾄ(4～3月)'!K$26:K$1004) -> 0 | I6: =SUMIF('内訳ﾘｽﾄ(4～3月)'!$D$26:$D$1004,'採算表(VND)'!$B6,'内訳ﾘｽﾄ(4～3月)'!L$26:L$1004) -> 0 | J6: =SUMIF('内訳ﾘｽﾄ(4～3月)'!$D$26:$D$1004,'採算表(VND)'!$B6,'内訳ﾘｽﾄ(4～3月)'!M$26:M$1004) -> 0 | ... N6: =SUMIF('内訳ﾘｽﾄ(4～3月)'!$D$26:$D$1004,'採算表(VND)'!$B6,'内訳ﾘｽﾄ(4～3月)'!Q$26:Q$1004) -> 0 | O6: =SUMIF('内訳ﾘｽﾄ(4～3月)'!$D$26:$D$803,'採算表(VND)'!$B6,'内訳ﾘｽﾄ(4～3月)'!R$26:R$803) -> 0
B7: 販売支援 | C7: =SUMIF('内訳ﾘｽﾄ(4～3月)'!$D$26:$D$1004,'採算表(VND)'!$B7,'内訳ﾘｽﾄ(4～3月)'!F$26:F$1004) -> 0 | D7: =SUMIF('内訳ﾘｽﾄ(4～3月)'!$D$26:$D$1004,'採算表(VND)'!$B7,'内訳ﾘｽﾄ(4～3月)'!G$26:G$1004) -> 0 | E7: =SUMIF('内訳ﾘｽﾄ(4～3月)'!$D$26:$D$1004,'採算表(VND)'!$B7,'内訳ﾘｽﾄ(4～3月)'!H$26:H$1004) -> 0 | F7: =SUMIF('内訳ﾘｽﾄ(4～3月)'!$D$26:$D$1004,'採算表(VND)'!$B7,'内訳ﾘｽﾄ(4～3月)'!I$26:I$1004) -> 0 | G7: =SUMIF('内訳ﾘｽﾄ(4～3月)'!$D$26:$D$1004,'採算表(VND)'!$B7,'内訳ﾘｽﾄ(4～3月)'!J$26:J$1004) -> 0 | H7: =SUMIF('内訳ﾘｽﾄ(4～3月)'!$D$26:$D$1004,'採算表(VND)'!$B7,'内訳ﾘｽﾄ(4～3月)'!K$26:K$1004) -> 0 | I7: =SUMIF('内訳ﾘｽﾄ(4～3月)'!$D$26:$D$1004,'採算表(VND)'!$B7,'内訳ﾘｽﾄ(4～3月)'!L$26:L$1004) -> 0 | J7: =SUMIF('内訳ﾘｽﾄ(4～3月)'!$D$26:$D$1004,'採算表(VND)'!$B7,'内訳ﾘｽﾄ(4～3月)'!M$26:M$1004) -> 0 | ... N7: =SUMIF('内訳ﾘｽﾄ(4～3月)'!$D$26:$D$1004,'採算表(VND)'!$B7,'内訳ﾘｽﾄ(4～3月)'!Q$26:Q$1004) -> 0 | O7: =SUMIF('内訳ﾘｽﾄ(4～3月)'!$D$26:$D$803,'採算表(VND)'!$B7,'内訳ﾘｽﾄ(4～3月)'!R$26:R$803) -> 0
B8: 社外出荷合計 | C8: =C6+C7 -> 0 | D8: =D6+D7 -> 0 | E8: =E6+E7 -> 0 | F8: =F6+F7 -> 0 | G8: =G6+G7 -> 0 | H8: =H6+H7 -> 0 | I8: =I6+I7 -> 0 | J8: =J6+J7 -> 0 | ... O8: =O6+O7 -> 0
B9: 社内売 | C9: =SUMIF('内訳ﾘｽﾄ(4～3月)'!$D$26:$D$1004,'採算表(VND)'!$B9,'内訳ﾘｽﾄ(4～3月)'!F$26:F$1004) -> 0 | D9: =SUMIF('内訳ﾘｽﾄ(4～3月)'!$D$26:$D$1004,'採算表(VND)'!$B9,'内訳ﾘｽﾄ(4～3月)'!G$26:G$1004) -> 0 | E9: =SUMIF('内訳ﾘｽﾄ(4～3月)'!$D$26:$D$1004,'採算表(VND)'!$B9,'内訳ﾘｽﾄ(4～3月)'!H$26:H$1004) -> 0 | F9: =SUMIF('内訳ﾘｽﾄ(4～3月)'!$D$26:$D$1004,'採算表(VND)'!$B9,'内訳ﾘｽﾄ(4～3月)'!I$26:I$1004) -> 0 | G9: =SUMIF('内訳ﾘｽﾄ(4～3月)'!$D$26:$D$1004,'採算表(VND)'!$B9,'内訳ﾘｽﾄ(4～3月)'!J$26:J$1004) -> 0 | H9: =SUMIF('内訳ﾘｽﾄ(4～3月)'!$D$26:$D$1004,'採算表(VND)'!$B9,'内訳ﾘｽﾄ(4～3月)'!K$26:K$1004) -> 0 | I9: =SUMIF('内訳ﾘｽﾄ(4～3月)'!$D$26:$D$1004,'採算表(VND)'!$B9,'内訳ﾘｽﾄ(4～3月)'!L$26:L$1004) -> 0 | J9: =SUMIF('内訳ﾘｽﾄ(4～3月)'!$D$26:$D$1004,'採算表(VND)'!$B9,'内訳ﾘｽﾄ(4～3月)'!M$26:M$1004) -> 0 | ... N9: =SUMIF('内訳ﾘｽﾄ(4～3月)'!$D$26:$D$1004,'採算表(VND)'!$B9,'内訳ﾘｽﾄ(4～3月)'!Q$26:Q$1004) -> 0 | O9: =SUMIF('内訳ﾘｽﾄ(4～3月)'!$D$26:$D$803,'採算表(VND)'!$B9,'内訳ﾘｽﾄ(4～3月)'!R$26:R$803) -> 0
B10: 社内買 | C10: =SUMIF('内訳ﾘｽﾄ(4～3月)'!$D$26:$D$1004,'採算表(VND)'!$B10,'内訳ﾘｽﾄ(4～3月)'!F$26:F$1004) -> 0 | D10: =SUMIF('内訳ﾘｽﾄ(4～3月)'!$D$26:$D$1004,'採算表(VND)'!$B10,'内訳ﾘｽﾄ(4～3月)'!G$26:G$1004) -> 0 | E10: =SUMIF('内訳ﾘｽﾄ(4～3月)'!$D$26:$D$1004,'採算表(VND)'!$B10,'内訳ﾘｽﾄ(4～3月)'!H$26:H$1004) -> 0 | F10: =SUMIF('内訳ﾘｽﾄ(4～3月)'!$D$26:$D$1004,'採算表(VND)'!$B10,'内訳ﾘｽﾄ(4～3月)'!I$26:I$1004) -> 0 | G10: =SUMIF('内訳ﾘｽﾄ(4～3月)'!$D$26:$D$1004,'採算表(VND)'!$B10,'内訳ﾘｽﾄ(4～3月)'!J$26:J$1004) -> 0 | H10: =SUMIF('内訳ﾘｽﾄ(4～3月)'!$D$26:$D$1004,'採算表(VND)'!$B10,'内訳ﾘｽﾄ(4～3月)'!K$26:K$1004) -> 0 | I10: =SUMIF('内訳ﾘｽﾄ(4～3月)'!$D$26:$D$1004,'採算表(VND)'!$B10,'内訳ﾘｽﾄ(4～3月)'!L$26:L$1004) -> 0 | J10: =SUMIF('内訳ﾘｽﾄ(4～3月)'!$D$26:$D$1004,'採算表(VND)'!$B10,'内訳ﾘｽﾄ(4～3月)'!M$26:M$1004) -> 0 | ... N10: =SUMIF('内訳ﾘｽﾄ(4～3月)'!$D$26:$D$1004,'採算表(VND)'!$B10,'内訳ﾘｽﾄ(4～3月)'!Q$26:Q$1004) -> 0 | O10: =SUMIF('内訳ﾘｽﾄ(4～3月)'!$D$26:$D$803,'採算表(VND)'!$B10,'内訳ﾘｽﾄ(4～3月)'!R$26:R$803) -> 0
B12: 総生産 | C12: =C5-C10 -> 0 | D12: =D5-D10 -> 0 | E12: =E5-E10 -> 0 | F12: =F5-F10 -> 0 | G12: =G5-G10 -> 0 | H12: =H5-H10 -> 0 | I12: =I5-I10 -> 0 | J12: =J5-J10 -> 0 | ... O12: =O5-O10 -> 0
B13: 控除額 | C13: =SUM(C14:C65) -> 0 | D13: =SUM(D14:D65) -> 0 | E13: =SUM(E14:E65) -> 0 | F13: =SUM(F14:F65) -> 0 | G13: =SUM(G14:G65) -> 0 | H13: =SUM(H14:H65) -> 0 | I13: =SUM(I14:I65) -> 0 | J13: =SUM(J14:J65) -> 0 | ... O13: =SUM(O14:O65) -> 0
B14: 材料費 | C14: =SUMIF('内訳ﾘｽﾄ(4～3月)'!$D$26:$D$1004,$B14,'内訳ﾘｽﾄ(4～3月)'!F$26:F$1004) -> 0 | D14: =SUMIF('内訳ﾘｽﾄ(4～3月)'!$D$26:$D$1004,$B14,'内訳ﾘｽﾄ(4～3月)'!G$26:G$1004) -> 0 | E14: =SUMIF('内訳ﾘｽﾄ(4～3月)'!$D$26:$D$1004,$B14,'内訳ﾘｽﾄ(4～3月)'!H$26:H$1004) -> 0 | F14: =SUMIF('内訳ﾘｽﾄ(4～3月)'!$D$26:$D$1004,$B14,'内訳ﾘｽﾄ(4～3月)'!I$26:I$1004) -> 0 | G14: =SUMIF('内訳ﾘｽﾄ(4～3月)'!$D$26:$D$1004,$B14,'内訳ﾘｽﾄ(4～3月)'!J$26:J$1004) -> 0 | H14: =SUMIF('内訳ﾘｽﾄ(4～3月)'!$D$26:$D$1004,$B14,'内訳ﾘｽﾄ(4～3月)'!K$26:K$1004) -> 0 | I14: =SUMIF('内訳ﾘｽﾄ(4～3月)'!$D$26:$D$1004,$B14,'内訳ﾘｽﾄ(4～3月)'!L$26:L$1004) -> 0 | J14: =SUMIF('内訳ﾘｽﾄ(4～3月)'!$D$26:$D$1004,$B14,'内訳ﾘｽﾄ(4～3月)'!M$26:M$1004) -> 0 | ... N14: =SUMIF('内訳ﾘｽﾄ(4～3月)'!$D$26:$D$1004,$B14,'内訳ﾘｽﾄ(4～3月)'!Q$26:Q$1004) -> 0 | O14: =SUMIF('内訳ﾘｽﾄ(4～3月)'!$D$26:$D$803,'採算表(VND)'!$B14,'内訳ﾘｽﾄ(4～3月)'!R$26:R$803) -> 0
B15: 設計変更材料費 | C15: =SUMIF('内訳ﾘｽﾄ(4～3月)'!$D$26:$D$1004,$B15,'内訳ﾘｽﾄ(4～3月)'!F$26:F$1004) -> 0 | D15: =SUMIF('内訳ﾘｽﾄ(4～3月)'!$D$26:$D$1004,$B15,'内訳ﾘｽﾄ(4～3月)'!G$26:G$1004) -> 0 | E15: =SUMIF('内訳ﾘｽﾄ(4～3月)'!$D$26:$D$1004,$B15,'内訳ﾘｽﾄ(4～3月)'!H$26:H$1004) -> 0 | F15: =SUMIF('内訳ﾘｽﾄ(4～3月)'!$D$26:$D$1004,$B15,'内訳ﾘｽﾄ(4～3月)'!I$26:I$1004) -> 0 | G15: =SUMIF('内訳ﾘｽﾄ(4～3月)'!$D$26:$D$1004,$B15,'内訳ﾘｽﾄ(4～3月)'!J$26:J$1004) -> 0 | H15: =SUMIF('内訳ﾘｽﾄ(4～3月)'!$D$26:$D$1004,$B15,'内訳ﾘｽﾄ(4～3月)'!K$26:K$1004) -> 0 | I15: =SUMIF('内訳ﾘｽﾄ(4～3月)'!$D$26:$D$1004,$B15,'内訳ﾘｽﾄ(4～3月)'!L$26:L$1004) -> 0 | J15: =SUMIF('内訳ﾘｽﾄ(4～3月)'!$D$26:$D$1004,$B15,'内訳ﾘｽﾄ(4～3月)'!M$26:M$1004) -> 0 | ... N15: =SUMIF('内訳ﾘｽﾄ(4～3月)'!$D$26:$D$1004,$B15,'内訳ﾘｽﾄ(4～3月)'!Q$26:Q$1004) -> 0 | O15: =SUMIF('内訳ﾘｽﾄ(4～3月)'!$D$26:$D$803,'採算表(VND)'!$B15,'内訳ﾘｽﾄ(4～3月)'!R$26:R$803) -> 0
B16: 仕掛仕損 | C16: =SUMIF('内訳ﾘｽﾄ(4～3月)'!$D$26:$D$1004,$B16,'内訳ﾘｽﾄ(4～3月)'!F$26:F$1004) -> 0 | D16: =SUMIF('内訳ﾘｽﾄ(4～3月)'!$D$26:$D$1004,$B16,'内訳ﾘｽﾄ(4～3月)'!G$26:G$1004) -> 0 | E16: =SUMIF('内訳ﾘｽﾄ(4～3月)'!$D$26:$D$1004,$B16,'内訳ﾘｽﾄ(4～3月)'!H$26:H$1004) -> 0 | F16: =SUMIF('内訳ﾘｽﾄ(4～3月)'!$D$26:$D$1004,$B16,'内訳ﾘｽﾄ(4～3月)'!I$26:I$1004) -> 0 | G16: =SUMIF('内訳ﾘｽﾄ(4～3月)'!$D$26:$D$1004,$B16,'内訳ﾘｽﾄ(4～3月)'!J$26:J$1004) -> 0 | H16: =SUMIF('内訳ﾘｽﾄ(4～3月)'!$D$26:$D$1004,$B16,'内訳ﾘｽﾄ(4～3月)'!K$26:K$1004) -> 0 | I16: =SUMIF('内訳ﾘｽﾄ(4～3月)'!$D$26:$D$1004,$B16,'内訳ﾘｽﾄ(4～3月)'!L$26:L$1004) -> 0 | J16: =SUMIF('内訳ﾘｽﾄ(4～3月)'!$D$26:$D$1004,$B16,'内訳ﾘｽﾄ(4～3月)'!M$26:M$1004) -> 0 | ... N16: =SUMIF('内訳ﾘｽﾄ(4～3月)'!$D$26:$D$1004,$B16,'内訳ﾘｽﾄ(4～3月)'!Q$26:Q$1004) -> 0 | O16: =SUMIF('内訳ﾘｽﾄ(4～3月)'!$D$26:$D$803,'採算表(VND)'!$B16,'内訳ﾘｽﾄ(4～3月)'!R$26:R$803) -> 0
B17: 仕入製商品費 | C17: =SUMIF('内訳ﾘｽﾄ(4～3月)'!$D$26:$D$1004,$B17,'内訳ﾘｽﾄ(4～3月)'!F$26:F$1004) -> 0 | D17: =SUMIF('内訳ﾘｽﾄ(4～3月)'!$D$26:$D$1004,$B17,'内訳ﾘｽﾄ(4～3月)'!G$26:G$1004) -> 0 | E17: =SUMIF('内訳ﾘｽﾄ(4～3月)'!$D$26:$D$1004,$B17,'内訳ﾘｽﾄ(4～3月)'!H$26:H$1004) -> 0 | F17: =SUMIF('内訳ﾘｽﾄ(4～3月)'!$D$26:$D$1004,$B17,'内訳ﾘｽﾄ(4～3月)'!I$26:I$1004) -> 0 | G17: =SUMIF('内訳ﾘｽﾄ(4～3月)'!$D$26:$D$1004,$B17,'内訳ﾘｽﾄ(4～3月)'!J$26:J$1004) -> 0 | H17: =SUMIF('内訳ﾘｽﾄ(4～3月)'!$D$26:$D$1004,$B17,'内訳ﾘｽﾄ(4～3月)'!K$26:K$1004) -> 0 | I17: =SUMIF('内訳ﾘｽﾄ(4～3月)'!$D$26:$D$1004,$B17,'内訳ﾘｽﾄ(4～3月)'!L$26:L$1004) -> 0 | J17: =SUMIF('内訳ﾘｽﾄ(4～3月)'!$D$26:$D$1004,$B17,'内訳ﾘｽﾄ(4～3月)'!M$26:M$1004) -> 0 | ... N17: =SUMIF('内訳ﾘｽﾄ(4～3月)'!$D$26:$D$1004,$B17,'内訳ﾘｽﾄ(4～3月)'!Q$26:Q$1004) -> 0 | O17: =SUMIF('内訳ﾘｽﾄ(4～3月)'!$D$26:$D$803,'採算表(VND)'!$B17,'内訳ﾘｽﾄ(4～3月)'!R$26:R$803) -> 0
B18: 内製品有償支給原価 | C18: =SUMIF('内訳ﾘｽﾄ(4～3月)'!$D$26:$D$1004,$B18,'内訳ﾘｽﾄ(4～3月)'!F$26:F$1004) -> 0 | D18: =SUMIF('内訳ﾘｽﾄ(4～3月)'!$D$26:$D$1004,$B18,'内訳ﾘｽﾄ(4～3月)'!G$26:G$1004) -> 0 | E18: =SUMIF('内訳ﾘｽﾄ(4～3月)'!$D$26:$D$1004,$B18,'内訳ﾘｽﾄ(4～3月)'!H$26:H$1004) -> 0 | F18: =SUMIF('内訳ﾘｽﾄ(4～3月)'!$D$26:$D$1004,$B18,'内訳ﾘｽﾄ(4～3月)'!I$26:I$1004) -> 0 | G18: =SUMIF('内訳ﾘｽﾄ(4～3月)'!$D$26:$D$1004,$B18,'内訳ﾘｽﾄ(4～3月)'!J$26:J$1004) -> 0 | H18: =SUMIF('内訳ﾘｽﾄ(4～3月)'!$D$26:$D$1004,$B18,'内訳ﾘｽﾄ(4～3月)'!K$26:K$1004) -> 0 | I18: =SUMIF('内訳ﾘｽﾄ(4～3月)'!$D$26:$D$1004,$B18,'内訳ﾘｽﾄ(4～3月)'!L$26:L$1004) -> 0 | J18: =SUMIF('内訳ﾘｽﾄ(4～3月)'!$D$26:$D$1004,$B18,'内訳ﾘｽﾄ(4～3月)'!M$26:M$1004) -> 0 | ... N18: =SUMIF('内訳ﾘｽﾄ(4～3月)'!$D$26:$D$1004,$B18,'内訳ﾘｽﾄ(4～3月)'!Q$26:Q$1004) -> 0 | O18: =SUMIF('内訳ﾘｽﾄ(4～3月)'!$D$26:$D$803,'採算表(VND)'!$B18,'内訳ﾘｽﾄ(4～3月)'!R$26:R$803) -> 0
B19: 外注加工費 | C19: =SUMIF('内訳ﾘｽﾄ(4～3月)'!$D$26:$D$1004,$B19,'内訳ﾘｽﾄ(4～3月)'!F$26:F$1004) -> 0 | D19: =SUMIF('内訳ﾘｽﾄ(4～3月)'!$D$26:$D$1004,$B19,'内訳ﾘｽﾄ(4～3月)'!G$26:G$1004) -> 0 | E19: =SUMIF('内訳ﾘｽﾄ(4～3月)'!$D$26:$D$1004,$B19,'内訳ﾘｽﾄ(4～3月)'!H$26:H$1004) -> 0 | F19: =SUMIF('内訳ﾘｽﾄ(4～3月)'!$D$26:$D$1004,$B19,'内訳ﾘｽﾄ(4～3月)'!I$26:I$1004) -> 0 | G19: =SUMIF('内訳ﾘｽﾄ(4～3月)'!$D$26:$D$1004,$B19,'内訳ﾘｽﾄ(4～3月)'!J$26:J$1004) -> 0 | H19: =SUMIF('内訳ﾘｽﾄ(4～3月)'!$D$26:$D$1004,$B19,'内訳ﾘｽﾄ(4～3月)'!K$26:K$1004) -> 0 | I19: =SUMIF('内訳ﾘｽﾄ(4～3月)'!$D$26:$D$1004,$B19,'内訳ﾘｽﾄ(4～3月)'!L$26:L$1004) -> 0 | J19: =SUMIF('内訳ﾘｽﾄ(4～3月)'!$D$26:$D$1004,$B19,'内訳ﾘｽﾄ(4～3月)'!M$26:M$1004) -> 0 | ... N19: =SUMIF('内訳ﾘｽﾄ(4～3月)'!$D$26:$D$1004,$B19,'内訳ﾘｽﾄ(4～3月)'!Q$26:Q$1004) -> 0 | O19: =SUMIF('内訳ﾘｽﾄ(4～3月)'!$D$26:$D$803,'採算表(VND)'!$B19,'内訳ﾘｽﾄ(4～3月)'!R$26:R$803) -> 0
B20: 減価償却費 | C20: =SUMIF('内訳ﾘｽﾄ(4～3月)'!$D$26:$D$1004,$B20,'内訳ﾘｽﾄ(4～3月)'!F$26:F$1004) -> 64678232 | D20: =SUMIF('内訳ﾘｽﾄ(4～3月)'!$D$26:$D$1004,$B20,'内訳ﾘｽﾄ(4～3月)'!G$26:G$1004) -> 64485776 | E20: =SUMIF('内訳ﾘｽﾄ(4～3月)'!$D$26:$D$1004,$B20,'内訳ﾘｽﾄ(4～3月)'!H$26:H$1004) -> 64718094 | F20: =SUMIF('内訳ﾘｽﾄ(4～3月)'!$D$26:$D$1004,$B20,'内訳ﾘｽﾄ(4～3月)'!I$26:I$1004) -> 62990051 | G20: =SUMIF('内訳ﾘｽﾄ(4～3月)'!$D$26:$D$1004,$B20,'内訳ﾘｽﾄ(4～3月)'!J$26:J$1004) -> 31108335 | H20: =SUMIF('内訳ﾘｽﾄ(4～3月)'!$D$26:$D$1004,$B20,'内訳ﾘｽﾄ(4～3月)'!K$26:K$1004) -> 30361361 | I20: =SUMIF('内訳ﾘｽﾄ(4～3月)'!$D$26:$D$1004,$B20,'内訳ﾘｽﾄ(4～3月)'!L$26:L$1004) -> 30010472 | J20: =SUMIF('内訳ﾘｽﾄ(4～3月)'!$D$26:$D$1004,$B20,'内訳ﾘｽﾄ(4～3月)'!M$26:M$1004) -> 29947759 | ... N20: =SUMIF('内訳ﾘｽﾄ(4～3月)'!$D$26:$D$1004,$B20,'内訳ﾘｽﾄ(4～3月)'!Q$26:Q$1004) -> 30469523 | O20: =SUMIF('内訳ﾘｽﾄ(4～3月)'!$D$26:$D$803,'採算表(VND)'!$B20,'内訳ﾘｽﾄ(4～3月)'!R$26:R$803) -> 498584694
B21: 金型償却費 | C21: =SUMIF('内訳ﾘｽﾄ(4～3月)'!$D$26:$D$1004,$B21,'内訳ﾘｽﾄ(4～3月)'!F$26:F$1004) -> 0 | D21: =SUMIF('内訳ﾘｽﾄ(4～3月)'!$D$26:$D$1004,$B21,'内訳ﾘｽﾄ(4～3月)'!G$26:G$1004) -> 0 | E21: =SUMIF('内訳ﾘｽﾄ(4～3月)'!$D$26:$D$1004,$B21,'内訳ﾘｽﾄ(4～3月)'!H$26:H$1004) -> 0 | F21: =SUMIF('内訳ﾘｽﾄ(4～3月)'!$D$26:$D$1004,$B21,'内訳ﾘｽﾄ(4～3月)'!I$26:I$1004) -> 0 | G21: =SUMIF('内訳ﾘｽﾄ(4～3月)'!$D$26:$D$1004,$B21,'内訳ﾘｽﾄ(4～3月)'!J$26:J$1004) -> 0 | H21: =SUMIF('内訳ﾘｽﾄ(4～3月)'!$D$26:$D$1004,$B21,'内訳ﾘｽﾄ(4～3月)'!K$26:K$1004) -> 0 | I21: =SUMIF('内訳ﾘｽﾄ(4～3月)'!$D$26:$D$1004,$B21,'内訳ﾘｽﾄ(4～3月)'!L$26:L$1004) -> 0 | J21: =SUMIF('内訳ﾘｽﾄ(4～3月)'!$D$26:$D$1004,$B21,'内訳ﾘｽﾄ(4～3月)'!M$26:M$1004) -> 0 | ... N21: =SUMIF('内訳ﾘｽﾄ(4～3月)'!$D$26:$D$1004,$B21,'内訳ﾘｽﾄ(4～3月)'!Q$26:Q$1004) -> 0 | O21: =SUMIF('内訳ﾘｽﾄ(4～3月)'!$D$26:$D$803,'採算表(VND)'!$B21,'内訳ﾘｽﾄ(4～3月)'!R$26:R$803) -> 0
B22: 賃借料 | C22: =SUMIF('内訳ﾘｽﾄ(4～3月)'!$D$26:$D$1004,$B22,'内訳ﾘｽﾄ(4～3月)'!F$26:F$1004) -> 0 | D22: =SUMIF('内訳ﾘｽﾄ(4～3月)'!$D$26:$D$1004,$B22,'内訳ﾘｽﾄ(4～3月)'!G$26:G$1004) -> 0 | E22: =SUMIF('内訳ﾘｽﾄ(4～3月)'!$D$26:$D$1004,$B22,'内訳ﾘｽﾄ(4～3月)'!H$26:H$1004) -> 0 | F22: =SUMIF('内訳ﾘｽﾄ(4～3月)'!$D$26:$D$1004,$B22,'内訳ﾘｽﾄ(4～3月)'!I$26:I$1004) -> 0 | G22: =SUMIF('内訳ﾘｽﾄ(4～3月)'!$D$26:$D$1004,$B22,'内訳ﾘｽﾄ(4～3月)'!J$26:J$1004) -> 0 | H22: =SUMIF('内訳ﾘｽﾄ(4～3月)'!$D$26:$D$1004,$B22,'内訳ﾘｽﾄ(4～3月)'!K$26:K$1004) -> 0 | I22: =SUMIF('内訳ﾘｽﾄ(4～3月)'!$D$26:$D$1004,$B22,'内訳ﾘｽﾄ(4～3月)'!L$26:L$1004) -> 0 | J22: =SUMIF('内訳ﾘｽﾄ(4～3月)'!$D$26:$D$1004,$B22,'内訳ﾘｽﾄ(4～3月)'!M$26:M$1004) -> 0 | ... N22: =SUMIF('内訳ﾘｽﾄ(4～3月)'!$D$26:$D$1004,$B22,'内訳ﾘｽﾄ(4～3月)'!Q$26:Q$1004) -> 0 | O22: =SUMIF('内訳ﾘｽﾄ(4～3月)'!$D$26:$D$803,'採算表(VND)'!$B22,'内訳ﾘｽﾄ(4～3月)'!R$26:R$803) -> 0
B23: 保険料 | C23: =SUMIF('内訳ﾘｽﾄ(4～3月)'!$D$26:$D$1004,$B23,'内訳ﾘｽﾄ(4～3月)'!F$26:F$1004) -> 0 | D23: =SUMIF('内訳ﾘｽﾄ(4～3月)'!$D$26:$D$1004,$B23,'内訳ﾘｽﾄ(4～3月)'!G$26:G$1004) -> 0 | E23: =SUMIF('内訳ﾘｽﾄ(4～3月)'!$D$26:$D$1004,$B23,'内訳ﾘｽﾄ(4～3月)'!H$26:H$1004) -> 0 | F23: =SUMIF('内訳ﾘｽﾄ(4～3月)'!$D$26:$D$1004,$B23,'内訳ﾘｽﾄ(4～3月)'!I$26:I$1004) -> 0 | G23: =SUMIF('内訳ﾘｽﾄ(4～3月)'!$D$26:$D$1004,$B23,'内訳ﾘｽﾄ(4～3月)'!J$26:J$1004) -> 0 | H23: =SUMIF('内訳ﾘｽﾄ(4～3月)'!$D$26:$D$1004,$B23,'内訳ﾘｽﾄ(4～3月)'!K$26:K$1004) -> 0 | I23: =SUMIF('内訳ﾘｽﾄ(4～3月)'!$D$26:$D$1004,$B23,'内訳ﾘｽﾄ(4～3月)'!L$26:L$1004) -> 0 | J23: =SUMIF('内訳ﾘｽﾄ(4～3月)'!$D$26:$D$1004,$B23,'内訳ﾘｽﾄ(4～3月)'!M$26:M$1004) -> 0 | ... N23: =SUMIF('内訳ﾘｽﾄ(4～3月)'!$D$26:$D$1004,$B23,'内訳ﾘｽﾄ(4～3月)'!Q$26:Q$1004) -> 0 | O23: =SUMIF('内訳ﾘｽﾄ(4～3月)'!$D$26:$D$803,'採算表(VND)'!$B23,'内訳ﾘｽﾄ(4～3月)'!R$26:R$803) -> 0
B24: 設計委託費 | C24: =SUMIF('内訳ﾘｽﾄ(4～3月)'!$D$26:$D$1004,$B24,'内訳ﾘｽﾄ(4～3月)'!F$26:F$1004) -> 0 | D24: =SUMIF('内訳ﾘｽﾄ(4～3月)'!$D$26:$D$1004,$B24,'内訳ﾘｽﾄ(4～3月)'!G$26:G$1004) -> 0 | E24: =SUMIF('内訳ﾘｽﾄ(4～3月)'!$D$26:$D$1004,$B24,'内訳ﾘｽﾄ(4～3月)'!H$26:H$1004) -> 0 | F24: =SUMIF('内訳ﾘｽﾄ(4～3月)'!$D$26:$D$1004,$B24,'内訳ﾘｽﾄ(4～3月)'!I$26:I$1004) -> 0 | G24: =SUMIF('内訳ﾘｽﾄ(4～3月)'!$D$26:$D$1004,$B24,'内訳ﾘｽﾄ(4～3月)'!J$26:J$1004) -> 0 | H24: =SUMIF('内訳ﾘｽﾄ(4～3月)'!$D$26:$D$1004,$B24,'内訳ﾘｽﾄ(4～3月)'!K$26:K$1004) -> 0 | I24: =SUMIF('内訳ﾘｽﾄ(4～3月)'!$D$26:$D$1004,$B24,'内訳ﾘｽﾄ(4～3月)'!L$26:L$1004) -> 0 | J24: =SUMIF('内訳ﾘｽﾄ(4～3月)'!$D$26:$D$1004,$B24,'内訳ﾘｽﾄ(4～3月)'!M$26:M$1004) -> 0 | ... N24: =SUMIF('内訳ﾘｽﾄ(4～3月)'!$D$26:$D$1004,$B24,'内訳ﾘｽﾄ(4～3月)'!Q$26:Q$1004) -> 0 | O24: =SUMIF('内訳ﾘｽﾄ(4～3月)'!$D$26:$D$803,'採算表(VND)'!$B24,'内訳ﾘｽﾄ(4～3月)'!R$26:R$803) -> 0
B25: 消耗品費 | C25: =SUMIF('内訳ﾘｽﾄ(4～3月)'!$D$26:$D$1004,$B25,'内訳ﾘｽﾄ(4～3月)'!F$26:F$1004) -> 13490470 | D25: =SUMIF('内訳ﾘｽﾄ(4～3月)'!$D$26:$D$1004,$B25,'内訳ﾘｽﾄ(4～3月)'!G$26:G$1004) -> 12890468 | E25: =SUMIF('内訳ﾘｽﾄ(4～3月)'!$D$26:$D$1004,$B25,'内訳ﾘｽﾄ(4～3月)'!H$26:H$1004) -> 14273484 | F25: =SUMIF('内訳ﾘｽﾄ(4～3月)'!$D$26:$D$1004,$B25,'内訳ﾘｽﾄ(4～3月)'!I$26:I$1004) -> 15656698 | G25: =SUMIF('内訳ﾘｽﾄ(4～3月)'!$D$26:$D$1004,$B25,'内訳ﾘｽﾄ(4～3月)'!J$26:J$1004) -> 1007552 | H25: =SUMIF('内訳ﾘｽﾄ(4～3月)'!$D$26:$D$1004,$B25,'内訳ﾘｽﾄ(4～3月)'!K$26:K$1004) -> 982604 | I25: =SUMIF('内訳ﾘｽﾄ(4～3月)'!$D$26:$D$1004,$B25,'内訳ﾘｽﾄ(4～3月)'!L$26:L$1004) -> 1290748 | J25: =SUMIF('内訳ﾘｽﾄ(4～3月)'!$D$26:$D$1004,$B25,'内訳ﾘｽﾄ(4～3月)'!M$26:M$1004) -> 1087120 | ... N25: =SUMIF('内訳ﾘｽﾄ(4～3月)'!$D$26:$D$1004,$B25,'内訳ﾘｽﾄ(4～3月)'!Q$26:Q$1004) -> 1320720 | O25: =SUMIF('内訳ﾘｽﾄ(4～3月)'!$D$26:$D$803,'採算表(VND)'!$B25,'内訳ﾘｽﾄ(4～3月)'!R$26:R$803) -> 65293121
... B60: 内部技術料 | C60: =SUMIF('内訳ﾘｽﾄ(4～3月)'!$D$26:$D$1004,$B60,'内訳ﾘｽﾄ(4～3月)'!F$26:F$1004) -> 0 | D60: =SUMIF('内訳ﾘｽﾄ(4～3月)'!$D$26:$D$1004,$B60,'内訳ﾘｽﾄ(4～3月)'!G$26:G$1004) -> 0 | E60: =SUMIF('内訳ﾘｽﾄ(4～3月)'!$D$26:$D$1004,$B60,'内訳ﾘｽﾄ(4～3月)'!H$26:H$1004) -> 0 | F60: =SUMIF('内訳ﾘｽﾄ(4～3月)'!$D$26:$D$1004,$B60,'内訳ﾘｽﾄ(4～3月)'!I$26:I$1004) -> 0 | G60: =SUMIF('内訳ﾘｽﾄ(4～3月)'!$D$26:$D$1004,$B60,'内訳ﾘｽﾄ(4～3月)'!J$26:J$1004) -> 0 | H60: =SUMIF('内訳ﾘｽﾄ(4～3月)'!$D$26:$D$1004,$B60,'内訳ﾘｽﾄ(4～3月)'!K$26:K$1004) -> 0 | I60: =SUMIF('内訳ﾘｽﾄ(4～3月)'!$D$26:$D$1004,$B60,'内訳ﾘｽﾄ(4～3月)'!L$26:L$1004) -> 0 | J60: =SUMIF('内訳ﾘｽﾄ(4～3月)'!$D$26:$D$1004,$B60,'内訳ﾘｽﾄ(4～3月)'!M$26:M$1004) -> 0 | ... N60: =SUMIF('内訳ﾘｽﾄ(4～3月)'!$D$26:$D$1004,$B60,'内訳ﾘｽﾄ(4～3月)'!Q$26:Q$1004) -> 0 | O60: =SUMIF('内訳ﾘｽﾄ(4～3月)'!$D$26:$D$803,'採算表(VND)'!$B60,'内訳ﾘｽﾄ(4～3月)'!R$26:R$803) -> 0
B61: 部内間接経費 | C61: =IF('内訳ﾘｽﾄ(4～3月)'!$D$5="製造",SUMIF('内訳ﾘｽﾄ(4～3月)'!$D$26:$D$1004,$B61,'内訳ﾘｽﾄ(4～3月)'!F$26:F$1004),IF('内訳ﾘｽﾄ(4～3月)'!$D$5="部内間接",-SUM(C$14:C$60,C$65),0)) -> -511006405 | D61: =IF('内訳ﾘｽﾄ(4～3月)'!$D$5="製造",SUMIF('内訳ﾘｽﾄ(4～3月)'!$D$26:$D$1004,$B61,'内訳ﾘｽﾄ(4～3月)'!G$26:G$1004),IF('内訳ﾘｽﾄ(4～3月)'!$D$5="部内間接",-SUM(D$14:D$60,D$65),0)) -> -736447527 | E61: =IF('内訳ﾘｽﾄ(4～3月)'!$D$5="製造",SUMIF('内訳ﾘｽﾄ(4～3月)'!$D$26:$D$1004,$B61,'内訳ﾘｽﾄ(4～3月)'!H$26:H$1004),IF('内訳ﾘｽﾄ(4～3月)'!$D$5="部内間接",-SUM(E$14:E$60,E$65),0)) -> -329640069 | F61: =IF('内訳ﾘｽﾄ(4～3月)'!$D$5="製造",SUMIF('内訳ﾘｽﾄ(4～3月)'!$D$26:$D$1004,$B61,'内訳ﾘｽﾄ(4～3月)'!I$26:I$1004),IF('内訳ﾘｽﾄ(4～3月)'!$D$5="部内間接",-SUM(F$14:F$60,F$65),0)) -> -295575098 | G61: =IF('内訳ﾘｽﾄ(4～3月)'!$D$5="製造",SUMIF('内訳ﾘｽﾄ(4～3月)'!$D$26:$D$1004,$B61,'内訳ﾘｽﾄ(4～3月)'!J$26:J$1004),IF('内訳ﾘｽﾄ(4～3月)'!$D$5="部内間接",-SUM(G$14:G$60,G$65),0)) -> -122869681 | H61: =IF('内訳ﾘｽﾄ(4～3月)'!$D$5="製造",SUMIF('内訳ﾘｽﾄ(4～3月)'!$D$26:$D$1004,$B61,'内訳ﾘｽﾄ(4～3月)'!K$26:K$1004),IF('内訳ﾘｽﾄ(4～3月)'!$D$5="部内間接",-SUM(H$14:H$60,H$65),0)) -> -127855273 | I61: =IF('内訳ﾘｽﾄ(4～3月)'!$D$5="製造",SUMIF('内訳ﾘｽﾄ(4～3月)'!$D$26:$D$1004,$B61,'内訳ﾘｽﾄ(4～3月)'!L$26:L$1004),IF('内訳ﾘｽﾄ(4～3月)'!$D$5="部内間接",-SUM(I$14:I$60,I$65),0)) -> -106916421 | J61: =IF('内訳ﾘｽﾄ(4～3月)'!$D$5="製造",SUMIF('内訳ﾘｽﾄ(4～3月)'!$D$26:$D$1004,$B61,'内訳ﾘｽﾄ(4～3月)'!M$26:M$1004),IF('内訳ﾘｽﾄ(4～3月)'!$D$5="部内間接",-SUM(J$14:J$60,J$65),0)) -> -101679511 | ... N61: =IF('内訳ﾘｽﾄ(4～3月)'!$D$5="製造",SUMIF('内訳ﾘｽﾄ(4～3月)'!$D$26:$D$1004,$B61,'内訳ﾘｽﾄ(4～3月)'!Q$26:Q$1004),IF('内訳ﾘｽﾄ(4～3月)'!$D$5="部内間接",-SUM(N$14:N$60,N$65),0)) -> -79669917 | O61: =IF('内訳ﾘｽﾄ(4～3月)'!$D$5="部内間接",-SUM(O$65,O$14:O$60),IF('内訳ﾘｽﾄ(4～3月)'!$D$5="製造",SUMIF('内訳ﾘｽﾄ(4～3月)'!$D$26:$D$803,'採算表(VND)'!$B61,'内訳ﾘｽﾄ(4～3月)'!R$26:R$803),0)) -> -2714812100
B62: 部外間接1経費 | C62: =IF('内訳ﾘｽﾄ(4～3月)'!$D$5="製造",SUMIF('内訳ﾘｽﾄ(4～3月)'!$D$26:$D$1004,$B62,'内訳ﾘｽﾄ(4～3月)'!F$26:F$1004),IF('内訳ﾘｽﾄ(4～3月)'!$D$5="部外間接1",-SUM(C$14:C$60,C$65),0)) -> 0 | D62: =IF('内訳ﾘｽﾄ(4～3月)'!$D$5="製造",SUMIF('内訳ﾘｽﾄ(4～3月)'!$D$26:$D$1004,$B62,'内訳ﾘｽﾄ(4～3月)'!G$26:G$1004),IF('内訳ﾘｽﾄ(4～3月)'!$D$5="部外間接1",-SUM(D$14:D$60,D$65),0)) -> 0 | E62: =IF('内訳ﾘｽﾄ(4～3月)'!$D$5="製造",SUMIF('内訳ﾘｽﾄ(4～3月)'!$D$26:$D$1004,$B62,'内訳ﾘｽﾄ(4～3月)'!H$26:H$1004),IF('内訳ﾘｽﾄ(4～3月)'!$D$5="部外間接1",-SUM(E$14:E$60,E$65),0)) -> 0 | F62: =IF('内訳ﾘｽﾄ(4～3月)'!$D$5="製造",SUMIF('内訳ﾘｽﾄ(4～3月)'!$D$26:$D$1004,$B62,'内訳ﾘｽﾄ(4～3月)'!I$26:I$1004),IF('内訳ﾘｽﾄ(4～3月)'!$D$5="部外間接1",-SUM(F$14:F$60,F$65),0)) -> 0 | G62: =IF('内訳ﾘｽﾄ(4～3月)'!$D$5="製造",SUMIF('内訳ﾘｽﾄ(4～3月)'!$D$26:$D$1004,$B62,'内訳ﾘｽﾄ(4～3月)'!J$26:J$1004),IF('内訳ﾘｽﾄ(4～3月)'!$D$5="部外間接1",-SUM(G$14:G$60,G$65),0)) -> 0 | H62: =IF('内訳ﾘｽﾄ(4～3月)'!$D$5="製造",SUMIF('内訳ﾘｽﾄ(4～3月)'!$D$26:$D$1004,$B62,'内訳ﾘｽﾄ(4～3月)'!K$26:K$1004),IF('内訳ﾘｽﾄ(4～3月)'!$D$5="部外間接1",-SUM(H$14:H$60,H$65),0)) -> 0 | I62: =IF('内訳ﾘｽﾄ(4～3月)'!$D$5="製造",SUMIF('内訳ﾘｽﾄ(4～3月)'!$D$26:$D$1004,$B62,'内訳ﾘｽﾄ(4～3月)'!L$26:L$1004),IF('内訳ﾘｽﾄ(4～3月)'!$D$5="部外間接1",-SUM(I$14:I$60,I$65),0)) -> 0 | J62: =IF('内訳ﾘｽﾄ(4～3月)'!$D$5="製造",SUMIF('内訳ﾘｽﾄ(4～3月)'!$D$26:$D$1004,$B62,'内訳ﾘｽﾄ(4～3月)'!M$26:M$1004),IF('内訳ﾘｽﾄ(4～3月)'!$D$5="部外間接1",-SUM(J$14:J$60,J$65),0)) -> 0 | ... N62: =IF('内訳ﾘｽﾄ(4～3月)'!$D$5="製造",SUMIF('内訳ﾘｽﾄ(4～3月)'!$D$26:$D$1004,$B62,'内訳ﾘｽﾄ(4～3月)'!Q$26:Q$1004),IF('内訳ﾘｽﾄ(4～3月)'!$D$5="部外間接1",-SUM(N$14:N$60,N$65),0)) -> 0 | O62: =IF('内訳ﾘｽﾄ(4～3月)'!$D$5="部外間接1",-SUM(O$65,O$14:O$60),IF('内訳ﾘｽﾄ(4～3月)'!$D$5="製造",SUMIF('内訳ﾘｽﾄ(4～3月)'!$D$26:$D$803,'採算表(VND)'!$B62,'内訳ﾘｽﾄ(4～3月)'!R$26:R$803),0)) -> 0
B63: 部外間接2経費 | C63: =IF('内訳ﾘｽﾄ(4～3月)'!$D$5="製造",SUMIF('内訳ﾘｽﾄ(4～3月)'!$D$26:$D$1004,$B63,'内訳ﾘｽﾄ(4～3月)'!F$26:F$1004),IF('内訳ﾘｽﾄ(4～3月)'!$D$5="部外間接2",-SUM(C$14:C$60,C$65),0)) -> 0 | D63: =IF('内訳ﾘｽﾄ(4～3月)'!$D$5="製造",SUMIF('内訳ﾘｽﾄ(4～3月)'!$D$26:$D$1004,$B63,'内訳ﾘｽﾄ(4～3月)'!G$26:G$1004),IF('内訳ﾘｽﾄ(4～3月)'!$D$5="部外間接2",-SUM(D$14:D$60,D$65),0)) -> 0 | E63: =IF('内訳ﾘｽﾄ(4～3月)'!$D$5="製造",SUMIF('内訳ﾘｽﾄ(4～3月)'!$D$26:$D$1004,$B63,'内訳ﾘｽﾄ(4～3月)'!H$26:H$1004),IF('内訳ﾘｽﾄ(4～3月)'!$D$5="部外間接2",-SUM(E$14:E$60,E$65),0)) -> 0 | F63: =IF('内訳ﾘｽﾄ(4～3月)'!$D$5="製造",SUMIF('内訳ﾘｽﾄ(4～3月)'!$D$26:$D$1004,$B63,'内訳ﾘｽﾄ(4～3月)'!I$26:I$1004),IF('内訳ﾘｽﾄ(4～3月)'!$D$5="部外間接2",-SUM(F$14:F$60,F$65),0)) -> 0 | G63: =IF('内訳ﾘｽﾄ(4～3月)'!$D$5="製造",SUMIF('内訳ﾘｽﾄ(4～3月)'!$D$26:$D$1004,$B63,'内訳ﾘｽﾄ(4～3月)'!J$26:J$1004),IF('内訳ﾘｽﾄ(4～3月)'!$D$5="部外間接2",-SUM(G$14:G$60,G$65),0)) -> 0 | H63: =IF('内訳ﾘｽﾄ(4～3月)'!$D$5="製造",SUMIF('内訳ﾘｽﾄ(4～3月)'!$D$26:$D$1004,$B63,'内訳ﾘｽﾄ(4～3月)'!K$26:K$1004),IF('内訳ﾘｽﾄ(4～3月)'!$D$5="部外間接2",-SUM(H$14:H$60,H$65),0)) -> 0 | I63: =IF('内訳ﾘｽﾄ(4～3月)'!$D$5="製造",SUMIF('内訳ﾘｽﾄ(4～3月)'!$D$26:$D$1004,$B63,'内訳ﾘｽﾄ(4～3月)'!L$26:L$1004),IF('内訳ﾘｽﾄ(4～3月)'!$D$5="部外間接2",-SUM(I$14:I$60,I$65),0)) -> 0 | J63: =IF('内訳ﾘｽﾄ(4～3月)'!$D$5="製造",SUMIF('内訳ﾘｽﾄ(4～3月)'!$D$26:$D$1004,$B63,'内訳ﾘｽﾄ(4～3月)'!M$26:M$1004),IF('内訳ﾘｽﾄ(4～3月)'!$D$5="部外間接2",-SUM(J$14:J$60,J$65),0)) -> 0 | ... N63: =IF('内訳ﾘｽﾄ(4～3月)'!$D$5="製造",SUMIF('内訳ﾘｽﾄ(4～3月)'!$D$26:$D$1004,$B63,'内訳ﾘｽﾄ(4～3月)'!Q$26:Q$1004),IF('内訳ﾘｽﾄ(4～3月)'!$D$5="部外間接2",-SUM(N$14:N$60,N$65),0)) -> 0 | O63: =IF('内訳ﾘｽﾄ(4～3月)'!$D$5="部外間接2",-SUM(O$65,O$14:O$60),IF('内訳ﾘｽﾄ(4～3月)'!$D$5="製造",SUMIF('内訳ﾘｽﾄ(4～3月)'!$D$26:$D$803,'採算表(VND)'!$B63,'内訳ﾘｽﾄ(4～3月)'!R$26:R$803),0)) -> 0
B64: 工場間接経費 | C64: =IF('内訳ﾘｽﾄ(4～3月)'!$D$5="製造",SUMIF('内訳ﾘｽﾄ(4～3月)'!$D$26:$D$1004,$B64,'内訳ﾘｽﾄ(4～3月)'!F$26:F$1004),IF('内訳ﾘｽﾄ(4～3月)'!$D$5="工場間接",-SUM(C$14:C$60,C$65),0)) -> 0 | D64: =IF('内訳ﾘｽﾄ(4～3月)'!$D$5="製造",SUMIF('内訳ﾘｽﾄ(4～3月)'!$D$26:$D$1004,$B64,'内訳ﾘｽﾄ(4～3月)'!G$26:G$1004),IF('内訳ﾘｽﾄ(4～3月)'!$D$5="工場間接",-SUM(D$14:D$60,D$65),0)) -> 0 | E64: =IF('内訳ﾘｽﾄ(4～3月)'!$D$5="製造",SUMIF('内訳ﾘｽﾄ(4～3月)'!$D$26:$D$1004,$B64,'内訳ﾘｽﾄ(4～3月)'!H$26:H$1004),IF('内訳ﾘｽﾄ(4～3月)'!$D$5="工場間接",-SUM(E$14:E$60,E$65),0)) -> 0 | F64: =IF('内訳ﾘｽﾄ(4～3月)'!$D$5="製造",SUMIF('内訳ﾘｽﾄ(4～3月)'!$D$26:$D$1004,$B64,'内訳ﾘｽﾄ(4～3月)'!I$26:I$1004),IF('内訳ﾘｽﾄ(4～3月)'!$D$5="工場間接",-SUM(F$14:F$60,F$65),0)) -> 0 | G64: =IF('内訳ﾘｽﾄ(4～3月)'!$D$5="製造",SUMIF('内訳ﾘｽﾄ(4～3月)'!$D$26:$D$1004,$B64,'内訳ﾘｽﾄ(4～3月)'!J$26:J$1004),IF('内訳ﾘｽﾄ(4～3月)'!$D$5="工場間接",-SUM(G$14:G$60,G$65),0)) -> 0 | H64: =IF('内訳ﾘｽﾄ(4～3月)'!$D$5="製造",SUMIF('内訳ﾘｽﾄ(4～3月)'!$D$26:$D$1004,$B64,'内訳ﾘｽﾄ(4～3月)'!K$26:K$1004),IF('内訳ﾘｽﾄ(4～3月)'!$D$5="工場間接",-SUM(H$14:H$60,H$65),0)) -> 0 | I64: =IF('内訳ﾘｽﾄ(4～3月)'!$D$5="製造",SUMIF('内訳ﾘｽﾄ(4～3月)'!$D$26:$D$1004,$B64,'内訳ﾘｽﾄ(4～3月)'!L$26:L$1004),IF('内訳ﾘｽﾄ(4～3月)'!$D$5="工場間接",-SUM(I$14:I$60,I$65),0)) -> 0 | J64: =IF('内訳ﾘｽﾄ(4～3月)'!$D$5="製造",SUMIF('内訳ﾘｽﾄ(4～3月)'!$D$26:$D$1004,$B64,'内訳ﾘｽﾄ(4～3月)'!M$26:M$1004),IF('内訳ﾘｽﾄ(4～3月)'!$D$5="工場間接",-SUM(J$14:J$60,J$65),0)) -> 0 | ... N64: =IF('内訳ﾘｽﾄ(4～3月)'!$D$5="製造",SUMIF('内訳ﾘｽﾄ(4～3月)'!$D$26:$D$1004,$B64,'内訳ﾘｽﾄ(4～3月)'!Q$26:Q$1004),IF('内訳ﾘｽﾄ(4～3月)'!$D$5="工場間接",-SUM(N$14:N$60,N$65),0)) -> 0 | O64: =IF('内訳ﾘｽﾄ(4～3月)'!$D$5="工場間接",-SUM(O$65,O$14:O$60),IF('内訳ﾘｽﾄ(4～3月)'!$D$5="製造",SUMIF('内訳ﾘｽﾄ(4～3月)'!$D$26:$D$803,'採算表(VND)'!$B64,'内訳ﾘｽﾄ(4～3月)'!R$26:R$803),0)) -> 0
B65: 本社機構経費 | C65: =SUMIF('内訳ﾘｽﾄ(4～3月)'!$D$26:$D$1004,$B65,'内訳ﾘｽﾄ(4～3月)'!F$26:F$1004) -> 0 | D65: =SUMIF('内訳ﾘｽﾄ(4～3月)'!$D$26:$D$1004,$B65,'内訳ﾘｽﾄ(4～3月)'!G$26:G$1004) -> 0 | E65: =SUMIF('内訳ﾘｽﾄ(4～3月)'!$D$26:$D$1004,$B65,'内訳ﾘｽﾄ(4～3月)'!H$26:H$1004) -> 0 | F65: =SUMIF('内訳ﾘｽﾄ(4～3月)'!$D$26:$D$1004,$B65,'内訳ﾘｽﾄ(4～3月)'!I$26:I$1004) -> 0 | G65: =SUMIF('内訳ﾘｽﾄ(4～3月)'!$D$26:$D$1004,$B65,'内訳ﾘｽﾄ(4～3月)'!J$26:J$1004) -> 0 | H65: =SUMIF('内訳ﾘｽﾄ(4～3月)'!$D$26:$D$1004,$B65,'内訳ﾘｽﾄ(4～3月)'!K$26:K$1004) -> 0 | I65: =SUMIF('内訳ﾘｽﾄ(4～3月)'!$D$26:$D$1004,$B65,'内訳ﾘｽﾄ(4～3月)'!L$26:L$1004) -> 0 | J65: =SUMIF('内訳ﾘｽﾄ(4～3月)'!$D$26:$D$1004,$B65,'内訳ﾘｽﾄ(4～3月)'!M$26:M$1004) -> 0 | ... N65: =SUMIF('内訳ﾘｽﾄ(4～3月)'!$D$26:$D$1004,$B65,'内訳ﾘｽﾄ(4～3月)'!Q$26:Q$1004) -> 0 | O65: =SUMIF('内訳ﾘｽﾄ(4～3月)'!$D$26:$D$803,'採算表(VND)'!$B65,'内訳ﾘｽﾄ(4～3月)'!R$26:R$803) -> 0
B66: 差引収益 | C66: =C12-C13 -> 0 | D66: =D12-D13 -> 0 | E66: =E12-E13 -> 0 | F66: =F12-F13 -> 0 | G66: =G12-G13 -> 0 | H66: =H12-H13 -> 0 | I66: =I12-I13 -> 0 | J66: =J12-J13 -> 0 | ... N66: =N12-N13 -> 0 | O66: =IF(ISBLANK(O4),"",O12-O13) -> 0
B67: 総時間 | C67: =C73+C79 -> 0 | D67: =D73+D79 -> 0 | E67: =E73+E79 -> 0 | F67: =F73+F79 -> 0 | G67: =G73+G79 -> 0 | H67: =H73+H79 -> 0 | I67: =I73+I79 -> 0 | J67: =J73+J79 -> 0 | ... N67: =N73+N79 -> 0 | O67: =IF(ISBLANK(O4),"",O73+O79) -> 0
B68: 直接部門 | C68: =SUMIF('内訳ﾘｽﾄ(4～3月)'!$D$8:$D$15,'採算表(VND)'!$B68,'内訳ﾘｽﾄ(4～3月)'!F$8:F$15) -> 31644 | D68: =SUMIF('内訳ﾘｽﾄ(4～3月)'!$D$8:$D$15,'採算表(VND)'!$B68,'内訳ﾘｽﾄ(4～3月)'!G$8:G$15) -> 30078 | E68: =SUMIF('内訳ﾘｽﾄ(4～3月)'!$D$8:$D$15,'採算表(VND)'!$B68,'内訳ﾘｽﾄ(4～3月)'!H$8:H$15) -> 33244 | F68: =SUMIF('内訳ﾘｽﾄ(4～3月)'!$D$8:$D$15,'採算表(VND)'!$B68,'内訳ﾘｽﾄ(4～3月)'!I$8:I$15) -> 5169 | G68: =SUMIF('内訳ﾘｽﾄ(4～3月)'!$D$8:$D$15,'採算表(VND)'!$B68,'内訳ﾘｽﾄ(4～3月)'!J$8:J$15) -> 4452.5 | H68: =SUMIF('内訳ﾘｽﾄ(4～3月)'!$D$8:$D$15,'採算表(VND)'!$B68,'内訳ﾘｽﾄ(4～3月)'!K$8:K$15) -> 4253 | I68: =SUMIF('内訳ﾘｽﾄ(4～3月)'!$D$8:$D$15,'採算表(VND)'!$B68,'内訳ﾘｽﾄ(4～3月)'!L$8:L$15) -> 5904 | J68: =SUMIF('内訳ﾘｽﾄ(4～3月)'!$D$8:$D$15,'採算表(VND)'!$B68,'内訳ﾘｽﾄ(4～3月)'!M$8:M$15) -> 5134 | ... N68: =SUMIF('内訳ﾘｽﾄ(4～3月)'!$D$8:$D$15,'採算表(VND)'!$B68,'内訳ﾘｽﾄ(4～3月)'!Q$8:Q$15) -> 5773 | O68: =SUMIF('内訳ﾘｽﾄ(4～3月)'!$D$8:$D$15,'採算表(VND)'!$B68,'内訳ﾘｽﾄ(4～3月)'!$R$8:$R$15) -> 140871.5
B69: 部内間接部門 | C69: =IF('内訳ﾘｽﾄ(4～3月)'!$D$5="製造",SUMIF('内訳ﾘｽﾄ(4～3月)'!$D$8:$D$15,$B69,'内訳ﾘｽﾄ(4～3月)'!F$8:F$15),IF('内訳ﾘｽﾄ(4～3月)'!$D$5="部内間接",-C$68,0)) -> -31644 | D69: =IF('内訳ﾘｽﾄ(4～3月)'!$D$5="製造",SUMIF('内訳ﾘｽﾄ(4～3月)'!$D$8:$D$15,$B69,'内訳ﾘｽﾄ(4～3月)'!G$8:G$15),IF('内訳ﾘｽﾄ(4～3月)'!$D$5="部内間接",-D$68,0)) -> -30078 | E69: =IF('内訳ﾘｽﾄ(4～3月)'!$D$5="製造",SUMIF('内訳ﾘｽﾄ(4～3月)'!$D$8:$D$15,$B69,'内訳ﾘｽﾄ(4～3月)'!H$8:H$15),IF('内訳ﾘｽﾄ(4～3月)'!$D$5="部内間接",-E$68,0)) -> -33244 | F69: =IF('内訳ﾘｽﾄ(4～3月)'!$D$5="製造",SUMIF('内訳ﾘｽﾄ(4～3月)'!$D$8:$D$15,$B69,'内訳ﾘｽﾄ(4～3月)'!I$8:I$15),IF('内訳ﾘｽﾄ(4～3月)'!$D$5="部内間接",-F$68,0)) -> -5169 | G69: =IF('内訳ﾘｽﾄ(4～3月)'!$D$5="製造",SUMIF('内訳ﾘｽﾄ(4～3月)'!$D$8:$D$15,$B69,'内訳ﾘｽﾄ(4～3月)'!J$8:J$15),IF('内訳ﾘｽﾄ(4～3月)'!$D$5="部内間接",-G$68,0)) -> -4452.5 | H69: =IF('内訳ﾘｽﾄ(4～3月)'!$D$5="製造",SUMIF('内訳ﾘｽﾄ(4～3月)'!$D$8:$D$15,$B69,'内訳ﾘｽﾄ(4～3月)'!K$8:K$15),IF('内訳ﾘｽﾄ(4～3月)'!$D$5="部内間接",-H$68,0)) -> -4253 | I69: =IF('内訳ﾘｽﾄ(4～3月)'!$D$5="製造",SUMIF('内訳ﾘｽﾄ(4～3月)'!$D$8:$D$15,$B69,'内訳ﾘｽﾄ(4～3月)'!L$8:L$15),IF('内訳ﾘｽﾄ(4～3月)'!$D$5="部内間接",-I$68,0)) -> -5904 | J69: =IF('内訳ﾘｽﾄ(4～3月)'!$D$5="製造",SUMIF('内訳ﾘｽﾄ(4～3月)'!$D$8:$D$15,$B69,'内訳ﾘｽﾄ(4～3月)'!M$8:M$15),IF('内訳ﾘｽﾄ(4～3月)'!$D$5="部内間接",-J$68,0)) -> -5134 | ... N69: =IF('内訳ﾘｽﾄ(4～3月)'!$D$5="製造",SUMIF('内訳ﾘｽﾄ(4～3月)'!$D$8:$D$15,$B69,'内訳ﾘｽﾄ(4～3月)'!Q$8:Q$15),IF('内訳ﾘｽﾄ(4～3月)'!$D$5="部内間接",-N$68,0)) -> -5773 | O69: =IF('内訳ﾘｽﾄ(4～3月)'!$D$5="部内間接",-SUM(O$68),IF('内訳ﾘｽﾄ(4～3月)'!$D$5="製造",SUMIF('内訳ﾘｽﾄ(4～3月)'!$D$8:$D$15,'採算表(VND)'!$B69,'内訳ﾘｽﾄ(4～3月)'!$R$8:$R$15),0)) -> -140871.5
B70: 部外間接部門1 | C70: =IF('内訳ﾘｽﾄ(4～3月)'!$D$5="製造",SUMIF('内訳ﾘｽﾄ(4～3月)'!$D$8:$D$15,$B70,'内訳ﾘｽﾄ(4～3月)'!F$8:F$15),IF('内訳ﾘｽﾄ(4～3月)'!$D$5="部外間接1",-C$68,0)) -> 0 | D70: =IF('内訳ﾘｽﾄ(4～3月)'!$D$5="製造",SUMIF('内訳ﾘｽﾄ(4～3月)'!$D$8:$D$15,$B70,'内訳ﾘｽﾄ(4～3月)'!G$8:G$15),IF('内訳ﾘｽﾄ(4～3月)'!$D$5="部外間接1",-D$68,0)) -> 0 | E70: =IF('内訳ﾘｽﾄ(4～3月)'!$D$5="製造",SUMIF('内訳ﾘｽﾄ(4～3月)'!$D$8:$D$15,$B70,'内訳ﾘｽﾄ(4～3月)'!H$8:H$15),IF('内訳ﾘｽﾄ(4～3月)'!$D$5="部外間接1",-E$68,0)) -> 0 | F70: =IF('内訳ﾘｽﾄ(4～3月)'!$D$5="製造",SUMIF('内訳ﾘｽﾄ(4～3月)'!$D$8:$D$15,$B70,'内訳ﾘｽﾄ(4～3月)'!I$8:I$15),IF('内訳ﾘｽﾄ(4～3月)'!$D$5="部外間接1",-F$68,0)) -> 0 | G70: =IF('内訳ﾘｽﾄ(4～3月)'!$D$5="製造",SUMIF('内訳ﾘｽﾄ(4～3月)'!$D$8:$D$15,$B70,'内訳ﾘｽﾄ(4～3月)'!J$8:J$15),IF('内訳ﾘｽﾄ(4～3月)'!$D$5="部外間接1",-G$68,0)) -> 0 | H70: =IF('内訳ﾘｽﾄ(4～3月)'!$D$5="製造",SUMIF('内訳ﾘｽﾄ(4～3月)'!$D$8:$D$15,$B70,'内訳ﾘｽﾄ(4～3月)'!K$8:K$15),IF('内訳ﾘｽﾄ(4～3月)'!$D$5="部外間接1",-H$68,0)) -> 0 | I70: =IF('内訳ﾘｽﾄ(4～3月)'!$D$5="製造",SUMIF('内訳ﾘｽﾄ(4～3月)'!$D$8:$D$15,$B70,'内訳ﾘｽﾄ(4～3月)'!L$8:L$15),IF('内訳ﾘｽﾄ(4～3月)'!$D$5="部外間接1",-I$68,0)) -> 0 | J70: =IF('内訳ﾘｽﾄ(4～3月)'!$D$5="製造",SUMIF('内訳ﾘｽﾄ(4～3月)'!$D$8:$D$15,$B70,'内訳ﾘｽﾄ(4～3月)'!M$8:M$15),IF('内訳ﾘｽﾄ(4～3月)'!$D$5="部外間接1",-J$68,0)) -> 0 | ... N70: =IF('内訳ﾘｽﾄ(4～3月)'!$D$5="製造",SUMIF('内訳ﾘｽﾄ(4～3月)'!$D$8:$D$15,$B70,'内訳ﾘｽﾄ(4～3月)'!Q$8:Q$15),IF('内訳ﾘｽﾄ(4～3月)'!$D$5="部外間接1",-N$68,0)) -> 0 | O70: =IF('内訳ﾘｽﾄ(4～3月)'!$D$5="部外間接1",-SUM(O$68),IF('内訳ﾘｽﾄ(4～3月)'!$D$5="製造",SUMIF('内訳ﾘｽﾄ(4～3月)'!$D$8:$D$15,'採算表(VND)'!$B70,'内訳ﾘｽﾄ(4～3月)'!$R$8:$R$15),0)) -> 0
B71: 部外間接部門2 | C71: =IF('内訳ﾘｽﾄ(4～3月)'!$D$5="製造",SUMIF('内訳ﾘｽﾄ(4～3月)'!$D$8:$D$15,$B71,'内訳ﾘｽﾄ(4～3月)'!F$8:F$15),IF('内訳ﾘｽﾄ(4～3月)'!$D$5="部外間接2",-C$68,0)) -> 0 | D71: =IF('内訳ﾘｽﾄ(4～3月)'!$D$5="製造",SUMIF('内訳ﾘｽﾄ(4～3月)'!$D$8:$D$15,$B71,'内訳ﾘｽﾄ(4～3月)'!G$8:G$15),IF('内訳ﾘｽﾄ(4～3月)'!$D$5="部外間接2",-D$68,0)) -> 0 | E71: =IF('内訳ﾘｽﾄ(4～3月)'!$D$5="製造",SUMIF('内訳ﾘｽﾄ(4～3月)'!$D$8:$D$15,$B71,'内訳ﾘｽﾄ(4～3月)'!H$8:H$15),IF('内訳ﾘｽﾄ(4～3月)'!$D$5="部外間接2",-E$68,0)) -> 0 | F71: =IF('内訳ﾘｽﾄ(4～3月)'!$D$5="製造",SUMIF('内訳ﾘｽﾄ(4～3月)'!$D$8:$D$15,$B71,'内訳ﾘｽﾄ(4～3月)'!I$8:I$15),IF('内訳ﾘｽﾄ(4～3月)'!$D$5="部外間接2",-F$68,0)) -> 0 | G71: =IF('内訳ﾘｽﾄ(4～3月)'!$D$5="製造",SUMIF('内訳ﾘｽﾄ(4～3月)'!$D$8:$D$15,$B71,'内訳ﾘｽﾄ(4～3月)'!J$8:J$15),IF('内訳ﾘｽﾄ(4～3月)'!$D$5="部外間接2",-G$68,0)) -> 0 | H71: =IF('内訳ﾘｽﾄ(4～3月)'!$D$5="製造",SUMIF('内訳ﾘｽﾄ(4～3月)'!$D$8:$D$15,$B71,'内訳ﾘｽﾄ(4～3月)'!K$8:K$15),IF('内訳ﾘｽﾄ(4～3月)'!$D$5="部外間接2",-H$68,0)) -> 0 | I71: =IF('内訳ﾘｽﾄ(4～3月)'!$D$5="製造",SUMIF('内訳ﾘｽﾄ(4～3月)'!$D$8:$D$15,$B71,'内訳ﾘｽﾄ(4～3月)'!L$8:L$15),IF('内訳ﾘｽﾄ(4～3月)'!$D$5="部外間接2",-I$68,0)) -> 0 | J71: =IF('内訳ﾘｽﾄ(4～3月)'!$D$5="製造",SUMIF('内訳ﾘｽﾄ(4～3月)'!$D$8:$D$15,$B71,'内訳ﾘｽﾄ(4～3月)'!M$8:M$15),IF('内訳ﾘｽﾄ(4～3月)'!$D$5="部外間接2",-J$68,0)) -> 0 | ... N71: =IF('内訳ﾘｽﾄ(4～3月)'!$D$5="製造",SUMIF('内訳ﾘｽﾄ(4～3月)'!$D$8:$D$15,$B71,'内訳ﾘｽﾄ(4～3月)'!Q$8:Q$15),IF('内訳ﾘｽﾄ(4～3月)'!$D$5="部外間接2",-N$68,0)) -> 0 | O71: =IF('内訳ﾘｽﾄ(4～3月)'!$D$5="部外間接2",-SUM(O$68),IF('内訳ﾘｽﾄ(4～3月)'!$D$5="製造",SUMIF('内訳ﾘｽﾄ(4～3月)'!$D$8:$D$15,'採算表(VND)'!$B71,'内訳ﾘｽﾄ(4～3月)'!$R$8:$R$15),0)) -> 0
B72: 工場間接部門 | C72: =IF('内訳ﾘｽﾄ(4～3月)'!$D$5="製造",SUMIF('内訳ﾘｽﾄ(4～3月)'!$D$8:$D$15,$B72,'内訳ﾘｽﾄ(4～3月)'!F$8:F$15),IF('内訳ﾘｽﾄ(4～3月)'!$D$5="工場間接",-C$68,0)) -> 0 | D72: =IF('内訳ﾘｽﾄ(4～3月)'!$D$5="製造",SUMIF('内訳ﾘｽﾄ(4～3月)'!$D$8:$D$15,$B72,'内訳ﾘｽﾄ(4～3月)'!G$8:G$15),IF('内訳ﾘｽﾄ(4～3月)'!$D$5="工場間接",-D$68,0)) -> 0 | E72: =IF('内訳ﾘｽﾄ(4～3月)'!$D$5="製造",SUMIF('内訳ﾘｽﾄ(4～3月)'!$D$8:$D$15,$B72,'内訳ﾘｽﾄ(4～3月)'!H$8:H$15),IF('内訳ﾘｽﾄ(4～3月)'!$D$5="工場間接",-E$68,0)) -> 0 | F72: =IF('内訳ﾘｽﾄ(4～3月)'!$D$5="製造",SUMIF('内訳ﾘｽﾄ(4～3月)'!$D$8:$D$15,$B72,'内訳ﾘｽﾄ(4～3月)'!I$8:I$15),IF('内訳ﾘｽﾄ(4～3月)'!$D$5="工場間接",-F$68,0)) -> 0 | G72: =IF('内訳ﾘｽﾄ(4～3月)'!$D$5="製造",SUMIF('内訳ﾘｽﾄ(4～3月)'!$D$8:$D$15,$B72,'内訳ﾘｽﾄ(4～3月)'!J$8:J$15),IF('内訳ﾘｽﾄ(4～3月)'!$D$5="工場間接",-G$68,0)) -> 0 | H72: =IF('内訳ﾘｽﾄ(4～3月)'!$D$5="製造",SUMIF('内訳ﾘｽﾄ(4～3月)'!$D$8:$D$15,$B72,'内訳ﾘｽﾄ(4～3月)'!K$8:K$15),IF('内訳ﾘｽﾄ(4～3月)'!$D$5="工場間接",-H$68,0)) -> 0 | I72: =IF('内訳ﾘｽﾄ(4～3月)'!$D$5="製造",SUMIF('内訳ﾘｽﾄ(4～3月)'!$D$8:$D$15,$B72,'内訳ﾘｽﾄ(4～3月)'!L$8:L$15),IF('内訳ﾘｽﾄ(4～3月)'!$D$5="工場間接",-I$68,0)) -> 0 | J72: =IF('内訳ﾘｽﾄ(4～3月)'!$D$5="製造",SUMIF('内訳ﾘｽﾄ(4～3月)'!$D$8:$D$15,$B72,'内訳ﾘｽﾄ(4～3月)'!M$8:M$15),IF('内訳ﾘｽﾄ(4～3月)'!$D$5="工場間接",-J$68,0)) -> 0 | ... N72: =IF('内訳ﾘｽﾄ(4～3月)'!$D$5="製造",SUMIF('内訳ﾘｽﾄ(4～3月)'!$D$8:$D$15,$B72,'内訳ﾘｽﾄ(4～3月)'!Q$8:Q$15),IF('内訳ﾘｽﾄ(4～3月)'!$D$5="工場間接",-N$68,0)) -> 0 | O72: =IF('内訳ﾘｽﾄ(4～3月)'!$D$5="工場間接",-SUM(O$68),IF('内訳ﾘｽﾄ(4～3月)'!$D$5="製造",SUMIF('内訳ﾘｽﾄ(4～3月)'!$D$8:$D$15,'採算表(VND)'!$B72,'内訳ﾘｽﾄ(4～3月)'!$R$8:$R$15),0)) -> 0
B73: 定時間合計 | C73: =SUM(C68:C72) -> 0 | D73: =SUM(D68:D72) -> 0 | E73: =SUM(E68:E72) -> 0 | F73: =SUM(F68:F72) -> 0 | G73: =SUM(G68:G72) -> 0 | H73: =SUM(H68:H72) -> 0 | I73: =SUM(I68:I72) -> 0 | J73: =SUM(J68:J72) -> 0 | ... N73: =SUM(N68:N72) -> 0 | O73: =IF(ISBLANK(O4),"",SUM(O68:O72)) -> 0
B74: 直接部門 | C74: =SUMIF('内訳ﾘｽﾄ(4～3月)'!$D$16:$D$23,'採算表(VND)'!$B74,'内訳ﾘｽﾄ(4～3月)'!F$16:F$23) -> 5021 | D74: =SUMIF('内訳ﾘｽﾄ(4～3月)'!$D$16:$D$23,'採算表(VND)'!$B74,'内訳ﾘｽﾄ(4～3月)'!G$16:G$23) -> 5015 | E74: =SUMIF('内訳ﾘｽﾄ(4～3月)'!$D$16:$D$23,'採算表(VND)'!$B74,'内訳ﾘｽﾄ(4～3月)'!H$16:H$23) -> 5035 | F74: =SUMIF('内訳ﾘｽﾄ(4～3月)'!$D$16:$D$23,'採算表(VND)'!$B74,'内訳ﾘｽﾄ(4～3月)'!I$16:I$23) -> 763 | G74: =SUMIF('内訳ﾘｽﾄ(4～3月)'!$D$16:$D$23,'採算表(VND)'!$B74,'内訳ﾘｽﾄ(4～3月)'!J$16:J$23) -> 735 | H74: =SUMIF('内訳ﾘｽﾄ(4～3月)'!$D$16:$D$23,'採算表(VND)'!$B74,'内訳ﾘｽﾄ(4～3月)'!K$16:K$23) -> 735 | I74: =SUMIF('内訳ﾘｽﾄ(4～3月)'!$D$16:$D$23,'採算表(VND)'!$B74,'内訳ﾘｽﾄ(4～3月)'!L$16:L$23) -> 863 | J74: =SUMIF('内訳ﾘｽﾄ(4～3月)'!$D$16:$D$23,'採算表(VND)'!$B74,'内訳ﾘｽﾄ(4～3月)'!M$16:M$23) -> 845 | ... N74: =SUMIF('内訳ﾘｽﾄ(4～3月)'!$D$16:$D$23,'採算表(VND)'!$B74,'内訳ﾘｽﾄ(4～3月)'!Q$16:Q$23) -> 945 | O74: =SUMIF('内訳ﾘｽﾄ(4～3月)'!$D$16:$D$23,'採算表(VND)'!$B74,'内訳ﾘｽﾄ(4～3月)'!$R$16:$R$23) -> 22587
B75: 部内間接部門 | C75: =IF('内訳ﾘｽﾄ(4～3月)'!$D$5="製造",SUMIF('内訳ﾘｽﾄ(4～3月)'!$D$16:$D$23,$B75,'内訳ﾘｽﾄ(4～3月)'!F$16:F$23),IF('内訳ﾘｽﾄ(4～3月)'!$D$5="部内間接",-C$74,0)) -> -5021 | D75: =IF('内訳ﾘｽﾄ(4～3月)'!$D$5="製造",SUMIF('内訳ﾘｽﾄ(4～3月)'!$D$16:$D$23,$B75,'内訳ﾘｽﾄ(4～3月)'!G$16:G$23),IF('内訳ﾘｽﾄ(4～3月)'!$D$5="部内間接",-D$74,0)) -> -5015 | E75: =IF('内訳ﾘｽﾄ(4～3月)'!$D$5="製造",SUMIF('内訳ﾘｽﾄ(4～3月)'!$D$16:$D$23,$B75,'内訳ﾘｽﾄ(4～3月)'!H$16:H$23),IF('内訳ﾘｽﾄ(4～3月)'!$D$5="部内間接",-E$74,0)) -> -5035 | F75: =IF('内訳ﾘｽﾄ(4～3月)'!$D$5="製造",SUMIF('内訳ﾘｽﾄ(4～3月)'!$D$16:$D$23,$B75,'内訳ﾘｽﾄ(4～3月)'!I$16:I$23),IF('内訳ﾘｽﾄ(4～3月)'!$D$5="部内間接",-F$74,0)) -> -763 | G75: =IF('内訳ﾘｽﾄ(4～3月)'!$D$5="製造",SUMIF('内訳ﾘｽﾄ(4～3月)'!$D$16:$D$23,$B75,'内訳ﾘｽﾄ(4～3月)'!J$16:J$23),IF('内訳ﾘｽﾄ(4～3月)'!$D$5="部内間接",-G$74,0)) -> -735 | H75: =IF('内訳ﾘｽﾄ(4～3月)'!$D$5="製造",SUMIF('内訳ﾘｽﾄ(4～3月)'!$D$16:$D$23,$B75,'内訳ﾘｽﾄ(4～3月)'!K$16:K$23),IF('内訳ﾘｽﾄ(4～3月)'!$D$5="部内間接",-H$74,0)) -> -735 | I75: =IF('内訳ﾘｽﾄ(4～3月)'!$D$5="製造",SUMIF('内訳ﾘｽﾄ(4～3月)'!$D$16:$D$23,$B75,'内訳ﾘｽﾄ(4～3月)'!L$16:L$23),IF('内訳ﾘｽﾄ(4～3月)'!$D$5="部内間接",-I$74,0)) -> -863 | J75: =IF('内訳ﾘｽﾄ(4～3月)'!$D$5="製造",SUMIF('内訳ﾘｽﾄ(4～3月)'!$D$16:$D$23,$B75,'内訳ﾘｽﾄ(4～3月)'!M$16:M$23),IF('内訳ﾘｽﾄ(4～3月)'!$D$5="部内間接",-J$74,0)) -> -845 | ... N75: =IF('内訳ﾘｽﾄ(4～3月)'!$D$5="製造",SUMIF('内訳ﾘｽﾄ(4～3月)'!$D$16:$D$23,$B75,'内訳ﾘｽﾄ(4～3月)'!Q$16:Q$23),IF('内訳ﾘｽﾄ(4～3月)'!$D$5="部内間接",-N$74,0)) -> -945 | O75: =IF('内訳ﾘｽﾄ(4～3月)'!$D$5="部内間接",-SUM(O$74),IF('内訳ﾘｽﾄ(4～3月)'!$D$5="製造",SUMIF('内訳ﾘｽﾄ(4～3月)'!$D$16:$D$23,'採算表(VND)'!$B75,'内訳ﾘｽﾄ(4～3月)'!$R$16:$R$23),0)) -> -22587
B76: 部外間接部門1 | C76: =IF('内訳ﾘｽﾄ(4～3月)'!$D$5="製造",SUMIF('内訳ﾘｽﾄ(4～3月)'!$D$16:$D$23,$B76,'内訳ﾘｽﾄ(4～3月)'!F$16:F$23),IF('内訳ﾘｽﾄ(4～3月)'!$D$5="部外間接1",-C$74,0)) -> 0 | D76: =IF('内訳ﾘｽﾄ(4～3月)'!$D$5="製造",SUMIF('内訳ﾘｽﾄ(4～3月)'!$D$16:$D$23,$B76,'内訳ﾘｽﾄ(4～3月)'!G$16:G$23),IF('内訳ﾘｽﾄ(4～3月)'!$D$5="部外間接1",-D$74,0)) -> 0 | E76: =IF('内訳ﾘｽﾄ(4～3月)'!$D$5="製造",SUMIF('内訳ﾘｽﾄ(4～3月)'!$D$16:$D$23,$B76,'内訳ﾘｽﾄ(4～3月)'!H$16:H$23),IF('内訳ﾘｽﾄ(4～3月)'!$D$5="部外間接1",-E$74,0)) -> 0 | F76: =IF('内訳ﾘｽﾄ(4～3月)'!$D$5="製造",SUMIF('内訳ﾘｽﾄ(4～3月)'!$D$16:$D$23,$B76,'内訳ﾘｽﾄ(4～3月)'!I$16:I$23),IF('内訳ﾘｽﾄ(4～3月)'!$D$5="部外間接1",-F$74,0)) -> 0 | G76: =IF('内訳ﾘｽﾄ(4～3月)'!$D$5="製造",SUMIF('内訳ﾘｽﾄ(4～3月)'!$D$16:$D$23,$B76,'内訳ﾘｽﾄ(4～3月)'!J$16:J$23),IF('内訳ﾘｽﾄ(4～3月)'!$D$5="部外間接1",-G$74,0)) -> 0 | H76: =IF('内訳ﾘｽﾄ(4～3月)'!$D$5="製造",SUMIF('内訳ﾘｽﾄ(4～3月)'!$D$16:$D$23,$B76,'内訳ﾘｽﾄ(4～3月)'!K$16:K$23),IF('内訳ﾘｽﾄ(4～3月)'!$D$5="部外間接1",-H$74,0)) -> 0 | I76: =IF('内訳ﾘｽﾄ(4～3月)'!$D$5="製造",SUMIF('内訳ﾘｽﾄ(4～3月)'!$D$16:$D$23,$B76,'内訳ﾘｽﾄ(4～3月)'!L$16:L$23),IF('内訳ﾘｽﾄ(4～3月)'!$D$5="部外間接1",-I$74,0)) -> 0 | J76: =IF('内訳ﾘｽﾄ(4～3月)'!$D$5="製造",SUMIF('内訳ﾘｽﾄ(4～3月)'!$D$16:$D$23,$B76,'内訳ﾘｽﾄ(4～3月)'!M$16:M$23),IF('内訳ﾘｽﾄ(4～3月)'!$D$5="部外間接1",-J$74,0)) -> 0 | ... N76: =IF('内訳ﾘｽﾄ(4～3月)'!$D$5="製造",SUMIF('内訳ﾘｽﾄ(4～3月)'!$D$16:$D$23,$B76,'内訳ﾘｽﾄ(4～3月)'!Q$16:Q$23),IF('内訳ﾘｽﾄ(4～3月)'!$D$5="部外間接1",-N$74,0)) -> 0 | O76: =IF('内訳ﾘｽﾄ(4～3月)'!$D$5="部外間接1",-SUM(O$74),IF('内訳ﾘｽﾄ(4～3月)'!$D$5="製造",SUMIF('内訳ﾘｽﾄ(4～3月)'!$D$16:$D$23,'採算表(VND)'!$B76,'内訳ﾘｽﾄ(4～3月)'!$R$16:$R$23),0)) -> 0
B77: 部外間接部門2 | C77: =IF('内訳ﾘｽﾄ(4～3月)'!$D$5="製造",SUMIF('内訳ﾘｽﾄ(4～3月)'!$D$16:$D$23,$B77,'内訳ﾘｽﾄ(4～3月)'!F$16:F$23),IF('内訳ﾘｽﾄ(4～3月)'!$D$5="部外間接2",-C$74,0)) -> 0 | D77: =IF('内訳ﾘｽﾄ(4～3月)'!$D$5="製造",SUMIF('内訳ﾘｽﾄ(4～3月)'!$D$16:$D$23,$B77,'内訳ﾘｽﾄ(4～3月)'!G$16:G$23),IF('内訳ﾘｽﾄ(4～3月)'!$D$5="部外間接2",-D$74,0)) -> 0 | E77: =IF('内訳ﾘｽﾄ(4～3月)'!$D$5="製造",SUMIF('内訳ﾘｽﾄ(4～3月)'!$D$16:$D$23,$B77,'内訳ﾘｽﾄ(4～3月)'!H$16:H$23),IF('内訳ﾘｽﾄ(4～3月)'!$D$5="部外間接2",-E$74,0)) -> 0 | F77: =IF('内訳ﾘｽﾄ(4～3月)'!$D$5="製造",SUMIF('内訳ﾘｽﾄ(4～3月)'!$D$16:$D$23,$B77,'内訳ﾘｽﾄ(4～3月)'!I$16:I$23),IF('内訳ﾘｽﾄ(4～3月)'!$D$5="部外間接2",-F$74,0)) -> 0 | G77: =IF('内訳ﾘｽﾄ(4～3月)'!$D$5="製造",SUMIF('内訳ﾘｽﾄ(4～3月)'!$D$16:$D$23,$B77,'内訳ﾘｽﾄ(4～3月)'!J$16:J$23),IF('内訳ﾘｽﾄ(4～3月)'!$D$5="部外間接2",-G$74,0)) -> 0 | H77: =IF('内訳ﾘｽﾄ(4～3月)'!$D$5="製造",SUMIF('内訳ﾘｽﾄ(4～3月)'!$D$16:$D$23,$B77,'内訳ﾘｽﾄ(4～3月)'!K$16:K$23),IF('内訳ﾘｽﾄ(4～3月)'!$D$5="部外間接2",-H$74,0)) -> 0 | I77: =IF('内訳ﾘｽﾄ(4～3月)'!$D$5="製造",SUMIF('内訳ﾘｽﾄ(4～3月)'!$D$16:$D$23,$B77,'内訳ﾘｽﾄ(4～3月)'!L$16:L$23),IF('内訳ﾘｽﾄ(4～3月)'!$D$5="部外間接2",-I$74,0)) -> 0 | J77: =IF('内訳ﾘｽﾄ(4～3月)'!$D$5="製造",SUMIF('内訳ﾘｽﾄ(4～3月)'!$D$16:$D$23,$B77,'内訳ﾘｽﾄ(4～3月)'!M$16:M$23),IF('内訳ﾘｽﾄ(4～3月)'!$D$5="部外間接2",-J$74,0)) -> 0 | ... N77: =IF('内訳ﾘｽﾄ(4～3月)'!$D$5="製造",SUMIF('内訳ﾘｽﾄ(4～3月)'!$D$16:$D$23,$B77,'内訳ﾘｽﾄ(4～3月)'!Q$16:Q$23),IF('内訳ﾘｽﾄ(4～3月)'!$D$5="部外間接2",-N$74,0)) -> 0 | O77: =IF('内訳ﾘｽﾄ(4～3月)'!$D$5="部外間接2",-SUM(O$74),IF('内訳ﾘｽﾄ(4～3月)'!$D$5="製造",SUMIF('内訳ﾘｽﾄ(4～3月)'!$D$16:$D$23,'採算表(VND)'!$B77,'内訳ﾘｽﾄ(4～3月)'!$R$16:$R$23),0)) -> 0
B78: 工場間接部門 | C78: =IF('内訳ﾘｽﾄ(4～3月)'!$D$5="製造",SUMIF('内訳ﾘｽﾄ(4～3月)'!$D$16:$D$23,$B78,'内訳ﾘｽﾄ(4～3月)'!F$16:F$23),IF('内訳ﾘｽﾄ(4～3月)'!$D$5="工場間接",-C$74,0)) -> 0 | D78: =IF('内訳ﾘｽﾄ(4～3月)'!$D$5="製造",SUMIF('内訳ﾘｽﾄ(4～3月)'!$D$16:$D$23,$B78,'内訳ﾘｽﾄ(4～3月)'!G$16:G$23),IF('内訳ﾘｽﾄ(4～3月)'!$D$5="工場間接",-D$74,0)) -> 0 | E78: =IF('内訳ﾘｽﾄ(4～3月)'!$D$5="製造",SUMIF('内訳ﾘｽﾄ(4～3月)'!$D$16:$D$23,$B78,'内訳ﾘｽﾄ(4～3月)'!H$16:H$23),IF('内訳ﾘｽﾄ(4～3月)'!$D$5="工場間接",-E$74,0)) -> 0 | F78: =IF('内訳ﾘｽﾄ(4～3月)'!$D$5="製造",SUMIF('内訳ﾘｽﾄ(4～3月)'!$D$16:$D$23,$B78,'内訳ﾘｽﾄ(4～3月)'!I$16:I$23),IF('内訳ﾘｽﾄ(4～3月)'!$D$5="工場間接",-F$74,0)) -> 0 | G78: =IF('内訳ﾘｽﾄ(4～3月)'!$D$5="製造",SUMIF('内訳ﾘｽﾄ(4～3月)'!$D$16:$D$23,$B78,'内訳ﾘｽﾄ(4～3月)'!J$16:J$23),IF('内訳ﾘｽﾄ(4～3月)'!$D$5="工場間接",-G$74,0)) -> 0 | H78: =IF('内訳ﾘｽﾄ(4～3月)'!$D$5="製造",SUMIF('内訳ﾘｽﾄ(4～3月)'!$D$16:$D$23,$B78,'内訳ﾘｽﾄ(4～3月)'!K$16:K$23),IF('内訳ﾘｽﾄ(4～3月)'!$D$5="工場間接",-H$74,0)) -> 0 | I78: =IF('内訳ﾘｽﾄ(4～3月)'!$D$5="製造",SUMIF('内訳ﾘｽﾄ(4～3月)'!$D$16:$D$23,$B78,'内訳ﾘｽﾄ(4～3月)'!L$16:L$23),IF('内訳ﾘｽﾄ(4～3月)'!$D$5="工場間接",-I$74,0)) -> 0 | J78: =IF('内訳ﾘｽﾄ(4～3月)'!$D$5="製造",SUMIF('内訳ﾘｽﾄ(4～3月)'!$D$16:$D$23,$B78,'内訳ﾘｽﾄ(4～3月)'!M$16:M$23),IF('内訳ﾘｽﾄ(4～3月)'!$D$5="工場間接",-J$74,0)) -> 0 | ... N78: =IF('内訳ﾘｽﾄ(4～3月)'!$D$5="製造",SUMIF('内訳ﾘｽﾄ(4～3月)'!$D$16:$D$23,$B78,'内訳ﾘｽﾄ(4～3月)'!Q$16:Q$23),IF('内訳ﾘｽﾄ(4～3月)'!$D$5="工場間接",-N$74,0)) -> 0 | O78: =IF('内訳ﾘｽﾄ(4～3月)'!$D$5="工場間接",-SUM(O$74),IF('内訳ﾘｽﾄ(4～3月)'!$D$5="製造",SUMIF('内訳ﾘｽﾄ(4～3月)'!$D$16:$D$23,'採算表(VND)'!$B78,'内訳ﾘｽﾄ(4～3月)'!$R$16:$R$23),0)) -> 0
B79: 残業時間合計 | C79: =SUM(C74:C78) -> 0 | D79: =SUM(D74:D78) -> 0 | E79: =SUM(E74:E78) -> 0 | F79: =SUM(F74:F78) -> 0 | G79: =SUM(G74:G78) -> 0 | H79: =SUM(H74:H78) -> 0 | I79: =SUM(I74:I78) -> 0 | J79: =SUM(J74:J78) -> 0 | ... N79: =SUM(N74:N78) -> 0 | O79: =IF(ISBLANK(O10),"",SUM(O74:O78)) -> 0
B80: 当月時間当り | C80: =IFERROR(ROUNDDOWN(C66/C67,0),0) -> 0 | D80: =IFERROR(ROUNDDOWN(D66/D67,0),0) -> 0 | E80: =IFERROR(ROUNDDOWN(E66/E67,0),0) -> 0 | F80: =IFERROR(ROUNDDOWN(F66/F67,0),0) -> 0 | G80: =IFERROR(ROUNDDOWN(G66/G67,0),0) -> 0 | H80: =IFERROR(ROUNDDOWN(H66/H67,0),0) -> 0 | I80: =IFERROR(ROUNDDOWN(I66/I67,0),0) -> 0 | J80: =IFERROR(ROUNDDOWN(J66/J67,0),0) -> 0 | ... O80: =IFERROR(ROUNDDOWN(O66/O67,0),0) -> 0
B81: 時間当り生産高 | C81: =IFERROR(ROUNDDOWN(C12/C67,0),0) -> 0 | D81: =IFERROR(ROUNDDOWN(D12/D67,0),0) -> 0 | E81: =IFERROR(ROUNDDOWN(E12/E67,0),0) -> 0 | F81: =IFERROR(ROUNDDOWN(F12/F67,0),0) -> 0 | G81: =IFERROR(ROUNDDOWN(G12/G67,0),0) -> 0 | H81: =IFERROR(ROUNDDOWN(H12/H67,0),0) -> 0 | I81: =IFERROR(ROUNDDOWN(I12/I67,0),0) -> 0 | J81: =IFERROR(ROUNDDOWN(J12/J67,0),0) -> 0 | ... O81: =IFERROR(ROUNDDOWN(O12/O67,0),0) -> 0
B86: ■人員
B87: 出向社員(人) | C87: =SUMIF('内訳ﾘｽﾄ(4～3月)'!$D$24:$D$25,'採算表(VND)'!$B87,'内訳ﾘｽﾄ(4～3月)'!F$24:F$25) -> 2 | D87: =SUMIF('内訳ﾘｽﾄ(4～3月)'!$D$24:$D$25,'採算表(VND)'!$B87,'内訳ﾘｽﾄ(4～3月)'!G$24:G$25) -> 2 | E87: =SUMIF('内訳ﾘｽﾄ(4～3月)'!$D$24:$D$25,'採算表(VND)'!$B87,'内訳ﾘｽﾄ(4～3月)'!H$24:H$25) -> 2 | F87: =SUMIF('内訳ﾘｽﾄ(4～3月)'!$D$24:$D$25,'採算表(VND)'!$B87,'内訳ﾘｽﾄ(4～3月)'!I$24:I$25) -> 2 | G87: =SUMIF('内訳ﾘｽﾄ(4～3月)'!$D$24:$D$25,'採算表(VND)'!$B87,'内訳ﾘｽﾄ(4～3月)'!J$24:J$25) -> 2 | H87: =SUMIF('内訳ﾘｽﾄ(4～3月)'!$D$24:$D$25,'採算表(VND)'!$B87,'内訳ﾘｽﾄ(4～3月)'!K$24:K$25) -> 2 | I87: =SUMIF('内訳ﾘｽﾄ(4～3月)'!$D$24:$D$25,'採算表(VND)'!$B87,'内訳ﾘｽﾄ(4～3月)'!L$24:L$25) -> 2 | J87: =SUMIF('内訳ﾘｽﾄ(4～3月)'!$D$24:$D$25,'採算表(VND)'!$B87,'内訳ﾘｽﾄ(4～3月)'!M$24:M$25) -> 2 | ... O87: =SUMIF('内訳ﾘｽﾄ(4～3月)'!$D$24:$D$25,'採算表(VND)'!$B87,'内訳ﾘｽﾄ(4～3月)'!R$24:R$25) -> 2
B88: ローカル社員(人) | C88: =SUMIF('内訳ﾘｽﾄ(4～3月)'!$D$24:$D$25,'採算表(VND)'!$B88,'内訳ﾘｽﾄ(4～3月)'!F$24:F$25) -> 196 | D88: =SUMIF('内訳ﾘｽﾄ(4～3月)'!$D$24:$D$25,'採算表(VND)'!$B88,'内訳ﾘｽﾄ(4～3月)'!G$24:G$25) -> 196 | E88: =SUMIF('内訳ﾘｽﾄ(4～3月)'!$D$24:$D$25,'採算表(VND)'!$B88,'内訳ﾘｽﾄ(4～3月)'!H$24:H$25) -> 196 | F88: =SUMIF('内訳ﾘｽﾄ(4～3月)'!$D$24:$D$25,'採算表(VND)'!$B88,'内訳ﾘｽﾄ(4～3月)'!I$24:I$25) -> 26 | G88: =SUMIF('内訳ﾘｽﾄ(4～3月)'!$D$24:$D$25,'採算表(VND)'!$B88,'内訳ﾘｽﾄ(4～3月)'!J$24:J$25) -> 26 | H88: =SUMIF('内訳ﾘｽﾄ(4～3月)'!$D$24:$D$25,'採算表(VND)'!$B88,'内訳ﾘｽﾄ(4～3月)'!K$24:K$25) -> 26 | I88: =SUMIF('内訳ﾘｽﾄ(4～3月)'!$D$24:$D$25,'採算表(VND)'!$B88,'内訳ﾘｽﾄ(4～3月)'!L$24:L$25) -> 30 | J88: =SUMIF('内訳ﾘｽﾄ(4～3月)'!$D$24:$D$25,'採算表(VND)'!$B88,'内訳ﾘｽﾄ(4～3月)'!M$24:M$25) -> 30 | ... O88: =SUMIF('内訳ﾘｽﾄ(4～3月)'!$D$24:$D$25,'採算表(VND)'!$B88,'内訳ﾘｽﾄ(4～3月)'!R$24:R$25) -> 34
B89: 人員計 | C89: =C87+C88 -> 198 | D89: =D87+D88 -> 198 | E89: =E87+E88 -> 198 | F89: =F87+F88 -> 28 | G89: =G87+G88 -> 28 | H89: =H87+H88 -> 28 | I89: =I87+I88 -> 32 | J89: =J87+J88 -> 32 | ... O89: =O87+O88 -> 36
B91: ■定時間
B92: 出向社員定時 | C92: =SUMIF('内訳ﾘｽﾄ(4～3月)'!$B$8:$B$15,$B92,'内訳ﾘｽﾄ(4～3月)'!F$8:F$15) -> 323 | D92: =SUMIF('内訳ﾘｽﾄ(4～3月)'!$B$8:$B$15,$B92,'内訳ﾘｽﾄ(4～3月)'!G$8:G$15) -> 323 | E92: =SUMIF('内訳ﾘｽﾄ(4～3月)'!$B$8:$B$15,$B92,'内訳ﾘｽﾄ(4～3月)'!H$8:H$15) -> 357 | F92: =SUMIF('内訳ﾘｽﾄ(4～3月)'!$B$8:$B$15,$B92,'内訳ﾘｽﾄ(4～3月)'!I$8:I$15) -> 391 | G92: =SUMIF('内訳ﾘｽﾄ(4～3月)'!$B$8:$B$15,$B92,'内訳ﾘｽﾄ(4～3月)'!J$8:J$15) -> 297.5 | H92: =SUMIF('内訳ﾘｽﾄ(4～3月)'!$B$8:$B$15,$B92,'内訳ﾘｽﾄ(4～3月)'!K$8:K$15) -> 306 | I92: =SUMIF('内訳ﾘｽﾄ(4～3月)'!$B$8:$B$15,$B92,'内訳ﾘｽﾄ(4～3月)'!L$8:L$15) -> 391 | J92: =SUMIF('内訳ﾘｽﾄ(4～3月)'!$B$8:$B$15,$B92,'内訳ﾘｽﾄ(4～3月)'!M$8:M$15) -> 340 | ... O92: =SUMIF('内訳ﾘｽﾄ(4～3月)'!$B$8:$B$15,$B92,'内訳ﾘｽﾄ(4～3月)'!R$8:R$15) -> 3986.5
B93: ローカル社員定時 | C93: =SUMIF('内訳ﾘｽﾄ(4～3月)'!$B$8:$B$15,$B93,'内訳ﾘｽﾄ(4～3月)'!F$8:F$15) -> 31321 | D93: =SUMIF('内訳ﾘｽﾄ(4～3月)'!$B$8:$B$15,$B93,'内訳ﾘｽﾄ(4～3月)'!G$8:G$15) -> 29755 | E93: =SUMIF('内訳ﾘｽﾄ(4～3月)'!$B$8:$B$15,$B93,'内訳ﾘｽﾄ(4～3月)'!H$8:H$15) -> 32887 | F93: =SUMIF('内訳ﾘｽﾄ(4～3月)'!$B$8:$B$15,$B93,'内訳ﾘｽﾄ(4～3月)'!I$8:I$15) -> 4778 | G93: =SUMIF('内訳ﾘｽﾄ(4～3月)'!$B$8:$B$15,$B93,'内訳ﾘｽﾄ(4～3月)'!J$8:J$15) -> 4155 | H93: =SUMIF('内訳ﾘｽﾄ(4～3月)'!$B$8:$B$15,$B93,'内訳ﾘｽﾄ(4～3月)'!K$8:K$15) -> 3947 | I93: =SUMIF('内訳ﾘｽﾄ(4～3月)'!$B$8:$B$15,$B93,'内訳ﾘｽﾄ(4～3月)'!L$8:L$15) -> 5513 | J93: =SUMIF('内訳ﾘｽﾄ(4～3月)'!$B$8:$B$15,$B93,'内訳ﾘｽﾄ(4～3月)'!M$8:M$15) -> 4794 | ... O93: =SUMIF('内訳ﾘｽﾄ(4～3月)'!$B$8:$B$15,$B93,'内訳ﾘｽﾄ(4～3月)'!R$8:R$15) -> 136885
B94: 人員計 | C94: =C92+C93 -> 31644 | D94: =D92+D93 -> 30078 | E94: =E92+E93 -> 33244 | F94: =F92+F93 -> 5169 | G94: =G92+G93 -> 4452.5 | H94: =H92+H93 -> 4253 | I94: =I92+I93 -> 5904 | J94: =J92+J93 -> 5134 | ... O94: =O92+O93 -> 140871.5
B96: ■残業時間
B97: 出向社員残業 | C97: =SUMIF('内訳ﾘｽﾄ(4～3月)'!$B$16:$B$23,$B97,'内訳ﾘｽﾄ(4～3月)'!F$16:F$23) -> 76 | D97: =SUMIF('内訳ﾘｽﾄ(4～3月)'!$B$16:$B$23,$B97,'内訳ﾘｽﾄ(4～3月)'!G$16:G$23) -> 76 | E97: =SUMIF('内訳ﾘｽﾄ(4～3月)'!$B$16:$B$23,$B97,'内訳ﾘｽﾄ(4～3月)'!H$16:H$23) -> 84 | F97: =SUMIF('内訳ﾘｽﾄ(4～3月)'!$B$16:$B$23,$B97,'内訳ﾘｽﾄ(4～3月)'!I$16:I$23) -> 92 | G97: =SUMIF('内訳ﾘｽﾄ(4～3月)'!$B$16:$B$23,$B97,'内訳ﾘｽﾄ(4～3月)'!J$16:J$23) -> 70 | H97: =SUMIF('内訳ﾘｽﾄ(4～3月)'!$B$16:$B$23,$B97,'内訳ﾘｽﾄ(4～3月)'!K$16:K$23) -> 72 | I97: =SUMIF('内訳ﾘｽﾄ(4～3月)'!$B$16:$B$23,$B97,'内訳ﾘｽﾄ(4～3月)'!L$16:L$23) -> 92 | J97: =SUMIF('内訳ﾘｽﾄ(4～3月)'!$B$16:$B$23,$B97,'内訳ﾘｽﾄ(4～3月)'!M$16:M$23) -> 80 | ... O97: =SUMIF('内訳ﾘｽﾄ(4～3月)'!$B$16:$B$23,$B97,'内訳ﾘｽﾄ(4～3月)'!R$16:R$23) -> 938
B98: ローカル社員残業 | C98: =SUMIF('内訳ﾘｽﾄ(4～3月)'!$B$16:$B$23,$B98,'内訳ﾘｽﾄ(4～3月)'!F$16:F$23) -> 4945 | D98: =SUMIF('内訳ﾘｽﾄ(4～3月)'!$B$16:$B$23,$B98,'内訳ﾘｽﾄ(4～3月)'!G$16:G$23) -> 4939 | E98: =SUMIF('内訳ﾘｽﾄ(4～3月)'!$B$16:$B$23,$B98,'内訳ﾘｽﾄ(4～3月)'!H$16:H$23) -> 4951 | F98: =SUMIF('内訳ﾘｽﾄ(4～3月)'!$B$16:$B$23,$B98,'内訳ﾘｽﾄ(4～3月)'!I$16:I$23) -> 671 | G98: =SUMIF('内訳ﾘｽﾄ(4～3月)'!$B$16:$B$23,$B98,'内訳ﾘｽﾄ(4～3月)'!J$16:J$23) -> 665 | H98: =SUMIF('内訳ﾘｽﾄ(4～3月)'!$B$16:$B$23,$B98,'内訳ﾘｽﾄ(4～3月)'!K$16:K$23) -> 663 | I98: =SUMIF('内訳ﾘｽﾄ(4～3月)'!$B$16:$B$23,$B98,'内訳ﾘｽﾄ(4～3月)'!L$16:L$23) -> 771 | J98: =SUMIF('内訳ﾘｽﾄ(4～3月)'!$B$16:$B$23,$B98,'内訳ﾘｽﾄ(4～3月)'!M$16:M$23) -> 765 | ... O98: =SUMIF('内訳ﾘｽﾄ(4～3月)'!$B$16:$B$23,$B98,'内訳ﾘｽﾄ(4～3月)'!R$16:R$23) -> 21649
B99: 人員計 | C99: =C97+C98 -> 5021 | D99: =D97+D98 -> 5015 | E99: =E97+E98 -> 5035 | F99: =F97+F98 -> 763 | G99: =G97+G98 -> 735 | H99: =H97+H98 -> 735 | I99: =I97+I98 -> 863 | J99: =J97+J98 -> 845 | ... O99: =O97+O98 -> 22587

Sheet 内訳ﾘｽﾄ(4～3月)
A1: MP FY2026_各予定
B2: 25390 | E2: 稼働日数 | F2: =OFFSET(稼働日!$B$2,MATCH('内訳ﾘｽﾄ(4～3月)'!F4,稼働日!$A$3:$A$14,0),0) -> 20 | G2: =OFFSET(稼働日!$B$2,MATCH('内訳ﾘｽﾄ(4～3月)'!G4,稼働日!$A$3:$A$14,0),0) -> 19 | H2: =OFFSET(稼働日!$B$2,MATCH('内訳ﾘｽﾄ(4～3月)'!H4,稼働日!$A$3:$A$14,0),0) -> 21 | I2: =OFFSET(稼働日!$B$2,MATCH('内訳ﾘｽﾄ(4～3月)'!I4,稼働日!$A$3:$A$14,0),0) -> 23 | J2: =OFFSET(稼働日!$B$2,MATCH('内訳ﾘｽﾄ(4～3月)'!J4,稼働日!$A$3:$A$14,0),0) -> 20 | K2: =OFFSET(稼働日!$B$2,MATCH('内訳ﾘｽﾄ(4～3月)'!K4,稼働日!$A$3:$A$14,0),0) -> 19 | L2: =OFFSET(稼働日!$B$2,MATCH('内訳ﾘｽﾄ(4～3月)'!L4,稼働日!$A$3:$A$14,0),0) -> 23 | M2: =OFFSET(稼働日!$B$2,MATCH('内訳ﾘｽﾄ(4～3月)'!M4,稼働日!$A$3:$A$14,0),0) -> 20 | ... Q2: =OFFSET(稼働日!$B$2,MATCH('内訳ﾘｽﾄ(4～3月)'!Q4,稼働日!$A$3:$A$14,0),0) -> 20
E3: CHECK | F3: {=IF(SUM((F8:F25)-ROUNDDOWN((F8:F25)*4,0)/4)<>0,"時間➝0.25の倍数では無い",IF(SUM(ROUND((F26:F1004),0)-ROUND((F26:F1004),4))<>0,"経費➝小数点",IF(F5<>IF($D$5="製造",'採算表(VND)'!C13,-VLOOKUP($D$5&"経費",'採算表(VND)'!$B:$N,'採算表(VND)'!C3,0)),"経費➝NG","OK")))} -> OK | G3: {=IF(SUM((G8:G25)-ROUNDDOWN((G8:G25)*4,0)/4)<>0,"時間➝0.25の倍数では無い",IF(SUM(ROUND((G26:G1004),0)-ROUND((G26:G1004),4))<>0,"経費➝小数点",IF(G5<>IF($D$5="製造",'採算表(VND)'!D13,-VLOOKUP($D$5&"経費",'採算表(VND)'!$B:$N,'採算表(VND)'!D3,0)),"経費➝NG","OK")))} -> OK | H3: {=IF(SUM((H8:H25)-ROUNDDOWN((H8:H25)*4,0)/4)<>0,"時間➝0.25の倍数では無い",IF(SUM(ROUND((H26:H1004),0)-ROUND((H26:H1004),4))<>0,"経費➝小数点",IF(H5<>IF($D$5="製造",'採算表(VND)'!E13,-VLOOKUP($D$5&"経費",'採算表(VND)'!$B:$N,'採算表(VND)'!E3,0)),"経費➝NG","OK")))} -> OK | I3: {=IF(SUM((I8:I25)-ROUNDDOWN((I8:I25)*4,0)/4)<>0,"時間➝0.25の倍数では無い",IF(SUM(ROUND((I26:I1004),0)-ROUND((I26:I1004),4))<>0,"経費➝小数点",IF(I5<>IF($D$5="製造",'採算表(VND)'!F13,-VLOOKUP($D$5&"経費",'採算表(VND)'!$B:$N,'採算表(VND)'!F3,0)),"経費➝NG","OK")))} -> OK | J3: {=IF(SUM((J8:J25)-ROUNDDOWN((J8:J25)*4,0)/4)<>0,"時間➝0.25の倍数では無い",IF(SUM(ROUND((J26:J1004),0)-ROUND((J26:J1004),4))<>0,"経費➝小数点",IF(J5<>IF($D$5="製造",'採算表(VND)'!G13,-VLOOKUP($D$5&"経費",'採算表(VND)'!$B:$N,'採算表(VND)'!G3,0)),"経費➝NG","OK")))} -> OK | K3: {=IF(SUM((K8:K25)-ROUNDDOWN((K8:K25)*4,0)/4)<>0,"時間➝0.25の倍数では無い",IF(SUM(ROUND((K26:K1004),0)-ROUND((K26:K1004),4))<>0,"経費➝小数点",IF(K5<>IF($D$5="製造",'採算表(VND)'!H13,-VLOOKUP($D$5&"経費",'採算表(VND)'!$B:$N,'採算表(VND)'!H3,0)),"経費➝NG","OK")))} -> OK | L3: {=IF(SUM((L8:L25)-ROUNDDOWN((L8:L25)*4,0)/4)<>0,"時間➝0.25の倍数では無い",IF(SUM(ROUND((L26:L1004),0)-ROUND((L26:L1004),4))<>0,"経費➝小数点",IF(L5<>IF($D$5="製造",'採算表(VND)'!I13,-VLOOKUP($D$5&"経費",'採算表(VND)'!$B:$N,'採算表(VND)'!I3,0)),"経費➝NG","OK")))} -> OK | M3: {=IF(SUM((M8:M25)-ROUNDDOWN((M8:M25)*4,0)/4)<>0,"時間➝0.25の倍数では無い",IF(SUM(ROUND((M26:M1004),0)-ROUND((M26:M1004),4))<>0,"経費➝小数点",IF(M5<>IF($D$5="製造",'採算表(VND)'!J13,-VLOOKUP($D$5&"経費",'採算表(VND)'!$B:$N,'採算表(VND)'!J3,0)),"経費➝NG","OK")))} -> OK | ... Q3: {=IF(SUM((Q8:Q25)-ROUNDDOWN((Q8:Q25)*4,0)/4)<>0,"時間➝0.25の倍数では無い",IF(SUM(ROUND((Q26:Q1004),0)-ROUND((Q26:Q1004),4))<>0,"経費➝小数点",IF(Q5<>IF($D$5="製造",'採算表(VND)'!N13,-VLOOKUP($D$5&"経費",'採算表(VND)'!$B:$N,'採算表(VND)'!N3,0)),"経費➝NG","OK")))} -> OK
B4: 原価センター | C4: 組織名 | D4: 採算区分 | E4: 原価区分 | F4: 4 | G4: 5 | H4: 6 | I4: 7 | J4: 8 | K4: 9 | L4: 10 | M4: 11 | N4: 12 | O4: 1 | P4: 2 | Q4: 3 | R4: 合計 | S4: ※MEBIUS経費になると "V02V0800" は T列に 反映お願いします
B5: 1412000053 | C5: =VLOOKUP($B$5,原価センタ!$A:$E,2,0) -> 工程品質管理1課 | D5: =VLOOKUP($B$5,原価センタ!$A:$E,4,0) -> 部内間接 | E5: =VLOOKUP($B$5,原価センタ!$A:$E,5,0) -> 製造 | F5: =SUM(F29:F1004) -> 511006405 | G5: =SUM(G29:G1004) -> 736447527 | H5: =SUM(H29:H1004) -> 329640069 | I5: =SUM(I29:I1004) -> 295575098 | J5: =SUM(J29:J1004) -> 122869681 | K5: =SUM(K29:K1004) -> 127855273 | L5: =SUM(L29:L1004) -> 106916421 | M5: =SUM(M29:M1004) -> 101679511 | ... R5: =SUM(R29:R1004) -> 2714812100
C7: 勘定科目名称 | D7: 採算科目 | E7: ﾃｰﾏｺｰﾄﾞ | F7: MP | G7: MP | H7: MP | I7: MP | J7: MP | K7: MP | L7: MP | M7: MP | N7: MP | O7: MP | P7: MP | Q7: MP | R7: MP | S7: 備考 | T7: WBS | BC7: WBS
B8: 出向社員定時 | C8: 定時間（日本社員） | D8: 直接部門 | F8: 323 | G8: 323 | H8: 357 | I8: 391 | J8: 297.5 | K8: 306 | L8: 391 | M8: 340 | N8: 357 | O8: 306 | P8: 255 | Q8: 340 | R8: =SUM(F8:Q8) -> 3986.5
B9: ローカル社員定時 | C9: 定時間（ベトナム社員） | D9: 直接部門 | F9: 31321 | G9: 29755 | H9: 32887 | I9: 4778 | J9: 4155 | K9: 3947 | L9: 5513 | M9: 4794 | N9: 5273 | O9: 4954 | P9: 4075 | Q9: 5433 | R9: =SUM(F9:Q9) -> 136885
B10: 出向社員定時 | C10: 定時間（移動分日本社員） | D10: 直接部門 | R10: =SUM(F10:Q10) -> 0
B11: ローカル社員定時 | C11: 定時間（移動分ベトナム社員） | D11: 直接部門 | R11: =SUM(F11:Q11) -> 0
C12: 定時間（部内間接部門） | D12: 部内間接部門 | R12: =SUM(F12:Q12) -> 0 | S12: この分には間接部門から直接部門に配賦された数字
C13: 定時間（部外間接部門1） | D13: 部外間接部門1 | R13: =SUM(F13:Q13) -> 0 | S13: この分には間接部門から直接部門に配賦された数字
C14: 定時間（部外間接部門2） | D14: 部外間接部門2 | R14: =SUM(F14:Q14) -> 0 | S14: この分には間接部門から直接部門に配賦された数字
C15: 定時間（工場間接部門） | D15: 工場間接部門 | R15: =SUM(F15:Q15) -> 0 | S15: この分には間接部門から直接部門に配賦された数字
B16: 出向社員残業 | C16: 残業時間（日本社員） | D16: 直接部門 | F16: 76 | G16: 76 | H16: 84 | I16: 92 | J16: 70 | K16: 72 | L16: 92 | M16: 80 | N16: 84 | O16: 72 | P16: 60 | Q16: 80 | R16: =SUM(F16:Q16) -> 938
B17: ローカル社員残業 | C17: 残業時間（ベトナム社員） | D17: 直接部門 | F17: 4945 | G17: 4939 | H17: 4951 | I17: 671 | J17: 665 | K17: 663 | L17: 771 | M17: 765 | N17: 769 | O17: 790 | P17: 855 | Q17: 865 | R17: =SUM(F17:Q17) -> 21649
B18: 出向社員残業 | C18: 残業時間（移動分日本社員） | D18: 直接部門 | R18: =SUM(F18:Q18) -> 0
B19: ローカル社員残業 | C19: 残業時間（移動分ベトナム社員） | D19: 直接部門 | R19: =SUM(F19:Q19) -> 0
C20: 残業時間（部内間接部門） | D20: 部内間接部門 | R20: =SUM(F20:Q20) -> 0 | S20: この分には間接部門から直接部門に配賦された数字
C21: 残業時間（部外間接部門1） | D21: 部外間接部門1 | R21: =SUM(F21:Q21) -> 0 | S21: この分には間接部門から直接部門に配賦された数字
C22: 残業時間（部外間接部門2） | D22: 部外間接部門2 | R22: =SUM(F22:Q22) -> 0 | S22: この分には間接部門から直接部門に配賦された数字
C23: 残業時間（工場間接部門） | D23: 工場間接部門 | R23: =SUM(F23:Q23) -> 0 | S23: この分には間接部門から直接部門に配賦された数字
B24: 出向社員(人) | C24: 出向社員(人) | D24: 出向社員(人) | F24: 2 | G24: 2 | H24: 2 | I24: 2 | J24: 2 | K24: 2 | L24: 2 | M24: 2 | N24: 2 | O24: 2 | P24: 2 | Q24: 2 | R24: =Q24 -> 2
B25: ローカル社員(人) | C25: ローカル社員(人) | D25: ローカル社員(人) | F25: 196 | G25: 196 | H25: 196 | I25: 26 | J25: 26 | K25: 26 | L25: 30 | M25: 30 | N25: 30 | O25: 31 | P25: 34 | Q25: 34 | R25: =Q25 -> 34 | V25: 4 | W25: 5 | X25: 6 | Y25: 7 | Z25: 8 | AA25: 9 | AB25: 10 | AC25: 11 | AD25: 12 | AE25: 1 | AF25: 2 | AG25: 3
B26: 9114120002 | C26: =IFERROR(IF(VLOOKUP($B26,勘定科目!$A:$H,HLOOKUP($E$5,勘定科目!$F$1:$H$2,2,0),0)="","",VLOOKUP($B26,勘定科目!$A:$E,2,0)),"") -> 社外出荷 | D26: =IF(C26="","",VLOOKUP($B26,勘定科目!$A:$E,4,0)) -> 社外出荷 | F26: =ROUNDDOWN(V26*$B$2,0) -> 0 | G26: =ROUNDDOWN(W26*$B$2,0) -> 0 | H26: =ROUNDDOWN(X26*$B$2,0) -> 0 | I26: =ROUNDDOWN(Y26*$B$2,0) -> 0 | J26: =ROUNDDOWN(Z26*$B$2,0) -> 0 | K26: =ROUNDDOWN(AA26*$B$2,0) -> 0 | L26: =ROUNDDOWN(AB26*$B$2,0) -> 0 | M26: =ROUNDDOWN(AC26*$B$2,0) -> 0 | ... Q26: =ROUNDDOWN(AG26*$B$2,0) -> 0 | R26: =SUM(F26:Q26) -> 0 | S26: 総生産
B27: 9114120004 | C27: =IFERROR(IF(VLOOKUP($B27,勘定科目!$A:$H,HLOOKUP($E$5,勘定科目!$F$1:$H$2,2,0),0)="","",VLOOKUP($B27,勘定科目!$A:$E,2,0)),"") -> 社内売 | D27: =IF(C27="","",VLOOKUP($B27,勘定科目!$A:$E,4,0)) -> 社内売 | F27: =ROUNDDOWN(V27*$B$2,0) -> 0 | G27: =ROUNDDOWN(W27*$B$2,0) -> 0 | H27: =ROUNDDOWN(X27*$B$2,0) -> 0 | I27: =ROUNDDOWN(Y27*$B$2,0) -> 0 | J27: =ROUNDDOWN(Z27*$B$2,0) -> 0 | K27: =ROUNDDOWN(AA27*$B$2,0) -> 0 | L27: =ROUNDDOWN(AB27*$B$2,0) -> 0 | M27: =ROUNDDOWN(AC27*$B$2,0) -> 0 | ... Q27: =ROUNDDOWN(AG27*$B$2,0) -> 0 | R27: =SUM(F27:Q27) -> 0 | S27: 総生産
B28: 9114120014 | C28: =IFERROR(IF(VLOOKUP($B28,勘定科目!$A:$H,HLOOKUP($E$5,勘定科目!$F$1:$H$2,2,0),0)="","",VLOOKUP($B28,勘定科目!$A:$E,2,0)),"") -> 社内買 | D28: =IF(C28="","",VLOOKUP($B28,勘定科目!$A:$E,4,0)) -> 社内買 | F28: =ROUNDDOWN(V28*$B$2,0) -> 0 | G28: =ROUNDDOWN(W28*$B$2,0) -> 0 | H28: =ROUNDDOWN(X28*$B$2,0) -> 0 | I28: =ROUNDDOWN(Y28*$B$2,0) -> 0 | J28: =ROUNDDOWN(Z28*$B$2,0) -> 0 | K28: =ROUNDDOWN(AA28*$B$2,0) -> 0 | L28: =ROUNDDOWN(AB28*$B$2,0) -> 0 | M28: =ROUNDDOWN(AC28*$B$2,0) -> 0 | ... Q28: =ROUNDDOWN(AG28*$B$2,0) -> 0 | R28: =SUM(F28:Q28) -> 0 | S28: 総生産
B29: 9114120006 | C29: =IFERROR(IF(VLOOKUP($B29,勘定科目!$A:$H,HLOOKUP($E$5,勘定科目!$F$1:$H$2,2,0),0)="","",VLOOKUP($B29,勘定科目!$A:$E,2,0)),"") -> 材料費(指図出庫） | D29: =IF(C29="","",VLOOKUP($B29,勘定科目!$A:$E,4,0)) -> 材料費 | F29: =ROUNDUP(V29*$B$2,0) -> 0 | G29: =ROUNDUP(W29*$B$2,0) -> 0 | H29: =ROUNDUP(X29*$B$2,0) -> 0 | I29: =ROUNDUP(Y29*$B$2,0) -> 0 | J29: =ROUNDUP(Z29*$B$2,0) -> 0 | K29: =ROUNDUP(AA29*$B$2,0) -> 0 | L29: =ROUNDUP(AB29*$B$2,0) -> 0 | M29: =ROUNDUP(AC29*$B$2,0) -> 0 | ... Q29: =ROUNDUP(AG29*$B$2,0) -> 0 | R29: =SUM(F29:Q29) -> 0 | S29: 総生産
C30: =IFERROR(IF(VLOOKUP($B30,勘定科目!$A:$H,HLOOKUP($E$5,勘定科目!$F$1:$H$2,2,0),0)="","",VLOOKUP($B30,勘定科目!$A:$E,2,0)),"") | D30: =IF(C30="","",VLOOKUP($B30,勘定科目!$A:$E,4,0)) | R30: =SUM(F30:Q30) -> 0
B31: 9114120018 | C31: =IFERROR(IF(VLOOKUP($B31,勘定科目!$A:$H,HLOOKUP($E$5,勘定科目!$F$1:$H$2,2,0),0)="","",VLOOKUP($B31,勘定科目!$A:$E,2,0)),"") -> 部内間接経費 | D31: =IF(C31="","",VLOOKUP($B31,勘定科目!$A:$E,4,0)) -> 部内間接経費 | R31: =SUM(F31:Q31) -> 0 | S31: この分には間接部門から直接部門に配賦された数字
B32: 9114120029 | C32: =IFERROR(IF(VLOOKUP($B32,勘定科目!$A:$H,HLOOKUP($E$5,勘定科目!$F$1:$H$2,2,0),0)="","",VLOOKUP($B32,勘定科目!$A:$E,2,0)),"") -> 部外間接経費1 | D32: =IF(C32="","",VLOOKUP($B32,勘定科目!$A:$E,4,0)) -> 部外間接経費1 | R32: =SUM(F32:Q32) -> 0 | S32: この分には間接部門から直接部門に配賦された数字
B33: 9114120030 | C33: =IFERROR(IF(VLOOKUP($B33,勘定科目!$A:$H,HLOOKUP($E$5,勘定科目!$F$1:$H$2,2,0),0)="","",VLOOKUP($B33,勘定科目!$A:$E,2,0)),"") -> 部外間接経費2 | D33: =IF(C33="","",VLOOKUP($B33,勘定科目!$A:$E,4,0)) -> 部外間接経費2 | R33: =SUM(F33:Q33) -> 0 | S33: この分には間接部門から直接部門に配賦された数字
B34: 9114120021 | C34: =IFERROR(IF(VLOOKUP($B34,勘定科目!$A:$H,HLOOKUP($E$5,勘定科目!$F$1:$H$2,2,0),0)="","",VLOOKUP($B34,勘定科目!$A:$E,2,0)),"") -> 工場間接経費 | D34: =IF(C34="","",VLOOKUP($B34,勘定科目!$A:$E,4,0)) -> 工場間接経費 | R34: =SUM(F34:Q34) -> 0 | S34: この分には間接部門から直接部門に配賦された数字
C35: =IFERROR(IF(VLOOKUP($B35,勘定科目!$A:$H,HLOOKUP($E$5,勘定科目!$F$1:$H$2,2,0),0)="","",VLOOKUP($B35,勘定科目!$A:$E,2,0)),"") | D35: =IF(C35="","",VLOOKUP($B35,勘定科目!$A:$E,4,0)) | R35: =SUM(F35:Q35) -> 0
B36: 9114120009 | C36: =IFERROR(IF(VLOOKUP($B36,勘定科目!$A:$H,HLOOKUP($E$5,勘定科目!$F$1:$H$2,2,0),0)="","",VLOOKUP($B36,勘定科目!$A:$E,2,0)),"") -> 社内金利（在庫） | D36: =IF(C36="","",VLOOKUP($B36,勘定科目!$A:$E,4,0)) -> 在庫金利 | R36: =SUM(F36:Q36) -> 0 | S36: LIBRA 2 PMT 在庫金利
C37: =IFERROR(IF(VLOOKUP($B37,勘定科目!$A:$H,HLOOKUP($E$5,勘定科目!$F$1:$H$2,2,0),0)="","",VLOOKUP($B37,勘定科目!$A:$E,2,0)),"") | D37: =IF(C37="","",VLOOKUP($B37,勘定科目!$A:$E,4,0)) | R37: =SUM(F37:Q37) -> 0
C38: =IFERROR(IF(VLOOKUP($B38,勘定科目!$A:$H,HLOOKUP($E$5,勘定科目!$F$1:$H$2,2,0),0)="","",VLOOKUP($B38,勘定科目!$A:$E,2,0)),"") | D38: =IF(C38="","",VLOOKUP($B38,勘定科目!$A:$E,4,0)) | R38: =SUM(F38:Q38) -> 0
B39: 9114120007 | C39: =IFERROR(IF(VLOOKUP($B39,勘定科目!$A:$H,HLOOKUP($E$5,勘定科目!$F$1:$H$2,2,0),0)="","",VLOOKUP($B39,勘定科目!$A:$E,2,0)),"") -> 社内金利（固定資産） | D39: =IF(C39="","",VLOOKUP($B39,勘定科目!$A:$E,4,0)) -> 固定資産金利 | R39: =SUM(F39:Q39) -> 0 | S39: 粉塵計測器 Máy đếm bụi
B40: 9114120007 | C40: =IFERROR(IF(VLOOKUP($B40,勘定科目!$A:$H,HLOOKUP($E$5,勘定科目!$F$1:$H$2,2,0),0)="","",VLOOKUP($B40,勘定科目!$A:$E,2,0)),"") -> 社内金利（固定資産） | D40: =IF(C40="","",VLOOKUP($B40,勘定科目!$A:$E,4,0)) -> 固定資産金利 | R40: =SUM(F40:Q40) -> 0 | S40: ライトĐèn pin Lãi
B41: 9114120007 | C41: =IFERROR(IF(VLOOKUP($B41,勘定科目!$A:$H,HLOOKUP($E$5,勘定科目!$F$1:$H$2,2,0),0)="","",VLOOKUP($B41,勘定科目!$A:$E,2,0)),"") -> 社内金利（固定資産） | D41: =IF(C41="","",VLOOKUP($B41,勘定科目!$A:$E,4,0)) -> 固定資産金利 | F41: =ROUND(1619.79*25390,0) -> 41126468 | G41: =ROUND(1529.32*25390,0) -> 38829435 | H41: =ROUND(1534.83*25390,0) -> 38969334 | I41: =ROUND(1493.85*25390,0) -> 37928852 | J41: =ROUND(737.76*25390,0) -> 18731726 | K41: =ROUND(720.04*25390,0)-254 -> 18281562 | L41: =ROUND(711.72*25390,0)-254 -> 18070317 | M41: =ROUND(710.23*25390,0)+253 -> 18032993 | N41: =ROUND(711.31*25390,0)+1 -> 18060162 | O41: =ROUND(708.23*25390,0) -> 17981960 | P41: =ROUND(710.48*25390,0) -> 18039087 | Q41: =ROUND(722.6*25390,0)+254 -> 18347068 | R41: =SUM(F41:Q41) -> 302398964 | S41: 固定資産金利/Interest (建物Building) Lãi TSCĐ ( Nhà) | BD41: #REF!
B42: 9114120007 | C42: =IFERROR(IF(VLOOKUP($B42,勘定科目!$A:$H,HLOOKUP($E$5,勘定科目!$F$1:$H$2,2,0),0)="","",VLOOKUP($B42,勘定科目!$A:$E,2,0)),"") -> 社内金利（固定資産） | D42: =IF(C42="","",VLOOKUP($B42,勘定科目!$A:$E,4,0)) -> 固定資産金利 | F42: =ROUND(200.28*25390,0) -> 5085109 | G42: =ROUND(193.9*25390,0) -> 4923121 | H42: =ROUND(194.6*25390,0) -> 4940894 | I42: =ROUND(189.41*25390,0) -> 4809120 | J42: =ROUND(93.54*25390,0) -> 2374981 | K42: =ROUND(91.29*25390,0) -> 2317853 | L42: =ROUND(90.24*25390,0) -> 2291194 | M42: =ROUND(90.05*25390,0)-1 -> 2286369 | N42: =ROUND(90.19*25390,0)+1 -> 2289925 | O42: =ROUND(89.79*25390,0)+253 -> 2280021 | P42: =ROUND(90.08*25390,0) -> 2287131 | Q42: =ROUND(91.62*25390,0) -> 2326232 | R42: =SUM(F42:Q42) -> 38211950 | S42: 固定資産金利 /Interest(土地 Land) Lãi TSCĐ ( Đất) | BD42: #REF!
C43: =IFERROR(IF(VLOOKUP($B43,勘定科目!$A:$H,HLOOKUP($E$5,勘定科目!$F$1:$H$2,2,0),0)="","",VLOOKUP($B43,勘定科目!$A:$E,2,0)),"") | D43: =IF(C43="","",VLOOKUP($B43,勘定科目!$A:$E,4,0)) | R43: =SUM(F43:Q43) -> 0 | BD43: #REF!
B44: 5005246282 | C44: =IFERROR(IF(VLOOKUP($B44,勘定科目!$A:$H,HLOOKUP($E$5,勘定科目!$F$1:$H$2,2,0),0)="","",VLOOKUP($B44,勘定科目!$A:$E,2,0)),"") -> ＫＤＣシステム使用料（製） | D44: =IF(C44="","",VLOOKUP($B44,勘定科目!$A:$E,4,0)) -> 図書及び事務費 | F44: =ROUND((3.18+11.46*36+91.58+34.98*3)*25359,0) -> 15526301 | G44: =ROUND((3.18+11.46*36+91.58+34.98*3)*25359,0) -> 15526301 | H44: =ROUND((3.18+11.46*36+91.58+34.98*3)*25359,0) -> 15526301 | I44: =ROUND((3.18+11.46*36+91.58+34.98*3)*25359,0) -> 15526301 | J44: =ROUND((3.18+11.46*16+91.58+34.98*3)*25359,0) -> 9714019 | K44: =ROUND((3.18+11.46*16+91.58+34.98*3)*25359,0) -> 9714019 | L44: =ROUND((3.18+11.46*16+91.58+34.98*3)*25359,0) -> 9714019 | M44: =ROUND((3.18+11.46*(16+2)+91.58+34.98*3)*25359,0)+1 -> 10295248 | N44: =ROUND((3.18+11.46*(16+2)+91.58+34.98*3)*25359,0)+1 -> 10295248 | O44: =ROUND((3.18+11.46*(16+2)+91.58+34.98*3)*25359,0)+1 -> 10295248 | P44: =ROUND((3.18+11.46*(16+2+1)+91.58+34.98*3)*25359,0)+1 -> 10585862 | Q44: =ROUND((3.18+11.46*(16+2+1)+91.58+34.98*3)*25359,0)+1 -> 10585862 | R44: =SUM(F44:Q44) -> 143304729 | S44: システム 使用費 CP sử dụng hệ thống (2024年4月から：-PLM) | BD44: #REF!
B45: 5005246283 | C45: =IFERROR(IF(VLOOKUP($B45,勘定科目!$A:$H,HLOOKUP($E$5,勘定科目!$F$1:$H$2,2,0),0)="","",VLOOKUP($B45,勘定科目!$A:$E,2,0)),"") -> ライセンス料（製） | D45: =IF(C45="","",VLOOKUP($B45,勘定科目!$A:$E,4,0)) -> 図書及び事務費 | R45: =SUM(F45:Q45) -> 0 | S45: 07月：WINのライセンス | BD45: #REF!
C46: =IFERROR(IF(VLOOKUP($B46,勘定科目!$A:$H,HLOOKUP($E$5,勘定科目!$F$1:$H$2,2,0),0)="","",VLOOKUP($B46,勘定科目!$A:$E,2,0)),"") | D46: =IF(C46="","",VLOOKUP($B46,勘定科目!$A:$E,4,0)) | R46: =SUM(F46:Q46) -> 0 | BD46: #REF!
B47: 5006016244 | C47: =IFERROR(IF(VLOOKUP($B47,勘定科目!$A:$H,HLOOKUP($E$5,勘定科目!$F$1:$H$2,2,0),0)="","",VLOOKUP($B47,勘定科目!$A:$E,2,0)),"") -> 減価償却費（製） 工具器具備品 | D47: =IF(C47="","",VLOOKUP($B47,勘定科目!$A:$E,4,0)) -> 減価償却費 | R47: =SUM(F47:Q47) -> 0 | BD47: #REF!
B48: 5006016244 | C48: =IFERROR(IF(VLOOKUP($B48,勘定科目!$A:$H,HLOOKUP($E$5,勘定科目!$F$1:$H$2,2,0),0)="","",VLOOKUP($B48,勘定科目!$A:$E,2,0)),"") -> 減価償却費（製） 工具器具備品 | D48: =IF(C48="","",VLOOKUP($B48,勘定科目!$A:$E,4,0)) -> 減価償却費 | R48: =SUM(F48:Q48) -> 0 | S48: 粉塵計測器 Máy đếm bụi | BD48: #REF!
B49: 5006016247 | C49: =IFERROR(IF(VLOOKUP($B49,勘定科目!$A:$H,HLOOKUP($E$5,勘定科目!$F$1:$H$2,2,0),0)="","",VLOOKUP($B49,勘定科目!$A:$E,2,0)),"") -> 減価償却費（製） その他有形固定資産 | D49: =IF(C49="","",VLOOKUP($B49,勘定科目!$A:$E,4,0)) -> 減価償却費 | R49: =SUM(F49:Q49) -> 0 | S49: ライト Đèn pin | BD49: #REF!
B50: 5006016260 | C50: =IFERROR(IF(VLOOKUP($B50,勘定科目!$A:$H,HLOOKUP($E$5,勘定科目!$F$1:$H$2,2,0),0)="","",VLOOKUP($B50,勘定科目!$A:$E,2,0)),"") -> 減価償却費配賦（製） 建物 | D50: =IF(C50="","",VLOOKUP($B50,勘定科目!$A:$E,4,0)) -> 減価償却費 | F50: =ROUND(2386.32*25390,0) -> 60588665 | G50: =ROUND(2379.22*25390,0) -> 60408396 | H50: =ROUND(2387.79*25390,0) -> 60625988 | I50: =ROUND(2324.04*25390,0) -> 59007376 | J50: =ROUND(1147.76*25390,0) -> 29141626 | K50: =ROUND(1120.19*25390,0)-1 -> 28441623 | L50: =ROUND(1107.25*25390,0)-1 -> 28113077 | M50: =ROUND(1104.93*25390,0) -> 28054173 | N50: =ROUND(1106.62*25390,0)-1 -> 28097081 | O50: =ROUND(1101.83*25390,0) -> 27975464 | P50: =ROUND(1105.31*25390,0)-1 -> 28063820 | Q50: =ROUND(1124.18*25390,0) -> 28542930 | R50: =SUM(F50:Q50) -> 467060219 | S50: 建物 Building Xây dựng （Depreciation Khấu hao） | BD50: #REF!
B51: 5006016261 | C51: =IFERROR(IF(VLOOKUP($B51,勘定科目!$A:$H,HLOOKUP($E$5,勘定科目!$F$1:$H$2,2,0),0)="","",VLOOKUP($B51,勘定科目!$A:$E,2,0)),"") -> 減価償却費配賦（製） 土地使用権 | D51: =IF(C51="","",VLOOKUP($B51,勘定科目!$A:$E,4,0)) -> 減価償却費 | F51: =ROUND(161.07*25390,0) -> 4089567 | G51: =ROUND(160.59*25390,0) -> 4077380 | H51: =ROUND(161.17*25390,0) -> 4092106 | I51: =ROUND(156.86*25390,0) -> 3982675 | J51: =ROUND(77.46*25390,0) -> 1966709 | K51: =ROUND(75.61*25390,0) -> 1919738 | L51: =ROUND(74.73*25390,0) -> 1897395 | M51: =ROUND(74.58*25390,0) -> 1893586 | N51: =ROUND(74.69*25390,0)-1 -> 1896378 | O51: =ROUND(74.37*25390,0) -> 1888254 | P51: =ROUND(74.6*25390,0) -> 1894094 | Q51: =ROUND(75.88*25390,0) -> 1926593 | R51: =SUM(F51:Q51) -> 31524475 | S51: 土地 Land Đất （Depreciation Khấu hao） | BD51: #REF!
C52: =IFERROR(IF(VLOOKUP($B52,勘定科目!$A:$H,HLOOKUP($E$5,勘定科目!$F$1:$H$2,2,0),0)="","",VLOOKUP($B52,勘定科目!$A:$E,2,0)),"") | D52: =IF(C52="","",VLOOKUP($B52,勘定科目!$A:$E,4,0)) | R52: =SUM(F52:Q52) -> 0 | BD52: #REF!
B53: 5005016372 | C53: =IFERROR(IF(VLOOKUP($B53,勘定科目!$A:$H,HLOOKUP($E$5,勘定科目!$F$1:$H$2,2,0),0)="","",VLOOKUP($B53,勘定科目!$A:$E,2,0)),"") -> その他消耗品（製） | D53: =IF(C53="","",VLOOKUP($B53,勘定科目!$A:$E,4,0)) -> 消耗品費 | F53: =ROUND(1430*5300,0) -> 7579000 | G53: =ROUND(1350*5300,0) -> 7155000 | H53: =ROUND(1510*5300,0) -> 8003000 | I53: =ROUND(1670*5300,0) -> 8851000 | J53: =ROUND(40*5300,0) -> 212000 | K53: =ROUND(40*5300,0) -> 212000 | L53: =ROUND(60*5300,0) -> 318000 | M53: =ROUND(40*5300,0) -> 212000 | N53: =ROUND(60*5300,0) -> 318000 | O53: =ROUND(40*5300,0) -> 212000 | P53: =ROUND(30*5300,0) -> 159000 | Q53: =ROUND(60*5300,0) -> 318000 | R53: =SUM(F53:Q53) -> 33549000 | S53: 手袋 Găng tay | BD53: #REF!
B54: 5005016372 | C54: =IFERROR(IF(VLOOKUP($B54,勘定科目!$A:$H,HLOOKUP($E$5,勘定科目!$F$1:$H$2,2,0),0)="","",VLOOKUP($B54,勘定科目!$A:$E,2,0)),"") -> その他消耗品（製） | D54: =IF(C54="","",VLOOKUP($B54,勘定科目!$A:$E,4,0)) -> 消耗品費 | F54: =ROUND(42*50000,0) -> 2100000 | G54: =ROUND(40*50000,0) -> 2000000 | H54: =ROUND(44*50000,0) -> 2200000 | I54: =ROUND(48*50000,0) -> 2400000 | J54: =ROUND(5*50000,0) -> 250000 | K54: =ROUND(5*50000,0) -> 250000 | L54: =ROUND(7*50000,0) -> 350000 | M54: =ROUND(5*50000,0) -> 250000 | N54: =ROUND(7*50000,0) -> 350000 | O54: =ROUND(5*50000,0) -> 250000 | P54: =ROUND(4*50000,0) -> 200000 | Q54: =ROUND(6*50000,0) -> 300000 | R54: =SUM(F54:Q54) -> 10900000 | S54: マスク Khẩu trang | BD54: #REF!
B55: 5005016372 | C55: =IFERROR(IF(VLOOKUP($B55,勘定科目!$A:$H,HLOOKUP($E$5,勘定科目!$F$1:$H$2,2,0),0)="","",VLOOKUP($B55,勘定科目!$A:$E,2,0)),"") -> その他消耗品（製） | D55: =IF(C55="","",VLOOKUP($B55,勘定科目!$A:$E,4,0)) -> 消耗品費 | F55: =ROUND((196-1)*18424,0) -> 3592680 | G55: =ROUND((F24+F25)*17736,0) -> 3511728 | H55: =ROUND((G24+G25)*19401,0) -> 3841398 | I55: =ROUND((H24+H25)*21138,0) -> 4185324 | J55: =ROUND((I24+I25)*18404,0) -> 515312 | K55: =ROUND((J24+J25)*17500,0) -> 490000 | L55: =ROUND((K24+K25)*21110,0) -> 591080 | M55: =ROUND((L24+L25)*18421,0) -> 589472 | N55: =ROUND((M24+M25)*20254,0) -> 648128 | O55: =ROUND((N24+N25)*18399,0) -> 588768 | P55: =ROUND((O24+O25)*13863,0) -> 457479 | Q55: =ROUND((P24+P25)*18435,0) -> 663660 | R55: =SUM(F55:Q55) -> 19675029 | S55: トイレットペーパ Giấy vệ sinh | BD55: #REF!
B56: 5005016372 | C56: =IFERROR(IF(VLOOKUP($B56,勘定科目!$A:$H,HLOOKUP($E$5,勘定科目!$F$1:$H$2,2,0),0)="","",VLOOKUP($B56,勘定科目!$A:$E,2,0)),"") -> その他消耗品（製） | D56: =IF(C56="","",VLOOKUP($B56,勘定科目!$A:$E,4,0)) -> 消耗品費 | F56: =ROUND((196-1)*1122,0) -> 218790 | G56: =ROUND((F24+F25)*1130,0) -> 223740 | H56: =ROUND((G24+G25)*1157,0) -> 229086 | I56: =ROUND((H24+H25)*1113,0) -> 220374 | J56: =ROUND((I24+I25)*1080,0) -> 30240 | K56: =ROUND((J24+J25)*1093,0) -> 30604 | L56: =ROUND((K24+K25)*1131,0) -> 31668 | M56: =ROUND((L24+L25)*1114,0) -> 35648 | N56: =ROUND((M24+M25)*1124,0) -> 35968 | O56: =ROUND((N24+N25)*1128,0) -> 36096 | P56: =ROUND((O24+O25)*1146,0) -> 37818 | Q56: =ROUND((P24+P25)*1085,0) -> 39060 | R56: =SUM(F56:Q56) -> 1169092 | S56: 手洗い洗剤費 Nước rửa tay | BD56: #REF!
B57: 5005016372 | C57: =IFERROR(IF(VLOOKUP($B57,勘定科目!$A:$H,HLOOKUP($E$5,勘定科目!$F$1:$H$2,2,0),0)="","",VLOOKUP($B57,勘定科目!$A:$E,2,0)),"") -> その他消耗品（製） | D57: =IF(C57="","",VLOOKUP($B57,勘定科目!$A:$E,4,0)) -> 消耗品費 | R57: =SUM(F57:Q57) -> 0 | S57: 消毒アルコール Cồn khử trùng | BD57: #REF!
B58: 5005016372 | C58: =IFERROR(IF(VLOOKUP($B58,勘定科目!$A:$H,HLOOKUP($E$5,勘定科目!$F$1:$H$2,2,0),0)="","",VLOOKUP($B58,勘定科目!$A:$E,2,0)),"") -> その他消耗品（製） | D58: =IF(C58="","",VLOOKUP($B58,勘定科目!$A:$E,4,0)) -> 消耗品費 | R58: =SUM(F58:Q58) -> 0 | S58: 1月+2月: EH 部品 Linh kiện EH | BD58: #REF!
B59: 5005016372 | C59: =IFERROR(IF(VLOOKUP($B59,勘定科目!$A:$H,HLOOKUP($E$5,勘定科目!$F$1:$H$2,2,0),0)="","",VLOOKUP($B59,勘定科目!$A:$E,2,0)),"") -> その他消耗品（製） | D59: =IF(C59="","",VLOOKUP($B59,勘定科目!$A:$E,4,0)) -> 消耗品費 | R59: =SUM(F59:Q59) -> 0 | S59: 5月・6月：事務用インキ Mực văn phòng | BD59: #REF!
B60: 5005016372 | C60: =IFERROR(IF(VLOOKUP($B60,勘定科目!$A:$H,HLOOKUP($E$5,勘定科目!$F$1:$H$2,2,0),0)="","",VLOOKUP($B60,勘定科目!$A:$E,2,0)),"") -> その他消耗品（製） | D60: =IF(C60="","",VLOOKUP($B60,勘定科目!$A:$E,4,0)) -> 消耗品費 | R60: =SUM(F60:Q60) -> 0 | S60: 07月：ほうき＋ちり取り | BD60: #REF!
C61: =IFERROR(IF(VLOOKUP($B61,勘定科目!$A:$H,HLOOKUP($E$5,勘定科目!$F$1:$H$2,2,0),0)="","",VLOOKUP($B61,勘定科目!$A:$E,2,0)),"") | D61: =IF(C61="","",VLOOKUP($B61,勘定科目!$A:$E,4,0)) | R61: =SUM(F61:Q61) -> 0 | BD61: #REF!
B62: 5005026371 | C62: =IFERROR(IF(VLOOKUP($B62,勘定科目!$A:$H,HLOOKUP($E$5,勘定科目!$F$1:$H$2,2,0),0)="","",VLOOKUP($B62,勘定科目!$A:$E,2,0)),"") -> 消耗工具器具備品費（製） | D62: =IF(C62="","",VLOOKUP($B62,勘定科目!$A:$E,4,0)) -> 消耗工具器具備品費 | F62: =4*16750000 -> 67000000 | G62: =4*16750000 -> 67000000 | H62: =4*16750000 -> 67000000 | I62: =4*16750000 -> 67000000 | J62: 0 | K62: =2*(16750000+4200000) -> 41900000 | N62: =1*(16750000+4200000) -> 20950000 | R62: =SUM(F62:Q62) -> 330850000 | S62: 4月/2025~1月/2026：LAPTOP購入 (分析班+QCCĐ+未然防止) | BD62: #REF!
B63: 5005026371 | C63: =IFERROR(IF(VLOOKUP($B63,勘定科目!$A:$H,HLOOKUP($E$5,勘定科目!$F$1:$H$2,2,0),0)="","",VLOOKUP($B63,勘定科目!$A:$E,2,0)),"") -> 消耗工具器具備品費（製） | D63: =IF(C63="","",VLOOKUP($B63,勘定科目!$A:$E,4,0)) -> 消耗工具器具備品費 | K63: =2*270000 -> 540000 | N63: =270000 -> 270000 | R63: =SUM(F63:Q63) -> 810000 | S63: 8月,9月,10月,12月/2025, 1月/2026：パソコンのマウス chuột máy tính | BD63: #REF!
B64: 5005026371 | C64: =IFERROR(IF(VLOOKUP($B64,勘定科目!$A:$H,HLOOKUP($E$5,勘定科目!$F$1:$H$2,2,0),0)="","",VLOOKUP($B64,勘定科目!$A:$E,2,0)),"") -> 消耗工具器具備品費（製） | D64: =IF(C64="","",VLOOKUP($B64,勘定科目!$A:$E,4,0)) -> 消耗工具器具備品費 | F64: 5000000 | G64: 5000000 | H64: 5000000 | R64: =SUM(F64:Q64) -> 15000000 | S64: 4月,5月,6月/2025: けいたいでんわđiện thoại Samsung chụp ảnh
B65: 5005026371 | C65: =IFERROR(IF(VLOOKUP($B65,勘定科目!$A:$H,HLOOKUP($E$5,勘定科目!$F$1:$H$2,2,0),0)="","",VLOOKUP($B65,勘定科目!$A:$E,2,0)),"") -> 消耗工具器具備品費（製） | D65: =IF(C65="","",VLOOKUP($B65,勘定科目!$A:$E,4,0)) -> 消耗工具器具備品費 | F65: =2*14*25390 -> 710920 | R65: =SUM(F65:Q65) -> 710920 | S65: 04月：USB (QCCĐ) | BD65: #REF!
B66: 5005026371 | C66: =IFERROR(IF(VLOOKUP($B66,勘定科目!$A:$H,HLOOKUP($E$5,勘定科目!$F$1:$H$2,2,0),0)="","",VLOOKUP($B66,勘定科目!$A:$E,2,0)),"") -> 消耗工具器具備品費（製） | D66: =IF(C66="","",VLOOKUP($B66,勘定科目!$A:$E,4,0)) -> 消耗工具器具備品費 | F66: 3224000 | R66: =SUM(F66:Q66) -> 3224000 | S66: 04月：Speaker (Loa) | BD66: #REF!
B67: 5005026371 | C67: =IFERROR(IF(VLOOKUP($B67,勘定科目!$A:$H,HLOOKUP($E$5,勘定科目!$F$1:$H$2,2,0),0)="","",VLOOKUP($B67,勘定科目!$A:$E,2,0)),"") -> 消耗工具器具備品費（製） | D67: =IF(C67="","",VLOOKUP($B67,勘定科目!$A:$E,4,0)) -> 消耗工具器具備品費 | F67: =14500000+300000 -> 14800000 | H67: =14500000+300000 -> 14800000 | P67: =5060800+550000 -> 5610800 | R67: =SUM(F67:Q67) -> 35210800 | S67: 4,6月/2025, 2月/2026：Camera カメラ+ カメラのメモリカード | BD67: #REF!
B68: 5005026371 | C68: =IFERROR(IF(VLOOKUP($B68,勘定科目!$A:$H,HLOOKUP($E$5,勘定科目!$F$1:$H$2,2,0),0)="","",VLOOKUP($B68,勘定科目!$A:$E,2,0)),"") -> 消耗工具器具備品費（製） | D68: =IF(C68="","",VLOOKUP($B68,勘定科目!$A:$E,4,0)) -> 消耗工具器具備品費 | L68: =2*8620000 -> 17240000 | M68: =2*8620000 -> 17240000 | N68: =2*8620000 -> 17240000 | R68: =SUM(F68:Q68) -> 51720000 | S68: 11月,12月,1月/2026：温度湿度計đồng hồ đo nhiệt độ độ ẩm(Spica, Leoライン用） | BC68: VKC0D800 | BD68: #REF!
B69: 5005026371 | C69: =IFERROR(IF(VLOOKUP($B69,勘定科目!$A:$H,HLOOKUP($E$5,勘定科目!$F$1:$H$2,2,0),0)="","",VLOOKUP($B69,勘定科目!$A:$E,2,0)),"") -> 消耗工具器具備品費（製） | D69: =IF(C69="","",VLOOKUP($B69,勘定科目!$A:$E,4,0)) -> 消耗工具器具備品費 | R69: =SUM(F69:Q69) -> 0 | S69: 12月：タブレットのキーボードbàn phím Tablet+パソコンのマウス(chuột có dây)(未然防止31班nhóm PN) | BD69: #REF!
B70: 5005026371 | C70: =IFERROR(IF(VLOOKUP($B70,勘定科目!$A:$H,HLOOKUP($E$5,勘定科目!$F$1:$H$2,2,0),0)="","",VLOOKUP($B70,勘定科目!$A:$E,2,0)),"") -> 消耗工具器具備品費（製） | D70: =IF(C70="","",VLOOKUP($B70,勘定科目!$A:$E,4,0)) -> 消耗工具器具備品費 | R70: =SUM(F70:Q70) -> 0 | S70: 12月：USBケーブル(bộ chia cổng USB)+USB中継ケーブル (cáp chuyển đổi USB)(分析班) | BD70: #REF!
C71: =IFERROR(IF(VLOOKUP($B71,勘定科目!$A:$H,HLOOKUP($E$5,勘定科目!$F$1:$H$2,2,0),0)="","",VLOOKUP($B71,勘定科目!$A:$E,2,0)),"") | D71: =IF(C71="","",VLOOKUP($B71,勘定科目!$A:$E,4,0)) | R71: =SUM(F71:Q71) -> 0 | BD71: #REF!
B72: 5005046283 | C72: =IFERROR(IF(VLOOKUP($B72,勘定科目!$A:$H,HLOOKUP($E$5,勘定科目!$F$1:$H$2,2,0),0)="","",VLOOKUP($B72,勘定科目!$A:$E,2,0)),"") -> 年間保守料（製） | D72: =IF(C72="","",VLOOKUP($B72,勘定科目!$A:$E,4,0)) -> 修繕費 | H72: 1000000 | J72: =500000 -> 500000 | R72: =SUM(F72:Q72) -> 1500000 | S72: 計測器 校正費 CP hiệu chuẩn thiết bị (3月,6月,8月,10月) | BD72: #REF!
C73: =IFERROR(IF(VLOOKUP($B73,勘定科目!$A:$H,HLOOKUP($E$5,勘定科目!$F$1:$H$2,2,0),0)="","",VLOOKUP($B73,勘定科目!$A:$E,2,0)),"") | D73: =IF(C73="","",VLOOKUP($B73,勘定科目!$A:$E,4,0)) | R73: =SUM(F73:Q73) -> 0 | BD73: #REF!
B74: 5005056281 | C74: =IFERROR(IF(VLOOKUP($B74,勘定科目!$A:$H,HLOOKUP($E$5,勘定科目!$F$1:$H$2,2,0),0)="","",VLOOKUP($B74,勘定科目!$A:$E,2,0)),"") -> ガス代（製） | D74: =IF(C74="","",VLOOKUP($B74,勘定科目!$A:$E,4,0)) -> 水道光熱費 | F74: =ROUND((196-1)*40366,0) -> 7871370 | G74: =ROUND((F24+F25)*39111,0) -> 7743978 | H74: =ROUND((G24+G25)*44856,0) -> 8881488 | I74: =ROUND((H24+H25)*46929,0) -> 9291942 | J74: =ROUND((I24+I25)*42688,0) -> 1195264 | K74: =ROUND((J24+J25)*38491,0) -> 1077748 | L74: =ROUND((K24+K25)*46977,0) -> 1315356 | M74: =ROUND((L24+L25)*41126,0) -> 1316032 | N74: =ROUND((M24+M25)*44086,0) -> 1410752 | O74: =ROUND((N24+N25)*42459,0) -> 1358688 | P74: =ROUND((O24+O25)*32894,0) -> 1085502 | Q74: =ROUND((P24+P25)*42542,0) -> 1531512 | R74: =SUM(F74:Q74) -> 44079632 | S74: 食堂燃料費 CP tiền gas | BD74: #REF!
B75: 5005066281 | C75: =IFERROR(IF(VLOOKUP($B75,勘定科目!$A:$H,HLOOKUP($E$5,勘定科目!$F$1:$H$2,2,0),0)="","",VLOOKUP($B75,勘定科目!$A:$E,2,0)),"") -> 電気代（製） | D75: =IF(C75="","",VLOOKUP($B75,勘定科目!$A:$E,4,0)) -> 水道光熱費 | F75: 5698137 | G75: 5847114 | H75: 7337765 | I75: 7902209 | J75: 4856647 | K75: 4454718 | L75: 4492693 | M75: 4019295 | N75: 3851824 | O75: 3378426 | P75: 3384824 | Q75: 2679530 | R75: =SUM(F75:Q75) -> 57903182 | S75: 電気代 CP tiền điện | BD75: #REF!
B76: 5005066282 | C76: =IFERROR(IF(VLOOKUP($B76,勘定科目!$A:$H,HLOOKUP($E$5,勘定科目!$F$1:$H$2,2,0),0)="","",VLOOKUP($B76,勘定科目!$A:$E,2,0)),"") -> 水道代（製） | D76: =IF(C76="","",VLOOKUP($B76,勘定科目!$A:$E,4,0)) -> 水道光熱費 | F76: 5754494 | G76: 6359651 | H76: 7182875 | I76: 10257665 | J76: =ROUND(1299197,0) -> 1299197 | K76: =ROUND(1127303.8989899,0) -> 1127304 | L76: =ROUND(882554.138613861,0) -> 882554 | M76: =ROUND(1229290.77227723,0) -> 1229291 | N76: =ROUND(1227743.36633663,0) -> 1227743 | O76: =ROUND(858543.118226601,0)+1 -> 858544 | P76: =ROUND(702317.127272727,0) -> 702317 | Q76: =ROUND(816013.309090909,0)+1 -> 816014 | R76: =SUM(F76:Q76) -> 37697649 | S76: 水道代 CP tiền nước | BD76: #REF!
C77: =IFERROR(IF(VLOOKUP($B77,勘定科目!$A:$H,HLOOKUP($E$5,勘定科目!$F$1:$H$2,2,0),0)="","",VLOOKUP($B77,勘定科目!$A:$E,2,0)),"") | D77: =IF(C77="","",VLOOKUP($B77,勘定科目!$A:$E,4,0)) | R77: =SUM(F77:Q77) -> 0 | BD77: #REF!
B78: 5005076281 | C78: =IFERROR(IF(VLOOKUP($B78,勘定科目!$A:$H,HLOOKUP($E$5,勘定科目!$F$1:$H$2,2,0),0)="","",VLOOKUP($B78,勘定科目!$A:$E,2,0)),"") -> 通関申告費用（製） | D78: =IF(C78="","",VLOOKUP($B78,勘定科目!$A:$E,4,0)) -> 荷造運賃 | R78: =SUM(F78:Q78) -> 0 | S78: DECLARATION FEE (P) Phí mở tờ khai hải quan | BD78: #REF!
B79: 5005076281 | C79: =IFERROR(IF(VLOOKUP($B79,勘定科目!$A:$H,HLOOKUP($E$5,勘定科目!$F$1:$H$2,2,0),0)="","",VLOOKUP($B79,勘定科目!$A:$E,2,0)),"") -> 通関申告費用（製） | D79: =IF(C79="","",VLOOKUP($B79,勘定科目!$A:$E,4,0)) -> 荷造運賃 | R79: =SUM(F79:Q79) -> 0 | S79: DECLARATION FEE (P)-Internal use Phí thủ tục hải quan mực mua nội bộ | BD79: #REF!
B80: 5005076281 | C80: =IFERROR(IF(VLOOKUP($B80,勘定科目!$A:$H,HLOOKUP($E$5,勘定科目!$F$1:$H$2,2,0),0)="","",VLOOKUP($B80,勘定科目!$A:$E,2,0)),"") -> 通関申告費用（製） | D80: =IF(C80="","",VLOOKUP($B80,勘定科目!$A:$E,4,0)) -> 荷造運賃 | R80: =SUM(F80:Q80) -> 0 | S80: 2月： DOMESTIC IMPORT CP mở tờ khai mua TESTO (23/12)通関申告書の費用 | BD80: #REF!
C81: =IFERROR(IF(VLOOKUP($B81,勘定科目!$A:$H,HLOOKUP($E$5,勘定科目!$F$1:$H$2,2,0),0)="","",VLOOKUP($B81,勘定科目!$A:$E,2,0)),"") | D81: =IF(C81="","",VLOOKUP($B81,勘定科目!$A:$E,4,0)) | R81: =SUM(F81:Q81) -> 0 | BD81: #REF!
B82: 5005076289 | C82: =IFERROR(IF(VLOOKUP($B82,勘定科目!$A:$H,HLOOKUP($E$5,勘定科目!$F$1:$H$2,2,0),0)="","",VLOOKUP($B82,勘定科目!$A:$E,2,0)),"") -> クーリエ費用（製） | D82: =IF(C82="","",VLOOKUP($B82,勘定科目!$A:$E,4,0)) -> 荷造運賃 | R82: =SUM(F82:Q82) -> 0 | S82: COURIER CHARGES (P) CP chuyển phát nhanh | BD82: #REF!
C83: =IFERROR(IF(VLOOKUP($B83,勘定科目!$A:$H,HLOOKUP($E$5,勘定科目!$F$1:$H$2,2,0),0)="","",VLOOKUP($B83,勘定科目!$A:$E,2,0)),"") | D83: =IF(C83="","",VLOOKUP($B83,勘定科目!$A:$E,4,0)) | R83: =SUM(F83:Q83) -> 0 | BD83: #REF!
B84: 5005076284 | C84: =IFERROR(IF(VLOOKUP($B84,勘定科目!$A:$H,HLOOKUP($E$5,勘定科目!$F$1:$H$2,2,0),0)="","",VLOOKUP($B84,勘定科目!$A:$E,2,0)),"") -> 輸入海上運賃（製） | D84: =IF(C84="","",VLOOKUP($B84,勘定科目!$A:$E,4,0)) -> 荷造運賃 | R84: =SUM(F84:Q84) -> 0 | S84: IMPORT BOAT FEE (P) | BD84: #REF!
C85: =IFERROR(IF(VLOOKUP($B85,勘定科目!$A:$H,HLOOKUP($E$5,勘定科目!$F$1:$H$2,2,0),0)="","",VLOOKUP($B85,勘定科目!$A:$E,2,0)),"") | D85: =IF(C85="","",VLOOKUP($B85,勘定科目!$A:$E,4,0)) | R85: =SUM(F85:Q85) -> 0 | BD85: #REF!
B86: 5005136291 | C86: =IFERROR(IF(VLOOKUP($B86,勘定科目!$A:$H,HLOOKUP($E$5,勘定科目!$F$1:$H$2,2,0),0)="","",VLOOKUP($B86,勘定科目!$A:$E,2,0)),"") -> 郵送代（製） | D86: =IF(C86="","",VLOOKUP($B86,勘定科目!$A:$E,4,0)) -> 通信費 | R86: =SUM(F86:Q86) -> 0 | S86: 郵送料 CP chuyển chứng từ (P. QLKD) gửi tài liệu đi KDC | BD86: #REF!
C87: =IFERROR(IF(VLOOKUP($B87,勘定科目!$A:$H,HLOOKUP($E$5,勘定科目!$F$1:$H$2,2,0),0)="","",VLOOKUP($B87,勘定科目!$A:$E,2,0)),"") | D87: =IF(C87="","",VLOOKUP($B87,勘定科目!$A:$E,4,0)) | R87: =SUM(F87:Q87) -> 0 | BD87: #REF!
B88: 5005076283 | C88: =IFERROR(IF(VLOOKUP($B88,勘定科目!$A:$H,HLOOKUP($E$5,勘定科目!$F$1:$H$2,2,0),0)="","",VLOOKUP($B88,勘定科目!$A:$E,2,0)),"") -> 輸入航空運賃（製） | D88: =IF(C88="","",VLOOKUP($B88,勘定科目!$A:$E,4,0)) -> 荷造運賃 | R88: =SUM(F88:Q88) -> 0 | S88: IMPORT AIR FEE (P) :12月：2021年 KDTCNカレンダーを貰います | BD88: #REF!
B89: 5005076283 | C89: =IFERROR(IF(VLOOKUP($B89,勘定科目!$A:$H,HLOOKUP($E$5,勘定科目!$F$1:$H$2,2,0),0)="","",VLOOKUP($B89,勘定科目!$A:$E,2,0)),"") -> 輸入航空運賃（製） | D89: =IF(C89="","",VLOOKUP($B89,勘定科目!$A:$E,4,0)) -> 荷造運賃 | R89: =SUM(F89:Q89) -> 0 | S89: IMPORT AIR FEE (P) サンプル8部NG画像 | BD89: #REF!
B90: 5005076283 | C90: =IFERROR(IF(VLOOKUP($B90,勘定科目!$A:$H,HLOOKUP($E$5,勘定科目!$F$1:$H$2,2,0),0)="","",VLOOKUP($B90,勘定科目!$A:$E,2,0)),"") -> 輸入航空運賃（製） | D90: =IF(C90="","",VLOOKUP($B90,勘定科目!$A:$E,4,0)) -> 荷造運賃 | R90: =SUM(F90:Q90) -> 0 | S90: IMPORT AIR FEE (P)(IRIS2020のUSB LOG ) | BD90: #REF!
C91: =IFERROR(IF(VLOOKUP($B91,勘定科目!$A:$H,HLOOKUP($E$5,勘定科目!$F$1:$H$2,2,0),0)="","",VLOOKUP($B91,勘定科目!$A:$E,2,0)),"") | D91: =IF(C91="","",VLOOKUP($B91,勘定科目!$A:$E,4,0)) | R91: =SUM(F91:Q91) -> 0 | BD91: #REF!
B92: 5005116292 | C92: =IFERROR(IF(VLOOKUP($B92,勘定科目!$A:$H,HLOOKUP($E$5,勘定科目!$F$1:$H$2,2,0),0)="","",VLOOKUP($B92,勘定科目!$A:$E,2,0)),"") -> 海外渡航費（製） | D92: =IF(C92="","",VLOOKUP($B92,勘定科目!$A:$E,4,0)) -> 渡航費 | F92: =(80000+145*25390+640000)*2 -> 8803100 | R92: =SUM(F92:Q92) -> 8803100 | S92: 4月,7月, 8月,9月:VISA取得費用(145$)＋写真(80.000)＋大使館に発生の経費(640.000)（日本へ出張）(phí công chứng chụp ảnh+phí xin VISA+lệ phí làm thủ tục tại đại sứ quán cho người đi công tác) | BD92: #REF!
B93: 5005116292 | C93: =IFERROR(IF(VLOOKUP($B93,勘定科目!$A:$H,HLOOKUP($E$5,勘定科目!$F$1:$H$2,2,0),0)="","",VLOOKUP($B93,勘定科目!$A:$E,2,0)),"") -> 海外渡航費（製） | D93: =IF(C93="","",VLOOKUP($B93,勘定科目!$A:$E,4,0)) -> 渡航費 | F93: =(35*25390)*2 -> 1777300 | R93: =SUM(F93:Q93) -> 1777300 | S93: 4月,7月, 8月,9月: 海外渡航保険代 bảo hiểm cho người đi công tác (ng Nhật ko cần) (35USD) | BD93: #REF!
B94: 5005116292 | C94: =IFERROR(IF(VLOOKUP($B94,勘定科目!$A:$H,HLOOKUP($E$5,勘定科目!$F$1:$H$2,2,0),0)="","",VLOOKUP($B94,勘定科目!$A:$E,2,0)),"") -> 海外渡航費（製） | D94: =IF(C94="","",VLOOKUP($B94,勘定科目!$A:$E,4,0)) -> 渡航費 | F94: =ROUND(88000*161.47*2,0) -> 28418720 | R94: =SUM(F94:Q94) -> 28418720 | S94: 4月,7月, 8月,9月: Tiền thuê nhàcho người đi công tác 宿泊費 (88000Yen) | BD94: #REF!
B95: 5005116292 | C95: =IFERROR(IF(VLOOKUP($B95,勘定科目!$A:$H,HLOOKUP($E$5,勘定科目!$F$1:$H$2,2,0),0)="","",VLOOKUP($B95,勘定科目!$A:$E,2,0)),"") -> 海外渡航費（製） | D95: =IF(C95="","",VLOOKUP($B95,勘定科目!$A:$E,4,0)) -> 渡航費 | F95: =ROUND((43*14+52*14)*25390,0) -> 33768700 | R95: =SUM(F95:Q95) -> 33768700 | S95: 4月,7月, 8月,9月: Phí công tác (tại Nhật)国際日当 Nhân viên: 602USD. Trợ lý: 728USD/2 tuần, Trung Quốc 41$/ngày | BD95: #REF!
B96: 5005116292 | C96: =IFERROR(IF(VLOOKUP($B96,勘定科目!$A:$H,HLOOKUP($E$5,勘定科目!$F$1:$H$2,2,0),0)="","",VLOOKUP($B96,勘定科目!$A:$E,2,0)),"") -> 海外渡航費（製） | D96: =IF(C96="","",VLOOKUP($B96,勘定科目!$A:$E,4,0)) -> 渡航費 | F96: =ROUND(7420*161.47*2,0) -> 2396215 | R96: =SUM(F96:Q96) -> 2396215 | S96: 4月,7月, 8月,9月: Phí di chuyển, liên lạc (công tác ở Nhật) 現地交通費、通信費 (日本）(7420 Yen)
B97: 5005116292 | C97: =IFERROR(IF(VLOOKUP($B97,勘定科目!$A:$H,HLOOKUP($E$5,勘定科目!$F$1:$H$2,2,0),0)="","",VLOOKUP($B97,勘定科目!$A:$E,2,0)),"") -> 海外渡航費（製） | D97: =IF(C97="","",VLOOKUP($B97,勘定科目!$A:$E,4,0)) -> 渡航費 | G97: =ROUND(800*2*25390,0) -> 40624000 | R97: =SUM(F97:Q97) -> 40624000 | S97: 4月,7月, 8月,9月: エアーチケット (KDC, KDTCN海外出張)Vé máy bay công tác (KDC:800USD/2chiều, KDTCN: 250+300USD/2chiều)
B98: 5005116292 | C98: =IFERROR(IF(VLOOKUP($B98,勘定科目!$A:$H,HLOOKUP($E$5,勘定科目!$F$1:$H$2,2,0),0)="","",VLOOKUP($B98,勘定科目!$A:$E,2,0)),"") -> 海外渡航費（製） | D98: =IF(C98="","",VLOOKUP($B98,勘定科目!$A:$E,4,0)) -> 渡航費 | R98: =SUM(F98:Q98) -> 0 | S98: 5月,8月,9月,10月phát sinh thêm gói cước sử dụng tại nước công tácChi phi dien thoai cong tac KDTCN
R99: =SUM(F99:Q99) -> 0
C100: =IFERROR(IF(VLOOKUP($B100,勘定科目!$A:$H,HLOOKUP($E$5,勘定科目!$F$1:$H$2,2,0),0)="","",VLOOKUP($B100,勘定科目!$A:$E,2,0)),"") | D100: =IF(C100="","",VLOOKUP($B100,勘定科目!$A:$E,4,0)) | R100: =SUM(F100:Q100) -> 0 | BD100: #REF!
B101: 5005136281 | C101: =IFERROR(IF(VLOOKUP($B101,勘定科目!$A:$H,HLOOKUP($E$5,勘定科目!$F$1:$H$2,2,0),0)="","",VLOOKUP($B101,勘定科目!$A:$E,2,0)),"") -> 通信費（製） | D101: =IF(C101="","",VLOOKUP($B101,勘定科目!$A:$E,4,0)) -> 通信費 | F101: =42*99000+16*149000 -> 6542000 | G101: =(42*99000+16*149000)+2*99000+400000*2 -> 7540000 | H101: =42*99000+16*149000+2*99000 -> 6740000 | I101: =(42*99000+16*149000+2*99000)+1*99000 -> 6839000 | J101: =(19*99000+3*149000+1*99000) -> 2427000 | K101: =(19*99000+3*149000+1*99000) -> 2427000 | L101: =(19*99000+3*149000+1*99000) -> 2427000 | M101: =(19*99000+3*149000+1*99000)+3*99000 -> 2724000 | N101: =(19*99000+3*149000+1*99000)+3*99000 -> 2724000 | O101: =(19*99000+3*149000+1*99000)+3*99000 -> 2724000 | P101: =(19*99000+3*149000+1*99000)+3*99000 -> 2724000 | Q101: =(19*99000+3*149000+1*99000)+3*99000 -> 2724000 | R101: =SUM(F101:Q101) -> 48562000 | S101: (4月, 6月/2025)携帯電話 CP điện thoại, | BD101: #REF!
...

Sheet 設備投資計画
B1: 設備投資金額一覧表 | D1: ='内訳ﾘｽﾄ(4～3月)'!C5 -> 工程品質管理1課 | E1: (単位： VND)
B3: 部門ｺｰﾄﾞ | C3: 購入物品名 | D3: 目 的 | E3: 4 | F3: 5 | G3: 6 | H3: 7 | I3: 8 | J3: 9 | K3: 10 | L3: 11 | M3: 12 | N3: 1 | O3: 2 | P3: 3 | Q3: 償却期間 (ヶ月) | R3: 購入金額合計 | S3: WBS
R4: =SUM(E4:P4) -> 0
R5: =SUM(E5:P5) -> 0
R6: =SUM(E6:P6) -> 0
R7: =SUM(E7:P7) -> 0
R8: =SUM(E8:P8) -> 0
R9: =SUM(E9:P9) -> 0
R10: =SUM(E10:P10) -> 0
R11: =SUM(E11:P11) -> 0
R12: =SUM(E12:P12) -> 0
R13: =SUM(E13:P13) -> 0
R14: =SUM(E14:P14) -> 0
R15: =SUM(E15:P15) -> 0
... R49: =SUM(E49:P49) -> 0
D50: TOTAL | R50: =SUM(E50:P50) -> 0
B52: ＊設備投資は、30,000,000VND以上、且つ1年以上使用するものが対象となります。
B53: ＊建設仮勘定を含む、取得基準にて記入して下さい。
B54: ＊重複を避ける為、稟議起案部門にて記入して下さい。
B55: ＊リースによる設備投資を含めないで下さい。

Sheet 勘定科目
A1: Account_Code | B1: JPN (50cha) | C1: Tiếng Việt_Tên tài khoản kế toán | D1: JP_Name | E1: Tiếng Việt_Hạng mục lợi nhuận | F1: 製造 | G1: 一般 | H1: 販売 | I1: REMARK
F2: =COLUMNS($A$2:F2) -> 6 | G2: =COLUMNS($A$2:G2) -> 7 | H2: =COLUMNS($A$2:H2) -> 8
A3: 7001065118 | B3: 雑収入 | C3: Doanh thu khác | D3: 雑収入 | E3: Thu nhập khác | F3: 7001065118 | G3: 7001065118 | H3: 7001065118
A4: 7001075118 | B4: 雑収入（関係会社） | C4: Doanh thu khác | D4: 雑収入 | E4: Thu nhập khác | F4: 7001075118 | G4: 7001075118 | H4: 7001075118
A5: 7001065119 | B5: 固定資産売却勘定 | C5: Doanh thu khác | D5: 雑収入 | E5: Thu nhập khác | F5: 7001065119 | G5: 7001065119 | H5: 7001065119
A6: 5001016131 | B6: 材料仕入割戻高 | C6: Chi phí nguyên liệu, vật liệu trực tiếp | D6: 材料費 | E6: Chi phí nguyên vật liệu | F6: 5001016131 | I6: 2016年4月から追加する。
A7: 5001016134 | B7: リーフレット用材料 | C7: Chi phí nguyên liệu, vật liệu trực tiếp | D7: 材料費 | E7: Chi phí nguyên vật liệu | F7: 5001016134 | G7: 5001016134 | H7: 5001016134 | I7: 2017年1月変更。
A8: 5001016135 | B8: 不良部品材料費 | C8: Chi phí nguyên liệu, vật liệu trực tiếp | D8: 材料費 | E8: Chi phí nguyên vật liệu | F8: 5001016135 | G8: 5001016135 | H8: 5001016135
A9: 5001016136 | B9: 追加指図部品費 | C9: Chi phí nguyên liệu, vật liệu trực tiếp | D9: 材料費 | E9: Chi phí nguyên vật liệu | F9: 5001016136 | G9: 5001016136 | H9: 5001016136
A10: 5001016142 | B10: 加工中不良廃棄損 | C10: Chi phí nguyên liệu, vật liệu trực tiếp | D10: 仕掛仕損 | E10: Sản phẩm chưa hoàn thiện,hỏng | F10: 5001016142 | G10: 5001016142 | H10: 5001016142
A11: 5001016149 | B11: 金型材料仕入 | C11: Chi phí nguyên liệu, vật liệu trực tiếp | D11: 材料費 | E11: Chi phí nguyên vật liệu | F11: 5001016149 | G11: 5001016149 | H11: 5001016149 | I11: 2月から追加する。
A12: 5001016151 | B12: 生産用副資材 | C12: Chi phí nguyên liệu, vật liệu trực tiếp | D12: 材料費 | E12: Chi phí nguyên vật liệu | F12: 5001016151 | I12: 2017年1月追加。
A13: 5004046221 | B13: 雑給（直製） | C13: Chi phí nhân công trực tiếp | D13: 雑給 | E13: Chi phí nhân công trực tiếp | F13: 5004046221
A14: 5004046371 | B14: 雑給（間製） | C14: Chi phí nhân viên phân xưởng | D14: 雑給 | E14: Chi phí nhân công trực tiếp | F14: 5004046371
A15: 5005016371 | B15: 生産用消耗品費（製） | C15: Chi phí dụng cụ sản xuất | D15: 消耗品費 | E15: Chi phí hàng hóa tiêu hao | F15: 5005016371
A16: 5005016372 | B16: その他消耗品（製） | C16: Chi phí dụng cụ sản xuất | D16: 消耗品費 | E16: Chi phí hàng hóa tiêu hao | F16: 5005016372
A17: 5005016373 | B17: 生産用文房具（製造） | C17: Chi phí dụng cụ sản xuất | D17: 消耗品費 | E17: Chi phí hàng hóa tiêu hao | F17: 5005016373 | I17: 2017年1月追加。
A18: 5005026371 | B18: 消耗工具器具備品費（製） | C18: Chi phí dụng cụ sản xuất | D18: 消耗工具器具備品費 | E18: Chi phí sử dụng công cụ,đồ đạc | F18: 5005026371
A19: 5005026372 | B19: 消耗金型代（製） | C19: Chi phí dụng cụ sản xuất | D19: 消耗金型費 | E19: Chi phí tiêu hao khuôn | F19: 5005026372
A20: 5006016241 | B20: 減価償却費（製） 建物 | C20: Chi phí khấu hao TSCĐ | D20: 減価償却費 | E20: Chi phí khấu hao | F20: 5006016241
A21: 5006016242 | B21: 減価償却費（製） 機械装置 | C21: Chi phí khấu hao TSCĐ | D21: 減価償却費 | E21: Chi phí khấu hao | F21: 5006016242
A22: 5006016243 | B22: 減価償却費（製） 車輌運搬具 | C22: Chi phí khấu hao TSCĐ | D22: 減価償却費 | E22: Chi phí khấu hao | F22: 5006016243
A23: 5006016244 | B23: 減価償却費（製） 工具器具備品 | C23: Chi phí khấu hao TSCĐ | D23: 減価償却費 | E23: Chi phí khấu hao | F23: 5006016244
A24: 5006016245 | B24: 減価償却費（製） 構築物 | C24: Chi phí khấu hao TSCĐ | D24: 減価償却費 | E24: Chi phí khấu hao | F24: 5006016245
A25: 5005036246 | B25: 減価償却費（製） 金型 | C25: Chi phí khấu hao TSCĐ | D25: 金型償却費 | E25: Chi phí khấu hao khuôn | F25: 5005036246
A26: 5006016247 | B26: 減価償却費（製） その他有形固定資産 | C26: Chi phí khấu hao TSCĐ | D26: 減価償却費 | E26: Chi phí khấu hao | F26: 5006016247
A27: 5006016248 | B27: 減価償却費（製） リース建物 | C27: Chi phí khấu hao TSCĐ | D27: 減価償却費 | E27: Chi phí khấu hao | F27: 5006016248
A28: 5006016249 | B28: 減価償却費（製） リース機械装置 | C28: Chi phí khấu hao TSCĐ | D28: 減価償却費 | E28: Chi phí khấu hao | F28: 5006016249
A29: 5006016250 | B29: 減価償却費（製） リース車輌運搬具 | C29: Chi phí khấu hao TSCĐ | D29: 減価償却費 | E29: Chi phí khấu hao | F29: 5006016250
... A44: 5005046283 | B44: 年間保守料（製） | C44: Chi phi dịch vụ mua ngoài | D44: 修繕費 | E44: Chi phí sửa chữa | F44: 5005046283
A45: 5005046284 | B45: 金型修繕費（製造） | C45: Chi phi dịch vụ mua ngoài | D45: 修繕費 | E45: Chi phí sửa chữa | F45: 5005046284 | I45: 2017年1月追加。
A46: 5005066281 | B46: 電気代（製） | C46: Chi phi dịch vụ mua ngoài | D46: 水道光熱費 | E46: Chi phí Utilities(điện,nước..) | F46: 5005066281
A47: 5005066282 | B47: 水道代（製） | C47: Chi phi dịch vụ mua ngoài | D47: 水道光熱費 | E47: Chi phí Utilities(điện,nước..) | F47: 5005066282
A48: 5005056281 | B48: ガス代（製） | C48: Chi phi dịch vụ mua ngoài | D48: 水道光熱費 | E48: Chi phí Utilities(điện,nước..) | F48: 5005056281
A49: 5005076281 | B49: 通関申告費用（製） | C49: Chi phi dịch vụ mua ngoài | D49: 荷造運賃 | E49: Chi phí vận chuyển hàng hóa | F49: 5005076281
A50: 5005076282 | B50: 設備輸送費（製） | C50: Chi phi dịch vụ mua ngoài | D50: 荷造運賃 | E50: Chi phí vận chuyển hàng hóa | F50: 5005076282
A51: 5005076283 | B51: 輸入航空運賃（製） | C51: Chi phi dịch vụ mua ngoài | D51: 荷造運賃 | E51: Chi phí vận chuyển hàng hóa | F51: 5005076283
A52: 5005076284 | B52: 輸入海上運賃（製） | C52: Chi phi dịch vụ mua ngoài | D52: 荷造運賃 | E52: Chi phí vận chuyển hàng hóa | F52: 5005076284
A53: 5005076285 | B53: 空箱返却費用 | C53: Chi phi dịch vụ mua ngoài | D53: 荷造運賃 | E53: Chi phí vận chuyển hàng hóa | F53: 5005076285
A54: 5005076286 | B54: 部品集荷トラック代 | C54: Chi phi dịch vụ mua ngoài | D54: 荷造運賃 | E54: Chi phí vận chuyển hàng hóa | F54: 5005076286
A55: 5005076287 | B55: 物流保険料（製） | C55: Chi phi dịch vụ mua ngoài | D55: 荷造運賃 | E55: Chi phí vận chuyển hàng hóa | F55: 5005076287
A56: 5005076288 | B56: 梱包材料費（製） | C56: Chi phi dịch vụ mua ngoài | D56: 荷造用品費 | E56: Chi phí NVL dùng đóng gói hàng | F56: 5005076288
A57: 5005076289 | B57: クーリエ費用（製） | C57: Chi phi dịch vụ mua ngoài | D57: 荷造運賃 | E57: Chi phí vận chuyển hàng hóa | F57: 5005076289
A58: 5005076291 | B58: 外部倉庫 取扱手数料（製造） | C58: Chi phi dịch vụ mua ngoài | D58: 荷造運賃 | E58: Chi phí vận chuyển hàng hóa | F58: 5005076291 | I58: 2017年1月追加。
A59: 5005076292 | B59: 外部倉庫 保管料（製造） | C59: Chi phi dịch vụ mua ngoài | D59: 荷造運賃 | E59: Chi phí vận chuyển hàng hóa | F59: 5005076292 | I59: 2017年1月追加。
A60: 5005076293 | B60: 外部倉庫 輸送料（製造） | C60: Chi phi dịch vụ mua ngoài | D60: 荷造運賃 | E60: Chi phí vận chuyển hàng hóa | F60: 5005076293 | I60: 2017年1月追加。
A61: 5005076294 | B61: 外部物流業者 取扱手数料（製造） | C61: Chi phi dịch vụ mua ngoài | D61: 荷造運賃 | E61: Chi phí vận chuyển hàng hóa | F61: 5005076294 | I61: 2017年1月追加。
A62: 5005086281 | B62: 技術料（製） | C62: Chi phi dịch vụ mua ngoài | D62: 技術料 | E62: Phí kỹ thuật | F62: 5005086281
A63: 5005136281 | B63: 通信費（製） | C63: Chi phi dịch vụ mua ngoài | D63: 通信費 | E63: Chi phí điện thoại | F63: 5005136281
A64: 5005246281 | B64: 図書印刷費（製） | C64: Chi phi dịch vụ mua ngoài | D64: 図書及び事務費 | E64: Chi phí văn phòng | F64: 5005246281
A65: 5005246282 | B65: ＫＤＣシステム使用料（製） | C65: Chi phi dịch vụ mua ngoài | D65: 図書及び事務費 | E65: Chi phí văn phòng | F65: 5005246282
A66: 5005246283 | B66: ライセンス料（製） | C66: Chi phi dịch vụ mua ngoài | D66: 図書及び事務費 | E66: Chi phí văn phòng | F66: 5005246283
A67: 5005246284 | B67: 会費（製） | C67: Chi phi dịch vụ mua ngoài | D67: 会費及び会議費 | E67: Chi phí cuộc họp | F67: 5005246284
A68: 5005216281 | B68: 委嘱報酬・設計委託費（製） | C68: Chi phi dịch vụ mua ngoài | D68: 委嘱報酬 | E68: Thù lao ủy thác,phí hoa hồng | F68: 5005216281
A69: 5005226281 | B69: 保険料（製） | C69: Chi phi dịch vụ mua ngoài | D69: 保険料 | E69: Chi phí bảo hiểm | F69: 5005226281
A70: 5005236281 | B70: 事務所賃借料（製） | C70: Chi phi dịch vụ mua ngoài | D70: 賃借料 | E70: Chi phí thuê | F70: 5005236281
A71: 5005236282 | B71: 倉庫賃借料（製） | C71: Chi phi dịch vụ mua ngoài | D71: 賃借料 | E71: Chi phí thuê | F71: 5005236282
A72: 5005246285 | B72: 取扱手数料（製） | C72: Chi phi dịch vụ mua ngoài | D72: 手数料 | E72: Tiền dịch vụ,tiền lệ phí | F72: 5005246285
A73: 5005246286 | B73: その他手数料（製） | C73: Chi phi dịch vụ mua ngoài | D73: 手数料 | E73: Tiền dịch vụ,tiền lệ phí | F73: 5005246286
... A82: 5005186292 | B82: その他税金（製） | C82: Chi phí bằng tiền khác | D82: 公租公課 | E82: Thuế,phí công cộng | F82: 5005186292
A83: 5005196373 | B83: 試験研究用材料費 | C83: Chi phí dụng cụ sản xuất | D83: 試験研究費 | E83: Chi phí thử nghiệm,nghiên cứu | F83: 5005196373 | G83: 5005196373 | H83: 5005196373 | I83: 2月から追加する。
A84: 5005196277 | B84: 試験研究用役務費 | C84: Chi phi dịch vụ mua ngoài | D84: 試験研究費 | E84: Chi phí thử nghiệm,nghiên cứu | F84: 5005196277 | G84: 5005196277 | H84: 5005196277 | I84: 2月から追加する。
A85: 5005246291 | B85: 会議費（製） | C85: Chi phí bằng tiền khác | D85: 会費及び会議費 | E85: Chi phí cuộc họp | F85: 5005246291
A86: 5005246292 | B86: 雑費（製） | C86: Chi phí bằng tiền khác | D86: 雑費 | E86: Các loại chi phí bằng tiền khác | F86: 5005246292
A87: 5005246294 | B87: 開発費振替勘定（製） | C87: Chi phí bằng tiền khác | D87: 雑費 | E87: Các loại chi phí bằng tiền khác | F87: 5005246294 | I87: 2月から追加する→9/2015からｘから雑費になった
A88: 5005256291 | B88: 棚卸減耗費（製） | C88: Chi phí bằng tiền khác | D88: 棚卸減耗費 | E88: Chi phí hao hụt sau kiểm kê | F88: 5005256291
A89: 5101016174 | B89: 製商品仕入諸掛 | C89: Giá vốn hàng bán | D89: 仕入製商品費 | E89: Chi phí bán hàng | F89: 5101016174
A90: 5101016179 | B90: 製品品目外注加工費 | C90: Giá vốn hàng bán | D90: 外注加工費 | E90: Chi phí gia công ngoài | F90: 5101016179
A91: 5101016187 | B91: 製商品在庫廃棄損 | C91: Giá vốn hàng bán | D91: 雑損失 | E91: Tổn thất,lỗ khác | F91: 5101016187
A92: 5101016189 | B92: 金型製作収入 | C92: Doanh thu bán thành phẩm | D92: 雑収入 | E92: Thu nhập khác | F92: 5101016189 | I92: 2月から追加する。
A93: 6004046511 | B93: 雑給（販売） | C93: Chi phí nhân viên | D93: 雑給 | E93: Chi phí nhân công trực tiếp | H93: 6004046511
A94: 6003036412 | B94: 梱包材料費（販売） | C94: Chi phí vật liệu bao bì | D94: 荷造用品費 | E94: Chi phí NVL dùng đóng gói hàng | H94: 6003036412
A95: 6005016413 | B95: 消耗品費（販売） | C95: Chi phí dụng cụ đồ dùng | D95: 消耗品費 | E95: Chi phí hàng hóa tiêu hao | H95: 6005016413
A96: 6005016414 | B96: 消耗備品費（販売） | C96: Chi phí dụng cụ đồ dùng | D96: 消耗工具器具備品費 | E96: Chi phí sử dụng công cụ,đồ đạc | G96: 6005016414 | H96: 6005016414 | I96: 2017年1月追加。
A97: 6006016521 | B97: 減価償却費（販） 建物 | C97: Chi phí khấu hao TSCĐ | D97: 減価償却費 | E97: Chi phí khấu hao | H97: 6006016521
A98: 6006016522 | B98: 減価償却費（販） 機械装置 | C98: Chi phí khấu hao TSCĐ | D98: 減価償却費 | E98: Chi phí khấu hao | H98: 6006016522
A99: 6006016523 | B99: 減価償却費（販） 車輌運搬具 | C99: Chi phí khấu hao TSCĐ | D99: 減価償却費 | E99: Chi phí khấu hao | H99: 6006016523
A100: 6006016524 | B100: 減価償却費（販） 工具器具備品 | C100: Chi phí khấu hao TSCĐ | D100: 減価償却費 | E100: Chi phí khấu hao | H100: 6006016524
A101: 6006016525 | B101: 減価償却費（販） 構築物 | C101: Chi phí khấu hao TSCĐ | D101: 減価償却費 | E101: Chi phí khấu hao | H101: 6006016525
A102: 6006016526 | B102: 減価償却費（販） その他有形固定資産 | C102: Chi phí khấu hao TSCĐ | D102: 減価償却費 | E102: Chi phí khấu hao | H102: 6006016526
A103: 6006016527 | B103: 減価償却費（販） リース建物 | C103: Chi phí khấu hao TSCĐ | D103: 減価償却費 | E103: Chi phí khấu hao | H103: 6006016527
A104: 6006016528 | B104: 減価償却費（販） リース機械装置 | C104: Chi phí khấu hao TSCĐ | D104: 減価償却費 | E104: Chi phí khấu hao | H104: 6006016528
A105: 6006016529 | B105: 減価償却費（販） リース車輌運搬具 | C105: Chi phí khấu hao TSCĐ | D105: 減価償却費 | E105: Chi phí khấu hao | H105: 6006016529
A106: 6006016530 | B106: 減価償却費（販） リース工具器具備品 | C106: Chi phí khấu hao TSCĐ | D106: 減価償却費 | E106: Chi phí khấu hao | H106: 6006016530
A107: 6006016531 | B107: 減価償却費（販） リース構築物 | C107: Chi phí khấu hao TSCĐ | D107: 減価償却費 | E107: Chi phí khấu hao | H107: 6006016531
A108: 6006016532 | B108: 減価償却費（販） 土地使用権 | C108: Chi phí khấu hao TSCĐ | D108: 減価償却費 | E108: Chi phí khấu hao | H108: 6006016532
... A122: 6003036542 | B122: クーリエ費用（販売） | C122: Chi phí dịch vụ mua ngòai | D122: 荷造運賃 | E122: Chi phí vận chuyển hàng hóa | H122: 6003036542
A123: 6003036543 | B123: 輸出航空運賃（販売） | C123: Chi phí dịch vụ mua ngòai | D123: 荷造運賃 | E123: Chi phí vận chuyển hàng hóa | F123: 6003036543 | H123: 6003036543
A124: 6003036544 | B124: 輸出海上運賃（販売） | C124: Chi phí dịch vụ mua ngòai | D124: 荷造運賃 | E124: Chi phí vận chuyển hàng hóa | F124: 6003036544 | G124: 6003036544 | H124: 6003036544
A125: 6003036545 | B125: 保管延長費（販売） | C125: Chi phí dịch vụ mua ngòai | D125: 荷造運賃 | E125: Chi phí vận chuyển hàng hóa | H125: 6003036545
A126: 6003036546 | B126: 物流保険料（販売） | C126: Chi phí dịch vụ mua ngòai | D126: 荷造運賃 | E126: Chi phí vận chuyển hàng hóa | H126: 6003036546
A127: 6003036547 | B127: 梱包費用（販売） | C127: Chi phí dịch vụ mua ngòai | D127: 荷造運賃 | E127: Chi phí vận chuyển hàng hóa | H127: 6003036547
A128: 6003036548 | B128: 返品手数料（販売） | C128: Chi phí dịch vụ mua ngòai | D128: 荷造運賃 | E128: Chi phí vận chuyển hàng hóa | H128: 6003036548
A129: 6003036549 | B129: 保管料（販売） | C129: Chi phí dịch vụ mua ngòai | D129: 荷造運賃 | E129: Chi phí vận chuyển hàng hóa | H129: 6003036549
A130: 6003036550 | B130: オーバーナイト費（販売） | C130: Chi phí dịch vụ mua ngòai | D130: 荷造運賃 | E130: Chi phí vận chuyển hàng hóa | H130: 6003036550
A131: 6003036551 | B131: バンニング費（販売） | C131: Chi phí dịch vụ mua ngòai | D131: 荷造運賃 | E131: Chi phí vận chuyển hàng hóa | H131: 6003036551
A132: 6003036552 | B132: その他物流費（販売） | C132: Chi phí dịch vụ mua ngòai | D132: 荷造運賃 | E132: Chi phí vận chuyển hàng hóa | F132: 6003036552 | H132: 6003036552
A133: 6003036554 | B133: 外部倉庫 取扱手数料（販売） | C133: Chi phí dịch vụ mua ngòai | D133: 荷造運賃 | E133: Chi phí vận chuyển hàng hóa | F133: 6003036554 | G133: 6003036554 | H133: 6003036554 | I133: 2017年1月追加。
A134: 6003036555 | B134: 外部倉庫 保管料（販売） | C134: Chi phí dịch vụ mua ngòai | D134: 荷造運賃 | E134: Chi phí vận chuyển hàng hóa | F134: 6003036555 | G134: 6003036555 | H134: 6003036555 | I134: 2017年1月追加。
A135: 6003036556 | B135: 外部倉庫 輸送料（販売） | C135: Chi phí dịch vụ mua ngòai | D135: 荷造運賃 | E135: Chi phí vận chuyển hàng hóa | F135: 6003036556 | G135: 6003036556 | H135: 6003036556 | I135: 2017年1月追加。
...

Sheet 原価センタ
B1: 原価センタ | D1: 採算区分 | E1: 原価区分
A2: 1412000004 | B2: 機器製造1課 | C2: 01. | D2: 製造 | E2: 製造 | G2: V02XD800
A3: 1412000005 | B3: 機器製造2課 | C3: 02. | D3: 製造 | E3: 製造
A4: 1412000062 | B4: 機器製造管理課 | C4: 03. | D4: 部内間接 | E4: 製造
A5: 1412000034 | B5: トナー製造課 | C5: 04. | D5: 製造 | E5: 製造
A6: 1412000048 | B6: トナー生産技術課 | C6: 05. | D6: 部内間接 | E6: 製造
A7: 1412000055 | B7: トナー品質管理課 | C7: 06. | D7: 部内間接 | E7: 製造
A8: 1412000050 | B8: MD1課 | C8: 07. | D8: 製造 | E8: 製造
A9: 1412000077 | B9: MD2課 | C9: 08. | D9: 製造 | E9: 製造
A10: 1412000053 | B10: 工程品質管理1課 | C10: 09. | D10: 部内間接 | E10: 製造
A11: 1412000008 | B11: 生産管理課 | C11: 10. | D11: 部内間接 | E11: 製造
A12: 1412000010 | B12: 採算管理課 | C12: 11. | D12: 部外間接1 | E12: 製造
A13: 1412000054 | B13: マスター管理課 | C13: 12. | D13: 部外間接1 | E13: 製造
A14: 1412000036 | B14: 部品管理課 | C14: 13. | D14: 部内間接 | E14: 製造
... A58: 1412000099 | B58: MD4課 | C58: 65. | D58: 製造 | E58: 製造

Sheet 稼働日
A2: FY2026 | B2: 稼働日
A3: 4 | B3: 20
A4: 5 | B4: 19
A5: 6 | B5: 21
A6: 7 | B6: 23
A7: 8 | B7: 20
A8: 9 | B8: 19
A9: 10 | B9: 23
A10: 11 | B10: 20
A11: 12 | B11: 22
A12: 1 | B12: 20
A13: 2 | B13: 15
A14: 3 | B14: 20
