Workbook
Name WBS: 原価センタ!$G$2:$G$3

Sheet 採算表(USD)
B1: 組織名 | C1: ='採算表(VND)'!C1 -> MP FY2026_各予定 | N1: ='内訳ﾘｽﾄ(4～3月)'!B2 -> 25390
B2: ='採算表(VND)'!B2 -> 総務課
B4: 項目 ＼ 部門 | C4: ='採算表(VND)'!C4 -> 4 | D4: ='採算表(VND)'!D4 -> 5 | E4: ='採算表(VND)'!E4 -> 6 | F4: ='採算表(VND)'!F4 -> 7 | G4: ='採算表(VND)'!G4 -> 8 | H4: ='採算表(VND)'!H4 -> 9 | I4: ='採算表(VND)'!I4 -> 10 | J4: ='採算表(VND)'!J4 -> 11 | ... O4: ='採算表(VND)'!O4 -> 合計
B5: 総出荷 | C5: =C8+C9 -> 0 | D5: =D8+D9 -> 0 | E5: =E8+E9 -> 0 | F5: =F8+F9 -> 0 | G5: =G8+G9 -> 0 | H5: =H8+H9 -> 0 | I5: =I8+I9 -> 0 | J5: =J8+J9 -> 0 | ... O5: =O8+O9 -> 0
B6: 社外出荷 | C6: =ROUNDDOWN('採算表(VND)'!C6/$N$1,2) -> 0 | D6: =ROUNDDOWN('採算表(VND)'!D6/$N$1,2) -> 0 | E6: =ROUNDDOWN('採算表(VND)'!E6/$N$1,2) -> 0 | F6: =ROUNDDOWN('採算表(VND)'!F6/$N$1,2) -> 0 | G6: =ROUNDDOWN('採算表(VND)'!G6/$N$1,2) -> 0 | H6: =ROUNDDOWN('採算表(VND)'!H6/$N$1,2) -> 0 | I6: =ROUNDDOWN('採算表(VND)'!I6/$N$1,2) -> 0 | J6: =ROUNDDOWN('採算表(VND)'!J6/$N$1,2) -> 0 | ... N6: =ROUNDDOWN('採算表(VND)'!N6/$N$1,2) -> 0 | O6: =SUM(C6:N6) -> 0
B7: 販売支援 | C7: =ROUNDDOWN('採算表(VND)'!C7/$N$1,2) -> 0 | D7: =ROUNDDOWN('採算表(VND)'!D7/$N$1,2) -> 0 | E7: =ROUNDDOWN('採算表(VND)'!E7/$N$1,2) -> 0 | F7: =ROUNDDOWN('採算表(VND)'!F7/$N$1,2) -> 0 | G7: =ROUNDDOWN('採算表(VND)'!G7/$N$1,2) -> 0 | H7: =ROUNDDOWN('採算表(VND)'!H7/$N$1,2) -> 0 | I7: =ROUNDDOWN('採算表(VND)'!I7/$N$1,2) -> 0 | J7: =ROUNDDOWN('採算表(VND)'!J7/$N$1,2) -> 0 | ... N7: =ROUNDDOWN('採算表(VND)'!N7/$N$1,2) -> 0 | O7: =SUM(C7:N7) -> 0
B8: 社外出荷合計 | C8: =C6+C7 -> 0 | D8: =D6+D7 -> 0 | E8: =E6+E7 -> 0 | F8: =F6+F7 -> 0 | G8: =G6+G7 -> 0 | H8: =H6+H7 -> 0 | I8: =I6+I7 -> 0 | J8: =J6+J7 -> 0 | ... O8: =O6+O7 -> 0
B9: 社内売 | C9: =ROUNDDOWN('採算表(VND)'!C9/$N$1,2) -> 0 | D9: =ROUNDDOWN('採算表(VND)'!D9/$N$1,2) -> 0 | E9: =ROUNDDOWN('採算表(VND)'!E9/$N$1,2) -> 0 | F9: =ROUNDDOWN('採算表(VND)'!F9/$N$1,2) -> 0 | G9: =ROUNDDOWN('採算表(VND)'!G9/$N$1,2) -> 0 | H9: =ROUNDDOWN('採算表(VND)'!H9/$N$1,2) -> 0 | I9: =ROUNDDOWN('採算表(VND)'!I9/$N$1,2) -> 0 | J9: =ROUNDDOWN('採算表(VND)'!J9/$N$1,2) -> 0 | ... N9: =ROUNDDOWN('採算表(VND)'!N9/$N$1,2) -> 0 | O9: =SUM(C9:N9) -> 0
B10: 社内買 | C10: =ROUNDDOWN('採算表(VND)'!C10/$N$1,2) -> 0 | D10: =ROUNDDOWN('採算表(VND)'!D10/$N$1,2) -> 0 | E10: =ROUNDDOWN('採算表(VND)'!E10/$N$1,2) -> 0 | F10: =ROUNDDOWN('採算表(VND)'!F10/$N$1,2) -> 0 | G10: =ROUNDDOWN('採算表(VND)'!G10/$N$1,2) -> 0 | H10: =ROUNDDOWN('採算表(VND)'!H10/$N$1,2) -> 0 | I10: =ROUNDDOWN('採算表(VND)'!I10/$N$1,2) -> 0 | J10: =ROUNDDOWN('採算表(VND)'!J10/$N$1,2) -> 0 | ... N10: =ROUNDDOWN('採算表(VND)'!N10/$N$1,2) -> 0 | O10: =SUM(C10:N10) -> 0
B12: 総生産 | C12: =C5-C10 -> 0 | D12: =D5-D10 -> 0 | E12: =E5-E10 -> 0 | F12: =F5-F10 -> 0 | G12: =G5-G10 -> 0 | H12: =H5-H10 -> 0 | I12: =I5-I10 -> 0 | J12: =J5-J10 -> 0 | ... O12: =O5-O10 -> 0
B13: 控除額 | C13: =SUM(C14:C65) -> 0.06 | D13: =SUM(D14:D65) -> 0.06 | E13: =SUM(E14:E65) -> 0.04 | F13: =SUM(F14:F65) -> 0.05 | G13: =SUM(G14:G65) -> 0.06 | H13: =SUM(H14:H65) -> 0.07 | I13: =SUM(I14:I65) -> 0.05 | J13: =SUM(J14:J65) -> 0.06 | ... O13: =SUM(O14:O65) -> 0.7
B14: 材料費 | C14: =ROUNDUP('採算表(VND)'!C14/$N$1,2) -> 0 | D14: =ROUNDUP('採算表(VND)'!D14/$N$1,2) -> 0 | E14: =ROUNDUP('採算表(VND)'!E14/$N$1,2) -> 0 | F14: =ROUNDUP('採算表(VND)'!F14/$N$1,2) -> 0 | G14: =ROUNDUP('採算表(VND)'!G14/$N$1,2) -> 0 | H14: =ROUNDUP('採算表(VND)'!H14/$N$1,2) -> 0 | I14: =ROUNDUP('採算表(VND)'!I14/$N$1,2) -> 0 | J14: =ROUNDUP('採算表(VND)'!J14/$N$1,2) -> 0 | ... N14: =ROUNDUP('採算表(VND)'!N14/$N$1,2) -> 0 | O14: =SUM(C14:N14) -> 0
B15: 設計変更材料費 | C15: =ROUNDUP('採算表(VND)'!C15/$N$1,2) -> 0 | D15: =ROUNDUP('採算表(VND)'!D15/$N$1,2) -> 0 | E15: =ROUNDUP('採算表(VND)'!E15/$N$1,2) -> 0 | F15: =ROUNDUP('採算表(VND)'!F15/$N$1,2) -> 0 | G15: =ROUNDUP('採算表(VND)'!G15/$N$1,2) -> 0 | H15: =ROUNDUP('採算表(VND)'!H15/$N$1,2) -> 0 | I15: =ROUNDUP('採算表(VND)'!I15/$N$1,2) -> 0 | J15: =ROUNDUP('採算表(VND)'!J15/$N$1,2) -> 0 | ... N15: =ROUNDUP('採算表(VND)'!N15/$N$1,2) -> 0 | O15: =SUM(C15:N15) -> 0
B16: 仕掛仕損 | C16: =ROUNDUP('採算表(VND)'!C16/$N$1,2) -> 0 | D16: =ROUNDUP('採算表(VND)'!D16/$N$1,2) -> 0 | E16: =ROUNDUP('採算表(VND)'!E16/$N$1,2) -> 0 | F16: =ROUNDUP('採算表(VND)'!F16/$N$1,2) -> 0 | G16: =ROUNDUP('採算表(VND)'!G16/$N$1,2) -> 0 | H16: =ROUNDUP('採算表(VND)'!H16/$N$1,2) -> 0 | I16: =ROUNDUP('採算表(VND)'!I16/$N$1,2) -> 0 | J16: =ROUNDUP('採算表(VND)'!J16/$N$1,2) -> 0 | ... N16: =ROUNDUP('採算表(VND)'!N16/$N$1,2) -> 0 | O16: =SUM(C16:N16) -> 0
B17: 仕入製商品費 | C17: =ROUNDUP('採算表(VND)'!C17/$N$1,2) -> 0 | D17: =ROUNDUP('採算表(VND)'!D17/$N$1,2) -> 0 | E17: =ROUNDUP('採算表(VND)'!E17/$N$1,2) -> 0 | F17: =ROUNDUP('採算表(VND)'!F17/$N$1,2) -> 0 | G17: =ROUNDUP('採算表(VND)'!G17/$N$1,2) -> 0 | H17: =ROUNDUP('採算表(VND)'!H17/$N$1,2) -> 0 | I17: =ROUNDUP('採算表(VND)'!I17/$N$1,2) -> 0 | J17: =ROUNDUP('採算表(VND)'!J17/$N$1,2) -> 0 | ... N17: =ROUNDUP('採算表(VND)'!N17/$N$1,2) -> 0 | O17: =SUM(C17:N17) -> 0
B18: 内製品有償支給原価 | C18: =ROUNDUP('採算表(VND)'!C18/$N$1,2) -> 0 | D18: =ROUNDUP('採算表(VND)'!D18/$N$1,2) -> 0 | E18: =ROUNDUP('採算表(VND)'!E18/$N$1,2) -> 0 | F18: =ROUNDUP('採算表(VND)'!F18/$N$1,2) -> 0 | G18: =ROUNDUP('採算表(VND)'!G18/$N$1,2) -> 0 | H18: =ROUNDUP('採算表(VND)'!H18/$N$1,2) -> 0 | I18: =ROUNDUP('採算表(VND)'!I18/$N$1,2) -> 0 | J18: =ROUNDUP('採算表(VND)'!J18/$N$1,2) -> 0 | ... N18: =ROUNDUP('採算表(VND)'!N18/$N$1,2) -> 0 | O18: =SUM(C18:N18) -> 0
B19: 外注加工費 | C19: =ROUNDUP('採算表(VND)'!C19/$N$1,2) -> 0 | D19: =ROUNDUP('採算表(VND)'!D19/$N$1,2) -> 0 | E19: =ROUNDUP('採算表(VND)'!E19/$N$1,2) -> 0 | F19: =ROUNDUP('採算表(VND)'!F19/$N$1,2) -> 0 | G19: =ROUNDUP('採算表(VND)'!G19/$N$1,2) -> 0 | H19: =ROUNDUP('採算表(VND)'!H19/$N$1,2) -> 0 | I19: =ROUNDUP('採算表(VND)'!I19/$N$1,2) -> 0 | J19: =ROUNDUP('採算表(VND)'!J19/$N$1,2) -> 0 | ... N19: =ROUNDUP('採算表(VND)'!N19/$N$1,2) -> 0 | O19: =SUM(C19:N19) -> 0
B20: 減価償却費 | C20: =ROUNDUP('採算表(VND)'!C20/$N$1,2) -> 20970.69 | D20: =ROUNDUP('採算表(VND)'!D20/$N$1,2) -> 20988.92 | E20: =ROUNDUP('採算表(VND)'!E20/$N$1,2) -> 20989.03 | F20: =ROUNDUP('採算表(VND)'!F20/$N$1,2) -> 21054.4 | G20: =ROUNDUP('採算表(VND)'!G20/$N$1,2) -> 21054.28 | H20: =ROUNDUP('採算表(VND)'!H20/$N$1,2) -> 21048.7 | I20: =ROUNDUP('採算表(VND)'!I20/$N$1,2) -> 21202.64 | J20: =ROUNDUP('採算表(VND)'!J20/$N$1,2) -> 21202.58 | ... N20: =ROUNDUP('採算表(VND)'!N20/$N$1,2) -> 21202.48 | O20: =SUM(C20:N20) -> 253321.08
B21: 金型償却費 | C21: =ROUNDUP('採算表(VND)'!C21/$N$1,2) -> 0 | D21: =ROUNDUP('採算表(VND)'!D21/$N$1,2) -> 0 | E21: =ROUNDUP('採算表(VND)'!E21/$N$1,2) -> 0 | F21: =ROUNDUP('採算表(VND)'!F21/$N$1,2) -> 0 | G21: =ROUNDUP('採算表(VND)'!G21/$N$1,2) -> 0 | H21: =ROUNDUP('採算表(VND)'!H21/$N$1,2) -> 0 | I21: =ROUNDUP('採算表(VND)'!I21/$N$1,2) -> 0 | J21: =ROUNDUP('採算表(VND)'!J21/$N$1,2) -> 0 | ... N21: =ROUNDUP('採算表(VND)'!N21/$N$1,2) -> 0 | O21: =SUM(C21:N21) -> 0
B22: 賃借料 | C22: =ROUNDUP('採算表(VND)'!C22/$N$1,2) -> 0 | D22: =ROUNDUP('採算表(VND)'!D22/$N$1,2) -> 0 | E22: =ROUNDUP('採算表(VND)'!E22/$N$1,2) -> 0 | F22: =ROUNDUP('採算表(VND)'!F22/$N$1,2) -> 0 | G22: =ROUNDUP('採算表(VND)'!G22/$N$1,2) -> 0 | H22: =ROUNDUP('採算表(VND)'!H22/$N$1,2) -> 0 | I22: =ROUNDUP('採算表(VND)'!I22/$N$1,2) -> 0 | J22: =ROUNDUP('採算表(VND)'!J22/$N$1,2) -> 0 | ... N22: =ROUNDUP('採算表(VND)'!N22/$N$1,2) -> 0 | O22: =SUM(C22:N22) -> 0
B23: 保険料 | C23: =ROUNDUP('採算表(VND)'!C23/$N$1,2) -> 0 | D23: =ROUNDUP('採算表(VND)'!D23/$N$1,2) -> 2166.21 | E23: =ROUNDUP('採算表(VND)'!E23/$N$1,2) -> 0 | F23: =ROUNDUP('採算表(VND)'!F23/$N$1,2) -> 0 | G23: =ROUNDUP('採算表(VND)'!G23/$N$1,2) -> 0 | H23: =ROUNDUP('採算表(VND)'!H23/$N$1,2) -> 0 | I23: =ROUNDUP('採算表(VND)'!I23/$N$1,2) -> 0 | J23: =ROUNDUP('採算表(VND)'!J23/$N$1,2) -> 0 | ... N23: =ROUNDUP('採算表(VND)'!N23/$N$1,2) -> 0 | O23: =SUM(C23:N23) -> 2166.21
B24: 設計委託費 | C24: =ROUNDUP('採算表(VND)'!C24/$N$1,2) -> 0 | D24: =ROUNDUP('採算表(VND)'!D24/$N$1,2) -> 0 | E24: =ROUNDUP('採算表(VND)'!E24/$N$1,2) -> 0 | F24: =ROUNDUP('採算表(VND)'!F24/$N$1,2) -> 0 | G24: =ROUNDUP('採算表(VND)'!G24/$N$1,2) -> 0 | H24: =ROUNDUP('採算表(VND)'!H24/$N$1,2) -> 0 | I24: =ROUNDUP('採算表(VND)'!I24/$N$1,2) -> 0 | J24: =ROUNDUP('採算表(VND)'!J24/$N$1,2) -> 0 | ... N24: =ROUNDUP('採算表(VND)'!N24/$N$1,2) -> 0 | O24: =SUM(C24:N24) -> 0
B25: 消耗品費 | C25: =ROUNDUP('採算表(VND)'!C25/$N$1,2) -> 139.32 | D25: =ROUNDUP('採算表(VND)'!D25/$N$1,2) -> 97.15 | E25: =ROUNDUP('採算表(VND)'!E25/$N$1,2) -> 140.93 | F25: =ROUNDUP('採算表(VND)'!F25/$N$1,2) -> 99.42 | G25: =ROUNDUP('採算表(VND)'!G25/$N$1,2) -> 139.92 | H25: =ROUNDUP('採算表(VND)'!H25/$N$1,2) -> 103.85 | I25: =ROUNDUP('採算表(VND)'!I25/$N$1,2) -> 141.27 | J25: =ROUNDUP('採算表(VND)'!J25/$N$1,2) -> 97.72 | ... N25: =ROUNDUP('採算表(VND)'!N25/$N$1,2) -> 97.56 | O25: =SUM(C25:N25) -> 1433.12
... B65: 本社機構経費 | C65: =ROUNDUP('採算表(VND)'!C65/$N$1,2) -> 0 | D65: =ROUNDUP('採算表(VND)'!D65/$N$1,2) -> 0 | E65: =ROUNDUP('採算表(VND)'!E65/$N$1,2) -> 0 | F65: =ROUNDUP('採算表(VND)'!F65/$N$1,2) -> 0 | G65: =ROUNDUP('採算表(VND)'!G65/$N$1,2) -> 0 | H65: =ROUNDUP('採算表(VND)'!H65/$N$1,2) -> 0 | I65: =ROUNDUP('採算表(VND)'!I65/$N$1,2) -> 0 | J65: =ROUNDUP('採算表(VND)'!J65/$N$1,2) -> 0 | ... N65: =ROUNDUP('採算表(VND)'!N65/$N$1,2) -> 0 | O65: =SUM(C65:N65) -> 0
B66: 差引収益 | C66: =C12-C13 -> -0.06 | D66: =IF(ISBLANK(D4),"",D12-D13) -> -0.06 | E66: =IF(ISBLANK(E4),"",E12-E13) -> -0.04 | F66: =IF(ISBLANK(F4),"",F12-F13) -> -0.05 | G66: =IF(ISBLANK(G4),"",G12-G13) -> -0.06 | H66: =IF(ISBLANK(H4),"",H12-H13) -> -0.07 | I66: =IF(ISBLANK(I4),"",I12-I13) -> -0.05 | J66: =IF(ISBLANK(J4),"",J12-J13) -> -0.06 | K66: =IF(ISBLANK(K4),"",K12-K13) -> -0.06 | ... O66: =IF(ISBLANK(O4),"",O12-O13) -> -0.7
B67: 総時間 | C67: =C73+C79 -> 0 | D67: =IF(ISBLANK(D4),"",D73+D79) -> 0 | E67: =IF(ISBLANK(E4),"",E73+E79) -> 0 | F67: =IF(ISBLANK(F4),"",F73+F79) -> 0 | G67: =IF(ISBLANK(G4),"",G73+G79) -> 0 | H67: =IF(ISBLANK(H4),"",H73+H79) -> 0 | I67: =IF(ISBLANK(I4),"",I73+I79) -> 0 | J67: =IF(ISBLANK(J4),"",J73+J79) -> 0 | K67: =IF(ISBLANK(K4),"",K73+K79) -> 0 | ... O67: =IF(ISBLANK(O4),"",O73+O79) -> 0
B68: 直接部門 | C68: ='採算表(VND)'!C68 -> 2767 | D68: ='採算表(VND)'!D68 -> 2709.5 | E68: ='採算表(VND)'!E68 -> 2979.5 | F68: ='採算表(VND)'!F68 -> 3190 | G68: ='採算表(VND)'!G68 -> 2767 | H68: ='採算表(VND)'!H68 -> 2616 | I68: ='採算表(VND)'!I68 -> 3190 | J68: ='採算表(VND)'!J68 -> 2767 | ... N68: ='採算表(VND)'!N68 -> 2902 | O68: =SUM(C68:N68) -> 34066
B69: 部内間接部門 | C69: ='採算表(VND)'!C69 -> 0 | D69: ='採算表(VND)'!D69 -> 0 | E69: ='採算表(VND)'!E69 -> 0 | F69: ='採算表(VND)'!F69 -> 0 | G69: ='採算表(VND)'!G69 -> 0 | H69: ='採算表(VND)'!H69 -> 0 | I69: ='採算表(VND)'!I69 -> 0 | J69: ='採算表(VND)'!J69 -> 0 | ... N69: ='採算表(VND)'!N69 -> 0 | O69: =SUM(C69:N69) -> 0
B70: 部外間接部門1 | C70: ='採算表(VND)'!C70 -> 0 | D70: ='採算表(VND)'!D70 -> 0 | E70: ='採算表(VND)'!E70 -> 0 | F70: ='採算表(VND)'!F70 -> 0 | G70: ='採算表(VND)'!G70 -> 0 | H70: ='採算表(VND)'!H70 -> 0 | I70: ='採算表(VND)'!I70 -> 0 | J70: ='採算表(VND)'!J70 -> 0 | ... N70: ='採算表(VND)'!N70 -> 0 | O70: =SUM(C70:N70) -> 0
B71: 部外間接部門2 | C71: ='採算表(VND)'!C71 -> 0 | D71: ='採算表(VND)'!D71 -> 0 | E71: ='採算表(VND)'!E71 -> 0 | F71: ='採算表(VND)'!F71 -> 0 | G71: ='採算表(VND)'!G71 -> 0 | H71: ='採算表(VND)'!H71 -> 0 | I71: ='採算表(VND)'!I71 -> 0 | J71: ='採算表(VND)'!J71 -> 0 | ... N71: ='採算表(VND)'!N71 -> 0 | O71: =SUM(C71:N71) -> 0
B72: 工場間接部門 | C72: ='採算表(VND)'!C72 -> -2767 | D72: ='採算表(VND)'!D72 -> -2709.5 | E72: ='採算表(VND)'!E72 -> -2979.5 | F72: ='採算表(VND)'!F72 -> -3190 | G72: ='採算表(VND)'!G72 -> -2767 | H72: ='採算表(VND)'!H72 -> -2616 | I72: ='採算表(VND)'!I72 -> -3190 | J72: ='採算表(VND)'!J72 -> -2767 | ... N72: ='採算表(VND)'!N72 -> -2902 | O72: =SUM(C72:N72) -> -34066
B73: 定時間合計 | C73: =SUM(C68:C72) -> 0 | D73: =IF(ISBLANK(D4),"",SUM(D68:D72)) -> 0 | E73: =IF(ISBLANK(E4),"",SUM(E68:E72)) -> 0 | F73: =IF(ISBLANK(F4),"",SUM(F68:F72)) -> 0 | G73: =IF(ISBLANK(G4),"",SUM(G68:G72)) -> 0 | H73: =IF(ISBLANK(H4),"",SUM(H68:H72)) -> 0 | I73: =IF(ISBLANK(I4),"",SUM(I68:I72)) -> 0 | J73: =IF(ISBLANK(J4),"",SUM(J68:J72)) -> 0 | K73: =IF(ISBLANK(K4),"",SUM(K68:K72)) -> 0 | ... O73: =IF(ISBLANK(O4),"",SUM(O68:O72)) -> 0
B74: 直接部門 | C74: ='採算表(VND)'!C74 -> 176.5 | D74: ='採算表(VND)'!D74 -> 193.5 | E74: ='採算表(VND)'!E74 -> 185.5 | F74: ='採算表(VND)'!F74 -> 203.5 | G74: ='採算表(VND)'!G74 -> 176.5 | H74: ='採算表(VND)'!H74 -> 251.5 | I74: ='採算表(VND)'!I74 -> 203.5 | J74: ='採算表(VND)'!J74 -> 246.5 | ... N74: ='採算表(VND)'!N74 -> 176.5 | O74: =SUM(C74:N74) -> 2316
B75: 部内間接部門 | C75: ='採算表(VND)'!C75 -> 0 | D75: ='採算表(VND)'!D75 -> 0 | E75: ='採算表(VND)'!E75 -> 0 | F75: ='採算表(VND)'!F75 -> 0 | G75: ='採算表(VND)'!G75 -> 0 | H75: ='採算表(VND)'!H75 -> 0 | I75: ='採算表(VND)'!I75 -> 0 | J75: ='採算表(VND)'!J75 -> 0 | ... N75: ='採算表(VND)'!N75 -> 0 | O75: =SUM(C75:N75) -> 0
B76: 部外間接部門1 | C76: ='採算表(VND)'!C76 -> 0 | D76: ='採算表(VND)'!D76 -> 0 | E76: ='採算表(VND)'!E76 -> 0 | F76: ='採算表(VND)'!F76 -> 0 | G76: ='採算表(VND)'!G76 -> 0 | H76: ='採算表(VND)'!H76 -> 0 | I76: ='採算表(VND)'!I76 -> 0 | J76: ='採算表(VND)'!J76 -> 0 | ... N76: ='採算表(VND)'!N76 -> 0 | O76: =SUM(C76:N76) -> 0
B77: 部外間接部門2 | C77: ='採算表(VND)'!C77 -> 0 | D77: ='採算表(VND)'!D77 -> 0 | E77: ='採算表(VND)'!E77 -> 0 | F77: ='採算表(VND)'!F77 -> 0 | G77: ='採算表(VND)'!G77 -> 0 | H77: ='採算表(VND)'!H77 -> 0 | I77: ='採算表(VND)'!I77 -> 0 | J77: ='採算表(VND)'!J77 -> 0 | ... N77: ='採算表(VND)'!N77 -> 0 | O77: =SUM(C77:N77) -> 0
B78: 工場間接部門 | C78: ='採算表(VND)'!C78 -> -176.5 | D78: ='採算表(VND)'!D78 -> -193.5 | E78: ='採算表(VND)'!E78 -> -185.5 | F78: ='採算表(VND)'!F78 -> -203.5 | G78: ='採算表(VND)'!G78 -> -176.5 | H78: ='採算表(VND)'!H78 -> -251.5 | I78: ='採算表(VND)'!I78 -> -203.5 | J78: ='採算表(VND)'!J78 -> -246.5 | ... N78: ='採算表(VND)'!N78 -> -176.5 | O78: =SUM(C78:N78) -> -2316
B79: 残業時間合計 | C79: =SUM(C74:C78) -> 0 | D79: =IF(ISBLANK(D4),"",SUM(D74:D78)) -> 0 | E79: =IF(ISBLANK(E4),"",SUM(E74:E78)) -> 0 | F79: =IF(ISBLANK(F4),"",SUM(F74:F78)) -> 0 | G79: =IF(ISBLANK(G4),"",SUM(G74:G78)) -> 0 | H79: =IF(ISBLANK(H4),"",SUM(H74:H78)) -> 0 | I79: =IF(ISBLANK(I4),"",SUM(I74:I78)) -> 0 | J79: =IF(ISBLANK(J4),"",SUM(J74:J78)) -> 0 | K79: =IF(ISBLANK(K4),"",SUM(K74:K78)) -> 0 | ... O79: =IF(ISBLANK(O4),"",SUM(O74:O78)) -> 0
B80: 当月時間当り | C80: =IFERROR(ROUNDDOWN(C66/C67,0),0) -> 0 | D80: =IFERROR(ROUNDDOWN(D66/D67,0),0) -> 0 | E80: =IFERROR(ROUNDDOWN(E66/E67,0),0) -> 0 | F80: =IFERROR(ROUNDDOWN(F66/F67,0),0) -> 0 | G80: =IFERROR(ROUNDDOWN(G66/G67,0),0) -> 0 | H80: =IFERROR(ROUNDDOWN(H66/H67,0),0) -> 0 | I80: =IFERROR(ROUNDDOWN(I66/I67,0),0) -> 0 | J80: =IFERROR(ROUNDDOWN(J66/J67,0),0) -> 0 | ... O80: =IFERROR(ROUNDDOWN(O66/O67,0),0) -> 0
B81: 時間当り生産高 | C81: =IFERROR(ROUNDDOWN(C12/C67,0),0) -> 0 | D81: =IFERROR(ROUNDDOWN(D12/D67,0),0) -> 0 | E81: =IFERROR(ROUNDDOWN(E12/E67,0),0) -> 0 | F81: =IFERROR(ROUNDDOWN(F12/F67,0),0) -> 0 | G81: =IFERROR(ROUNDDOWN(G12/G67,0),0) -> 0 | H81: =IFERROR(ROUNDDOWN(H12/H67,0),0) -> 0 | I81: =IFERROR(ROUNDDOWN(I12/I67,0),0) -> 0 | J81: =IFERROR(ROUNDDOWN(J12/J67,0),0) -> 0 | ... O81: =IFERROR(ROUNDDOWN(O12/O67,0),0) -> 0
B86: ■人員
B87: 出向社員(人) | C87: ='採算表(VND)'!C87 -> 1 | D87: ='採算表(VND)'!D87 -> 1 | E87: ='採算表(VND)'!E87 -> 1 | F87: ='採算表(VND)'!F87 -> 1 | G87: ='採算表(VND)'!G87 -> 1 | H87: ='採算表(VND)'!H87 -> 1 | I87: ='採算表(VND)'!I87 -> 1 | J87: ='採算表(VND)'!J87 -> 1 | ... N87: ='採算表(VND)'!N87 -> 1 | O87: =SUM(C87:N87) -> 12
B88: ローカル社員(人) | C88: ='採算表(VND)'!C88 -> 16 | D88: ='採算表(VND)'!D88 -> 17 | E88: ='採算表(VND)'!E88 -> 17 | F88: ='採算表(VND)'!F88 -> 17 | G88: ='採算表(VND)'!G88 -> 17 | H88: ='採算表(VND)'!H88 -> 17 | I88: ='採算表(VND)'!I88 -> 17 | J88: ='採算表(VND)'!J88 -> 17 | ... N88: ='採算表(VND)'!N88 -> 17 | O88: =SUM(C88:N88) -> 203
B89: 人員計 | C89: =C87+C88 -> 17 | D89: =D87+D88 -> 18 | E89: =E87+E88 -> 18 | F89: =F87+F88 -> 18 | G89: =G87+G88 -> 18 | H89: =H87+H88 -> 18 | I89: =I87+I88 -> 18 | J89: =J87+J88 -> 18 | ... O89: =O87+O88 -> 215
B91: ■定時間
B92: 出向社員定時 | C92: ='採算表(VND)'!C92 -> 170 | D92: ='採算表(VND)'!D92 -> 161.5 | E92: ='採算表(VND)'!E92 -> 178.5 | F92: ='採算表(VND)'!F92 -> 195.5 | G92: ='採算表(VND)'!G92 -> 170 | H92: ='採算表(VND)'!H92 -> 161.5 | I92: ='採算表(VND)'!I92 -> 195.5 | J92: ='採算表(VND)'!J92 -> 170 | ... N92: ='採算表(VND)'!N92 -> 170 | O92: =SUM(C92:N92) -> 2057
B93: ローカル社員定時 | C93: ='採算表(VND)'!C93 -> 2597 | D93: ='採算表(VND)'!D93 -> 2548 | E93: ='採算表(VND)'!E93 -> 2801 | F93: ='採算表(VND)'!F93 -> 2994.5 | G93: ='採算表(VND)'!G93 -> 2597 | H93: ='採算表(VND)'!H93 -> 2454.5 | I93: ='採算表(VND)'!I93 -> 2994.5 | J93: ='採算表(VND)'!J93 -> 2597 | ... N93: ='採算表(VND)'!N93 -> 2732 | O93: =SUM(C93:N93) -> 32009
B94: 人員計 | C94: =C92+C93 -> 2767 | D94: =D92+D93 -> 2709.5 | E94: =E92+E93 -> 2979.5 | F94: =F92+F93 -> 3190 | G94: =G92+G93 -> 2767 | H94: =H92+H93 -> 2616 | I94: =I92+I93 -> 3190 | J94: =J92+J93 -> 2767 | ... O94: =O92+O93 -> 34066
B96: ■残業時間
B97: 出向社員残業 | C97: ='採算表(VND)'!C97 -> 40 | D97: ='採算表(VND)'!D97 -> 38 | E97: ='採算表(VND)'!E97 -> 42 | F97: ='採算表(VND)'!F97 -> 46 | G97: ='採算表(VND)'!G97 -> 40 | H97: ='採算表(VND)'!H97 -> 38 | I97: ='採算表(VND)'!I97 -> 46 | J97: ='採算表(VND)'!J97 -> 40 | ... N97: ='採算表(VND)'!N97 -> 40 | O97: =SUM(C97:N97) -> 484
B98: ローカル社員残業 | C98: ='採算表(VND)'!C98 -> 136.5 | D98: ='採算表(VND)'!D98 -> 155.5 | E98: ='採算表(VND)'!E98 -> 143.5 | F98: ='採算表(VND)'!F98 -> 157.5 | G98: ='採算表(VND)'!G98 -> 136.5 | H98: ='採算表(VND)'!H98 -> 213.5 | I98: ='採算表(VND)'!I98 -> 157.5 | J98: ='採算表(VND)'!J98 -> 206.5 | ... N98: ='採算表(VND)'!N98 -> 136.5 | O98: =SUM(C98:N98) -> 1832
B99: 人員計 | C99: =C97+C98 -> 176.5 | D99: =D97+D98 -> 193.5 | E99: =E97+E98 -> 185.5 | F99: =F97+F98 -> 203.5 | G99: =G97+G98 -> 176.5 | H99: =H97+H98 -> 251.5 | I99: =I97+I98 -> 203.5 | J99: =J97+J98 -> 246.5 | ... O99: =O97+O98 -> 2316

Sheet 採算表(VND)
B1: 組織名 | C1: ='内訳ﾘｽﾄ(4～3月)'!A1 -> MP FY2026_各予定
B2: ='内訳ﾘｽﾄ(4～3月)'!C5 -> 総務課
C3: 2 | D3: 3 | E3: 4 | F3: 5 | G3: 6 | H3: 7 | I3: 8 | J3: 9 | K3: 10 | L3: 11 | M3: 12 | N3: 13
B4: 項目 ＼ 部門 | C4: ='内訳ﾘｽﾄ(4～3月)'!F4 -> 4 | D4: 5 | E4: 6 | F4: 7 | G4: 8 | H4: 9 | I4: 10 | J4: 11 | K4: 12 | L4: 1 | M4: 2 | N4: 3 | O4: 合計
B5: 総出荷 | C5: =C8+C9 -> 0 | D5: =D8+D9 -> 0 | E5: =E8+E9 -> 0 | F5: =F8+F9 -> 0 | G5: =G8+G9 -> 0 | H5: =H8+H9 -> 0 | I5: =I8+I9 -> 0 | J5: =J8+J9 -> 0 | ... O5: =O8+O9 -> 0
B6: 社外出荷 | C6: =SUMIF('内訳ﾘｽﾄ(4～3月)'!$D$26:$D$973,'採算表(VND)'!$B6,'内訳ﾘｽﾄ(4～3月)'!F$26:F$973) -> 0 | D6: =SUMIF('内訳ﾘｽﾄ(4～3月)'!$D$26:$D$973,'採算表(VND)'!$B6,'内訳ﾘｽﾄ(4～3月)'!G$26:G$973) -> 0 | E6: =SUMIF('内訳ﾘｽﾄ(4～3月)'!$D$26:$D$973,'採算表(VND)'!$B6,'内訳ﾘｽﾄ(4～3月)'!H$26:H$973) -> 0 | F6: =SUMIF('内訳ﾘｽﾄ(4～3月)'!$D$26:$D$973,'採算表(VND)'!$B6,'内訳ﾘｽﾄ(4～3月)'!I$26:I$973) -> 0 | G6: =SUMIF('内訳ﾘｽﾄ(4～3月)'!$D$26:$D$973,'採算表(VND)'!$B6,'内訳ﾘｽﾄ(4～3月)'!J$26:J$973) -> 0 | H6: =SUMIF('内訳ﾘｽﾄ(4～3月)'!$D$26:$D$973,'採算表(VND)'!$B6,'内訳ﾘｽﾄ(4～3月)'!K$26:K$973) -> 0 | I6: =SUMIF('内訳ﾘｽﾄ(4～3月)'!$D$26:$D$973,'採算表(VND)'!$B6,'内訳ﾘｽﾄ(4～3月)'!L$26:L$973) -> 0 | J6: =SUMIF('内訳ﾘｽﾄ(4～3月)'!$D$26:$D$973,'採算表(VND)'!$B6,'内訳ﾘｽﾄ(4～3月)'!M$26:M$973) -> 0 | ... N6: =SUMIF('内訳ﾘｽﾄ(4～3月)'!$D$26:$D$973,'採算表(VND)'!$B6,'内訳ﾘｽﾄ(4～3月)'!Q$26:Q$973) -> 0 | O6: =SUMIF('内訳ﾘｽﾄ(4～3月)'!$D$26:$D$772,'採算表(VND)'!$B6,'内訳ﾘｽﾄ(4～3月)'!R$26:R$772) -> 0
B7: 販売支援 | C7: =SUMIF('内訳ﾘｽﾄ(4～3月)'!$D$26:$D$973,'採算表(VND)'!$B7,'内訳ﾘｽﾄ(4～3月)'!F$26:F$973) -> 0 | D7: =SUMIF('内訳ﾘｽﾄ(4～3月)'!$D$26:$D$973,'採算表(VND)'!$B7,'内訳ﾘｽﾄ(4～3月)'!G$26:G$973) -> 0 | E7: =SUMIF('内訳ﾘｽﾄ(4～3月)'!$D$26:$D$973,'採算表(VND)'!$B7,'内訳ﾘｽﾄ(4～3月)'!H$26:H$973) -> 0 | F7: =SUMIF('内訳ﾘｽﾄ(4～3月)'!$D$26:$D$973,'採算表(VND)'!$B7,'内訳ﾘｽﾄ(4～3月)'!I$26:I$973) -> 0 | G7: =SUMIF('内訳ﾘｽﾄ(4～3月)'!$D$26:$D$973,'採算表(VND)'!$B7,'内訳ﾘｽﾄ(4～3月)'!J$26:J$973) -> 0 | H7: =SUMIF('内訳ﾘｽﾄ(4～3月)'!$D$26:$D$973,'採算表(VND)'!$B7,'内訳ﾘｽﾄ(4～3月)'!K$26:K$973) -> 0 | I7: =SUMIF('内訳ﾘｽﾄ(4～3月)'!$D$26:$D$973,'採算表(VND)'!$B7,'内訳ﾘｽﾄ(4～3月)'!L$26:L$973) -> 0 | J7: =SUMIF('内訳ﾘｽﾄ(4～3月)'!$D$26:$D$973,'採算表(VND)'!$B7,'内訳ﾘｽﾄ(4～3月)'!M$26:M$973) -> 0 | ... N7: =SUMIF('内訳ﾘｽﾄ(4～3月)'!$D$26:$D$973,'採算表(VND)'!$B7,'内訳ﾘｽﾄ(4～3月)'!Q$26:Q$973) -> 0 | O7: =SUMIF('内訳ﾘｽﾄ(4～3月)'!$D$26:$D$772,'採算表(VND)'!$B7,'内訳ﾘｽﾄ(4～3月)'!R$26:R$772) -> 0
B8: 社外出荷合計 | C8: =C6+C7 -> 0 | D8: =D6+D7 -> 0 | E8: =E6+E7 -> 0 | F8: =F6+F7 -> 0 | G8: =G6+G7 -> 0 | H8: =H6+H7 -> 0 | I8: =I6+I7 -> 0 | J8: =J6+J7 -> 0 | ... O8: =O6+O7 -> 0
B9: 社内売 | C9: =SUMIF('内訳ﾘｽﾄ(4～3月)'!$D$26:$D$973,'採算表(VND)'!$B9,'内訳ﾘｽﾄ(4～3月)'!F$26:F$973) -> 0 | D9: =SUMIF('内訳ﾘｽﾄ(4～3月)'!$D$26:$D$973,'採算表(VND)'!$B9,'内訳ﾘｽﾄ(4～3月)'!G$26:G$973) -> 0 | E9: =SUMIF('内訳ﾘｽﾄ(4～3月)'!$D$26:$D$973,'採算表(VND)'!$B9,'内訳ﾘｽﾄ(4～3月)'!H$26:H$973) -> 0 | F9: =SUMIF('内訳ﾘｽﾄ(4～3月)'!$D$26:$D$973,'採算表(VND)'!$B9,'内訳ﾘｽﾄ(4～3月)'!I$26:I$973) -> 0 | G9: =SUMIF('内訳ﾘｽﾄ(4～3月)'!$D$26:$D$973,'採算表(VND)'!$B9,'内訳ﾘｽﾄ(4～3月)'!J$26:J$973) -> 0 | H9: =SUMIF('内訳ﾘｽﾄ(4～3月)'!$D$26:$D$973,'採算表(VND)'!$B9,'内訳ﾘｽﾄ(4～3月)'!K$26:K$973) -> 0 | I9: =SUMIF('内訳ﾘｽﾄ(4～3月)'!$D$26:$D$973,'採算表(VND)'!$B9,'内訳ﾘｽﾄ(4～3月)'!L$26:L$973) -> 0 | J9: =SUMIF('内訳ﾘｽﾄ(4～3月)'!$D$26:$D$973,'採算表(VND)'!$B9,'内訳ﾘｽﾄ(4～3月)'!M$26:M$973) -> 0 | ... N9: =SUMIF('内訳ﾘｽﾄ(4～3月)'!$D$26:$D$973,'採算表(VND)'!$B9,'内訳ﾘｽﾄ(4～3月)'!Q$26:Q$973) -> 0 | O9: =SUMIF('内訳ﾘｽﾄ(4～3月)'!$D$26:$D$772,'採算表(VND)'!$B9,'内訳ﾘｽﾄ(4～3月)'!R$26:R$772) -> 0
B10: 社内買 | C10: =SUMIF('内訳ﾘｽﾄ(4～3月)'!$D$26:$D$973,'採算表(VND)'!$B10,'内訳ﾘｽﾄ(4～3月)'!F$26:F$973) -> 0 | D10: =SUMIF('内訳ﾘｽﾄ(4～3月)'!$D$26:$D$973,'採算表(VND)'!$B10,'内訳ﾘｽﾄ(4～3月)'!G$26:G$973) -> 0 | E10: =SUMIF('内訳ﾘｽﾄ(4～3月)'!$D$26:$D$973,'採算表(VND)'!$B10,'内訳ﾘｽﾄ(4～3月)'!H$26:H$973) -> 0 | F10: =SUMIF('内訳ﾘｽﾄ(4～3月)'!$D$26:$D$973,'採算表(VND)'!$B10,'内訳ﾘｽﾄ(4～3月)'!I$26:I$973) -> 0 | G10: =SUMIF('内訳ﾘｽﾄ(4～3月)'!$D$26:$D$973,'採算表(VND)'!$B10,'内訳ﾘｽﾄ(4～3月)'!J$26:J$973) -> 0 | H10: =SUMIF('内訳ﾘｽﾄ(4～3月)'!$D$26:$D$973,'採算表(VND)'!$B10,'内訳ﾘｽﾄ(4～3月)'!K$26:K$973) -> 0 | I10: =SUMIF('内訳ﾘｽﾄ(4～3月)'!$D$26:$D$973,'採算表(VND)'!$B10,'内訳ﾘｽﾄ(4～3月)'!L$26:L$973) -> 0 | J10: =SUMIF('内訳ﾘｽﾄ(4～3月)'!$D$26:$D$973,'採算表(VND)'!$B10,'内訳ﾘｽﾄ(4～3月)'!M$26:M$973) -> 0 | ... N10: =SUMIF('内訳ﾘｽﾄ(4～3月)'!$D$26:$D$973,'採算表(VND)'!$B10,'内訳ﾘｽﾄ(4～3月)'!Q$26:Q$973) -> 0 | O10: =SUMIF('内訳ﾘｽﾄ(4～3月)'!$D$26:$D$772,'採算表(VND)'!$B10,'内訳ﾘｽﾄ(4～3月)'!R$26:R$772) -> 0
B12: 総生産 | C12: =C5-C10 -> 0 | D12: =D5-D10 -> 0 | E12: =E5-E10 -> 0 | F12: =F5-F10 -> 0 | G12: =G5-G10 -> 0 | H12: =H5-H10 -> 0 | I12: =I5-I10 -> 0 | J12: =J5-J10 -> 0 | ... O12: =O5-O10 -> 0
B13: 控除額 | C13: =SUM(C14:C65) -> 0 | D13: =SUM(D14:D65) -> 0 | E13: =SUM(E14:E65) -> 0 | F13: =SUM(F14:F65) -> 0 | G13: =SUM(G14:G65) -> 0 | H13: =SUM(H14:H65) -> 0 | I13: =SUM(I14:I65) -> 0 | J13: =SUM(J14:J65) -> 0 | ... O13: =SUM(O14:O65) -> 0
B14: 材料費 | C14: =SUMIF('内訳ﾘｽﾄ(4～3月)'!$D$26:$D$973,$B14,'内訳ﾘｽﾄ(4～3月)'!F$26:F$973) -> 0 | D14: =SUMIF('内訳ﾘｽﾄ(4～3月)'!$D$26:$D$973,$B14,'内訳ﾘｽﾄ(4～3月)'!G$26:G$973) -> 0 | E14: =SUMIF('内訳ﾘｽﾄ(4～3月)'!$D$26:$D$973,$B14,'内訳ﾘｽﾄ(4～3月)'!H$26:H$973) -> 0 | F14: =SUMIF('内訳ﾘｽﾄ(4～3月)'!$D$26:$D$973,$B14,'内訳ﾘｽﾄ(4～3月)'!I$26:I$973) -> 0 | G14: =SUMIF('内訳ﾘｽﾄ(4～3月)'!$D$26:$D$973,$B14,'内訳ﾘｽﾄ(4～3月)'!J$26:J$973) -> 0 | H14: =SUMIF('内訳ﾘｽﾄ(4～3月)'!$D$26:$D$973,$B14,'内訳ﾘｽﾄ(4～3月)'!K$26:K$973) -> 0 | I14: =SUMIF('内訳ﾘｽﾄ(4～3月)'!$D$26:$D$973,$B14,'内訳ﾘｽﾄ(4～3月)'!L$26:L$973) -> 0 | J14: =SUMIF('内訳ﾘｽﾄ(4～3月)'!$D$26:$D$973,$B14,'内訳ﾘｽﾄ(4～3月)'!M$26:M$973) -> 0 | ... N14: =SUMIF('内訳ﾘｽﾄ(4～3月)'!$D$26:$D$973,$B14,'内訳ﾘｽﾄ(4～3月)'!Q$26:Q$973) -> 0 | O14: =SUMIF('内訳ﾘｽﾄ(4～3月)'!$D$26:$D$772,'採算表(VND)'!$B14,'内訳ﾘｽﾄ(4～3月)'!R$26:R$772) -> 0
B15: 設計変更材料費 | C15: =SUMIF('内訳ﾘｽﾄ(4～3月)'!$D$26:$D$973,$B15,'内訳ﾘｽﾄ(4～3月)'!F$26:F$973) -> 0 | D15: =SUMIF('内訳ﾘｽﾄ(4～3月)'!$D$26:$D$973,$B15,'内訳ﾘｽﾄ(4～3月)'!G$26:G$973) -> 0 | E15: =SUMIF('内訳ﾘｽﾄ(4～3月)'!$D$26:$D$973,$B15,'内訳ﾘｽﾄ(4～3月)'!H$26:H$973) -> 0 | F15: =SUMIF('内訳ﾘｽﾄ(4～3月)'!$D$26:$D$973,$B15,'内訳ﾘｽﾄ(4～3月)'!I$26:I$973) -> 0 | G15: =SUMIF('内訳ﾘｽﾄ(4～3月)'!$D$26:$D$973,$B15,'内訳ﾘｽﾄ(4～3月)'!J$26:J$973) -> 0 | H15: =SUMIF('内訳ﾘｽﾄ(4～3月)'!$D$26:$D$973,$B15,'内訳ﾘｽﾄ(4～3月)'!K$26:K$973) -> 0 | I15: =SUMIF('内訳ﾘｽﾄ(4～3月)'!$D$26:$D$973,$B15,'内訳ﾘｽﾄ(4～3月)'!L$26:L$973) -> 0 | J15: =SUMIF('内訳ﾘｽﾄ(4～3月)'!$D$26:$D$973,$B15,'内訳ﾘｽﾄ(4～3月)'!M$26:M$973) -> 0 | ... N15: =SUMIF('内訳ﾘｽﾄ(4～3月)'!$D$26:$D$973,$B15,'内訳ﾘｽﾄ(4～3月)'!Q$26:Q$973) -> 0 | O15: =SUMIF('内訳ﾘｽﾄ(4～3月)'!$D$26:$D$772,'採算表(VND)'!$B15,'内訳ﾘｽﾄ(4～3月)'!R$26:R$772) -> 0
B16: 仕掛仕損 | C16: =SUMIF('内訳ﾘｽﾄ(4～3月)'!$D$26:$D$973,$B16,'内訳ﾘｽﾄ(4～3月)'!F$26:F$973) -> 0 | D16: =SUMIF('内訳ﾘｽﾄ(4～3月)'!$D$26:$D$973,$B16,'内訳ﾘｽﾄ(4～3月)'!G$26:G$973) -> 0 | E16: =SUMIF('内訳ﾘｽﾄ(4～3月)'!$D$26:$D$973,$B16,'内訳ﾘｽﾄ(4～3月)'!H$26:H$973) -> 0 | F16: =SUMIF('内訳ﾘｽﾄ(4～3月)'!$D$26:$D$973,$B16,'内訳ﾘｽﾄ(4～3月)'!I$26:I$973) -> 0 | G16: =SUMIF('内訳ﾘｽﾄ(4～3月)'!$D$26:$D$973,$B16,'内訳ﾘｽﾄ(4～3月)'!J$26:J$973) -> 0 | H16: =SUMIF('内訳ﾘｽﾄ(4～3月)'!$D$26:$D$973,$B16,'内訳ﾘｽﾄ(4～3月)'!K$26:K$973) -> 0 | I16: =SUMIF('内訳ﾘｽﾄ(4～3月)'!$D$26:$D$973,$B16,'内訳ﾘｽﾄ(4～3月)'!L$26:L$973) -> 0 | J16: =SUMIF('内訳ﾘｽﾄ(4～3月)'!$D$26:$D$973,$B16,'内訳ﾘｽﾄ(4～3月)'!M$26:M$973) -> 0 | ... N16: =SUMIF('内訳ﾘｽﾄ(4～3月)'!$D$26:$D$973,$B16,'内訳ﾘｽﾄ(4～3月)'!Q$26:Q$973) -> 0 | O16: =SUMIF('内訳ﾘｽﾄ(4～3月)'!$D$26:$D$772,'採算表(VND)'!$B16,'内訳ﾘｽﾄ(4～3月)'!R$26:R$772) -> 0
B17: 仕入製商品費 | C17: =SUMIF('内訳ﾘｽﾄ(4～3月)'!$D$26:$D$973,$B17,'内訳ﾘｽﾄ(4～3月)'!F$26:F$973) -> 0 | D17: =SUMIF('内訳ﾘｽﾄ(4～3月)'!$D$26:$D$973,$B17,'内訳ﾘｽﾄ(4～3月)'!G$26:G$973) -> 0 | E17: =SUMIF('内訳ﾘｽﾄ(4～3月)'!$D$26:$D$973,$B17,'内訳ﾘｽﾄ(4～3月)'!H$26:H$973) -> 0 | F17: =SUMIF('内訳ﾘｽﾄ(4～3月)'!$D$26:$D$973,$B17,'内訳ﾘｽﾄ(4～3月)'!I$26:I$973) -> 0 | G17: =SUMIF('内訳ﾘｽﾄ(4～3月)'!$D$26:$D$973,$B17,'内訳ﾘｽﾄ(4～3月)'!J$26:J$973) -> 0 | H17: =SUMIF('内訳ﾘｽﾄ(4～3月)'!$D$26:$D$973,$B17,'内訳ﾘｽﾄ(4～3月)'!K$26:K$973) -> 0 | I17: =SUMIF('内訳ﾘｽﾄ(4～3月)'!$D$26:$D$973,$B17,'内訳ﾘｽﾄ(4～3月)'!L$26:L$973) -> 0 | J17: =SUMIF('内訳ﾘｽﾄ(4～3月)'!$D$26:$D$973,$B17,'内訳ﾘｽﾄ(4～3月)'!M$26:M$973) -> 0 | ... N17: =SUMIF('内訳ﾘｽﾄ(4～3月)'!$D$26:$D$973,$B17,'内訳ﾘｽﾄ(4～3月)'!Q$26:Q$973) -> 0 | O17: =SUMIF('内訳ﾘｽﾄ(4～3月)'!$D$26:$D$772,'採算表(VND)'!$B17,'内訳ﾘｽﾄ(4～3月)'!R$26:R$772) -> 0
B18: 内製品有償支給原価 | C18: =SUMIF('内訳ﾘｽﾄ(4～3月)'!$D$26:$D$973,$B18,'内訳ﾘｽﾄ(4～3月)'!F$26:F$973) -> 0 | D18: =SUMIF('内訳ﾘｽﾄ(4～3月)'!$D$26:$D$973,$B18,'内訳ﾘｽﾄ(4～3月)'!G$26:G$973) -> 0 | E18: =SUMIF('内訳ﾘｽﾄ(4～3月)'!$D$26:$D$973,$B18,'内訳ﾘｽﾄ(4～3月)'!H$26:H$973) -> 0 | F18: =SUMIF('内訳ﾘｽﾄ(4～3月)'!$D$26:$D$973,$B18,'内訳ﾘｽﾄ(4～3月)'!I$26:I$973) -> 0 | G18: =SUMIF('内訳ﾘｽﾄ(4～3月)'!$D$26:$D$973,$B18,'内訳ﾘｽﾄ(4～3月)'!J$26:J$973) -> 0 | H18: =SUMIF('内訳ﾘｽﾄ(4～3月)'!$D$26:$D$973,$B18,'内訳ﾘｽﾄ(4～3月)'!K$26:K$973) -> 0 | I18: =SUMIF('内訳ﾘｽﾄ(4～3月)'!$D$26:$D$973,$B18,'内訳ﾘｽﾄ(4～3月)'!L$26:L$973) -> 0 | J18: =SUMIF('内訳ﾘｽﾄ(4～3月)'!$D$26:$D$973,$B18,'内訳ﾘｽﾄ(4～3月)'!M$26:M$973) -> 0 | ... N18: =SUMIF('内訳ﾘｽﾄ(4～3月)'!$D$26:$D$973,$B18,'内訳ﾘｽﾄ(4～3月)'!Q$26:Q$973) -> 0 | O18: =SUMIF('内訳ﾘｽﾄ(4～3月)'!$D$26:$D$772,'採算表(VND)'!$B18,'内訳ﾘｽﾄ(4～3月)'!R$26:R$772) -> 0
B19: 外注加工費 | C19: =SUMIF('内訳ﾘｽﾄ(4～3月)'!$D$26:$D$973,$B19,'内訳ﾘｽﾄ(4～3月)'!F$26:F$973) -> 0 | D19: =SUMIF('内訳ﾘｽﾄ(4～3月)'!$D$26:$D$973,$B19,'内訳ﾘｽﾄ(4～3月)'!G$26:G$973) -> 0 | E19: =SUMIF('内訳ﾘｽﾄ(4～3月)'!$D$26:$D$973,$B19,'内訳ﾘｽﾄ(4～3月)'!H$26:H$973) -> 0 | F19: =SUMIF('内訳ﾘｽﾄ(4～3月)'!$D$26:$D$973,$B19,'内訳ﾘｽﾄ(4～3月)'!I$26:I$973) -> 0 | G19: =SUMIF('内訳ﾘｽﾄ(4～3月)'!$D$26:$D$973,$B19,'内訳ﾘｽﾄ(4～3月)'!J$26:J$973) -> 0 | H19: =SUMIF('内訳ﾘｽﾄ(4～3月)'!$D$26:$D$973,$B19,'内訳ﾘｽﾄ(4～3月)'!K$26:K$973) -> 0 | I19: =SUMIF('内訳ﾘｽﾄ(4～3月)'!$D$26:$D$973,$B19,'内訳ﾘｽﾄ(4～3月)'!L$26:L$973) -> 0 | J19: =SUMIF('内訳ﾘｽﾄ(4～3月)'!$D$26:$D$973,$B19,'内訳ﾘｽﾄ(4～3月)'!M$26:M$973) -> 0 | ... N19: =SUMIF('内訳ﾘｽﾄ(4～3月)'!$D$26:$D$973,$B19,'内訳ﾘｽﾄ(4～3月)'!Q$26:Q$973) -> 0 | O19: =SUMIF('内訳ﾘｽﾄ(4～3月)'!$D$26:$D$772,'採算表(VND)'!$B19,'内訳ﾘｽﾄ(4～3月)'!R$26:R$772) -> 0
B20: 減価償却費 | C20: =SUMIF('内訳ﾘｽﾄ(4～3月)'!$D$26:$D$973,$B20,'内訳ﾘｽﾄ(4～3月)'!F$26:F$973) -> 532445568 | D20: =SUMIF('内訳ﾘｽﾄ(4～3月)'!$D$26:$D$973,$B20,'内訳ﾘｽﾄ(4～3月)'!G$26:G$973) -> 532908428 | E20: =SUMIF('内訳ﾘｽﾄ(4～3月)'!$D$26:$D$973,$B20,'内訳ﾘｽﾄ(4～3月)'!H$26:H$973) -> 532911221 | F20: =SUMIF('内訳ﾘｽﾄ(4～3月)'!$D$26:$D$973,$B20,'内訳ﾘｽﾄ(4～3月)'!I$26:I$973) -> 534570966 | G20: =SUMIF('内訳ﾘｽﾄ(4～3月)'!$D$26:$D$973,$B20,'内訳ﾘｽﾄ(4～3月)'!J$26:J$973) -> 534567919 | H20: =SUMIF('内訳ﾘｽﾄ(4～3月)'!$D$26:$D$973,$B20,'内訳ﾘｽﾄ(4～3月)'!K$26:K$973) -> 534426242 | I20: =SUMIF('内訳ﾘｽﾄ(4～3月)'!$D$26:$D$973,$B20,'内訳ﾘｽﾄ(4～3月)'!L$26:L$973) -> 538334779 | J20: =SUMIF('内訳ﾘｽﾄ(4～3月)'!$D$26:$D$973,$B20,'内訳ﾘｽﾄ(4～3月)'!M$26:M$973) -> 538333256 | ... N20: =SUMIF('内訳ﾘｽﾄ(4～3月)'!$D$26:$D$973,$B20,'内訳ﾘｽﾄ(4～3月)'!Q$26:Q$973) -> 538330718 | O20: =SUMIF('内訳ﾘｽﾄ(4～3月)'!$D$26:$D$772,'採算表(VND)'!$B20,'内訳ﾘｽﾄ(4～3月)'!R$26:R$772) -> 6431819219
B21: 金型償却費 | C21: =SUMIF('内訳ﾘｽﾄ(4～3月)'!$D$26:$D$973,$B21,'内訳ﾘｽﾄ(4～3月)'!F$26:F$973) -> 0 | D21: =SUMIF('内訳ﾘｽﾄ(4～3月)'!$D$26:$D$973,$B21,'内訳ﾘｽﾄ(4～3月)'!G$26:G$973) -> 0 | E21: =SUMIF('内訳ﾘｽﾄ(4～3月)'!$D$26:$D$973,$B21,'内訳ﾘｽﾄ(4～3月)'!H$26:H$973) -> 0 | F21: =SUMIF('内訳ﾘｽﾄ(4～3月)'!$D$26:$D$973,$B21,'内訳ﾘｽﾄ(4～3月)'!I$26:I$973) -> 0 | G21: =SUMIF('内訳ﾘｽﾄ(4～3月)'!$D$26:$D$973,$B21,'内訳ﾘｽﾄ(4～3月)'!J$26:J$973) -> 0 | H21: =SUMIF('内訳ﾘｽﾄ(4～3月)'!$D$26:$D$973,$B21,'内訳ﾘｽﾄ(4～3月)'!K$26:K$973) -> 0 | I21: =SUMIF('内訳ﾘｽﾄ(4～3月)'!$D$26:$D$973,$B21,'内訳ﾘｽﾄ(4～3月)'!L$26:L$973) -> 0 | J21: =SUMIF('内訳ﾘｽﾄ(4～3月)'!$D$26:$D$973,$B21,'内訳ﾘｽﾄ(4～3月)'!M$26:M$973) -> 0 | ... N21: =SUMIF('内訳ﾘｽﾄ(4～3月)'!$D$26:$D$973,$B21,'内訳ﾘｽﾄ(4～3月)'!Q$26:Q$973) -> 0 | O21: =SUMIF('内訳ﾘｽﾄ(4～3月)'!$D$26:$D$772,'採算表(VND)'!$B21,'内訳ﾘｽﾄ(4～3月)'!R$26:R$772) -> 0
B22: 賃借料 | C22: =SUMIF('内訳ﾘｽﾄ(4～3月)'!$D$26:$D$973,$B22,'内訳ﾘｽﾄ(4～3月)'!F$26:F$973) -> 0 | D22: =SUMIF('内訳ﾘｽﾄ(4～3月)'!$D$26:$D$973,$B22,'内訳ﾘｽﾄ(4～3月)'!G$26:G$973) -> 0 | E22: =SUMIF('内訳ﾘｽﾄ(4～3月)'!$D$26:$D$973,$B22,'内訳ﾘｽﾄ(4～3月)'!H$26:H$973) -> 0 | F22: =SUMIF('内訳ﾘｽﾄ(4～3月)'!$D$26:$D$973,$B22,'内訳ﾘｽﾄ(4～3月)'!I$26:I$973) -> 0 | G22: =SUMIF('内訳ﾘｽﾄ(4～3月)'!$D$26:$D$973,$B22,'内訳ﾘｽﾄ(4～3月)'!J$26:J$973) -> 0 | H22: =SUMIF('内訳ﾘｽﾄ(4～3月)'!$D$26:$D$973,$B22,'内訳ﾘｽﾄ(4～3月)'!K$26:K$973) -> 0 | I22: =SUMIF('内訳ﾘｽﾄ(4～3月)'!$D$26:$D$973,$B22,'内訳ﾘｽﾄ(4～3月)'!L$26:L$973) -> 0 | J22: =SUMIF('内訳ﾘｽﾄ(4～3月)'!$D$26:$D$973,$B22,'内訳ﾘｽﾄ(4～3月)'!M$26:M$973) -> 0 | ... N22: =SUMIF('内訳ﾘｽﾄ(4～3月)'!$D$26:$D$973,$B22,'内訳ﾘｽﾄ(4～3月)'!Q$26:Q$973) -> 0 | O22: =SUMIF('内訳ﾘｽﾄ(4～3月)'!$D$26:$D$772,'採算表(VND)'!$B22,'内訳ﾘｽﾄ(4～3月)'!R$26:R$772) -> 0
B23: 保険料 | C23: =SUMIF('内訳ﾘｽﾄ(4～3月)'!$D$26:$D$973,$B23,'内訳ﾘｽﾄ(4～3月)'!F$26:F$973) -> 0 | D23: =SUMIF('内訳ﾘｽﾄ(4～3月)'!$D$26:$D$973,$B23,'内訳ﾘｽﾄ(4～3月)'!G$26:G$973) -> 55000000 | E23: =SUMIF('内訳ﾘｽﾄ(4～3月)'!$D$26:$D$973,$B23,'内訳ﾘｽﾄ(4～3月)'!H$26:H$973) -> 0 | F23: =SUMIF('内訳ﾘｽﾄ(4～3月)'!$D$26:$D$973,$B23,'内訳ﾘｽﾄ(4～3月)'!I$26:I$973) -> 0 | G23: =SUMIF('内訳ﾘｽﾄ(4～3月)'!$D$26:$D$973,$B23,'内訳ﾘｽﾄ(4～3月)'!J$26:J$973) -> 0 | H23: =SUMIF('内訳ﾘｽﾄ(4～3月)'!$D$26:$D$973,$B23,'内訳ﾘｽﾄ(4～3月)'!K$26:K$973) -> 0 | I23: =SUMIF('内訳ﾘｽﾄ(4～3月)'!$D$26:$D$973,$B23,'内訳ﾘｽﾄ(4～3月)'!L$26:L$973) -> 0 | J23: =SUMIF('内訳ﾘｽﾄ(4～3月)'!$D$26:$D$973,$B23,'内訳ﾘｽﾄ(4～3月)'!M$26:M$973) -> 0 | ... N23: =SUMIF('内訳ﾘｽﾄ(4～3月)'!$D$26:$D$973,$B23,'内訳ﾘｽﾄ(4～3月)'!Q$26:Q$973) -> 0 | O23: =SUMIF('内訳ﾘｽﾄ(4～3月)'!$D$26:$D$772,'採算表(VND)'!$B23,'内訳ﾘｽﾄ(4～3月)'!R$26:R$772) -> 55000000
B24: 設計委託費 | C24: =SUMIF('内訳ﾘｽﾄ(4～3月)'!$D$26:$D$973,$B24,'内訳ﾘｽﾄ(4～3月)'!F$26:F$973) -> 0 | D24: =SUMIF('内訳ﾘｽﾄ(4～3月)'!$D$26:$D$973,$B24,'内訳ﾘｽﾄ(4～3月)'!G$26:G$973) -> 0 | E24: =SUMIF('内訳ﾘｽﾄ(4～3月)'!$D$26:$D$973,$B24,'内訳ﾘｽﾄ(4～3月)'!H$26:H$973) -> 0 | F24: =SUMIF('内訳ﾘｽﾄ(4～3月)'!$D$26:$D$973,$B24,'内訳ﾘｽﾄ(4～3月)'!I$26:I$973) -> 0 | G24: =SUMIF('内訳ﾘｽﾄ(4～3月)'!$D$26:$D$973,$B24,'内訳ﾘｽﾄ(4～3月)'!J$26:J$973) -> 0 | H24: =SUMIF('内訳ﾘｽﾄ(4～3月)'!$D$26:$D$973,$B24,'内訳ﾘｽﾄ(4～3月)'!K$26:K$973) -> 0 | I24: =SUMIF('内訳ﾘｽﾄ(4～3月)'!$D$26:$D$973,$B24,'内訳ﾘｽﾄ(4～3月)'!L$26:L$973) -> 0 | J24: =SUMIF('内訳ﾘｽﾄ(4～3月)'!$D$26:$D$973,$B24,'内訳ﾘｽﾄ(4～3月)'!M$26:M$973) -> 0 | ... N24: =SUMIF('内訳ﾘｽﾄ(4～3月)'!$D$26:$D$973,$B24,'内訳ﾘｽﾄ(4～3月)'!Q$26:Q$973) -> 0 | O24: =SUMIF('内訳ﾘｽﾄ(4～3月)'!$D$26:$D$772,'採算表(VND)'!$B24,'内訳ﾘｽﾄ(4～3月)'!R$26:R$772) -> 0
B25: 消耗品費 | C25: =SUMIF('内訳ﾘｽﾄ(4～3月)'!$D$26:$D$973,$B25,'内訳ﾘｽﾄ(4～3月)'!F$26:F$973) -> 3537120 | D25: =SUMIF('内訳ﾘｽﾄ(4～3月)'!$D$26:$D$973,$B25,'内訳ﾘｽﾄ(4～3月)'!G$26:G$973) -> 2466490 | E25: =SUMIF('内訳ﾘｽﾄ(4～3月)'!$D$26:$D$973,$B25,'内訳ﾘｽﾄ(4～3月)'!H$26:H$973) -> 3578200 | F25: =SUMIF('内訳ﾘｽﾄ(4～3月)'!$D$26:$D$973,$B25,'内訳ﾘｽﾄ(4～3月)'!I$26:I$973) -> 2524131 | G25: =SUMIF('内訳ﾘｽﾄ(4～3月)'!$D$26:$D$973,$B25,'内訳ﾘｽﾄ(4～3月)'!J$26:J$973) -> 3552412 | H25: =SUMIF('内訳ﾘｽﾄ(4～3月)'!$D$26:$D$973,$B25,'内訳ﾘｽﾄ(4～3月)'!K$26:K$973) -> 2636513 | I25: =SUMIF('内訳ﾘｽﾄ(4～3月)'!$D$26:$D$973,$B25,'内訳ﾘｽﾄ(4～3月)'!L$26:L$973) -> 3586803 | J25: =SUMIF('内訳ﾘｽﾄ(4～3月)'!$D$26:$D$973,$B25,'内訳ﾘｽﾄ(4～3月)'!M$26:M$973) -> 2481025 | ... N25: =SUMIF('内訳ﾘｽﾄ(4～3月)'!$D$26:$D$973,$B25,'内訳ﾘｽﾄ(4～3月)'!Q$26:Q$973) -> 2477000 | O25: =SUMIF('内訳ﾘｽﾄ(4～3月)'!$D$26:$D$772,'採算表(VND)'!$B25,'内訳ﾘｽﾄ(4～3月)'!R$26:R$772) -> 36385410
... B60: 内部技術料 | C60: =SUMIF('内訳ﾘｽﾄ(4～3月)'!$D$26:$D$973,$B60,'内訳ﾘｽﾄ(4～3月)'!F$26:F$973) -> 0 | D60: =SUMIF('内訳ﾘｽﾄ(4～3月)'!$D$26:$D$973,$B60,'内訳ﾘｽﾄ(4～3月)'!G$26:G$973) -> 0 | E60: =SUMIF('内訳ﾘｽﾄ(4～3月)'!$D$26:$D$973,$B60,'内訳ﾘｽﾄ(4～3月)'!H$26:H$973) -> 0 | F60: =SUMIF('内訳ﾘｽﾄ(4～3月)'!$D$26:$D$973,$B60,'内訳ﾘｽﾄ(4～3月)'!I$26:I$973) -> 0 | G60: =SUMIF('内訳ﾘｽﾄ(4～3月)'!$D$26:$D$973,$B60,'内訳ﾘｽﾄ(4～3月)'!J$26:J$973) -> 0 | H60: =SUMIF('内訳ﾘｽﾄ(4～3月)'!$D$26:$D$973,$B60,'内訳ﾘｽﾄ(4～3月)'!K$26:K$973) -> 0 | I60: =SUMIF('内訳ﾘｽﾄ(4～3月)'!$D$26:$D$973,$B60,'内訳ﾘｽﾄ(4～3月)'!L$26:L$973) -> 0 | J60: =SUMIF('内訳ﾘｽﾄ(4～3月)'!$D$26:$D$973,$B60,'内訳ﾘｽﾄ(4～3月)'!M$26:M$973) -> 0 | ... N60: =SUMIF('内訳ﾘｽﾄ(4～3月)'!$D$26:$D$973,$B60,'内訳ﾘｽﾄ(4～3月)'!Q$26:Q$973) -> 0 | O60: =SUMIF('内訳ﾘｽﾄ(4～3月)'!$D$26:$D$772,'採算表(VND)'!$B60,'内訳ﾘｽﾄ(4～3月)'!R$26:R$772) -> 0
B61: 部内間接経費 | C61: =IF('内訳ﾘｽﾄ(4～3月)'!$D$5="製造",SUMIF('内訳ﾘｽﾄ(4～3月)'!$D$26:$D$973,$B61,'内訳ﾘｽﾄ(4～3月)'!F$26:F$973),IF('内訳ﾘｽﾄ(4～3月)'!$D$5="部内間接",-SUM(C$14:C$60,C$65),0)) -> 0 | D61: =IF('内訳ﾘｽﾄ(4～3月)'!$D$5="製造",SUMIF('内訳ﾘｽﾄ(4～3月)'!$D$26:$D$973,$B61,'内訳ﾘｽﾄ(4～3月)'!G$26:G$973),IF('内訳ﾘｽﾄ(4～3月)'!$D$5="部内間接",-SUM(D$14:D$60,D$65),0)) -> 0 | E61: =IF('内訳ﾘｽﾄ(4～3月)'!$D$5="製造",SUMIF('内訳ﾘｽﾄ(4～3月)'!$D$26:$D$973,$B61,'内訳ﾘｽﾄ(4～3月)'!H$26:H$973),IF('内訳ﾘｽﾄ(4～3月)'!$D$5="部内間接",-SUM(E$14:E$60,E$65),0)) -> 0 | F61: =IF('内訳ﾘｽﾄ(4～3月)'!$D$5="製造",SUMIF('内訳ﾘｽﾄ(4～3月)'!$D$26:$D$973,$B61,'内訳ﾘｽﾄ(4～3月)'!I$26:I$973),IF('内訳ﾘｽﾄ(4～3月)'!$D$5="部内間接",-SUM(F$14:F$60,F$65),0)) -> 0 | G61: =IF('内訳ﾘｽﾄ(4～3月)'!$D$5="製造",SUMIF('内訳ﾘｽﾄ(4～3月)'!$D$26:$D$973,$B61,'内訳ﾘｽﾄ(4～3月)'!J$26:J$973),IF('内訳ﾘｽﾄ(4～3月)'!$D$5="部内間接",-SUM(G$14:G$60,G$65),0)) -> 0 | H61: =IF('内訳ﾘｽﾄ(4～3月)'!$D$5="製造",SUMIF('内訳ﾘｽﾄ(4～3月)'!$D$26:$D$973,$B61,'内訳ﾘｽﾄ(4～3月)'!K$26:K$973),IF('内訳ﾘｽﾄ(4～3月)'!$D$5="部内間接",-SUM(H$14:H$60,H$65),0)) -> 0 | I61: =IF('内訳ﾘｽﾄ(4～3月)'!$D$5="製造",SUMIF('内訳ﾘｽﾄ(4～3月)'!$D$26:$D$973,$B61,'内訳ﾘｽﾄ(4～3月)'!L$26:L$973),IF('内訳ﾘｽﾄ(4～3月)'!$D$5="部内間接",-SUM(I$14:I$60,I$65),0)) -> 0 | J61: =IF('内訳ﾘｽﾄ(4～3月)'!$D$5="製造",SUMIF('内訳ﾘｽﾄ(4～3月)'!$D$26:$D$973,$B61,'内訳ﾘｽﾄ(4～3月)'!M$26:M$973),IF('内訳ﾘｽﾄ(4～3月)'!$D$5="部内間接",-SUM(J$14:J$60,J$65),0)) -> 0 | ... N61: =IF('内訳ﾘｽﾄ(4～3月)'!$D$5="製造",SUMIF('内訳ﾘｽﾄ(4～3月)'!$D$26:$D$973,$B61,'内訳ﾘｽﾄ(4～3月)'!Q$26:Q$973),IF('内訳ﾘｽﾄ(4～3月)'!$D$5="部内間接",-SUM(N$14:N$60,N$65),0)) -> 0 | O61: =IF('内訳ﾘｽﾄ(4～3月)'!$D$5="部内間接",-SUM(O$65,O$14:O$60),IF('内訳ﾘｽﾄ(4～3月)'!$D$5="製造",SUMIF('内訳ﾘｽﾄ(4～3月)'!$D$26:$D$772,'採算表(VND)'!$B61,'内訳ﾘｽﾄ(4～3月)'!R$26:R$772),0)) -> 0
B62: 部外間接1経費 | C62: =IF('内訳ﾘｽﾄ(4～3月)'!$D$5="製造",SUMIF('内訳ﾘｽﾄ(4～3月)'!$D$26:$D$973,$B62,'内訳ﾘｽﾄ(4～3月)'!F$26:F$973),IF('内訳ﾘｽﾄ(4～3月)'!$D$5="部外間接1",-SUM(C$14:C$60,C$65),0)) -> 0 | D62: =IF('内訳ﾘｽﾄ(4～3月)'!$D$5="製造",SUMIF('内訳ﾘｽﾄ(4～3月)'!$D$26:$D$973,$B62,'内訳ﾘｽﾄ(4～3月)'!G$26:G$973),IF('内訳ﾘｽﾄ(4～3月)'!$D$5="部外間接1",-SUM(D$14:D$60,D$65),0)) -> 0 | E62: =IF('内訳ﾘｽﾄ(4～3月)'!$D$5="製造",SUMIF('内訳ﾘｽﾄ(4～3月)'!$D$26:$D$973,$B62,'内訳ﾘｽﾄ(4～3月)'!H$26:H$973),IF('内訳ﾘｽﾄ(4～3月)'!$D$5="部外間接1",-SUM(E$14:E$60,E$65),0)) -> 0 | F62: =IF('内訳ﾘｽﾄ(4～3月)'!$D$5="製造",SUMIF('内訳ﾘｽﾄ(4～3月)'!$D$26:$D$973,$B62,'内訳ﾘｽﾄ(4～3月)'!I$26:I$973),IF('内訳ﾘｽﾄ(4～3月)'!$D$5="部外間接1",-SUM(F$14:F$60,F$65),0)) -> 0 | G62: =IF('内訳ﾘｽﾄ(4～3月)'!$D$5="製造",SUMIF('内訳ﾘｽﾄ(4～3月)'!$D$26:$D$973,$B62,'内訳ﾘｽﾄ(4～3月)'!J$26:J$973),IF('内訳ﾘｽﾄ(4～3月)'!$D$5="部外間接1",-SUM(G$14:G$60,G$65),0)) -> 0 | H62: =IF('内訳ﾘｽﾄ(4～3月)'!$D$5="製造",SUMIF('内訳ﾘｽﾄ(4～3月)'!$D$26:$D$973,$B62,'内訳ﾘｽﾄ(4～3月)'!K$26:K$973),IF('内訳ﾘｽﾄ(4～3月)'!$D$5="部外間接1",-SUM(H$14:H$60,H$65),0)) -> 0 | I62: =IF('内訳ﾘｽﾄ(4～3月)'!$D$5="製造",SUMIF('内訳ﾘｽﾄ(4～3月)'!$D$26:$D$973,$B62,'内訳ﾘｽﾄ(4～3月)'!L$26:L$973),IF('内訳ﾘｽﾄ(4～3月)'!$D$5="部外間接1",-SUM(I$14:I$60,I$65),0)) -> 0 | J62: =IF('内訳ﾘｽﾄ(4～3月)'!$D$5="製造",SUMIF('内訳ﾘｽﾄ(4～3月)'!$D$26:$D$973,$B62,'内訳ﾘｽﾄ(4～3月)'!M$26:M$973),IF('内訳ﾘｽﾄ(4～3月)'!$D$5="部外間接1",-SUM(J$14:J$60,J$65),0)) -> 0 | ... N62: =IF('内訳ﾘｽﾄ(4～3月)'!$D$5="製造",SUMIF('内訳ﾘｽﾄ(4～3月)'!$D$26:$D$973,$B62,'内訳ﾘｽﾄ(4～3月)'!Q$26:Q$973),IF('内訳ﾘｽﾄ(4～3月)'!$D$5="部外間接1",-SUM(N$14:N$60,N$65),0)) -> 0 | O62: =IF('内訳ﾘｽﾄ(4～3月)'!$D$5="部外間接1",-SUM(O$65,O$14:O$60),IF('内訳ﾘｽﾄ(4～3月)'!$D$5="製造",SUMIF('内訳ﾘｽﾄ(4～3月)'!$D$26:$D$772,'採算表(VND)'!$B62,'内訳ﾘｽﾄ(4～3月)'!R$26:R$772),0)) -> 0
B63: 部外間接2経費 | C63: =IF('内訳ﾘｽﾄ(4～3月)'!$D$5="製造",SUMIF('内訳ﾘｽﾄ(4～3月)'!$D$26:$D$973,$B63,'内訳ﾘｽﾄ(4～3月)'!F$26:F$973),IF('内訳ﾘｽﾄ(4～3月)'!$D$5="部外間接2",-SUM(C$14:C$60,C$65),0)) -> 0 | D63: =IF('内訳ﾘｽﾄ(4～3月)'!$D$5="製造",SUMIF('内訳ﾘｽﾄ(4～3月)'!$D$26:$D$973,$B63,'内訳ﾘｽﾄ(4～3月)'!G$26:G$973),IF('内訳ﾘｽﾄ(4～3月)'!$D$5="部外間接2",-SUM(D$14:D$60,D$65),0)) -> 0 | E63: =IF('内訳ﾘｽﾄ(4～3月)'!$D$5="製造",SUMIF('内訳ﾘｽﾄ(4～3月)'!$D$26:$D$973,$B63,'内訳ﾘｽﾄ(4～3月)'!H$26:H$973),IF('内訳ﾘｽﾄ(4～3月)'!$D$5="部外間接2",-SUM(E$14:E$60,E$65),0)) -> 0 | F63: =IF('内訳ﾘｽﾄ(4～3月)'!$D$5="製造",SUMIF('内訳ﾘｽﾄ(4～3月)'!$D$26:$D$973,$B63,'内訳ﾘｽﾄ(4～3月)'!I$26:I$973),IF('内訳ﾘｽﾄ(4～3月)'!$D$5="部外間接2",-SUM(F$14:F$60,F$65),0)) -> 0 | G63: =IF('内訳ﾘｽﾄ(4～3月)'!$D$5="製造",SUMIF('内訳ﾘｽﾄ(4～3月)'!$D$26:$D$973,$B63,'内訳ﾘｽﾄ(4～3月)'!J$26:J$973),IF('内訳ﾘｽﾄ(4～3月)'!$D$5="部外間接2",-SUM(G$14:G$60,G$65),0)) -> 0 | H63: =IF('内訳ﾘｽﾄ(4～3月)'!$D$5="製造",SUMIF('内訳ﾘｽﾄ(4～3月)'!$D$26:$D$973,$B63,'内訳ﾘｽﾄ(4～3月)'!K$26:K$973),IF('内訳ﾘｽﾄ(4～3月)'!$D$5="部外間接2",-SUM(H$14:H$60,H$65),0)) -> 0 | I63: =IF('内訳ﾘｽﾄ(4～3月)'!$D$5="製造",SUMIF('内訳ﾘｽﾄ(4～3月)'!$D$26:$D$973,$B63,'内訳ﾘｽﾄ(4～3月)'!L$26:L$973),IF('内訳ﾘｽﾄ(4～3月)'!$D$5="部外間接2",-SUM(I$14:I$60,I$65),0)) -> 0 | J63: =IF('内訳ﾘｽﾄ(4～3月)'!$D$5="製造",SUMIF('内訳ﾘｽﾄ(4～3月)'!$D$26:$D$973,$B63,'内訳ﾘｽﾄ(4～3月)'!M$26:M$973),IF('内訳ﾘｽﾄ(4～3月)'!$D$5="部外間接2",-SUM(J$14:J$60,J$65),0)) -> 0 | ... N63: =IF('内訳ﾘｽﾄ(4～3月)'!$D$5="製造",SUMIF('内訳ﾘｽﾄ(4～3月)'!$D$26:$D$973,$B63,'内訳ﾘｽﾄ(4～3月)'!Q$26:Q$973),IF('内訳ﾘｽﾄ(4～3月)'!$D$5="部外間接2",-SUM(N$14:N$60,N$65),0)) -> 0 | O63: =IF('内訳ﾘｽﾄ(4～3月)'!$D$5="部外間接2",-SUM(O$65,O$14:O$60),IF('内訳ﾘｽﾄ(4～3月)'!$D$5="製造",SUMIF('内訳ﾘｽﾄ(4～3月)'!$D$26:$D$772,'採算表(VND)'!$B63,'内訳ﾘｽﾄ(4～3月)'!R$26:R$772),0)) -> 0
B64: 工場間接経費 | C64: =IF('内訳ﾘｽﾄ(4～3月)'!$D$5="製造",SUMIF('内訳ﾘｽﾄ(4～3月)'!$D$26:$D$973,$B64,'内訳ﾘｽﾄ(4～3月)'!F$26:F$973),IF('内訳ﾘｽﾄ(4～3月)'!$D$5="工場間接",-SUM(C$14:C$60,C$65),0)) -> -3232448531 | D64: =IF('内訳ﾘｽﾄ(4～3月)'!$D$5="製造",SUMIF('内訳ﾘｽﾄ(4～3月)'!$D$26:$D$973,$B64,'内訳ﾘｽﾄ(4～3月)'!G$26:G$973),IF('内訳ﾘｽﾄ(4～3月)'!$D$5="工場間接",-SUM(D$14:D$60,D$65),0)) -> -1191581278 | E64: =IF('内訳ﾘｽﾄ(4～3月)'!$D$5="製造",SUMIF('内訳ﾘｽﾄ(4～3月)'!$D$26:$D$973,$B64,'内訳ﾘｽﾄ(4～3月)'!H$26:H$973),IF('内訳ﾘｽﾄ(4～3月)'!$D$5="工場間接",-SUM(E$14:E$60,E$65),0)) -> -1137648047 | F64: =IF('内訳ﾘｽﾄ(4～3月)'!$D$5="製造",SUMIF('内訳ﾘｽﾄ(4～3月)'!$D$26:$D$973,$B64,'内訳ﾘｽﾄ(4～3月)'!I$26:I$973),IF('内訳ﾘｽﾄ(4～3月)'!$D$5="工場間接",-SUM(F$14:F$60,F$65),0)) -> -1140451181 | G64: =IF('内訳ﾘｽﾄ(4～3月)'!$D$5="製造",SUMIF('内訳ﾘｽﾄ(4～3月)'!$D$26:$D$973,$B64,'内訳ﾘｽﾄ(4～3月)'!J$26:J$973),IF('内訳ﾘｽﾄ(4～3月)'!$D$5="工場間接",-SUM(G$14:G$60,G$65),0)) -> -1223940850 | H64: =IF('内訳ﾘｽﾄ(4～3月)'!$D$5="製造",SUMIF('内訳ﾘｽﾄ(4～3月)'!$D$26:$D$973,$B64,'内訳ﾘｽﾄ(4～3月)'!K$26:K$973),IF('内訳ﾘｽﾄ(4～3月)'!$D$5="工場間接",-SUM(H$14:H$60,H$65),0)) -> -1245870347 | I64: =IF('内訳ﾘｽﾄ(4～3月)'!$D$5="製造",SUMIF('内訳ﾘｽﾄ(4～3月)'!$D$26:$D$973,$B64,'内訳ﾘｽﾄ(4～3月)'!L$26:L$973),IF('内訳ﾘｽﾄ(4～3月)'!$D$5="工場間接",-SUM(I$14:I$60,I$65),0)) -> -1039609847 | J64: =IF('内訳ﾘｽﾄ(4～3月)'!$D$5="製造",SUMIF('内訳ﾘｽﾄ(4～3月)'!$D$26:$D$973,$B64,'内訳ﾘｽﾄ(4～3月)'!M$26:M$973),IF('内訳ﾘｽﾄ(4～3月)'!$D$5="工場間接",-SUM(J$14:J$60,J$65),0)) -> -1245812344 | ... N64: =IF('内訳ﾘｽﾄ(4～3月)'!$D$5="製造",SUMIF('内訳ﾘｽﾄ(4～3月)'!$D$26:$D$973,$B64,'内訳ﾘｽﾄ(4～3月)'!Q$26:Q$973),IF('内訳ﾘｽﾄ(4～3月)'!$D$5="工場間接",-SUM(N$14:N$60,N$65),0)) -> -1095461921 | O64: =IF('内訳ﾘｽﾄ(4～3月)'!$D$5="工場間接",-SUM(O$65,O$14:O$60),IF('内訳ﾘｽﾄ(4～3月)'!$D$5="製造",SUMIF('内訳ﾘｽﾄ(4～3月)'!$D$26:$D$772,'採算表(VND)'!$B64,'内訳ﾘｽﾄ(4～3月)'!R$26:R$772),0)) -> -16318790325
B65: 本社機構経費 | C65: =SUMIF('内訳ﾘｽﾄ(4～3月)'!$D$26:$D$973,$B65,'内訳ﾘｽﾄ(4～3月)'!F$26:F$973) -> 0 | D65: =SUMIF('内訳ﾘｽﾄ(4～3月)'!$D$26:$D$973,$B65,'内訳ﾘｽﾄ(4～3月)'!G$26:G$973) -> 0 | E65: =SUMIF('内訳ﾘｽﾄ(4～3月)'!$D$26:$D$973,$B65,'内訳ﾘｽﾄ(4～3月)'!H$26:H$973) -> 0 | F65: =SUMIF('内訳ﾘｽﾄ(4～3月)'!$D$26:$D$973,$B65,'内訳ﾘｽﾄ(4～3月)'!I$26:I$973) -> 0 | G65: =SUMIF('内訳ﾘｽﾄ(4～3月)'!$D$26:$D$973,$B65,'内訳ﾘｽﾄ(4～3月)'!J$26:J$973) -> 0 | H65: =SUMIF('内訳ﾘｽﾄ(4～3月)'!$D$26:$D$973,$B65,'内訳ﾘｽﾄ(4～3月)'!K$26:K$973) -> 0 | I65: =SUMIF('内訳ﾘｽﾄ(4～3月)'!$D$26:$D$973,$B65,'内訳ﾘｽﾄ(4～3月)'!L$26:L$973) -> 0 | J65: =SUMIF('内訳ﾘｽﾄ(4～3月)'!$D$26:$D$973,$B65,'内訳ﾘｽﾄ(4～3月)'!M$26:M$973) -> 0 | ... N65: =SUMIF('内訳ﾘｽﾄ(4～3月)'!$D$26:$D$973,$B65,'内訳ﾘｽﾄ(4～3月)'!Q$26:Q$973) -> 0 | O65: =SUMIF('内訳ﾘｽﾄ(4～3月)'!$D$26:$D$772,'採算表(VND)'!$B65,'内訳ﾘｽﾄ(4～3月)'!R$26:R$772) -> 0
B66: 差引収益 | C66: =C12-C13 -> 0 | D66: =D12-D13 -> 0 | E66: =E12-E13 -> 0 | F66: =F12-F13 -> 0 | G66: =G12-G13 -> 0 | H66: =H12-H13 -> 0 | I66: =I12-I13 -> 0 | J66: =J12-J13 -> 0 | ... N66: =N12-N13 -> 0 | O66: =IF(ISBLANK(O4),"",O12-O13) -> 0
B67: 総時間 | C67: =C73+C79 -> 0 | D67: =D73+D79 -> 0 | E67: =E73+E79 -> 0 | F67: =F73+F79 -> 0 | G67: =G73+G79 -> 0 | H67: =H73+H79 -> 0 | I67: =I73+I79 -> 0 | J67: =J73+J79 -> 0 | ... N67: =N73+N79 -> 0 | O67: =IF(ISBLANK(O4),"",O73+O79) -> 0
B68: 直接部門 | C68: =SUMIF('内訳ﾘｽﾄ(4～3月)'!$D$8:$D$15,'採算表(VND)'!$B68,'内訳ﾘｽﾄ(4～3月)'!F$8:F$15) -> 2767 | D68: =SUMIF('内訳ﾘｽﾄ(4～3月)'!$D$8:$D$15,'採算表(VND)'!$B68,'内訳ﾘｽﾄ(4～3月)'!G$8:G$15) -> 2709.5 | E68: =SUMIF('内訳ﾘｽﾄ(4～3月)'!$D$8:$D$15,'採算表(VND)'!$B68,'内訳ﾘｽﾄ(4～3月)'!H$8:H$15) -> 2979.5 | F68: =SUMIF('内訳ﾘｽﾄ(4～3月)'!$D$8:$D$15,'採算表(VND)'!$B68,'内訳ﾘｽﾄ(4～3月)'!I$8:I$15) -> 3190 | G68: =SUMIF('内訳ﾘｽﾄ(4～3月)'!$D$8:$D$15,'採算表(VND)'!$B68,'内訳ﾘｽﾄ(4～3月)'!J$8:J$15) -> 2767 | H68: =SUMIF('内訳ﾘｽﾄ(4～3月)'!$D$8:$D$15,'採算表(VND)'!$B68,'内訳ﾘｽﾄ(4～3月)'!K$8:K$15) -> 2616 | I68: =SUMIF('内訳ﾘｽﾄ(4～3月)'!$D$8:$D$15,'採算表(VND)'!$B68,'内訳ﾘｽﾄ(4～3月)'!L$8:L$15) -> 3190 | J68: =SUMIF('内訳ﾘｽﾄ(4～3月)'!$D$8:$D$15,'採算表(VND)'!$B68,'内訳ﾘｽﾄ(4～3月)'!M$8:M$15) -> 2767 | ... N68: =SUMIF('内訳ﾘｽﾄ(4～3月)'!$D$8:$D$15,'採算表(VND)'!$B68,'内訳ﾘｽﾄ(4～3月)'!Q$8:Q$15) -> 2902 | O68: =SUMIF('内訳ﾘｽﾄ(4～3月)'!$D$8:$D$15,'採算表(VND)'!$B68,'内訳ﾘｽﾄ(4～3月)'!$R$8:$R$15) -> 34066
B69: 部内間接部門 | C69: =IF('内訳ﾘｽﾄ(4～3月)'!$D$5="製造",SUMIF('内訳ﾘｽﾄ(4～3月)'!$D$8:$D$15,$B69,'内訳ﾘｽﾄ(4～3月)'!F$8:F$15),IF('内訳ﾘｽﾄ(4～3月)'!$D$5="部内間接",-C$68,0)) -> 0 | D69: =IF('内訳ﾘｽﾄ(4～3月)'!$D$5="製造",SUMIF('内訳ﾘｽﾄ(4～3月)'!$D$8:$D$15,$B69,'内訳ﾘｽﾄ(4～3月)'!G$8:G$15),IF('内訳ﾘｽﾄ(4～3月)'!$D$5="部内間接",-D$68,0)) -> 0 | E69: =IF('内訳ﾘｽﾄ(4～3月)'!$D$5="製造",SUMIF('内訳ﾘｽﾄ(4～3月)'!$D$8:$D$15,$B69,'内訳ﾘｽﾄ(4～3月)'!H$8:H$15),IF('内訳ﾘｽﾄ(4～3月)'!$D$5="部内間接",-E$68,0)) -> 0 | F69: =IF('内訳ﾘｽﾄ(4～3月)'!$D$5="製造",SUMIF('内訳ﾘｽﾄ(4～3月)'!$D$8:$D$15,$B69,'内訳ﾘｽﾄ(4～3月)'!I$8:I$15),IF('内訳ﾘｽﾄ(4～3月)'!$D$5="部内間接",-F$68,0)) -> 0 | G69: =IF('内訳ﾘｽﾄ(4～3月)'!$D$5="製造",SUMIF('内訳ﾘｽﾄ(4～3月)'!$D$8:$D$15,$B69,'内訳ﾘｽﾄ(4～3月)'!J$8:J$15),IF('内訳ﾘｽﾄ(4～3月)'!$D$5="部内間接",-G$68,0)) -> 0 | H69: =IF('内訳ﾘｽﾄ(4～3月)'!$D$5="製造",SUMIF('内訳ﾘｽﾄ(4～3月)'!$D$8:$D$15,$B69,'内訳ﾘｽﾄ(4～3月)'!K$8:K$15),IF('内訳ﾘｽﾄ(4～3月)'!$D$5="部内間接",-H$68,0)) -> 0 | I69: =IF('内訳ﾘｽﾄ(4～3月)'!$D$5="製造",SUMIF('内訳ﾘｽﾄ(4～3月)'!$D$8:$D$15,$B69,'内訳ﾘｽﾄ(4～3月)'!L$8:L$15),IF('内訳ﾘｽﾄ(4～3月)'!$D$5="部内間接",-I$68,0)) -> 0 | J69: =IF('内訳ﾘｽﾄ(4～3月)'!$D$5="製造",SUMIF('内訳ﾘｽﾄ(4～3月)'!$D$8:$D$15,$B69,'内訳ﾘｽﾄ(4～3月)'!M$8:M$15),IF('内訳ﾘｽﾄ(4～3月)'!$D$5="部内間接",-J$68,0)) -> 0 | ... N69: =IF('内訳ﾘｽﾄ(4～3月)'!$D$5="製造",SUMIF('内訳ﾘｽﾄ(4～3月)'!$D$8:$D$15,$B69,'内訳ﾘｽﾄ(4～3月)'!Q$8:Q$15),IF('内訳ﾘｽﾄ(4～3月)'!$D$5="部内間接",-N$68,0)) -> 0 | O69: =IF('内訳ﾘｽﾄ(4～3月)'!$D$5="部内間接",-SUM(O$68),IF('内訳ﾘｽﾄ(4～3月)'!$D$5="製造",SUMIF('内訳ﾘｽﾄ(4～3月)'!$D$8:$D$15,'採算表(VND)'!$B69,'内訳ﾘｽﾄ(4～3月)'!$R$8:$R$15),0)) -> 0
B70: 部外間接部門1 | C70: =IF('内訳ﾘｽﾄ(4～3月)'!$D$5="製造",SUMIF('内訳ﾘｽﾄ(4～3月)'!$D$8:$D$15,$B70,'内訳ﾘｽﾄ(4～3月)'!F$8:F$15),IF('内訳ﾘｽﾄ(4～3月)'!$D$5="部外間接1",-C$68,0)) -> 0 | D70: =IF('内訳ﾘｽﾄ(4～3月)'!$D$5="製造",SUMIF('内訳ﾘｽﾄ(4～3月)'!$D$8:$D$15,$B70,'内訳ﾘｽﾄ(4～3月)'!G$8:G$15),IF('内訳ﾘｽﾄ(4～3月)'!$D$5="部外間接1",-D$68,0)) -> 0 | E70: =IF('内訳ﾘｽﾄ(4～3月)'!$D$5="製造",SUMIF('内訳ﾘｽﾄ(4～3月)'!$D$8:$D$15,$B70,'内訳ﾘｽﾄ(4～3月)'!H$8:H$15),IF('内訳ﾘｽﾄ(4～3月)'!$D$5="部外間接1",-E$68,0)) -> 0 | F70: =IF('内訳ﾘｽﾄ(4～3月)'!$D$5="製造",SUMIF('内訳ﾘｽﾄ(4～3月)'!$D$8:$D$15,$B70,'内訳ﾘｽﾄ(4～3月)'!I$8:I$15),IF('内訳ﾘｽﾄ(4～3月)'!$D$5="部外間接1",-F$68,0)) -> 0 | G70: =IF('内訳ﾘｽﾄ(4～3月)'!$D$5="製造",SUMIF('内訳ﾘｽﾄ(4～3月)'!$D$8:$D$15,$B70,'内訳ﾘｽﾄ(4～3月)'!J$8:J$15),IF('内訳ﾘｽﾄ(4～3月)'!$D$5="部外間接1",-G$68,0)) -> 0 | H70: =IF('内訳ﾘｽﾄ(4～3月)'!$D$5="製造",SUMIF('内訳ﾘｽﾄ(4～3月)'!$D$8:$D$15,$B70,'内訳ﾘｽﾄ(4～3月)'!K$8:K$15),IF('内訳ﾘｽﾄ(4～3月)'!$D$5="部外間接1",-H$68,0)) -> 0 | I70: =IF('内訳ﾘｽﾄ(4～3月)'!$D$5="製造",SUMIF('内訳ﾘｽﾄ(4～3月)'!$D$8:$D$15,$B70,'内訳ﾘｽﾄ(4～3月)'!L$8:L$15),IF('内訳ﾘｽﾄ(4～3月)'!$D$5="部外間接1",-I$68,0)) -> 0 | J70: =IF('内訳ﾘｽﾄ(4～3月)'!$D$5="製造",SUMIF('内訳ﾘｽﾄ(4～3月)'!$D$8:$D$15,$B70,'内訳ﾘｽﾄ(4～3月)'!M$8:M$15),IF('内訳ﾘｽﾄ(4～3月)'!$D$5="部外間接1",-J$68,0)) -> 0 | ... N70: =IF('内訳ﾘｽﾄ(4～3月)'!$D$5="製造",SUMIF('内訳ﾘｽﾄ(4～3月)'!$D$8:$D$15,$B70,'内訳ﾘｽﾄ(4～3月)'!Q$8:Q$15),IF('内訳ﾘｽﾄ(4～3月)'!$D$5="部外間接1",-N$68,0)) -> 0 | O70: =IF('内訳ﾘｽﾄ(4～3月)'!$D$5="部外間接1",-SUM(O$68),IF('内訳ﾘｽﾄ(4～3月)'!$D$5="製造",SUMIF('内訳ﾘｽﾄ(4～3月)'!$D$8:$D$15,'採算表(VND)'!$B70,'内訳ﾘｽﾄ(4～3月)'!$R$8:$R$15),0)) -> 0
B71: 部外間接部門2 | C71: =IF('内訳ﾘｽﾄ(4～3月)'!$D$5="製造",SUMIF('内訳ﾘｽﾄ(4～3月)'!$D$8:$D$15,$B71,'内訳ﾘｽﾄ(4～3月)'!F$8:F$15),IF('内訳ﾘｽﾄ(4～3月)'!$D$5="部外間接2",-C$68,0)) -> 0 | D71: =IF('内訳ﾘｽﾄ(4～3月)'!$D$5="製造",SUMIF('内訳ﾘｽﾄ(4～3月)'!$D$8:$D$15,$B71,'内訳ﾘｽﾄ(4～3月)'!G$8:G$15),IF('内訳ﾘｽﾄ(4～3月)'!$D$5="部外間接2",-D$68,0)) -> 0 | E71: =IF('内訳ﾘｽﾄ(4～3月)'!$D$5="製造",SUMIF('内訳ﾘｽﾄ(4～3月)'!$D$8:$D$15,$B71,'内訳ﾘｽﾄ(4～3月)'!H$8:H$15),IF('内訳ﾘｽﾄ(4～3月)'!$D$5="部外間接2",-E$68,0)) -> 0 | F71: =IF('内訳ﾘｽﾄ(4～3月)'!$D$5="製造",SUMIF('内訳ﾘｽﾄ(4～3月)'!$D$8:$D$15,$B71,'内訳ﾘｽﾄ(4～3月)'!I$8:I$15),IF('内訳ﾘｽﾄ(4～3月)'!$D$5="部外間接2",-F$68,0)) -> 0 | G71: =IF('内訳ﾘｽﾄ(4～3月)'!$D$5="製造",SUMIF('内訳ﾘｽﾄ(4～3月)'!$D$8:$D$15,$B71,'内訳ﾘｽﾄ(4～3月)'!J$8:J$15),IF('内訳ﾘｽﾄ(4～3月)'!$D$5="部外間接2",-G$68,0)) -> 0 | H71: =IF('内訳ﾘｽﾄ(4～3月)'!$D$5="製造",SUMIF('内訳ﾘｽﾄ(4～3月)'!$D$8:$D$15,$B71,'内訳ﾘｽﾄ(4～3月)'!K$8:K$15),IF('内訳ﾘｽﾄ(4～3月)'!$D$5="部外間接2",-H$68,0)) -> 0 | I71: =IF('内訳ﾘｽﾄ(4～3月)'!$D$5="製造",SUMIF('内訳ﾘｽﾄ(4～3月)'!$D$8:$D$15,$B71,'内訳ﾘｽﾄ(4～3月)'!L$8:L$15),IF('内訳ﾘｽﾄ(4～3月)'!$D$5="部外間接2",-I$68,0)) -> 0 | J71: =IF('内訳ﾘｽﾄ(4～3月)'!$D$5="製造",SUMIF('内訳ﾘｽﾄ(4～3月)'!$D$8:$D$15,$B71,'内訳ﾘｽﾄ(4～3月)'!M$8:M$15),IF('内訳ﾘｽﾄ(4～3月)'!$D$5="部外間接2",-J$68,0)) -> 0 | ... N71: =IF('内訳ﾘｽﾄ(4～3月)'!$D$5="製造",SUMIF('内訳ﾘｽﾄ(4～3月)'!$D$8:$D$15,$B71,'内訳ﾘｽﾄ(4～3月)'!Q$8:Q$15),IF('内訳ﾘｽﾄ(4～3月)'!$D$5="部外間接2",-N$68,0)) -> 0 | O71: =IF('内訳ﾘｽﾄ(4～3月)'!$D$5="部外間接2",-SUM(O$68),IF('内訳ﾘｽﾄ(4～3月)'!$D$5="製造",SUMIF('内訳ﾘｽﾄ(4～3月)'!$D$8:$D$15,'採算表(VND)'!$B71,'内訳ﾘｽﾄ(4～3月)'!$R$8:$R$15),0)) -> 0
B72: 工場間接部門 | C72: =IF('内訳ﾘｽﾄ(4～3月)'!$D$5="製造",SUMIF('内訳ﾘｽﾄ(4～3月)'!$D$8:$D$15,$B72,'内訳ﾘｽﾄ(4～3月)'!F$8:F$15),IF('内訳ﾘｽﾄ(4～3月)'!$D$5="工場間接",-C$68,0)) -> -2767 | D72: =IF('内訳ﾘｽﾄ(4～3月)'!$D$5="製造",SUMIF('内訳ﾘｽﾄ(4～3月)'!$D$8:$D$15,$B72,'内訳ﾘｽﾄ(4～3月)'!G$8:G$15),IF('内訳ﾘｽﾄ(4～3月)'!$D$5="工場間接",-D$68,0)) -> -2709.5 | E72: =IF('内訳ﾘｽﾄ(4～3月)'!$D$5="製造",SUMIF('内訳ﾘｽﾄ(4～3月)'!$D$8:$D$15,$B72,'内訳ﾘｽﾄ(4～3月)'!H$8:H$15),IF('内訳ﾘｽﾄ(4～3月)'!$D$5="工場間接",-E$68,0)) -> -2979.5 | F72: =IF('内訳ﾘｽﾄ(4～3月)'!$D$5="製造",SUMIF('内訳ﾘｽﾄ(4～3月)'!$D$8:$D$15,$B72,'内訳ﾘｽﾄ(4～3月)'!I$8:I$15),IF('内訳ﾘｽﾄ(4～3月)'!$D$5="工場間接",-F$68,0)) -> -3190 | G72: =IF('内訳ﾘｽﾄ(4～3月)'!$D$5="製造",SUMIF('内訳ﾘｽﾄ(4～3月)'!$D$8:$D$15,$B72,'内訳ﾘｽﾄ(4～3月)'!J$8:J$15),IF('内訳ﾘｽﾄ(4～3月)'!$D$5="工場間接",-G$68,0)) -> -2767 | H72: =IF('内訳ﾘｽﾄ(4～3月)'!$D$5="製造",SUMIF('内訳ﾘｽﾄ(4～3月)'!$D$8:$D$15,$B72,'内訳ﾘｽﾄ(4～3月)'!K$8:K$15),IF('内訳ﾘｽﾄ(4～3月)'!$D$5="工場間接",-H$68,0)) -> -2616 | I72: =IF('内訳ﾘｽﾄ(4～3月)'!$D$5="製造",SUMIF('内訳ﾘｽﾄ(4～3月)'!$D$8:$D$15,$B72,'内訳ﾘｽﾄ(4～3月)'!L$8:L$15),IF('内訳ﾘｽﾄ(4～3月)'!$D$5="工場間接",-I$68,0)) -> -3190 | J72: =IF('内訳ﾘｽﾄ(4～3月)'!$D$5="製造",SUMIF('内訳ﾘｽﾄ(4～3月)'!$D$8:$D$15,$B72,'内訳ﾘｽﾄ(4～3月)'!M$8:M$15),IF('内訳ﾘｽﾄ(4～3月)'!$D$5="工場間接",-J$68,0)) -> -2767 | ... N72: =IF('内訳ﾘｽﾄ(4～3月)'!$D$5="製造",SUMIF('内訳ﾘｽﾄ(4～3月)'!$D$8:$D$15,$B72,'内訳ﾘｽﾄ(4～3月)'!Q$8:Q$15),IF('内訳ﾘｽﾄ(4～3月)'!$D$5="工場間接",-N$68,0)) -> -2902 | O72: =IF('内訳ﾘｽﾄ(4～3月)'!$D$5="工場間接",-SUM(O$68),IF('内訳ﾘｽﾄ(4～3月)'!$D$5="製造",SUMIF('内訳ﾘｽﾄ(4～3月)'!$D$8:$D$15,'採算表(VND)'!$B72,'内訳ﾘｽﾄ(4～3月)'!$R$8:$R$15),0)) -> -34066
B73: 定時間合計 | C73: =SUM(C68:C72) -> 0 | D73: =SUM(D68:D72) -> 0 | E73: =SUM(E68:E72) -> 0 | F73: =SUM(F68:F72) -> 0 | G73: =SUM(G68:G72) -> 0 | H73: =SUM(H68:H72) -> 0 | I73: =SUM(I68:I72) -> 0 | J73: =SUM(J68:J72) -> 0 | ... N73: =SUM(N68:N72) -> 0 | O73: =IF(ISBLANK(O4),"",SUM(O68:O72)) -> 0
B74: 直接部門 | C74: =SUMIF('内訳ﾘｽﾄ(4～3月)'!$D$16:$D$23,'採算表(VND)'!$B74,'内訳ﾘｽﾄ(4～3月)'!F$16:F$23) -> 176.5 | D74: =SUMIF('内訳ﾘｽﾄ(4～3月)'!$D$16:$D$23,'採算表(VND)'!$B74,'内訳ﾘｽﾄ(4～3月)'!G$16:G$23) -> 193.5 | E74: =SUMIF('内訳ﾘｽﾄ(4～3月)'!$D$16:$D$23,'採算表(VND)'!$B74,'内訳ﾘｽﾄ(4～3月)'!H$16:H$23) -> 185.5 | F74: =SUMIF('内訳ﾘｽﾄ(4～3月)'!$D$16:$D$23,'採算表(VND)'!$B74,'内訳ﾘｽﾄ(4～3月)'!I$16:I$23) -> 203.5 | G74: =SUMIF('内訳ﾘｽﾄ(4～3月)'!$D$16:$D$23,'採算表(VND)'!$B74,'内訳ﾘｽﾄ(4～3月)'!J$16:J$23) -> 176.5 | H74: =SUMIF('内訳ﾘｽﾄ(4～3月)'!$D$16:$D$23,'採算表(VND)'!$B74,'内訳ﾘｽﾄ(4～3月)'!K$16:K$23) -> 251.5 | I74: =SUMIF('内訳ﾘｽﾄ(4～3月)'!$D$16:$D$23,'採算表(VND)'!$B74,'内訳ﾘｽﾄ(4～3月)'!L$16:L$23) -> 203.5 | J74: =SUMIF('内訳ﾘｽﾄ(4～3月)'!$D$16:$D$23,'採算表(VND)'!$B74,'内訳ﾘｽﾄ(4～3月)'!M$16:M$23) -> 246.5 | ... N74: =SUMIF('内訳ﾘｽﾄ(4～3月)'!$D$16:$D$23,'採算表(VND)'!$B74,'内訳ﾘｽﾄ(4～3月)'!Q$16:Q$23) -> 176.5 | O74: =SUMIF('内訳ﾘｽﾄ(4～3月)'!$D$16:$D$23,'採算表(VND)'!$B74,'内訳ﾘｽﾄ(4～3月)'!$R$16:$R$23) -> 2316
B75: 部内間接部門 | C75: =IF('内訳ﾘｽﾄ(4～3月)'!$D$5="製造",SUMIF('内訳ﾘｽﾄ(4～3月)'!$D$16:$D$23,$B75,'内訳ﾘｽﾄ(4～3月)'!F$16:F$23),IF('内訳ﾘｽﾄ(4～3月)'!$D$5="部内間接",-C$74,0)) -> 0 | D75: =IF('内訳ﾘｽﾄ(4～3月)'!$D$5="製造",SUMIF('内訳ﾘｽﾄ(4～3月)'!$D$16:$D$23,$B75,'内訳ﾘｽﾄ(4～3月)'!G$16:G$23),IF('内訳ﾘｽﾄ(4～3月)'!$D$5="部内間接",-D$74,0)) -> 0 | E75: =IF('内訳ﾘｽﾄ(4～3月)'!$D$5="製造",SUMIF('内訳ﾘｽﾄ(4～3月)'!$D$16:$D$23,$B75,'内訳ﾘｽﾄ(4～3月)'!H$16:H$23),IF('内訳ﾘｽﾄ(4～3月)'!$D$5="部内間接",-E$74,0)) -> 0 | F75: =IF('内訳ﾘｽﾄ(4～3月)'!$D$5="製造",SUMIF('内訳ﾘｽﾄ(4～3月)'!$D$16:$D$23,$B75,'内訳ﾘｽﾄ(4～3月)'!I$16:I$23),IF('内訳ﾘｽﾄ(4～3月)'!$D$5="部内間接",-F$74,0)) -> 0 | G75: =IF('内訳ﾘｽﾄ(4～3月)'!$D$5="製造",SUMIF('内訳ﾘｽﾄ(4～3月)'!$D$16:$D$23,$B75,'内訳ﾘｽﾄ(4～3月)'!J$16:J$23),IF('内訳ﾘｽﾄ(4～3月)'!$D$5="部内間接",-G$74,0)) -> 0 | H75: =IF('内訳ﾘｽﾄ(4～3月)'!$D$5="製造",SUMIF('内訳ﾘｽﾄ(4～3月)'!$D$16:$D$23,$B75,'内訳ﾘｽﾄ(4～3月)'!K$16:K$23),IF('内訳ﾘｽﾄ(4～3月)'!$D$5="部内間接",-H$74,0)) -> 0 | I75: =IF('内訳ﾘｽﾄ(4～3月)'!$D$5="製造",SUMIF('内訳ﾘｽﾄ(4～3月)'!$D$16:$D$23,$B75,'内訳ﾘｽﾄ(4～3月)'!L$16:L$23),IF('内訳ﾘｽﾄ(4～3月)'!$D$5="部内間接",-I$74,0)) -> 0 | J75: =IF('内訳ﾘｽﾄ(4～3月)'!$D$5="製造",SUMIF('内訳ﾘｽﾄ(4～3月)'!$D$16:$D$23,$B75,'内訳ﾘｽﾄ(4～3月)'!M$16:M$23),IF('内訳ﾘｽﾄ(4～3月)'!$D$5="部内間接",-J$74,0)) -> 0 | ... N75: =IF('内訳ﾘｽﾄ(4～3月)'!$D$5="製造",SUMIF('内訳ﾘｽﾄ(4～3月)'!$D$16:$D$23,$B75,'内訳ﾘｽﾄ(4～3月)'!Q$16:Q$23),IF('内訳ﾘｽﾄ(4～3月)'!$D$5="部内間接",-N$74,0)) -> 0 | O75: =IF('内訳ﾘｽﾄ(4～3月)'!$D$5="部内間接",-SUM(O$74),IF('内訳ﾘｽﾄ(4～3月)'!$D$5="製造",SUMIF('内訳ﾘｽﾄ(4～3月)'!$D$16:$D$23,'採算表(VND)'!$B75,'内訳ﾘｽﾄ(4～3月)'!$R$16:$R$23),0)) -> 0
B76: 部外間接部門1 | C76: =IF('内訳ﾘｽﾄ(4～3月)'!$D$5="製造",SUMIF('内訳ﾘｽﾄ(4～3月)'!$D$16:$D$23,$B76,'内訳ﾘｽﾄ(4～3月)'!F$16:F$23),IF('内訳ﾘｽﾄ(4～3月)'!$D$5="部外間接1",-C$74,0)) -> 0 | D76: =IF('内訳ﾘｽﾄ(4～3月)'!$D$5="製造",SUMIF('内訳ﾘｽﾄ(4～3月)'!$D$16:$D$23,$B76,'内訳ﾘｽﾄ(4～3月)'!G$16:G$23),IF('内訳ﾘｽﾄ(4～3月)'!$D$5="部外間接1",-D$74,0)) -> 0 | E76: =IF('内訳ﾘｽﾄ(4～3月)'!$D$5="製造",SUMIF('内訳ﾘｽﾄ(4～3月)'!$D$16:$D$23,$B76,'内訳ﾘｽﾄ(4～3月)'!H$16:H$23),IF('内訳ﾘｽﾄ(4～3月)'!$D$5="部外間接1",-E$74,0)) -> 0 | F76: =IF('内訳ﾘｽﾄ(4～3月)'!$D$5="製造",SUMIF('内訳ﾘｽﾄ(4～3月)'!$D$16:$D$23,$B76,'内訳ﾘｽﾄ(4～3月)'!I$16:I$23),IF('内訳ﾘｽﾄ(4～3月)'!$D$5="部外間接1",-F$74,0)) -> 0 | G76: =IF('内訳ﾘｽﾄ(4～3月)'!$D$5="製造",SUMIF('内訳ﾘｽﾄ(4～3月)'!$D$16:$D$23,$B76,'内訳ﾘｽﾄ(4～3月)'!J$16:J$23),IF('内訳ﾘｽﾄ(4～3月)'!$D$5="部外間接1",-G$74,0)) -> 0 | H76: =IF('内訳ﾘｽﾄ(4～3月)'!$D$5="製造",SUMIF('内訳ﾘｽﾄ(4～3月)'!$D$16:$D$23,$B76,'内訳ﾘｽﾄ(4～3月)'!K$16:K$23),IF('内訳ﾘｽﾄ(4～3月)'!$D$5="部外間接1",-H$74,0)) -> 0 | I76: =IF('内訳ﾘｽﾄ(4～3月)'!$D$5="製造",SUMIF('内訳ﾘｽﾄ(4～3月)'!$D$16:$D$23,$B76,'内訳ﾘｽﾄ(4～3月)'!L$16:L$23),IF('内訳ﾘｽﾄ(4～3月)'!$D$5="部外間接1",-I$74,0)) -> 0 | J76: =IF('内訳ﾘｽﾄ(4～3月)'!$D$5="製造",SUMIF('内訳ﾘｽﾄ(4～3月)'!$D$16:$D$23,$B76,'内訳ﾘｽﾄ(4～3月)'!M$16:M$23),IF('内訳ﾘｽﾄ(4～3月)'!$D$5="部外間接1",-J$74,0)) -> 0 | ... N76: =IF('内訳ﾘｽﾄ(4～3月)'!$D$5="製造",SUMIF('内訳ﾘｽﾄ(4～3月)'!$D$16:$D$23,$B76,'内訳ﾘｽﾄ(4～3月)'!Q$16:Q$23),IF('内訳ﾘｽﾄ(4～3月)'!$D$5="部外間接1",-N$74,0)) -> 0 | O76: =IF('内訳ﾘｽﾄ(4～3月)'!$D$5="部外間接1",-SUM(O$74),IF('内訳ﾘｽﾄ(4～3月)'!$D$5="製造",SUMIF('内訳ﾘｽﾄ(4～3月)'!$D$16:$D$23,'採算表(VND)'!$B76,'内訳ﾘｽﾄ(4～3月)'!$R$16:$R$23),0)) -> 0
B77: 部外間接部門2 | C77: =IF('内訳ﾘｽﾄ(4～3月)'!$D$5="製造",SUMIF('内訳ﾘｽﾄ(4～3月)'!$D$16:$D$23,$B77,'内訳ﾘｽﾄ(4～3月)'!F$16:F$23),IF('内訳ﾘｽﾄ(4～3月)'!$D$5="部外間接2",-C$74,0)) -> 0 | D77: =IF('内訳ﾘｽﾄ(4～3月)'!$D$5="製造",SUMIF('内訳ﾘｽﾄ(4～3月)'!$D$16:$D$23,$B77,'内訳ﾘｽﾄ(4～3月)'!G$16:G$23),IF('内訳ﾘｽﾄ(4～3月)'!$D$5="部外間接2",-D$74,0)) -> 0 | E77: =IF('内訳ﾘｽﾄ(4～3月)'!$D$5="製造",SUMIF('内訳ﾘｽﾄ(4～3月)'!$D$16:$D$23,$B77,'内訳ﾘｽﾄ(4～3月)'!H$16:H$23),IF('内訳ﾘｽﾄ(4～3月)'!$D$5="部外間接2",-E$74,0)) -> 0 | F77: =IF('内訳ﾘｽﾄ(4～3月)'!$D$5="製造",SUMIF('内訳ﾘｽﾄ(4～3月)'!$D$16:$D$23,$B77,'内訳ﾘｽﾄ(4～3月)'!I$16:I$23),IF('内訳ﾘｽﾄ(4～3月)'!$D$5="部外間接2",-F$74,0)) -> 0 | G77: =IF('内訳ﾘｽﾄ(4～3月)'!$D$5="製造",SUMIF('内訳ﾘｽﾄ(4～3月)'!$D$16:$D$23,$B77,'内訳ﾘｽﾄ(4～3月)'!J$16:J$23),IF('内訳ﾘｽﾄ(4～3月)'!$D$5="部外間接2",-G$74,0)) -> 0 | H77: =IF('内訳ﾘｽﾄ(4～3月)'!$D$5="製造",SUMIF('内訳ﾘｽﾄ(4～3月)'!$D$16:$D$23,$B77,'内訳ﾘｽﾄ(4～3月)'!K$16:K$23),IF('内訳ﾘｽﾄ(4～3月)'!$D$5="部外間接2",-H$74,0)) -> 0 | I77: =IF('内訳ﾘｽﾄ(4～3月)'!$D$5="製造",SUMIF('内訳ﾘｽﾄ(4～3月)'!$D$16:$D$23,$B77,'内訳ﾘｽﾄ(4～3月)'!L$16:L$23),IF('内訳ﾘｽﾄ(4～3月)'!$D$5="部外間接2",-I$74,0)) -> 0 | J77: =IF('内訳ﾘｽﾄ(4～3月)'!$D$5="製造",SUMIF('内訳ﾘｽﾄ(4～3月)'!$D$16:$D$23,$B77,'内訳ﾘｽﾄ(4～3月)'!M$16:M$23),IF('内訳ﾘｽﾄ(4～3月)'!$D$5="部外間接2",-J$74,0)) -> 0 | ... N77: =IF('内訳ﾘｽﾄ(4～3月)'!$D$5="製造",SUMIF('内訳ﾘｽﾄ(4～3月)'!$D$16:$D$23,$B77,'内訳ﾘｽﾄ(4～3月)'!Q$16:Q$23),IF('内訳ﾘｽﾄ(4～3月)'!$D$5="部外間接2",-N$74,0)) -> 0 | O77: =IF('内訳ﾘｽﾄ(4～3月)'!$D$5="部外間接2",-SUM(O$74),IF('内訳ﾘｽﾄ(4～3月)'!$D$5="製造",SUMIF('内訳ﾘｽﾄ(4～3月)'!$D$16:$D$23,'採算表(VND)'!$B77,'内訳ﾘｽﾄ(4～3月)'!$R$16:$R$23),0)) -> 0
B78: 工場間接部門 | C78: =IF('内訳ﾘｽﾄ(4～3月)'!$D$5="製造",SUMIF('内訳ﾘｽﾄ(4～3月)'!$D$16:$D$23,$B78,'内訳ﾘｽﾄ(4～3月)'!F$16:F$23),IF('内訳ﾘｽﾄ(4～3月)'!$D$5="工場間接",-C$74,0)) -> -176.5 | D78: =IF('内訳ﾘｽﾄ(4～3月)'!$D$5="製造",SUMIF('内訳ﾘｽﾄ(4～3月)'!$D$16:$D$23,$B78,'内訳ﾘｽﾄ(4～3月)'!G$16:G$23),IF('内訳ﾘｽﾄ(4～3月)'!$D$5="工場間接",-D$74,0)) -> -193.5 | E78: =IF('内訳ﾘｽﾄ(4～3月)'!$D$5="製造",SUMIF('内訳ﾘｽﾄ(4～3月)'!$D$16:$D$23,$B78,'内訳ﾘｽﾄ(4～3月)'!H$16:H$23),IF('内訳ﾘｽﾄ(4～3月)'!$D$5="工場間接",-E$74,0)) -> -185.5 | F78: =IF('内訳ﾘｽﾄ(4～3月)'!$D$5="製造",SUMIF('内訳ﾘｽﾄ(4～3月)'!$D$16:$D$23,$B78,'内訳ﾘｽﾄ(4～3月)'!I$16:I$23),IF('内訳ﾘｽﾄ(4～3月)'!$D$5="工場間接",-F$74,0)) -> -203.5 | G78: =IF('内訳ﾘｽﾄ(4～3月)'!$D$5="製造",SUMIF('内訳ﾘｽﾄ(4～3月)'!$D$16:$D$23,$B78,'内訳ﾘｽﾄ(4～3月)'!J$16:J$23),IF('内訳ﾘｽﾄ(4～3月)'!$D$5="工場間接",-G$74,0)) -> -176.5 | H78: =IF('内訳ﾘｽﾄ(4～3月)'!$D$5="製造",SUMIF('内訳ﾘｽﾄ(4～3月)'!$D$16:$D$23,$B78,'内訳ﾘｽﾄ(4～3月)'!K$16:K$23),IF('内訳ﾘｽﾄ(4～3月)'!$D$5="工場間接",-H$74,0)) -> -251.5 | I78: =IF('内訳ﾘｽﾄ(4～3月)'!$D$5="製造",SUMIF('内訳ﾘｽﾄ(4～3月)'!$D$16:$D$23,$B78,'内訳ﾘｽﾄ(4～3月)'!L$16:L$23),IF('内訳ﾘｽﾄ(4～3月)'!$D$5="工場間接",-I$74,0)) -> -203.5 | J78: =IF('内訳ﾘｽﾄ(4～3月)'!$D$5="製造",SUMIF('内訳ﾘｽﾄ(4～3月)'!$D$16:$D$23,$B78,'内訳ﾘｽﾄ(4～3月)'!M$16:M$23),IF('内訳ﾘｽﾄ(4～3月)'!$D$5="工場間接",-J$74,0)) -> -246.5 | ... N78: =IF('内訳ﾘｽﾄ(4～3月)'!$D$5="製造",SUMIF('内訳ﾘｽﾄ(4～3月)'!$D$16:$D$23,$B78,'内訳ﾘｽﾄ(4～3月)'!Q$16:Q$23),IF('内訳ﾘｽﾄ(4～3月)'!$D$5="工場間接",-N$74,0)) -> -176.5 | O78: =IF('内訳ﾘｽﾄ(4～3月)'!$D$5="工場間接",-SUM(O$74),IF('内訳ﾘｽﾄ(4～3月)'!$D$5="製造",SUMIF('内訳ﾘｽﾄ(4～3月)'!$D$16:$D$23,'採算表(VND)'!$B78,'内訳ﾘｽﾄ(4～3月)'!$R$16:$R$23),0)) -> -2316
B79: 残業時間合計 | C79: =SUM(C74:C78) -> 0 | D79: =SUM(D74:D78) -> 0 | E79: =SUM(E74:E78) -> 0 | F79: =SUM(F74:F78) -> 0 | G79: =SUM(G74:G78) -> 0 | H79: =SUM(H74:H78) -> 0 | I79: =SUM(I74:I78) -> 0 | J79: =SUM(J74:J78) -> 0 | ... N79: =SUM(N74:N78) -> 0 | O79: =IF(ISBLANK(O10),"",SUM(O74:O78)) -> 0
B80: 当月時間当り | C80: =IFERROR(ROUNDDOWN(C66/C67,0),0) -> 0 | D80: =IFERROR(ROUNDDOWN(D66/D67,0),0) -> 0 | E80: =IFERROR(ROUNDDOWN(E66/E67,0),0) -> 0 | F80: =IFERROR(ROUNDDOWN(F66/F67,0),0) -> 0 | G80: =IFERROR(ROUNDDOWN(G66/G67,0),0) -> 0 | H80: =IFERROR(ROUNDDOWN(H66/H67,0),0) -> 0 | I80: =IFERROR(ROUNDDOWN(I66/I67,0),0) -> 0 | J80: =IFERROR(ROUNDDOWN(J66/J67,0),0) -> 0 | ... O80: =IFERROR(ROUNDDOWN(O66/O67,0),0) -> 0
B81: 時間当り生産高 | C81: =IFERROR(ROUNDDOWN(C12/C67,0),0) -> 0 | D81: =IFERROR(ROUNDDOWN(D12/D67,0),0) -> 0 | E81: =IFERROR(ROUNDDOWN(E12/E67,0),0) -> 0 | F81: =IFERROR(ROUNDDOWN(F12/F67,0),0) -> 0 | G81: =IFERROR(ROUNDDOWN(G12/G67,0),0) -> 0 | H81: =IFERROR(ROUNDDOWN(H12/H67,0),0) -> 0 | I81: =IFERROR(ROUNDDOWN(I12/I67,0),0) -> 0 | J81: =IFERROR(ROUNDDOWN(J12/J67,0),0) -> 0 | ... O81: =IFERROR(ROUNDDOWN(O12/O67,0),0) -> 0
B86: ■人員
B87: 出向社員(人) | C87: =SUMIF('内訳ﾘｽﾄ(4～3月)'!$D$24:$D$25,'採算表(VND)'!$B87,'内訳ﾘｽﾄ(4～3月)'!F$24:F$25) -> 1 | D87: =SUMIF('内訳ﾘｽﾄ(4～3月)'!$D$24:$D$25,'採算表(VND)'!$B87,'内訳ﾘｽﾄ(4～3月)'!G$24:G$25) -> 1 | E87: =SUMIF('内訳ﾘｽﾄ(4～3月)'!$D$24:$D$25,'採算表(VND)'!$B87,'内訳ﾘｽﾄ(4～3月)'!H$24:H$25) -> 1 | F87: =SUMIF('内訳ﾘｽﾄ(4～3月)'!$D$24:$D$25,'採算表(VND)'!$B87,'内訳ﾘｽﾄ(4～3月)'!I$24:I$25) -> 1 | G87: =SUMIF('内訳ﾘｽﾄ(4～3月)'!$D$24:$D$25,'採算表(VND)'!$B87,'内訳ﾘｽﾄ(4～3月)'!J$24:J$25) -> 1 | H87: =SUMIF('内訳ﾘｽﾄ(4～3月)'!$D$24:$D$25,'採算表(VND)'!$B87,'内訳ﾘｽﾄ(4～3月)'!K$24:K$25) -> 1 | I87: =SUMIF('内訳ﾘｽﾄ(4～3月)'!$D$24:$D$25,'採算表(VND)'!$B87,'内訳ﾘｽﾄ(4～3月)'!L$24:L$25) -> 1 | J87: =SUMIF('内訳ﾘｽﾄ(4～3月)'!$D$24:$D$25,'採算表(VND)'!$B87,'内訳ﾘｽﾄ(4～3月)'!M$24:M$25) -> 1 | ... O87: =SUMIF('内訳ﾘｽﾄ(4～3月)'!$D$24:$D$25,'採算表(VND)'!$B87,'内訳ﾘｽﾄ(4～3月)'!R$24:R$25) -> 1
B88: ローカル社員(人) | C88: =SUMIF('内訳ﾘｽﾄ(4～3月)'!$D$24:$D$25,'採算表(VND)'!$B88,'内訳ﾘｽﾄ(4～3月)'!F$24:F$25) -> 16 | D88: =SUMIF('内訳ﾘｽﾄ(4～3月)'!$D$24:$D$25,'採算表(VND)'!$B88,'内訳ﾘｽﾄ(4～3月)'!G$24:G$25) -> 17 | E88: =SUMIF('内訳ﾘｽﾄ(4～3月)'!$D$24:$D$25,'採算表(VND)'!$B88,'内訳ﾘｽﾄ(4～3月)'!H$24:H$25) -> 17 | F88: =SUMIF('内訳ﾘｽﾄ(4～3月)'!$D$24:$D$25,'採算表(VND)'!$B88,'内訳ﾘｽﾄ(4～3月)'!I$24:I$25) -> 17 | G88: =SUMIF('内訳ﾘｽﾄ(4～3月)'!$D$24:$D$25,'採算表(VND)'!$B88,'内訳ﾘｽﾄ(4～3月)'!J$24:J$25) -> 17 | H88: =SUMIF('内訳ﾘｽﾄ(4～3月)'!$D$24:$D$25,'採算表(VND)'!$B88,'内訳ﾘｽﾄ(4～3月)'!K$24:K$25) -> 17 | I88: =SUMIF('内訳ﾘｽﾄ(4～3月)'!$D$24:$D$25,'採算表(VND)'!$B88,'内訳ﾘｽﾄ(4～3月)'!L$24:L$25) -> 17 | J88: =SUMIF('内訳ﾘｽﾄ(4～3月)'!$D$24:$D$25,'採算表(VND)'!$B88,'内訳ﾘｽﾄ(4～3月)'!M$24:M$25) -> 17 | ... O88: =SUMIF('内訳ﾘｽﾄ(4～3月)'!$D$24:$D$25,'採算表(VND)'!$B88,'内訳ﾘｽﾄ(4～3月)'!R$24:R$25) -> 17
B89: 人員計 | C89: =C87+C88 -> 17 | D89: =D87+D88 -> 18 | E89: =E87+E88 -> 18 | F89: =F87+F88 -> 18 | G89: =G87+G88 -> 18 | H89: =H87+H88 -> 18 | I89: =I87+I88 -> 18 | J89: =J87+J88 -> 18 | ... O89: =O87+O88 -> 18
B91: ■定時間
B92: 出向社員定時 | C92: =SUMIF('内訳ﾘｽﾄ(4～3月)'!$B$8:$B$15,$B92,'内訳ﾘｽﾄ(4～3月)'!F$8:F$15) -> 170 | D92: =SUMIF('内訳ﾘｽﾄ(4～3月)'!$B$8:$B$15,$B92,'内訳ﾘｽﾄ(4～3月)'!G$8:G$15) -> 161.5 | E92: =SUMIF('内訳ﾘｽﾄ(4～3月)'!$B$8:$B$15,$B92,'内訳ﾘｽﾄ(4～3月)'!H$8:H$15) -> 178.5 | F92: =SUMIF('内訳ﾘｽﾄ(4～3月)'!$B$8:$B$15,$B92,'内訳ﾘｽﾄ(4～3月)'!I$8:I$15) -> 195.5 | G92: =SUMIF('内訳ﾘｽﾄ(4～3月)'!$B$8:$B$15,$B92,'内訳ﾘｽﾄ(4～3月)'!J$8:J$15) -> 170 | H92: =SUMIF('内訳ﾘｽﾄ(4～3月)'!$B$8:$B$15,$B92,'内訳ﾘｽﾄ(4～3月)'!K$8:K$15) -> 161.5 | I92: =SUMIF('内訳ﾘｽﾄ(4～3月)'!$B$8:$B$15,$B92,'内訳ﾘｽﾄ(4～3月)'!L$8:L$15) -> 195.5 | J92: =SUMIF('内訳ﾘｽﾄ(4～3月)'!$B$8:$B$15,$B92,'内訳ﾘｽﾄ(4～3月)'!M$8:M$15) -> 170 | ... O92: =SUMIF('内訳ﾘｽﾄ(4～3月)'!$B$8:$B$15,$B92,'内訳ﾘｽﾄ(4～3月)'!R$8:R$15) -> 2057
B93: ローカル社員定時 | C93: =SUMIF('内訳ﾘｽﾄ(4～3月)'!$B$8:$B$15,$B93,'内訳ﾘｽﾄ(4～3月)'!F$8:F$15) -> 2597 | D93: =SUMIF('内訳ﾘｽﾄ(4～3月)'!$B$8:$B$15,$B93,'内訳ﾘｽﾄ(4～3月)'!G$8:G$15) -> 2548 | E93: =SUMIF('内訳ﾘｽﾄ(4～3月)'!$B$8:$B$15,$B93,'内訳ﾘｽﾄ(4～3月)'!H$8:H$15) -> 2801 | F93: =SUMIF('内訳ﾘｽﾄ(4～3月)'!$B$8:$B$15,$B93,'内訳ﾘｽﾄ(4～3月)'!I$8:I$15) -> 2994.5 | G93: =SUMIF('内訳ﾘｽﾄ(4～3月)'!$B$8:$B$15,$B93,'内訳ﾘｽﾄ(4～3月)'!J$8:J$15) -> 2597 | H93: =SUMIF('内訳ﾘｽﾄ(4～3月)'!$B$8:$B$15,$B93,'内訳ﾘｽﾄ(4～3月)'!K$8:K$15) -> 2454.5 | I93: =SUMIF('内訳ﾘｽﾄ(4～3月)'!$B$8:$B$15,$B93,'内訳ﾘｽﾄ(4～3月)'!L$8:L$15) -> 2994.5 | J93: =SUMIF('内訳ﾘｽﾄ(4～3月)'!$B$8:$B$15,$B93,'内訳ﾘｽﾄ(4～3月)'!M$8:M$15) -> 2597 | ... O93: =SUMIF('内訳ﾘｽﾄ(4～3月)'!$B$8:$B$15,$B93,'内訳ﾘｽﾄ(4～3月)'!R$8:R$15) -> 32009
B94: 人員計 | C94: =C92+C93 -> 2767 | D94: =D92+D93 -> 2709.5 | E94: =E92+E93 -> 2979.5 | F94: =F92+F93 -> 3190 | G94: =G92+G93 -> 2767 | H94: =H92+H93 -> 2616 | I94: =I92+I93 -> 3190 | J94: =J92+J93 -> 2767 | ... O94: =O92+O93 -> 34066
B96: ■残業時間
B97: 出向社員残業 | C97: =SUMIF('内訳ﾘｽﾄ(4～3月)'!$B$16:$B$23,$B97,'内訳ﾘｽﾄ(4～3月)'!F$16:F$23) -> 40 | D97: =SUMIF('内訳ﾘｽﾄ(4～3月)'!$B$16:$B$23,$B97,'内訳ﾘｽﾄ(4～3月)'!G$16:G$23) -> 38 | E97: =SUMIF('内訳ﾘｽﾄ(4～3月)'!$B$16:$B$23,$B97,'内訳ﾘｽﾄ(4～3月)'!H$16:H$23) -> 42 | F97: =SUMIF('内訳ﾘｽﾄ(4～3月)'!$B$16:$B$23,$B97,'内訳ﾘｽﾄ(4～3月)'!I$16:I$23) -> 46 | G97: =SUMIF('内訳ﾘｽﾄ(4～3月)'!$B$16:$B$23,$B97,'内訳ﾘｽﾄ(4～3月)'!J$16:J$23) -> 40 | H97: =SUMIF('内訳ﾘｽﾄ(4～3月)'!$B$16:$B$23,$B97,'内訳ﾘｽﾄ(4～3月)'!K$16:K$23) -> 38 | I97: =SUMIF('内訳ﾘｽﾄ(4～3月)'!$B$16:$B$23,$B97,'内訳ﾘｽﾄ(4～3月)'!L$16:L$23) -> 46 | J97: =SUMIF('内訳ﾘｽﾄ(4～3月)'!$B$16:$B$23,$B97,'内訳ﾘｽﾄ(4～3月)'!M$16:M$23) -> 40 | ... O97: =SUMIF('内訳ﾘｽﾄ(4～3月)'!$B$16:$B$23,$B97,'内訳ﾘｽﾄ(4～3月)'!R$16:R$23) -> 484
B98: ローカル社員残業 | C98: =SUMIF('内訳ﾘｽﾄ(4～3月)'!$B$16:$B$23,$B98,'内訳ﾘｽﾄ(4～3月)'!F$16:F$23) -> 136.5 | D98: =SUMIF('内訳ﾘｽﾄ(4～3月)'!$B$16:$B$23,$B98,'内訳ﾘｽﾄ(4～3月)'!G$16:G$23) -> 155.5 | E98: =SUMIF('内訳ﾘｽﾄ(4～3月)'!$B$16:$B$23,$B98,'内訳ﾘｽﾄ(4～3月)'!H$16:H$23) -> 143.5 | F98: =SUMIF('内訳ﾘｽﾄ(4～3月)'!$B$16:$B$23,$B98,'内訳ﾘｽﾄ(4～3月)'!I$16:I$23) -> 157.5 | G98: =SUMIF('内訳ﾘｽﾄ(4～3月)'!$B$16:$B$23,$B98,'内訳ﾘｽﾄ(4～3月)'!J$16:J$23) -> 136.5 | H98: =SUMIF('内訳ﾘｽﾄ(4～3月)'!$B$16:$B$23,$B98,'内訳ﾘｽﾄ(4～3月)'!K$16:K$23) -> 213.5 | I98: =SUMIF('内訳ﾘｽﾄ(4～3月)'!$B$16:$B$23,$B98,'内訳ﾘｽﾄ(4～3月)'!L$16:L$23) -> 157.5 | J98: =SUMIF('内訳ﾘｽﾄ(4～3月)'!$B$16:$B$23,$B98,'内訳ﾘｽﾄ(4～3月)'!M$16:M$23) -> 206.5 | ... O98: =SUMIF('内訳ﾘｽﾄ(4～3月)'!$B$16:$B$23,$B98,'内訳ﾘｽﾄ(4～3月)'!R$16:R$23) -> 1832
B99: 人員計 | C99: =C97+C98 -> 176.5 | D99: =D97+D98 -> 193.5 | E99: =E97+E98 -> 185.5 | F99: =F97+F98 -> 203.5 | G99: =G97+G98 -> 176.5 | H99: =H97+H98 -> 251.5 | I99: =I97+I98 -> 203.5 | J99: =J97+J98 -> 246.5 | ... O99: =O97+O98 -> 2316

Sheet 内訳ﾘｽﾄ(4～3月)
A1: MP FY2026_各予定 | F1: 5797 | G1: 5753 | H1: 5618 | I1: 6137 | J1: 6325 | K1: 6547 | L1: 6897 | M1: 7003 | N1: 6941 | O1: 7207 | P1: 7661 | Q1: 7193
B2: 25390 | E2: 稼働日数 | F2: =OFFSET(稼働日!$B$2,MATCH('内訳ﾘｽﾄ(4～3月)'!F4,稼働日!$A$3:$A$14,0),0) -> 20 | G2: =OFFSET(稼働日!$B$2,MATCH('内訳ﾘｽﾄ(4～3月)'!G4,稼働日!$A$3:$A$14,0),0) -> 19 | H2: =OFFSET(稼働日!$B$2,MATCH('内訳ﾘｽﾄ(4～3月)'!H4,稼働日!$A$3:$A$14,0),0) -> 21 | I2: =OFFSET(稼働日!$B$2,MATCH('内訳ﾘｽﾄ(4～3月)'!I4,稼働日!$A$3:$A$14,0),0) -> 23 | J2: =OFFSET(稼働日!$B$2,MATCH('内訳ﾘｽﾄ(4～3月)'!J4,稼働日!$A$3:$A$14,0),0) -> 20 | K2: =OFFSET(稼働日!$B$2,MATCH('内訳ﾘｽﾄ(4～3月)'!K4,稼働日!$A$3:$A$14,0),0) -> 19 | L2: =OFFSET(稼働日!$B$2,MATCH('内訳ﾘｽﾄ(4～3月)'!L4,稼働日!$A$3:$A$14,0),0) -> 23 | M2: =OFFSET(稼働日!$B$2,MATCH('内訳ﾘｽﾄ(4～3月)'!M4,稼働日!$A$3:$A$14,0),0) -> 20 | ... Q2: =OFFSET(稼働日!$B$2,MATCH('内訳ﾘｽﾄ(4～3月)'!Q4,稼働日!$A$3:$A$14,0),0) -> 20
E3: CHECK | F3: {=IF(SUM((F8:F25)-ROUNDDOWN((F8:F25)*4,0)/4)<>0,"時間➝0.25の倍数では無い",IF(SUM(ROUND((F26:F973),0)-ROUND((F26:F973),4))<>0,"経費➝小数点",IF(F5<>IF($D$5="製造",'採算表(VND)'!C13,-VLOOKUP($D$5&"経費",'採算表(VND)'!$B:$N,'採算表(VND)'!C3,0)),"経費➝NG","OK")))} -> OK | G3: {=IF(SUM((G8:G25)-ROUNDDOWN((G8:G25)*4,0)/4)<>0,"時間➝0.25の倍数では無い",IF(SUM(ROUND((G26:G973),0)-ROUND((G26:G973),4))<>0,"経費➝小数点",IF(G5<>IF($D$5="製造",'採算表(VND)'!D13,-VLOOKUP($D$5&"経費",'採算表(VND)'!$B:$N,'採算表(VND)'!D3,0)),"経費➝NG","OK")))} -> OK | H3: {=IF(SUM((H8:H25)-ROUNDDOWN((H8:H25)*4,0)/4)<>0,"時間➝0.25の倍数では無い",IF(SUM(ROUND((H26:H973),0)-ROUND((H26:H973),4))<>0,"経費➝小数点",IF(H5<>IF($D$5="製造",'採算表(VND)'!E13,-VLOOKUP($D$5&"経費",'採算表(VND)'!$B:$N,'採算表(VND)'!E3,0)),"経費➝NG","OK")))} -> OK | I3: {=IF(SUM((I8:I25)-ROUNDDOWN((I8:I25)*4,0)/4)<>0,"時間➝0.25の倍数では無い",IF(SUM(ROUND((I26:I973),0)-ROUND((I26:I973),4))<>0,"経費➝小数点",IF(I5<>IF($D$5="製造",'採算表(VND)'!F13,-VLOOKUP($D$5&"経費",'採算表(VND)'!$B:$N,'採算表(VND)'!F3,0)),"経費➝NG","OK")))} -> OK | J3: {=IF(SUM((J8:J25)-ROUNDDOWN((J8:J25)*4,0)/4)<>0,"時間➝0.25の倍数では無い",IF(SUM(ROUND((J26:J973),0)-ROUND((J26:J973),4))<>0,"経費➝小数点",IF(J5<>IF($D$5="製造",'採算表(VND)'!G13,-VLOOKUP($D$5&"経費",'採算表(VND)'!$B:$N,'採算表(VND)'!G3,0)),"経費➝NG","OK")))} -> OK | K3: {=IF(SUM((K8:K25)-ROUNDDOWN((K8:K25)*4,0)/4)<>0,"時間➝0.25の倍数では無い",IF(SUM(ROUND((K26:K973),0)-ROUND((K26:K973),4))<>0,"経費➝小数点",IF(K5<>IF($D$5="製造",'採算表(VND)'!H13,-VLOOKUP($D$5&"経費",'採算表(VND)'!$B:$N,'採算表(VND)'!H3,0)),"経費➝NG","OK")))} -> OK | L3: {=IF(SUM((L8:L25)-ROUNDDOWN((L8:L25)*4,0)/4)<>0,"時間➝0.25の倍数では無い",IF(SUM(ROUND((L26:L973),0)-ROUND((L26:L973),4))<>0,"経費➝小数点",IF(L5<>IF($D$5="製造",'採算表(VND)'!I13,-VLOOKUP($D$5&"経費",'採算表(VND)'!$B:$N,'採算表(VND)'!I3,0)),"経費➝NG","OK")))} -> OK | M3: {=IF(SUM((M8:M25)-ROUNDDOWN((M8:M25)*4,0)/4)<>0,"時間➝0.25の倍数では無い",IF(SUM(ROUND((M26:M973),0)-ROUND((M26:M973),4))<>0,"経費➝小数点",IF(M5<>IF($D$5="製造",'採算表(VND)'!J13,-VLOOKUP($D$5&"経費",'採算表(VND)'!$B:$N,'採算表(VND)'!J3,0)),"経費➝NG","OK")))} -> OK | ... Q3: {=IF(SUM((Q8:Q25)-ROUNDDOWN((Q8:Q25)*4,0)/4)<>0,"時間➝0.25の倍数では無い",IF(SUM(ROUND((Q26:Q973),0)-ROUND((Q26:Q973),4))<>0,"経費➝小数点",IF(Q5<>IF($D$5="製造",'採算表(VND)'!N13,-VLOOKUP($D$5&"経費",'採算表(VND)'!$B:$N,'採算表(VND)'!N3,0)),"経費➝NG","OK")))} -> OK
B4: 原価センター | C4: 組織名 | D4: 採算区分 | E4: 原価区分 | F4: 4 | G4: 5 | H4: 6 | I4: 7 | J4: 8 | K4: 9 | L4: 10 | M4: 11 | N4: 12 | O4: 1 | P4: 2 | Q4: 3 | R4: 合計
B5: 1412000024 | C5: =VLOOKUP($B$5,原価センタ!$A:$E,2,0) -> 総務課 | D5: =VLOOKUP($B$5,原価センタ!$A:$E,4,0) -> 工場間接 | E5: =VLOOKUP($B$5,原価センタ!$A:$E,5,0) -> 一般 | F5: =SUM(F29:F973) -> 3232448531 | G5: =SUM(G29:G973) -> 1191581278 | H5: =SUM(H29:H973) -> 1137648047 | I5: =SUM(I29:I973) -> 1140451181 | J5: =SUM(J29:J973) -> 1223940850 | K5: =SUM(K29:K973) -> 1245870347 | L5: =SUM(L29:L973) -> 1039609847 | M5: =SUM(M29:M973) -> 1245812344 | ... R5: =SUM(R29:R973) -> 16318790325
C7: 勘定科目名称 | D7: 採算科目 | E7: ﾃｰﾏｺｰﾄﾞ | F7: MP | G7: MP | H7: MP | I7: MP | J7: MP | K7: MP | L7: MP | M7: MP | N7: MP | O7: MP | P7: MP | Q7: MP | R7: MP | S7: 備考 | T7: WBS | BC7: WBS
B8: 出向社員定時 | C8: 定時間（日本社員） | D8: 直接部門 | F8: 170 | G8: 161.5 | H8: 178.5 | I8: 195.5 | J8: 170 | K8: 161.5 | L8: 195.5 | M8: 170 | N8: 187 | O8: 170 | P8: 127.5 | Q8: 170 | R8: =SUM(F8:Q8) -> 2057
B9: ローカル社員定時 | C9: 定時間（ベトナム社員） | D9: 直接部門 | F9: 2597 | G9: 2548 | H9: 2801 | I9: 2994.5 | J9: 2597 | K9: 2454.5 | L9: 2994.5 | M9: 2597 | N9: 2934.5 | O9: 2739.5 | P9: 2019.5 | Q9: 2732 | R9: =SUM(F9:Q9) -> 32009
B10: 出向社員定時 | C10: 定時間（移動分日本社員） | D10: 直接部門 | R10: =SUM(F10:Q10) -> 0
B11: ローカル社員定時 | C11: 定時間（移動分ベトナム社員） | D11: 直接部門 | R11: =SUM(F11:Q11) -> 0
C12: 定時間（部内間接部門） | D12: 部内間接部門 | R12: =SUM(F12:Q12) -> 0 | S12: この分には間接部門から直接部門に配賦された数字
C13: 定時間（部外間接部門1） | D13: 部外間接部門1 | R13: =SUM(F13:Q13) -> 0 | S13: この分には間接部門から直接部門に配賦された数字
C14: 定時間（部外間接部門2） | D14: 部外間接部門2 | R14: =SUM(F14:Q14) -> 0 | S14: この分には間接部門から直接部門に配賦された数字
C15: 定時間（工場間接部門） | D15: 工場間接部門 | R15: =SUM(F15:Q15) -> 0 | S15: この分には間接部門から直接部門に配賦された数字
B16: 出向社員残業 | C16: 残業時間（日本社員） | D16: 直接部門 | F16: 40 | G16: 38 | H16: 42 | I16: 46 | J16: 40 | K16: 38 | L16: 46 | M16: 40 | N16: 44 | O16: 40 | P16: 30 | Q16: 40 | R16: =SUM(F16:Q16) -> 484
B17: ローカル社員残業 | C17: 残業時間（ベトナム社員） | D17: 直接部門 | F17: 136.5 | G17: 155.5 | H17: 143.5 | I17: 157.5 | J17: 136.5 | K17: 213.5 | L17: 157.5 | M17: 206.5 | N17: 150.5 | O17: 136.5 | P17: 101.5 | Q17: 136.5 | R17: =SUM(F17:Q17) -> 1832
B18: 出向社員残業 | C18: 残業時間（移動分日本社員） | D18: 直接部門 | R18: =SUM(F18:Q18) -> 0
B19: ローカル社員残業 | C19: 残業時間（移動分ベトナム社員） | D19: 直接部門 | R19: =SUM(F19:Q19) -> 0
C20: 残業時間（部内間接部門） | D20: 部内間接部門 | R20: =SUM(F20:Q20) -> 0 | S20: この分には間接部門から直接部門に配賦された数字
C21: 残業時間（部外間接部門1） | D21: 部外間接部門1 | R21: =SUM(F21:Q21) -> 0 | S21: この分には間接部門から直接部門に配賦された数字
C22: 残業時間（部外間接部門2） | D22: 部外間接部門2 | R22: =SUM(F22:Q22) -> 0 | S22: この分には間接部門から直接部門に配賦された数字
C23: 残業時間（工場間接部門） | D23: 工場間接部門 | R23: =SUM(F23:Q23) -> 0 | S23: この分には間接部門から直接部門に配賦された数字
B24: 出向社員(人) | C24: 出向社員(人) | D24: 出向社員(人) | F24: 1 | G24: 1 | H24: 1 | I24: 1 | J24: 1 | K24: 1 | L24: 1 | M24: 1 | N24: 1 | O24: 1 | P24: 1 | Q24: 1 | R24: =Q24 -> 1
B25: ローカル社員(人) | C25: ローカル社員(人) | D25: ローカル社員(人) | F25: 16 | G25: 17 | H25: 17 | I25: 17 | J25: 17 | K25: 17 | L25: 17 | M25: 17 | N25: 17 | O25: 17 | P25: 17 | Q25: 17 | R25: =Q25 -> 17 | V25: 4 | W25: 5 | X25: 6 | Y25: 7 | Z25: 8 | AA25: 9 | AB25: 10 | AC25: 11 | AD25: 12 | AE25: 1 | AF25: 2 | AG25: 3
B26: 9114120002 | C26: =IFERROR(IF(VLOOKUP($B26,勘定科目!$A:$H,HLOOKUP($E$5,勘定科目!$F$1:$H$2,2,0),0)="","",VLOOKUP($B26,勘定科目!$A:$E,2,0)),"") -> 社外出荷 | D26: =IF(C26="","",VLOOKUP($B26,勘定科目!$A:$E,4,0)) -> 社外出荷 | F26: =ROUNDDOWN(V26*$B$2,0) -> 0 | G26: =ROUNDDOWN(W26*$B$2,0) -> 0 | H26: =ROUNDDOWN(X26*$B$2,0) -> 0 | I26: =ROUNDDOWN(Y26*$B$2,0) -> 0 | J26: =ROUNDDOWN(Z26*$B$2,0) -> 0 | K26: =ROUNDDOWN(AA26*$B$2,0) -> 0 | L26: =ROUNDDOWN(AB26*$B$2,0) -> 0 | M26: =ROUNDDOWN(AC26*$B$2,0) -> 0 | ... Q26: =ROUNDDOWN(AG26*$B$2,0) -> 0 | R26: =SUM(F26:Q26) -> 0 | S26: 総生産
B27: 9114120004 | C27: =IFERROR(IF(VLOOKUP($B27,勘定科目!$A:$H,HLOOKUP($E$5,勘定科目!$F$1:$H$2,2,0),0)="","",VLOOKUP($B27,勘定科目!$A:$E,2,0)),"") -> 社内売 | D27: =IF(C27="","",VLOOKUP($B27,勘定科目!$A:$E,4,0)) -> 社内売 | F27: =ROUNDDOWN(V27*$B$2,0) -> 0 | G27: =ROUNDDOWN(W27*$B$2,0) -> 0 | H27: =ROUNDDOWN(X27*$B$2,0) -> 0 | I27: =ROUNDDOWN(Y27*$B$2,0) -> 0 | J27: =ROUNDDOWN(Z27*$B$2,0) -> 0 | K27: =ROUNDDOWN(AA27*$B$2,0) -> 0 | L27: =ROUNDDOWN(AB27*$B$2,0) -> 0 | M27: =ROUNDDOWN(AC27*$B$2,0) -> 0 | ... Q27: =ROUNDDOWN(AG27*$B$2,0) -> 0 | R27: =SUM(F27:Q27) -> 0 | S27: 総生産
B28: 9114120014 | C28: =IFERROR(IF(VLOOKUP($B28,勘定科目!$A:$H,HLOOKUP($E$5,勘定科目!$F$1:$H$2,2,0),0)="","",VLOOKUP($B28,勘定科目!$A:$E,2,0)),"") -> 社内買 | D28: =IF(C28="","",VLOOKUP($B28,勘定科目!$A:$E,4,0)) -> 社内買 | F28: =ROUNDDOWN(V28*$B$2,0) -> 0 | G28: =ROUNDDOWN(W28*$B$2,0) -> 0 | H28: =ROUNDDOWN(X28*$B$2,0) -> 0 | I28: =ROUNDDOWN(Y28*$B$2,0) -> 0 | J28: =ROUNDDOWN(Z28*$B$2,0) -> 0 | K28: =ROUNDDOWN(AA28*$B$2,0) -> 0 | L28: =ROUNDDOWN(AB28*$B$2,0) -> 0 | M28: =ROUNDDOWN(AC28*$B$2,0) -> 0 | ... Q28: =ROUNDDOWN(AG28*$B$2,0) -> 0 | R28: =SUM(F28:Q28) -> 0 | S28: 総生産
B29: 9114120006 | C29: =IFERROR(IF(VLOOKUP($B29,勘定科目!$A:$H,HLOOKUP($E$5,勘定科目!$F$1:$H$2,2,0),0)="","",VLOOKUP($B29,勘定科目!$A:$E,2,0)),"") -> 材料費(指図出庫） | D29: =IF(C29="","",VLOOKUP($B29,勘定科目!$A:$E,4,0)) -> 材料費 | F29: =ROUNDUP(V29*$B$2,0) -> 0 | G29: =ROUNDUP(W29*$B$2,0) -> 0 | H29: =ROUNDUP(X29*$B$2,0) -> 0 | I29: =ROUNDUP(Y29*$B$2,0) -> 0 | J29: =ROUNDUP(Z29*$B$2,0) -> 0 | K29: =ROUNDUP(AA29*$B$2,0) -> 0 | L29: =ROUNDUP(AB29*$B$2,0) -> 0 | M29: =ROUNDUP(AC29*$B$2,0) -> 0 | ... Q29: =ROUNDUP(AG29*$B$2,0) -> 0 | R29: =SUM(F29:Q29) -> 0 | S29: 総生産
C30: =IFERROR(IF(VLOOKUP($B30,勘定科目!$A:$H,HLOOKUP($E$5,勘定科目!$F$1:$H$2,2,0),0)="","",VLOOKUP($B30,勘定科目!$A:$E,2,0)),"") | D30: =IF(C30="","",VLOOKUP($B30,勘定科目!$A:$E,4,0)) | R30: =SUM(F30:Q30) -> 0
B31: 9114120018 | C31: =IFERROR(IF(VLOOKUP($B31,勘定科目!$A:$H,HLOOKUP($E$5,勘定科目!$F$1:$H$2,2,0),0)="","",VLOOKUP($B31,勘定科目!$A:$E,2,0)),"") -> 部内間接経費 | D31: =IF(C31="","",VLOOKUP($B31,勘定科目!$A:$E,4,0)) -> 部内間接経費 | R31: =SUM(F31:Q31) -> 0 | S31: この分には間接部門から直接部門に配賦された数字
B32: 9114120029 | C32: =IFERROR(IF(VLOOKUP($B32,勘定科目!$A:$H,HLOOKUP($E$5,勘定科目!$F$1:$H$2,2,0),0)="","",VLOOKUP($B32,勘定科目!$A:$E,2,0)),"") -> 部外間接経費1 | D32: =IF(C32="","",VLOOKUP($B32,勘定科目!$A:$E,4,0)) -> 部外間接経費1 | R32: =SUM(F32:Q32) -> 0 | S32: この分には間接部門から直接部門に配賦された数字
B33: 9114120030 | C33: =IFERROR(IF(VLOOKUP($B33,勘定科目!$A:$H,HLOOKUP($E$5,勘定科目!$F$1:$H$2,2,0),0)="","",VLOOKUP($B33,勘定科目!$A:$E,2,0)),"") -> 部外間接経費2 | D33: =IF(C33="","",VLOOKUP($B33,勘定科目!$A:$E,4,0)) -> 部外間接経費2 | R33: =SUM(F33:Q33) -> 0 | S33: この分には間接部門から直接部門に配賦された数字
B34: 9114120021 | C34: =IFERROR(IF(VLOOKUP($B34,勘定科目!$A:$H,HLOOKUP($E$5,勘定科目!$F$1:$H$2,2,0),0)="","",VLOOKUP($B34,勘定科目!$A:$E,2,0)),"") -> 工場間接経費 | D34: =IF(C34="","",VLOOKUP($B34,勘定科目!$A:$E,4,0)) -> 工場間接経費 | R34: =SUM(F34:Q34) -> 0 | S34: この分には間接部門から直接部門に配賦された数字
C35: =IFERROR(IF(VLOOKUP($B35,勘定科目!$A:$H,HLOOKUP($E$5,勘定科目!$F$1:$H$2,2,0),0)="","",VLOOKUP($B35,勘定科目!$A:$E,2,0)),"") | D35: =IF(C35="","",VLOOKUP($B35,勘定科目!$A:$E,4,0)) | R35: =SUM(F35:Q35) -> 0
B36: 9114120009 | C36: =IFERROR(IF(VLOOKUP($B36,勘定科目!$A:$H,HLOOKUP($E$5,勘定科目!$F$1:$H$2,2,0),0)="","",VLOOKUP($B36,勘定科目!$A:$E,2,0)),"") -> 社内金利（在庫） | D36: =IF(C36="","",VLOOKUP($B36,勘定科目!$A:$E,4,0)) -> 在庫金利 | R36: =SUM(F36:Q36) -> 0
C37: =IFERROR(IF(VLOOKUP($B37,勘定科目!$A:$H,HLOOKUP($E$5,勘定科目!$F$1:$H$2,2,0),0)="","",VLOOKUP($B37,勘定科目!$A:$E,2,0)),"") | D37: =IF(C37="","",VLOOKUP($B37,勘定科目!$A:$E,4,0)) | R37: =SUM(F37:Q37) -> 0
B38: 6006016628 | C38: =IFERROR(IF(VLOOKUP($B38,勘定科目!$A:$H,HLOOKUP($E$5,勘定科目!$F$1:$H$2,2,0),0)="","",VLOOKUP($B38,勘定科目!$A:$E,2,0)),"") -> 減価償却費配賦（一般） 建物 | D38: =IF(C38="","",VLOOKUP($B38,勘定科目!$A:$E,4,0)) -> 減価償却費 | E38: 施設 | F38: =ROUNDUP(18247.45*$B$2,0) -> 463302756 | G38: =ROUNDUP(18264.53*$B$2,0) -> 463736417 | H38: =ROUNDUP(18264.63*$B$2,0) -> 463738956 | I38: =ROUNDUP(18264.27*$B$2,0) -> 463729816 | J38: =ROUNDUP(18264.16*$B$2,0) -> 463727023 | K38: =ROUNDUP(18258.93*$B$2,0) -> 463594233 | L38: =ROUNDUP(18257.42*$B$2,0) -> 463555894 | M38: =ROUNDUP(18257.36*$B$2,0) -> 463554371 | N38: =ROUNDUP(18257.39*$B$2,0) -> 463555133 | O38: =ROUNDUP(18257.27*$B$2,0) -> 463552086 | P38: =ROUNDUP(18257.07*$B$2,0) -> 463547008 | Q38: =ROUNDUP(18257.27*$B$2,0) -> 463552086 | R38: =SUM(F38:Q38) -> 5563145779 | S38: 建屋償却費 Khấu hao nhà xưởng
B39: 6006016629 | C39: =IFERROR(IF(VLOOKUP($B39,勘定科目!$A:$H,HLOOKUP($E$5,勘定科目!$F$1:$H$2,2,0),0)="","",VLOOKUP($B39,勘定科目!$A:$E,2,0)),"") -> 減価償却費配賦（一般） 土地使用権 | D39: =IF(C39="","",VLOOKUP($B39,勘定科目!$A:$E,4,0)) -> 減価償却費 | E39: 施設 | F39: =ROUNDUP(1231.63*$B$2,0) -> 31271086 | G39: =ROUNDUP(1232.78*$B$2,0) -> 31300285 | H39: =ROUNDUP(1232.79*$B$2,0) -> 31300539 | I39: =ROUNDUP(1232.77*$B$2,0) -> 31300031 | J39: =ROUNDUP(1232.76*$B$2,0) -> 31299777 | K39: =ROUNDUP(1232.41*$B$2,0) -> 31290890 | L39: =ROUNDUP(1232.3*$B$2,0) -> 31288097 | M39: =ROUNDUP(1232.3*$B$2,0) -> 31288097 | N39: =ROUNDUP(1232.3*$B$2,0) -> 31288097 | O39: =ROUNDUP(1232.29*$B$2,0) -> 31287844 | P39: =ROUNDUP(1232.28*$B$2,0) -> 31287590 | Q39: =ROUNDUP(1232.29*$B$2,0) -> 31287844 | R39: =SUM(F39:Q39) -> 375490177 | S39: 土地使用権償却費 Khấu hao đất sử dụng
B40: 9114120007 | C40: =IFERROR(IF(VLOOKUP($B40,勘定科目!$A:$H,HLOOKUP($E$5,勘定科目!$F$1:$H$2,2,0),0)="","",VLOOKUP($B40,勘定科目!$A:$E,2,0)),"") -> 社内金利（固定資産） | D40: =IF(C40="","",VLOOKUP($B40,勘定科目!$A:$E,4,0)) -> 固定資産金利 | E40: 施設 | F40: =ROUNDUP(12386.05*$B$2,0) -> 314481810 | G40: =ROUNDUP(11740.13*$B$2,0) -> 298081901 | H40: =ROUNDUP(11740.19*$B$2,0) -> 298083425 | I40: =ROUNDUP(11739.96*$B$2,0) -> 298077585 | J40: =ROUNDUP(11739.89*$B$2,0) -> 298075808 | K40: =ROUNDUP(11736.53*$B$2,0) -> 297990497 | L40: =ROUNDUP(11735.55*$B$2,0) -> 297965615 | M40: =ROUNDUP(11735.52*$B$2,0) -> 297964853 | N40: =ROUNDUP(11735.54*$B$2,0) -> 297965361 | O40: =ROUNDUP(11735.46*$B$2,0) -> 297963330 | P40: =ROUNDUP(11735.336*$B$2,0) -> 297960182 | Q40: =ROUNDUP(11735.46*$B$2,0) -> 297963330 | R40: =SUM(F40:Q40) -> 3592573697 | S40: 建物利益 Lãi nhà xưởng
B41: 9114120007 | C41: =IFERROR(IF(VLOOKUP($B41,勘定科目!$A:$H,HLOOKUP($E$5,勘定科目!$F$1:$H$2,2,0),0)="","",VLOOKUP($B41,勘定科目!$A:$E,2,0)),"") -> 社内金利（固定資産） | D41: =IF(C41="","",VLOOKUP($B41,勘定科目!$A:$E,4,0)) -> 固定資産金利 | E41: 施設 | F41: =ROUNDUP(1531.48*$B$2,0) -> 38884278 | G41: =ROUNDUP(1488.53*$B$2,0) -> 37793777 | H41: =ROUNDUP(1488.54*$B$2,0) -> 37794031 | I41: =ROUNDUP(1488.51*$B$2,0) -> 37793269 | J41: =ROUNDUP(1488.5*$B$2,0) -> 37793015 | K41: =ROUNDUP(1488.07*$B$2,0) -> 37782098 | L41: =ROUNDUP(1487.95*$B$2,0) -> 37779051 | M41: =ROUNDUP(1487.95*$B$2,0) -> 37779051 | N41: =ROUNDUP(1487.95*$B$2,0) -> 37779051 | O41: =ROUNDUP(1487.94*$B$2,0) -> 37778797 | P41: =ROUNDUP(1487.92*$B$2,0) -> 37778289 | Q41: =ROUNDUP(1487.94*$B$2,0) -> 37778797 | R41: =SUM(F41:Q41) -> 454513504 | S41: 土地利益 Lãi đất sử dụng
B42: 9114120009 | C42: =IFERROR(IF(VLOOKUP($B42,勘定科目!$A:$H,HLOOKUP($E$5,勘定科目!$F$1:$H$2,2,0),0)="","",VLOOKUP($B42,勘定科目!$A:$E,2,0)),"") -> 社内金利（在庫） | D42: =IF(C42="","",VLOOKUP($B42,勘定科目!$A:$E,4,0)) -> 在庫金利 | E42: QLKD | R42: =SUM(F42:Q42) -> 0 | S42: 文房具金利 Lãi VPP
B43: 8001037111 | C43: =IFERROR(IF(VLOOKUP($B43,勘定科目!$A:$H,HLOOKUP($E$5,勘定科目!$F$1:$H$2,2,0),0)="","",VLOOKUP($B43,勘定科目!$A:$E,2,0)),"") -> その他特別利益 | D43: =IF(C43="","",VLOOKUP($B43,勘定科目!$A:$E,4,0)) -> 特別利益 | E43: Thơ | R43: =SUM(F43:Q43) -> 0 | S43: 特別利益 Lợi nhuận đặc biệt
B44: 6006016612 | C44: =IFERROR(IF(VLOOKUP($B44,勘定科目!$A:$H,HLOOKUP($E$5,勘定科目!$F$1:$H$2,2,0),0)="","",VLOOKUP($B44,勘定科目!$A:$E,2,0)),"") -> 減価償却費（一般） 車輌運搬具 | D44: =IF(C44="","",VLOOKUP($B44,勘定科目!$A:$E,4,0)) -> 減価償却費 | E44: 定額 | F44: =ROUNDUP(830.47*$B$2,0) -> 21085634 | G44: =ROUNDUP(830.47*$B$2,0) -> 21085634 | H44: =ROUNDUP(830.47*$B$2,0) -> 21085634 | I44: =ROUNDUP(830.47*$B$2,0) -> 21085634 | J44: =ROUNDUP(830.47*$B$2,0) -> 21085634 | K44: =ROUNDUP(830.47*$B$2,0) -> 21085634 | L44: =ROUNDUP(830.47*$B$2,0) -> 21085634 | M44: =ROUNDUP(830.47*$B$2,0) -> 21085634 | ... Q44: =ROUNDUP(830.47*$B$2,0) -> 21085634 | R44: =SUM(F44:Q44) -> 253027608 | S44: 車償却費 Khấu hao xe Camry (hết khấu hao T5.2027)
B45: 6006016613 | C45: =IFERROR(IF(VLOOKUP($B45,勘定科目!$A:$H,HLOOKUP($E$5,勘定科目!$F$1:$H$2,2,0),0)="","",VLOOKUP($B45,勘定科目!$A:$E,2,0)),"") -> 減価償却費（一般） 工具器具備品 | D45: =IF(C45="","",VLOOKUP($B45,勘定科目!$A:$E,4,0)) -> 減価償却費 | E45: 定額 | F45: =ROUNDUP(155.56*$B$2,0) -> 3949669 | G45: =ROUNDUP(155.56*$B$2,0) -> 3949669 | H45: =ROUNDUP(155.56*$B$2,0) -> 3949669 | I45: =ROUNDUP(155.56*$B$2,0) -> 3949669 | J45: =ROUNDUP(155.56*$B$2,0) -> 3949669 | K45: =ROUNDUP(155.56*$B$2,0) -> 3949669 | L45: =ROUNDUP(155.56*$B$2,0) -> 3949669 | M45: =ROUNDUP(155.56*$B$2,0) -> 3949669 | ... Q45: =ROUNDUP(155.56*$B$2,0) -> 3949669 | R45: =SUM(F45:Q45) -> 47396028 | S45: 乾燥機償却費 Khấu hao vạc nấu canh nhà B ( T4/2025 ~ T4/2028)
B46: 6006016613 | C46: =IFERROR(IF(VLOOKUP($B46,勘定科目!$A:$H,HLOOKUP($E$5,勘定科目!$F$1:$H$2,2,0),0)="","",VLOOKUP($B46,勘定科目!$A:$E,2,0)),"") -> 減価償却費（一般） 工具器具備品 | D46: =IF(C46="","",VLOOKUP($B46,勘定科目!$A:$E,4,0)) -> 減価償却費 | E46: 定額 | L46: =ROUNDUP(155.56*$B$2,0) -> 3949669 | M46: =ROUNDUP(155.56*$B$2,0) -> 3949669 | N46: =ROUNDUP(155.56*$B$2,0) -> 3949669 | O46: =ROUNDUP(155.56*$B$2,0) -> 3949669 | P46: =ROUNDUP(155.56*$B$2,0) -> 3949669 | Q46: =ROUNDUP(155.56*$B$2,0) -> 3949669 | R46: =SUM(F46:Q46) -> 23698014 | S46: 乾燥機償却費 Khấu hao vạc xào nấu nhà B ( T10/2025 ~ T10/2028)
B47: 6006016613 | C47: =IFERROR(IF(VLOOKUP($B47,勘定科目!$A:$H,HLOOKUP($E$5,勘定科目!$F$1:$H$2,2,0),0)="","",VLOOKUP($B47,勘定科目!$A:$E,2,0)),"") -> 減価償却費（一般） 工具器具備品 | D47: =IF(C47="","",VLOOKUP($B47,勘定科目!$A:$E,4,0)) -> 減価償却費 | E47: 定額 | F47: =ROUNDUP(505.57*$B$2,0) -> 12836423 | G47: =ROUNDUP(505.57*$B$2,0) -> 12836423 | H47: =ROUNDUP(505.57*$B$2,0) -> 12836423 | I47: =ROUNDUP(505.57*$B$2,0) -> 12836423 | J47: =ROUNDUP(505.57*$B$2,0) -> 12836423 | K47: =ROUNDUP(505.57*$B$2,0) -> 12836423 | L47: =ROUNDUP(505.57*$B$2,0) -> 12836423 | M47: =ROUNDUP(505.57*$B$2,0) -> 12836423 | ... Q47: =ROUNDUP(505.57*$B$2,0) -> 12836423 | R47: =SUM(F47:Q47) -> 154037076 | S47: 食堂経営ソフト償却 Khấu hao phần mềm quản lý nhà ăn T5/2026
B48: 6006016613 | C48: =IFERROR(IF(VLOOKUP($B48,勘定科目!$A:$H,HLOOKUP($E$5,勘定科目!$F$1:$H$2,2,0),0)="","",VLOOKUP($B48,勘定科目!$A:$E,2,0)),"") -> 減価償却費（一般） 工具器具備品 | D48: =IF(C48="","",VLOOKUP($B48,勘定科目!$A:$E,4,0)) -> 減価償却費 | E48: 定額 | I48: =ROUNDUP(65.75*$B$2,0) -> 1669393 | J48: =ROUNDUP(65.75*$B$2,0) -> 1669393 | K48: =ROUNDUP(65.75*$B$2,0) -> 1669393 | L48: =ROUNDUP(65.75*$B$2,0) -> 1669393 | M48: =ROUNDUP(65.75*$B$2,0) -> 1669393 | N48: =ROUNDUP(65.75*$B$2,0) -> 1669393 | O48: =ROUNDUP(65.75*$B$2,0) -> 1669393 | P48: =ROUNDUP(65.75*$B$2,0) -> 1669393 | Q48: =ROUNDUP(65.75*$B$2,0) -> 1669393 | R48: =SUM(F48:Q48) -> 15024537 | S48: チャーハン調理器償却費Khấu hao bàn đảo cơm rang (từ tháng 7/2025 ~ T7/2028)
B49: 9114120007 | C49: =IFERROR(IF(VLOOKUP($B49,勘定科目!$A:$H,HLOOKUP($E$5,勘定科目!$F$1:$H$2,2,0),0)="","",VLOOKUP($B49,勘定科目!$A:$E,2,0)),"") -> 社内金利（固定資産） | D49: =IF(C49="","",VLOOKUP($B49,勘定科目!$A:$E,4,0)) -> 固定資産金利 | E49: 定額 | F49: =ROUNDUP(92.9*$B$2,0) -> 2358731 | G49: =ROUNDUP(63.01*$B$2,0) -> 1599824 | H49: =ROUNDUP(63.01*$B$2,0) -> 1599824 | I49: =ROUNDUP(63.01*$B$2,0) -> 1599824 | J49: =ROUNDUP(63.01*$B$2,0) -> 1599824 | K49: =ROUNDUP(63.01*$B$2,0) -> 1599824 | L49: =ROUNDUP(63.01*$B$2,0) -> 1599824 | M49: =ROUNDUP(63.01*$B$2,0) -> 1599824 | N49: =ROUNDUP(63.01*$B$2,0) -> 1599824 | ... Q49: =ROUNDUP(63.01*$B$2,0) -> 1599824 | R49: =SUM(F49:Q49) -> 19956795 | S49: 車利益 Lãi xe Camry (T4/2027 hết khấu hao)
B50: 9114120007 | C50: =IFERROR(IF(VLOOKUP($B50,勘定科目!$A:$H,HLOOKUP($E$5,勘定科目!$F$1:$H$2,2,0),0)="","",VLOOKUP($B50,勘定科目!$A:$E,2,0)),"") -> 社内金利（固定資産） | D50: =IF(C50="","",VLOOKUP($B50,勘定科目!$A:$E,4,0)) -> 固定資産金利 | E50: 定額 | G50: =ROUNDUP(16.8*$B$2,0) -> 426552 | H50: =ROUNDUP(16.8*$B$2,0) -> 426552 | I50: =ROUNDUP(16.8*$B$2,0) -> 426552 | J50: =ROUNDUP(16.8*$B$2,0) -> 426552 | K50: =ROUNDUP(16.8*$B$2,0) -> 426552 | L50: =ROUNDUP(16.8*$B$2,0) -> 426552 | M50: =ROUNDUP(16.8*$B$2,0) -> 426552 | N50: =ROUNDUP(16.8*$B$2,0) -> 426552 | ... Q50: =ROUNDUP(16.8*$B$2,0) -> 426552 | R50: =SUM(F50:Q50) -> 4692072 | S50: 乾燥機利益 Lãi vạc nấu canh nhà B ( T5/2025 ~ T5/2028)
B51: 9114120007 | C51: =IFERROR(IF(VLOOKUP($B51,勘定科目!$A:$H,HLOOKUP($E$5,勘定科目!$F$1:$H$2,2,0),0)="","",VLOOKUP($B51,勘定科目!$A:$E,2,0)),"") -> 社内金利（固定資産） | D51: =IF(C51="","",VLOOKUP($B51,勘定科目!$A:$E,4,0)) -> 固定資産金利 | E51: 定額 | M51: =ROUNDUP(16.8*$B$2,0) -> 426552 | N51: =ROUNDUP(16.8*$B$2,0) -> 426552 | O51: =ROUNDUP(16.8*$B$2,0) -> 426552 | P51: =ROUNDUP(16.8*$B$2,0) -> 426552 | Q51: =ROUNDUP(16.8*$B$2,0) -> 426552 | R51: =SUM(F51:Q51) -> 2132760 | S51: 乾燥機利益 Lãi vạc xào nấu nhà B ( T11/2025 ~ T11/2028)
B52: 9114120007 | C52: =IFERROR(IF(VLOOKUP($B52,勘定科目!$A:$H,HLOOKUP($E$5,勘定科目!$F$1:$H$2,2,0),0)="","",VLOOKUP($B52,勘定科目!$A:$E,2,0)),"") -> 社内金利（固定資産） | D52: =IF(C52="","",VLOOKUP($B52,勘定科目!$A:$E,4,0)) -> 固定資産金利 | E52: 定額 | F52: =ROUNDUP(39.49*$B$2,0) -> 1002652 | G52: =ROUNDUP(21.29*$B$2,0) -> 540554 | H52: =ROUNDUP(21.29*$B$2,0) -> 540554 | I52: =ROUNDUP(21.29*$B$2,0) -> 540554 | J52: =ROUNDUP(21.29*$B$2,0) -> 540554 | K52: =ROUNDUP(21.29*$B$2,0) -> 540554 | L52: =ROUNDUP(21.29*$B$2,0) -> 540554 | M52: =ROUNDUP(21.29*$B$2,0) -> 540554 | N52: =ROUNDUP(21.29*$B$2,0) -> 540554 | ... Q52: =ROUNDUP(21.29*$B$2,0) -> 540554 | R52: =SUM(F52:Q52) -> 6948746 | S52: 食堂経営ソフト利益 Lãi phần mềm quản lý nhà ăn (T5/2026 hết khấu hao)
B53: 9114120007 | C53: =IFERROR(IF(VLOOKUP($B53,勘定科目!$A:$H,HLOOKUP($E$5,勘定科目!$F$1:$H$2,2,0),0)="","",VLOOKUP($B53,勘定科目!$A:$E,2,0)),"") -> 社内金利（固定資産） | D53: =IF(C53="","",VLOOKUP($B53,勘定科目!$A:$E,4,0)) -> 固定資産金利 | E53: 定額 | J53: =ROUNDUP(7.1*$B$2,0) -> 180269 | K53: =ROUNDUP(7.1*$B$2,0) -> 180269 | L53: =ROUNDUP(7.1*$B$2,0) -> 180269 | M53: =ROUNDUP(7.1*$B$2,0) -> 180269 | N53: =ROUNDUP(7.1*$B$2,0) -> 180269 | O53: =ROUNDUP(7.1*$B$2,0) -> 180269 | P53: =ROUNDUP(7.1*$B$2,0) -> 180269 | Q53: =ROUNDUP(7.1*$B$2,0) -> 180269 | R53: =SUM(F53:Q53) -> 1442152 | S53: チャーハン調理器利益 Lãi bàn đảo cơm rang (T8/2025 ~ T8/2028)
B54: 6005226633 | C54: =IFERROR(IF(VLOOKUP($B54,勘定科目!$A:$H,HLOOKUP($E$5,勘定科目!$F$1:$H$2,2,0),0)="","",VLOOKUP($B54,勘定科目!$A:$E,2,0)),"") -> 保険料（一般） | D54: =IF(C54="","",VLOOKUP($B54,勘定科目!$A:$E,4,0)) -> 保険料 | E54: KAL | G54: 55000000 | R54: =SUM(F54:Q54) -> 55000000 | S54: 社有車 対人の自賠責保険 + 車体保険 BH xe oto công ty (T5 hàng năm)
B55: 6005016422 | C55: =IFERROR(IF(VLOOKUP($B55,勘定科目!$A:$H,HLOOKUP($E$5,勘定科目!$F$1:$H$2,2,0),0)="","",VLOOKUP($B55,勘定科目!$A:$E,2,0)),"") -> 消耗品費（一般） | D55: =IF(C55="","",VLOOKUP($B55,勘定科目!$A:$E,4,0)) -> 消耗品費 | E55: Thủy | F55: 6500000 | G55: 6500000 | H55: 6500000 | I55: 6825000 | J55: 6825000 | K55: 7150000 | L55: 7800000 | M55: 7800000 | N55: 7800000 | O55: 8125000 | P55: 8775000 | Q55: 7800000 | R55: =SUM(F55:Q55) -> 88400000 | S55: 手洗い洗剤 発注額 345.000 VND/4L Lifebouy
B56: 6005016422 | C56: =IFERROR(IF(VLOOKUP($B56,勘定科目!$A:$H,HLOOKUP($E$5,勘定科目!$F$1:$H$2,2,0),0)="","",VLOOKUP($B56,勘定科目!$A:$E,2,0)),"") -> 消耗品費（一般） | D56: =IF(C56="","",VLOOKUP($B56,勘定科目!$A:$E,4,0)) -> 消耗品費 | E56: Thủy | F56: -6504234 | G56: -6500890 | H56: -6500026 | I56: -6830481 | J56: -6831000 | K56: -7155871 | L56: -7800507 | M56: -7801342 | N56: -7801684 | O56: -8129496 | P56: -8779506 | Q56: -7804405 | R56: =SUM(F56:Q56) -> -88439442 | S56: 手洗い洗剤 振替額 Phân bổ chi phí nước rửa tay
B57: 6005016422 | C57: =IFERROR(IF(VLOOKUP($B57,勘定科目!$A:$H,HLOOKUP($E$5,勘定科目!$F$1:$H$2,2,0),0)="","",VLOOKUP($B57,勘定科目!$A:$E,2,0)),"") -> 消耗品費（一般） | D57: =IF(C57="","",VLOOKUP($B57,勘定科目!$A:$E,4,0)) -> 消耗品費 | E57: 人頭 | F57: =1122*17 -> 19074 | G57: =1130*18 -> 20340 | H57: =1157*18 -> 20826 | I57: =1113*18 -> 20034 | J57: =1080*18 -> 19440 | K57: =10938*18 -> 196884 | L57: =1131*L773 -> 0 | M57: =1114*18 -> 20052 | N57: =1124*18 -> 20232 | O57: =1128*18 -> 20304 | P57: =1146*18 -> 20628 | Q57: =1085*18 -> 19530 | R57: =SUM(F57:Q57) -> 397344 | S57: 手洗い洗剤 総務課振替額 Nước rửa tay phân bổ cho p.HC
B58: 6005016422 | C58: =IFERROR(IF(VLOOKUP($B58,勘定科目!$A:$H,HLOOKUP($E$5,勘定科目!$F$1:$H$2,2,0),0)="","",VLOOKUP($B58,勘定科目!$A:$E,2,0)),"") -> 消耗品費（一般） | D58: =IF(C58="","",VLOOKUP($B58,勘定科目!$A:$E,4,0)) -> 消耗品費 | E58: Thủy | F58: 106800000 | G58: 102030000 | H58: 108990000 | I58: 129720000 | J58: 116400000 | K58: 114570000 | L58: 145590000 | M58: 129000000 | N58: 140580000 | O58: 132600000 | P58: 106200000 | Q58: 132600000 | R58: =SUM(F58:Q58) -> 1465080000 | S58: トイレットペーパー 発注額 Giấy vệ sinh 32,000VND
B59: 6005016422 | C59: =IFERROR(IF(VLOOKUP($B59,勘定科目!$A:$H,HLOOKUP($E$5,勘定科目!$F$1:$H$2,2,0),0)="","",VLOOKUP($B59,勘定科目!$A:$E,2,0)),"") -> 消耗品費（一般） | D59: =IF(C59="","",VLOOKUP($B59,勘定科目!$A:$E,4,0)) -> 消耗品費 | E59: Thủy | F59: -106803928 | G59: -102035208 | H59: -108994818 | I59: -129723906 | J59: -116405300 | K59: -114572500 | L59: -145595670 | M59: -129002263 | N59: -140583014 | O59: -132601593 | P59: -106204443 | Q59: -132602955 | R59: =SUM(F59:Q59) -> -1465125598 | S59: トイレットペーパー 振替額 Phân bổ chi phí giấy vệ sinh
B60: 6005016422 | C60: =IFERROR(IF(VLOOKUP($B60,勘定科目!$A:$H,HLOOKUP($E$5,勘定科目!$F$1:$H$2,2,0),0)="","",VLOOKUP($B60,勘定科目!$A:$E,2,0)),"") -> 消耗品費（一般） | D60: =IF(C60="","",VLOOKUP($B60,勘定科目!$A:$E,4,0)) -> 消耗品費 | E60: 人頭 | F60: 313208 | G60: 319248 | H60: 349218 | I60: 380484 | J60: 331272 | K60: 315000 | L60: 379980 | M60: 331578 | N60: 364572 | O60: 331182 | P60: 249534 | Q60: 331830 | R60: =SUM(F60:Q60) -> 3997106 | S60: トイレットペーパー 総務課振替額 Giấy vệ sinh phân bổ cho p.HC
B61: 6005016422 | C61: =IFERROR(IF(VLOOKUP($B61,勘定科目!$A:$H,HLOOKUP($E$5,勘定科目!$F$1:$H$2,2,0),0)="","",VLOOKUP($B61,勘定科目!$A:$E,2,0)),"") -> 消耗品費（一般） | D61: =IF(C61="","",VLOOKUP($B61,勘定科目!$A:$E,4,0)) -> 消耗品費 | E61: Thủy | F61: =540000*4 -> 2160000 | G61: =540000*2 -> 1080000 | H61: =540000*4 -> 2160000 | I61: =540000*2 -> 1080000 | J61: =540000*4 -> 2160000 | K61: =540000*2 -> 1080000 | L61: =540000*4 -> 2160000 | M61: =540000*2 -> 1080000 | N61: =540000*4 -> 2160000 | O61: =540000*2 -> 1080000 | P61: =540000*4 -> 2160000 | Q61: =540000*2 -> 1080000 | R61: =SUM(F61:Q61) -> 19440000 | S61: アルコール消毒 発注額 Cồn khử trùng
B62: 6005016422 | C62: =IFERROR(IF(VLOOKUP($B62,勘定科目!$A:$H,HLOOKUP($E$5,勘定科目!$F$1:$H$2,2,0),0)="","",VLOOKUP($B62,勘定科目!$A:$E,2,0)),"") -> 消耗品費（一般） | D62: =IF(C62="","",VLOOKUP($B62,勘定科目!$A:$E,4,0)) -> 消耗品費 | E62: KAB | F62: 1053000 | G62: 1053000 | H62: 1053000 | I62: 1053000 | J62: 1053000 | K62: 1053000 | L62: 1053000 | M62: 1053000 | N62: 1053000 | O62: 1053000 | P62: 1053000 | Q62: 1053000 | R62: =SUM(F62:Q62) -> 12636000 | S62: 洗剤 Nước giặt
B63: 6005116654 | C63: =IFERROR(IF(VLOOKUP($B63,勘定科目!$A:$H,HLOOKUP($E$5,勘定科目!$F$1:$H$2,2,0),0)="","",VLOOKUP($B63,勘定科目!$A:$E,2,0)),"") -> ベトナム国内交通費（一般） | D63: =IF(C63="","",VLOOKUP($B63,勘定科目!$A:$E,4,0)) -> 旅費交通費 | E63: KAL | R63: =SUM(F63:Q63) -> 0 | S63: 会社の車 Xe công ty（総務課員使用） p.HC sử dụng
B64: 6005116654 | C64: =IFERROR(IF(VLOOKUP($B64,勘定科目!$A:$H,HLOOKUP($E$5,勘定科目!$F$1:$H$2,2,0),0)="","",VLOOKUP($B64,勘定科目!$A:$E,2,0)),"") -> ベトナム国内交通費（一般） | D64: =IF(C64="","",VLOOKUP($B64,勘定科目!$A:$E,4,0)) -> 旅費交通費 | E64: KAL | F64: 95000 | G64: 95000 | H64: -180000 | I64: 95000 | J64: 95000 | K64: -180000 | L64: 95000 | M64: 95000 | N64: -180000 | O64: 95000 | P64: 95000 | Q64: -150000 | R64: =SUM(F64:Q64) -> 70000 | S64: 会社の車 Xe công ty（ガソリン代) Chênh lệch xăng xe
B65: 6005116654 | C65: =IFERROR(IF(VLOOKUP($B65,勘定科目!$A:$H,HLOOKUP($E$5,勘定科目!$F$1:$H$2,2,0),0)="","",VLOOKUP($B65,勘定科目!$A:$E,2,0)),"") -> ベトナム国内交通費（一般） | D65: =IF(C65="","",VLOOKUP($B65,勘定科目!$A:$E,4,0)) -> 旅費交通費 | E65: KAL | F65: =25*70000 -> 1750000 | G65: =25*70000 -> 1750000 | H65: =25*70000 -> 1750000 | I65: =25*70000 -> 1750000 | J65: =25*70000 -> 1750000 | K65: =25*70000 -> 1750000 | L65: =25*70000 -> 1750000 | M65: =25*70000 -> 1750000 | ... Q65: =25*70000 -> 1750000 | R65: =SUM(F65:Q65) -> 21000000 | S65: 運転手の出張昼ごはん費用 Phí tiền ăn khi công tác của lái xe (theo lịch công tác)
B66: 6005116654 | C66: =IFERROR(IF(VLOOKUP($B66,勘定科目!$A:$H,HLOOKUP($E$5,勘定科目!$F$1:$H$2,2,0),0)="","",VLOOKUP($B66,勘定科目!$A:$E,2,0)),"") -> ベトナム国内交通費（一般） | D66: =IF(C66="","",VLOOKUP($B66,勘定科目!$A:$E,4,0)) -> 旅費交通費 | E66: KAL | F66: =8*80000+100000 -> 740000 | G66: =8*80000+100000 -> 740000 | H66: =8*80000+100000 -> 740000 | I66: =8*80000+100000 -> 740000 | J66: =8*80000+100000 -> 740000 | K66: =8*80000+100000 -> 740000 | L66: =8*80000+100000 -> 740000 | M66: =8*80000+100000 -> 740000 | ... Q66: =8*80000+100000 -> 740000 | R66: =SUM(F66:Q66) -> 8880000 | S66: 社有車洗車費用 Chi phí rửa xe công ty (tính theo từng tháng)
B67: 6005116654 | C67: =IFERROR(IF(VLOOKUP($B67,勘定科目!$A:$H,HLOOKUP($E$5,勘定科目!$F$1:$H$2,2,0),0)="","",VLOOKUP($B67,勘定科目!$A:$E,2,0)),"") -> ベトナム国内交通費（一般） | D67: =IF(C67="","",VLOOKUP($B67,勘定科目!$A:$E,4,0)) -> 旅費交通費 | E67: KAL | F67: 300000 | G67: 300000 | H67: 500000 | I67: 500000 | J67: 500000 | K67: 500000 | L67: 500000 | M67: 500000 | N67: 500000 | O67: 500000 | P67: 500000 | Q67: 500000 | R67: =SUM(F67:Q67) -> 5600000 | S67: 国内タクシー費(Trung Kien) Taxi đi lại p.HC
B68: 6005116654 | C68: =IFERROR(IF(VLOOKUP($B68,勘定科目!$A:$H,HLOOKUP($E$5,勘定科目!$F$1:$H$2,2,0),0)="","",VLOOKUP($B68,勘定科目!$A:$E,2,0)),"") -> ベトナム国内交通費（一般） | D68: =IF(C68="","",VLOOKUP($B68,勘定科目!$A:$E,4,0)) -> 旅費交通費 | E68: KAL | R68: =SUM(F68:Q68) -> 0 | S68: 国内タクシー費(Hoang Anh) Taxi đi lại p.HC
B69: 6005116654 | C69: =IFERROR(IF(VLOOKUP($B69,勘定科目!$A:$H,HLOOKUP($E$5,勘定科目!$F$1:$H$2,2,0),0)="","",VLOOKUP($B69,勘定科目!$A:$E,2,0)),"") -> ベトナム国内交通費（一般） | D69: =IF(C69="","",VLOOKUP($B69,勘定科目!$A:$E,4,0)) -> 旅費交通費 | E69: Thơ | K69: =400000*2 -> 800000 | P69: =400000*2 -> 800000 | R69: =SUM(F69:Q69) -> 1600000 | S69: 日本語試験交通費 Phí đi lại thi tiếng Nhật
B70: 6005046622 | C70: 修繕費（一般） | D70: =IF(C70="","",VLOOKUP($B70,勘定科目!$A:$E,4,0)) -> 修繕費 | E70: KAL | F70: 2000000 | G70: 2000000 | H70: 2000000 | I70: 2000000 | J70: 2000000 | K70: 2000000 | L70: 2000000 | M70: 2000000 | N70: 2000000 | O70: 2000000 | P70: 2000000 | Q70: 2000000 | R70: =SUM(F70:Q70) -> 24000000 | S70: 車両メンテナンス Bảo dưỡng & thay thế thiết bị xe công ty
B71: 6005116654 | C71: =IFERROR(IF(VLOOKUP($B71,勘定科目!$A:$H,HLOOKUP($E$5,勘定科目!$F$1:$H$2,2,0),0)="","",VLOOKUP($B71,勘定科目!$A:$E,2,0)),"") -> ベトナム国内交通費（一般） | D71: =IF(C71="","",VLOOKUP($B71,勘定科目!$A:$E,4,0)) -> 旅費交通費 | E71: Thơ | R71: =SUM(F71:Q71) -> 0 | S71: 出張日当 Công tác phí (trợ lý: 70,000, NV: 40,000) + tiền ăn 30,000
B72: 6005116655 | C72: =IFERROR(IF(VLOOKUP($B72,勘定科目!$A:$H,HLOOKUP($E$5,勘定科目!$F$1:$H$2,2,0),0)="","",VLOOKUP($B72,勘定科目!$A:$E,2,0)),"") -> 海外渡航費（一般） | D72: =IF(C72="","",VLOOKUP($B72,勘定科目!$A:$E,4,0)) -> 渡航費 | E72: Thơ | R72: =SUM(F72:Q72) -> 0 | S72: 大形さん 日本出張航空券代 Vé máy bay công tác nước ngoài của TGĐ
B73: 6005116655 | C73: =IFERROR(IF(VLOOKUP($B73,勘定科目!$A:$H,HLOOKUP($E$5,勘定科目!$F$1:$H$2,2,0),0)="","",VLOOKUP($B73,勘定科目!$A:$E,2,0)),"") -> 海外渡航費（一般） | D73: =IF(C73="","",VLOOKUP($B73,勘定科目!$A:$E,4,0)) -> 渡航費 | E73: Thơ | R73: =SUM(F73:Q73) -> 0 | S73: 大形さん 日本出張時の日本国内交通費/出張日当 (60usd/日) Phí công tác nước ngoài
B74: 6005116655 | C74: =IFERROR(IF(VLOOKUP($B74,勘定科目!$A:$H,HLOOKUP($E$5,勘定科目!$F$1:$H$2,2,0),0)="","",VLOOKUP($B74,勘定科目!$A:$E,2,0)),"") -> 海外渡航費（一般） | D74: =IF(C74="","",VLOOKUP($B74,勘定科目!$A:$E,4,0)) -> 渡航費 | E74: Thơ | R74: =SUM(F74:Q74) -> 0 | S74: 大形さん 空港送迎費用 (taxi) Mr.Ogata đi sân bay
B75: 6005116655 | C75: =IFERROR(IF(VLOOKUP($B75,勘定科目!$A:$H,HLOOKUP($E$5,勘定科目!$F$1:$H$2,2,0),0)="","",VLOOKUP($B75,勘定科目!$A:$E,2,0)),"") -> 海外渡航費（一般） | D75: =IF(C75="","",VLOOKUP($B75,勘定科目!$A:$E,4,0)) -> 渡航費 | E75: Thơ | R75: =SUM(F75:Q75) -> 0 | S75: 大形さん 空港送迎費用 (xe công ty) Mr.Ogata đi sân bay
B76: 6005056623 | C76: =IFERROR(IF(VLOOKUP($B76,勘定科目!$A:$H,HLOOKUP($E$5,勘定科目!$F$1:$H$2,2,0),0)="","",VLOOKUP($B76,勘定科目!$A:$E,2,0)),"") -> 電気代（一般） | D76: =IF(C76="","",VLOOKUP($B76,勘定科目!$A:$E,4,0)) -> 水道光熱費 | E76: 施設 | F76: 118935307 | G76: 121902360 | H76: 153792013 | I76: 165622168 | J76: 171537139 | K76: 157335827 | L76: 156675555 | M76: 141957137 | N76: 136042256 | O76: 121323837 | P76: 122777190 | Q76: 94638091 | R76: =SUM(F76:Q76) -> 1662538880 | S76: 電気代 Tiền điện
B77: 6005056624 | C77: =IFERROR(IF(VLOOKUP($B77,勘定科目!$A:$H,HLOOKUP($E$5,勘定科目!$F$1:$H$2,2,0),0)="","",VLOOKUP($B77,勘定科目!$A:$E,2,0)),"") -> 水道代（一般） | D77: =IF(C77="","",VLOOKUP($B77,勘定科目!$A:$E,4,0)) -> 水道光熱費 | E77: 施設 | F77: 494073 | G77: 578150 | H77: 652989 | I77: 932515 | J77: 835198 | K77: 724695 | L77: 496437 | M77: 691476 | N77: 690606 | O77: 468296 | P77: 351159 | Q77: 408007 | R77: =SUM(F77:Q77) -> 7323601 | S77: 水道代 Tiền nước
B78: 6005056625 | C78: =IFERROR(IF(VLOOKUP($B78,勘定科目!$A:$H,HLOOKUP($E$5,勘定科目!$F$1:$H$2,2,0),0)="","",VLOOKUP($B78,勘定科目!$A:$E,2,0)),"") -> ガス代（一般） | D78: =IF(C78="","",VLOOKUP($B78,勘定科目!$A:$E,4,0)) -> 水道光熱費 | E78: KAB | F78: 234000000 | G78: 225000000 | H78: 252000000 | I78: 288000000 | J78: 270000000 | K78: 252000000 | L78: 324000000 | M78: 288000000 | N78: 306000000 | O78: 306000000 | P78: 252000000 | Q78: 306000000 | R78: =SUM(F78:Q78) -> 3303000000 | S78: 食堂用ガス 発注額 Gas nhà ăn
B79: 6005056625 | C79: =IFERROR(IF(VLOOKUP($B79,勘定科目!$A:$H,HLOOKUP($E$5,勘定科目!$F$1:$H$2,2,0),0)="","",VLOOKUP($B79,勘定科目!$A:$E,2,0)),"") -> ガス代（一般） | D79: =IF(C79="","",VLOOKUP($B79,勘定科目!$A:$E,4,0)) -> 水道光熱費 | E79: KAB | F79: -234001702 | G79: -225005583 | H79: -252001008 | I79: -288003273 | J79: -270001600 | K79: -252000577 | L79: -324000369 | M79: -288005378 | N79: -306000926 | O79: -306002013 | P79: -252000934 | Q79: -306004606 | R79: =SUM(F79:Q79) -> -3303027969 | S79: 食堂用ガス 振替額 Phân bổ chi phí gas
B80: 6005056625 | C80: =IFERROR(IF(VLOOKUP($B80,勘定科目!$A:$H,HLOOKUP($E$5,勘定科目!$F$1:$H$2,2,0),0)="","",VLOOKUP($B80,勘定科目!$A:$E,2,0)),"") -> ガス代（一般） | D80: =IF(C80="","",VLOOKUP($B80,勘定科目!$A:$E,4,0)) -> 水道光熱費 | E80: 人頭 | F80: 686222 | G80: 703998 | H80: 807408 | I80: 844722 | J80: 768384 | K80: 692838 | L80: 845586 | M80: 740268 | N80: 793548 | O80: 764262 | P80: 592092 | Q80: 765756 | R80: =SUM(F80:Q80) -> 9005084 | S80: 食堂用ガス 総務課負担額 Gas phân bổ cho p.HC
B81: 6005046622 | C81: =IFERROR(IF(VLOOKUP($B81,勘定科目!$A:$H,HLOOKUP($E$5,勘定科目!$F$1:$H$2,2,0),0)="","",VLOOKUP($B81,勘定科目!$A:$E,2,0)),"") -> 修繕費（一般） | D81: =IF(C81="","",VLOOKUP($B81,勘定科目!$A:$E,4,0)) -> 修繕費 | E81: Thủy | H81: 500000 | K81: 500000 | N81: 500000 | Q81: 500000 | R81: =SUM(F81:Q81) -> 2000000 | S81: テーブルと椅子修理費用 Sửa chữa bàn ghế
B82: 6005116654 | C82: ベトナム国内交通費（一般） | D82: =IF(C82="","",VLOOKUP($B82,勘定科目!$A:$E,4,0)) -> 旅費交通費 | E82: KAL | R82: =SUM(F82:Q82) -> 0 | S82: 大形さん 労働許可証.Visa取得のため、タクシー代 Phí taxi làm GPLD, VISA cho TGĐ (T1~3/2025)
B83: 6005046622 | C83: =IFERROR(IF(VLOOKUP($B83,勘定科目!$A:$H,HLOOKUP($E$5,勘定科目!$F$1:$H$2,2,0),0)="","",VLOOKUP($B83,勘定科目!$A:$E,2,0)),"") -> 修繕費（一般） | D83: =IF(C83="","",VLOOKUP($B83,勘定科目!$A:$E,4,0)) -> 修繕費 | E83: Thủy | R83: =SUM(F83:Q83) -> 0 | S83: プロジェクト修繕費用 Sửa chữa máy chiếu
B84: 6005046622 | C84: =IFERROR(IF(VLOOKUP($B84,勘定科目!$A:$H,HLOOKUP($E$5,勘定科目!$F$1:$H$2,2,0),0)="","",VLOOKUP($B84,勘定科目!$A:$E,2,0)),"") -> 修繕費（一般） | D84: =IF(C84="","",VLOOKUP($B84,勘定科目!$A:$E,4,0)) -> 修繕費 | E84: KAB | F84: 10000000 | G84: 10000000 | H84: 10000000 | I84: 10000000 | J84: 10000000 | K84: 10000000 | L84: 10000000 | M84: 10000000 | N84: 10000000 | O84: 10000000 | P84: 10000000 | Q84: 10000000 | R84: =SUM(F84:Q84) -> 120000000 | S84: A食堂 設備メンテ費用 Bảo dưỡng nhà ăn A
B85: 6005046622 | C85: =IFERROR(IF(VLOOKUP($B85,勘定科目!$A:$H,HLOOKUP($E$5,勘定科目!$F$1:$H$2,2,0),0)="","",VLOOKUP($B85,勘定科目!$A:$E,2,0)),"") -> 修繕費（一般） | D85: =IF(C85="","",VLOOKUP($B85,勘定科目!$A:$E,4,0)) -> 修繕費 | E85: KAB | F85: 10000000 | G85: 10000000 | H85: 10000000 | I85: 10000000 | J85: 10000000 | K85: 10000000 | L85: 10000000 | M85: 10000000 | N85: 10000000 | O85: 10000000 | P85: 10000000 | Q85: 10000000 | R85: =SUM(F85:Q85) -> 120000000 | S85: B食堂 設備メンテ費用 Bảo dưỡng nhà ăn B
B86: 6005046622 | C86: =IFERROR(IF(VLOOKUP($B86,勘定科目!$A:$H,HLOOKUP($E$5,勘定科目!$F$1:$H$2,2,0),0)="","",VLOOKUP($B86,勘定科目!$A:$E,2,0)),"") -> 修繕費（一般） | D86: =IF(C86="","",VLOOKUP($B86,勘定科目!$A:$E,4,0)) -> 修繕費 | E86: KAB | F86: 255000000 | R86: =SUM(F86:Q86) -> 255000000 | S86: 食堂 電流修繕 Bảo dưỡng đường điện nhà ăn
B87: 6005046622 | C87: =IFERROR(IF(VLOOKUP($B87,勘定科目!$A:$H,HLOOKUP($E$5,勘定科目!$F$1:$H$2,2,0),0)="","",VLOOKUP($B87,勘定科目!$A:$E,2,0)),"") -> 修繕費（一般） | D87: =IF(C87="","",VLOOKUP($B87,勘定科目!$A:$E,4,0)) -> 修繕費 | E87: KAB | R87: =SUM(F87:Q87) -> 0 | S87: 食堂 ガスパイプ修繕 Bảo dưỡng đường gas nhà ăn
B88: 6005046622 | C88: =IFERROR(IF(VLOOKUP($B88,勘定科目!$A:$H,HLOOKUP($E$5,勘定科目!$F$1:$H$2,2,0),0)="","",VLOOKUP($B88,勘定科目!$A:$E,2,0)),"") -> 修繕費（一般） | D88: =IF(C88="","",VLOOKUP($B88,勘定科目!$A:$E,4,0)) -> 修繕費 | E88: KAB | F88: 36500000 | R88: =SUM(F88:Q88) -> 36500000 | S88: 食堂 水道パイプ修繕 Bảo dưỡng đường nước nhà ăn
B89: 6005046622 | C89: =IFERROR(IF(VLOOKUP($B89,勘定科目!$A:$H,HLOOKUP($E$5,勘定科目!$F$1:$H$2,2,0),0)="","",VLOOKUP($B89,勘定科目!$A:$E,2,0)),"") -> 修繕費（一般） | D89: =IF(C89="","",VLOOKUP($B89,勘定科目!$A:$E,4,0)) -> 修繕費 | E89: KAB | R89: =SUM(F89:Q89) -> 0 | S89: A食堂 設備メンテ費用 換気扇 Bảo dưỡng hệ thống hút mùi nhà ăn A
B90: 6005046622 | C90: =IFERROR(IF(VLOOKUP($B90,勘定科目!$A:$H,HLOOKUP($E$5,勘定科目!$F$1:$H$2,2,0),0)="","",VLOOKUP($B90,勘定科目!$A:$E,2,0)),"") -> 修繕費（一般） | D90: =IF(C90="","",VLOOKUP($B90,勘定科目!$A:$E,4,0)) -> 修繕費 | E90: KAB | R90: =SUM(F90:Q90) -> 0 | S90: B食堂 設備メンテ費用 換気扇 Bảo dưỡng hệ thống hút mùi nhà ăn B
B91: 6005046622 | C91: =IFERROR(IF(VLOOKUP($B91,勘定科目!$A:$H,HLOOKUP($E$5,勘定科目!$F$1:$H$2,2,0),0)="","",VLOOKUP($B91,勘定科目!$A:$E,2,0)),"") -> 修繕費（一般） | D91: =IF(C91="","",VLOOKUP($B91,勘定科目!$A:$E,4,0)) -> 修繕費 | E91: KAB | R91: =SUM(F91:Q91) -> 0 | S91: A食堂 設備メンテ費用 エアコン Bảo dưỡng điều hòa nhà ăn A
B92: 6005046622 | C92: =IFERROR(IF(VLOOKUP($B92,勘定科目!$A:$H,HLOOKUP($E$5,勘定科目!$F$1:$H$2,2,0),0)="","",VLOOKUP($B92,勘定科目!$A:$E,2,0)),"") -> 修繕費（一般） | D92: =IF(C92="","",VLOOKUP($B92,勘定科目!$A:$E,4,0)) -> 修繕費 | E92: KAB | R92: =SUM(F92:Q92) -> 0 | S92: B食堂 設備メンテ費用 エアコン Bảo dưỡng điều hòa nhà ăn B
B93: 6005046622 | C93: =IFERROR(IF(VLOOKUP($B93,勘定科目!$A:$H,HLOOKUP($E$5,勘定科目!$F$1:$H$2,2,0),0)="","",VLOOKUP($B93,勘定科目!$A:$E,2,0)),"") -> 修繕費（一般） | D93: =IF(C93="","",VLOOKUP($B93,勘定科目!$A:$E,4,0)) -> 修繕費 | E93: KAB | N93: 3950000 | R93: =SUM(F93:Q93) -> 3950000 | S93: 食堂 設備メンテ費用 タイヤ交換、設備修繕など Thay bánh xe, hiệu chuẩn đồ cân/đo lường
B94: 6005046622 | C94: =IFERROR(IF(VLOOKUP($B94,勘定科目!$A:$H,HLOOKUP($E$5,勘定科目!$F$1:$H$2,2,0),0)="","",VLOOKUP($B94,勘定科目!$A:$E,2,0)),"") -> 修繕費（一般） | D94: =IF(C94="","",VLOOKUP($B94,勘定科目!$A:$E,4,0)) -> 修繕費 | E94: KAB | R94: =SUM(F94:Q94) -> 0 | S94: 食堂 設備メンテ費用 炊飯器 Sửa chữa tủ cơm nhà ăn
B95: 6005046622 | C95: =IFERROR(IF(VLOOKUP($B95,勘定科目!$A:$H,HLOOKUP($E$5,勘定科目!$F$1:$H$2,2,0),0)="","",VLOOKUP($B95,勘定科目!$A:$E,2,0)),"") -> 修繕費（一般） | D95: =IF(C95="","",VLOOKUP($B95,勘定科目!$A:$E,4,0)) -> 修繕費 | E95: Thơ | I95: 1000000 | N95: 1000000 | R95: =SUM(F95:Q95) -> 2000000 | S95: 備品 受付パソコン修理 Thay màn hình máy tính/ổ cứng/RAM/UPS/TPLink
B96: 6005046622 | C96: =IFERROR(IF(VLOOKUP($B96,勘定科目!$A:$H,HLOOKUP($E$5,勘定科目!$F$1:$H$2,2,0),0)="","",VLOOKUP($B96,勘定科目!$A:$E,2,0)),"") -> 修繕費（一般） | D96: =IF(C96="","",VLOOKUP($B96,勘定科目!$A:$E,4,0)) -> 修繕費 | E96: KAB | R96: =SUM(F96:Q96) -> 0 | S96: 食堂 設備メンテ費用 冷凍庫 Sửa chữa tủ đông Berjara nhà ăn A
B97: 6005046622 | C97: =IFERROR(IF(VLOOKUP($B97,勘定科目!$A:$H,HLOOKUP($E$5,勘定科目!$F$1:$H$2,2,0),0)="","",VLOOKUP($B97,勘定科目!$A:$E,2,0)),"") -> 修繕費（一般） | D97: =IF(C97="","",VLOOKUP($B97,勘定科目!$A:$E,4,0)) -> 修繕費 | E97: KAB | R97: =SUM(F97:Q97) -> 0 | S97: 食堂 設備メンテ費用 冷蔵庫 Sửa chữa tủ lạnh Sanaky nhà ăn A
B98: 6005046622 | C98: =IFERROR(IF(VLOOKUP($B98,勘定科目!$A:$H,HLOOKUP($E$5,勘定科目!$F$1:$H$2,2,0),0)="","",VLOOKUP($B98,勘定科目!$A:$E,2,0)),"") -> 修繕費（一般） | D98: =IF(C98="","",VLOOKUP($B98,勘定科目!$A:$E,4,0)) -> 修繕費 | E98: KAB | R98: =SUM(F98:Q98) -> 0 | S98: 食堂 設備メンテ費用 冷凍庫 Sửa chữa tủ đông Berjara nhà ăn B
B99: 6005246673 | C99: =IFERROR(IF(VLOOKUP($B99,勘定科目!$A:$H,HLOOKUP($E$5,勘定科目!$F$1:$H$2,2,0),0)="","",VLOOKUP($B99,勘定科目!$A:$E,2,0)),"") -> その他手数料（一般） | D99: =IF(C99="","",VLOOKUP($B99,勘定科目!$A:$E,4,0)) -> 手数料 | E99: Thủy | F99: =(39*7690000) -> 299910000 | G99: =(39*7690000) -> 299910000 | H99: =(39*7690000) -> 299910000 | I99: =(39*7690000) -> 299910000 | J99: =(39*7690000) -> 299910000 | K99: =(39*7690000) -> 299910000 | L99: =(39*7690000) -> 299910000 | M99: =(39*7690000) -> 299910000 | ... Q99: =(39*7690000) -> 299910000 | R99: =SUM(F99:Q99) -> 3598920000 | S99: 清掃費 Chi phí làm sạch
B100: 6005246673 | C100: =IFERROR(IF(VLOOKUP($B100,勘定科目!$A:$H,HLOOKUP($E$5,勘定科目!$F$1:$H$2,2,0),0)="","",VLOOKUP($B100,勘定科目!$A:$E,2,0)),"") -> その他手数料（一般） | D100: =IF(C100="","",VLOOKUP($B100,勘定科目!$A:$E,4,0)) -> 手数料 | E100: Thủy | F100: =27500*951 -> 26152500 | G100: =27500*906 -> 24915000 | H100: =27500*984 -> 27060000 | I100: =27500*990 -> 27225000 | J100: =27500*1029 -> 28297500 | K100: =27500*900 -> 24750000 | L100: =27500*990 -> 27225000 | M100: =27500*1023 -> 28132500 | N100: =27500*951 -> 26152500 | O100: =27500*879 -> 24172500 | P100: =27500*951 -> 26152500 | Q100: =27500*744 -> 20460000 | R100: =SUM(F100:Q100) -> 310695000 | S100: 清掃社員の食事代 Tiền ăn cho nhân viên làm sạch
B101: 6005246673 | C101: =IFERROR(IF(VLOOKUP($B101,勘定科目!$A:$H,HLOOKUP($E$5,勘定科目!$F$1:$H$2,2,0),0)="","",VLOOKUP($B101,勘定科目!$A:$E,2,0)),"") -> その他手数料（一般） | D101: =IF(C101="","",VLOOKUP($B101,勘定科目!$A:$E,4,0)) -> 手数料 | E101: Thủy | F101: -326063859 | G101: -324825886 | H101: -326973218 | I101: -327138922 | J101: -328210575 | K101: -324665730 | L101: -327138504 | M101: -328048532 | N101: -326067357 | O101: -324084376 | P101: -326067482 | Q101: -320376220 | R101: =SUM(F101:Q101) -> -3909660661 | S101: 清掃 振替額 Phân bổ chi phí làm sạch
...

Sheet Sheet1

Sheet 設備投資計画
B1: 設備投資金額一覧表 | D1: ='内訳ﾘｽﾄ(4～3月)'!C5 -> 総務課 | E1: (単位： VND)
B3: 部門ｺｰﾄﾞ | C3: 購入物品名 | D3: 目 的 | E3: 4 | F3: 5 | G3: 6 | H3: 7 | I3: 8 | J3: 9 | K3: 10 | L3: 11 | M3: 12 | N3: 1 | O3: 2 | P3: 3 | Q3: 償却期間 (ヶ月) | R3: 購入金額合計 | S3: WBS
R4: =SUM(E4:P4) -> 0
R5: =SUM(E5:P5) -> 0
R6: =SUM(E6:P6) -> 0
R7: =SUM(E7:P7) -> 0
R8: =SUM(E8:P8) -> 0
R9: =SUM(E9:P9) -> 0
R10: =SUM(E10:P10) -> 0
R11: =SUM(E11:P11) -> 0
R12: =SUM(E12:P12) -> 0
R13: =SUM(E13:P13) -> 0
R14: =SUM(E14:P14) -> 0
R15: =SUM(E15:P15) -> 0
... R49: =SUM(E49:P49) -> 0
D50: TOTAL | R50: =SUM(E50:P50) -> 0
B52: ＊設備投資は、30,000,000VND以上、且つ1年以上使用するものが対象となります。
B53: ＊建設仮勘定を含む、取得基準にて記入して下さい。
B54: ＊重複を避ける為、稟議起案部門にて記入して下さい。
B55: ＊リースによる設備投資を含めないで下さい。

Sheet 勘定科目
A1: Account_Code | B1: JPN (50cha) | C1: Tiếng Việt_Tên tài khoản kế toán | D1: JP_Name | E1: Tiếng Việt_Hạng mục lợi nhuận | F1: 製造 | G1: 一般 | H1: 販売 | I1: REMARK
F2: =COLUMNS($A$2:F2) -> 6 | G2: =COLUMNS($A$2:G2) -> 7 | H2: =COLUMNS($A$2:H2) -> 8
A3: 7001065118 | B3: 雑収入 | C3: Doanh thu khác | D3: 雑収入 | E3: Thu nhập khác | F3: 7001065118 | G3: 7001065118 | H3: 7001065118
A4: 7001075118 | B4: 雑収入（関係会社） | C4: Doanh thu khác | D4: 雑収入 | E4: Thu nhập khác | F4: 7001075118 | G4: 7001075118 | H4: 7001075118
A5: 7001065119 | B5: 固定資産売却勘定 | C5: Doanh thu khác | D5: 雑収入 | E5: Thu nhập khác | F5: 7001065119 | G5: 7001065119 | H5: 7001065119
A6: 5001016131 | B6: 材料仕入割戻高 | C6: Chi phí nguyên liệu, vật liệu trực tiếp | D6: 材料費 | E6: Chi phí nguyên vật liệu | F6: 5001016131 | I6: 2016年4月から追加する。
A7: 5001016134 | B7: リーフレット用材料 | C7: Chi phí nguyên liệu, vật liệu trực tiếp | D7: 材料費 | E7: Chi phí nguyên vật liệu | F7: 5001016134 | G7: 5001016134 | H7: 5001016134 | I7: 2017年1月変更。
A8: 5001016135 | B8: 不良部品材料費 | C8: Chi phí nguyên liệu, vật liệu trực tiếp | D8: 材料費 | E8: Chi phí nguyên vật liệu | F8: 5001016135 | G8: 5001016135 | H8: 5001016135
A9: 5001016136 | B9: 追加指図部品費 | C9: Chi phí nguyên liệu, vật liệu trực tiếp | D9: 材料費 | E9: Chi phí nguyên vật liệu | F9: 5001016136 | G9: 5001016136 | H9: 5001016136
A10: 5001016142 | B10: 加工中不良廃棄損 | C10: Chi phí nguyên liệu, vật liệu trực tiếp | D10: 仕掛仕損 | E10: Sản phẩm chưa hoàn thiện,hỏng | F10: 5001016142 | G10: 5001016142 | H10: 5001016142
A11: 5001016149 | B11: 金型材料仕入 | C11: Chi phí nguyên liệu, vật liệu trực tiếp | D11: 材料費 | E11: Chi phí nguyên vật liệu | F11: 5001016149 | G11: 5001016149 | H11: 5001016149 | I11: 2月から追加する。
A12: 5001016151 | B12: 生産用副資材 | C12: Chi phí nguyên liệu, vật liệu trực tiếp | D12: 材料費 | E12: Chi phí nguyên vật liệu | F12: 5001016151 | I12: 2017年1月追加。
A13: 5004046221 | B13: 雑給（直製） | C13: Chi phí nhân công trực tiếp | D13: 雑給 | E13: Chi phí nhân công trực tiếp | F13: 5004046221
A14: 5004046371 | B14: 雑給（間製） | C14: Chi phí nhân viên phân xưởng | D14: 雑給 | E14: Chi phí nhân công trực tiếp | F14: 5004046371
A15: 5005016371 | B15: 生産用消耗品費（製） | C15: Chi phí dụng cụ sản xuất | D15: 消耗品費 | E15: Chi phí hàng hóa tiêu hao | F15: 5005016371
A16: 5005016372 | B16: その他消耗品（製） | C16: Chi phí dụng cụ sản xuất | D16: 消耗品費 | E16: Chi phí hàng hóa tiêu hao | F16: 5005016372
A17: 5005016373 | B17: 生産用文房具（製造） | C17: Chi phí dụng cụ sản xuất | D17: 消耗品費 | E17: Chi phí hàng hóa tiêu hao | F17: 5005016373 | I17: 2017年1月追加。
A18: 5005026371 | B18: 消耗工具器具備品費（製） | C18: Chi phí dụng cụ sản xuất | D18: 消耗工具器具備品費 | E18: Chi phí sử dụng công cụ,đồ đạc | F18: 5005026371
A19: 5005026372 | B19: 消耗金型代（製） | C19: Chi phí dụng cụ sản xuất | D19: 消耗金型費 | E19: Chi phí tiêu hao khuôn | F19: 5005026372
A20: 5006016241 | B20: 減価償却費（製） 建物 | C20: Chi phí khấu hao TSCĐ | D20: 減価償却費 | E20: Chi phí khấu hao | F20: 5006016241
A21: 5006016242 | B21: 減価償却費（製） 機械装置 | C21: Chi phí khấu hao TSCĐ | D21: 減価償却費 | E21: Chi phí khấu hao | F21: 5006016242
A22: 5006016243 | B22: 減価償却費（製） 車輌運搬具 | C22: Chi phí khấu hao TSCĐ | D22: 減価償却費 | E22: Chi phí khấu hao | F22: 5006016243
A23: 5006016244 | B23: 減価償却費（製） 工具器具備品 | C23: Chi phí khấu hao TSCĐ | D23: 減価償却費 | E23: Chi phí khấu hao | F23: 5006016244
A24: 5006016245 | B24: 減価償却費（製） 構築物 | C24: Chi phí khấu hao TSCĐ | D24: 減価償却費 | E24: Chi phí khấu hao | F24: 5006016245
A25: 5005036246 | B25: 減価償却費（製） 金型 | C25: Chi phí khấu hao TSCĐ | D25: 金型償却費 | E25: Chi phí khấu hao khuôn | F25: 5005036246
A26: 5006016247 | B26: 減価償却費（製） その他有形固定資産 | C26: Chi phí khấu hao TSCĐ | D26: 減価償却費 | E26: Chi phí khấu hao | F26: 5006016247
A27: 5006016248 | B27: 減価償却費（製） リース建物 | C27: Chi phí khấu hao TSCĐ | D27: 減価償却費 | E27: Chi phí khấu hao | F27: 5006016248
A28: 5006016249 | B28: 減価償却費（製） リース機械装置 | C28: Chi phí khấu hao TSCĐ | D28: 減価償却費 | E28: Chi phí khấu hao | F28: 5006016249
A29: 5006016250 | B29: 減価償却費（製） リース車輌運搬具 | C29: Chi phí khấu hao TSCĐ | D29: 減価償却費 | E29: Chi phí khấu hao | F29: 5006016250
... A44: 5005046283 | B44: 年間保守料（製） | C44: Chi phi dịch vụ mua ngoài | D44: 修繕費 | E44: Chi phí sửa chữa | F44: 5005046283
A45: 5005046284 | B45: 金型修繕費（製造） | C45: Chi phi dịch vụ mua ngoài | D45: 修繕費 | E45: Chi phí sửa chữa | F45: 5005046284 | I45: 2017年1月追加。
A46: 5005066281 | B46: 電気代（製） | C46: Chi phi dịch vụ mua ngoài | D46: 水道光熱費 | E46: Chi phí Utilities(điện,nước..) | F46: 5005066281
A47: 5005066282 | B47: 水道代（製） | C47: Chi phi dịch vụ mua ngoài | D47: 水道光熱費 | E47: Chi phí Utilities(điện,nước..) | F47: 5005066282
A48: 5005056281 | B48: ガス代（製） | C48: Chi phi dịch vụ mua ngoài | D48: 水道光熱費 | E48: Chi phí Utilities(điện,nước..) | F48: 5005056281
A49: 5005076281 | B49: 通関申告費用（製） | C49: Chi phi dịch vụ mua ngoài | D49: 荷造運賃 | E49: Chi phí vận chuyển hàng hóa | F49: 5005076281
A50: 5005076282 | B50: 設備輸送費（製） | C50: Chi phi dịch vụ mua ngoài | D50: 荷造運賃 | E50: Chi phí vận chuyển hàng hóa | F50: 5005076282
A51: 5005076283 | B51: 輸入航空運賃（製） | C51: Chi phi dịch vụ mua ngoài | D51: 荷造運賃 | E51: Chi phí vận chuyển hàng hóa | F51: 5005076283
A52: 5005076284 | B52: 輸入海上運賃（製） | C52: Chi phi dịch vụ mua ngoài | D52: 荷造運賃 | E52: Chi phí vận chuyển hàng hóa | F52: 5005076284
A53: 5005076285 | B53: 空箱返却費用 | C53: Chi phi dịch vụ mua ngoài | D53: 荷造運賃 | E53: Chi phí vận chuyển hàng hóa | F53: 5005076285
A54: 5005076286 | B54: 部品集荷トラック代 | C54: Chi phi dịch vụ mua ngoài | D54: 荷造運賃 | E54: Chi phí vận chuyển hàng hóa | F54: 5005076286
A55: 5005076287 | B55: 物流保険料（製） | C55: Chi phi dịch vụ mua ngoài | D55: 荷造運賃 | E55: Chi phí vận chuyển hàng hóa | F55: 5005076287
A56: 5005076288 | B56: 梱包材料費（製） | C56: Chi phi dịch vụ mua ngoài | D56: 荷造用品費 | E56: Chi phí NVL dùng đóng gói hàng | F56: 5005076288
A57: 5005076289 | B57: クーリエ費用（製） | C57: Chi phi dịch vụ mua ngoài | D57: 荷造運賃 | E57: Chi phí vận chuyển hàng hóa | F57: 5005076289
A58: 5005076291 | B58: 外部倉庫 取扱手数料（製造） | C58: Chi phi dịch vụ mua ngoài | D58: 荷造運賃 | E58: Chi phí vận chuyển hàng hóa | F58: 5005076291 | I58: 2017年1月追加。
A59: 5005076292 | B59: 外部倉庫 保管料（製造） | C59: Chi phi dịch vụ mua ngoài | D59: 荷造運賃 | E59: Chi phí vận chuyển hàng hóa | F59: 5005076292 | I59: 2017年1月追加。
A60: 5005076293 | B60: 外部倉庫 輸送料（製造） | C60: Chi phi dịch vụ mua ngoài | D60: 荷造運賃 | E60: Chi phí vận chuyển hàng hóa | F60: 5005076293 | I60: 2017年1月追加。
A61: 5005076294 | B61: 外部物流業者 取扱手数料（製造） | C61: Chi phi dịch vụ mua ngoài | D61: 荷造運賃 | E61: Chi phí vận chuyển hàng hóa | F61: 5005076294 | I61: 2017年1月追加。
A62: 5005086281 | B62: 技術料（製） | C62: Chi phi dịch vụ mua ngoài | D62: 技術料 | E62: Phí kỹ thuật | F62: 5005086281
A63: 5005136281 | B63: 通信費（製） | C63: Chi phi dịch vụ mua ngoài | D63: 通信費 | E63: Chi phí điện thoại | F63: 5005136281
A64: 5005246281 | B64: 図書印刷費（製） | C64: Chi phi dịch vụ mua ngoài | D64: 図書及び事務費 | E64: Chi phí văn phòng | F64: 5005246281
A65: 5005246282 | B65: ＫＤＣシステム使用料（製） | C65: Chi phi dịch vụ mua ngoài | D65: 図書及び事務費 | E65: Chi phí văn phòng | F65: 5005246282
A66: 5005246283 | B66: ライセンス料（製） | C66: Chi phi dịch vụ mua ngoài | D66: 図書及び事務費 | E66: Chi phí văn phòng | F66: 5005246283
A67: 5005246284 | B67: 会費（製） | C67: Chi phi dịch vụ mua ngoài | D67: 会費及び会議費 | E67: Chi phí cuộc họp | F67: 5005246284
A68: 5005216281 | B68: 委嘱報酬・設計委託費（製） | C68: Chi phi dịch vụ mua ngoài | D68: 委嘱報酬 | E68: Thù lao ủy thác,phí hoa hồng | F68: 5005216281
A69: 5005226281 | B69: 保険料（製） | C69: Chi phi dịch vụ mua ngoài | D69: 保険料 | E69: Chi phí bảo hiểm | F69: 5005226281
A70: 5005236281 | B70: 事務所賃借料（製） | C70: Chi phi dịch vụ mua ngoài | D70: 賃借料 | E70: Chi phí thuê | F70: 5005236281
A71: 5005236282 | B71: 倉庫賃借料（製） | C71: Chi phi dịch vụ mua ngoài | D71: 賃借料 | E71: Chi phí thuê | F71: 5005236282
A72: 5005246285 | B72: 取扱手数料（製） | C72: Chi phi dịch vụ mua ngoài | D72: 手数料 | E72: Tiền dịch vụ,tiền lệ phí | F72: 5005246285
A73: 5005246286 | B73: その他手数料（製） | C73: Chi phi dịch vụ mua ngoài | D73: 手数料 | E73: Tiền dịch vụ,tiền lệ phí | F73: 5005246286
... A82: 5005186292 | B82: その他税金（製） | C82: Chi phí bằng tiền khác | D82: 公租公課 | E82: Thuế,phí công cộng | F82: 5005186292
A83: 5005196373 | B83: 試験研究用材料費 | C83: Chi phí dụng cụ sản xuất | D83: 試験研究費 | E83: Chi phí thử nghiệm,nghiên cứu | F83: 5005196373 | G83: 5005196373 | H83: 5005196373 | I83: 2月から追加する。
A84: 5005196277 | B84: 試験研究用役務費 | C84: Chi phi dịch vụ mua ngoài | D84: 試験研究費 | E84: Chi phí thử nghiệm,nghiên cứu | F84: 5005196277 | G84: 5005196277 | H84: 5005196277 | I84: 2月から追加する。
A85: 5005246291 | B85: 会議費（製） | C85: Chi phí bằng tiền khác | D85: 会費及び会議費 | E85: Chi phí cuộc họp | F85: 5005246291
A86: 5005246292 | B86: 雑費（製） | C86: Chi phí bằng tiền khác | D86: 雑費 | E86: Các loại chi phí bằng tiền khác | F86: 5005246292
A87: 5005246294 | B87: 開発費振替勘定（製） | C87: Chi phí bằng tiền khác | D87: 雑費 | E87: Các loại chi phí bằng tiền khác | F87: 5005246294 | I87: 2月から追加する→9/2015からｘから雑費になった
A88: 5005256291 | B88: 棚卸減耗費（製） | C88: Chi phí bằng tiền khác | D88: 棚卸減耗費 | E88: Chi phí hao hụt sau kiểm kê | F88: 5005256291
A89: 5101016174 | B89: 製商品仕入諸掛 | C89: Giá vốn hàng bán | D89: 仕入製商品費 | E89: Chi phí bán hàng | F89: 5101016174
A90: 5101016179 | B90: 製品品目外注加工費 | C90: Giá vốn hàng bán | D90: 外注加工費 | E90: Chi phí gia công ngoài | F90: 5101016179
A91: 5101016187 | B91: 製商品在庫廃棄損 | C91: Giá vốn hàng bán | D91: 雑損失 | E91: Tổn thất,lỗ khác | F91: 5101016187
A92: 5101016189 | B92: 金型製作収入 | C92: Doanh thu bán thành phẩm | D92: 雑収入 | E92: Thu nhập khác | F92: 5101016189 | I92: 2月から追加する。
A93: 6004046511 | B93: 雑給（販売） | C93: Chi phí nhân viên | D93: 雑給 | E93: Chi phí nhân công trực tiếp | H93: 6004046511
A94: 6003036412 | B94: 梱包材料費（販売） | C94: Chi phí vật liệu bao bì | D94: 荷造用品費 | E94: Chi phí NVL dùng đóng gói hàng | H94: 6003036412
A95: 6005016413 | B95: 消耗品費（販売） | C95: Chi phí dụng cụ đồ dùng | D95: 消耗品費 | E95: Chi phí hàng hóa tiêu hao | H95: 6005016413
A96: 6005016414 | B96: 消耗備品費（販売） | C96: Chi phí dụng cụ đồ dùng | D96: 消耗工具器具備品費 | E96: Chi phí sử dụng công cụ,đồ đạc | G96: 6005016414 | H96: 6005016414 | I96: 2017年1月追加。
A97: 6006016521 | B97: 減価償却費（販） 建物 | C97: Chi phí khấu hao TSCĐ | D97: 減価償却費 | E97: Chi phí khấu hao | H97: 6006016521
A98: 6006016522 | B98: 減価償却費（販） 機械装置 | C98: Chi phí khấu hao TSCĐ | D98: 減価償却費 | E98: Chi phí khấu hao | H98: 6006016522
A99: 6006016523 | B99: 減価償却費（販） 車輌運搬具 | C99: Chi phí khấu hao TSCĐ | D99: 減価償却費 | E99: Chi phí khấu hao | H99: 6006016523
A100: 6006016524 | B100: 減価償却費（販） 工具器具備品 | C100: Chi phí khấu hao TSCĐ | D100: 減価償却費 | E100: Chi phí khấu hao | H100: 6006016524
A101: 6006016525 | B101: 減価償却費（販） 構築物 | C101: Chi phí khấu hao TSCĐ | D101: 減価償却費 | E101: Chi phí khấu hao | H101: 6006016525
A102: 6006016526 | B102: 減価償却費（販） その他有形固定資産 | C102: Chi phí khấu hao TSCĐ | D102: 減価償却費 | E102: Chi phí khấu hao | H102: 6006016526
A103: 6006016527 | B103: 減価償却費（販） リース建物 | C103: Chi phí khấu hao TSCĐ | D103: 減価償却費 | E103: Chi phí khấu hao | H103: 6006016527
A104: 6006016528 | B104: 減価償却費（販） リース機械装置 | C104: Chi phí khấu hao TSCĐ | D104: 減価償却費 | E104: Chi phí khấu hao | H104: 6006016528
A105: 6006016529 | B105: 減価償却費（販） リース車輌運搬具 | C105: Chi phí khấu hao TSCĐ | D105: 減価償却費 | E105: Chi phí khấu hao | H105: 6006016529
A106: 6006016530 | B106: 減価償却費（販） リース工具器具備品 | C106: Chi phí khấu hao TSCĐ | D106: 減価償却費 | E106: Chi phí khấu hao | H106: 6006016530
A107: 6006016531 | B107: 減価償却費（販） リース構築物 | C107: Chi phí khấu hao TSCĐ | D107: 減価償却費 | E107: Chi phí khấu hao | H107: 6006016531
A108: 6006016532 | B108: 減価償却費（販） 土地使用権 | C108: Chi phí khấu hao TSCĐ | D108: 減価償却費 | E108: Chi phí khấu hao | H108: 6006016532
... A122: 6003036542 | B122: クーリエ費用（販売） | C122: Chi phí dịch vụ mua ngòai | D122: 荷造運賃 | E122: Chi phí vận chuyển hàng hóa | H122: 6003036542
A123: 6003036543 | B123: 輸出航空運賃（販売） | C123: Chi phí dịch vụ mua ngòai | D123: 荷造運賃 | E123: Chi phí vận chuyển hàng hóa | F123: 6003036543 | H123: 6003036543
A124: 6003036544 | B124: 輸出海上運賃（販売） | C124: Chi phí dịch vụ mua ngòai | D124: 荷造運賃 | E124: Chi phí vận chuyển hàng hóa | F124: 6003036544 | G124: 6003036544 | H124: 6003036544
A125: 6003036545 | B125: 保管延長費（販売） | C125: Chi phí dịch vụ mua ngòai | D125: 荷造運賃 | E125: Chi phí vận chuyển hàng hóa | H125: 6003036545
A126: 6003036546 | B126: 物流保険料（販売） | C126: Chi phí dịch vụ mua ngòai | D126: 荷造運賃 | E126: Chi phí vận chuyển hàng hóa | H126: 6003036546
A127: 6003036547 | B127: 梱包費用（販売） | C127: Chi phí dịch vụ mua ngòai | D127: 荷造運賃 | E127: Chi phí vận chuyển hàng hóa | H127: 6003036547
A128: 6003036548 | B128: 返品手数料（販売） | C128: Chi phí dịch vụ mua ngòai | D128: 荷造運賃 | E128: Chi phí vận chuyển hàng hóa | H128: 6003036548
A129: 6003036549 | B129: 保管料（販売） | C129: Chi phí dịch vụ mua ngòai | D129: 荷造運賃 | E129: Chi phí vận chuyển hàng hóa | H129: 6003036549
A130: 6003036550 | B130: オーバーナイト費（販売） | C130: Chi phí dịch vụ mua ngòai | D130: 荷造運賃 | E130: Chi phí vận chuyển hàng hóa | H130: 6003036550
A131: 6003036551 | B131: バンニング費（販売） | C131: Chi phí dịch vụ mua ngòai | D131: 荷造運賃 | E131: Chi phí vận chuyển hàng hóa | H131: 6003036551
A132: 6003036552 | B132: その他物流費（販売） | C132: Chi phí dịch vụ mua ngòai | D132: 荷造運賃 | E132: Chi phí vận chuyển hàng hóa | F132: 6003036552 | H132: 6003036552
A133: 6003036554 | B133: 外部倉庫 取扱手数料（販売） | C133: Chi phí dịch vụ mua ngòai | D133: 荷造運賃 | E133: Chi phí vận chuyển hàng hóa | F133: 6003036554 | G133: 6003036554 | H133: 6003036554 | I133: 2017年1月追加。
A134: 6003036555 | B134: 外部倉庫 保管料（販売） | C134: Chi phí dịch vụ mua ngòai | D134: 荷造運賃 | E134: Chi phí vận chuyển hàng hóa | F134: 6003036555 | G134: 6003036555 | H134: 6003036555 | I134: 2017年1月追加。
A135: 6003036556 | B135: 外部倉庫 輸送料（販売） | C135: Chi phí dịch vụ mua ngòai | D135: 荷造運賃 | E135: Chi phí vận chuyển hàng hóa | F135: 6003036556 | G135: 6003036556 | H135: 6003036556 | I135: 2017年1月追加。
...

Sheet 原価センタ
B1: 原価センタ | D1: 採算区分 | E1: 原価区分
A2: 1412000004 | B2: 機器製造1課 | C2: 01. | D2: 製造 | E2: 製造 | G2: V02XD800
A3: 1412000005 | B3: 機器製造2課 | C3: 02. | D3: 製造 | E3: 製造
A4: 1412000062 | B4: 機器製造管理課 | C4: 03. | D4: 部内間接 | E4: 製造
A5: 1412000034 | B5: トナー製造課 | C5: 04. | D5: 製造 | E5: 製造
A6: 1412000048 | B6: トナー生産技術課 | C6: 05. | D6: 部内間接 | E6: 製造
A7: 1412000055 | B7: トナー品質管理課 | C7: 06. | D7: 部内間接 | E7: 製造
A8: 1412000050 | B8: MD1課 | C8: 07. | D8: 製造 | E8: 製造
A9: 1412000077 | B9: MD2課 | C9: 08. | D9: 製造 | E9: 製造
A10: 1412000053 | B10: 工程品質管理1課 | C10: 09. | D10: 部内間接 | E10: 製造
A11: 1412000008 | B11: 生産管理課 | C11: 10. | D11: 部内間接 | E11: 製造
A12: 1412000010 | B12: 採算管理課 | C12: 11. | D12: 部外間接1 | E12: 製造
A13: 1412000054 | B13: マスター管理課 | C13: 12. | D13: 部外間接1 | E13: 製造
A14: 1412000036 | B14: 部品管理課 | C14: 13. | D14: 部内間接 | E14: 製造
... A58: 1412000099 | B58: MD4課 | C58: 65. | D58: 製造 | E58: 製造

Sheet 稼働日
A2: FY2026 | B2: 稼働日
A3: 4 | B3: 20
A4: 5 | B4: 19
A5: 6 | B5: 21
A6: 7 | B6: 23
A7: 8 | B7: 20
A8: 9 | B8: 19
A9: 10 | B9: 23
A10: 11 | B10: 20
A11: 12 | B11: 22
A12: 1 | B12: 20
A13: 2 | B13: 15
A14: 3 | B14: 20
