Workbook
Name WBS: 原価センタ!$G$2:$G$3

Sheet 採算表(USD)
B1: 組織名 | C1: ='採算表(VND)'!C1 -> MP FY2026_各予定 | N1: ='内訳ﾘｽﾄ(4～3月)'!B2 -> 25390
B2: ='採算表(VND)'!B2 -> MD3課
B4: 項目 ＼ 部門 | C4: ='採算表(VND)'!C4 -> 4 | D4: ='採算表(VND)'!D4 -> 5 | E4: ='採算表(VND)'!E4 -> 6 | F4: ='採算表(VND)'!F4 -> 7 | G4: ='採算表(VND)'!G4 -> 8 | H4: ='採算表(VND)'!H4 -> 9 | I4: ='採算表(VND)'!I4 -> 10 | J4: ='採算表(VND)'!J4 -> 11 | ... O4: ='採算表(VND)'!O4 -> 合計
B5: 総出荷 | C5: =C8+C9 -> 29803.37 | D5: =D8+D9 -> 43553.32 | E5: =E8+E9 -> 40419.06 | F5: =F8+F9 -> 41786.85 | G5: =G8+G9 -> 45272.7 | H5: =H8+H9 -> 45438.09 | I5: =I8+I9 -> 57256.11 | J5: =J8+J9 -> 46122.27 | ... O5: =O8+O9 -> 529556.24
B6: 社外出荷 | C6: =ROUNDDOWN('採算表(VND)'!C6/$N$1,2) -> 29803.37 | D6: =ROUNDDOWN('採算表(VND)'!D6/$N$1,2) -> 43553.32 | E6: =ROUNDDOWN('採算表(VND)'!E6/$N$1,2) -> 40419.06 | F6: =ROUNDDOWN('採算表(VND)'!F6/$N$1,2) -> 41786.85 | G6: =ROUNDDOWN('採算表(VND)'!G6/$N$1,2) -> 45272.7 | H6: =ROUNDDOWN('採算表(VND)'!H6/$N$1,2) -> 45438.09 | I6: =ROUNDDOWN('採算表(VND)'!I6/$N$1,2) -> 57256.11 | J6: =ROUNDDOWN('採算表(VND)'!J6/$N$1,2) -> 46122.27 | ... N6: =ROUNDDOWN('採算表(VND)'!N6/$N$1,2) -> 44490.33 | O6: =SUM(C6:N6) -> 529556.24
B7: 販売支援 | C7: =ROUNDDOWN('採算表(VND)'!C7/$N$1,2) -> 0 | D7: =ROUNDDOWN('採算表(VND)'!D7/$N$1,2) -> 0 | E7: =ROUNDDOWN('採算表(VND)'!E7/$N$1,2) -> 0 | F7: =ROUNDDOWN('採算表(VND)'!F7/$N$1,2) -> 0 | G7: =ROUNDDOWN('採算表(VND)'!G7/$N$1,2) -> 0 | H7: =ROUNDDOWN('採算表(VND)'!H7/$N$1,2) -> 0 | I7: =ROUNDDOWN('採算表(VND)'!I7/$N$1,2) -> 0 | J7: =ROUNDDOWN('採算表(VND)'!J7/$N$1,2) -> 0 | ... N7: =ROUNDDOWN('採算表(VND)'!N7/$N$1,2) -> 0 | O7: =SUM(C7:N7) -> 0
B8: 社外出荷合計 | C8: =C6+C7 -> 29803.37 | D8: =D6+D7 -> 43553.32 | E8: =E6+E7 -> 40419.06 | F8: =F6+F7 -> 41786.85 | G8: =G6+G7 -> 45272.7 | H8: =H6+H7 -> 45438.09 | I8: =I6+I7 -> 57256.11 | J8: =J6+J7 -> 46122.27 | ... O8: =O6+O7 -> 529556.24
B9: 社内売 | C9: =ROUNDDOWN('採算表(VND)'!C9/$N$1,2) -> 0 | D9: =ROUNDDOWN('採算表(VND)'!D9/$N$1,2) -> 0 | E9: =ROUNDDOWN('採算表(VND)'!E9/$N$1,2) -> 0 | F9: =ROUNDDOWN('採算表(VND)'!F9/$N$1,2) -> 0 | G9: =ROUNDDOWN('採算表(VND)'!G9/$N$1,2) -> 0 | H9: =ROUNDDOWN('採算表(VND)'!H9/$N$1,2) -> 0 | I9: =ROUNDDOWN('採算表(VND)'!I9/$N$1,2) -> 0 | J9: =ROUNDDOWN('採算表(VND)'!J9/$N$1,2) -> 0 | ... N9: =ROUNDDOWN('採算表(VND)'!N9/$N$1,2) -> 0 | O9: =SUM(C9:N9) -> 0
B10: 社内買 | C10: =ROUNDDOWN('採算表(VND)'!C10/$N$1,2) -> 0 | D10: =ROUNDDOWN('採算表(VND)'!D10/$N$1,2) -> 0 | E10: =ROUNDDOWN('採算表(VND)'!E10/$N$1,2) -> 0 | F10: =ROUNDDOWN('採算表(VND)'!F10/$N$1,2) -> 0 | G10: =ROUNDDOWN('採算表(VND)'!G10/$N$1,2) -> 0 | H10: =ROUNDDOWN('採算表(VND)'!H10/$N$1,2) -> 0 | I10: =ROUNDDOWN('採算表(VND)'!I10/$N$1,2) -> 0 | J10: =ROUNDDOWN('採算表(VND)'!J10/$N$1,2) -> 0 | ... N10: =ROUNDDOWN('採算表(VND)'!N10/$N$1,2) -> 0 | O10: =SUM(C10:N10) -> 0
B12: 総生産 | C12: =C5-C10 -> 29803.37 | D12: =D5-D10 -> 43553.32 | E12: =E5-E10 -> 40419.06 | F12: =F5-F10 -> 41786.85 | G12: =G5-G10 -> 45272.7 | H12: =H5-H10 -> 45438.09 | I12: =I5-I10 -> 57256.11 | J12: =J5-J10 -> 46122.27 | ... O12: =O5-O10 -> 529556.24
B13: 控除額 | C13: =SUM(C14:C65) -> 15786.73 | D13: =SUM(D14:D65) -> 17904.1 | E13: =SUM(E14:E65) -> 16382.29 | F13: =SUM(F14:F65) -> 18303.13 | G13: =SUM(G14:G65) -> 18206.71 | H13: =SUM(H14:H65) -> 30694.92 | I13: =SUM(I14:I65) -> 18556.05 | J13: =SUM(J14:J65) -> 17609.38 | ... O13: =SUM(O14:O65) -> 224210.84
B14: 材料費 | C14: =ROUNDUP('採算表(VND)'!C14/$N$1,2) -> 0 | D14: =ROUNDUP('採算表(VND)'!D14/$N$1,2) -> 0 | E14: =ROUNDUP('採算表(VND)'!E14/$N$1,2) -> 0 | F14: =ROUNDUP('採算表(VND)'!F14/$N$1,2) -> 0 | G14: =ROUNDUP('採算表(VND)'!G14/$N$1,2) -> 0 | H14: =ROUNDUP('採算表(VND)'!H14/$N$1,2) -> 0 | I14: =ROUNDUP('採算表(VND)'!I14/$N$1,2) -> 0 | J14: =ROUNDUP('採算表(VND)'!J14/$N$1,2) -> 0 | ... N14: =ROUNDUP('採算表(VND)'!N14/$N$1,2) -> 0 | O14: =SUM(C14:N14) -> 0
B15: 設計変更材料費 | C15: =ROUNDUP('採算表(VND)'!C15/$N$1,2) -> 0 | D15: =ROUNDUP('採算表(VND)'!D15/$N$1,2) -> 0 | E15: =ROUNDUP('採算表(VND)'!E15/$N$1,2) -> 0 | F15: =ROUNDUP('採算表(VND)'!F15/$N$1,2) -> 0 | G15: =ROUNDUP('採算表(VND)'!G15/$N$1,2) -> 0 | H15: =ROUNDUP('採算表(VND)'!H15/$N$1,2) -> 0 | I15: =ROUNDUP('採算表(VND)'!I15/$N$1,2) -> 0 | J15: =ROUNDUP('採算表(VND)'!J15/$N$1,2) -> 0 | ... N15: =ROUNDUP('採算表(VND)'!N15/$N$1,2) -> 0 | O15: =SUM(C15:N15) -> 0
B16: 仕掛仕損 | C16: =ROUNDUP('採算表(VND)'!C16/$N$1,2) -> 0 | D16: =ROUNDUP('採算表(VND)'!D16/$N$1,2) -> 0 | E16: =ROUNDUP('採算表(VND)'!E16/$N$1,2) -> 0 | F16: =ROUNDUP('採算表(VND)'!F16/$N$1,2) -> 0 | G16: =ROUNDUP('採算表(VND)'!G16/$N$1,2) -> 0 | H16: =ROUNDUP('採算表(VND)'!H16/$N$1,2) -> 0 | I16: =ROUNDUP('採算表(VND)'!I16/$N$1,2) -> 0 | J16: =ROUNDUP('採算表(VND)'!J16/$N$1,2) -> 0 | ... N16: =ROUNDUP('採算表(VND)'!N16/$N$1,2) -> 0 | O16: =SUM(C16:N16) -> 0
B17: 仕入製商品費 | C17: =ROUNDUP('採算表(VND)'!C17/$N$1,2) -> 0 | D17: =ROUNDUP('採算表(VND)'!D17/$N$1,2) -> 0 | E17: =ROUNDUP('採算表(VND)'!E17/$N$1,2) -> 0 | F17: =ROUNDUP('採算表(VND)'!F17/$N$1,2) -> 0 | G17: =ROUNDUP('採算表(VND)'!G17/$N$1,2) -> 0 | H17: =ROUNDUP('採算表(VND)'!H17/$N$1,2) -> 0 | I17: =ROUNDUP('採算表(VND)'!I17/$N$1,2) -> 0 | J17: =ROUNDUP('採算表(VND)'!J17/$N$1,2) -> 0 | ... N17: =ROUNDUP('採算表(VND)'!N17/$N$1,2) -> 0 | O17: =SUM(C17:N17) -> 0
B18: 内製品有償支給原価 | C18: =ROUNDUP('採算表(VND)'!C18/$N$1,2) -> 0 | D18: =ROUNDUP('採算表(VND)'!D18/$N$1,2) -> 0 | E18: =ROUNDUP('採算表(VND)'!E18/$N$1,2) -> 0 | F18: =ROUNDUP('採算表(VND)'!F18/$N$1,2) -> 0 | G18: =ROUNDUP('採算表(VND)'!G18/$N$1,2) -> 0 | H18: =ROUNDUP('採算表(VND)'!H18/$N$1,2) -> 0 | I18: =ROUNDUP('採算表(VND)'!I18/$N$1,2) -> 0 | J18: =ROUNDUP('採算表(VND)'!J18/$N$1,2) -> 0 | ... N18: =ROUNDUP('採算表(VND)'!N18/$N$1,2) -> 0 | O18: =SUM(C18:N18) -> 0
B19: 外注加工費 | C19: =ROUNDUP('採算表(VND)'!C19/$N$1,2) -> 0 | D19: =ROUNDUP('採算表(VND)'!D19/$N$1,2) -> 0 | E19: =ROUNDUP('採算表(VND)'!E19/$N$1,2) -> 0 | F19: =ROUNDUP('採算表(VND)'!F19/$N$1,2) -> 0 | G19: =ROUNDUP('採算表(VND)'!G19/$N$1,2) -> 0 | H19: =ROUNDUP('採算表(VND)'!H19/$N$1,2) -> 0 | I19: =ROUNDUP('採算表(VND)'!I19/$N$1,2) -> 0 | J19: =ROUNDUP('採算表(VND)'!J19/$N$1,2) -> 0 | ... N19: =ROUNDUP('採算表(VND)'!N19/$N$1,2) -> 0 | O19: =SUM(C19:N19) -> 0
B20: 減価償却費 | C20: =ROUNDUP('採算表(VND)'!C20/$N$1,2) -> 10862.61 | D20: =ROUNDUP('採算表(VND)'!D20/$N$1,2) -> 10789.26 | E20: =ROUNDUP('採算表(VND)'!E20/$N$1,2) -> 10790.77 | F20: =ROUNDUP('採算表(VND)'!F20/$N$1,2) -> 11982 | G20: =ROUNDUP('採算表(VND)'!G20/$N$1,2) -> 12864.18 | H20: =ROUNDUP('採算表(VND)'!H20/$N$1,2) -> 12847.1 | I20: =ROUNDUP('採算表(VND)'!I20/$N$1,2) -> 12847.1 | J20: =ROUNDUP('採算表(VND)'!J20/$N$1,2) -> 12832.58 | ... N20: =ROUNDUP('採算表(VND)'!N20/$N$1,2) -> 12830.48 | O20: =SUM(C20:N20) -> 147168.35
B21: 金型償却費 | C21: =ROUNDUP('採算表(VND)'!C21/$N$1,2) -> 0 | D21: =ROUNDUP('採算表(VND)'!D21/$N$1,2) -> 0 | E21: =ROUNDUP('採算表(VND)'!E21/$N$1,2) -> 0 | F21: =ROUNDUP('採算表(VND)'!F21/$N$1,2) -> 0 | G21: =ROUNDUP('採算表(VND)'!G21/$N$1,2) -> 0 | H21: =ROUNDUP('採算表(VND)'!H21/$N$1,2) -> 0 | I21: =ROUNDUP('採算表(VND)'!I21/$N$1,2) -> 0 | J21: =ROUNDUP('採算表(VND)'!J21/$N$1,2) -> 0 | ... N21: =ROUNDUP('採算表(VND)'!N21/$N$1,2) -> 0 | O21: =SUM(C21:N21) -> 0
B22: 賃借料 | C22: =ROUNDUP('採算表(VND)'!C22/$N$1,2) -> 0 | D22: =ROUNDUP('採算表(VND)'!D22/$N$1,2) -> 0 | E22: =ROUNDUP('採算表(VND)'!E22/$N$1,2) -> 0 | F22: =ROUNDUP('採算表(VND)'!F22/$N$1,2) -> 0 | G22: =ROUNDUP('採算表(VND)'!G22/$N$1,2) -> 0 | H22: =ROUNDUP('採算表(VND)'!H22/$N$1,2) -> 0 | I22: =ROUNDUP('採算表(VND)'!I22/$N$1,2) -> 0 | J22: =ROUNDUP('採算表(VND)'!J22/$N$1,2) -> 0 | ... N22: =ROUNDUP('採算表(VND)'!N22/$N$1,2) -> 0 | O22: =SUM(C22:N22) -> 0
B23: 保険料 | C23: =ROUNDUP('採算表(VND)'!C23/$N$1,2) -> 0 | D23: =ROUNDUP('採算表(VND)'!D23/$N$1,2) -> 0 | E23: =ROUNDUP('採算表(VND)'!E23/$N$1,2) -> 0 | F23: =ROUNDUP('採算表(VND)'!F23/$N$1,2) -> 0 | G23: =ROUNDUP('採算表(VND)'!G23/$N$1,2) -> 0 | H23: =ROUNDUP('採算表(VND)'!H23/$N$1,2) -> 0 | I23: =ROUNDUP('採算表(VND)'!I23/$N$1,2) -> 0 | J23: =ROUNDUP('採算表(VND)'!J23/$N$1,2) -> 0 | ... N23: =ROUNDUP('採算表(VND)'!N23/$N$1,2) -> 0 | O23: =SUM(C23:N23) -> 0
B24: 設計委託費 | C24: =ROUNDUP('採算表(VND)'!C24/$N$1,2) -> 0 | D24: =ROUNDUP('採算表(VND)'!D24/$N$1,2) -> 0 | E24: =ROUNDUP('採算表(VND)'!E24/$N$1,2) -> 0 | F24: =ROUNDUP('採算表(VND)'!F24/$N$1,2) -> 0 | G24: =ROUNDUP('採算表(VND)'!G24/$N$1,2) -> 0 | H24: =ROUNDUP('採算表(VND)'!H24/$N$1,2) -> 0 | I24: =ROUNDUP('採算表(VND)'!I24/$N$1,2) -> 0 | J24: =ROUNDUP('採算表(VND)'!J24/$N$1,2) -> 0 | ... N24: =ROUNDUP('採算表(VND)'!N24/$N$1,2) -> 0 | O24: =SUM(C24:N24) -> 0
B25: 消耗品費 | C25: =ROUNDUP('採算表(VND)'!C25/$N$1,2) -> 33.15 | D25: =ROUNDUP('採算表(VND)'!D25/$N$1,2) -> 33.15 | E25: =ROUNDUP('採算表(VND)'!E25/$N$1,2) -> 33.15 | F25: =ROUNDUP('採算表(VND)'!F25/$N$1,2) -> 33.15 | G25: =ROUNDUP('採算表(VND)'!G25/$N$1,2) -> 33.15 | H25: =ROUNDUP('採算表(VND)'!H25/$N$1,2) -> 33.15 | I25: =ROUNDUP('採算表(VND)'!I25/$N$1,2) -> 33.15 | J25: =ROUNDUP('採算表(VND)'!J25/$N$1,2) -> 33.15 | ... N25: =ROUNDUP('採算表(VND)'!N25/$N$1,2) -> 33.15 | O25: =SUM(C25:N25) -> 397.8
... B65: 本社機構経費 | C65: =ROUNDUP('採算表(VND)'!C65/$N$1,2) -> 0 | D65: =ROUNDUP('採算表(VND)'!D65/$N$1,2) -> 0 | E65: =ROUNDUP('採算表(VND)'!E65/$N$1,2) -> 0 | F65: =ROUNDUP('採算表(VND)'!F65/$N$1,2) -> 0 | G65: =ROUNDUP('採算表(VND)'!G65/$N$1,2) -> 0 | H65: =ROUNDUP('採算表(VND)'!H65/$N$1,2) -> 0 | I65: =ROUNDUP('採算表(VND)'!I65/$N$1,2) -> 0 | J65: =ROUNDUP('採算表(VND)'!J65/$N$1,2) -> 0 | ... N65: =ROUNDUP('採算表(VND)'!N65/$N$1,2) -> 0 | O65: =SUM(C65:N65) -> 0
B66: 差引収益 | C66: =C12-C13 -> 14016.64 | D66: =IF(ISBLANK(D4),"",D12-D13) -> 25649.22 | E66: =IF(ISBLANK(E4),"",E12-E13) -> 24036.77 | F66: =IF(ISBLANK(F4),"",F12-F13) -> 23483.72 | G66: =IF(ISBLANK(G4),"",G12-G13) -> 27065.99 | H66: =IF(ISBLANK(H4),"",H12-H13) -> 14743.17 | I66: =IF(ISBLANK(I4),"",I12-I13) -> 38700.06 | J66: =IF(ISBLANK(J4),"",J12-J13) -> 28512.89 | K66: =IF(ISBLANK(K4),"",K12-K13) -> 27062.68 | ... O66: =IF(ISBLANK(O4),"",O12-O13) -> 305345.4
B67: 総時間 | C67: =C73+C79 -> 2247 | D67: =IF(ISBLANK(D4),"",D73+D79) -> 2097.5 | E67: =IF(ISBLANK(E4),"",E73+E79) -> 2315.25 | F67: =IF(ISBLANK(F4),"",F73+F79) -> 2579.5 | G67: =IF(ISBLANK(G4),"",G73+G79) -> 2257.5 | H67: =IF(ISBLANK(H4),"",H73+H79) -> 2146.25 | I67: =IF(ISBLANK(I4),"",I73+I79) -> 2545.25 | J67: =IF(ISBLANK(J4),"",J73+J79) -> 2228.75 | K67: =IF(ISBLANK(K4),"",K73+K79) -> 2447.5 | ... O67: =IF(ISBLANK(O4),"",O73+O79) -> 27004.5
B68: 直接部門 | C68: ='採算表(VND)'!C68 -> 1997.5 | D68: ='採算表(VND)'!D68 -> 1853 | E68: ='採算表(VND)'!E68 -> 2057 | F68: ='採算表(VND)'!F68 -> 2261 | G68: ='採算表(VND)'!G68 -> 1955 | H68: ='採算表(VND)'!H68 -> 1853 | I68: ='採算表(VND)'!I68 -> 2261 | J68: ='採算表(VND)'!J68 -> 1963.5 | ... N68: ='採算表(VND)'!N68 -> 1963.5 | O68: =SUM(C68:N68) -> 23749
B69: 部内間接部門 | C69: ='採算表(VND)'!C69 -> 0 | D69: ='採算表(VND)'!D69 -> 0 | E69: ='採算表(VND)'!E69 -> 0 | F69: ='採算表(VND)'!F69 -> 0 | G69: ='採算表(VND)'!G69 -> 0 | H69: ='採算表(VND)'!H69 -> 0 | I69: ='採算表(VND)'!I69 -> 0 | J69: ='採算表(VND)'!J69 -> 0 | ... N69: ='採算表(VND)'!N69 -> 0 | O69: =SUM(C69:N69) -> 0
B70: 部外間接部門1 | C70: ='採算表(VND)'!C70 -> 6.75 | D70: ='採算表(VND)'!D70 -> 7 | E70: ='採算表(VND)'!E70 -> 7.75 | F70: ='採算表(VND)'!F70 -> 12 | G70: ='採算表(VND)'!G70 -> 10.75 | H70: ='採算表(VND)'!H70 -> 10 | I70: ='採算表(VND)'!I70 -> 8.25 | J70: ='採算表(VND)'!J70 -> 7.25 | ... N70: ='採算表(VND)'!N70 -> 7.5 | O70: =SUM(C70:N70) -> 98.25
B71: 部外間接部門2 | C71: ='採算表(VND)'!C71 -> 12.75 | D71: ='採算表(VND)'!D71 -> 12.25 | E71: ='採算表(VND)'!E71 -> 14 | F71: ='採算表(VND)'!F71 -> 23.25 | G71: ='採算表(VND)'!G71 -> 20.25 | H71: ='採算表(VND)'!H71 -> 19.75 | I71: ='採算表(VND)'!I71 -> 16.25 | J71: ='採算表(VND)'!J71 -> 14 | ... N71: ='採算表(VND)'!N71 -> 14 | O71: =SUM(C71:N71) -> 187
B72: 工場間接部門 | C72: ='採算表(VND)'!C72 -> 57 | D72: ='採算表(VND)'!D72 -> 56.5 | E72: ='採算表(VND)'!E72 -> 60 | F72: ='採算表(VND)'!F72 -> 96 | G72: ='採算表(VND)'!G72 -> 88.25 | H72: ='採算表(VND)'!H72 -> 82.5 | I72: ='採算表(VND)'!I72 -> 65 | J72: ='採算表(VND)'!J72 -> 59.25 | ... N72: ='採算表(VND)'!N72 -> 60.5 | O72: =SUM(C72:N72) -> 794.25
B73: 定時間合計 | C73: =SUM(C68:C72) -> 2074 | D73: =IF(ISBLANK(D4),"",SUM(D68:D72)) -> 1928.75 | E73: =IF(ISBLANK(E4),"",SUM(E68:E72)) -> 2138.75 | F73: =IF(ISBLANK(F4),"",SUM(F68:F72)) -> 2392.25 | G73: =IF(ISBLANK(G4),"",SUM(G68:G72)) -> 2074.25 | H73: =IF(ISBLANK(H4),"",SUM(H68:H72)) -> 1965.25 | I73: =IF(ISBLANK(I4),"",SUM(I68:I72)) -> 2350.5 | J73: =IF(ISBLANK(J4),"",SUM(J68:J72)) -> 2044 | K73: =IF(ISBLANK(K4),"",SUM(K68:K72)) -> 2254.75 | ... O73: =IF(ISBLANK(O4),"",SUM(O68:O72)) -> 24828.5
B74: 直接部門 | C74: ='採算表(VND)'!C74 -> 168 | D74: ='採算表(VND)'!D74 -> 164 | E74: ='採算表(VND)'!E74 -> 172 | F74: ='採算表(VND)'!F74 -> 180 | G74: ='採算表(VND)'!G74 -> 178 | H74: ='採算表(VND)'!H74 -> 174 | I74: ='採算表(VND)'!I74 -> 190 | J74: ='採算表(VND)'!J74 -> 180 | ... N74: ='採算表(VND)'!N74 -> 180 | O74: =SUM(C74:N74) -> 2114
B75: 部内間接部門 | C75: ='採算表(VND)'!C75 -> 0 | D75: ='採算表(VND)'!D75 -> 0 | E75: ='採算表(VND)'!E75 -> 0 | F75: ='採算表(VND)'!F75 -> 0 | G75: ='採算表(VND)'!G75 -> 0 | H75: ='採算表(VND)'!H75 -> 0 | I75: ='採算表(VND)'!I75 -> 0 | J75: ='採算表(VND)'!J75 -> 0 | ... N75: ='採算表(VND)'!N75 -> 0 | O75: =SUM(C75:N75) -> 0
B76: 部外間接部門1 | C76: ='採算表(VND)'!C76 -> 0.5 | D76: ='採算表(VND)'!D76 -> 0.5 | E76: ='採算表(VND)'!E76 -> 0.5 | F76: ='採算表(VND)'!F76 -> 0.75 | G76: ='採算表(VND)'!G76 -> 0.75 | H76: ='採算表(VND)'!H76 -> 0.75 | I76: ='採算表(VND)'!I76 -> 0.5 | J76: ='採算表(VND)'!J76 -> 0.5 | ... N76: ='採算表(VND)'!N76 -> 0.5 | O76: =SUM(C76:N76) -> 6.5
B77: 部外間接部門2 | C77: ='採算表(VND)'!C77 -> 1.25 | D77: ='採算表(VND)'!D77 -> 1 | E77: ='採算表(VND)'!E77 -> 1.25 | F77: ='採算表(VND)'!F77 -> 2 | G77: ='採算表(VND)'!G77 -> 1.25 | H77: ='採算表(VND)'!H77 -> 1.25 | I77: ='採算表(VND)'!I77 -> 1.25 | J77: ='採算表(VND)'!J77 -> 1.25 | ... N77: ='採算表(VND)'!N77 -> 1.5 | O77: =SUM(C77:N77) -> 15.25
B78: 工場間接部門 | C78: ='採算表(VND)'!C78 -> 3.25 | D78: ='採算表(VND)'!D78 -> 3.25 | E78: ='採算表(VND)'!E78 -> 2.75 | F78: ='採算表(VND)'!F78 -> 4.5 | G78: ='採算表(VND)'!G78 -> 3.25 | H78: ='採算表(VND)'!H78 -> 5 | I78: ='採算表(VND)'!I78 -> 3 | J78: ='採算表(VND)'!J78 -> 3 | ... N78: ='採算表(VND)'!N78 -> 2.75 | O78: =SUM(C78:N78) -> 40.25
B79: 残業時間合計 | C79: =SUM(C74:C78) -> 173 | D79: =IF(ISBLANK(D4),"",SUM(D74:D78)) -> 168.75 | E79: =IF(ISBLANK(E4),"",SUM(E74:E78)) -> 176.5 | F79: =IF(ISBLANK(F4),"",SUM(F74:F78)) -> 187.25 | G79: =IF(ISBLANK(G4),"",SUM(G74:G78)) -> 183.25 | H79: =IF(ISBLANK(H4),"",SUM(H74:H78)) -> 181 | I79: =IF(ISBLANK(I4),"",SUM(I74:I78)) -> 194.75 | J79: =IF(ISBLANK(J4),"",SUM(J74:J78)) -> 184.75 | K79: =IF(ISBLANK(K4),"",SUM(K74:K78)) -> 192.75 | ... O79: =IF(ISBLANK(O4),"",SUM(O74:O78)) -> 2176
B80: 当月時間当り | C80: =IFERROR(ROUNDDOWN(C66/C67,0),0) -> 6 | D80: =IFERROR(ROUNDDOWN(D66/D67,0),0) -> 12 | E80: =IFERROR(ROUNDDOWN(E66/E67,0),0) -> 10 | F80: =IFERROR(ROUNDDOWN(F66/F67,0),0) -> 9 | G80: =IFERROR(ROUNDDOWN(G66/G67,0),0) -> 11 | H80: =IFERROR(ROUNDDOWN(H66/H67,0),0) -> 6 | I80: =IFERROR(ROUNDDOWN(I66/I67,0),0) -> 15 | J80: =IFERROR(ROUNDDOWN(J66/J67,0),0) -> 12 | ... O80: =IFERROR(ROUNDDOWN(O66/O67,0),0) -> 11
B81: 時間当り生産高 | C81: =IFERROR(ROUNDDOWN(C12/C67,0),0) -> 13 | D81: =IFERROR(ROUNDDOWN(D12/D67,0),0) -> 20 | E81: =IFERROR(ROUNDDOWN(E12/E67,0),0) -> 17 | F81: =IFERROR(ROUNDDOWN(F12/F67,0),0) -> 16 | G81: =IFERROR(ROUNDDOWN(G12/G67,0),0) -> 20 | H81: =IFERROR(ROUNDDOWN(H12/H67,0),0) -> 21 | I81: =IFERROR(ROUNDDOWN(I12/I67,0),0) -> 22 | J81: =IFERROR(ROUNDDOWN(J12/J67,0),0) -> 20 | ... O81: =IFERROR(ROUNDDOWN(O12/O67,0),0) -> 19
B86: ■人員
B87: 出向社員(人) | C87: ='採算表(VND)'!C87 -> 1 | D87: ='採算表(VND)'!D87 -> 1 | E87: ='採算表(VND)'!E87 -> 1 | F87: ='採算表(VND)'!F87 -> 1 | G87: ='採算表(VND)'!G87 -> 1 | H87: ='採算表(VND)'!H87 -> 1 | I87: ='採算表(VND)'!I87 -> 1 | J87: ='採算表(VND)'!J87 -> 1 | ... N87: ='採算表(VND)'!N87 -> 1 | O87: =SUM(C87:N87) -> 12
B88: ローカル社員(人) | C88: ='採算表(VND)'!C88 -> 11 | D88: ='採算表(VND)'!D88 -> 11 | E88: ='採算表(VND)'!E88 -> 11 | F88: ='採算表(VND)'!F88 -> 11 | G88: ='採算表(VND)'!G88 -> 11 | H88: ='採算表(VND)'!H88 -> 11 | I88: ='採算表(VND)'!I88 -> 11 | J88: ='採算表(VND)'!J88 -> 11 | ... N88: ='採算表(VND)'!N88 -> 11 | O88: =SUM(C88:N88) -> 132
B89: 人員計 | C89: =C87+C88 -> 12 | D89: =D87+D88 -> 12 | E89: =E87+E88 -> 12 | F89: =F87+F88 -> 12 | G89: =G87+G88 -> 12 | H89: =H87+H88 -> 12 | I89: =I87+I88 -> 12 | J89: =J87+J88 -> 12 | ... O89: =O87+O88 -> 144
B91: ■定時間
B92: 出向社員定時 | C92: ='採算表(VND)'!C92 -> 161.5 | D92: ='採算表(VND)'!D92 -> 153 | E92: ='採算表(VND)'!E92 -> 170 | F92: ='採算表(VND)'!F92 -> 187 | G92: ='採算表(VND)'!G92 -> 161.5 | H92: ='採算表(VND)'!H92 -> 153 | I92: ='採算表(VND)'!I92 -> 187 | J92: ='採算表(VND)'!J92 -> 170 | ... N92: ='採算表(VND)'!N92 -> 170 | O92: =SUM(C92:N92) -> 1997.5
B93: ローカル社員定時 | C93: ='採算表(VND)'!C93 -> 1836 | D93: ='採算表(VND)'!D93 -> 1700 | E93: ='採算表(VND)'!E93 -> 1887 | F93: ='採算表(VND)'!F93 -> 2074 | G93: ='採算表(VND)'!G93 -> 1793.5 | H93: ='採算表(VND)'!H93 -> 1700 | I93: ='採算表(VND)'!I93 -> 2074 | J93: ='採算表(VND)'!J93 -> 1793.5 | ... N93: ='採算表(VND)'!N93 -> 1793.5 | O93: =SUM(C93:N93) -> 21751.5
B94: 人員計 | C94: =C92+C93 -> 1997.5 | D94: =D92+D93 -> 1853 | E94: =E92+E93 -> 2057 | F94: =F92+F93 -> 2261 | G94: =G92+G93 -> 1955 | H94: =H92+H93 -> 1853 | I94: =I92+I93 -> 2261 | J94: =J92+J93 -> 1963.5 | ... O94: =O92+O93 -> 23749
B96: ■残業時間
B97: 出向社員残業 | C97: ='採算表(VND)'!C97 -> 38 | D97: ='採算表(VND)'!D97 -> 36 | E97: ='採算表(VND)'!E97 -> 40 | F97: ='採算表(VND)'!F97 -> 44 | G97: ='採算表(VND)'!G97 -> 38 | H97: ='採算表(VND)'!H97 -> 36 | I97: ='採算表(VND)'!I97 -> 44 | J97: ='採算表(VND)'!J97 -> 40 | ... N97: ='採算表(VND)'!N97 -> 40 | O97: =SUM(C97:N97) -> 470
B98: ローカル社員残業 | C98: ='採算表(VND)'!C98 -> 130 | D98: ='採算表(VND)'!D98 -> 128 | E98: ='採算表(VND)'!E98 -> 132 | F98: ='採算表(VND)'!F98 -> 136 | G98: ='採算表(VND)'!G98 -> 140 | H98: ='採算表(VND)'!H98 -> 138 | I98: ='採算表(VND)'!I98 -> 146 | J98: ='採算表(VND)'!J98 -> 140 | ... N98: ='採算表(VND)'!N98 -> 140 | O98: =SUM(C98:N98) -> 1644
B99: 人員計 | C99: =C97+C98 -> 168 | D99: =D97+D98 -> 164 | E99: =E97+E98 -> 172 | F99: =F97+F98 -> 180 | G99: =G97+G98 -> 178 | H99: =H97+H98 -> 174 | I99: =I97+I98 -> 190 | J99: =J97+J98 -> 180 | ... O99: =O97+O98 -> 2114

Sheet 採算表(VND)
B1: 組織名 | C1: ='内訳ﾘｽﾄ(4～3月)'!A1 -> MP FY2026_各予定
B2: ='内訳ﾘｽﾄ(4～3月)'!C5 -> MD3課
C3: 2 | D3: 3 | E3: 4 | F3: 5 | G3: 6 | H3: 7 | I3: 8 | J3: 9 | K3: 10 | L3: 11 | M3: 12 | N3: 13
B4: 項目 ＼ 部門 | C4: ='内訳ﾘｽﾄ(4～3月)'!F4 -> 4 | D4: 5 | E4: 6 | F4: 7 | G4: 8 | H4: 9 | I4: 10 | J4: 11 | K4: 12 | L4: 1 | M4: 2 | N4: 3 | O4: 合計
B5: 総出荷 | C5: =C8+C9 -> 756707565 | D5: =D8+D9 -> 1105818795 | E5: =E8+E9 -> 1026239934 | F5: =F8+F9 -> 1060968122 | G5: =G8+G9 -> 1149473853 | H5: =H8+H9 -> 1153673106 | I5: =I8+I9 -> 1453732633 | J5: =J8+J9 -> 1171044436 | ... O5: =O8+O9 -> 13445432939
B6: 社外出荷 | C6: =SUMIF('内訳ﾘｽﾄ(4～3月)'!$D$26:$D$595,'採算表(VND)'!$B6,'内訳ﾘｽﾄ(4～3月)'!F$26:F$595) -> 756707565 | D6: =SUMIF('内訳ﾘｽﾄ(4～3月)'!$D$26:$D$595,'採算表(VND)'!$B6,'内訳ﾘｽﾄ(4～3月)'!G$26:G$595) -> 1105818795 | E6: =SUMIF('内訳ﾘｽﾄ(4～3月)'!$D$26:$D$595,'採算表(VND)'!$B6,'内訳ﾘｽﾄ(4～3月)'!H$26:H$595) -> 1026239934 | F6: =SUMIF('内訳ﾘｽﾄ(4～3月)'!$D$26:$D$595,'採算表(VND)'!$B6,'内訳ﾘｽﾄ(4～3月)'!I$26:I$595) -> 1060968122 | G6: =SUMIF('内訳ﾘｽﾄ(4～3月)'!$D$26:$D$595,'採算表(VND)'!$B6,'内訳ﾘｽﾄ(4～3月)'!J$26:J$595) -> 1149473853 | H6: =SUMIF('内訳ﾘｽﾄ(4～3月)'!$D$26:$D$595,'採算表(VND)'!$B6,'内訳ﾘｽﾄ(4～3月)'!K$26:K$595) -> 1153673106 | I6: =SUMIF('内訳ﾘｽﾄ(4～3月)'!$D$26:$D$595,'採算表(VND)'!$B6,'内訳ﾘｽﾄ(4～3月)'!L$26:L$595) -> 1453732633 | J6: =SUMIF('内訳ﾘｽﾄ(4～3月)'!$D$26:$D$595,'採算表(VND)'!$B6,'内訳ﾘｽﾄ(4～3月)'!M$26:M$595) -> 1171044436 | ... N6: =SUMIF('内訳ﾘｽﾄ(4～3月)'!$D$26:$D$595,'採算表(VND)'!$B6,'内訳ﾘｽﾄ(4～3月)'!Q$26:Q$595) -> 1129609479 | O6: =SUMIF('内訳ﾘｽﾄ(4～3月)'!$D$26:$D$394,'採算表(VND)'!$B6,'内訳ﾘｽﾄ(4～3月)'!R$26:R$394) -> 13445432939
B7: 販売支援 | C7: =SUMIF('内訳ﾘｽﾄ(4～3月)'!$D$26:$D$595,'採算表(VND)'!$B7,'内訳ﾘｽﾄ(4～3月)'!F$26:F$595) -> 0 | D7: =SUMIF('内訳ﾘｽﾄ(4～3月)'!$D$26:$D$595,'採算表(VND)'!$B7,'内訳ﾘｽﾄ(4～3月)'!G$26:G$595) -> 0 | E7: =SUMIF('内訳ﾘｽﾄ(4～3月)'!$D$26:$D$595,'採算表(VND)'!$B7,'内訳ﾘｽﾄ(4～3月)'!H$26:H$595) -> 0 | F7: =SUMIF('内訳ﾘｽﾄ(4～3月)'!$D$26:$D$595,'採算表(VND)'!$B7,'内訳ﾘｽﾄ(4～3月)'!I$26:I$595) -> 0 | G7: =SUMIF('内訳ﾘｽﾄ(4～3月)'!$D$26:$D$595,'採算表(VND)'!$B7,'内訳ﾘｽﾄ(4～3月)'!J$26:J$595) -> 0 | H7: =SUMIF('内訳ﾘｽﾄ(4～3月)'!$D$26:$D$595,'採算表(VND)'!$B7,'内訳ﾘｽﾄ(4～3月)'!K$26:K$595) -> 0 | I7: =SUMIF('内訳ﾘｽﾄ(4～3月)'!$D$26:$D$595,'採算表(VND)'!$B7,'内訳ﾘｽﾄ(4～3月)'!L$26:L$595) -> 0 | J7: =SUMIF('内訳ﾘｽﾄ(4～3月)'!$D$26:$D$595,'採算表(VND)'!$B7,'内訳ﾘｽﾄ(4～3月)'!M$26:M$595) -> 0 | ... N7: =SUMIF('内訳ﾘｽﾄ(4～3月)'!$D$26:$D$595,'採算表(VND)'!$B7,'内訳ﾘｽﾄ(4～3月)'!Q$26:Q$595) -> 0 | O7: =SUMIF('内訳ﾘｽﾄ(4～3月)'!$D$26:$D$394,'採算表(VND)'!$B7,'内訳ﾘｽﾄ(4～3月)'!R$26:R$394) -> 0
B8: 社外出荷合計 | C8: =C6+C7 -> 756707565 | D8: =D6+D7 -> 1105818795 | E8: =E6+E7 -> 1026239934 | F8: =F6+F7 -> 1060968122 | G8: =G6+G7 -> 1149473853 | H8: =H6+H7 -> 1153673106 | I8: =I6+I7 -> 1453732633 | J8: =J6+J7 -> 1171044436 | ... O8: =O6+O7 -> 13445432939
B9: 社内売 | C9: =SUMIF('内訳ﾘｽﾄ(4～3月)'!$D$26:$D$595,'採算表(VND)'!$B9,'内訳ﾘｽﾄ(4～3月)'!F$26:F$595) -> 0 | D9: =SUMIF('内訳ﾘｽﾄ(4～3月)'!$D$26:$D$595,'採算表(VND)'!$B9,'内訳ﾘｽﾄ(4～3月)'!G$26:G$595) -> 0 | E9: =SUMIF('内訳ﾘｽﾄ(4～3月)'!$D$26:$D$595,'採算表(VND)'!$B9,'内訳ﾘｽﾄ(4～3月)'!H$26:H$595) -> 0 | F9: =SUMIF('内訳ﾘｽﾄ(4～3月)'!$D$26:$D$595,'採算表(VND)'!$B9,'内訳ﾘｽﾄ(4～3月)'!I$26:I$595) -> 0 | G9: =SUMIF('内訳ﾘｽﾄ(4～3月)'!$D$26:$D$595,'採算表(VND)'!$B9,'内訳ﾘｽﾄ(4～3月)'!J$26:J$595) -> 0 | H9: =SUMIF('内訳ﾘｽﾄ(4～3月)'!$D$26:$D$595,'採算表(VND)'!$B9,'内訳ﾘｽﾄ(4～3月)'!K$26:K$595) -> 0 | I9: =SUMIF('内訳ﾘｽﾄ(4～3月)'!$D$26:$D$595,'採算表(VND)'!$B9,'内訳ﾘｽﾄ(4～3月)'!L$26:L$595) -> 0 | J9: =SUMIF('内訳ﾘｽﾄ(4～3月)'!$D$26:$D$595,'採算表(VND)'!$B9,'内訳ﾘｽﾄ(4～3月)'!M$26:M$595) -> 0 | ... N9: =SUMIF('内訳ﾘｽﾄ(4～3月)'!$D$26:$D$595,'採算表(VND)'!$B9,'内訳ﾘｽﾄ(4～3月)'!Q$26:Q$595) -> 0 | O9: =SUMIF('内訳ﾘｽﾄ(4～3月)'!$D$26:$D$394,'採算表(VND)'!$B9,'内訳ﾘｽﾄ(4～3月)'!R$26:R$394) -> 0
B10: 社内買 | C10: =SUMIF('内訳ﾘｽﾄ(4～3月)'!$D$26:$D$595,'採算表(VND)'!$B10,'内訳ﾘｽﾄ(4～3月)'!F$26:F$595) -> 0 | D10: =SUMIF('内訳ﾘｽﾄ(4～3月)'!$D$26:$D$595,'採算表(VND)'!$B10,'内訳ﾘｽﾄ(4～3月)'!G$26:G$595) -> 0 | E10: =SUMIF('内訳ﾘｽﾄ(4～3月)'!$D$26:$D$595,'採算表(VND)'!$B10,'内訳ﾘｽﾄ(4～3月)'!H$26:H$595) -> 0 | F10: =SUMIF('内訳ﾘｽﾄ(4～3月)'!$D$26:$D$595,'採算表(VND)'!$B10,'内訳ﾘｽﾄ(4～3月)'!I$26:I$595) -> 0 | G10: =SUMIF('内訳ﾘｽﾄ(4～3月)'!$D$26:$D$595,'採算表(VND)'!$B10,'内訳ﾘｽﾄ(4～3月)'!J$26:J$595) -> 0 | H10: =SUMIF('内訳ﾘｽﾄ(4～3月)'!$D$26:$D$595,'採算表(VND)'!$B10,'内訳ﾘｽﾄ(4～3月)'!K$26:K$595) -> 0 | I10: =SUMIF('内訳ﾘｽﾄ(4～3月)'!$D$26:$D$595,'採算表(VND)'!$B10,'内訳ﾘｽﾄ(4～3月)'!L$26:L$595) -> 0 | J10: =SUMIF('内訳ﾘｽﾄ(4～3月)'!$D$26:$D$595,'採算表(VND)'!$B10,'内訳ﾘｽﾄ(4～3月)'!M$26:M$595) -> 0 | ... N10: =SUMIF('内訳ﾘｽﾄ(4～3月)'!$D$26:$D$595,'採算表(VND)'!$B10,'内訳ﾘｽﾄ(4～3月)'!Q$26:Q$595) -> 0 | O10: =SUMIF('内訳ﾘｽﾄ(4～3月)'!$D$26:$D$394,'採算表(VND)'!$B10,'内訳ﾘｽﾄ(4～3月)'!R$26:R$394) -> 0
B12: 総生産 | C12: =C5-C10 -> 756707565 | D12: =D5-D10 -> 1105818795 | E12: =E5-E10 -> 1026239934 | F12: =F5-F10 -> 1060968122 | G12: =G5-G10 -> 1149473853 | H12: =H5-H10 -> 1153673106 | I12: =I5-I10 -> 1453732633 | J12: =J5-J10 -> 1171044436 | ... O12: =O5-O10 -> 13445432939
B13: 控除額 | C13: =SUM(C14:C65) -> 400823203 | D13: =SUM(D14:D65) -> 454583044 | E13: =SUM(E14:E65) -> 415944472 | F13: =SUM(F14:F65) -> 464714882 | G13: =SUM(G14:G65) -> 462266346 | H13: =SUM(H14:H65) -> 779341928 | I13: =SUM(I14:I65) -> 471136190 | J13: =SUM(J14:J65) -> 447100639 | ... O13: =SUM(O14:O65) -> 5692691901
B14: 材料費 | C14: =SUMIF('内訳ﾘｽﾄ(4～3月)'!$D$26:$D$595,$B14,'内訳ﾘｽﾄ(4～3月)'!F$26:F$595) -> 0 | D14: =SUMIF('内訳ﾘｽﾄ(4～3月)'!$D$26:$D$595,$B14,'内訳ﾘｽﾄ(4～3月)'!G$26:G$595) -> 0 | E14: =SUMIF('内訳ﾘｽﾄ(4～3月)'!$D$26:$D$595,$B14,'内訳ﾘｽﾄ(4～3月)'!H$26:H$595) -> 0 | F14: =SUMIF('内訳ﾘｽﾄ(4～3月)'!$D$26:$D$595,$B14,'内訳ﾘｽﾄ(4～3月)'!I$26:I$595) -> 0 | G14: =SUMIF('内訳ﾘｽﾄ(4～3月)'!$D$26:$D$595,$B14,'内訳ﾘｽﾄ(4～3月)'!J$26:J$595) -> 0 | H14: =SUMIF('内訳ﾘｽﾄ(4～3月)'!$D$26:$D$595,$B14,'内訳ﾘｽﾄ(4～3月)'!K$26:K$595) -> 0 | I14: =SUMIF('内訳ﾘｽﾄ(4～3月)'!$D$26:$D$595,$B14,'内訳ﾘｽﾄ(4～3月)'!L$26:L$595) -> 0 | J14: =SUMIF('内訳ﾘｽﾄ(4～3月)'!$D$26:$D$595,$B14,'内訳ﾘｽﾄ(4～3月)'!M$26:M$595) -> 0 | ... N14: =SUMIF('内訳ﾘｽﾄ(4～3月)'!$D$26:$D$595,$B14,'内訳ﾘｽﾄ(4～3月)'!Q$26:Q$595) -> 0 | O14: =SUMIF('内訳ﾘｽﾄ(4～3月)'!$D$26:$D$394,'採算表(VND)'!$B14,'内訳ﾘｽﾄ(4～3月)'!R$26:R$394) -> 0
B15: 設計変更材料費 | C15: =SUMIF('内訳ﾘｽﾄ(4～3月)'!$D$26:$D$595,$B15,'内訳ﾘｽﾄ(4～3月)'!F$26:F$595) -> 0 | D15: =SUMIF('内訳ﾘｽﾄ(4～3月)'!$D$26:$D$595,$B15,'内訳ﾘｽﾄ(4～3月)'!G$26:G$595) -> 0 | E15: =SUMIF('内訳ﾘｽﾄ(4～3月)'!$D$26:$D$595,$B15,'内訳ﾘｽﾄ(4～3月)'!H$26:H$595) -> 0 | F15: =SUMIF('内訳ﾘｽﾄ(4～3月)'!$D$26:$D$595,$B15,'内訳ﾘｽﾄ(4～3月)'!I$26:I$595) -> 0 | G15: =SUMIF('内訳ﾘｽﾄ(4～3月)'!$D$26:$D$595,$B15,'内訳ﾘｽﾄ(4～3月)'!J$26:J$595) -> 0 | H15: =SUMIF('内訳ﾘｽﾄ(4～3月)'!$D$26:$D$595,$B15,'内訳ﾘｽﾄ(4～3月)'!K$26:K$595) -> 0 | I15: =SUMIF('内訳ﾘｽﾄ(4～3月)'!$D$26:$D$595,$B15,'内訳ﾘｽﾄ(4～3月)'!L$26:L$595) -> 0 | J15: =SUMIF('内訳ﾘｽﾄ(4～3月)'!$D$26:$D$595,$B15,'内訳ﾘｽﾄ(4～3月)'!M$26:M$595) -> 0 | ... N15: =SUMIF('内訳ﾘｽﾄ(4～3月)'!$D$26:$D$595,$B15,'内訳ﾘｽﾄ(4～3月)'!Q$26:Q$595) -> 0 | O15: =SUMIF('内訳ﾘｽﾄ(4～3月)'!$D$26:$D$394,'採算表(VND)'!$B15,'内訳ﾘｽﾄ(4～3月)'!R$26:R$394) -> 0
B16: 仕掛仕損 | C16: =SUMIF('内訳ﾘｽﾄ(4～3月)'!$D$26:$D$595,$B16,'内訳ﾘｽﾄ(4～3月)'!F$26:F$595) -> 0 | D16: =SUMIF('内訳ﾘｽﾄ(4～3月)'!$D$26:$D$595,$B16,'内訳ﾘｽﾄ(4～3月)'!G$26:G$595) -> 0 | E16: =SUMIF('内訳ﾘｽﾄ(4～3月)'!$D$26:$D$595,$B16,'内訳ﾘｽﾄ(4～3月)'!H$26:H$595) -> 0 | F16: =SUMIF('内訳ﾘｽﾄ(4～3月)'!$D$26:$D$595,$B16,'内訳ﾘｽﾄ(4～3月)'!I$26:I$595) -> 0 | G16: =SUMIF('内訳ﾘｽﾄ(4～3月)'!$D$26:$D$595,$B16,'内訳ﾘｽﾄ(4～3月)'!J$26:J$595) -> 0 | H16: =SUMIF('内訳ﾘｽﾄ(4～3月)'!$D$26:$D$595,$B16,'内訳ﾘｽﾄ(4～3月)'!K$26:K$595) -> 0 | I16: =SUMIF('内訳ﾘｽﾄ(4～3月)'!$D$26:$D$595,$B16,'内訳ﾘｽﾄ(4～3月)'!L$26:L$595) -> 0 | J16: =SUMIF('内訳ﾘｽﾄ(4～3月)'!$D$26:$D$595,$B16,'内訳ﾘｽﾄ(4～3月)'!M$26:M$595) -> 0 | ... N16: =SUMIF('内訳ﾘｽﾄ(4～3月)'!$D$26:$D$595,$B16,'内訳ﾘｽﾄ(4～3月)'!Q$26:Q$595) -> 0 | O16: =SUMIF('内訳ﾘｽﾄ(4～3月)'!$D$26:$D$394,'採算表(VND)'!$B16,'内訳ﾘｽﾄ(4～3月)'!R$26:R$394) -> 0
B17: 仕入製商品費 | C17: =SUMIF('内訳ﾘｽﾄ(4～3月)'!$D$26:$D$595,$B17,'内訳ﾘｽﾄ(4～3月)'!F$26:F$595) -> 0 | D17: =SUMIF('内訳ﾘｽﾄ(4～3月)'!$D$26:$D$595,$B17,'内訳ﾘｽﾄ(4～3月)'!G$26:G$595) -> 0 | E17: =SUMIF('内訳ﾘｽﾄ(4～3月)'!$D$26:$D$595,$B17,'内訳ﾘｽﾄ(4～3月)'!H$26:H$595) -> 0 | F17: =SUMIF('内訳ﾘｽﾄ(4～3月)'!$D$26:$D$595,$B17,'内訳ﾘｽﾄ(4～3月)'!I$26:I$595) -> 0 | G17: =SUMIF('内訳ﾘｽﾄ(4～3月)'!$D$26:$D$595,$B17,'内訳ﾘｽﾄ(4～3月)'!J$26:J$595) -> 0 | H17: =SUMIF('内訳ﾘｽﾄ(4～3月)'!$D$26:$D$595,$B17,'内訳ﾘｽﾄ(4～3月)'!K$26:K$595) -> 0 | I17: =SUMIF('内訳ﾘｽﾄ(4～3月)'!$D$26:$D$595,$B17,'内訳ﾘｽﾄ(4～3月)'!L$26:L$595) -> 0 | J17: =SUMIF('内訳ﾘｽﾄ(4～3月)'!$D$26:$D$595,$B17,'内訳ﾘｽﾄ(4～3月)'!M$26:M$595) -> 0 | ... N17: =SUMIF('内訳ﾘｽﾄ(4～3月)'!$D$26:$D$595,$B17,'内訳ﾘｽﾄ(4～3月)'!Q$26:Q$595) -> 0 | O17: =SUMIF('内訳ﾘｽﾄ(4～3月)'!$D$26:$D$394,'採算表(VND)'!$B17,'内訳ﾘｽﾄ(4～3月)'!R$26:R$394) -> 0
B18: 内製品有償支給原価 | C18: =SUMIF('内訳ﾘｽﾄ(4～3月)'!$D$26:$D$595,$B18,'内訳ﾘｽﾄ(4～3月)'!F$26:F$595) -> 0 | D18: =SUMIF('内訳ﾘｽﾄ(4～3月)'!$D$26:$D$595,$B18,'内訳ﾘｽﾄ(4～3月)'!G$26:G$595) -> 0 | E18: =SUMIF('内訳ﾘｽﾄ(4～3月)'!$D$26:$D$595,$B18,'内訳ﾘｽﾄ(4～3月)'!H$26:H$595) -> 0 | F18: =SUMIF('内訳ﾘｽﾄ(4～3月)'!$D$26:$D$595,$B18,'内訳ﾘｽﾄ(4～3月)'!I$26:I$595) -> 0 | G18: =SUMIF('内訳ﾘｽﾄ(4～3月)'!$D$26:$D$595,$B18,'内訳ﾘｽﾄ(4～3月)'!J$26:J$595) -> 0 | H18: =SUMIF('内訳ﾘｽﾄ(4～3月)'!$D$26:$D$595,$B18,'内訳ﾘｽﾄ(4～3月)'!K$26:K$595) -> 0 | I18: =SUMIF('内訳ﾘｽﾄ(4～3月)'!$D$26:$D$595,$B18,'内訳ﾘｽﾄ(4～3月)'!L$26:L$595) -> 0 | J18: =SUMIF('内訳ﾘｽﾄ(4～3月)'!$D$26:$D$595,$B18,'内訳ﾘｽﾄ(4～3月)'!M$26:M$595) -> 0 | ... N18: =SUMIF('内訳ﾘｽﾄ(4～3月)'!$D$26:$D$595,$B18,'内訳ﾘｽﾄ(4～3月)'!Q$26:Q$595) -> 0 | O18: =SUMIF('内訳ﾘｽﾄ(4～3月)'!$D$26:$D$394,'採算表(VND)'!$B18,'内訳ﾘｽﾄ(4～3月)'!R$26:R$394) -> 0
B19: 外注加工費 | C19: =SUMIF('内訳ﾘｽﾄ(4～3月)'!$D$26:$D$595,$B19,'内訳ﾘｽﾄ(4～3月)'!F$26:F$595) -> 0 | D19: =SUMIF('内訳ﾘｽﾄ(4～3月)'!$D$26:$D$595,$B19,'内訳ﾘｽﾄ(4～3月)'!G$26:G$595) -> 0 | E19: =SUMIF('内訳ﾘｽﾄ(4～3月)'!$D$26:$D$595,$B19,'内訳ﾘｽﾄ(4～3月)'!H$26:H$595) -> 0 | F19: =SUMIF('内訳ﾘｽﾄ(4～3月)'!$D$26:$D$595,$B19,'内訳ﾘｽﾄ(4～3月)'!I$26:I$595) -> 0 | G19: =SUMIF('内訳ﾘｽﾄ(4～3月)'!$D$26:$D$595,$B19,'内訳ﾘｽﾄ(4～3月)'!J$26:J$595) -> 0 | H19: =SUMIF('内訳ﾘｽﾄ(4～3月)'!$D$26:$D$595,$B19,'内訳ﾘｽﾄ(4～3月)'!K$26:K$595) -> 0 | I19: =SUMIF('内訳ﾘｽﾄ(4～3月)'!$D$26:$D$595,$B19,'内訳ﾘｽﾄ(4～3月)'!L$26:L$595) -> 0 | J19: =SUMIF('内訳ﾘｽﾄ(4～3月)'!$D$26:$D$595,$B19,'内訳ﾘｽﾄ(4～3月)'!M$26:M$595) -> 0 | ... N19: =SUMIF('内訳ﾘｽﾄ(4～3月)'!$D$26:$D$595,$B19,'内訳ﾘｽﾄ(4～3月)'!Q$26:Q$595) -> 0 | O19: =SUMIF('内訳ﾘｽﾄ(4～3月)'!$D$26:$D$394,'採算表(VND)'!$B19,'内訳ﾘｽﾄ(4～3月)'!R$26:R$394) -> 0
B20: 減価償却費 | C20: =SUMIF('内訳ﾘｽﾄ(4～3月)'!$D$26:$D$595,$B20,'内訳ﾘｽﾄ(4～3月)'!F$26:F$595) -> 275801558 | D20: =SUMIF('内訳ﾘｽﾄ(4～3月)'!$D$26:$D$595,$B20,'内訳ﾘｽﾄ(4～3月)'!G$26:G$595) -> 273939202 | E20: =SUMIF('内訳ﾘｽﾄ(4～3月)'!$D$26:$D$595,$B20,'内訳ﾘｽﾄ(4～3月)'!H$26:H$595) -> 273977541 | F20: =SUMIF('内訳ﾘｽﾄ(4～3月)'!$D$26:$D$595,$B20,'内訳ﾘｽﾄ(4～3月)'!I$26:I$595) -> 304222824 | G20: =SUMIF('内訳ﾘｽﾄ(4～3月)'!$D$26:$D$595,$B20,'内訳ﾘｽﾄ(4～3月)'!J$26:J$595) -> 326621516 | H20: =SUMIF('内訳ﾘｽﾄ(4～3月)'!$D$26:$D$595,$B20,'内訳ﾘｽﾄ(4～3月)'!K$26:K$595) -> 326187855 | I20: =SUMIF('内訳ﾘｽﾄ(4～3月)'!$D$26:$D$595,$B20,'内訳ﾘｽﾄ(4～3月)'!L$26:L$595) -> 326187855 | J20: =SUMIF('内訳ﾘｽﾄ(4～3月)'!$D$26:$D$595,$B20,'内訳ﾘｽﾄ(4～3月)'!M$26:M$595) -> 325819192 | ... N20: =SUMIF('内訳ﾘｽﾄ(4～3月)'!$D$26:$D$595,$B20,'内訳ﾘｽﾄ(4～3月)'!Q$26:Q$595) -> 325765873 | O20: =SUMIF('内訳ﾘｽﾄ(4～3月)'!$D$26:$D$394,'採算表(VND)'!$B20,'内訳ﾘｽﾄ(4～3月)'!R$26:R$394) -> 3736603808
B21: 金型償却費 | C21: =SUMIF('内訳ﾘｽﾄ(4～3月)'!$D$26:$D$595,$B21,'内訳ﾘｽﾄ(4～3月)'!F$26:F$595) -> 0 | D21: =SUMIF('内訳ﾘｽﾄ(4～3月)'!$D$26:$D$595,$B21,'内訳ﾘｽﾄ(4～3月)'!G$26:G$595) -> 0 | E21: =SUMIF('内訳ﾘｽﾄ(4～3月)'!$D$26:$D$595,$B21,'内訳ﾘｽﾄ(4～3月)'!H$26:H$595) -> 0 | F21: =SUMIF('内訳ﾘｽﾄ(4～3月)'!$D$26:$D$595,$B21,'内訳ﾘｽﾄ(4～3月)'!I$26:I$595) -> 0 | G21: =SUMIF('内訳ﾘｽﾄ(4～3月)'!$D$26:$D$595,$B21,'内訳ﾘｽﾄ(4～3月)'!J$26:J$595) -> 0 | H21: =SUMIF('内訳ﾘｽﾄ(4～3月)'!$D$26:$D$595,$B21,'内訳ﾘｽﾄ(4～3月)'!K$26:K$595) -> 0 | I21: =SUMIF('内訳ﾘｽﾄ(4～3月)'!$D$26:$D$595,$B21,'内訳ﾘｽﾄ(4～3月)'!L$26:L$595) -> 0 | J21: =SUMIF('内訳ﾘｽﾄ(4～3月)'!$D$26:$D$595,$B21,'内訳ﾘｽﾄ(4～3月)'!M$26:M$595) -> 0 | ... N21: =SUMIF('内訳ﾘｽﾄ(4～3月)'!$D$26:$D$595,$B21,'内訳ﾘｽﾄ(4～3月)'!Q$26:Q$595) -> 0 | O21: =SUMIF('内訳ﾘｽﾄ(4～3月)'!$D$26:$D$394,'採算表(VND)'!$B21,'内訳ﾘｽﾄ(4～3月)'!R$26:R$394) -> 0
B22: 賃借料 | C22: =SUMIF('内訳ﾘｽﾄ(4～3月)'!$D$26:$D$595,$B22,'内訳ﾘｽﾄ(4～3月)'!F$26:F$595) -> 0 | D22: =SUMIF('内訳ﾘｽﾄ(4～3月)'!$D$26:$D$595,$B22,'内訳ﾘｽﾄ(4～3月)'!G$26:G$595) -> 0 | E22: =SUMIF('内訳ﾘｽﾄ(4～3月)'!$D$26:$D$595,$B22,'内訳ﾘｽﾄ(4～3月)'!H$26:H$595) -> 0 | F22: =SUMIF('内訳ﾘｽﾄ(4～3月)'!$D$26:$D$595,$B22,'内訳ﾘｽﾄ(4～3月)'!I$26:I$595) -> 0 | G22: =SUMIF('内訳ﾘｽﾄ(4～3月)'!$D$26:$D$595,$B22,'内訳ﾘｽﾄ(4～3月)'!J$26:J$595) -> 0 | H22: =SUMIF('内訳ﾘｽﾄ(4～3月)'!$D$26:$D$595,$B22,'内訳ﾘｽﾄ(4～3月)'!K$26:K$595) -> 0 | I22: =SUMIF('内訳ﾘｽﾄ(4～3月)'!$D$26:$D$595,$B22,'内訳ﾘｽﾄ(4～3月)'!L$26:L$595) -> 0 | J22: =SUMIF('内訳ﾘｽﾄ(4～3月)'!$D$26:$D$595,$B22,'内訳ﾘｽﾄ(4～3月)'!M$26:M$595) -> 0 | ... N22: =SUMIF('内訳ﾘｽﾄ(4～3月)'!$D$26:$D$595,$B22,'内訳ﾘｽﾄ(4～3月)'!Q$26:Q$595) -> 0 | O22: =SUMIF('内訳ﾘｽﾄ(4～3月)'!$D$26:$D$394,'採算表(VND)'!$B22,'内訳ﾘｽﾄ(4～3月)'!R$26:R$394) -> 0
B23: 保険料 | C23: =SUMIF('内訳ﾘｽﾄ(4～3月)'!$D$26:$D$595,$B23,'内訳ﾘｽﾄ(4～3月)'!F$26:F$595) -> 0 | D23: =SUMIF('内訳ﾘｽﾄ(4～3月)'!$D$26:$D$595,$B23,'内訳ﾘｽﾄ(4～3月)'!G$26:G$595) -> 0 | E23: =SUMIF('内訳ﾘｽﾄ(4～3月)'!$D$26:$D$595,$B23,'内訳ﾘｽﾄ(4～3月)'!H$26:H$595) -> 0 | F23: =SUMIF('内訳ﾘｽﾄ(4～3月)'!$D$26:$D$595,$B23,'内訳ﾘｽﾄ(4～3月)'!I$26:I$595) -> 0 | G23: =SUMIF('内訳ﾘｽﾄ(4～3月)'!$D$26:$D$595,$B23,'内訳ﾘｽﾄ(4～3月)'!J$26:J$595) -> 0 | H23: =SUMIF('内訳ﾘｽﾄ(4～3月)'!$D$26:$D$595,$B23,'内訳ﾘｽﾄ(4～3月)'!K$26:K$595) -> 0 | I23: =SUMIF('内訳ﾘｽﾄ(4～3月)'!$D$26:$D$595,$B23,'内訳ﾘｽﾄ(4～3月)'!L$26:L$595) -> 0 | J23: =SUMIF('内訳ﾘｽﾄ(4～3月)'!$D$26:$D$595,$B23,'内訳ﾘｽﾄ(4～3月)'!M$26:M$595) -> 0 | ... N23: =SUMIF('内訳ﾘｽﾄ(4～3月)'!$D$26:$D$595,$B23,'内訳ﾘｽﾄ(4～3月)'!Q$26:Q$595) -> 0 | O23: =SUMIF('内訳ﾘｽﾄ(4～3月)'!$D$26:$D$394,'採算表(VND)'!$B23,'内訳ﾘｽﾄ(4～3月)'!R$26:R$394) -> 0
B24: 設計委託費 | C24: =SUMIF('内訳ﾘｽﾄ(4～3月)'!$D$26:$D$595,$B24,'内訳ﾘｽﾄ(4～3月)'!F$26:F$595) -> 0 | D24: =SUMIF('内訳ﾘｽﾄ(4～3月)'!$D$26:$D$595,$B24,'内訳ﾘｽﾄ(4～3月)'!G$26:G$595) -> 0 | E24: =SUMIF('内訳ﾘｽﾄ(4～3月)'!$D$26:$D$595,$B24,'内訳ﾘｽﾄ(4～3月)'!H$26:H$595) -> 0 | F24: =SUMIF('内訳ﾘｽﾄ(4～3月)'!$D$26:$D$595,$B24,'内訳ﾘｽﾄ(4～3月)'!I$26:I$595) -> 0 | G24: =SUMIF('内訳ﾘｽﾄ(4～3月)'!$D$26:$D$595,$B24,'内訳ﾘｽﾄ(4～3月)'!J$26:J$595) -> 0 | H24: =SUMIF('内訳ﾘｽﾄ(4～3月)'!$D$26:$D$595,$B24,'内訳ﾘｽﾄ(4～3月)'!K$26:K$595) -> 0 | I24: =SUMIF('内訳ﾘｽﾄ(4～3月)'!$D$26:$D$595,$B24,'内訳ﾘｽﾄ(4～3月)'!L$26:L$595) -> 0 | J24: =SUMIF('内訳ﾘｽﾄ(4～3月)'!$D$26:$D$595,$B24,'内訳ﾘｽﾄ(4～3月)'!M$26:M$595) -> 0 | ... N24: =SUMIF('内訳ﾘｽﾄ(4～3月)'!$D$26:$D$595,$B24,'内訳ﾘｽﾄ(4～3月)'!Q$26:Q$595) -> 0 | O24: =SUMIF('内訳ﾘｽﾄ(4～3月)'!$D$26:$D$394,'採算表(VND)'!$B24,'内訳ﾘｽﾄ(4～3月)'!R$26:R$394) -> 0
B25: 消耗品費 | C25: =SUMIF('内訳ﾘｽﾄ(4～3月)'!$D$26:$D$595,$B25,'内訳ﾘｽﾄ(4～3月)'!F$26:F$595) -> 841440 | D25: =SUMIF('内訳ﾘｽﾄ(4～3月)'!$D$26:$D$595,$B25,'内訳ﾘｽﾄ(4～3月)'!G$26:G$595) -> 841440 | E25: =SUMIF('内訳ﾘｽﾄ(4～3月)'!$D$26:$D$595,$B25,'内訳ﾘｽﾄ(4～3月)'!H$26:H$595) -> 841440 | F25: =SUMIF('内訳ﾘｽﾄ(4～3月)'!$D$26:$D$595,$B25,'内訳ﾘｽﾄ(4～3月)'!I$26:I$595) -> 841440 | G25: =SUMIF('内訳ﾘｽﾄ(4～3月)'!$D$26:$D$595,$B25,'内訳ﾘｽﾄ(4～3月)'!J$26:J$595) -> 841440 | H25: =SUMIF('内訳ﾘｽﾄ(4～3月)'!$D$26:$D$595,$B25,'内訳ﾘｽﾄ(4～3月)'!K$26:K$595) -> 841440 | I25: =SUMIF('内訳ﾘｽﾄ(4～3月)'!$D$26:$D$595,$B25,'内訳ﾘｽﾄ(4～3月)'!L$26:L$595) -> 841440 | J25: =SUMIF('内訳ﾘｽﾄ(4～3月)'!$D$26:$D$595,$B25,'内訳ﾘｽﾄ(4～3月)'!M$26:M$595) -> 841440 | ... N25: =SUMIF('内訳ﾘｽﾄ(4～3月)'!$D$26:$D$595,$B25,'内訳ﾘｽﾄ(4～3月)'!Q$26:Q$595) -> 841440 | O25: =SUMIF('内訳ﾘｽﾄ(4～3月)'!$D$26:$D$394,'採算表(VND)'!$B25,'内訳ﾘｽﾄ(4～3月)'!R$26:R$394) -> 10097280
... B65: 本社機構経費 | C65: =SUMIF('内訳ﾘｽﾄ(4～3月)'!$D$26:$D$595,$B65,'内訳ﾘｽﾄ(4～3月)'!F$26:F$595) -> 0 | D65: =SUMIF('内訳ﾘｽﾄ(4～3月)'!$D$26:$D$595,$B65,'内訳ﾘｽﾄ(4～3月)'!G$26:G$595) -> 0 | E65: =SUMIF('内訳ﾘｽﾄ(4～3月)'!$D$26:$D$595,$B65,'内訳ﾘｽﾄ(4～3月)'!H$26:H$595) -> 0 | F65: =SUMIF('内訳ﾘｽﾄ(4～3月)'!$D$26:$D$595,$B65,'内訳ﾘｽﾄ(4～3月)'!I$26:I$595) -> 0 | G65: =SUMIF('内訳ﾘｽﾄ(4～3月)'!$D$26:$D$595,$B65,'内訳ﾘｽﾄ(4～3月)'!J$26:J$595) -> 0 | H65: =SUMIF('内訳ﾘｽﾄ(4～3月)'!$D$26:$D$595,$B65,'内訳ﾘｽﾄ(4～3月)'!K$26:K$595) -> 0 | I65: =SUMIF('内訳ﾘｽﾄ(4～3月)'!$D$26:$D$595,$B65,'内訳ﾘｽﾄ(4～3月)'!L$26:L$595) -> 0 | J65: =SUMIF('内訳ﾘｽﾄ(4～3月)'!$D$26:$D$595,$B65,'内訳ﾘｽﾄ(4～3月)'!M$26:M$595) -> 0 | ... N65: =SUMIF('内訳ﾘｽﾄ(4～3月)'!$D$26:$D$595,$B65,'内訳ﾘｽﾄ(4～3月)'!Q$26:Q$595) -> 0 | O65: =SUMIF('内訳ﾘｽﾄ(4～3月)'!$D$26:$D$394,'採算表(VND)'!$B65,'内訳ﾘｽﾄ(4～3月)'!R$26:R$394) -> 0
B66: 差引収益 | C66: =C12-C13 -> 355884362 | D66: =D12-D13 -> 651235751 | E66: =E12-E13 -> 610295462 | F66: =F12-F13 -> 596253240 | G66: =G12-G13 -> 687207507 | H66: =H12-H13 -> 374331178 | I66: =I12-I13 -> 982596443 | J66: =J12-J13 -> 723943797 | ... N66: =N12-N13 -> 690651260 | O66: =IF(ISBLANK(O4),"",O12-O13) -> 7752741038
B67: 総時間 | C67: =C73+C79 -> 2247 | D67: =D73+D79 -> 2097.5 | E67: =E73+E79 -> 2315.25 | F67: =F73+F79 -> 2579.5 | G67: =G73+G79 -> 2257.5 | H67: =H73+H79 -> 2146.25 | I67: =I73+I79 -> 2545.25 | J67: =J73+J79 -> 2228.75 | ... N67: =N73+N79 -> 2230.25 | O67: =IF(ISBLANK(O4),"",O73+O79) -> 27004.5
B68: 直接部門 | C68: =SUMIF('内訳ﾘｽﾄ(4～3月)'!$D$8:$D$15,'採算表(VND)'!$B68,'内訳ﾘｽﾄ(4～3月)'!F$8:F$15) -> 1997.5 | D68: =SUMIF('内訳ﾘｽﾄ(4～3月)'!$D$8:$D$15,'採算表(VND)'!$B68,'内訳ﾘｽﾄ(4～3月)'!G$8:G$15) -> 1853 | E68: =SUMIF('内訳ﾘｽﾄ(4～3月)'!$D$8:$D$15,'採算表(VND)'!$B68,'内訳ﾘｽﾄ(4～3月)'!H$8:H$15) -> 2057 | F68: =SUMIF('内訳ﾘｽﾄ(4～3月)'!$D$8:$D$15,'採算表(VND)'!$B68,'内訳ﾘｽﾄ(4～3月)'!I$8:I$15) -> 2261 | G68: =SUMIF('内訳ﾘｽﾄ(4～3月)'!$D$8:$D$15,'採算表(VND)'!$B68,'内訳ﾘｽﾄ(4～3月)'!J$8:J$15) -> 1955 | H68: =SUMIF('内訳ﾘｽﾄ(4～3月)'!$D$8:$D$15,'採算表(VND)'!$B68,'内訳ﾘｽﾄ(4～3月)'!K$8:K$15) -> 1853 | I68: =SUMIF('内訳ﾘｽﾄ(4～3月)'!$D$8:$D$15,'採算表(VND)'!$B68,'内訳ﾘｽﾄ(4～3月)'!L$8:L$15) -> 2261 | J68: =SUMIF('内訳ﾘｽﾄ(4～3月)'!$D$8:$D$15,'採算表(VND)'!$B68,'内訳ﾘｽﾄ(4～3月)'!M$8:M$15) -> 1963.5 | ... N68: =SUMIF('内訳ﾘｽﾄ(4～3月)'!$D$8:$D$15,'採算表(VND)'!$B68,'内訳ﾘｽﾄ(4～3月)'!Q$8:Q$15) -> 1963.5 | O68: =SUMIF('内訳ﾘｽﾄ(4～3月)'!$D$8:$D$15,'採算表(VND)'!$B68,'内訳ﾘｽﾄ(4～3月)'!$R$8:$R$15) -> 23749
B69: 部内間接部門 | C69: =IF('内訳ﾘｽﾄ(4～3月)'!$D$5="製造",SUMIF('内訳ﾘｽﾄ(4～3月)'!$D$8:$D$15,$B69,'内訳ﾘｽﾄ(4～3月)'!F$8:F$15),IF('内訳ﾘｽﾄ(4～3月)'!$D$5="部内間接",-C$68,0)) -> 0 | D69: =IF('内訳ﾘｽﾄ(4～3月)'!$D$5="製造",SUMIF('内訳ﾘｽﾄ(4～3月)'!$D$8:$D$15,$B69,'内訳ﾘｽﾄ(4～3月)'!G$8:G$15),IF('内訳ﾘｽﾄ(4～3月)'!$D$5="部内間接",-D$68,0)) -> 0 | E69: =IF('内訳ﾘｽﾄ(4～3月)'!$D$5="製造",SUMIF('内訳ﾘｽﾄ(4～3月)'!$D$8:$D$15,$B69,'内訳ﾘｽﾄ(4～3月)'!H$8:H$15),IF('内訳ﾘｽﾄ(4～3月)'!$D$5="部内間接",-E$68,0)) -> 0 | F69: =IF('内訳ﾘｽﾄ(4～3月)'!$D$5="製造",SUMIF('内訳ﾘｽﾄ(4～3月)'!$D$8:$D$15,$B69,'内訳ﾘｽﾄ(4～3月)'!I$8:I$15),IF('内訳ﾘｽﾄ(4～3月)'!$D$5="部内間接",-F$68,0)) -> 0 | G69: =IF('内訳ﾘｽﾄ(4～3月)'!$D$5="製造",SUMIF('内訳ﾘｽﾄ(4～3月)'!$D$8:$D$15,$B69,'内訳ﾘｽﾄ(4～3月)'!J$8:J$15),IF('内訳ﾘｽﾄ(4～3月)'!$D$5="部内間接",-G$68,0)) -> 0 | H69: =IF('内訳ﾘｽﾄ(4～3月)'!$D$5="製造",SUMIF('内訳ﾘｽﾄ(4～3月)'!$D$8:$D$15,$B69,'内訳ﾘｽﾄ(4～3月)'!K$8:K$15),IF('内訳ﾘｽﾄ(4～3月)'!$D$5="部内間接",-H$68,0)) -> 0 | I69: =IF('内訳ﾘｽﾄ(4～3月)'!$D$5="製造",SUMIF('内訳ﾘｽﾄ(4～3月)'!$D$8:$D$15,$B69,'内訳ﾘｽﾄ(4～3月)'!L$8:L$15),IF('内訳ﾘｽﾄ(4～3月)'!$D$5="部内間接",-I$68,0)) -> 0 | J69: =IF('内訳ﾘｽﾄ(4～3月)'!$D$5="製造",SUMIF('内訳ﾘｽﾄ(4～3月)'!$D$8:$D$15,$B69,'内訳ﾘｽﾄ(4～3月)'!M$8:M$15),IF('内訳ﾘｽﾄ(4～3月)'!$D$5="部内間接",-J$68,0)) -> 0 | ... N69: =IF('内訳ﾘｽﾄ(4～3月)'!$D$5="製造",SUMIF('内訳ﾘｽﾄ(4～3月)'!$D$8:$D$15,$B69,'内訳ﾘｽﾄ(4～3月)'!Q$8:Q$15),IF('内訳ﾘｽﾄ(4～3月)'!$D$5="部内間接",-N$68,0)) -> 0 | O69: =IF('内訳ﾘｽﾄ(4～3月)'!$D$5="部内間接",-SUM(O$68),IF('内訳ﾘｽﾄ(4～3月)'!$D$5="製造",SUMIF('内訳ﾘｽﾄ(4～3月)'!$D$8:$D$15,'採算表(VND)'!$B69,'内訳ﾘｽﾄ(4～3月)'!$R$8:$R$15),0)) -> 0
B70: 部外間接部門1 | C70: =IF('内訳ﾘｽﾄ(4～3月)'!$D$5="製造",SUMIF('内訳ﾘｽﾄ(4～3月)'!$D$8:$D$15,$B70,'内訳ﾘｽﾄ(4～3月)'!F$8:F$15),IF('内訳ﾘｽﾄ(4～3月)'!$D$5="部外間接1",-C$68,0)) -> 6.75 | D70: =IF('内訳ﾘｽﾄ(4～3月)'!$D$5="製造",SUMIF('内訳ﾘｽﾄ(4～3月)'!$D$8:$D$15,$B70,'内訳ﾘｽﾄ(4～3月)'!G$8:G$15),IF('内訳ﾘｽﾄ(4～3月)'!$D$5="部外間接1",-D$68,0)) -> 7 | E70: =IF('内訳ﾘｽﾄ(4～3月)'!$D$5="製造",SUMIF('内訳ﾘｽﾄ(4～3月)'!$D$8:$D$15,$B70,'内訳ﾘｽﾄ(4～3月)'!H$8:H$15),IF('内訳ﾘｽﾄ(4～3月)'!$D$5="部外間接1",-E$68,0)) -> 7.75 | F70: =IF('内訳ﾘｽﾄ(4～3月)'!$D$5="製造",SUMIF('内訳ﾘｽﾄ(4～3月)'!$D$8:$D$15,$B70,'内訳ﾘｽﾄ(4～3月)'!I$8:I$15),IF('内訳ﾘｽﾄ(4～3月)'!$D$5="部外間接1",-F$68,0)) -> 12 | G70: =IF('内訳ﾘｽﾄ(4～3月)'!$D$5="製造",SUMIF('内訳ﾘｽﾄ(4～3月)'!$D$8:$D$15,$B70,'内訳ﾘｽﾄ(4～3月)'!J$8:J$15),IF('内訳ﾘｽﾄ(4～3月)'!$D$5="部外間接1",-G$68,0)) -> 10.75 | H70: =IF('内訳ﾘｽﾄ(4～3月)'!$D$5="製造",SUMIF('内訳ﾘｽﾄ(4～3月)'!$D$8:$D$15,$B70,'内訳ﾘｽﾄ(4～3月)'!K$8:K$15),IF('内訳ﾘｽﾄ(4～3月)'!$D$5="部外間接1",-H$68,0)) -> 10 | I70: =IF('内訳ﾘｽﾄ(4～3月)'!$D$5="製造",SUMIF('内訳ﾘｽﾄ(4～3月)'!$D$8:$D$15,$B70,'内訳ﾘｽﾄ(4～3月)'!L$8:L$15),IF('内訳ﾘｽﾄ(4～3月)'!$D$5="部外間接1",-I$68,0)) -> 8.25 | J70: =IF('内訳ﾘｽﾄ(4～3月)'!$D$5="製造",SUMIF('内訳ﾘｽﾄ(4～3月)'!$D$8:$D$15,$B70,'内訳ﾘｽﾄ(4～3月)'!M$8:M$15),IF('内訳ﾘｽﾄ(4～3月)'!$D$5="部外間接1",-J$68,0)) -> 7.25 | ... N70: =IF('内訳ﾘｽﾄ(4～3月)'!$D$5="製造",SUMIF('内訳ﾘｽﾄ(4～3月)'!$D$8:$D$15,$B70,'内訳ﾘｽﾄ(4～3月)'!Q$8:Q$15),IF('内訳ﾘｽﾄ(4～3月)'!$D$5="部外間接1",-N$68,0)) -> 7.5 | O70: =IF('内訳ﾘｽﾄ(4～3月)'!$D$5="部外間接1",-SUM(O$68),IF('内訳ﾘｽﾄ(4～3月)'!$D$5="製造",SUMIF('内訳ﾘｽﾄ(4～3月)'!$D$8:$D$15,'採算表(VND)'!$B70,'内訳ﾘｽﾄ(4～3月)'!$R$8:$R$15),0)) -> 98.25
B71: 部外間接部門2 | C71: =IF('内訳ﾘｽﾄ(4～3月)'!$D$5="製造",SUMIF('内訳ﾘｽﾄ(4～3月)'!$D$8:$D$15,$B71,'内訳ﾘｽﾄ(4～3月)'!F$8:F$15),IF('内訳ﾘｽﾄ(4～3月)'!$D$5="部外間接2",-C$68,0)) -> 12.75 | D71: =IF('内訳ﾘｽﾄ(4～3月)'!$D$5="製造",SUMIF('内訳ﾘｽﾄ(4～3月)'!$D$8:$D$15,$B71,'内訳ﾘｽﾄ(4～3月)'!G$8:G$15),IF('内訳ﾘｽﾄ(4～3月)'!$D$5="部外間接2",-D$68,0)) -> 12.25 | E71: =IF('内訳ﾘｽﾄ(4～3月)'!$D$5="製造",SUMIF('内訳ﾘｽﾄ(4～3月)'!$D$8:$D$15,$B71,'内訳ﾘｽﾄ(4～3月)'!H$8:H$15),IF('内訳ﾘｽﾄ(4～3月)'!$D$5="部外間接2",-E$68,0)) -> 14 | F71: =IF('内訳ﾘｽﾄ(4～3月)'!$D$5="製造",SUMIF('内訳ﾘｽﾄ(4～3月)'!$D$8:$D$15,$B71,'内訳ﾘｽﾄ(4～3月)'!I$8:I$15),IF('内訳ﾘｽﾄ(4～3月)'!$D$5="部外間接2",-F$68,0)) -> 23.25 | G71: =IF('内訳ﾘｽﾄ(4～3月)'!$D$5="製造",SUMIF('内訳ﾘｽﾄ(4～3月)'!$D$8:$D$15,$B71,'内訳ﾘｽﾄ(4～3月)'!J$8:J$15),IF('内訳ﾘｽﾄ(4～3月)'!$D$5="部外間接2",-G$68,0)) -> 20.25 | H71: =IF('内訳ﾘｽﾄ(4～3月)'!$D$5="製造",SUMIF('内訳ﾘｽﾄ(4～3月)'!$D$8:$D$15,$B71,'内訳ﾘｽﾄ(4～3月)'!K$8:K$15),IF('内訳ﾘｽﾄ(4～3月)'!$D$5="部外間接2",-H$68,0)) -> 19.75 | I71: =IF('内訳ﾘｽﾄ(4～3月)'!$D$5="製造",SUMIF('内訳ﾘｽﾄ(4～3月)'!$D$8:$D$15,$B71,'内訳ﾘｽﾄ(4～3月)'!L$8:L$15),IF('内訳ﾘｽﾄ(4～3月)'!$D$5="部外間接2",-I$68,0)) -> 16.25 | J71: =IF('内訳ﾘｽﾄ(4～3月)'!$D$5="製造",SUMIF('内訳ﾘｽﾄ(4～3月)'!$D$8:$D$15,$B71,'内訳ﾘｽﾄ(4～3月)'!M$8:M$15),IF('内訳ﾘｽﾄ(4～3月)'!$D$5="部外間接2",-J$68,0)) -> 14 | ... N71: =IF('内訳ﾘｽﾄ(4～3月)'!$D$5="製造",SUMIF('内訳ﾘｽﾄ(4～3月)'!$D$8:$D$15,$B71,'内訳ﾘｽﾄ(4～3月)'!Q$8:Q$15),IF('内訳ﾘｽﾄ(4～3月)'!$D$5="部外間接2",-N$68,0)) -> 14 | O71: =IF('内訳ﾘｽﾄ(4～3月)'!$D$5="部外間接2",-SUM(O$68),IF('内訳ﾘｽﾄ(4～3月)'!$D$5="製造",SUMIF('内訳ﾘｽﾄ(4～3月)'!$D$8:$D$15,'採算表(VND)'!$B71,'内訳ﾘｽﾄ(4～3月)'!$R$8:$R$15),0)) -> 187
B72: 工場間接部門 | C72: =IF('内訳ﾘｽﾄ(4～3月)'!$D$5="製造",SUMIF('内訳ﾘｽﾄ(4～3月)'!$D$8:$D$15,$B72,'内訳ﾘｽﾄ(4～3月)'!F$8:F$15),IF('内訳ﾘｽﾄ(4～3月)'!$D$5="工場間接",-C$68,0)) -> 57 | D72: =IF('内訳ﾘｽﾄ(4～3月)'!$D$5="製造",SUMIF('内訳ﾘｽﾄ(4～3月)'!$D$8:$D$15,$B72,'内訳ﾘｽﾄ(4～3月)'!G$8:G$15),IF('内訳ﾘｽﾄ(4～3月)'!$D$5="工場間接",-D$68,0)) -> 56.5 | E72: =IF('内訳ﾘｽﾄ(4～3月)'!$D$5="製造",SUMIF('内訳ﾘｽﾄ(4～3月)'!$D$8:$D$15,$B72,'内訳ﾘｽﾄ(4～3月)'!H$8:H$15),IF('内訳ﾘｽﾄ(4～3月)'!$D$5="工場間接",-E$68,0)) -> 60 | F72: =IF('内訳ﾘｽﾄ(4～3月)'!$D$5="製造",SUMIF('内訳ﾘｽﾄ(4～3月)'!$D$8:$D$15,$B72,'内訳ﾘｽﾄ(4～3月)'!I$8:I$15),IF('内訳ﾘｽﾄ(4～3月)'!$D$5="工場間接",-F$68,0)) -> 96 | G72: =IF('内訳ﾘｽﾄ(4～3月)'!$D$5="製造",SUMIF('内訳ﾘｽﾄ(4～3月)'!$D$8:$D$15,$B72,'内訳ﾘｽﾄ(4～3月)'!J$8:J$15),IF('内訳ﾘｽﾄ(4～3月)'!$D$5="工場間接",-G$68,0)) -> 88.25 | H72: =IF('内訳ﾘｽﾄ(4～3月)'!$D$5="製造",SUMIF('内訳ﾘｽﾄ(4～3月)'!$D$8:$D$15,$B72,'内訳ﾘｽﾄ(4～3月)'!K$8:K$15),IF('内訳ﾘｽﾄ(4～3月)'!$D$5="工場間接",-H$68,0)) -> 82.5 | I72: =IF('内訳ﾘｽﾄ(4～3月)'!$D$5="製造",SUMIF('内訳ﾘｽﾄ(4～3月)'!$D$8:$D$15,$B72,'内訳ﾘｽﾄ(4～3月)'!L$8:L$15),IF('内訳ﾘｽﾄ(4～3月)'!$D$5="工場間接",-I$68,0)) -> 65 | J72: =IF('内訳ﾘｽﾄ(4～3月)'!$D$5="製造",SUMIF('内訳ﾘｽﾄ(4～3月)'!$D$8:$D$15,$B72,'内訳ﾘｽﾄ(4～3月)'!M$8:M$15),IF('内訳ﾘｽﾄ(4～3月)'!$D$5="工場間接",-J$68,0)) -> 59.25 | ... N72: =IF('内訳ﾘｽﾄ(4～3月)'!$D$5="製造",SUMIF('内訳ﾘｽﾄ(4～3月)'!$D$8:$D$15,$B72,'内訳ﾘｽﾄ(4～3月)'!Q$8:Q$15),IF('内訳ﾘｽﾄ(4～3月)'!$D$5="工場間接",-N$68,0)) -> 60.5 | O72: =IF('内訳ﾘｽﾄ(4～3月)'!$D$5="工場間接",-SUM(O$68),IF('内訳ﾘｽﾄ(4～3月)'!$D$5="製造",SUMIF('内訳ﾘｽﾄ(4～3月)'!$D$8:$D$15,'採算表(VND)'!$B72,'内訳ﾘｽﾄ(4～3月)'!$R$8:$R$15),0)) -> 794.25
B73: 定時間合計 | C73: =SUM(C68:C72) -> 2074 | D73: =SUM(D68:D72) -> 1928.75 | E73: =SUM(E68:E72) -> 2138.75 | F73: =SUM(F68:F72) -> 2392.25 | G73: =SUM(G68:G72) -> 2074.25 | H73: =SUM(H68:H72) -> 1965.25 | I73: =SUM(I68:I72) -> 2350.5 | J73: =SUM(J68:J72) -> 2044 | ... N73: =SUM(N68:N72) -> 2045.5 | O73: =IF(ISBLANK(O4),"",SUM(O68:O72)) -> 24828.5
B74: 直接部門 | C74: =SUMIF('内訳ﾘｽﾄ(4～3月)'!$D$16:$D$23,'採算表(VND)'!$B74,'内訳ﾘｽﾄ(4～3月)'!F$16:F$23) -> 168 | D74: =SUMIF('内訳ﾘｽﾄ(4～3月)'!$D$16:$D$23,'採算表(VND)'!$B74,'内訳ﾘｽﾄ(4～3月)'!G$16:G$23) -> 164 | E74: =SUMIF('内訳ﾘｽﾄ(4～3月)'!$D$16:$D$23,'採算表(VND)'!$B74,'内訳ﾘｽﾄ(4～3月)'!H$16:H$23) -> 172 | F74: =SUMIF('内訳ﾘｽﾄ(4～3月)'!$D$16:$D$23,'採算表(VND)'!$B74,'内訳ﾘｽﾄ(4～3月)'!I$16:I$23) -> 180 | G74: =SUMIF('内訳ﾘｽﾄ(4～3月)'!$D$16:$D$23,'採算表(VND)'!$B74,'内訳ﾘｽﾄ(4～3月)'!J$16:J$23) -> 178 | H74: =SUMIF('内訳ﾘｽﾄ(4～3月)'!$D$16:$D$23,'採算表(VND)'!$B74,'内訳ﾘｽﾄ(4～3月)'!K$16:K$23) -> 174 | I74: =SUMIF('内訳ﾘｽﾄ(4～3月)'!$D$16:$D$23,'採算表(VND)'!$B74,'内訳ﾘｽﾄ(4～3月)'!L$16:L$23) -> 190 | J74: =SUMIF('内訳ﾘｽﾄ(4～3月)'!$D$16:$D$23,'採算表(VND)'!$B74,'内訳ﾘｽﾄ(4～3月)'!M$16:M$23) -> 180 | ... N74: =SUMIF('内訳ﾘｽﾄ(4～3月)'!$D$16:$D$23,'採算表(VND)'!$B74,'内訳ﾘｽﾄ(4～3月)'!Q$16:Q$23) -> 180 | O74: =SUMIF('内訳ﾘｽﾄ(4～3月)'!$D$16:$D$23,'採算表(VND)'!$B74,'内訳ﾘｽﾄ(4～3月)'!$R$16:$R$23) -> 2114
B75: 部内間接部門 | C75: =IF('内訳ﾘｽﾄ(4～3月)'!$D$5="製造",SUMIF('内訳ﾘｽﾄ(4～3月)'!$D$16:$D$23,$B75,'内訳ﾘｽﾄ(4～3月)'!F$16:F$23),IF('内訳ﾘｽﾄ(4～3月)'!$D$5="部内間接",-C$74,0)) -> 0 | D75: =IF('内訳ﾘｽﾄ(4～3月)'!$D$5="製造",SUMIF('内訳ﾘｽﾄ(4～3月)'!$D$16:$D$23,$B75,'内訳ﾘｽﾄ(4～3月)'!G$16:G$23),IF('内訳ﾘｽﾄ(4～3月)'!$D$5="部内間接",-D$74,0)) -> 0 | E75: =IF('内訳ﾘｽﾄ(4～3月)'!$D$5="製造",SUMIF('内訳ﾘｽﾄ(4～3月)'!$D$16:$D$23,$B75,'内訳ﾘｽﾄ(4～3月)'!H$16:H$23),IF('内訳ﾘｽﾄ(4～3月)'!$D$5="部内間接",-E$74,0)) -> 0 | F75: =IF('内訳ﾘｽﾄ(4～3月)'!$D$5="製造",SUMIF('内訳ﾘｽﾄ(4～3月)'!$D$16:$D$23,$B75,'内訳ﾘｽﾄ(4～3月)'!I$16:I$23),IF('内訳ﾘｽﾄ(4～3月)'!$D$5="部内間接",-F$74,0)) -> 0 | G75: =IF('内訳ﾘｽﾄ(4～3月)'!$D$5="製造",SUMIF('内訳ﾘｽﾄ(4～3月)'!$D$16:$D$23,$B75,'内訳ﾘｽﾄ(4～3月)'!J$16:J$23),IF('内訳ﾘｽﾄ(4～3月)'!$D$5="部内間接",-G$74,0)) -> 0 | H75: =IF('内訳ﾘｽﾄ(4～3月)'!$D$5="製造",SUMIF('内訳ﾘｽﾄ(4～3月)'!$D$16:$D$23,$B75,'内訳ﾘｽﾄ(4～3月)'!K$16:K$23),IF('内訳ﾘｽﾄ(4～3月)'!$D$5="部内間接",-H$74,0)) -> 0 | I75: =IF('内訳ﾘｽﾄ(4～3月)'!$D$5="製造",SUMIF('内訳ﾘｽﾄ(4～3月)'!$D$16:$D$23,$B75,'内訳ﾘｽﾄ(4～3月)'!L$16:L$23),IF('内訳ﾘｽﾄ(4～3月)'!$D$5="部内間接",-I$74,0)) -> 0 | J75: =IF('内訳ﾘｽﾄ(4～3月)'!$D$5="製造",SUMIF('内訳ﾘｽﾄ(4～3月)'!$D$16:$D$23,$B75,'内訳ﾘｽﾄ(4～3月)'!M$16:M$23),IF('内訳ﾘｽﾄ(4～3月)'!$D$5="部内間接",-J$74,0)) -> 0 | ... N75: =IF('内訳ﾘｽﾄ(4～3月)'!$D$5="製造",SUMIF('内訳ﾘｽﾄ(4～3月)'!$D$16:$D$23,$B75,'内訳ﾘｽﾄ(4～3月)'!Q$16:Q$23),IF('内訳ﾘｽﾄ(4～3月)'!$D$5="部内間接",-N$74,0)) -> 0 | O75: =IF('内訳ﾘｽﾄ(4～3月)'!$D$5="部内間接",-SUM(O$74),IF('内訳ﾘｽﾄ(4～3月)'!$D$5="製造",SUMIF('内訳ﾘｽﾄ(4～3月)'!$D$16:$D$23,'採算表(VND)'!$B75,'内訳ﾘｽﾄ(4～3月)'!$R$16:$R$23),0)) -> 0
B76: 部外間接部門1 | C76: =IF('内訳ﾘｽﾄ(4～3月)'!$D$5="製造",SUMIF('内訳ﾘｽﾄ(4～3月)'!$D$16:$D$23,$B76,'内訳ﾘｽﾄ(4～3月)'!F$16:F$23),IF('内訳ﾘｽﾄ(4～3月)'!$D$5="部外間接1",-C$74,0)) -> 0.5 | D76: =IF('内訳ﾘｽﾄ(4～3月)'!$D$5="製造",SUMIF('内訳ﾘｽﾄ(4～3月)'!$D$16:$D$23,$B76,'内訳ﾘｽﾄ(4～3月)'!G$16:G$23),IF('内訳ﾘｽﾄ(4～3月)'!$D$5="部外間接1",-D$74,0)) -> 0.5 | E76: =IF('内訳ﾘｽﾄ(4～3月)'!$D$5="製造",SUMIF('内訳ﾘｽﾄ(4～3月)'!$D$16:$D$23,$B76,'内訳ﾘｽﾄ(4～3月)'!H$16:H$23),IF('内訳ﾘｽﾄ(4～3月)'!$D$5="部外間接1",-E$74,0)) -> 0.5 | F76: =IF('内訳ﾘｽﾄ(4～3月)'!$D$5="製造",SUMIF('内訳ﾘｽﾄ(4～3月)'!$D$16:$D$23,$B76,'内訳ﾘｽﾄ(4～3月)'!I$16:I$23),IF('内訳ﾘｽﾄ(4～3月)'!$D$5="部外間接1",-F$74,0)) -> 0.75 | G76: =IF('内訳ﾘｽﾄ(4～3月)'!$D$5="製造",SUMIF('内訳ﾘｽﾄ(4～3月)'!$D$16:$D$23,$B76,'内訳ﾘｽﾄ(4～3月)'!J$16:J$23),IF('内訳ﾘｽﾄ(4～3月)'!$D$5="部外間接1",-G$74,0)) -> 0.75 | H76: =IF('内訳ﾘｽﾄ(4～3月)'!$D$5="製造",SUMIF('内訳ﾘｽﾄ(4～3月)'!$D$16:$D$23,$B76,'内訳ﾘｽﾄ(4～3月)'!K$16:K$23),IF('内訳ﾘｽﾄ(4～3月)'!$D$5="部外間接1",-H$74,0)) -> 0.75 | I76: =IF('内訳ﾘｽﾄ(4～3月)'!$D$5="製造",SUMIF('内訳ﾘｽﾄ(4～3月)'!$D$16:$D$23,$B76,'内訳ﾘｽﾄ(4～3月)'!L$16:L$23),IF('内訳ﾘｽﾄ(4～3月)'!$D$5="部外間接1",-I$74,0)) -> 0.5 | J76: =IF('内訳ﾘｽﾄ(4～3月)'!$D$5="製造",SUMIF('内訳ﾘｽﾄ(4～3月)'!$D$16:$D$23,$B76,'内訳ﾘｽﾄ(4～3月)'!M$16:M$23),IF('内訳ﾘｽﾄ(4～3月)'!$D$5="部外間接1",-J$74,0)) -> 0.5 | ... N76: =IF('内訳ﾘｽﾄ(4～3月)'!$D$5="製造",SUMIF('内訳ﾘｽﾄ(4～3月)'!$D$16:$D$23,$B76,'内訳ﾘｽﾄ(4～3月)'!Q$16:Q$23),IF('内訳ﾘｽﾄ(4～3月)'!$D$5="部外間接1",-N$74,0)) -> 0.5 | O76: =IF('内訳ﾘｽﾄ(4～3月)'!$D$5="部外間接1",-SUM(O$74),IF('内訳ﾘｽﾄ(4～3月)'!$D$5="製造",SUMIF('内訳ﾘｽﾄ(4～3月)'!$D$16:$D$23,'採算表(VND)'!$B76,'内訳ﾘｽﾄ(4～3月)'!$R$16:$R$23),0)) -> 6.5
B77: 部外間接部門2 | C77: =IF('内訳ﾘｽﾄ(4～3月)'!$D$5="製造",SUMIF('内訳ﾘｽﾄ(4～3月)'!$D$16:$D$23,$B77,'内訳ﾘｽﾄ(4～3月)'!F$16:F$23),IF('内訳ﾘｽﾄ(4～3月)'!$D$5="部外間接2",-C$74,0)) -> 1.25 | D77: =IF('内訳ﾘｽﾄ(4～3月)'!$D$5="製造",SUMIF('内訳ﾘｽﾄ(4～3月)'!$D$16:$D$23,$B77,'内訳ﾘｽﾄ(4～3月)'!G$16:G$23),IF('内訳ﾘｽﾄ(4～3月)'!$D$5="部外間接2",-D$74,0)) -> 1 | E77: =IF('内訳ﾘｽﾄ(4～3月)'!$D$5="製造",SUMIF('内訳ﾘｽﾄ(4～3月)'!$D$16:$D$23,$B77,'内訳ﾘｽﾄ(4～3月)'!H$16:H$23),IF('内訳ﾘｽﾄ(4～3月)'!$D$5="部外間接2",-E$74,0)) -> 1.25 | F77: =IF('内訳ﾘｽﾄ(4～3月)'!$D$5="製造",SUMIF('内訳ﾘｽﾄ(4～3月)'!$D$16:$D$23,$B77,'内訳ﾘｽﾄ(4～3月)'!I$16:I$23),IF('内訳ﾘｽﾄ(4～3月)'!$D$5="部外間接2",-F$74,0)) -> 2 | G77: =IF('内訳ﾘｽﾄ(4～3月)'!$D$5="製造",SUMIF('内訳ﾘｽﾄ(4～3月)'!$D$16:$D$23,$B77,'内訳ﾘｽﾄ(4～3月)'!J$16:J$23),IF('内訳ﾘｽﾄ(4～3月)'!$D$5="部外間接2",-G$74,0)) -> 1.25 | H77: =IF('内訳ﾘｽﾄ(4～3月)'!$D$5="製造",SUMIF('内訳ﾘｽﾄ(4～3月)'!$D$16:$D$23,$B77,'内訳ﾘｽﾄ(4～3月)'!K$16:K$23),IF('内訳ﾘｽﾄ(4～3月)'!$D$5="部外間接2",-H$74,0)) -> 1.25 | I77: =IF('内訳ﾘｽﾄ(4～3月)'!$D$5="製造",SUMIF('内訳ﾘｽﾄ(4～3月)'!$D$16:$D$23,$B77,'内訳ﾘｽﾄ(4～3月)'!L$16:L$23),IF('内訳ﾘｽﾄ(4～3月)'!$D$5="部外間接2",-I$74,0)) -> 1.25 | J77: =IF('内訳ﾘｽﾄ(4～3月)'!$D$5="製造",SUMIF('内訳ﾘｽﾄ(4～3月)'!$D$16:$D$23,$B77,'内訳ﾘｽﾄ(4～3月)'!M$16:M$23),IF('内訳ﾘｽﾄ(4～3月)'!$D$5="部外間接2",-J$74,0)) -> 1.25 | ... N77: =IF('内訳ﾘｽﾄ(4～3月)'!$D$5="製造",SUMIF('内訳ﾘｽﾄ(4～3月)'!$D$16:$D$23,$B77,'内訳ﾘｽﾄ(4～3月)'!Q$16:Q$23),IF('内訳ﾘｽﾄ(4～3月)'!$D$5="部外間接2",-N$74,0)) -> 1.5 | O77: =IF('内訳ﾘｽﾄ(4～3月)'!$D$5="部外間接2",-SUM(O$74),IF('内訳ﾘｽﾄ(4～3月)'!$D$5="製造",SUMIF('内訳ﾘｽﾄ(4～3月)'!$D$16:$D$23,'採算表(VND)'!$B77,'内訳ﾘｽﾄ(4～3月)'!$R$16:$R$23),0)) -> 15.25
B78: 工場間接部門 | C78: =IF('内訳ﾘｽﾄ(4～3月)'!$D$5="製造",SUMIF('内訳ﾘｽﾄ(4～3月)'!$D$16:$D$23,$B78,'内訳ﾘｽﾄ(4～3月)'!F$16:F$23),IF('内訳ﾘｽﾄ(4～3月)'!$D$5="工場間接",-C$74,0)) -> 3.25 | D78: =IF('内訳ﾘｽﾄ(4～3月)'!$D$5="製造",SUMIF('内訳ﾘｽﾄ(4～3月)'!$D$16:$D$23,$B78,'内訳ﾘｽﾄ(4～3月)'!G$16:G$23),IF('内訳ﾘｽﾄ(4～3月)'!$D$5="工場間接",-D$74,0)) -> 3.25 | E78: =IF('内訳ﾘｽﾄ(4～3月)'!$D$5="製造",SUMIF('内訳ﾘｽﾄ(4～3月)'!$D$16:$D$23,$B78,'内訳ﾘｽﾄ(4～3月)'!H$16:H$23),IF('内訳ﾘｽﾄ(4～3月)'!$D$5="工場間接",-E$74,0)) -> 2.75 | F78: =IF('内訳ﾘｽﾄ(4～3月)'!$D$5="製造",SUMIF('内訳ﾘｽﾄ(4～3月)'!$D$16:$D$23,$B78,'内訳ﾘｽﾄ(4～3月)'!I$16:I$23),IF('内訳ﾘｽﾄ(4～3月)'!$D$5="工場間接",-F$74,0)) -> 4.5 | G78: =IF('内訳ﾘｽﾄ(4～3月)'!$D$5="製造",SUMIF('内訳ﾘｽﾄ(4～3月)'!$D$16:$D$23,$B78,'内訳ﾘｽﾄ(4～3月)'!J$16:J$23),IF('内訳ﾘｽﾄ(4～3月)'!$D$5="工場間接",-G$74,0)) -> 3.25 | H78: =IF('内訳ﾘｽﾄ(4～3月)'!$D$5="製造",SUMIF('内訳ﾘｽﾄ(4～3月)'!$D$16:$D$23,$B78,'内訳ﾘｽﾄ(4～3月)'!K$16:K$23),IF('内訳ﾘｽﾄ(4～3月)'!$D$5="工場間接",-H$74,0)) -> 5 | I78: =IF('内訳ﾘｽﾄ(4～3月)'!$D$5="製造",SUMIF('内訳ﾘｽﾄ(4～3月)'!$D$16:$D$23,$B78,'内訳ﾘｽﾄ(4～3月)'!L$16:L$23),IF('内訳ﾘｽﾄ(4～3月)'!$D$5="工場間接",-I$74,0)) -> 3 | J78: =IF('内訳ﾘｽﾄ(4～3月)'!$D$5="製造",SUMIF('内訳ﾘｽﾄ(4～3月)'!$D$16:$D$23,$B78,'内訳ﾘｽﾄ(4～3月)'!M$16:M$23),IF('内訳ﾘｽﾄ(4～3月)'!$D$5="工場間接",-J$74,0)) -> 3 | ... N78: =IF('内訳ﾘｽﾄ(4～3月)'!$D$5="製造",SUMIF('内訳ﾘｽﾄ(4～3月)'!$D$16:$D$23,$B78,'内訳ﾘｽﾄ(4～3月)'!Q$16:Q$23),IF('内訳ﾘｽﾄ(4～3月)'!$D$5="工場間接",-N$74,0)) -> 2.75 | O78: =IF('内訳ﾘｽﾄ(4～3月)'!$D$5="工場間接",-SUM(O$74),IF('内訳ﾘｽﾄ(4～3月)'!$D$5="製造",SUMIF('内訳ﾘｽﾄ(4～3月)'!$D$16:$D$23,'採算表(VND)'!$B78,'内訳ﾘｽﾄ(4～3月)'!$R$16:$R$23),0)) -> 40.25
B79: 残業時間合計 | C79: =SUM(C74:C78) -> 173 | D79: =SUM(D74:D78) -> 168.75 | E79: =SUM(E74:E78) -> 176.5 | F79: =SUM(F74:F78) -> 187.25 | G79: =SUM(G74:G78) -> 183.25 | H79: =SUM(H74:H78) -> 181 | I79: =SUM(I74:I78) -> 194.75 | J79: =SUM(J74:J78) -> 184.75 | ... N79: =SUM(N74:N78) -> 184.75 | O79: =IF(ISBLANK(O10),"",SUM(O74:O78)) -> 2176
B80: 当月時間当り | C80: =IFERROR(ROUNDDOWN(C66/C67,0),0) -> 158382 | D80: =IFERROR(ROUNDDOWN(D66/D67,0),0) -> 310481 | E80: =IFERROR(ROUNDDOWN(E66/E67,0),0) -> 263598 | F80: =IFERROR(ROUNDDOWN(F66/F67,0),0) -> 231150 | G80: =IFERROR(ROUNDDOWN(G66/G67,0),0) -> 304410 | H80: =IFERROR(ROUNDDOWN(H66/H67,0),0) -> 174411 | I80: =IFERROR(ROUNDDOWN(I66/I67,0),0) -> 386051 | J80: =IFERROR(ROUNDDOWN(J66/J67,0),0) -> 324820 | ... O80: =IFERROR(ROUNDDOWN(O66/O67,0),0) -> 287090
B81: 時間当り生産高 | C81: =IFERROR(ROUNDDOWN(C12/C67,0),0) -> 336763 | D81: =IFERROR(ROUNDDOWN(D12/D67,0),0) -> 527208 | E81: =IFERROR(ROUNDDOWN(E12/E67,0),0) -> 443252 | F81: =IFERROR(ROUNDDOWN(F12/F67,0),0) -> 411307 | G81: =IFERROR(ROUNDDOWN(G12/G67,0),0) -> 509180 | H81: =IFERROR(ROUNDDOWN(H12/H67,0),0) -> 537529 | I81: =IFERROR(ROUNDDOWN(I12/I67,0),0) -> 571155 | J81: =IFERROR(ROUNDDOWN(J12/J67,0),0) -> 525426 | ... O81: =IFERROR(ROUNDDOWN(O12/O67,0),0) -> 497896
B86: ■人員
B87: 出向社員(人) | C87: =SUMIF('内訳ﾘｽﾄ(4～3月)'!$D$24:$D$25,'採算表(VND)'!$B87,'内訳ﾘｽﾄ(4～3月)'!F$24:F$25) -> 1 | D87: =SUMIF('内訳ﾘｽﾄ(4～3月)'!$D$24:$D$25,'採算表(VND)'!$B87,'内訳ﾘｽﾄ(4～3月)'!G$24:G$25) -> 1 | E87: =SUMIF('内訳ﾘｽﾄ(4～3月)'!$D$24:$D$25,'採算表(VND)'!$B87,'内訳ﾘｽﾄ(4～3月)'!H$24:H$25) -> 1 | F87: =SUMIF('内訳ﾘｽﾄ(4～3月)'!$D$24:$D$25,'採算表(VND)'!$B87,'内訳ﾘｽﾄ(4～3月)'!I$24:I$25) -> 1 | G87: =SUMIF('内訳ﾘｽﾄ(4～3月)'!$D$24:$D$25,'採算表(VND)'!$B87,'内訳ﾘｽﾄ(4～3月)'!J$24:J$25) -> 1 | H87: =SUMIF('内訳ﾘｽﾄ(4～3月)'!$D$24:$D$25,'採算表(VND)'!$B87,'内訳ﾘｽﾄ(4～3月)'!K$24:K$25) -> 1 | I87: =SUMIF('内訳ﾘｽﾄ(4～3月)'!$D$24:$D$25,'採算表(VND)'!$B87,'内訳ﾘｽﾄ(4～3月)'!L$24:L$25) -> 1 | J87: =SUMIF('内訳ﾘｽﾄ(4～3月)'!$D$24:$D$25,'採算表(VND)'!$B87,'内訳ﾘｽﾄ(4～3月)'!M$24:M$25) -> 1 | ... O87: =SUMIF('内訳ﾘｽﾄ(4～3月)'!$D$24:$D$25,'採算表(VND)'!$B87,'内訳ﾘｽﾄ(4～3月)'!R$24:R$25) -> 1
B88: ローカル社員(人) | C88: =SUMIF('内訳ﾘｽﾄ(4～3月)'!$D$24:$D$25,'採算表(VND)'!$B88,'内訳ﾘｽﾄ(4～3月)'!F$24:F$25) -> 11 | D88: =SUMIF('内訳ﾘｽﾄ(4～3月)'!$D$24:$D$25,'採算表(VND)'!$B88,'内訳ﾘｽﾄ(4～3月)'!G$24:G$25) -> 11 | E88: =SUMIF('内訳ﾘｽﾄ(4～3月)'!$D$24:$D$25,'採算表(VND)'!$B88,'内訳ﾘｽﾄ(4～3月)'!H$24:H$25) -> 11 | F88: =SUMIF('内訳ﾘｽﾄ(4～3月)'!$D$24:$D$25,'採算表(VND)'!$B88,'内訳ﾘｽﾄ(4～3月)'!I$24:I$25) -> 11 | G88: =SUMIF('内訳ﾘｽﾄ(4～3月)'!$D$24:$D$25,'採算表(VND)'!$B88,'内訳ﾘｽﾄ(4～3月)'!J$24:J$25) -> 11 | H88: =SUMIF('内訳ﾘｽﾄ(4～3月)'!$D$24:$D$25,'採算表(VND)'!$B88,'内訳ﾘｽﾄ(4～3月)'!K$24:K$25) -> 11 | I88: =SUMIF('内訳ﾘｽﾄ(4～3月)'!$D$24:$D$25,'採算表(VND)'!$B88,'内訳ﾘｽﾄ(4～3月)'!L$24:L$25) -> 11 | J88: =SUMIF('内訳ﾘｽﾄ(4～3月)'!$D$24:$D$25,'採算表(VND)'!$B88,'内訳ﾘｽﾄ(4～3月)'!M$24:M$25) -> 11 | ... O88: =SUMIF('内訳ﾘｽﾄ(4～3月)'!$D$24:$D$25,'採算表(VND)'!$B88,'内訳ﾘｽﾄ(4～3月)'!R$24:R$25) -> 11
B89: 人員計 | C89: =C87+C88 -> 12 | D89: =D87+D88 -> 12 | E89: =E87+E88 -> 12 | F89: =F87+F88 -> 12 | G89: =G87+G88 -> 12 | H89: =H87+H88 -> 12 | I89: =I87+I88 -> 12 | J89: =J87+J88 -> 12 | ... O89: =O87+O88 -> 12
B91: ■定時間
B92: 出向社員定時 | C92: =SUMIF('内訳ﾘｽﾄ(4～3月)'!$B$8:$B$15,$B92,'内訳ﾘｽﾄ(4～3月)'!F$8:F$15) -> 161.5 | D92: =SUMIF('内訳ﾘｽﾄ(4～3月)'!$B$8:$B$15,$B92,'内訳ﾘｽﾄ(4～3月)'!G$8:G$15) -> 153 | E92: =SUMIF('内訳ﾘｽﾄ(4～3月)'!$B$8:$B$15,$B92,'内訳ﾘｽﾄ(4～3月)'!H$8:H$15) -> 170 | F92: =SUMIF('内訳ﾘｽﾄ(4～3月)'!$B$8:$B$15,$B92,'内訳ﾘｽﾄ(4～3月)'!I$8:I$15) -> 187 | G92: =SUMIF('内訳ﾘｽﾄ(4～3月)'!$B$8:$B$15,$B92,'内訳ﾘｽﾄ(4～3月)'!J$8:J$15) -> 161.5 | H92: =SUMIF('内訳ﾘｽﾄ(4～3月)'!$B$8:$B$15,$B92,'内訳ﾘｽﾄ(4～3月)'!K$8:K$15) -> 153 | I92: =SUMIF('内訳ﾘｽﾄ(4～3月)'!$B$8:$B$15,$B92,'内訳ﾘｽﾄ(4～3月)'!L$8:L$15) -> 187 | J92: =SUMIF('内訳ﾘｽﾄ(4～3月)'!$B$8:$B$15,$B92,'内訳ﾘｽﾄ(4～3月)'!M$8:M$15) -> 170 | ... O92: =SUMIF('内訳ﾘｽﾄ(4～3月)'!$B$8:$B$15,$B92,'内訳ﾘｽﾄ(4～3月)'!R$8:R$15) -> 1997.5
B93: ローカル社員定時 | C93: =SUMIF('内訳ﾘｽﾄ(4～3月)'!$B$8:$B$15,$B93,'内訳ﾘｽﾄ(4～3月)'!F$8:F$15) -> 1836 | D93: =SUMIF('内訳ﾘｽﾄ(4～3月)'!$B$8:$B$15,$B93,'内訳ﾘｽﾄ(4～3月)'!G$8:G$15) -> 1700 | E93: =SUMIF('内訳ﾘｽﾄ(4～3月)'!$B$8:$B$15,$B93,'内訳ﾘｽﾄ(4～3月)'!H$8:H$15) -> 1887 | F93: =SUMIF('内訳ﾘｽﾄ(4～3月)'!$B$8:$B$15,$B93,'内訳ﾘｽﾄ(4～3月)'!I$8:I$15) -> 2074 | G93: =SUMIF('内訳ﾘｽﾄ(4～3月)'!$B$8:$B$15,$B93,'内訳ﾘｽﾄ(4～3月)'!J$8:J$15) -> 1793.5 | H93: =SUMIF('内訳ﾘｽﾄ(4～3月)'!$B$8:$B$15,$B93,'内訳ﾘｽﾄ(4～3月)'!K$8:K$15) -> 1700 | I93: =SUMIF('内訳ﾘｽﾄ(4～3月)'!$B$8:$B$15,$B93,'内訳ﾘｽﾄ(4～3月)'!L$8:L$15) -> 2074 | J93: =SUMIF('内訳ﾘｽﾄ(4～3月)'!$B$8:$B$15,$B93,'内訳ﾘｽﾄ(4～3月)'!M$8:M$15) -> 1793.5 | ... O93: =SUMIF('内訳ﾘｽﾄ(4～3月)'!$B$8:$B$15,$B93,'内訳ﾘｽﾄ(4～3月)'!R$8:R$15) -> 21751.5
B94: 人員計 | C94: =C92+C93 -> 1997.5 | D94: =D92+D93 -> 1853 | E94: =E92+E93 -> 2057 | F94: =F92+F93 -> 2261 | G94: =G92+G93 -> 1955 | H94: =H92+H93 -> 1853 | I94: =I92+I93 -> 2261 | J94: =J92+J93 -> 1963.5 | ... O94: =O92+O93 -> 23749
B96: ■残業時間
B97: 出向社員残業 | C97: =SUMIF('内訳ﾘｽﾄ(4～3月)'!$B$16:$B$23,$B97,'内訳ﾘｽﾄ(4～3月)'!F$16:F$23) -> 38 | D97: =SUMIF('内訳ﾘｽﾄ(4～3月)'!$B$16:$B$23,$B97,'内訳ﾘｽﾄ(4～3月)'!G$16:G$23) -> 36 | E97: =SUMIF('内訳ﾘｽﾄ(4～3月)'!$B$16:$B$23,$B97,'内訳ﾘｽﾄ(4～3月)'!H$16:H$23) -> 40 | F97: =SUMIF('内訳ﾘｽﾄ(4～3月)'!$B$16:$B$23,$B97,'内訳ﾘｽﾄ(4～3月)'!I$16:I$23) -> 44 | G97: =SUMIF('内訳ﾘｽﾄ(4～3月)'!$B$16:$B$23,$B97,'内訳ﾘｽﾄ(4～3月)'!J$16:J$23) -> 38 | H97: =SUMIF('内訳ﾘｽﾄ(4～3月)'!$B$16:$B$23,$B97,'内訳ﾘｽﾄ(4～3月)'!K$16:K$23) -> 36 | I97: =SUMIF('内訳ﾘｽﾄ(4～3月)'!$B$16:$B$23,$B97,'内訳ﾘｽﾄ(4～3月)'!L$16:L$23) -> 44 | J97: =SUMIF('内訳ﾘｽﾄ(4～3月)'!$B$16:$B$23,$B97,'内訳ﾘｽﾄ(4～3月)'!M$16:M$23) -> 40 | ... O97: =SUMIF('内訳ﾘｽﾄ(4～3月)'!$B$16:$B$23,$B97,'内訳ﾘｽﾄ(4～3月)'!R$16:R$23) -> 470
B98: ローカル社員残業 | C98: =SUMIF('内訳ﾘｽﾄ(4～3月)'!$B$16:$B$23,$B98,'内訳ﾘｽﾄ(4～3月)'!F$16:F$23) -> 130 | D98: =SUMIF('内訳ﾘｽﾄ(4～3月)'!$B$16:$B$23,$B98,'内訳ﾘｽﾄ(4～3月)'!G$16:G$23) -> 128 | E98: =SUMIF('内訳ﾘｽﾄ(4～3月)'!$B$16:$B$23,$B98,'内訳ﾘｽﾄ(4～3月)'!H$16:H$23) -> 132 | F98: =SUMIF('内訳ﾘｽﾄ(4～3月)'!$B$16:$B$23,$B98,'内訳ﾘｽﾄ(4～3月)'!I$16:I$23) -> 136 | G98: =SUMIF('内訳ﾘｽﾄ(4～3月)'!$B$16:$B$23,$B98,'内訳ﾘｽﾄ(4～3月)'!J$16:J$23) -> 140 | H98: =SUMIF('内訳ﾘｽﾄ(4～3月)'!$B$16:$B$23,$B98,'内訳ﾘｽﾄ(4～3月)'!K$16:K$23) -> 138 | I98: =SUMIF('内訳ﾘｽﾄ(4～3月)'!$B$16:$B$23,$B98,'内訳ﾘｽﾄ(4～3月)'!L$16:L$23) -> 146 | J98: =SUMIF('内訳ﾘｽﾄ(4～3月)'!$B$16:$B$23,$B98,'内訳ﾘｽﾄ(4～3月)'!M$16:M$23) -> 140 | ... O98: =SUMIF('内訳ﾘｽﾄ(4～3月)'!$B$16:$B$23,$B98,'内訳ﾘｽﾄ(4～3月)'!R$16:R$23) -> 1644
B99: 人員計 | C99: =C97+C98 -> 168 | D99: =D97+D98 -> 164 | E99: =E97+E98 -> 172 | F99: =F97+F98 -> 180 | G99: =G97+G98 -> 178 | H99: =H97+H98 -> 174 | I99: =I97+I98 -> 190 | J99: =J97+J98 -> 180 | ... O99: =O97+O98 -> 2114

Sheet 内訳ﾘｽﾄ(4～3月)
A1: MP FY2026_各予定
B2: 25390 | E2: 稼働日数 | F2: =OFFSET(稼働日!$B$2,MATCH('内訳ﾘｽﾄ(4～3月)'!F4,稼働日!$A$3:$A$14,0),0) -> 20 | G2: =OFFSET(稼働日!$B$2,MATCH('内訳ﾘｽﾄ(4～3月)'!G4,稼働日!$A$3:$A$14,0),0) -> 19 | H2: =OFFSET(稼働日!$B$2,MATCH('内訳ﾘｽﾄ(4～3月)'!H4,稼働日!$A$3:$A$14,0),0) -> 21 | I2: =OFFSET(稼働日!$B$2,MATCH('内訳ﾘｽﾄ(4～3月)'!I4,稼働日!$A$3:$A$14,0),0) -> 23 | J2: =OFFSET(稼働日!$B$2,MATCH('内訳ﾘｽﾄ(4～3月)'!J4,稼働日!$A$3:$A$14,0),0) -> 20 | K2: =OFFSET(稼働日!$B$2,MATCH('内訳ﾘｽﾄ(4～3月)'!K4,稼働日!$A$3:$A$14,0),0) -> 19 | L2: =OFFSET(稼働日!$B$2,MATCH('内訳ﾘｽﾄ(4～3月)'!L4,稼働日!$A$3:$A$14,0),0) -> 23 | M2: =OFFSET(稼働日!$B$2,MATCH('内訳ﾘｽﾄ(4～3月)'!M4,稼働日!$A$3:$A$14,0),0) -> 20 | ... Q2: =OFFSET(稼働日!$B$2,MATCH('内訳ﾘｽﾄ(4～3月)'!Q4,稼働日!$A$3:$A$14,0),0) -> 20
E3: CHECK | F3: {=IF(SUM((F8:F25)-ROUNDDOWN((F8:F25)*4,0)/4)<>0,"時間➝0.25の倍数では無い",IF(SUM(ROUND((F26:F1001),0)-ROUND((F26:F1001),4))<>0,"経費➝小数点",IF(F5<>IF($D$5="製造",'採算表(VND)'!C13,-VLOOKUP($D$5&"経費",'採算表(VND)'!$B:$N,'採算表(VND)'!C3,0)),"経費➝NG","OK")))} -> OK | G3: {=IF(SUM((G8:G25)-ROUNDDOWN((G8:G25)*4,0)/4)<>0,"時間➝0.25の倍数では無い",IF(SUM(ROUND((G26:G1001),0)-ROUND((G26:G1001),4))<>0,"経費➝小数点",IF(G5<>IF($D$5="製造",'採算表(VND)'!D13,-VLOOKUP($D$5&"経費",'採算表(VND)'!$B:$N,'採算表(VND)'!D3,0)),"経費➝NG","OK")))} -> OK | H3: {=IF(SUM((H8:H25)-ROUNDDOWN((H8:H25)*4,0)/4)<>0,"時間➝0.25の倍数では無い",IF(SUM(ROUND((H26:H1001),0)-ROUND((H26:H1001),4))<>0,"経費➝小数点",IF(H5<>IF($D$5="製造",'採算表(VND)'!E13,-VLOOKUP($D$5&"経費",'採算表(VND)'!$B:$N,'採算表(VND)'!E3,0)),"経費➝NG","OK")))} -> OK | I3: {=IF(SUM((I8:I25)-ROUNDDOWN((I8:I25)*4,0)/4)<>0,"時間➝0.25の倍数では無い",IF(SUM(ROUND((I26:I1001),0)-ROUND((I26:I1001),4))<>0,"経費➝小数点",IF(I5<>IF($D$5="製造",'採算表(VND)'!F13,-VLOOKUP($D$5&"経費",'採算表(VND)'!$B:$N,'採算表(VND)'!F3,0)),"経費➝NG","OK")))} -> OK | J3: {=IF(SUM((J8:J25)-ROUNDDOWN((J8:J25)*4,0)/4)<>0,"時間➝0.25の倍数では無い",IF(SUM(ROUND((J26:J1001),0)-ROUND((J26:J1001),4))<>0,"経費➝小数点",IF(J5<>IF($D$5="製造",'採算表(VND)'!G13,-VLOOKUP($D$5&"経費",'採算表(VND)'!$B:$N,'採算表(VND)'!G3,0)),"経費➝NG","OK")))} -> OK | K3: {=IF(SUM((K8:K25)-ROUNDDOWN((K8:K25)*4,0)/4)<>0,"時間➝0.25の倍数では無い",IF(SUM(ROUND((K26:K1001),0)-ROUND((K26:K1001),4))<>0,"経費➝小数点",IF(K5<>IF($D$5="製造",'採算表(VND)'!H13,-VLOOKUP($D$5&"経費",'採算表(VND)'!$B:$N,'採算表(VND)'!H3,0)),"経費➝NG","OK")))} -> OK | L3: {=IF(SUM((L8:L25)-ROUNDDOWN((L8:L25)*4,0)/4)<>0,"時間➝0.25の倍数では無い",IF(SUM(ROUND((L26:L1001),0)-ROUND((L26:L1001),4))<>0,"経費➝小数点",IF(L5<>IF($D$5="製造",'採算表(VND)'!I13,-VLOOKUP($D$5&"経費",'採算表(VND)'!$B:$N,'採算表(VND)'!I3,0)),"経費➝NG","OK")))} -> OK | M3: {=IF(SUM((M8:M25)-ROUNDDOWN((M8:M25)*4,0)/4)<>0,"時間➝0.25の倍数では無い",IF(SUM(ROUND((M26:M1001),0)-ROUND((M26:M1001),4))<>0,"経費➝小数点",IF(M5<>IF($D$5="製造",'採算表(VND)'!J13,-VLOOKUP($D$5&"経費",'採算表(VND)'!$B:$N,'採算表(VND)'!J3,0)),"経費➝NG","OK")))} -> OK | ... Q3: {=IF(SUM((Q8:Q25)-ROUNDDOWN((Q8:Q25)*4,0)/4)<>0,"時間➝0.25の倍数では無い",IF(SUM(ROUND((Q26:Q1001),0)-ROUND((Q26:Q1001),4))<>0,"経費➝小数点",IF(Q5<>IF($D$5="製造",'採算表(VND)'!N13,-VLOOKUP($D$5&"経費",'採算表(VND)'!$B:$N,'採算表(VND)'!N3,0)),"経費➝NG","OK")))} -> OK
B4: 原価センター | C4: 組織名 | D4: 採算区分 | E4: 原価区分 | F4: 4 | G4: 5 | H4: 6 | I4: 7 | J4: 8 | K4: 9 | L4: 10 | M4: 11 | N4: 12 | O4: 1 | P4: 2 | Q4: 3 | R4: 合計 | S4: ※MEBIUS経費になると "V02V0800" は T列に 反映お願いします
B5: 1412000083 | C5: =VLOOKUP($B$5,原価センタ!$A:$E,2,0) -> MD3課 | D5: =VLOOKUP($B$5,原価センタ!$A:$E,4,0) -> 製造 | E5: =VLOOKUP($B$5,原価センタ!$A:$E,5,0) -> 製造 | F5: =SUM(F29:F1000) -> 400823203 | G5: =SUM(G29:G1000) -> 454583044 | H5: =SUM(H29:H1000) -> 415944472 | I5: =SUM(I29:I1000) -> 464714882 | J5: =SUM(J29:J1000) -> 462266346 | K5: =SUM(K29:K1000) -> 779341928 | L5: =SUM(L29:L1000) -> 471136190 | M5: =SUM(M29:M1000) -> 447100639 | ... Q5: =SUM(Q29:Q1000) -> 438958219 | R5: =SUM(R29:R595) -> 5692691901
C7: 勘定科目名称 | D7: 採算科目 | E7: ﾃｰﾏｺｰﾄﾞ | F7: MP | G7: MP | H7: MP | I7: MP | J7: MP | K7: MP | L7: MP | M7: MP | N7: MP | O7: MP | P7: MP | Q7: MP | R7: MP | S7: 備考 | T7: WBS | BC7: WBS | BG7: 12 | BH7: 12 | BI7: 12 | BJ7: 1 | BK7: 2 | BL7: 3 | BM7: 4
B8: 出向社員定時 | C8: 定時間（日本社員） | D8: 直接部門 | F8: 161.5 | G8: 153 | H8: 170 | I8: 187 | J8: 161.5 | K8: 153 | L8: 187 | M8: 170 | N8: 187 | O8: 170 | P8: 127.5 | Q8: 170 | R8: =SUM(F8:Q8) -> 1997.5 | BE8: USD換算Rate (VND/USD) | BG8: 25359 | BH8: 25359 | BI8: 25359 | BJ8: 25359 | BK8: 25359 | BL8: 25359 | BM8: 25359
B9: ローカル社員定時 | C9: 定時間（ベトナム社員） | D9: 直接部門 | F9: 1836 | G9: 1700 | H9: 1887 | I9: 2074 | J9: 1793.5 | K9: 1700 | L9: 2074 | M9: 1793.5 | N9: 1980.5 | O9: 1793.5 | P9: 1326 | Q9: 1793.5 | R9: =SUM(F9:Q9) -> 21751.5 | BE9: JPY換算Rate (VND/JPY) | BG9: 164.27 | BH9: 164.27 | BI9: 164.27 | BJ9: 164.27 | BK9: 164.27 | BL9: 164.27 | BM9: 164.27
B10: 出向社員定時 | C10: 定時間（移動分日本社員） | D10: 直接部門 | R10: =SUM(F10:Q10) -> 0 | BE10: 【システム課金金額】 Mail | BF10: 7.05 | BG10: 1966590 | BH10: 1966590 | BI10: 1966590 | BJ10: 1966590 | BK10: 1966590 | BL10: 1966590 | BM10: 1966590
B11: ローカル社員定時 | C11: 定時間（移動分ベトナム社員） | D11: 直接部門 | R11: =SUM(F11:Q11) -> 0 | BE11: 【システム課金金額】 R3 | BF11: 0
C12: 定時間（部内間接部門） | D12: 部内間接部門 | F12: 0 | G12: 0 | H12: 0 | I12: 0 | J12: 0 | K12: 0 | L12: 0 | M12: 0 | N12: 0 | O12: 0 | P12: 0 | Q12: 0 | R12: =SUM(F12:Q12) -> 0 | S12: この分には間接部門から直接部門に配賦された数字 | BE12: 【システム課金金額】 VPS | BF12: 0
C13: 定時間（部外間接部門1） | D13: 部外間接部門1 | F13: 6.75 | G13: 7 | H13: 7.75 | I13: 12 | J13: 10.75 | K13: 10 | L13: 8.25 | M13: 7.25 | N13: 8 | O13: 7.5 | P13: 5.5 | Q13: 7.5 | R13: =SUM(F13:Q13) -> 98.25 | S13: この分には間接部門から直接部門に配賦された数字 | BE13: 【システム課金金額】 VPN | BF13: 3.52 | BG13: 89264 | BH13: 89264 | BI13: 89264 | BJ13: 89264 | BK13: 89264 | BL13: 89264 | BM13: 89264
C14: 定時間（部外間接部門2） | D14: 部外間接部門2 | F14: 12.75 | G14: 12.25 | H14: 14 | I14: 23.25 | J14: 20.25 | K14: 19.75 | L14: 16.25 | M14: 14 | N14: 15.5 | O14: 14.25 | P14: 10.75 | Q14: 14 | R14: =SUM(F14:Q14) -> 187 | S14: この分には間接部門から直接部門に配賦された数字 | BE14: [減価償却費] 建物 | BF14: (USD) | BG14: 182.06 | BH14: 182.06 | BI14: 182.06 | BJ14: 182.01 | BK14: 182.01 | BL14: 182.01 | BM14: 182.01
C15: 定時間（工場間接部門） | D15: 工場間接部門 | F15: 57 | G15: 56.5 | H15: 60 | I15: 96 | J15: 88.25 | K15: 82.5 | L15: 65 | M15: 59.25 | N15: 63.75 | O15: 60.25 | P15: 45.25 | Q15: 60.5 | R15: =SUM(F15:Q15) -> 794.25 | S15: この分には間接部門から直接部門に配賦された数字 | BE15: [減価償却費] 土地使用権 | BF15: (USD) | BG15: 12.29 | BH15: 12.29 | BI15: 12.29 | BJ15: 12.29 | BK15: 12.29 | BL15: 12.29 | BM15: 12.29
B16: 出向社員残業 | C16: 残業時間（日本社員） | D16: 直接部門 | F16: 38 | G16: 36 | H16: 40 | I16: 44 | J16: 38 | K16: 36 | L16: 44 | M16: 40 | N16: 44 | O16: 40 | P16: 30 | Q16: 40 | R16: =SUM(F16:Q16) -> 470 | BE16: [固定資産金利] 建物 | BF16: (USD) | BG16: 123.58 | BH16: 123.58 | BI16: 123.58 | BJ16: 123.55 | BK16: 123.55 | BL16: 123.55 | BM16: 123.55
B17: ローカル社員残業 | C17: 残業時間（ベトナム社員） | D17: 直接部門 | F17: 130 | G17: 128 | H17: 132 | I17: 136 | J17: 140 | K17: 138 | L17: 146 | M17: 140 | N17: 144 | O17: 140 | P17: 130 | Q17: 140 | R17: =SUM(F17:Q17) -> 1644 | S17: 13時間/人・月(1-12期生)で計算 係責任者は2時間のみなし残業 | BE17: [固定資産金利] 土地使用権 | BF17: (USD) | BG17: 15.28 | BH17: 15.28 | BI17: 15.28 | BJ17: 15.28 | BK17: 15.28 | BL17: 15.28 | BM17: 15.28
B18: 出向社員残業 | C18: 残業時間（移動分日本社員） | D18: 直接部門 | R18: =SUM(F18:Q18) -> 0 | BE18: 電気代 | BF18: (VND) | BG18: 1278721 | BH18: 1323787 | BI18: 1323787 | BJ18: 1226674 | BK18: 858672 | BL18: 1104007 | BM18: 1300274
B19: ローカル社員残業 | C19: 残業時間（移動分ベトナム社員） | D19: 直接部門 | R19: =SUM(F19:Q19) -> 0 | BE19: 水道代 | BF19: (VND) | BG19: 424631 | BH19: 424631 | BI19: 424631 | BJ19: 295783 | BK19: 235769 | BL19: 257202 | BM19: 300069
C20: 残業時間（部内間接部門） | D20: 部内間接部門 | F20: 0 | G20: 0 | H20: 0 | I20: 0 | J20: 0 | K20: 0 | L20: 0 | M20: 0 | N20: 0 | O20: 0 | P20: 0 | Q20: 0 | R20: =SUM(F20:Q20) -> 0 | S20: この分には間接部門から直接部門に配賦された数字 | BE20: ガス | BF20: (USD) | BG20: 39585 | BH20: 39585 | BI20: 39585 | BJ20: 35606 | BK20: 38435 | BL20: 38435 | BM20: 38435
C21: 残業時間（部外間接部門1） | D21: 部外間接部門1 | F21: 0.5 | G21: 0.5 | H21: 0.5 | I21: 0.75 | J21: 0.75 | K21: 0.75 | L21: 0.5 | M21: 0.5 | N21: 0.5 | O21: 0.5 | P21: 0.25 | Q21: 0.5 | R21: =SUM(F21:Q21) -> 6.5 | S21: この分には間接部門から直接部門に配賦された数字 | BE21: 手洗い洗剤 | BF21: (USD) | BG21: 1079 | BH21: 1079 | BI21: 1079 | BJ21: 1028 | BK21: 1126 | BL21: 1174 | BM21: 1174
C22: 残業時間（部外間接部門2） | D22: 部外間接部門2 | F22: 1.25 | G22: 1 | H22: 1.25 | I22: 2 | J22: 1.25 | K22: 1.25 | L22: 1.25 | M22: 1.25 | N22: 1.25 | O22: 1.5 | P22: 0.5 | Q22: 1.5 | R22: =SUM(F22:Q22) -> 15.25 | S22: この分には間接部門から直接部門に配賦された数字 | BE22: トイレットペーパー | BF22: (USD) | BG22: 17105 | BH22: 17105 | BI22: 17105 | BJ22: 15443 | BK22: 16391 | BL22: 17520 | BM22: 17520
C23: 残業時間（工場間接部門） | D23: 工場間接部門 | F23: 3.25 | G23: 3.25 | H23: 2.75 | I23: 4.5 | J23: 3.25 | K23: 5 | L23: 3 | M23: 3 | N23: 3 | O23: 2.75 | P23: 3.75 | Q23: 2.75 | R23: =SUM(F23:Q23) -> 40.25 | S23: この分には間接部門から直接部門に配賦された数字 | BE23: 清掃費 | BF23: (USD) | BG23: 49155 | BH23: 49155 | BI23: 49155 | BJ23: 49027 | BK23: 48431 | BL23: 48915 | BM23: 49077
B24: 出向社員(人) | C24: 出向社員(人) | D24: 出向社員(人) | F24: 1 | G24: 1 | H24: 1 | I24: 1 | J24: 1 | K24: 1 | L24: 1 | M24: 1 | N24: 1 | O24: 1 | P24: 1 | Q24: 1 | R24: =Q24 -> 1 | BE24: 出向者送迎費 | BF24: (USD) | BG24: 727642 | BH24: 727642 | BI24: 727642 | BJ24: 585189 | BK24: 546296 | BL24: 803438 | BM24: 803438
B25: ローカル社員(人) | C25: ローカル社員(人) | D25: ローカル社員(人) | F25: 11 | G25: 11 | H25: 11 | I25: 11 | J25: 11 | K25: 11 | L25: 11 | M25: 11 | N25: 11 | O25: 11 | P25: 11 | Q25: 11 | R25: =Q25 -> 11 | V25: 4 | W25: 5 | X25: 6 | Y25: 7 | Z25: 8 | AA25: 9 | AB25: 10 | AC25: 11 | AD25: 12 | AE25: 1 | AF25: 2 | AG25: 3 | BE25: Local社員送迎費 | BF25: (USD) | BG25: 1620318 | BH25: 1620318 | BI25: 1620318 | BJ25: 1505412 | BK25: 1488121 | BL25: 1167909 | BM25: 1259044
B26: 9114120002 | C26: 社外出荷 | D26: 社外出荷 | F26: =ROUNDDOWN(V26*$B$2,0)+1 -> 756707565 | G26: =ROUNDDOWN(W26*$B$2,0)+1 -> 1105818795 | H26: =ROUNDDOWN(X26*$B$2,0)+1 -> 1026239934 | I26: =ROUNDDOWN(Y26*$B$2,0)+1 -> 1060968122 | J26: =ROUNDDOWN(Z26*$B$2,0) -> 1149473853 | K26: =ROUNDDOWN(AA26*$B$2,0)+1 -> 1153673106 | L26: =ROUNDDOWN(AB26*$B$2,0)+1 -> 1453732633 | M26: =ROUNDDOWN(AC26*$B$2,0)+1 -> 1171044436 | N26: =ROUNDDOWN(AD26*$B$2,0)+1 -> 1135944792 | O26: =ROUNDDOWN(AE26*$B$2,0)+1 -> 1161632363 | P26: =ROUNDDOWN(AF26*$B$2,0)+1 -> 1140587861 | Q26: =ROUNDDOWN(AG26*$B$2,0)+1 -> 1129609479 | R26: =SUM(F26:Q26) -> 13445432939 | S26: 総生産情報 | V26: 29803.37 | W26: 43553.32 | X26: 40419.06 | Y26: 41786.85 | Z26: 45272.7 | AA26: 45438.09 | AB26: 57256.11 | AC26: 46122.27 | AD26: 44739.85 | AE26: 45751.57 | AF26: 44922.72 | AG26: 44490.33 | BE26: 休(出向) 人日 | BG26: 1 | BH26: 1 | BI26: 1 | BJ26: 1 | BK26: 1 | BL26: 1 | BM26: 1
B27: 9114120004 | C27: 社内売 | D27: 社内売 | F27: 0 | G27: 0 | H27: 0 | I27: 0 | J27: 0 | K27: 0 | L27: 0 | M27: 0 | N27: 0 | O27: 0 | P27: 0 | Q27: 0 | R27: =SUM(F27:Q27) -> 0 | S27: 総生産情報 | BE27: 休(Local) 人日 | BG27: 7 | BH27: 7 | BI27: 7 | BJ27: 5 | BK27: 5 | BL27: 5 | BM27: 6
B28: 9114120014 | C28: 社内買 | D28: 社内買 | F28: 0 | G28: 0 | H28: 0 | I28: 0 | J28: 0 | K28: 0 | L28: 0 | M28: 0 | N28: 0 | O28: 0 | P28: 0 | Q28: 0 | R28: =SUM(F28:Q28) -> 0 | S28: 総生産情報 | BE28: 残(Local) 時間 | BG28: 10 | BH28: 10 | BI28: 10 | BJ28: 10 | BK28: 100 | BL28: 100 | BM28: 100
B29: 9114120006 | C29: 材料費(指図出庫） | D29: 材料費 | F29: 0 | G29: 0 | H29: 0 | I29: 0 | J29: 0 | K29: 0 | L29: 0 | M29: 0 | N29: 0 | O29: 0 | P29: 0 | Q29: 0 | R29: =SUM(F29:Q29) -> 0 | S29: 総生産情報 | BE29: 誕生会人数 | BG29: 0 | BH29: 0 | BI29: 0 | BJ29: 2 | BK29: 2 | BL29: 2 | BM29: 1
C30: =IFERROR(IF(VLOOKUP($B30,[1]勘定科目!$A:$H,HLOOKUP($E$5,[1]勘定科目!$F$1:$H$2,2,0),0)="","",VLOOKUP($B30,[1]勘定科目!$A:$E,2,0)),"") | D30: =IF(C30="","",VLOOKUP($B30,[1]勘定科目!$A:$E,4,0)) | R30: =SUM(F30:Q30) -> 0 | BE30: CHI さん産休 ( 9/5~9/11) | BG30: 20 | BH30: 20 | BI30: 20 | BJ30: 17 | BK30: 19 | BL30: 20 | BM30: 19
B31: 9114120018 | C31: =IFERROR(IF(VLOOKUP($B31,[1]勘定科目!$A:$H,HLOOKUP($E$5,[1]勘定科目!$F$1:$H$2,2,0),0)="","",VLOOKUP($B31,[1]勘定科目!$A:$E,2,0)),"") -> 部内間接経費 | D31: =IF(C31="","",VLOOKUP($B31,[1]勘定科目!$A:$E,4,0)) -> 部内間接経費 | F31: 0 | G31: 0 | H31: 0 | I31: 0 | J31: 0 | K31: 0 | L31: 0 | M31: 0 | N31: 0 | O31: 0 | P31: 0 | Q31: 0 | R31: =SUM(F31:Q31) -> 0 | S31: この分には間接部門から直接部門に配賦された数字
B32: 9114120029 | C32: =IFERROR(IF(VLOOKUP($B32,[1]勘定科目!$A:$H,HLOOKUP($E$5,[1]勘定科目!$F$1:$H$2,2,0),0)="","",VLOOKUP($B32,[1]勘定科目!$A:$E,2,0)),"") -> 部外間接経費1 | D32: =IF(C32="","",VLOOKUP($B32,[1]勘定科目!$A:$E,4,0)) -> 部外間接経費1 | F32: 397748 | G32: 456535 | H32: 380026 | I32: 628019 | J32: 564637 | K32: 617936 | L32: 371560 | M32: 373979 | N32: 377736 | O32: 363367 | P32: 384655 | Q32: 367742 | R32: =SUM(F32:Q32) -> 5283940 | S32: この分には間接部門から直接部門に配賦された数字
B33: 9114120030 | C33: =IFERROR(IF(VLOOKUP($B33,[1]勘定科目!$A:$H,HLOOKUP($E$5,[1]勘定科目!$F$1:$H$2,2,0),0)="","",VLOOKUP($B33,[1]勘定科目!$A:$E,2,0)),"") -> 部外間接経費2 | D33: =IF(C33="","",VLOOKUP($B33,[1]勘定科目!$A:$E,4,0)) -> 部外間接経費2 | F33: 2428308 | G33: 829829 | H33: 594132 | I33: 960180 | J33: 862028 | K33: 775164 | L33: 646360 | M33: 664785 | N33: 642063 | O33: 502068 | P33: 525403 | Q33: 516391 | R33: =SUM(F33:Q33) -> 9946711 | S33: この分には間接部門から直接部門に配賦された数字
B34: 9114120021 | C34: =IFERROR(IF(VLOOKUP($B34,[1]勘定科目!$A:$H,HLOOKUP($E$5,[1]勘定科目!$F$1:$H$2,2,0),0)="","",VLOOKUP($B34,[1]勘定科目!$A:$E,2,0)),"") -> 工場間接経費 | D34: =IF(C34="","",VLOOKUP($B34,[1]勘定科目!$A:$E,4,0)) -> 工場間接経費 | F34: 28869303 | G34: 36883360 | H34: 27306721 | I34: 59003732 | J34: 32875220 | K34: 32133504 | L34: 27208202 | M34: 22922178 | N34: 22670432 | O34: 25237009 | P34: 17427497 | Q34: 17985042 | R34: =SUM(F34:Q34) -> 350522200 | S34: この分には間接部門から直接部門に配賦された数字
C35: =IFERROR(IF(VLOOKUP($B35,[1]勘定科目!$A:$H,HLOOKUP($E$5,[1]勘定科目!$F$1:$H$2,2,0),0)="","",VLOOKUP($B35,[1]勘定科目!$A:$E,2,0)),"") | D35: =IF(C35="","",VLOOKUP($B35,[1]勘定科目!$A:$E,4,0)) | R35: =SUM(F35:Q35) -> 0
C36: =IFERROR(IF(VLOOKUP($B36,[1]勘定科目!$A:$H,HLOOKUP($E$5,[1]勘定科目!$F$1:$H$2,2,0),0)="","",VLOOKUP($B36,[1]勘定科目!$A:$E,2,0)),"") | D36: =IF(C36="","",VLOOKUP($B36,[1]勘定科目!$A:$E,4,0)) | R36: =SUM(F36:Q36) -> 0
C37: =IFERROR(IF(VLOOKUP($B37,[1]勘定科目!$A:$H,HLOOKUP($E$5,[1]勘定科目!$F$1:$H$2,2,0),0)="","",VLOOKUP($B37,[1]勘定科目!$A:$E,2,0)),"") | D37: =IF(C37="","",VLOOKUP($B37,[1]勘定科目!$A:$E,4,0)) | R37: =SUM(F37:Q37) -> 0
C38: =IFERROR(IF(VLOOKUP($B38,[1]勘定科目!$A:$H,HLOOKUP($E$5,[1]勘定科目!$F$1:$H$2,2,0),0)="","",VLOOKUP($B38,[1]勘定科目!$A:$E,2,0)),"") | D38: =IF(C38="","",VLOOKUP($B38,[1]勘定科目!$A:$E,4,0)) | R38: =SUM(F38:Q38) -> 0
C39: =IFERROR(IF(VLOOKUP($B39,[1]勘定科目!$A:$H,HLOOKUP($E$5,[1]勘定科目!$F$1:$H$2,2,0),0)="","",VLOOKUP($B39,[1]勘定科目!$A:$E,2,0)),"") | D39: =IF(C39="","",VLOOKUP($B39,[1]勘定科目!$A:$E,4,0)) | S39: 一般経費↓
B40: 5006016260 | C40: =IFERROR(IF(VLOOKUP($B40,[1]勘定科目!$A:$H,HLOOKUP($E$5,[1]勘定科目!$F$1:$H$2,2,0),0)="","",VLOOKUP($B40,[1]勘定科目!$A:$E,2,0)),"") -> 減価償却費配賦（製） 建物 | D40: =IF(C40="","",VLOOKUP($B40,[1]勘定科目!$A:$E,4,0)) -> 減価償却費 | F40: 13339144 | G40: 11594597 | H40: 11630397 | I40: 12403015 | J40: 11652233 | K40: 11245993 | L40: 11245993 | M40: 10900689 | N40: 11211208 | O40: 11202576 | P40: 10871998 | Q40: 10850670 | R40: =SUM(F40:Q40) -> 138148513 | S40: 減価償却費配賦 建物
B41: 5006016261 | C41: =IFERROR(IF(VLOOKUP($B41,[1]勘定科目!$A:$H,HLOOKUP($E$5,[1]勘定科目!$F$1:$H$2,2,0),0)="","",VLOOKUP($B41,[1]勘定科目!$A:$E,2,0)),"") -> 減価償却費配賦（製） 土地使用権 | D41: =IF(C41="","",VLOOKUP($B41,[1]勘定科目!$A:$E,4,0)) -> 減価償却費 | F41: 900329 | G41: 782520 | H41: 785059 | I41: 837108 | J41: 786582 | K41: 759161 | L41: 759161 | M41: 735802 | N41: 756622 | O41: 756114 | P41: 733771 | Q41: 732502 | R41: =SUM(F41:Q41) -> 9324731 | S41: 減価償却費配賦 土地使用権
B42: 9114120007 | C42: =IFERROR(IF(VLOOKUP($B42,[1]勘定科目!$A:$H,HLOOKUP($E$5,[1]勘定科目!$F$1:$H$2,2,0),0)="","",VLOOKUP($B42,[1]勘定科目!$A:$E,2,0)),"") -> 社内金利（固定資産） | D42: =IF(C42="","",VLOOKUP($B42,[1]勘定科目!$A:$E,4,0)) -> 固定資産金利 | F42: 9534707 | G42: 7870138 | H42: 7894513 | I42: 8419070 | J42: 7909239 | K42: 7633757 | L42: 7633504 | M42: 7399154 | N42: 7610145 | O42: 7606590 | P42: 7379604 | Q42: 7365131 | R42: =SUM(F42:Q42) -> 94255552 | S42: 固定資産金利 建物
B43: 9114120007 | C43: =IFERROR(IF(VLOOKUP($B43,[1]勘定科目!$A:$H,HLOOKUP($E$5,[1]勘定科目!$F$1:$H$2,2,0),0)="","",VLOOKUP($B43,[1]勘定科目!$A:$E,2,0)),"") -> 社内金利（固定資産） | D43: =IF(C43="","",VLOOKUP($B43,[1]勘定科目!$A:$E,4,0)) -> 固定資産金利 | F43: 1151944 | G43: 973199 | H43: 975992 | I43: 1040990 | J43: 978023 | K43: 943746 | L43: 943746 | M43: 914802 | N43: 940953 | O43: 940446 | P43: 912517 | Q43: 910739 | R43: =SUM(F43:Q43) -> 11627097 | S43: 固定資産金利 土地使用権
B44: 5005066281 | C44: =IFERROR(IF(VLOOKUP($B44,[1]勘定科目!$A:$H,HLOOKUP($E$5,[1]勘定科目!$F$1:$H$2,2,0),0)="","",VLOOKUP($B44,[1]勘定科目!$A:$E,2,0)),"") -> 電気代（製） | D44: =IF(C44="","",VLOOKUP($B44,[1]勘定科目!$A:$E,4,0)) -> 水道光熱費 | F44: 3626471 | G44: 2849621 | H44: 2879559 | I44: 3850638 | J44: 4268883 | K44: 3980921 | L44: 3349017 | M44: 3405947 | N44: 3754361 | O44: 2166157 | P44: 3101743 | Q44: 2097317 | R44: =SUM(F44:Q44) -> 39330635 | S44: 電気代
B45: 5005066282 | C45: =IFERROR(IF(VLOOKUP($B45,[1]勘定科目!$A:$H,HLOOKUP($E$5,[1]勘定科目!$F$1:$H$2,2,0),0)="","",VLOOKUP($B45,[1]勘定科目!$A:$E,2,0)),"") -> 水道代（製） | D45: =IF(C45="","",VLOOKUP($B45,[1]勘定科目!$A:$E,4,0)) -> 水道光熱費 | F45: 921387 | G45: 839383 | H45: 766451 | I45: 1052652 | J45: 1183456 | K45: 1046349 | L45: 793382 | M45: 921498 | N45: 841980 | O45: 726254 | P45: 673794 | Q45: 575180 | R45: =SUM(F45:Q45) -> 10341766 | S45: 水道代
B46: 5005056281 | C46: =IFERROR(IF(VLOOKUP($B46,[1]勘定科目!$A:$H,HLOOKUP($E$5,[1]勘定科目!$F$1:$H$2,2,0),0)="","",VLOOKUP($B46,[1]勘定科目!$A:$E,2,0)),"") -> ガス代（製） | D46: =IF(C46="","",VLOOKUP($B46,[1]勘定科目!$A:$E,4,0)) -> 水道光熱費 | F46: 541020 | G46: 541020 | H46: 541020 | I46: 541020 | J46: 541020 | K46: 541020 | L46: 541020 | M46: 541020 | N46: 541020 | O46: 541020 | P46: 541020 | Q46: 541020 | R46: =SUM(F46:Q46) -> 6492240 | S46: ガス
B47: 5005016372 | C47: =IFERROR(IF(VLOOKUP($B47,[1]勘定科目!$A:$H,HLOOKUP($E$5,[1]勘定科目!$F$1:$H$2,2,0),0)="","",VLOOKUP($B47,[1]勘定科目!$A:$E,2,0)),"") -> その他消耗品（製） | D47: =IF(C47="","",VLOOKUP($B47,[1]勘定科目!$A:$E,4,0)) -> 消耗品費 | F47: 18240 | G47: 18240 | H47: 18240 | I47: 18240 | J47: 18240 | K47: 18240 | L47: 18240 | M47: 18240 | N47: 18240 | O47: 18240 | P47: 18240 | Q47: 18240 | R47: =SUM(F47:Q47) -> 218880 | S47: 手洗い洗剤
B48: 5005016372 | C48: =IFERROR(IF(VLOOKUP($B48,[1]勘定科目!$A:$H,HLOOKUP($E$5,[1]勘定科目!$F$1:$H$2,2,0),0)="","",VLOOKUP($B48,[1]勘定科目!$A:$E,2,0)),"") -> その他消耗品（製） | D48: =IF(C48="","",VLOOKUP($B48,[1]勘定科目!$A:$E,4,0)) -> 消耗品費 | F48: 215652 | G48: 215652 | H48: 215652 | I48: 215652 | J48: 215652 | K48: 215652 | L48: 215652 | M48: 215652 | N48: 215652 | O48: 215652 | P48: 215652 | Q48: 215652 | R48: =SUM(F48:Q48) -> 2587824 | S48: トイレットペーパー
B49: 5005016372 | C49: =IFERROR(IF(VLOOKUP($B49,[1]勘定科目!$A:$H,HLOOKUP($E$5,[1]勘定科目!$F$1:$H$2,2,0),0)="","",VLOOKUP($B49,[1]勘定科目!$A:$E,2,0)),"") -> その他消耗品（製） | D49: =IF(C49="","",VLOOKUP($B49,[1]勘定科目!$A:$E,4,0)) -> 消耗品費 | F49: 607548 | G49: 607548 | H49: 607548 | I49: 607548 | J49: 607548 | K49: 607548 | L49: 607548 | M49: 607548 | N49: 607548 | O49: 607548 | P49: 607548 | Q49: 607548 | R49: =SUM(F49:Q49) -> 7290576 | S49: アルコール 消毒
B50: 5005246286 | C50: =IFERROR(IF(VLOOKUP($B50,[1]勘定科目!$A:$H,HLOOKUP($E$5,[1]勘定科目!$F$1:$H$2,2,0),0)="","",VLOOKUP($B50,[1]勘定科目!$A:$E,2,0)),"") -> その他手数料（製） | D50: =IF(C50="","",VLOOKUP($B50,[1]勘定科目!$A:$E,4,0)) -> 手数料 | F50: 45204 | G50: 45204 | H50: 45204 | I50: 45204 | J50: 45204 | K50: 45204 | L50: 45204 | M50: 45204 | N50: 45204 | O50: 45204 | P50: 45204 | Q50: 45204 | R50: =SUM(F50:Q50) -> 542448 | S50: 清掃費
B51: 5004086291 | C51: =IFERROR(IF(VLOOKUP($B51,[1]勘定科目!$A:$H,HLOOKUP($E$5,[1]勘定科目!$F$1:$H$2,2,0),0)="","",VLOOKUP($B51,[1]勘定科目!$A:$E,2,0)),"") -> 福利厚生費（製） | D51: =IF(C51="","",VLOOKUP($B51,[1]勘定科目!$A:$E,4,0)) -> 福利厚生費 | F51: 700000 | G51: 700000 | H51: 700000 | I51: 700000 | J51: 700000 | K51: 700000 | L51: 700000 | M51: 700000 | N51: 700000 | O51: 700000 | P51: 700000 | Q51: 700000 | R51: =SUM(F51:Q51) -> 8400000 | S51: 出向者送迎費
B52: 5004086291 | C52: =IFERROR(IF(VLOOKUP($B52,[1]勘定科目!$A:$H,HLOOKUP($E$5,[1]勘定科目!$F$1:$H$2,2,0),0)="","",VLOOKUP($B52,[1]勘定科目!$A:$E,2,0)),"") -> 福利厚生費（製） | D52: =IF(C52="","",VLOOKUP($B52,[1]勘定科目!$A:$E,4,0)) -> 福利厚生費 | F52: 3400000 | G52: 3400000 | H52: 3400000 | I52: 3400000 | J52: 3400000 | K52: 3400000 | L52: 3400000 | M52: 3400000 | N52: 3400000 | O52: 3400000 | P52: 3400000 | Q52: 3400000 | R52: =SUM(F52:Q52) -> 40800000 | S52: Local Bus送迎費 (local Member 人員比率 で計算) | U52: 2 | V52: ローカルバス利用者
B53: 5004086291 | C53: =IFERROR(IF(VLOOKUP($B53,[1]勘定科目!$A:$H,HLOOKUP($E$5,[1]勘定科目!$F$1:$H$2,2,0),0)="","",VLOOKUP($B53,[1]勘定科目!$A:$E,2,0)),"") -> 福利厚生費（製） | D53: =IF(C53="","",VLOOKUP($B53,[1]勘定科目!$A:$E,4,0)) -> 福利厚生費 | F53: 0 | G53: 0 | H53: 0 | I53: 0 | J53: 0 | K53: 0 | L53: 0 | M53: 0 | N53: 0 | O53: 0 | P53: 0 | Q53: 0 | R53: =SUM(F53:Q53) -> 0 | S53: 残業時のタクシー送迎費 | U53: 2 | V53: ローカルバス利用者
B54: 5004086291 | C54: =IFERROR(IF(VLOOKUP($B54,[1]勘定科目!$A:$H,HLOOKUP($E$5,[1]勘定科目!$F$1:$H$2,2,0),0)="","",VLOOKUP($B54,[1]勘定科目!$A:$E,2,0)),"") -> 福利厚生費（製） | D54: =IF(C54="","",VLOOKUP($B54,[1]勘定科目!$A:$E,4,0)) -> 福利厚生費 | F54: 0 | G54: 0 | H54: 0 | I54: 0 | J54: 0 | K54: 0 | L54: 0 | M54: 0 | N54: 0 | O54: 0 | P54: 0 | Q54: 0 | R54: =SUM(F54:Q54) -> 0 | S54: 出向者 通勤タクシー費用 （140,000*4 朝会 160,000×8 英語 固定 ＋α)
B55: 5004086291 | C55: =IFERROR(IF(VLOOKUP($B55,[1]勘定科目!$A:$H,HLOOKUP($E$5,[1]勘定科目!$F$1:$H$2,2,0),0)="","",VLOOKUP($B55,[1]勘定科目!$A:$E,2,0)),"") -> 福利厚生費（製） | D55: =IF(C55="","",VLOOKUP($B55,[1]勘定科目!$A:$E,4,0)) -> 福利厚生費 | F55: 0 | G55: 0 | H55: 0 | I55: 0 | J55: 0 | K55: 585000 | L55: 0 | M55: 0 | N55: 0 | O55: 0 | P55: 0 | Q55: 0 | R55: =SUM(F55:Q55) -> 585000 | S55: 月餅
B56: 5004086291 | C56: =IFERROR(IF(VLOOKUP($B56,[1]勘定科目!$A:$H,HLOOKUP($E$5,[1]勘定科目!$F$1:$H$2,2,0),0)="","",VLOOKUP($B56,[1]勘定科目!$A:$E,2,0)),"") -> 福利厚生費（製） | D56: =IF(C56="","",VLOOKUP($B56,[1]勘定科目!$A:$E,4,0)) -> 福利厚生費 | F56: 0 | G56: 0 | H56: 0 | I56: 0 | J56: 0 | K56: 0 | L56: 0 | M56: 0 | N56: 0 | O56: 0 | P56: 0 | Q56: 0 | R56: =SUM(F56:Q56) -> 0 | S56: 昼食代 (前月21日～当月20日を当月)
B57: 5004086291 | C57: =IFERROR(IF(VLOOKUP($B57,[1]勘定科目!$A:$H,HLOOKUP($E$5,[1]勘定科目!$F$1:$H$2,2,0),0)="","",VLOOKUP($B57,[1]勘定科目!$A:$E,2,0)),"") -> 福利厚生費（製） | D57: =IF(C57="","",VLOOKUP($B57,[1]勘定科目!$A:$E,4,0)) -> 福利厚生費 | F57: 0 | G57: 21000000 | H57: 0 | I57: 0 | J57: 0 | K57: 0 | L57: 0 | M57: 0 | N57: 0 | O57: 0 | P57: 0 | Q57: 0 | R57: =SUM(F57:Q57) -> 21000000 | S57: 社員旅行
B58: 5004086291 | C58: =IFERROR(IF(VLOOKUP($B58,[1]勘定科目!$A:$H,HLOOKUP($E$5,[1]勘定科目!$F$1:$H$2,2,0),0)="","",VLOOKUP($B58,[1]勘定科目!$A:$E,2,0)),"") -> 福利厚生費（製） | D58: =IF(C58="","",VLOOKUP($B58,[1]勘定科目!$A:$E,4,0)) -> 福利厚生費 | F58: 0 | G58: 0 | H58: 0 | I58: 0 | J58: 0 | K58: 1608000 | L58: 0 | M58: 0 | N58: 0 | O58: 0 | P58: 0 | Q58: 0 | R58: =SUM(F58:Q58) -> 1608000 | S58: kyouceraフェスティバル
B59: 5004086291 | C59: =IFERROR(IF(VLOOKUP($B59,[1]勘定科目!$A:$H,HLOOKUP($E$5,[1]勘定科目!$F$1:$H$2,2,0),0)="","",VLOOKUP($B59,[1]勘定科目!$A:$E,2,0)),"") -> 福利厚生費（製） | D59: =IF(C59="","",VLOOKUP($B59,[1]勘定科目!$A:$E,4,0)) -> 福利厚生費 | F59: 0 | G59: 0 | H59: 0 | I59: 0 | J59: 0 | K59: 0 | L59: 0 | M59: 1236000 | N59: 0 | O59: 0 | P59: 0 | Q59: 0 | R59: =SUM(F59:Q59) -> 1236000 | S59: 運動会
B60: 5004086291 | C60: =IFERROR(IF(VLOOKUP($B60,[1]勘定科目!$A:$H,HLOOKUP($E$5,[1]勘定科目!$F$1:$H$2,2,0),0)="","",VLOOKUP($B60,[1]勘定科目!$A:$E,2,0)),"") -> 福利厚生費（製） | D60: =IF(C60="","",VLOOKUP($B60,[1]勘定科目!$A:$E,4,0)) -> 福利厚生費 | F60: 0 | G60: 0 | H60: 0 | I60: 0 | J60: 0 | K60: 0 | L60: 0 | M60: 0 | N60: 0 | O60: 2400000 | P60: 0 | Q60: 0 | R60: =SUM(F60:Q60) -> 2400000 | S60: 忘年会補助金
B61: 5004086291 | C61: =IFERROR(IF(VLOOKUP($B61,[1]勘定科目!$A:$H,HLOOKUP($E$5,[1]勘定科目!$F$1:$H$2,2,0),0)="","",VLOOKUP($B61,[1]勘定科目!$A:$E,2,0)),"") -> 福利厚生費（製） | D61: =IF(C61="","",VLOOKUP($B61,[1]勘定科目!$A:$E,4,0)) -> 福利厚生費 | F61: 0 | G61: 0 | H61: 0 | I61: 0 | J61: 0 | K61: 0 | L61: 0 | M61: 0 | N61: 0 | O61: 0 | P61: 1200000 | Q61: 0 | R61: =SUM(F61:Q61) -> 1200000 | S61: お年玉
B62: 5004086291 | C62: =IFERROR(IF(VLOOKUP($B62,[1]勘定科目!$A:$H,HLOOKUP($E$5,[1]勘定科目!$F$1:$H$2,2,0),0)="","",VLOOKUP($B62,[1]勘定科目!$A:$E,2,0)),"") -> 福利厚生費（製） | D62: =IF(C62="","",VLOOKUP($B62,[1]勘定科目!$A:$E,4,0)) -> 福利厚生費 | F62: 0 | G62: 0 | H62: 0 | I62: 0 | J62: 0 | K62: 0 | L62: 0 | M62: 0 | N62: 0 | O62: 0 | P62: 0 | Q62: 0 | R62: =SUM(F62:Q62) -> 0 | S62: 誕生日会
B63: 5004086291 | C63: =IFERROR(IF(VLOOKUP($B63,[1]勘定科目!$A:$H,HLOOKUP($E$5,[1]勘定科目!$F$1:$H$2,2,0),0)="","",VLOOKUP($B63,[1]勘定科目!$A:$E,2,0)),"") -> 福利厚生費（製） | D63: =IF(C63="","",VLOOKUP($B63,[1]勘定科目!$A:$E,4,0)) -> 福利厚生費 | G63: 1200000 | R63: =SUM(F63:Q63) -> 1200000 | S63: 決起コンパ
B64: 5005246281 | C64: =IFERROR(IF(VLOOKUP($B64,[1]勘定科目!$A:$H,HLOOKUP($E$5,[1]勘定科目!$F$1:$H$2,2,0),0)="","",VLOOKUP($B64,[1]勘定科目!$A:$E,2,0)),"") -> 図書印刷費（製） | D64: =IF(C64="","",VLOOKUP($B64,[1]勘定科目!$A:$E,4,0)) -> 図書及び事務費 | F64: 0 | G64: 0 | H64: 0 | I64: 0 | J64: 0 | K64: 0 | L64: 0 | M64: 18300 | N64: 0 | O64: 0 | P64: 0 | Q64: 0 | R64: =SUM(F64:Q64) -> 18300 | S64: ポケットカレンダー
B65: 5004086291 | C65: =IFERROR(IF(VLOOKUP($B65,[1]勘定科目!$A:$H,HLOOKUP($E$5,[1]勘定科目!$F$1:$H$2,2,0),0)="","",VLOOKUP($B65,[1]勘定科目!$A:$E,2,0)),"") -> 福利厚生費（製） | D65: =IF(C65="","",VLOOKUP($B65,[1]勘定科目!$A:$E,4,0)) -> 福利厚生費 | F65: 0 | G65: 0 | H65: 0 | I65: 275000 | J65: 0 | K65: 0 | L65: 0 | M65: 0 | N65: 0 | O65: 0 | P65: 0 | Q65: 0 | R65: =SUM(F65:Q65) -> 275000 | S65: フィロソフィ論文参加賞
B66: 5004086291 | C66: =IFERROR(IF(VLOOKUP($B66,[1]勘定科目!$A:$H,HLOOKUP($E$5,[1]勘定科目!$F$1:$H$2,2,0),0)="","",VLOOKUP($B66,[1]勘定科目!$A:$E,2,0)),"") -> 福利厚生費（製） | D66: =IF(C66="","",VLOOKUP($B66,[1]勘定科目!$A:$E,4,0)) -> 福利厚生費 | F66: 0 | G66: 0 | H66: 0 | I66: 0 | J66: 0 | K66: 0 | L66: 0 | M66: 0 | N66: 1701000 | O66: 0 | P66: 0 | Q66: 0 | R66: =SUM(F66:Q66) -> 1701000 | S66: 健康診断（ローカル）男性
B67: 5004086291 | C67: =IFERROR(IF(VLOOKUP($B67,[1]勘定科目!$A:$H,HLOOKUP($E$5,[1]勘定科目!$F$1:$H$2,2,0),0)="","",VLOOKUP($B67,[1]勘定科目!$A:$E,2,0)),"") -> 福利厚生費（製） | D67: =IF(C67="","",VLOOKUP($B67,[1]勘定科目!$A:$E,4,0)) -> 福利厚生費 | F67: 0 | G67: 0 | H67: 0 | I67: 0 | J67: 0 | K67: 0 | L67: 0 | M67: 0 | N67: 408000 | O67: 0 | P67: 0 | Q67: 0 | R67: =SUM(F67:Q67) -> 408000 | S67: 健康診断（ローカル）女性
C68: =IFERROR(IF(VLOOKUP($B68,[1]勘定科目!$A:$H,HLOOKUP($E$5,[1]勘定科目!$F$1:$H$2,2,0),0)="","",VLOOKUP($B68,[1]勘定科目!$A:$E,2,0)),"") | D68: =IF(C68="","",VLOOKUP($B68,[1]勘定科目!$A:$E,4,0)) | R68: =SUM(F68:Q68) -> 0
C69: =IFERROR(IF(VLOOKUP($B69,[1]勘定科目!$A:$H,HLOOKUP($E$5,[1]勘定科目!$F$1:$H$2,2,0),0)="","",VLOOKUP($B69,[1]勘定科目!$A:$E,2,0)),"") | D69: =IF(C69="","",VLOOKUP($B69,[1]勘定科目!$A:$E,4,0)) | R69: =SUM(F69:Q69) -> 0 | S69: システム経費↓
B70: 5005246282 | C70: =IFERROR(IF(VLOOKUP($B70,[1]勘定科目!$A:$H,HLOOKUP($E$5,[1]勘定科目!$F$1:$H$2,2,0),0)="","",VLOOKUP($B70,[1]勘定科目!$A:$E,2,0)),"") -> ＫＤＣシステム使用料（製） | D70: =IF(C70="","",VLOOKUP($B70,[1]勘定科目!$A:$E,4,0)) -> 図書及び事務費 | F70: 2024525 | G70: 2024525 | H70: 2024525 | I70: 2024525 | J70: 2024525 | K70: 2024525 | L70: 2024525 | M70: 2024525 | N70: 2024525 | O70: 2024525 | P70: 2024525 | Q70: 2024525 | R70: =SUM(F70:Q70) -> 24294300 | S70: メール
B71: 5005246282 | C71: =IFERROR(IF(VLOOKUP($B71,[1]勘定科目!$A:$H,HLOOKUP($E$5,[1]勘定科目!$F$1:$H$2,2,0),0)="","",VLOOKUP($B71,[1]勘定科目!$A:$E,2,0)),"") -> ＫＤＣシステム使用料（製） | D71: =IF(C71="","",VLOOKUP($B71,[1]勘定科目!$A:$E,4,0)) -> 図書及び事務費 | R71: =SUM(F71:Q71) -> 0 | S71: R3
B72: 5005246282 | C72: =IFERROR(IF(VLOOKUP($B72,[1]勘定科目!$A:$H,HLOOKUP($E$5,[1]勘定科目!$F$1:$H$2,2,0),0)="","",VLOOKUP($B72,[1]勘定科目!$A:$E,2,0)),"") -> ＫＤＣシステム使用料（製） | D72: =IF(C72="","",VLOOKUP($B72,[1]勘定科目!$A:$E,4,0)) -> 図書及び事務費 | R72: =SUM(F72:Q72) -> 0 | S72: PLM
B73: 5005246282 | C73: =IFERROR(IF(VLOOKUP($B73,[1]勘定科目!$A:$H,HLOOKUP($E$5,[1]勘定科目!$F$1:$H$2,2,0),0)="","",VLOOKUP($B73,[1]勘定科目!$A:$E,2,0)),"") -> ＫＤＣシステム使用料（製） | D73: =IF(C73="","",VLOOKUP($B73,[1]勘定科目!$A:$E,4,0)) -> 図書及び事務費 | R73: =SUM(F73:Q73) -> 0 | S73: VPS
B74: 5005246282 | C74: =IFERROR(IF(VLOOKUP($B74,[1]勘定科目!$A:$H,HLOOKUP($E$5,[1]勘定科目!$F$1:$H$2,2,0),0)="","",VLOOKUP($B74,[1]勘定科目!$A:$E,2,0)),"") -> ＫＤＣシステム使用料（製） | D74: =IF(C74="","",VLOOKUP($B74,[1]勘定科目!$A:$E,4,0)) -> 図書及び事務費 | R74: =SUM(F74:Q74) -> 0 | S74: 翻訳ツール(COTOHA)
B75: 5005246282 | C75: =IFERROR(IF(VLOOKUP($B75,[1]勘定科目!$A:$H,HLOOKUP($E$5,[1]勘定科目!$F$1:$H$2,2,0),0)="","",VLOOKUP($B75,[1]勘定科目!$A:$E,2,0)),"") -> ＫＤＣシステム使用料（製） | D75: =IF(C75="","",VLOOKUP($B75,[1]勘定科目!$A:$E,4,0)) -> 図書及び事務費 | R75: =SUM(F75:Q75) -> 0 | S75: CAD \4,931,701/月 （新CADも含む CADユーザー追加分で予測）→FY2026～MD4課へ移動
B76: 5005246282 | C76: =IFERROR(IF(VLOOKUP($B76,[1]勘定科目!$A:$H,HLOOKUP($E$5,[1]勘定科目!$F$1:$H$2,2,0),0)="","",VLOOKUP($B76,[1]勘定科目!$A:$E,2,0)),"") -> ＫＤＣシステム使用料（製） | D76: =IF(C76="","",VLOOKUP($B76,[1]勘定科目!$A:$E,4,0)) -> 図書及び事務費 | F76: 83520 | G76: 83520 | H76: 83520 | I76: 83520 | J76: 83520 | K76: 83520 | L76: 83520 | M76: 83520 | N76: 83520 | O76: 83520 | P76: 83520 | Q76: 83520 | R76: =SUM(F76:Q76) -> 1002240 | S76: VPN 出向者分
C77: =IFERROR(IF(VLOOKUP($B77,[1]勘定科目!$A:$H,HLOOKUP($E$5,[1]勘定科目!$F$1:$H$2,2,0),0)="","",VLOOKUP($B77,[1]勘定科目!$A:$E,2,0)),"") | D77: =IF(C77="","",VLOOKUP($B77,[1]勘定科目!$A:$E,4,0)) | R77: =SUM(F77:Q77) -> 0 | S77: 新入社員経費↓
B78: 5005246281 | C78: =IFERROR(IF(VLOOKUP($B78,[1]勘定科目!$A:$H,HLOOKUP($E$5,[1]勘定科目!$F$1:$H$2,2,0),0)="","",VLOOKUP($B78,[1]勘定科目!$A:$E,2,0)),"") -> 図書印刷費（製） | D78: =IF(C78="","",VLOOKUP($B78,[1]勘定科目!$A:$E,4,0)) -> 図書及び事務費 | J78: 0 | R78: =SUM(F78:Q78) -> 0 | S78: 新入社員 社員証
B79: 5005246281 | C79: =IFERROR(IF(VLOOKUP($B79,[1]勘定科目!$A:$H,HLOOKUP($E$5,[1]勘定科目!$F$1:$H$2,2,0),0)="","",VLOOKUP($B79,[1]勘定科目!$A:$E,2,0)),"") -> 図書印刷費（製） | D79: =IF(C79="","",VLOOKUP($B79,[1]勘定科目!$A:$E,4,0)) -> 図書及び事務費 | J79: 0 | R79: =SUM(F79:Q79) -> 0 | S79: 新入社員 社員証ケース
B80: 5005246288 | C80: =IFERROR(IF(VLOOKUP($B80,[1]勘定科目!$A:$H,HLOOKUP($E$5,[1]勘定科目!$F$1:$H$2,2,0),0)="","",VLOOKUP($B80,[1]勘定科目!$A:$E,2,0)),"") -> 事務用品費（製） | D80: =IF(C80="","",VLOOKUP($B80,[1]勘定科目!$A:$E,4,0)) -> 図書及び事務費 | J80: 0 | R80: =SUM(F80:Q80) -> 0 | S80: 新入社員 Pen
B81: 5005246288 | C81: =IFERROR(IF(VLOOKUP($B81,[1]勘定科目!$A:$H,HLOOKUP($E$5,[1]勘定科目!$F$1:$H$2,2,0),0)="","",VLOOKUP($B81,[1]勘定科目!$A:$E,2,0)),"") -> 事務用品費（製） | D81: =IF(C81="","",VLOOKUP($B81,[1]勘定科目!$A:$E,4,0)) -> 図書及び事務費 | J81: 0 | R81: =SUM(F81:Q81) -> 0 | S81: 新入社員 Note
B82: 5005246281 | C82: =IFERROR(IF(VLOOKUP($B82,[1]勘定科目!$A:$H,HLOOKUP($E$5,[1]勘定科目!$F$1:$H$2,2,0),0)="","",VLOOKUP($B82,[1]勘定科目!$A:$E,2,0)),"") -> 図書印刷費（製） | D82: =IF(C82="","",VLOOKUP($B82,[1]勘定科目!$A:$E,4,0)) -> 図書及び事務費 | J82: 0 | R82: =SUM(F82:Q82) -> 0 | S82: 新入社員 フィロソフィ手帳
B83: 5004086291 | C83: =IFERROR(IF(VLOOKUP($B83,[1]勘定科目!$A:$H,HLOOKUP($E$5,[1]勘定科目!$F$1:$H$2,2,0),0)="","",VLOOKUP($B83,[1]勘定科目!$A:$E,2,0)),"") -> 福利厚生費（製） | D83: =IF(C83="","",VLOOKUP($B83,[1]勘定科目!$A:$E,4,0)) -> 福利厚生費 | J83: 0 | R83: =SUM(F83:Q83) -> 0 | S83: 新入社員 採用時健康診断 （採用時）男性
B84: 5004086291 | C84: =IFERROR(IF(VLOOKUP($B84,[1]勘定科目!$A:$H,HLOOKUP($E$5,[1]勘定科目!$F$1:$H$2,2,0),0)="","",VLOOKUP($B84,[1]勘定科目!$A:$E,2,0)),"") -> 福利厚生費（製） | D84: =IF(C84="","",VLOOKUP($B84,[1]勘定科目!$A:$E,4,0)) -> 福利厚生費 | R84: =SUM(F84:Q84) -> 0 | S84: 新入社員 採用時健康診断 （採用時）女性
B85: 5004086291 | C85: =IFERROR(IF(VLOOKUP($B85,[1]勘定科目!$A:$H,HLOOKUP($E$5,[1]勘定科目!$F$1:$H$2,2,0),0)="","",VLOOKUP($B85,[1]勘定科目!$A:$E,2,0)),"") -> 福利厚生費（製） | D85: =IF(C85="","",VLOOKUP($B85,[1]勘定科目!$A:$E,4,0)) -> 福利厚生費 | J85: 0 | R85: =SUM(F85:Q85) -> 0 | S85: 新入社員 帽子
B86: 5004086291 | C86: =IFERROR(IF(VLOOKUP($B86,[1]勘定科目!$A:$H,HLOOKUP($E$5,[1]勘定科目!$F$1:$H$2,2,0),0)="","",VLOOKUP($B86,[1]勘定科目!$A:$E,2,0)),"") -> 福利厚生費（製） | D86: =IF(C86="","",VLOOKUP($B86,[1]勘定科目!$A:$E,4,0)) -> 福利厚生費 | J86: 0 | R86: =SUM(F86:Q86) -> 0 | S86: 新入社員 制服上着(夏服) x2枚/人
B87: 5004086291 | C87: =IFERROR(IF(VLOOKUP($B87,[1]勘定科目!$A:$H,HLOOKUP($E$5,[1]勘定科目!$F$1:$H$2,2,0),0)="","",VLOOKUP($B87,[1]勘定科目!$A:$E,2,0)),"") -> 福利厚生費（製） | D87: =IF(C87="","",VLOOKUP($B87,[1]勘定科目!$A:$E,4,0)) -> 福利厚生費 | J87: 0 | R87: =SUM(F87:Q87) -> 0 | S87: 新入社員 制服上着(冬服) x2枚/人
B88: 5004086291 | C88: =IFERROR(IF(VLOOKUP($B88,[1]勘定科目!$A:$H,HLOOKUP($E$5,[1]勘定科目!$F$1:$H$2,2,0),0)="","",VLOOKUP($B88,[1]勘定科目!$A:$E,2,0)),"") -> 福利厚生費（製） | D88: =IF(C88="","",VLOOKUP($B88,[1]勘定科目!$A:$E,4,0)) -> 福利厚生費 | J88: 0 | R88: =SUM(F88:Q88) -> 0 | S88: 新入社員 制服(ズボン) x2枚/人
B89: 5004086291 | C89: =IFERROR(IF(VLOOKUP($B89,[1]勘定科目!$A:$H,HLOOKUP($E$5,[1]勘定科目!$F$1:$H$2,2,0),0)="","",VLOOKUP($B89,[1]勘定科目!$A:$E,2,0)),"") -> 福利厚生費（製） | D89: =IF(C89="","",VLOOKUP($B89,[1]勘定科目!$A:$E,4,0)) -> 福利厚生費 | J89: 0 | R89: =SUM(F89:Q89) -> 0 | S89: 新入社員 靴 男性
B90: 5004086291 | C90: =IFERROR(IF(VLOOKUP($B90,[1]勘定科目!$A:$H,HLOOKUP($E$5,[1]勘定科目!$F$1:$H$2,2,0),0)="","",VLOOKUP($B90,[1]勘定科目!$A:$E,2,0)),"") -> 福利厚生費（製） | D90: =IF(C90="","",VLOOKUP($B90,[1]勘定科目!$A:$E,4,0)) -> 福利厚生費 | J90: 0 | R90: =SUM(F90:Q90) -> 0 | S90: 新入社員 靴 女性
B91: 5005246281 | C91: =IFERROR(IF(VLOOKUP($B91,[1]勘定科目!$A:$H,HLOOKUP($E$5,[1]勘定科目!$F$1:$H$2,2,0),0)="","",VLOOKUP($B91,[1]勘定科目!$A:$E,2,0)),"") -> 図書印刷費（製） | D91: =IF(C91="","",VLOOKUP($B91,[1]勘定科目!$A:$E,4,0)) -> 図書及び事務費 | J91: 0 | R91: =SUM(F91:Q91) -> 0 | S91: 新入社員 ポケットカレンダー
B92: 5005246288 | C92: =IFERROR(IF(VLOOKUP($B92,[1]勘定科目!$A:$H,HLOOKUP($E$5,[1]勘定科目!$F$1:$H$2,2,0),0)="","",VLOOKUP($B92,[1]勘定科目!$A:$E,2,0)),"") -> 事務用品費（製） | D92: =IF(C92="","",VLOOKUP($B92,[1]勘定科目!$A:$E,4,0)) -> 図書及び事務費 | L92: 400000 | R92: =SUM(F92:Q92) -> 400000 | S92: データ印 (12期生)
B93: 5005026371 | C93: =IFERROR(IF(VLOOKUP($B93,[1]勘定科目!$A:$H,HLOOKUP($E$5,[1]勘定科目!$F$1:$H$2,2,0),0)="","",VLOOKUP($B93,[1]勘定科目!$A:$E,2,0)),"") -> 消耗工具器具備品費（製） | D93: =IF(C93="","",VLOOKUP($B93,[1]勘定科目!$A:$E,4,0)) -> 消耗工具器具備品費 | I93: 0 | R93: =SUM(F93:Q93) -> 0 | S93: 新入社員PC購入費 1名
B94: 5005026371 | C94: =IFERROR(IF(VLOOKUP($B94,[1]勘定科目!$A:$H,HLOOKUP($E$5,[1]勘定科目!$F$1:$H$2,2,0),0)="","",VLOOKUP($B94,[1]勘定科目!$A:$E,2,0)),"") -> 消耗工具器具備品費（製） | D94: =IF(C94="","",VLOOKUP($B94,[1]勘定科目!$A:$E,4,0)) -> 消耗工具器具備品費 | R94: =SUM(F94:Q94) -> 0 | S94: 事務机
B95: 5005026371 | C95: =IFERROR(IF(VLOOKUP($B95,[1]勘定科目!$A:$H,HLOOKUP($E$5,[1]勘定科目!$F$1:$H$2,2,0),0)="","",VLOOKUP($B95,[1]勘定科目!$A:$E,2,0)),"") -> 消耗工具器具備品費（製） | D95: =IF(C95="","",VLOOKUP($B95,[1]勘定科目!$A:$E,4,0)) -> 消耗工具器具備品費 | I95: 0 | R95: =SUM(F95:Q95) -> 0 | S95: 新入社員机/椅子購入費 1名
C96: =IFERROR(IF(VLOOKUP($B96,[1]勘定科目!$A:$H,HLOOKUP($E$5,[1]勘定科目!$F$1:$H$2,2,0),0)="","",VLOOKUP($B96,[1]勘定科目!$A:$E,2,0)),"") | D96: =IF(C96="","",VLOOKUP($B96,[1]勘定科目!$A:$E,4,0)) | R96: =SUM(F96:Q96) -> 0 | S96: INTERNSHIP↓
C97: =IFERROR(IF(VLOOKUP($B97,[1]勘定科目!$A:$H,HLOOKUP($E$5,[1]勘定科目!$F$1:$H$2,2,0),0)="","",VLOOKUP($B97,[1]勘定科目!$A:$E,2,0)),"") | D97: =IF(C97="","",VLOOKUP($B97,[1]勘定科目!$A:$E,4,0)) | R97: =SUM(F97:Q97) -> 0
C98: =IFERROR(IF(VLOOKUP($B98,[1]勘定科目!$A:$H,HLOOKUP($E$5,[1]勘定科目!$F$1:$H$2,2,0),0)="","",VLOOKUP($B98,[1]勘定科目!$A:$E,2,0)),"") | D98: =IF(C98="","",VLOOKUP($B98,[1]勘定科目!$A:$E,4,0)) | R98: =SUM(F98:Q98) -> 0 | S98: 計測器校正費↓
C99: =IFERROR(IF(VLOOKUP($B99,[1]勘定科目!$A:$H,HLOOKUP($E$5,[1]勘定科目!$F$1:$H$2,2,0),0)="","",VLOOKUP($B99,[1]勘定科目!$A:$E,2,0)),"") | D99: =IF(C99="","",VLOOKUP($B99,[1]勘定科目!$A:$E,4,0)) | R99: =SUM(F99:Q99) -> 0
C100: =IFERROR(IF(VLOOKUP($B100,[1]勘定科目!$A:$H,HLOOKUP($E$5,[1]勘定科目!$F$1:$H$2,2,0),0)="","",VLOOKUP($B100,[1]勘定科目!$A:$E,2,0)),"") | D100: =IF(C100="","",VLOOKUP($B100,[1]勘定科目!$A:$E,4,0)) | R100: =SUM(F100:Q100) -> 0 | S100: 減価償却費↓
B101: 5006016244 | C101: =IFERROR(IF(VLOOKUP($B101,[1]勘定科目!$A:$H,HLOOKUP($E$5,[1]勘定科目!$F$1:$H$2,2,0),0)="","",VLOOKUP($B101,[1]勘定科目!$A:$E,2,0)),"") -> 減価償却費（製） 工具器具備品 | D101: =IF(C101="","",VLOOKUP($B101,[1]勘定科目!$A:$E,4,0)) -> 減価償却費 | J101: 23200000 | K101: 23200000 | L101: 23200000 | M101: 23200000 | N101: 23200000 | O101: 23200000 | P101: 23200000 | Q101: 23200000 | R101: =SUM(F101:Q101) -> 185600000 | S101: 防音室 5,000,000JPY
...

Sheet 設備投資計画
B1: 設備投資金額一覧表 | D1: ='内訳ﾘｽﾄ(4～3月)'!C5 -> MD3課 | E1: (単位： VND)
B3: 部門ｺｰﾄﾞ | C3: 購入物品名 | D3: 目 的 | E3: 4 | F3: 5 | G3: 6 | H3: 7 | I3: 8 | J3: 9 | K3: 10 | L3: 11 | M3: 12 | N3: 1 | O3: 2 | P3: 3 | Q3: 償却期間 (ヶ月) | R3: 購入金額合計 | S3: WBS
B4: 1412000083 | C4: 防音室 | D4: 騒音測定、異常音調査 | I4: =23200000*36 -> 835200000 | Q4: 36 | R4: =SUM(E4:P4) -> 835200000
B5: 1412000083 | D5: 元素分析 | H5: =29420616*36 -> 1059142176 | Q5: 36 | R5: =SUM(E5:P5) -> 1059142176
R6: =SUM(E6:P6) -> 0
R7: =SUM(E7:P7) -> 0
R8: =SUM(E8:P8) -> 0
R9: =SUM(E9:P9) -> 0
R10: =SUM(E10:P10) -> 0
R11: =SUM(E11:P11) -> 0
R12: =SUM(E12:P12) -> 0
R13: =SUM(E13:P13) -> 0
R14: =SUM(E14:P14) -> 0
R15: =SUM(E15:P15) -> 0
R16: =SUM(E16:P16) -> 0
R17: =SUM(E17:P17) -> 0
... R49: =SUM(E49:P49) -> 0
D50: TOTAL | R50: =SUM(E50:P50) -> 0
B52: ＊設備投資は、30,000,000VND以上、且つ1年以上使用するものが対象となります。
B53: ＊建設仮勘定を含む、取得基準にて記入して下さい。
B54: ＊重複を避ける為、稟議起案部門にて記入して下さい。
B55: ＊リースによる設備投資を含めないで下さい。

Sheet 勘定科目
A1: Account_Code | B1: JPN (50cha) | C1: Tiếng Việt_Tên tài khoản kế toán | D1: JP_Name | E1: Tiếng Việt_Hạng mục lợi nhuận | F1: 製造 | G1: 一般 | H1: 販売 | I1: REMARK
F2: =COLUMNS($A$2:F2) -> 6 | G2: =COLUMNS($A$2:G2) -> 7 | H2: =COLUMNS($A$2:H2) -> 8
A3: 7001065118 | B3: 雑収入 | C3: Doanh thu khác | D3: 雑収入 | E3: Thu nhập khác | F3: 7001065118 | G3: 7001065118 | H3: 7001065118
A4: 7001075118 | B4: 雑収入（関係会社） | C4: Doanh thu khác | D4: 雑収入 | E4: Thu nhập khác | F4: 7001075118 | G4: 7001075118 | H4: 7001075118
A5: 7001065119 | B5: 固定資産売却勘定 | C5: Doanh thu khác | D5: 雑収入 | E5: Thu nhập khác | F5: 7001065119 | G5: 7001065119 | H5: 7001065119
A6: 5001016131 | B6: 材料仕入割戻高 | C6: Chi phí nguyên liệu, vật liệu trực tiếp | D6: 材料費 | E6: Chi phí nguyên vật liệu | F6: 5001016131 | I6: 2016年4月から追加する。
A7: 5001016134 | B7: リーフレット用材料 | C7: Chi phí nguyên liệu, vật liệu trực tiếp | D7: 材料費 | E7: Chi phí nguyên vật liệu | F7: 5001016134 | G7: 5001016134 | H7: 5001016134 | I7: 2017年1月変更。
A8: 5001016135 | B8: 不良部品材料費 | C8: Chi phí nguyên liệu, vật liệu trực tiếp | D8: 材料費 | E8: Chi phí nguyên vật liệu | F8: 5001016135 | G8: 5001016135 | H8: 5001016135
A9: 5001016136 | B9: 追加指図部品費 | C9: Chi phí nguyên liệu, vật liệu trực tiếp | D9: 材料費 | E9: Chi phí nguyên vật liệu | F9: 5001016136 | G9: 5001016136 | H9: 5001016136
A10: 5001016142 | B10: 加工中不良廃棄損 | C10: Chi phí nguyên liệu, vật liệu trực tiếp | D10: 仕掛仕損 | E10: Sản phẩm chưa hoàn thiện,hỏng | F10: 5001016142 | G10: 5001016142 | H10: 5001016142
A11: 5001016149 | B11: 金型材料仕入 | C11: Chi phí nguyên liệu, vật liệu trực tiếp | D11: 材料費 | E11: Chi phí nguyên vật liệu | F11: 5001016149 | G11: 5001016149 | H11: 5001016149 | I11: 2月から追加する。
A12: 5001016151 | B12: 生産用副資材 | C12: Chi phí nguyên liệu, vật liệu trực tiếp | D12: 材料費 | E12: Chi phí nguyên vật liệu | F12: 5001016151 | I12: 2017年1月追加。
A13: 5004046221 | B13: 雑給（直製） | C13: Chi phí nhân công trực tiếp | D13: 雑給 | E13: Chi phí nhân công trực tiếp | F13: 5004046221
A14: 5004046371 | B14: 雑給（間製） | C14: Chi phí nhân viên phân xưởng | D14: 雑給 | E14: Chi phí nhân công trực tiếp | F14: 5004046371
A15: 5005016371 | B15: 生産用消耗品費（製） | C15: Chi phí dụng cụ sản xuất | D15: 消耗品費 | E15: Chi phí hàng hóa tiêu hao | F15: 5005016371
A16: 5005016372 | B16: その他消耗品（製） | C16: Chi phí dụng cụ sản xuất | D16: 消耗品費 | E16: Chi phí hàng hóa tiêu hao | F16: 5005016372
A17: 5005016373 | B17: 生産用文房具（製造） | C17: Chi phí dụng cụ sản xuất | D17: 消耗品費 | E17: Chi phí hàng hóa tiêu hao | F17: 5005016373 | I17: 2017年1月追加。
A18: 5005026371 | B18: 消耗工具器具備品費（製） | C18: Chi phí dụng cụ sản xuất | D18: 消耗工具器具備品費 | E18: Chi phí sử dụng công cụ,đồ đạc | F18: 5005026371
A19: 5005026372 | B19: 消耗金型代（製） | C19: Chi phí dụng cụ sản xuất | D19: 消耗金型費 | E19: Chi phí tiêu hao khuôn | F19: 5005026372
A20: 5006016241 | B20: 減価償却費（製） 建物 | C20: Chi phí khấu hao TSCĐ | D20: 減価償却費 | E20: Chi phí khấu hao | F20: 5006016241
A21: 5006016242 | B21: 減価償却費（製） 機械装置 | C21: Chi phí khấu hao TSCĐ | D21: 減価償却費 | E21: Chi phí khấu hao | F21: 5006016242
A22: 5006016243 | B22: 減価償却費（製） 車輌運搬具 | C22: Chi phí khấu hao TSCĐ | D22: 減価償却費 | E22: Chi phí khấu hao | F22: 5006016243
A23: 5006016244 | B23: 減価償却費（製） 工具器具備品 | C23: Chi phí khấu hao TSCĐ | D23: 減価償却費 | E23: Chi phí khấu hao | F23: 5006016244
A24: 5006016245 | B24: 減価償却費（製） 構築物 | C24: Chi phí khấu hao TSCĐ | D24: 減価償却費 | E24: Chi phí khấu hao | F24: 5006016245
A25: 5005036246 | B25: 減価償却費（製） 金型 | C25: Chi phí khấu hao TSCĐ | D25: 金型償却費 | E25: Chi phí khấu hao khuôn | F25: 5005036246
A26: 5006016247 | B26: 減価償却費（製） その他有形固定資産 | C26: Chi phí khấu hao TSCĐ | D26: 減価償却費 | E26: Chi phí khấu hao | F26: 5006016247
A27: 5006016248 | B27: 減価償却費（製） リース建物 | C27: Chi phí khấu hao TSCĐ | D27: 減価償却費 | E27: Chi phí khấu hao | F27: 5006016248
A28: 5006016249 | B28: 減価償却費（製） リース機械装置 | C28: Chi phí khấu hao TSCĐ | D28: 減価償却費 | E28: Chi phí khấu hao | F28: 5006016249
A29: 5006016250 | B29: 減価償却費（製） リース車輌運搬具 | C29: Chi phí khấu hao TSCĐ | D29: 減価償却費 | E29: Chi phí khấu hao | F29: 5006016250
... A44: 5005046283 | B44: 年間保守料（製） | C44: Chi phi dịch vụ mua ngoài | D44: 修繕費 | E44: Chi phí sửa chữa | F44: 5005046283
A45: 5005046284 | B45: 金型修繕費（製造） | C45: Chi phi dịch vụ mua ngoài | D45: 修繕費 | E45: Chi phí sửa chữa | F45: 5005046284 | I45: 2017年1月追加。
A46: 5005066281 | B46: 電気代（製） | C46: Chi phi dịch vụ mua ngoài | D46: 水道光熱費 | E46: Chi phí Utilities(điện,nước..) | F46: 5005066281
A47: 5005066282 | B47: 水道代（製） | C47: Chi phi dịch vụ mua ngoài | D47: 水道光熱費 | E47: Chi phí Utilities(điện,nước..) | F47: 5005066282
A48: 5005056281 | B48: ガス代（製） | C48: Chi phi dịch vụ mua ngoài | D48: 水道光熱費 | E48: Chi phí Utilities(điện,nước..) | F48: 5005056281
A49: 5005076281 | B49: 通関申告費用（製） | C49: Chi phi dịch vụ mua ngoài | D49: 荷造運賃 | E49: Chi phí vận chuyển hàng hóa | F49: 5005076281
A50: 5005076282 | B50: 設備輸送費（製） | C50: Chi phi dịch vụ mua ngoài | D50: 荷造運賃 | E50: Chi phí vận chuyển hàng hóa | F50: 5005076282
A51: 5005076283 | B51: 輸入航空運賃（製） | C51: Chi phi dịch vụ mua ngoài | D51: 荷造運賃 | E51: Chi phí vận chuyển hàng hóa | F51: 5005076283
A52: 5005076284 | B52: 輸入海上運賃（製） | C52: Chi phi dịch vụ mua ngoài | D52: 荷造運賃 | E52: Chi phí vận chuyển hàng hóa | F52: 5005076284
A53: 5005076285 | B53: 空箱返却費用 | C53: Chi phi dịch vụ mua ngoài | D53: 荷造運賃 | E53: Chi phí vận chuyển hàng hóa | F53: 5005076285
A54: 5005076286 | B54: 部品集荷トラック代 | C54: Chi phi dịch vụ mua ngoài | D54: 荷造運賃 | E54: Chi phí vận chuyển hàng hóa | F54: 5005076286
A55: 5005076287 | B55: 物流保険料（製） | C55: Chi phi dịch vụ mua ngoài | D55: 荷造運賃 | E55: Chi phí vận chuyển hàng hóa | F55: 5005076287
A56: 5005076288 | B56: 梱包材料費（製） | C56: Chi phi dịch vụ mua ngoài | D56: 荷造用品費 | E56: Chi phí NVL dùng đóng gói hàng | F56: 5005076288
A57: 5005076289 | B57: クーリエ費用（製） | C57: Chi phi dịch vụ mua ngoài | D57: 荷造運賃 | E57: Chi phí vận chuyển hàng hóa | F57: 5005076289
A58: 5005076291 | B58: 外部倉庫 取扱手数料（製造） | C58: Chi phi dịch vụ mua ngoài | D58: 荷造運賃 | E58: Chi phí vận chuyển hàng hóa | F58: 5005076291 | I58: 2017年1月追加。
A59: 5005076292 | B59: 外部倉庫 保管料（製造） | C59: Chi phi dịch vụ mua ngoài | D59: 荷造運賃 | E59: Chi phí vận chuyển hàng hóa | F59: 5005076292 | I59: 2017年1月追加。
A60: 5005076293 | B60: 外部倉庫 輸送料（製造） | C60: Chi phi dịch vụ mua ngoài | D60: 荷造運賃 | E60: Chi phí vận chuyển hàng hóa | F60: 5005076293 | I60: 2017年1月追加。
A61: 5005076294 | B61: 外部物流業者 取扱手数料（製造） | C61: Chi phi dịch vụ mua ngoài | D61: 荷造運賃 | E61: Chi phí vận chuyển hàng hóa | F61: 5005076294 | I61: 2017年1月追加。
A62: 5005086281 | B62: 技術料（製） | C62: Chi phi dịch vụ mua ngoài | D62: 技術料 | E62: Phí kỹ thuật | F62: 5005086281
A63: 5005136281 | B63: 通信費（製） | C63: Chi phi dịch vụ mua ngoài | D63: 通信費 | E63: Chi phí điện thoại | F63: 5005136281
A64: 5005246281 | B64: 図書印刷費（製） | C64: Chi phi dịch vụ mua ngoài | D64: 図書及び事務費 | E64: Chi phí văn phòng | F64: 5005246281
A65: 5005246282 | B65: ＫＤＣシステム使用料（製） | C65: Chi phi dịch vụ mua ngoài | D65: 図書及び事務費 | E65: Chi phí văn phòng | F65: 5005246282
A66: 5005246283 | B66: ライセンス料（製） | C66: Chi phi dịch vụ mua ngoài | D66: 図書及び事務費 | E66: Chi phí văn phòng | F66: 5005246283
A67: 5005246284 | B67: 会費（製） | C67: Chi phi dịch vụ mua ngoài | D67: 会費及び会議費 | E67: Chi phí cuộc họp | F67: 5005246284
A68: 5005216281 | B68: 委嘱報酬・設計委託費（製） | C68: Chi phi dịch vụ mua ngoài | D68: 委嘱報酬 | E68: Thù lao ủy thác,phí hoa hồng | F68: 5005216281
A69: 5005226281 | B69: 保険料（製） | C69: Chi phi dịch vụ mua ngoài | D69: 保険料 | E69: Chi phí bảo hiểm | F69: 5005226281
A70: 5005236281 | B70: 事務所賃借料（製） | C70: Chi phi dịch vụ mua ngoài | D70: 賃借料 | E70: Chi phí thuê | F70: 5005236281
A71: 5005236282 | B71: 倉庫賃借料（製） | C71: Chi phi dịch vụ mua ngoài | D71: 賃借料 | E71: Chi phí thuê | F71: 5005236282
A72: 5005246285 | B72: 取扱手数料（製） | C72: Chi phi dịch vụ mua ngoài | D72: 手数料 | E72: Tiền dịch vụ,tiền lệ phí | F72: 5005246285
A73: 5005246286 | B73: その他手数料（製） | C73: Chi phi dịch vụ mua ngoài | D73: 手数料 | E73: Tiền dịch vụ,tiền lệ phí | F73: 5005246286
... A82: 5005186292 | B82: その他税金（製） | C82: Chi phí bằng tiền khác | D82: 公租公課 | E82: Thuế,phí công cộng | F82: 5005186292
A83: 5005196373 | B83: 試験研究用材料費 | C83: Chi phí dụng cụ sản xuất | D83: 試験研究費 | E83: Chi phí thử nghiệm,nghiên cứu | F83: 5005196373 | G83: 5005196373 | H83: 5005196373 | I83: 2月から追加する。
A84: 5005196277 | B84: 試験研究用役務費 | C84: Chi phi dịch vụ mua ngoài | D84: 試験研究費 | E84: Chi phí thử nghiệm,nghiên cứu | F84: 5005196277 | G84: 5005196277 | H84: 5005196277 | I84: 2月から追加する。
A85: 5005246291 | B85: 会議費（製） | C85: Chi phí bằng tiền khác | D85: 会費及び会議費 | E85: Chi phí cuộc họp | F85: 5005246291
A86: 5005246292 | B86: 雑費（製） | C86: Chi phí bằng tiền khác | D86: 雑費 | E86: Các loại chi phí bằng tiền khác | F86: 5005246292
A87: 5005246294 | B87: 開発費振替勘定（製） | C87: Chi phí bằng tiền khác | D87: 雑費 | E87: Các loại chi phí bằng tiền khác | F87: 5005246294 | I87: 2月から追加する→9/2015からｘから雑費になった
A88: 5005256291 | B88: 棚卸減耗費（製） | C88: Chi phí bằng tiền khác | D88: 棚卸減耗費 | E88: Chi phí hao hụt sau kiểm kê | F88: 5005256291
A89: 5101016174 | B89: 製商品仕入諸掛 | C89: Giá vốn hàng bán | D89: 仕入製商品費 | E89: Chi phí bán hàng | F89: 5101016174
A90: 5101016179 | B90: 製品品目外注加工費 | C90: Giá vốn hàng bán | D90: 外注加工費 | E90: Chi phí gia công ngoài | F90: 5101016179
A91: 5101016187 | B91: 製商品在庫廃棄損 | C91: Giá vốn hàng bán | D91: 雑損失 | E91: Tổn thất,lỗ khác | F91: 5101016187
A92: 5101016189 | B92: 金型製作収入 | C92: Doanh thu bán thành phẩm | D92: 雑収入 | E92: Thu nhập khác | F92: 5101016189 | I92: 2月から追加する。
A93: 6004046511 | B93: 雑給（販売） | C93: Chi phí nhân viên | D93: 雑給 | E93: Chi phí nhân công trực tiếp | H93: 6004046511
A94: 6003036412 | B94: 梱包材料費（販売） | C94: Chi phí vật liệu bao bì | D94: 荷造用品費 | E94: Chi phí NVL dùng đóng gói hàng | H94: 6003036412
A95: 6005016413 | B95: 消耗品費（販売） | C95: Chi phí dụng cụ đồ dùng | D95: 消耗品費 | E95: Chi phí hàng hóa tiêu hao | H95: 6005016413
A96: 6005016414 | B96: 消耗備品費（販売） | C96: Chi phí dụng cụ đồ dùng | D96: 消耗工具器具備品費 | E96: Chi phí sử dụng công cụ,đồ đạc | G96: 6005016414 | H96: 6005016414 | I96: 2017年1月追加。
A97: 6006016521 | B97: 減価償却費（販） 建物 | C97: Chi phí khấu hao TSCĐ | D97: 減価償却費 | E97: Chi phí khấu hao | H97: 6006016521
A98: 6006016522 | B98: 減価償却費（販） 機械装置 | C98: Chi phí khấu hao TSCĐ | D98: 減価償却費 | E98: Chi phí khấu hao | H98: 6006016522
A99: 6006016523 | B99: 減価償却費（販） 車輌運搬具 | C99: Chi phí khấu hao TSCĐ | D99: 減価償却費 | E99: Chi phí khấu hao | H99: 6006016523
A100: 6006016524 | B100: 減価償却費（販） 工具器具備品 | C100: Chi phí khấu hao TSCĐ | D100: 減価償却費 | E100: Chi phí khấu hao | H100: 6006016524
A101: 6006016525 | B101: 減価償却費（販） 構築物 | C101: Chi phí khấu hao TSCĐ | D101: 減価償却費 | E101: Chi phí khấu hao | H101: 6006016525
A102: 6006016526 | B102: 減価償却費（販） その他有形固定資産 | C102: Chi phí khấu hao TSCĐ | D102: 減価償却費 | E102: Chi phí khấu hao | H102: 6006016526
A103: 6006016527 | B103: 減価償却費（販） リース建物 | C103: Chi phí khấu hao TSCĐ | D103: 減価償却費 | E103: Chi phí khấu hao | H103: 6006016527
A104: 6006016528 | B104: 減価償却費（販） リース機械装置 | C104: Chi phí khấu hao TSCĐ | D104: 減価償却費 | E104: Chi phí khấu hao | H104: 6006016528
A105: 6006016529 | B105: 減価償却費（販） リース車輌運搬具 | C105: Chi phí khấu hao TSCĐ | D105: 減価償却費 | E105: Chi phí khấu hao | H105: 6006016529
A106: 6006016530 | B106: 減価償却費（販） リース工具器具備品 | C106: Chi phí khấu hao TSCĐ | D106: 減価償却費 | E106: Chi phí khấu hao | H106: 6006016530
A107: 6006016531 | B107: 減価償却費（販） リース構築物 | C107: Chi phí khấu hao TSCĐ | D107: 減価償却費 | E107: Chi phí khấu hao | H107: 6006016531
A108: 6006016532 | B108: 減価償却費（販） 土地使用権 | C108: Chi phí khấu hao TSCĐ | D108: 減価償却費 | E108: Chi phí khấu hao | H108: 6006016532
... A122: 6003036542 | B122: クーリエ費用（販売） | C122: Chi phí dịch vụ mua ngòai | D122: 荷造運賃 | E122: Chi phí vận chuyển hàng hóa | H122: 6003036542
A123: 6003036543 | B123: 輸出航空運賃（販売） | C123: Chi phí dịch vụ mua ngòai | D123: 荷造運賃 | E123: Chi phí vận chuyển hàng hóa | F123: 6003036543 | H123: 6003036543
A124: 6003036544 | B124: 輸出海上運賃（販売） | C124: Chi phí dịch vụ mua ngòai | D124: 荷造運賃 | E124: Chi phí vận chuyển hàng hóa | F124: 6003036544 | G124: 6003036544 | H124: 6003036544
A125: 6003036545 | B125: 保管延長費（販売） | C125: Chi phí dịch vụ mua ngòai | D125: 荷造運賃 | E125: Chi phí vận chuyển hàng hóa | H125: 6003036545
A126: 6003036546 | B126: 物流保険料（販売） | C126: Chi phí dịch vụ mua ngòai | D126: 荷造運賃 | E126: Chi phí vận chuyển hàng hóa | H126: 6003036546
A127: 6003036547 | B127: 梱包費用（販売） | C127: Chi phí dịch vụ mua ngòai | D127: 荷造運賃 | E127: Chi phí vận chuyển hàng hóa | H127: 6003036547
A128: 6003036548 | B128: 返品手数料（販売） | C128: Chi phí dịch vụ mua ngòai | D128: 荷造運賃 | E128: Chi phí vận chuyển hàng hóa | H128: 6003036548
A129: 6003036549 | B129: 保管料（販売） | C129: Chi phí dịch vụ mua ngòai | D129: 荷造運賃 | E129: Chi phí vận chuyển hàng hóa | H129: 6003036549
A130: 6003036550 | B130: オーバーナイト費（販売） | C130: Chi phí dịch vụ mua ngòai | D130: 荷造運賃 | E130: Chi phí vận chuyển hàng hóa | H130: 6003036550
A131: 6003036551 | B131: バンニング費（販売） | C131: Chi phí dịch vụ mua ngòai | D131: 荷造運賃 | E131: Chi phí vận chuyển hàng hóa | H131: 6003036551
A132: 6003036552 | B132: その他物流費（販売） | C132: Chi phí dịch vụ mua ngòai | D132: 荷造運賃 | E132: Chi phí vận chuyển hàng hóa | F132: 6003036552 | H132: 6003036552
A133: 6003036554 | B133: 外部倉庫 取扱手数料（販売） | C133: Chi phí dịch vụ mua ngòai | D133: 荷造運賃 | E133: Chi phí vận chuyển hàng hóa | F133: 6003036554 | G133: 6003036554 | H133: 6003036554 | I133: 2017年1月追加。
A134: 6003036555 | B134: 外部倉庫 保管料（販売） | C134: Chi phí dịch vụ mua ngòai | D134: 荷造運賃 | E134: Chi phí vận chuyển hàng hóa | F134: 6003036555 | G134: 6003036555 | H134: 6003036555 | I134: 2017年1月追加。
A135: 6003036556 | B135: 外部倉庫 輸送料（販売） | C135: Chi phí dịch vụ mua ngòai | D135: 荷造運賃 | E135: Chi phí vận chuyển hàng hóa | F135: 6003036556 | G135: 6003036556 | H135: 6003036556 | I135: 2017年1月追加。
...

Sheet 原価センタ
B1: 原価センタ | D1: 採算区分 | E1: 原価区分
A2: 1412000004 | B2: 機器製造1課 | C2: 01. | D2: 製造 | E2: 製造 | G2: V02XD800
A3: 1412000005 | B3: 機器製造2課 | C3: 02. | D3: 製造 | E3: 製造
A4: 1412000062 | B4: 機器製造管理課 | C4: 03. | D4: 部内間接 | E4: 製造
A5: 1412000034 | B5: トナー製造課 | C5: 04. | D5: 製造 | E5: 製造
A6: 1412000048 | B6: トナー生産技術課 | C6: 05. | D6: 部内間接 | E6: 製造
A7: 1412000055 | B7: トナー品質管理課 | C7: 06. | D7: 部内間接 | E7: 製造
A8: 1412000050 | B8: MD1課 | C8: 07. | D8: 製造 | E8: 製造
A9: 1412000077 | B9: MD2課 | C9: 08. | D9: 製造 | E9: 製造
A10: 1412000053 | B10: 工程品質管理1課 | C10: 09. | D10: 部内間接 | E10: 製造
A11: 1412000008 | B11: 生産管理課 | C11: 10. | D11: 部内間接 | E11: 製造
A12: 1412000010 | B12: 採算管理課 | C12: 11. | D12: 部外間接1 | E12: 製造
A13: 1412000054 | B13: マスター管理課 | C13: 12. | D13: 部外間接1 | E13: 製造
A14: 1412000036 | B14: 部品管理課 | C14: 13. | D14: 部内間接 | E14: 製造
... A58: 1412000099 | B58: MD4課 | C58: 65. | D58: 製造 | E58: 製造

Sheet 稼働日
A2: FY2026 | B2: 稼働日
A3: 4 | B3: 20
A4: 5 | B4: 19
A5: 6 | B5: 21
A6: 7 | B6: 23
A7: 8 | B7: 20
A8: 9 | B8: 19
A9: 10 | B9: 23
A10: 11 | B10: 20
A11: 12 | B11: 22
A12: 1 | B12: 20
A13: 2 | B13: 15
A14: 3 | B14: 20
