Workbook
Name WBS: 原価センタ!$G$2:$G$3

Sheet 採算表(USD)
B1: 組織名 | C1: ='採算表(VND)'!C1 -> MP FY2026_各予定 | N1: ='内訳ﾘｽﾄ(4～3月)'!B2 -> 25390
B2: ='採算表(VND)'!B2 -> EI2課
B4: 項目 ＼ 部門 | C4: ='採算表(VND)'!C4 -> 4 | D4: ='採算表(VND)'!D4 -> 5 | E4: ='採算表(VND)'!E4 -> 6 | F4: ='採算表(VND)'!F4 -> 7 | G4: ='採算表(VND)'!G4 -> 8 | H4: ='採算表(VND)'!H4 -> 9 | I4: ='採算表(VND)'!I4 -> 10 | J4: ='採算表(VND)'!J4 -> 11 | ... O4: ='採算表(VND)'!O4 -> 合計
B5: 総出荷 | C5: =C8+C9 -> 0 | D5: =D8+D9 -> 38768 | E5: =E8+E9 -> 32552 | F5: =F8+F9 -> 37632 | G5: =G8+G9 -> 37049.21 | H5: =H8+H9 -> 39508.74 | I5: =I8+I9 -> 38788.92 | J5: =J8+J9 -> 46165.54 | ... O5: =O8+O9 -> 426491.11
B6: 社外出荷 | C6: =ROUNDDOWN('採算表(VND)'!C6/$N$1,2) -> 0 | D6: =ROUNDDOWN('採算表(VND)'!D6/$N$1,2) -> 38768 | E6: =ROUNDDOWN('採算表(VND)'!E6/$N$1,2) -> 32552 | F6: =ROUNDDOWN('採算表(VND)'!F6/$N$1,2) -> 37632 | G6: =ROUNDDOWN('採算表(VND)'!G6/$N$1,2) -> 37049.21 | H6: =ROUNDDOWN('採算表(VND)'!H6/$N$1,2) -> 39508.74 | I6: =ROUNDDOWN('採算表(VND)'!I6/$N$1,2) -> 38788.92 | J6: =ROUNDDOWN('採算表(VND)'!J6/$N$1,2) -> 46165.54 | ... N6: =ROUNDDOWN('採算表(VND)'!N6/$N$1,2) -> 38294.13 | O6: =SUM(C6:N6) -> 426491.11
B7: 販売支援 | C7: =ROUNDDOWN('採算表(VND)'!C7/$N$1,2) -> 0 | D7: =ROUNDDOWN('採算表(VND)'!D7/$N$1,2) -> 0 | E7: =ROUNDDOWN('採算表(VND)'!E7/$N$1,2) -> 0 | F7: =ROUNDDOWN('採算表(VND)'!F7/$N$1,2) -> 0 | G7: =ROUNDDOWN('採算表(VND)'!G7/$N$1,2) -> 0 | H7: =ROUNDDOWN('採算表(VND)'!H7/$N$1,2) -> 0 | I7: =ROUNDDOWN('採算表(VND)'!I7/$N$1,2) -> 0 | J7: =ROUNDDOWN('採算表(VND)'!J7/$N$1,2) -> 0 | ... N7: =ROUNDDOWN('採算表(VND)'!N7/$N$1,2) -> 0 | O7: =SUM(C7:N7) -> 0
B8: 社外出荷合計 | C8: =C6+C7 -> 0 | D8: =D6+D7 -> 38768 | E8: =E6+E7 -> 32552 | F8: =F6+F7 -> 37632 | G8: =G6+G7 -> 37049.21 | H8: =H6+H7 -> 39508.74 | I8: =I6+I7 -> 38788.92 | J8: =J6+J7 -> 46165.54 | ... O8: =O6+O7 -> 426491.11
B9: 社内売 | C9: =ROUNDDOWN('採算表(VND)'!C9/$N$1,2) -> 0 | D9: =ROUNDDOWN('採算表(VND)'!D9/$N$1,2) -> 0 | E9: =ROUNDDOWN('採算表(VND)'!E9/$N$1,2) -> 0 | F9: =ROUNDDOWN('採算表(VND)'!F9/$N$1,2) -> 0 | G9: =ROUNDDOWN('採算表(VND)'!G9/$N$1,2) -> 0 | H9: =ROUNDDOWN('採算表(VND)'!H9/$N$1,2) -> 0 | I9: =ROUNDDOWN('採算表(VND)'!I9/$N$1,2) -> 0 | J9: =ROUNDDOWN('採算表(VND)'!J9/$N$1,2) -> 0 | ... N9: =ROUNDDOWN('採算表(VND)'!N9/$N$1,2) -> 0 | O9: =SUM(C9:N9) -> 0
B10: 社内買 | C10: =ROUNDDOWN('採算表(VND)'!C10/$N$1,2) -> 0 | D10: =ROUNDDOWN('採算表(VND)'!D10/$N$1,2) -> 0 | E10: =ROUNDDOWN('採算表(VND)'!E10/$N$1,2) -> 0 | F10: =ROUNDDOWN('採算表(VND)'!F10/$N$1,2) -> 0 | G10: =ROUNDDOWN('採算表(VND)'!G10/$N$1,2) -> 0 | H10: =ROUNDDOWN('採算表(VND)'!H10/$N$1,2) -> 0 | I10: =ROUNDDOWN('採算表(VND)'!I10/$N$1,2) -> 0 | J10: =ROUNDDOWN('採算表(VND)'!J10/$N$1,2) -> 0 | ... N10: =ROUNDDOWN('採算表(VND)'!N10/$N$1,2) -> 0 | O10: =SUM(C10:N10) -> 0
B12: 総生産 | C12: =C5-C10 -> 0 | D12: =D5-D10 -> 38768 | E12: =E5-E10 -> 32552 | F12: =F5-F10 -> 37632 | G12: =G5-G10 -> 37049.21 | H12: =H5-H10 -> 39508.74 | I12: =I5-I10 -> 38788.92 | J12: =J5-J10 -> 46165.54 | ... O12: =O5-O10 -> 426491.11
B13: 控除額 | C13: =SUM(C14:C65) -> 2051.12 | D13: =SUM(D14:D65) -> 3191.53 | E13: =SUM(E14:E65) -> 5474.08 | F13: =SUM(F14:F65) -> 2286.23 | G13: =SUM(G14:G65) -> 2585.7 | H13: =SUM(H14:H65) -> 5457.32 | I13: =SUM(I14:I65) -> 8865.34 | J13: =SUM(J14:J65) -> 1689.26 | ... O13: =SUM(O14:O65) -> 46140.44
B14: 材料費 | C14: =ROUNDUP('採算表(VND)'!C14/$N$1,2) -> 0 | D14: =ROUNDUP('採算表(VND)'!D14/$N$1,2) -> 0 | E14: =ROUNDUP('採算表(VND)'!E14/$N$1,2) -> 0 | F14: =ROUNDUP('採算表(VND)'!F14/$N$1,2) -> 0 | G14: =ROUNDUP('採算表(VND)'!G14/$N$1,2) -> 0 | H14: =ROUNDUP('採算表(VND)'!H14/$N$1,2) -> 0 | I14: =ROUNDUP('採算表(VND)'!I14/$N$1,2) -> 0 | J14: =ROUNDUP('採算表(VND)'!J14/$N$1,2) -> 0 | ... N14: =ROUNDUP('採算表(VND)'!N14/$N$1,2) -> 0 | O14: =SUM(C14:N14) -> 0
B15: 設計変更材料費 | C15: =ROUNDUP('採算表(VND)'!C15/$N$1,2) -> 0 | D15: =ROUNDUP('採算表(VND)'!D15/$N$1,2) -> 0 | E15: =ROUNDUP('採算表(VND)'!E15/$N$1,2) -> 0 | F15: =ROUNDUP('採算表(VND)'!F15/$N$1,2) -> 0 | G15: =ROUNDUP('採算表(VND)'!G15/$N$1,2) -> 0 | H15: =ROUNDUP('採算表(VND)'!H15/$N$1,2) -> 0 | I15: =ROUNDUP('採算表(VND)'!I15/$N$1,2) -> 0 | J15: =ROUNDUP('採算表(VND)'!J15/$N$1,2) -> 0 | ... N15: =ROUNDUP('採算表(VND)'!N15/$N$1,2) -> 0 | O15: =SUM(C15:N15) -> 0
B16: 仕掛仕損 | C16: =ROUNDUP('採算表(VND)'!C16/$N$1,2) -> 0 | D16: =ROUNDUP('採算表(VND)'!D16/$N$1,2) -> 0 | E16: =ROUNDUP('採算表(VND)'!E16/$N$1,2) -> 0 | F16: =ROUNDUP('採算表(VND)'!F16/$N$1,2) -> 0 | G16: =ROUNDUP('採算表(VND)'!G16/$N$1,2) -> 0 | H16: =ROUNDUP('採算表(VND)'!H16/$N$1,2) -> 0 | I16: =ROUNDUP('採算表(VND)'!I16/$N$1,2) -> 0 | J16: =ROUNDUP('採算表(VND)'!J16/$N$1,2) -> 0 | ... N16: =ROUNDUP('採算表(VND)'!N16/$N$1,2) -> 0 | O16: =SUM(C16:N16) -> 0
B17: 仕入製商品費 | C17: =ROUNDUP('採算表(VND)'!C17/$N$1,2) -> 0 | D17: =ROUNDUP('採算表(VND)'!D17/$N$1,2) -> 0 | E17: =ROUNDUP('採算表(VND)'!E17/$N$1,2) -> 0 | F17: =ROUNDUP('採算表(VND)'!F17/$N$1,2) -> 0 | G17: =ROUNDUP('採算表(VND)'!G17/$N$1,2) -> 0 | H17: =ROUNDUP('採算表(VND)'!H17/$N$1,2) -> 0 | I17: =ROUNDUP('採算表(VND)'!I17/$N$1,2) -> 0 | J17: =ROUNDUP('採算表(VND)'!J17/$N$1,2) -> 0 | ... N17: =ROUNDUP('採算表(VND)'!N17/$N$1,2) -> 0 | O17: =SUM(C17:N17) -> 0
B18: 内製品有償支給原価 | C18: =ROUNDUP('採算表(VND)'!C18/$N$1,2) -> 0 | D18: =ROUNDUP('採算表(VND)'!D18/$N$1,2) -> 0 | E18: =ROUNDUP('採算表(VND)'!E18/$N$1,2) -> 0 | F18: =ROUNDUP('採算表(VND)'!F18/$N$1,2) -> 0 | G18: =ROUNDUP('採算表(VND)'!G18/$N$1,2) -> 0 | H18: =ROUNDUP('採算表(VND)'!H18/$N$1,2) -> 0 | I18: =ROUNDUP('採算表(VND)'!I18/$N$1,2) -> 0 | J18: =ROUNDUP('採算表(VND)'!J18/$N$1,2) -> 0 | ... N18: =ROUNDUP('採算表(VND)'!N18/$N$1,2) -> 0 | O18: =SUM(C18:N18) -> 0
B19: 外注加工費 | C19: =ROUNDUP('採算表(VND)'!C19/$N$1,2) -> 0 | D19: =ROUNDUP('採算表(VND)'!D19/$N$1,2) -> 0 | E19: =ROUNDUP('採算表(VND)'!E19/$N$1,2) -> 0 | F19: =ROUNDUP('採算表(VND)'!F19/$N$1,2) -> 0 | G19: =ROUNDUP('採算表(VND)'!G19/$N$1,2) -> 0 | H19: =ROUNDUP('採算表(VND)'!H19/$N$1,2) -> 0 | I19: =ROUNDUP('採算表(VND)'!I19/$N$1,2) -> 0 | J19: =ROUNDUP('採算表(VND)'!J19/$N$1,2) -> 0 | ... N19: =ROUNDUP('採算表(VND)'!N19/$N$1,2) -> 0 | O19: =SUM(C19:N19) -> 0
B20: 減価償却費 | C20: =ROUNDUP('採算表(VND)'!C20/$N$1,2) -> 160.36 | D20: =ROUNDUP('採算表(VND)'!D20/$N$1,2) -> 160.36 | E20: =ROUNDUP('採算表(VND)'!E20/$N$1,2) -> 160.36 | F20: =ROUNDUP('採算表(VND)'!F20/$N$1,2) -> 160.36 | G20: =ROUNDUP('採算表(VND)'!G20/$N$1,2) -> 160.36 | H20: =ROUNDUP('採算表(VND)'!H20/$N$1,2) -> 160.36 | I20: =ROUNDUP('採算表(VND)'!I20/$N$1,2) -> 160.36 | J20: =ROUNDUP('採算表(VND)'!J20/$N$1,2) -> 160.36 | ... N20: =ROUNDUP('採算表(VND)'!N20/$N$1,2) -> 160.36 | O20: =SUM(C20:N20) -> 1924.32
B21: 金型償却費 | C21: =ROUNDUP('採算表(VND)'!C21/$N$1,2) -> 0 | D21: =ROUNDUP('採算表(VND)'!D21/$N$1,2) -> 0 | E21: =ROUNDUP('採算表(VND)'!E21/$N$1,2) -> 0 | F21: =ROUNDUP('採算表(VND)'!F21/$N$1,2) -> 0 | G21: =ROUNDUP('採算表(VND)'!G21/$N$1,2) -> 0 | H21: =ROUNDUP('採算表(VND)'!H21/$N$1,2) -> 0 | I21: =ROUNDUP('採算表(VND)'!I21/$N$1,2) -> 0 | J21: =ROUNDUP('採算表(VND)'!J21/$N$1,2) -> 0 | ... N21: =ROUNDUP('採算表(VND)'!N21/$N$1,2) -> 0 | O21: =SUM(C21:N21) -> 0
B22: 賃借料 | C22: =ROUNDUP('採算表(VND)'!C22/$N$1,2) -> 0 | D22: =ROUNDUP('採算表(VND)'!D22/$N$1,2) -> 0 | E22: =ROUNDUP('採算表(VND)'!E22/$N$1,2) -> 0 | F22: =ROUNDUP('採算表(VND)'!F22/$N$1,2) -> 0 | G22: =ROUNDUP('採算表(VND)'!G22/$N$1,2) -> 0 | H22: =ROUNDUP('採算表(VND)'!H22/$N$1,2) -> 0 | I22: =ROUNDUP('採算表(VND)'!I22/$N$1,2) -> 0 | J22: =ROUNDUP('採算表(VND)'!J22/$N$1,2) -> 0 | ... N22: =ROUNDUP('採算表(VND)'!N22/$N$1,2) -> 0 | O22: =SUM(C22:N22) -> 0
B23: 保険料 | C23: =ROUNDUP('採算表(VND)'!C23/$N$1,2) -> 0 | D23: =ROUNDUP('採算表(VND)'!D23/$N$1,2) -> 0 | E23: =ROUNDUP('採算表(VND)'!E23/$N$1,2) -> 0 | F23: =ROUNDUP('採算表(VND)'!F23/$N$1,2) -> 0 | G23: =ROUNDUP('採算表(VND)'!G23/$N$1,2) -> 0 | H23: =ROUNDUP('採算表(VND)'!H23/$N$1,2) -> 0 | I23: =ROUNDUP('採算表(VND)'!I23/$N$1,2) -> 0 | J23: =ROUNDUP('採算表(VND)'!J23/$N$1,2) -> 0 | ... N23: =ROUNDUP('採算表(VND)'!N23/$N$1,2) -> 0 | O23: =SUM(C23:N23) -> 0
B24: 設計委託費 | C24: =ROUNDUP('採算表(VND)'!C24/$N$1,2) -> 0 | D24: =ROUNDUP('採算表(VND)'!D24/$N$1,2) -> 0 | E24: =ROUNDUP('採算表(VND)'!E24/$N$1,2) -> 0 | F24: =ROUNDUP('採算表(VND)'!F24/$N$1,2) -> 0 | G24: =ROUNDUP('採算表(VND)'!G24/$N$1,2) -> 0 | H24: =ROUNDUP('採算表(VND)'!H24/$N$1,2) -> 0 | I24: =ROUNDUP('採算表(VND)'!I24/$N$1,2) -> 0 | J24: =ROUNDUP('採算表(VND)'!J24/$N$1,2) -> 0 | ... N24: =ROUNDUP('採算表(VND)'!N24/$N$1,2) -> 0 | O24: =SUM(C24:N24) -> 0
B25: 消耗品費 | C25: =ROUNDUP('採算表(VND)'!C25/$N$1,2) -> 7.68 | D25: =ROUNDUP('採算表(VND)'!D25/$N$1,2) -> 7.68 | E25: =ROUNDUP('採算表(VND)'!E25/$N$1,2) -> 7.68 | F25: =ROUNDUP('採算表(VND)'!F25/$N$1,2) -> 7.68 | G25: =ROUNDUP('採算表(VND)'!G25/$N$1,2) -> 7.68 | H25: =ROUNDUP('採算表(VND)'!H25/$N$1,2) -> 8.45 | I25: =ROUNDUP('採算表(VND)'!I25/$N$1,2) -> 8.45 | J25: =ROUNDUP('採算表(VND)'!J25/$N$1,2) -> 8.45 | ... N25: =ROUNDUP('採算表(VND)'!N25/$N$1,2) -> 8.45 | O25: =SUM(C25:N25) -> 97.55
... B65: 本社機構経費 | C65: =ROUNDUP('採算表(VND)'!C65/$N$1,2) -> 0 | D65: =ROUNDUP('採算表(VND)'!D65/$N$1,2) -> 0 | E65: =ROUNDUP('採算表(VND)'!E65/$N$1,2) -> 0 | F65: =ROUNDUP('採算表(VND)'!F65/$N$1,2) -> 0 | G65: =ROUNDUP('採算表(VND)'!G65/$N$1,2) -> 0 | H65: =ROUNDUP('採算表(VND)'!H65/$N$1,2) -> 0 | I65: =ROUNDUP('採算表(VND)'!I65/$N$1,2) -> 0 | J65: =ROUNDUP('採算表(VND)'!J65/$N$1,2) -> 0 | ... N65: =ROUNDUP('採算表(VND)'!N65/$N$1,2) -> 0 | O65: =SUM(C65:N65) -> 0
B66: 差引収益 | C66: =C12-C13 -> -2051.12 | D66: =IF(ISBLANK(D4),"",D12-D13) -> 35576.47 | E66: =IF(ISBLANK(E4),"",E12-E13) -> 27077.92 | F66: =IF(ISBLANK(F4),"",F12-F13) -> 35345.77 | G66: =IF(ISBLANK(G4),"",G12-G13) -> 34463.51 | H66: =IF(ISBLANK(H4),"",H12-H13) -> 34051.42 | I66: =IF(ISBLANK(I4),"",I12-I13) -> 29923.58 | J66: =IF(ISBLANK(J4),"",J12-J13) -> 44476.28 | K66: =IF(ISBLANK(K4),"",K12-K13) -> 37360.65 | ... O66: =IF(ISBLANK(O4),"",O12-O13) -> 380350.67
B67: 総時間 | C67: =C73+C79 -> 1547.5 | D67: =IF(ISBLANK(D4),"",D73+D79) -> 1476.5 | E67: =IF(ISBLANK(E4),"",E73+E79) -> 1622.25 | F67: =IF(ISBLANK(F4),"",F73+F79) -> 1769.25 | G67: =IF(ISBLANK(G4),"",G73+G79) -> 1549.5 | H67: =IF(ISBLANK(H4),"",H73+H79) -> 1637 | I67: =IF(ISBLANK(I4),"",I73+I79) -> 1965.75 | J67: =IF(ISBLANK(J4),"",J73+J79) -> 1721.25 | K67: =IF(ISBLANK(K4),"",K73+K79) -> 1885 | ... O67: =IF(ISBLANK(O4),"",O73+O79) -> 19876.5
B68: 直接部門 | C68: ='採算表(VND)'!C68 -> 1326 | D68: ='採算表(VND)'!D68 -> 1258 | E68: ='採算表(VND)'!E68 -> 1394 | F68: ='採算表(VND)'!F68 -> 1530 | G68: ='採算表(VND)'!G68 -> 1326 | H68: ='採算表(VND)'!H68 -> 1419.5 | I68: ='採算表(VND)'!I68 -> 1725.5 | J68: ='採算表(VND)'!J68 -> 1496 | ... N68: ='採算表(VND)'!N68 -> 1496 | O68: =SUM(C68:N68) -> 17187
B69: 部内間接部門 | C69: ='採算表(VND)'!C69 -> 0 | D69: ='採算表(VND)'!D69 -> 0 | E69: ='採算表(VND)'!E69 -> 0 | F69: ='採算表(VND)'!F69 -> 0 | G69: ='採算表(VND)'!G69 -> 0 | H69: ='採算表(VND)'!H69 -> 0 | I69: ='採算表(VND)'!I69 -> 0 | J69: ='採算表(VND)'!J69 -> 0 | ... N69: ='採算表(VND)'!N69 -> 0 | O69: =SUM(C69:N69) -> 0
B70: 部外間接部門1 | C70: ='採算表(VND)'!C70 -> 6.75 | D70: ='採算表(VND)'!D70 -> 7 | E70: ='採算表(VND)'!E70 -> 7.75 | F70: ='採算表(VND)'!F70 -> 8.25 | G70: ='採算表(VND)'!G70 -> 7 | H70: ='採算表(VND)'!H70 -> 6.5 | I70: ='採算表(VND)'!I70 -> 8.25 | J70: ='採算表(VND)'!J70 -> 7.25 | ... N70: ='採算表(VND)'!N70 -> 7.5 | O70: =SUM(C70:N70) -> 87.25
B71: 部外間接部門2 | C71: ='採算表(VND)'!C71 -> 12.75 | D71: ='採算表(VND)'!D71 -> 12.25 | E71: ='採算表(VND)'!E71 -> 14 | F71: ='採算表(VND)'!F71 -> 15.5 | G71: ='採算表(VND)'!G71 -> 13 | H71: ='採算表(VND)'!H71 -> 13 | I71: ='採算表(VND)'!I71 -> 16.25 | J71: ='採算表(VND)'!J71 -> 14 | ... N71: ='採算表(VND)'!N71 -> 14 | O71: =SUM(C71:N71) -> 165.25
B72: 工場間接部門 | C72: ='採算表(VND)'!C72 -> 57 | D72: ='採算表(VND)'!D72 -> 56.5 | E72: ='採算表(VND)'!E72 -> 60 | F72: ='採算表(VND)'!F72 -> 64.75 | G72: ='採算表(VND)'!G72 -> 59 | H72: ='採算表(VND)'!H72 -> 54.75 | I72: ='採算表(VND)'!I72 -> 65 | J72: ='採算表(VND)'!J72 -> 59.25 | ... N72: ='採算表(VND)'!N72 -> 60.5 | O72: =SUM(C72:N72) -> 706
B73: 定時間合計 | C73: =SUM(C68:C72) -> 1402.5 | D73: =IF(ISBLANK(D4),"",SUM(D68:D72)) -> 1333.75 | E73: =IF(ISBLANK(E4),"",SUM(E68:E72)) -> 1475.75 | F73: =IF(ISBLANK(F4),"",SUM(F68:F72)) -> 1618.5 | G73: =IF(ISBLANK(G4),"",SUM(G68:G72)) -> 1405 | H73: =IF(ISBLANK(H4),"",SUM(H68:H72)) -> 1493.75 | I73: =IF(ISBLANK(I4),"",SUM(I68:I72)) -> 1815 | J73: =IF(ISBLANK(J4),"",SUM(J68:J72)) -> 1576.5 | K73: =IF(ISBLANK(K4),"",SUM(K68:K72)) -> 1736.25 | ... O73: =IF(ISBLANK(O4),"",SUM(O68:O72)) -> 18145.5
B74: 直接部門 | C74: ='採算表(VND)'!C74 -> 140 | D74: ='採算表(VND)'!D74 -> 138 | E74: ='採算表(VND)'!E74 -> 142 | F74: ='採算表(VND)'!F74 -> 146 | G74: ='採算表(VND)'!G74 -> 140 | H74: ='採算表(VND)'!H74 -> 138 | I74: ='採算表(VND)'!I74 -> 146 | J74: ='採算表(VND)'!J74 -> 140 | ... N74: ='採算表(VND)'!N74 -> 140 | O74: =SUM(C74:N74) -> 1674
B75: 部内間接部門 | C75: ='採算表(VND)'!C75 -> 0 | D75: ='採算表(VND)'!D75 -> 0 | E75: ='採算表(VND)'!E75 -> 0 | F75: ='採算表(VND)'!F75 -> 0 | G75: ='採算表(VND)'!G75 -> 0 | H75: ='採算表(VND)'!H75 -> 0 | I75: ='採算表(VND)'!I75 -> 0 | J75: ='採算表(VND)'!J75 -> 0 | ... N75: ='採算表(VND)'!N75 -> 0 | O75: =SUM(C75:N75) -> 0
B76: 部外間接部門1 | C76: ='採算表(VND)'!C76 -> 0.5 | D76: ='採算表(VND)'!D76 -> 0.5 | E76: ='採算表(VND)'!E76 -> 0.5 | F76: ='採算表(VND)'!F76 -> 0.5 | G76: ='採算表(VND)'!G76 -> 0.5 | H76: ='採算表(VND)'!H76 -> 0.5 | I76: ='採算表(VND)'!I76 -> 0.5 | J76: ='採算表(VND)'!J76 -> 0.5 | ... N76: ='採算表(VND)'!N76 -> 0.5 | O76: =SUM(C76:N76) -> 5.75
B77: 部外間接部門2 | C77: ='採算表(VND)'!C77 -> 1.25 | D77: ='採算表(VND)'!D77 -> 1 | E77: ='採算表(VND)'!E77 -> 1.25 | F77: ='採算表(VND)'!F77 -> 1.25 | G77: ='採算表(VND)'!G77 -> 1.25 | H77: ='採算表(VND)'!H77 -> 1 | I77: ='採算表(VND)'!I77 -> 1.25 | J77: ='採算表(VND)'!J77 -> 1.25 | ... N77: ='採算表(VND)'!N77 -> 1.5 | O77: =SUM(C77:N77) -> 14.25
B78: 工場間接部門 | C78: ='採算表(VND)'!C78 -> 3.25 | D78: ='採算表(VND)'!D78 -> 3.25 | E78: ='採算表(VND)'!E78 -> 2.75 | F78: ='採算表(VND)'!F78 -> 3 | G78: ='採算表(VND)'!G78 -> 2.75 | H78: ='採算表(VND)'!H78 -> 3.75 | I78: ='採算表(VND)'!I78 -> 3 | J78: ='採算表(VND)'!J78 -> 3 | ... N78: ='採算表(VND)'!N78 -> 2.75 | O78: =SUM(C78:N78) -> 37
B79: 残業時間合計 | C79: =SUM(C74:C78) -> 145 | D79: =IF(ISBLANK(D4),"",SUM(D74:D78)) -> 142.75 | E79: =IF(ISBLANK(E4),"",SUM(E74:E78)) -> 146.5 | F79: =IF(ISBLANK(F4),"",SUM(F74:F78)) -> 150.75 | G79: =IF(ISBLANK(G4),"",SUM(G74:G78)) -> 144.5 | H79: =IF(ISBLANK(H4),"",SUM(H74:H78)) -> 143.25 | I79: =IF(ISBLANK(I4),"",SUM(I74:I78)) -> 150.75 | J79: =IF(ISBLANK(J4),"",SUM(J74:J78)) -> 144.75 | K79: =IF(ISBLANK(K4),"",SUM(K74:K78)) -> 148.75 | ... O79: =IF(ISBLANK(O4),"",SUM(O74:O78)) -> 1731
B80: 当月時間当り | C80: =IFERROR(ROUNDDOWN(C66/C67,0),0) -> -1 | D80: =IFERROR(ROUNDDOWN(D66/D67,0),0) -> 24 | E80: =IFERROR(ROUNDDOWN(E66/E67,0),0) -> 16 | F80: =IFERROR(ROUNDDOWN(F66/F67,0),0) -> 19 | G80: =IFERROR(ROUNDDOWN(G66/G67,0),0) -> 22 | H80: =IFERROR(ROUNDDOWN(H66/H67,0),0) -> 20 | I80: =IFERROR(ROUNDDOWN(I66/I67,0),0) -> 15 | J80: =IFERROR(ROUNDDOWN(J66/J67,0),0) -> 25 | ... O80: =IFERROR(ROUNDDOWN(O66/O67,0),0) -> 19
B81: 時間当り生産高 | C81: =IFERROR(ROUNDDOWN(C12/C67,0),0) -> 0 | D81: =IFERROR(ROUNDDOWN(D12/D67,0),0) -> 26 | E81: =IFERROR(ROUNDDOWN(E12/E67,0),0) -> 20 | F81: =IFERROR(ROUNDDOWN(F12/F67,0),0) -> 21 | G81: =IFERROR(ROUNDDOWN(G12/G67,0),0) -> 23 | H81: =IFERROR(ROUNDDOWN(H12/H67,0),0) -> 24 | I81: =IFERROR(ROUNDDOWN(I12/I67,0),0) -> 19 | J81: =IFERROR(ROUNDDOWN(J12/J67,0),0) -> 26 | ... O81: =IFERROR(ROUNDDOWN(O12/O67,0),0) -> 21
B86: ■人員
B87: 出向社員(人) | C87: ='採算表(VND)'!C87 -> 1 | D87: ='採算表(VND)'!D87 -> 1 | E87: ='採算表(VND)'!E87 -> 1 | F87: ='採算表(VND)'!F87 -> 1 | G87: ='採算表(VND)'!G87 -> 1 | H87: ='採算表(VND)'!H87 -> 1 | I87: ='採算表(VND)'!I87 -> 1 | J87: ='採算表(VND)'!J87 -> 1 | ... N87: ='採算表(VND)'!N87 -> 1 | O87: =SUM(C87:N87) -> 12
B88: ローカル社員(人) | C88: ='採算表(VND)'!C88 -> 7 | D88: ='採算表(VND)'!D88 -> 7 | E88: ='採算表(VND)'!E88 -> 7 | F88: ='採算表(VND)'!F88 -> 7 | G88: ='採算表(VND)'!G88 -> 7 | H88: ='採算表(VND)'!H88 -> 8 | I88: ='採算表(VND)'!I88 -> 8 | J88: ='採算表(VND)'!J88 -> 8 | ... N88: ='採算表(VND)'!N88 -> 8 | O88: =SUM(C88:N88) -> 91
B89: 人員計 | C89: =C87+C88 -> 8 | D89: =D87+D88 -> 8 | E89: =E87+E88 -> 8 | F89: =F87+F88 -> 8 | G89: =G87+G88 -> 8 | H89: =H87+H88 -> 9 | I89: =I87+I88 -> 9 | J89: =J87+J88 -> 9 | ... O89: =O87+O88 -> 103
B91: ■定時間
B92: 出向社員定時 | C92: ='採算表(VND)'!C92 -> 170 | D92: ='採算表(VND)'!D92 -> 161.5 | E92: ='採算表(VND)'!E92 -> 178.5 | F92: ='採算表(VND)'!F92 -> 195.5 | G92: ='採算表(VND)'!G92 -> 170 | H92: ='採算表(VND)'!H92 -> 161.5 | I92: ='採算表(VND)'!I92 -> 195.5 | J92: ='採算表(VND)'!J92 -> 170 | ... N92: ='採算表(VND)'!N92 -> 170 | O92: =SUM(C92:N92) -> 2014.5
B93: ローカル社員定時 | C93: ='採算表(VND)'!C93 -> 1156 | D93: ='採算表(VND)'!D93 -> 1096.5 | E93: ='採算表(VND)'!E93 -> 1215.5 | F93: ='採算表(VND)'!F93 -> 1334.5 | G93: ='採算表(VND)'!G93 -> 1156 | H93: ='採算表(VND)'!H93 -> 1258 | I93: ='採算表(VND)'!I93 -> 1530 | J93: ='採算表(VND)'!J93 -> 1326 | ... N93: ='採算表(VND)'!N93 -> 1326 | O93: =SUM(C93:N93) -> 15172.5
B94: 人員計 | C94: =C92+C93 -> 1326 | D94: =D92+D93 -> 1258 | E94: =E92+E93 -> 1394 | F94: =F92+F93 -> 1530 | G94: =G92+G93 -> 1326 | H94: =H92+H93 -> 1419.5 | I94: =I92+I93 -> 1725.5 | J94: =J92+J93 -> 1496 | ... O94: =O92+O93 -> 17187
B96: ■残業時間
B97: 出向社員残業 | C97: ='採算表(VND)'!C97 -> 40 | D97: ='採算表(VND)'!D97 -> 38 | E97: ='採算表(VND)'!E97 -> 42 | F97: ='採算表(VND)'!F97 -> 46 | G97: ='採算表(VND)'!G97 -> 40 | H97: ='採算表(VND)'!H97 -> 38 | I97: ='採算表(VND)'!I97 -> 46 | J97: ='採算表(VND)'!J97 -> 40 | ... N97: ='採算表(VND)'!N97 -> 40 | O97: =SUM(C97:N97) -> 474
B98: ローカル社員残業 | C98: ='採算表(VND)'!C98 -> 100 | D98: ='採算表(VND)'!D98 -> 100 | E98: ='採算表(VND)'!E98 -> 100 | F98: ='採算表(VND)'!F98 -> 100 | G98: ='採算表(VND)'!G98 -> 100 | H98: ='採算表(VND)'!H98 -> 100 | I98: ='採算表(VND)'!I98 -> 100 | J98: ='採算表(VND)'!J98 -> 100 | ... N98: ='採算表(VND)'!N98 -> 100 | O98: =SUM(C98:N98) -> 1200
B99: 人員計 | C99: =C97+C98 -> 140 | D99: =D97+D98 -> 138 | E99: =E97+E98 -> 142 | F99: =F97+F98 -> 146 | G99: =G97+G98 -> 140 | H99: =H97+H98 -> 138 | I99: =I97+I98 -> 146 | J99: =J97+J98 -> 140 | ... O99: =O97+O98 -> 1674

Sheet 採算表(VND)
B1: 組織名 | C1: ='内訳ﾘｽﾄ(4～3月)'!A1 -> MP FY2026_各予定
B2: ='内訳ﾘｽﾄ(4～3月)'!C5 -> EI2課
C3: 2 | D3: 3 | E3: 4 | F3: 5 | G3: 6 | H3: 7 | I3: 8 | J3: 9 | K3: 10 | L3: 11 | M3: 12 | N3: 13
B4: 項目 ＼ 部門 | C4: ='内訳ﾘｽﾄ(4～3月)'!F4 -> 4 | D4: 5 | E4: 6 | F4: 7 | G4: 8 | H4: 9 | I4: 10 | J4: 11 | K4: 12 | L4: 1 | M4: 2 | N4: 3 | O4: 合計
B5: 総出荷 | C5: =C8+C9 -> 0 | D5: =D8+D9 -> 984319520 | E5: =E8+E9 -> 826495280 | F5: =F8+F9 -> 955476480 | G5: =G8+G9 -> 940679442 | H5: =H8+H9 -> 1003126909 | I5: =I8+I9 -> 984850679 | J5: =J8+J9 -> 1172143061 | ... O5: =O8+O9 -> 10828609286
B6: 社外出荷 | C6: =SUMIF('内訳ﾘｽﾄ(4～3月)'!$D$26:$D$1000,'採算表(VND)'!$B6,'内訳ﾘｽﾄ(4～3月)'!F$26:F$1000) -> 0 | D6: =SUMIF('内訳ﾘｽﾄ(4～3月)'!$D$26:$D$1000,'採算表(VND)'!$B6,'内訳ﾘｽﾄ(4～3月)'!G$26:G$1000) -> 984319520 | E6: =SUMIF('内訳ﾘｽﾄ(4～3月)'!$D$26:$D$1000,'採算表(VND)'!$B6,'内訳ﾘｽﾄ(4～3月)'!H$26:H$1000) -> 826495280 | F6: =SUMIF('内訳ﾘｽﾄ(4～3月)'!$D$26:$D$1000,'採算表(VND)'!$B6,'内訳ﾘｽﾄ(4～3月)'!I$26:I$1000) -> 955476480 | G6: =SUMIF('内訳ﾘｽﾄ(4～3月)'!$D$26:$D$1000,'採算表(VND)'!$B6,'内訳ﾘｽﾄ(4～3月)'!J$26:J$1000) -> 940679442 | H6: =SUMIF('内訳ﾘｽﾄ(4～3月)'!$D$26:$D$1000,'採算表(VND)'!$B6,'内訳ﾘｽﾄ(4～3月)'!K$26:K$1000) -> 1003126909 | I6: =SUMIF('内訳ﾘｽﾄ(4～3月)'!$D$26:$D$1000,'採算表(VND)'!$B6,'内訳ﾘｽﾄ(4～3月)'!L$26:L$1000) -> 984850679 | J6: =SUMIF('内訳ﾘｽﾄ(4～3月)'!$D$26:$D$1000,'採算表(VND)'!$B6,'内訳ﾘｽﾄ(4～3月)'!M$26:M$1000) -> 1172143061 | ... N6: =SUMIF('内訳ﾘｽﾄ(4～3月)'!$D$26:$D$1000,'採算表(VND)'!$B6,'内訳ﾘｽﾄ(4～3月)'!Q$26:Q$1000) -> 972287961 | O6: =SUMIF('内訳ﾘｽﾄ(4～3月)'!$D$26:$D$799,'採算表(VND)'!$B6,'内訳ﾘｽﾄ(4～3月)'!R$26:R$799) -> 10828609286
B7: 販売支援 | C7: =SUMIF('内訳ﾘｽﾄ(4～3月)'!$D$26:$D$1000,'採算表(VND)'!$B7,'内訳ﾘｽﾄ(4～3月)'!F$26:F$1000) -> 0 | D7: =SUMIF('内訳ﾘｽﾄ(4～3月)'!$D$26:$D$1000,'採算表(VND)'!$B7,'内訳ﾘｽﾄ(4～3月)'!G$26:G$1000) -> 0 | E7: =SUMIF('内訳ﾘｽﾄ(4～3月)'!$D$26:$D$1000,'採算表(VND)'!$B7,'内訳ﾘｽﾄ(4～3月)'!H$26:H$1000) -> 0 | F7: =SUMIF('内訳ﾘｽﾄ(4～3月)'!$D$26:$D$1000,'採算表(VND)'!$B7,'内訳ﾘｽﾄ(4～3月)'!I$26:I$1000) -> 0 | G7: =SUMIF('内訳ﾘｽﾄ(4～3月)'!$D$26:$D$1000,'採算表(VND)'!$B7,'内訳ﾘｽﾄ(4～3月)'!J$26:J$1000) -> 0 | H7: =SUMIF('内訳ﾘｽﾄ(4～3月)'!$D$26:$D$1000,'採算表(VND)'!$B7,'内訳ﾘｽﾄ(4～3月)'!K$26:K$1000) -> 0 | I7: =SUMIF('内訳ﾘｽﾄ(4～3月)'!$D$26:$D$1000,'採算表(VND)'!$B7,'内訳ﾘｽﾄ(4～3月)'!L$26:L$1000) -> 0 | J7: =SUMIF('内訳ﾘｽﾄ(4～3月)'!$D$26:$D$1000,'採算表(VND)'!$B7,'内訳ﾘｽﾄ(4～3月)'!M$26:M$1000) -> 0 | ... N7: =SUMIF('内訳ﾘｽﾄ(4～3月)'!$D$26:$D$1000,'採算表(VND)'!$B7,'内訳ﾘｽﾄ(4～3月)'!Q$26:Q$1000) -> 0 | O7: =SUMIF('内訳ﾘｽﾄ(4～3月)'!$D$26:$D$799,'採算表(VND)'!$B7,'内訳ﾘｽﾄ(4～3月)'!R$26:R$799) -> 0
B8: 社外出荷合計 | C8: =C6+C7 -> 0 | D8: =D6+D7 -> 984319520 | E8: =E6+E7 -> 826495280 | F8: =F6+F7 -> 955476480 | G8: =G6+G7 -> 940679442 | H8: =H6+H7 -> 1003126909 | I8: =I6+I7 -> 984850679 | J8: =J6+J7 -> 1172143061 | ... O8: =O6+O7 -> 10828609286
B9: 社内売 | C9: =SUMIF('内訳ﾘｽﾄ(4～3月)'!$D$26:$D$1000,'採算表(VND)'!$B9,'内訳ﾘｽﾄ(4～3月)'!F$26:F$1000) -> 0 | D9: =SUMIF('内訳ﾘｽﾄ(4～3月)'!$D$26:$D$1000,'採算表(VND)'!$B9,'内訳ﾘｽﾄ(4～3月)'!G$26:G$1000) -> 0 | E9: =SUMIF('内訳ﾘｽﾄ(4～3月)'!$D$26:$D$1000,'採算表(VND)'!$B9,'内訳ﾘｽﾄ(4～3月)'!H$26:H$1000) -> 0 | F9: =SUMIF('内訳ﾘｽﾄ(4～3月)'!$D$26:$D$1000,'採算表(VND)'!$B9,'内訳ﾘｽﾄ(4～3月)'!I$26:I$1000) -> 0 | G9: =SUMIF('内訳ﾘｽﾄ(4～3月)'!$D$26:$D$1000,'採算表(VND)'!$B9,'内訳ﾘｽﾄ(4～3月)'!J$26:J$1000) -> 0 | H9: =SUMIF('内訳ﾘｽﾄ(4～3月)'!$D$26:$D$1000,'採算表(VND)'!$B9,'内訳ﾘｽﾄ(4～3月)'!K$26:K$1000) -> 0 | I9: =SUMIF('内訳ﾘｽﾄ(4～3月)'!$D$26:$D$1000,'採算表(VND)'!$B9,'内訳ﾘｽﾄ(4～3月)'!L$26:L$1000) -> 0 | J9: =SUMIF('内訳ﾘｽﾄ(4～3月)'!$D$26:$D$1000,'採算表(VND)'!$B9,'内訳ﾘｽﾄ(4～3月)'!M$26:M$1000) -> 0 | ... N9: =SUMIF('内訳ﾘｽﾄ(4～3月)'!$D$26:$D$1000,'採算表(VND)'!$B9,'内訳ﾘｽﾄ(4～3月)'!Q$26:Q$1000) -> 0 | O9: =SUMIF('内訳ﾘｽﾄ(4～3月)'!$D$26:$D$799,'採算表(VND)'!$B9,'内訳ﾘｽﾄ(4～3月)'!R$26:R$799) -> 0
B10: 社内買 | C10: =SUMIF('内訳ﾘｽﾄ(4～3月)'!$D$26:$D$1000,'採算表(VND)'!$B10,'内訳ﾘｽﾄ(4～3月)'!F$26:F$1000) -> 0 | D10: =SUMIF('内訳ﾘｽﾄ(4～3月)'!$D$26:$D$1000,'採算表(VND)'!$B10,'内訳ﾘｽﾄ(4～3月)'!G$26:G$1000) -> 0 | E10: =SUMIF('内訳ﾘｽﾄ(4～3月)'!$D$26:$D$1000,'採算表(VND)'!$B10,'内訳ﾘｽﾄ(4～3月)'!H$26:H$1000) -> 0 | F10: =SUMIF('内訳ﾘｽﾄ(4～3月)'!$D$26:$D$1000,'採算表(VND)'!$B10,'内訳ﾘｽﾄ(4～3月)'!I$26:I$1000) -> 0 | G10: =SUMIF('内訳ﾘｽﾄ(4～3月)'!$D$26:$D$1000,'採算表(VND)'!$B10,'内訳ﾘｽﾄ(4～3月)'!J$26:J$1000) -> 0 | H10: =SUMIF('内訳ﾘｽﾄ(4～3月)'!$D$26:$D$1000,'採算表(VND)'!$B10,'内訳ﾘｽﾄ(4～3月)'!K$26:K$1000) -> 0 | I10: =SUMIF('内訳ﾘｽﾄ(4～3月)'!$D$26:$D$1000,'採算表(VND)'!$B10,'内訳ﾘｽﾄ(4～3月)'!L$26:L$1000) -> 0 | J10: =SUMIF('内訳ﾘｽﾄ(4～3月)'!$D$26:$D$1000,'採算表(VND)'!$B10,'内訳ﾘｽﾄ(4～3月)'!M$26:M$1000) -> 0 | ... N10: =SUMIF('内訳ﾘｽﾄ(4～3月)'!$D$26:$D$1000,'採算表(VND)'!$B10,'内訳ﾘｽﾄ(4～3月)'!Q$26:Q$1000) -> 0 | O10: =SUMIF('内訳ﾘｽﾄ(4～3月)'!$D$26:$D$799,'採算表(VND)'!$B10,'内訳ﾘｽﾄ(4～3月)'!R$26:R$799) -> 0
B12: 総生産 | C12: =C5-C10 -> 0 | D12: =D5-D10 -> 984319520 | E12: =E5-E10 -> 826495280 | F12: =F5-F10 -> 955476480 | G12: =G5-G10 -> 940679442 | H12: =H5-H10 -> 1003126909 | I12: =I5-I10 -> 984850679 | J12: =J5-J10 -> 1172143061 | ... O12: =O5-O10 -> 10828609286
B13: 控除額 | C13: =SUM(C14:C65) -> 52076543 | D13: =SUM(D14:D65) -> 81031255 | E13: =SUM(E14:E65) -> 138985384 | F13: =SUM(F14:F65) -> 58046167 | G13: =SUM(G14:G65) -> 65649208 | H13: =SUM(H14:H65) -> 138559879 | I13: =SUM(I14:I65) -> 225089418 | J13: =SUM(J14:J65) -> 42889147 | ... O13: =SUM(O14:O65) -> 1171488828
B14: 材料費 | C14: =SUMIF('内訳ﾘｽﾄ(4～3月)'!$D$26:$D$1000,$B14,'内訳ﾘｽﾄ(4～3月)'!F$26:F$1000) -> 0 | D14: =SUMIF('内訳ﾘｽﾄ(4～3月)'!$D$26:$D$1000,$B14,'内訳ﾘｽﾄ(4～3月)'!G$26:G$1000) -> 0 | E14: =SUMIF('内訳ﾘｽﾄ(4～3月)'!$D$26:$D$1000,$B14,'内訳ﾘｽﾄ(4～3月)'!H$26:H$1000) -> 0 | F14: =SUMIF('内訳ﾘｽﾄ(4～3月)'!$D$26:$D$1000,$B14,'内訳ﾘｽﾄ(4～3月)'!I$26:I$1000) -> 0 | G14: =SUMIF('内訳ﾘｽﾄ(4～3月)'!$D$26:$D$1000,$B14,'内訳ﾘｽﾄ(4～3月)'!J$26:J$1000) -> 0 | H14: =SUMIF('内訳ﾘｽﾄ(4～3月)'!$D$26:$D$1000,$B14,'内訳ﾘｽﾄ(4～3月)'!K$26:K$1000) -> 0 | I14: =SUMIF('内訳ﾘｽﾄ(4～3月)'!$D$26:$D$1000,$B14,'内訳ﾘｽﾄ(4～3月)'!L$26:L$1000) -> 0 | J14: =SUMIF('内訳ﾘｽﾄ(4～3月)'!$D$26:$D$1000,$B14,'内訳ﾘｽﾄ(4～3月)'!M$26:M$1000) -> 0 | ... N14: =SUMIF('内訳ﾘｽﾄ(4～3月)'!$D$26:$D$1000,$B14,'内訳ﾘｽﾄ(4～3月)'!Q$26:Q$1000) -> 0 | O14: =SUMIF('内訳ﾘｽﾄ(4～3月)'!$D$26:$D$799,'採算表(VND)'!$B14,'内訳ﾘｽﾄ(4～3月)'!R$26:R$799) -> 0
B15: 設計変更材料費 | C15: =SUMIF('内訳ﾘｽﾄ(4～3月)'!$D$26:$D$1000,$B15,'内訳ﾘｽﾄ(4～3月)'!F$26:F$1000) -> 0 | D15: =SUMIF('内訳ﾘｽﾄ(4～3月)'!$D$26:$D$1000,$B15,'内訳ﾘｽﾄ(4～3月)'!G$26:G$1000) -> 0 | E15: =SUMIF('内訳ﾘｽﾄ(4～3月)'!$D$26:$D$1000,$B15,'内訳ﾘｽﾄ(4～3月)'!H$26:H$1000) -> 0 | F15: =SUMIF('内訳ﾘｽﾄ(4～3月)'!$D$26:$D$1000,$B15,'内訳ﾘｽﾄ(4～3月)'!I$26:I$1000) -> 0 | G15: =SUMIF('内訳ﾘｽﾄ(4～3月)'!$D$26:$D$1000,$B15,'内訳ﾘｽﾄ(4～3月)'!J$26:J$1000) -> 0 | H15: =SUMIF('内訳ﾘｽﾄ(4～3月)'!$D$26:$D$1000,$B15,'内訳ﾘｽﾄ(4～3月)'!K$26:K$1000) -> 0 | I15: =SUMIF('内訳ﾘｽﾄ(4～3月)'!$D$26:$D$1000,$B15,'内訳ﾘｽﾄ(4～3月)'!L$26:L$1000) -> 0 | J15: =SUMIF('内訳ﾘｽﾄ(4～3月)'!$D$26:$D$1000,$B15,'内訳ﾘｽﾄ(4～3月)'!M$26:M$1000) -> 0 | ... N15: =SUMIF('内訳ﾘｽﾄ(4～3月)'!$D$26:$D$1000,$B15,'内訳ﾘｽﾄ(4～3月)'!Q$26:Q$1000) -> 0 | O15: =SUMIF('内訳ﾘｽﾄ(4～3月)'!$D$26:$D$799,'採算表(VND)'!$B15,'内訳ﾘｽﾄ(4～3月)'!R$26:R$799) -> 0
B16: 仕掛仕損 | C16: =SUMIF('内訳ﾘｽﾄ(4～3月)'!$D$26:$D$1000,$B16,'内訳ﾘｽﾄ(4～3月)'!F$26:F$1000) -> 0 | D16: =SUMIF('内訳ﾘｽﾄ(4～3月)'!$D$26:$D$1000,$B16,'内訳ﾘｽﾄ(4～3月)'!G$26:G$1000) -> 0 | E16: =SUMIF('内訳ﾘｽﾄ(4～3月)'!$D$26:$D$1000,$B16,'内訳ﾘｽﾄ(4～3月)'!H$26:H$1000) -> 0 | F16: =SUMIF('内訳ﾘｽﾄ(4～3月)'!$D$26:$D$1000,$B16,'内訳ﾘｽﾄ(4～3月)'!I$26:I$1000) -> 0 | G16: =SUMIF('内訳ﾘｽﾄ(4～3月)'!$D$26:$D$1000,$B16,'内訳ﾘｽﾄ(4～3月)'!J$26:J$1000) -> 0 | H16: =SUMIF('内訳ﾘｽﾄ(4～3月)'!$D$26:$D$1000,$B16,'内訳ﾘｽﾄ(4～3月)'!K$26:K$1000) -> 0 | I16: =SUMIF('内訳ﾘｽﾄ(4～3月)'!$D$26:$D$1000,$B16,'内訳ﾘｽﾄ(4～3月)'!L$26:L$1000) -> 0 | J16: =SUMIF('内訳ﾘｽﾄ(4～3月)'!$D$26:$D$1000,$B16,'内訳ﾘｽﾄ(4～3月)'!M$26:M$1000) -> 0 | ... N16: =SUMIF('内訳ﾘｽﾄ(4～3月)'!$D$26:$D$1000,$B16,'内訳ﾘｽﾄ(4～3月)'!Q$26:Q$1000) -> 0 | O16: =SUMIF('内訳ﾘｽﾄ(4～3月)'!$D$26:$D$799,'採算表(VND)'!$B16,'内訳ﾘｽﾄ(4～3月)'!R$26:R$799) -> 0
B17: 仕入製商品費 | C17: =SUMIF('内訳ﾘｽﾄ(4～3月)'!$D$26:$D$1000,$B17,'内訳ﾘｽﾄ(4～3月)'!F$26:F$1000) -> 0 | D17: =SUMIF('内訳ﾘｽﾄ(4～3月)'!$D$26:$D$1000,$B17,'内訳ﾘｽﾄ(4～3月)'!G$26:G$1000) -> 0 | E17: =SUMIF('内訳ﾘｽﾄ(4～3月)'!$D$26:$D$1000,$B17,'内訳ﾘｽﾄ(4～3月)'!H$26:H$1000) -> 0 | F17: =SUMIF('内訳ﾘｽﾄ(4～3月)'!$D$26:$D$1000,$B17,'内訳ﾘｽﾄ(4～3月)'!I$26:I$1000) -> 0 | G17: =SUMIF('内訳ﾘｽﾄ(4～3月)'!$D$26:$D$1000,$B17,'内訳ﾘｽﾄ(4～3月)'!J$26:J$1000) -> 0 | H17: =SUMIF('内訳ﾘｽﾄ(4～3月)'!$D$26:$D$1000,$B17,'内訳ﾘｽﾄ(4～3月)'!K$26:K$1000) -> 0 | I17: =SUMIF('内訳ﾘｽﾄ(4～3月)'!$D$26:$D$1000,$B17,'内訳ﾘｽﾄ(4～3月)'!L$26:L$1000) -> 0 | J17: =SUMIF('内訳ﾘｽﾄ(4～3月)'!$D$26:$D$1000,$B17,'内訳ﾘｽﾄ(4～3月)'!M$26:M$1000) -> 0 | ... N17: =SUMIF('内訳ﾘｽﾄ(4～3月)'!$D$26:$D$1000,$B17,'内訳ﾘｽﾄ(4～3月)'!Q$26:Q$1000) -> 0 | O17: =SUMIF('内訳ﾘｽﾄ(4～3月)'!$D$26:$D$799,'採算表(VND)'!$B17,'内訳ﾘｽﾄ(4～3月)'!R$26:R$799) -> 0
B18: 内製品有償支給原価 | C18: =SUMIF('内訳ﾘｽﾄ(4～3月)'!$D$26:$D$1000,$B18,'内訳ﾘｽﾄ(4～3月)'!F$26:F$1000) -> 0 | D18: =SUMIF('内訳ﾘｽﾄ(4～3月)'!$D$26:$D$1000,$B18,'内訳ﾘｽﾄ(4～3月)'!G$26:G$1000) -> 0 | E18: =SUMIF('内訳ﾘｽﾄ(4～3月)'!$D$26:$D$1000,$B18,'内訳ﾘｽﾄ(4～3月)'!H$26:H$1000) -> 0 | F18: =SUMIF('内訳ﾘｽﾄ(4～3月)'!$D$26:$D$1000,$B18,'内訳ﾘｽﾄ(4～3月)'!I$26:I$1000) -> 0 | G18: =SUMIF('内訳ﾘｽﾄ(4～3月)'!$D$26:$D$1000,$B18,'内訳ﾘｽﾄ(4～3月)'!J$26:J$1000) -> 0 | H18: =SUMIF('内訳ﾘｽﾄ(4～3月)'!$D$26:$D$1000,$B18,'内訳ﾘｽﾄ(4～3月)'!K$26:K$1000) -> 0 | I18: =SUMIF('内訳ﾘｽﾄ(4～3月)'!$D$26:$D$1000,$B18,'内訳ﾘｽﾄ(4～3月)'!L$26:L$1000) -> 0 | J18: =SUMIF('内訳ﾘｽﾄ(4～3月)'!$D$26:$D$1000,$B18,'内訳ﾘｽﾄ(4～3月)'!M$26:M$1000) -> 0 | ... N18: =SUMIF('内訳ﾘｽﾄ(4～3月)'!$D$26:$D$1000,$B18,'内訳ﾘｽﾄ(4～3月)'!Q$26:Q$1000) -> 0 | O18: =SUMIF('内訳ﾘｽﾄ(4～3月)'!$D$26:$D$799,'採算表(VND)'!$B18,'内訳ﾘｽﾄ(4～3月)'!R$26:R$799) -> 0
B19: 外注加工費 | C19: =SUMIF('内訳ﾘｽﾄ(4～3月)'!$D$26:$D$1000,$B19,'内訳ﾘｽﾄ(4～3月)'!F$26:F$1000) -> 0 | D19: =SUMIF('内訳ﾘｽﾄ(4～3月)'!$D$26:$D$1000,$B19,'内訳ﾘｽﾄ(4～3月)'!G$26:G$1000) -> 0 | E19: =SUMIF('内訳ﾘｽﾄ(4～3月)'!$D$26:$D$1000,$B19,'内訳ﾘｽﾄ(4～3月)'!H$26:H$1000) -> 0 | F19: =SUMIF('内訳ﾘｽﾄ(4～3月)'!$D$26:$D$1000,$B19,'内訳ﾘｽﾄ(4～3月)'!I$26:I$1000) -> 0 | G19: =SUMIF('内訳ﾘｽﾄ(4～3月)'!$D$26:$D$1000,$B19,'内訳ﾘｽﾄ(4～3月)'!J$26:J$1000) -> 0 | H19: =SUMIF('内訳ﾘｽﾄ(4～3月)'!$D$26:$D$1000,$B19,'内訳ﾘｽﾄ(4～3月)'!K$26:K$1000) -> 0 | I19: =SUMIF('内訳ﾘｽﾄ(4～3月)'!$D$26:$D$1000,$B19,'内訳ﾘｽﾄ(4～3月)'!L$26:L$1000) -> 0 | J19: =SUMIF('内訳ﾘｽﾄ(4～3月)'!$D$26:$D$1000,$B19,'内訳ﾘｽﾄ(4～3月)'!M$26:M$1000) -> 0 | ... N19: =SUMIF('内訳ﾘｽﾄ(4～3月)'!$D$26:$D$1000,$B19,'内訳ﾘｽﾄ(4～3月)'!Q$26:Q$1000) -> 0 | O19: =SUMIF('内訳ﾘｽﾄ(4～3月)'!$D$26:$D$799,'採算表(VND)'!$B19,'内訳ﾘｽﾄ(4～3月)'!R$26:R$799) -> 0
B20: 減価償却費 | C20: =SUMIF('内訳ﾘｽﾄ(4～3月)'!$D$26:$D$1000,$B20,'内訳ﾘｽﾄ(4～3月)'!F$26:F$1000) -> 4071540 | D20: =SUMIF('内訳ﾘｽﾄ(4～3月)'!$D$26:$D$1000,$B20,'内訳ﾘｽﾄ(4～3月)'!G$26:G$1000) -> 4071540 | E20: =SUMIF('内訳ﾘｽﾄ(4～3月)'!$D$26:$D$1000,$B20,'内訳ﾘｽﾄ(4～3月)'!H$26:H$1000) -> 4071540 | F20: =SUMIF('内訳ﾘｽﾄ(4～3月)'!$D$26:$D$1000,$B20,'内訳ﾘｽﾄ(4～3月)'!I$26:I$1000) -> 4071540 | G20: =SUMIF('内訳ﾘｽﾄ(4～3月)'!$D$26:$D$1000,$B20,'内訳ﾘｽﾄ(4～3月)'!J$26:J$1000) -> 4071540 | H20: =SUMIF('内訳ﾘｽﾄ(4～3月)'!$D$26:$D$1000,$B20,'内訳ﾘｽﾄ(4～3月)'!K$26:K$1000) -> 4071540 | I20: =SUMIF('内訳ﾘｽﾄ(4～3月)'!$D$26:$D$1000,$B20,'内訳ﾘｽﾄ(4～3月)'!L$26:L$1000) -> 4071540 | J20: =SUMIF('内訳ﾘｽﾄ(4～3月)'!$D$26:$D$1000,$B20,'内訳ﾘｽﾄ(4～3月)'!M$26:M$1000) -> 4071540 | ... N20: =SUMIF('内訳ﾘｽﾄ(4～3月)'!$D$26:$D$1000,$B20,'内訳ﾘｽﾄ(4～3月)'!Q$26:Q$1000) -> 4071540 | O20: =SUMIF('内訳ﾘｽﾄ(4～3月)'!$D$26:$D$799,'採算表(VND)'!$B20,'内訳ﾘｽﾄ(4～3月)'!R$26:R$799) -> 48858480
B21: 金型償却費 | C21: =SUMIF('内訳ﾘｽﾄ(4～3月)'!$D$26:$D$1000,$B21,'内訳ﾘｽﾄ(4～3月)'!F$26:F$1000) -> 0 | D21: =SUMIF('内訳ﾘｽﾄ(4～3月)'!$D$26:$D$1000,$B21,'内訳ﾘｽﾄ(4～3月)'!G$26:G$1000) -> 0 | E21: =SUMIF('内訳ﾘｽﾄ(4～3月)'!$D$26:$D$1000,$B21,'内訳ﾘｽﾄ(4～3月)'!H$26:H$1000) -> 0 | F21: =SUMIF('内訳ﾘｽﾄ(4～3月)'!$D$26:$D$1000,$B21,'内訳ﾘｽﾄ(4～3月)'!I$26:I$1000) -> 0 | G21: =SUMIF('内訳ﾘｽﾄ(4～3月)'!$D$26:$D$1000,$B21,'内訳ﾘｽﾄ(4～3月)'!J$26:J$1000) -> 0 | H21: =SUMIF('内訳ﾘｽﾄ(4～3月)'!$D$26:$D$1000,$B21,'内訳ﾘｽﾄ(4～3月)'!K$26:K$1000) -> 0 | I21: =SUMIF('内訳ﾘｽﾄ(4～3月)'!$D$26:$D$1000,$B21,'内訳ﾘｽﾄ(4～3月)'!L$26:L$1000) -> 0 | J21: =SUMIF('内訳ﾘｽﾄ(4～3月)'!$D$26:$D$1000,$B21,'内訳ﾘｽﾄ(4～3月)'!M$26:M$1000) -> 0 | ... N21: =SUMIF('内訳ﾘｽﾄ(4～3月)'!$D$26:$D$1000,$B21,'内訳ﾘｽﾄ(4～3月)'!Q$26:Q$1000) -> 0 | O21: =SUMIF('内訳ﾘｽﾄ(4～3月)'!$D$26:$D$799,'採算表(VND)'!$B21,'内訳ﾘｽﾄ(4～3月)'!R$26:R$799) -> 0
B22: 賃借料 | C22: =SUMIF('内訳ﾘｽﾄ(4～3月)'!$D$26:$D$1000,$B22,'内訳ﾘｽﾄ(4～3月)'!F$26:F$1000) -> 0 | D22: =SUMIF('内訳ﾘｽﾄ(4～3月)'!$D$26:$D$1000,$B22,'内訳ﾘｽﾄ(4～3月)'!G$26:G$1000) -> 0 | E22: =SUMIF('内訳ﾘｽﾄ(4～3月)'!$D$26:$D$1000,$B22,'内訳ﾘｽﾄ(4～3月)'!H$26:H$1000) -> 0 | F22: =SUMIF('内訳ﾘｽﾄ(4～3月)'!$D$26:$D$1000,$B22,'内訳ﾘｽﾄ(4～3月)'!I$26:I$1000) -> 0 | G22: =SUMIF('内訳ﾘｽﾄ(4～3月)'!$D$26:$D$1000,$B22,'内訳ﾘｽﾄ(4～3月)'!J$26:J$1000) -> 0 | H22: =SUMIF('内訳ﾘｽﾄ(4～3月)'!$D$26:$D$1000,$B22,'内訳ﾘｽﾄ(4～3月)'!K$26:K$1000) -> 0 | I22: =SUMIF('内訳ﾘｽﾄ(4～3月)'!$D$26:$D$1000,$B22,'内訳ﾘｽﾄ(4～3月)'!L$26:L$1000) -> 0 | J22: =SUMIF('内訳ﾘｽﾄ(4～3月)'!$D$26:$D$1000,$B22,'内訳ﾘｽﾄ(4～3月)'!M$26:M$1000) -> 0 | ... N22: =SUMIF('内訳ﾘｽﾄ(4～3月)'!$D$26:$D$1000,$B22,'内訳ﾘｽﾄ(4～3月)'!Q$26:Q$1000) -> 0 | O22: =SUMIF('内訳ﾘｽﾄ(4～3月)'!$D$26:$D$799,'採算表(VND)'!$B22,'内訳ﾘｽﾄ(4～3月)'!R$26:R$799) -> 0
B23: 保険料 | C23: =SUMIF('内訳ﾘｽﾄ(4～3月)'!$D$26:$D$1000,$B23,'内訳ﾘｽﾄ(4～3月)'!F$26:F$1000) -> 0 | D23: =SUMIF('内訳ﾘｽﾄ(4～3月)'!$D$26:$D$1000,$B23,'内訳ﾘｽﾄ(4～3月)'!G$26:G$1000) -> 0 | E23: =SUMIF('内訳ﾘｽﾄ(4～3月)'!$D$26:$D$1000,$B23,'内訳ﾘｽﾄ(4～3月)'!H$26:H$1000) -> 0 | F23: =SUMIF('内訳ﾘｽﾄ(4～3月)'!$D$26:$D$1000,$B23,'内訳ﾘｽﾄ(4～3月)'!I$26:I$1000) -> 0 | G23: =SUMIF('内訳ﾘｽﾄ(4～3月)'!$D$26:$D$1000,$B23,'内訳ﾘｽﾄ(4～3月)'!J$26:J$1000) -> 0 | H23: =SUMIF('内訳ﾘｽﾄ(4～3月)'!$D$26:$D$1000,$B23,'内訳ﾘｽﾄ(4～3月)'!K$26:K$1000) -> 0 | I23: =SUMIF('内訳ﾘｽﾄ(4～3月)'!$D$26:$D$1000,$B23,'内訳ﾘｽﾄ(4～3月)'!L$26:L$1000) -> 0 | J23: =SUMIF('内訳ﾘｽﾄ(4～3月)'!$D$26:$D$1000,$B23,'内訳ﾘｽﾄ(4～3月)'!M$26:M$1000) -> 0 | ... N23: =SUMIF('内訳ﾘｽﾄ(4～3月)'!$D$26:$D$1000,$B23,'内訳ﾘｽﾄ(4～3月)'!Q$26:Q$1000) -> 0 | O23: =SUMIF('内訳ﾘｽﾄ(4～3月)'!$D$26:$D$799,'採算表(VND)'!$B23,'内訳ﾘｽﾄ(4～3月)'!R$26:R$799) -> 0
B24: 設計委託費 | C24: =SUMIF('内訳ﾘｽﾄ(4～3月)'!$D$26:$D$1000,$B24,'内訳ﾘｽﾄ(4～3月)'!F$26:F$1000) -> 0 | D24: =SUMIF('内訳ﾘｽﾄ(4～3月)'!$D$26:$D$1000,$B24,'内訳ﾘｽﾄ(4～3月)'!G$26:G$1000) -> 0 | E24: =SUMIF('内訳ﾘｽﾄ(4～3月)'!$D$26:$D$1000,$B24,'内訳ﾘｽﾄ(4～3月)'!H$26:H$1000) -> 0 | F24: =SUMIF('内訳ﾘｽﾄ(4～3月)'!$D$26:$D$1000,$B24,'内訳ﾘｽﾄ(4～3月)'!I$26:I$1000) -> 0 | G24: =SUMIF('内訳ﾘｽﾄ(4～3月)'!$D$26:$D$1000,$B24,'内訳ﾘｽﾄ(4～3月)'!J$26:J$1000) -> 0 | H24: =SUMIF('内訳ﾘｽﾄ(4～3月)'!$D$26:$D$1000,$B24,'内訳ﾘｽﾄ(4～3月)'!K$26:K$1000) -> 0 | I24: =SUMIF('内訳ﾘｽﾄ(4～3月)'!$D$26:$D$1000,$B24,'内訳ﾘｽﾄ(4～3月)'!L$26:L$1000) -> 0 | J24: =SUMIF('内訳ﾘｽﾄ(4～3月)'!$D$26:$D$1000,$B24,'内訳ﾘｽﾄ(4～3月)'!M$26:M$1000) -> 0 | ... N24: =SUMIF('内訳ﾘｽﾄ(4～3月)'!$D$26:$D$1000,$B24,'内訳ﾘｽﾄ(4～3月)'!Q$26:Q$1000) -> 0 | O24: =SUMIF('内訳ﾘｽﾄ(4～3月)'!$D$26:$D$799,'採算表(VND)'!$B24,'内訳ﾘｽﾄ(4～3月)'!R$26:R$799) -> 0
B25: 消耗品費 | C25: =SUMIF('内訳ﾘｽﾄ(4～3月)'!$D$26:$D$1000,$B25,'内訳ﾘｽﾄ(4～3月)'!F$26:F$1000) -> 194910 | D25: =SUMIF('内訳ﾘｽﾄ(4～3月)'!$D$26:$D$1000,$B25,'内訳ﾘｽﾄ(4～3月)'!G$26:G$1000) -> 194910 | E25: =SUMIF('内訳ﾘｽﾄ(4～3月)'!$D$26:$D$1000,$B25,'内訳ﾘｽﾄ(4～3月)'!H$26:H$1000) -> 194910 | F25: =SUMIF('内訳ﾘｽﾄ(4～3月)'!$D$26:$D$1000,$B25,'内訳ﾘｽﾄ(4～3月)'!I$26:I$1000) -> 194910 | G25: =SUMIF('内訳ﾘｽﾄ(4～3月)'!$D$26:$D$1000,$B25,'内訳ﾘｽﾄ(4～3月)'!J$26:J$1000) -> 194910 | H25: =SUMIF('内訳ﾘｽﾄ(4～3月)'!$D$26:$D$1000,$B25,'内訳ﾘｽﾄ(4～3月)'!K$26:K$1000) -> 214401 | I25: =SUMIF('内訳ﾘｽﾄ(4～3月)'!$D$26:$D$1000,$B25,'内訳ﾘｽﾄ(4～3月)'!L$26:L$1000) -> 214401 | J25: =SUMIF('内訳ﾘｽﾄ(4～3月)'!$D$26:$D$1000,$B25,'内訳ﾘｽﾄ(4～3月)'!M$26:M$1000) -> 214401 | ... N25: =SUMIF('内訳ﾘｽﾄ(4～3月)'!$D$26:$D$1000,$B25,'内訳ﾘｽﾄ(4～3月)'!Q$26:Q$1000) -> 214401 | O25: =SUMIF('内訳ﾘｽﾄ(4～3月)'!$D$26:$D$799,'採算表(VND)'!$B25,'内訳ﾘｽﾄ(4～3月)'!R$26:R$799) -> 2475357
... B65: 本社機構経費 | C65: =SUMIF('内訳ﾘｽﾄ(4～3月)'!$D$26:$D$1000,$B65,'内訳ﾘｽﾄ(4～3月)'!F$26:F$1000) -> 0 | D65: =SUMIF('内訳ﾘｽﾄ(4～3月)'!$D$26:$D$1000,$B65,'内訳ﾘｽﾄ(4～3月)'!G$26:G$1000) -> 0 | E65: =SUMIF('内訳ﾘｽﾄ(4～3月)'!$D$26:$D$1000,$B65,'内訳ﾘｽﾄ(4～3月)'!H$26:H$1000) -> 0 | F65: =SUMIF('内訳ﾘｽﾄ(4～3月)'!$D$26:$D$1000,$B65,'内訳ﾘｽﾄ(4～3月)'!I$26:I$1000) -> 0 | G65: =SUMIF('内訳ﾘｽﾄ(4～3月)'!$D$26:$D$1000,$B65,'内訳ﾘｽﾄ(4～3月)'!J$26:J$1000) -> 0 | H65: =SUMIF('内訳ﾘｽﾄ(4～3月)'!$D$26:$D$1000,$B65,'内訳ﾘｽﾄ(4～3月)'!K$26:K$1000) -> 0 | I65: =SUMIF('内訳ﾘｽﾄ(4～3月)'!$D$26:$D$1000,$B65,'内訳ﾘｽﾄ(4～3月)'!L$26:L$1000) -> 0 | J65: =SUMIF('内訳ﾘｽﾄ(4～3月)'!$D$26:$D$1000,$B65,'内訳ﾘｽﾄ(4～3月)'!M$26:M$1000) -> 0 | ... N65: =SUMIF('内訳ﾘｽﾄ(4～3月)'!$D$26:$D$1000,$B65,'内訳ﾘｽﾄ(4～3月)'!Q$26:Q$1000) -> 0 | O65: =SUMIF('内訳ﾘｽﾄ(4～3月)'!$D$26:$D$799,'採算表(VND)'!$B65,'内訳ﾘｽﾄ(4～3月)'!R$26:R$799) -> 0
B66: 差引収益 | C66: =C12-C13 -> -52076543 | D66: =D12-D13 -> 903288265 | E66: =E12-E13 -> 687509896 | F66: =F12-F13 -> 897430313 | G66: =G12-G13 -> 875030234 | H66: =H12-H13 -> 864567030 | I66: =I12-I13 -> 759761261 | J66: =J12-J13 -> 1129253914 | ... N66: =N12-N13 -> 842461200 | O66: =IF(ISBLANK(O4),"",O12-O13) -> 9657120458
B67: 総時間 | C67: =C73+C79 -> 1547.5 | D67: =D73+D79 -> 1476.5 | E67: =E73+E79 -> 1622.25 | F67: =F73+F79 -> 1769.25 | G67: =G73+G79 -> 1549.5 | H67: =H73+H79 -> 1637 | I67: =I73+I79 -> 1965.75 | J67: =J73+J79 -> 1721.25 | ... N67: =N73+N79 -> 1722.75 | O67: =IF(ISBLANK(O4),"",O73+O79) -> 19876.5
B68: 直接部門 | C68: =SUMIF('内訳ﾘｽﾄ(4～3月)'!$D$8:$D$15,'採算表(VND)'!$B68,'内訳ﾘｽﾄ(4～3月)'!F$8:F$15) -> 1326 | D68: =SUMIF('内訳ﾘｽﾄ(4～3月)'!$D$8:$D$15,'採算表(VND)'!$B68,'内訳ﾘｽﾄ(4～3月)'!G$8:G$15) -> 1258 | E68: =SUMIF('内訳ﾘｽﾄ(4～3月)'!$D$8:$D$15,'採算表(VND)'!$B68,'内訳ﾘｽﾄ(4～3月)'!H$8:H$15) -> 1394 | F68: =SUMIF('内訳ﾘｽﾄ(4～3月)'!$D$8:$D$15,'採算表(VND)'!$B68,'内訳ﾘｽﾄ(4～3月)'!I$8:I$15) -> 1530 | G68: =SUMIF('内訳ﾘｽﾄ(4～3月)'!$D$8:$D$15,'採算表(VND)'!$B68,'内訳ﾘｽﾄ(4～3月)'!J$8:J$15) -> 1326 | H68: =SUMIF('内訳ﾘｽﾄ(4～3月)'!$D$8:$D$15,'採算表(VND)'!$B68,'内訳ﾘｽﾄ(4～3月)'!K$8:K$15) -> 1419.5 | I68: =SUMIF('内訳ﾘｽﾄ(4～3月)'!$D$8:$D$15,'採算表(VND)'!$B68,'内訳ﾘｽﾄ(4～3月)'!L$8:L$15) -> 1725.5 | J68: =SUMIF('内訳ﾘｽﾄ(4～3月)'!$D$8:$D$15,'採算表(VND)'!$B68,'内訳ﾘｽﾄ(4～3月)'!M$8:M$15) -> 1496 | ... N68: =SUMIF('内訳ﾘｽﾄ(4～3月)'!$D$8:$D$15,'採算表(VND)'!$B68,'内訳ﾘｽﾄ(4～3月)'!Q$8:Q$15) -> 1496 | O68: =SUMIF('内訳ﾘｽﾄ(4～3月)'!$D$8:$D$15,'採算表(VND)'!$B68,'内訳ﾘｽﾄ(4～3月)'!$R$8:$R$15) -> 17187
B69: 部内間接部門 | C69: =IF('内訳ﾘｽﾄ(4～3月)'!$D$5="製造",SUMIF('内訳ﾘｽﾄ(4～3月)'!$D$8:$D$15,$B69,'内訳ﾘｽﾄ(4～3月)'!F$8:F$15),IF('内訳ﾘｽﾄ(4～3月)'!$D$5="部内間接",-C$68,0)) -> 0 | D69: =IF('内訳ﾘｽﾄ(4～3月)'!$D$5="製造",SUMIF('内訳ﾘｽﾄ(4～3月)'!$D$8:$D$15,$B69,'内訳ﾘｽﾄ(4～3月)'!G$8:G$15),IF('内訳ﾘｽﾄ(4～3月)'!$D$5="部内間接",-D$68,0)) -> 0 | E69: =IF('内訳ﾘｽﾄ(4～3月)'!$D$5="製造",SUMIF('内訳ﾘｽﾄ(4～3月)'!$D$8:$D$15,$B69,'内訳ﾘｽﾄ(4～3月)'!H$8:H$15),IF('内訳ﾘｽﾄ(4～3月)'!$D$5="部内間接",-E$68,0)) -> 0 | F69: =IF('内訳ﾘｽﾄ(4～3月)'!$D$5="製造",SUMIF('内訳ﾘｽﾄ(4～3月)'!$D$8:$D$15,$B69,'内訳ﾘｽﾄ(4～3月)'!I$8:I$15),IF('内訳ﾘｽﾄ(4～3月)'!$D$5="部内間接",-F$68,0)) -> 0 | G69: =IF('内訳ﾘｽﾄ(4～3月)'!$D$5="製造",SUMIF('内訳ﾘｽﾄ(4～3月)'!$D$8:$D$15,$B69,'内訳ﾘｽﾄ(4～3月)'!J$8:J$15),IF('内訳ﾘｽﾄ(4～3月)'!$D$5="部内間接",-G$68,0)) -> 0 | H69: =IF('内訳ﾘｽﾄ(4～3月)'!$D$5="製造",SUMIF('内訳ﾘｽﾄ(4～3月)'!$D$8:$D$15,$B69,'内訳ﾘｽﾄ(4～3月)'!K$8:K$15),IF('内訳ﾘｽﾄ(4～3月)'!$D$5="部内間接",-H$68,0)) -> 0 | I69: =IF('内訳ﾘｽﾄ(4～3月)'!$D$5="製造",SUMIF('内訳ﾘｽﾄ(4～3月)'!$D$8:$D$15,$B69,'内訳ﾘｽﾄ(4～3月)'!L$8:L$15),IF('内訳ﾘｽﾄ(4～3月)'!$D$5="部内間接",-I$68,0)) -> 0 | J69: =IF('内訳ﾘｽﾄ(4～3月)'!$D$5="製造",SUMIF('内訳ﾘｽﾄ(4～3月)'!$D$8:$D$15,$B69,'内訳ﾘｽﾄ(4～3月)'!M$8:M$15),IF('内訳ﾘｽﾄ(4～3月)'!$D$5="部内間接",-J$68,0)) -> 0 | ... N69: =IF('内訳ﾘｽﾄ(4～3月)'!$D$5="製造",SUMIF('内訳ﾘｽﾄ(4～3月)'!$D$8:$D$15,$B69,'内訳ﾘｽﾄ(4～3月)'!Q$8:Q$15),IF('内訳ﾘｽﾄ(4～3月)'!$D$5="部内間接",-N$68,0)) -> 0 | O69: =IF('内訳ﾘｽﾄ(4～3月)'!$D$5="部内間接",-SUM(O$68),IF('内訳ﾘｽﾄ(4～3月)'!$D$5="製造",SUMIF('内訳ﾘｽﾄ(4～3月)'!$D$8:$D$15,'採算表(VND)'!$B69,'内訳ﾘｽﾄ(4～3月)'!$R$8:$R$15),0)) -> 0
B70: 部外間接部門1 | C70: =IF('内訳ﾘｽﾄ(4～3月)'!$D$5="製造",SUMIF('内訳ﾘｽﾄ(4～3月)'!$D$8:$D$15,$B70,'内訳ﾘｽﾄ(4～3月)'!F$8:F$15),IF('内訳ﾘｽﾄ(4～3月)'!$D$5="部外間接1",-C$68,0)) -> 6.75 | D70: =IF('内訳ﾘｽﾄ(4～3月)'!$D$5="製造",SUMIF('内訳ﾘｽﾄ(4～3月)'!$D$8:$D$15,$B70,'内訳ﾘｽﾄ(4～3月)'!G$8:G$15),IF('内訳ﾘｽﾄ(4～3月)'!$D$5="部外間接1",-D$68,0)) -> 7 | E70: =IF('内訳ﾘｽﾄ(4～3月)'!$D$5="製造",SUMIF('内訳ﾘｽﾄ(4～3月)'!$D$8:$D$15,$B70,'内訳ﾘｽﾄ(4～3月)'!H$8:H$15),IF('内訳ﾘｽﾄ(4～3月)'!$D$5="部外間接1",-E$68,0)) -> 7.75 | F70: =IF('内訳ﾘｽﾄ(4～3月)'!$D$5="製造",SUMIF('内訳ﾘｽﾄ(4～3月)'!$D$8:$D$15,$B70,'内訳ﾘｽﾄ(4～3月)'!I$8:I$15),IF('内訳ﾘｽﾄ(4～3月)'!$D$5="部外間接1",-F$68,0)) -> 8.25 | G70: =IF('内訳ﾘｽﾄ(4～3月)'!$D$5="製造",SUMIF('内訳ﾘｽﾄ(4～3月)'!$D$8:$D$15,$B70,'内訳ﾘｽﾄ(4～3月)'!J$8:J$15),IF('内訳ﾘｽﾄ(4～3月)'!$D$5="部外間接1",-G$68,0)) -> 7 | H70: =IF('内訳ﾘｽﾄ(4～3月)'!$D$5="製造",SUMIF('内訳ﾘｽﾄ(4～3月)'!$D$8:$D$15,$B70,'内訳ﾘｽﾄ(4～3月)'!K$8:K$15),IF('内訳ﾘｽﾄ(4～3月)'!$D$5="部外間接1",-H$68,0)) -> 6.5 | I70: =IF('内訳ﾘｽﾄ(4～3月)'!$D$5="製造",SUMIF('内訳ﾘｽﾄ(4～3月)'!$D$8:$D$15,$B70,'内訳ﾘｽﾄ(4～3月)'!L$8:L$15),IF('内訳ﾘｽﾄ(4～3月)'!$D$5="部外間接1",-I$68,0)) -> 8.25 | J70: =IF('内訳ﾘｽﾄ(4～3月)'!$D$5="製造",SUMIF('内訳ﾘｽﾄ(4～3月)'!$D$8:$D$15,$B70,'内訳ﾘｽﾄ(4～3月)'!M$8:M$15),IF('内訳ﾘｽﾄ(4～3月)'!$D$5="部外間接1",-J$68,0)) -> 7.25 | ... N70: =IF('内訳ﾘｽﾄ(4～3月)'!$D$5="製造",SUMIF('内訳ﾘｽﾄ(4～3月)'!$D$8:$D$15,$B70,'内訳ﾘｽﾄ(4～3月)'!Q$8:Q$15),IF('内訳ﾘｽﾄ(4～3月)'!$D$5="部外間接1",-N$68,0)) -> 7.5 | O70: =IF('内訳ﾘｽﾄ(4～3月)'!$D$5="部外間接1",-SUM(O$68),IF('内訳ﾘｽﾄ(4～3月)'!$D$5="製造",SUMIF('内訳ﾘｽﾄ(4～3月)'!$D$8:$D$15,'採算表(VND)'!$B70,'内訳ﾘｽﾄ(4～3月)'!$R$8:$R$15),0)) -> 87.25
B71: 部外間接部門2 | C71: =IF('内訳ﾘｽﾄ(4～3月)'!$D$5="製造",SUMIF('内訳ﾘｽﾄ(4～3月)'!$D$8:$D$15,$B71,'内訳ﾘｽﾄ(4～3月)'!F$8:F$15),IF('内訳ﾘｽﾄ(4～3月)'!$D$5="部外間接2",-C$68,0)) -> 12.75 | D71: =IF('内訳ﾘｽﾄ(4～3月)'!$D$5="製造",SUMIF('内訳ﾘｽﾄ(4～3月)'!$D$8:$D$15,$B71,'内訳ﾘｽﾄ(4～3月)'!G$8:G$15),IF('内訳ﾘｽﾄ(4～3月)'!$D$5="部外間接2",-D$68,0)) -> 12.25 | E71: =IF('内訳ﾘｽﾄ(4～3月)'!$D$5="製造",SUMIF('内訳ﾘｽﾄ(4～3月)'!$D$8:$D$15,$B71,'内訳ﾘｽﾄ(4～3月)'!H$8:H$15),IF('内訳ﾘｽﾄ(4～3月)'!$D$5="部外間接2",-E$68,0)) -> 14 | F71: =IF('内訳ﾘｽﾄ(4～3月)'!$D$5="製造",SUMIF('内訳ﾘｽﾄ(4～3月)'!$D$8:$D$15,$B71,'内訳ﾘｽﾄ(4～3月)'!I$8:I$15),IF('内訳ﾘｽﾄ(4～3月)'!$D$5="部外間接2",-F$68,0)) -> 15.5 | G71: =IF('内訳ﾘｽﾄ(4～3月)'!$D$5="製造",SUMIF('内訳ﾘｽﾄ(4～3月)'!$D$8:$D$15,$B71,'内訳ﾘｽﾄ(4～3月)'!J$8:J$15),IF('内訳ﾘｽﾄ(4～3月)'!$D$5="部外間接2",-G$68,0)) -> 13 | H71: =IF('内訳ﾘｽﾄ(4～3月)'!$D$5="製造",SUMIF('内訳ﾘｽﾄ(4～3月)'!$D$8:$D$15,$B71,'内訳ﾘｽﾄ(4～3月)'!K$8:K$15),IF('内訳ﾘｽﾄ(4～3月)'!$D$5="部外間接2",-H$68,0)) -> 13 | I71: =IF('内訳ﾘｽﾄ(4～3月)'!$D$5="製造",SUMIF('内訳ﾘｽﾄ(4～3月)'!$D$8:$D$15,$B71,'内訳ﾘｽﾄ(4～3月)'!L$8:L$15),IF('内訳ﾘｽﾄ(4～3月)'!$D$5="部外間接2",-I$68,0)) -> 16.25 | J71: =IF('内訳ﾘｽﾄ(4～3月)'!$D$5="製造",SUMIF('内訳ﾘｽﾄ(4～3月)'!$D$8:$D$15,$B71,'内訳ﾘｽﾄ(4～3月)'!M$8:M$15),IF('内訳ﾘｽﾄ(4～3月)'!$D$5="部外間接2",-J$68,0)) -> 14 | ... N71: =IF('内訳ﾘｽﾄ(4～3月)'!$D$5="製造",SUMIF('内訳ﾘｽﾄ(4～3月)'!$D$8:$D$15,$B71,'内訳ﾘｽﾄ(4～3月)'!Q$8:Q$15),IF('内訳ﾘｽﾄ(4～3月)'!$D$5="部外間接2",-N$68,0)) -> 14 | O71: =IF('内訳ﾘｽﾄ(4～3月)'!$D$5="部外間接2",-SUM(O$68),IF('内訳ﾘｽﾄ(4～3月)'!$D$5="製造",SUMIF('内訳ﾘｽﾄ(4～3月)'!$D$8:$D$15,'採算表(VND)'!$B71,'内訳ﾘｽﾄ(4～3月)'!$R$8:$R$15),0)) -> 165.25
B72: 工場間接部門 | C72: =IF('内訳ﾘｽﾄ(4～3月)'!$D$5="製造",SUMIF('内訳ﾘｽﾄ(4～3月)'!$D$8:$D$15,$B72,'内訳ﾘｽﾄ(4～3月)'!F$8:F$15),IF('内訳ﾘｽﾄ(4～3月)'!$D$5="工場間接",-C$68,0)) -> 57 | D72: =IF('内訳ﾘｽﾄ(4～3月)'!$D$5="製造",SUMIF('内訳ﾘｽﾄ(4～3月)'!$D$8:$D$15,$B72,'内訳ﾘｽﾄ(4～3月)'!G$8:G$15),IF('内訳ﾘｽﾄ(4～3月)'!$D$5="工場間接",-D$68,0)) -> 56.5 | E72: =IF('内訳ﾘｽﾄ(4～3月)'!$D$5="製造",SUMIF('内訳ﾘｽﾄ(4～3月)'!$D$8:$D$15,$B72,'内訳ﾘｽﾄ(4～3月)'!H$8:H$15),IF('内訳ﾘｽﾄ(4～3月)'!$D$5="工場間接",-E$68,0)) -> 60 | F72: =IF('内訳ﾘｽﾄ(4～3月)'!$D$5="製造",SUMIF('内訳ﾘｽﾄ(4～3月)'!$D$8:$D$15,$B72,'内訳ﾘｽﾄ(4～3月)'!I$8:I$15),IF('内訳ﾘｽﾄ(4～3月)'!$D$5="工場間接",-F$68,0)) -> 64.75 | G72: =IF('内訳ﾘｽﾄ(4～3月)'!$D$5="製造",SUMIF('内訳ﾘｽﾄ(4～3月)'!$D$8:$D$15,$B72,'内訳ﾘｽﾄ(4～3月)'!J$8:J$15),IF('内訳ﾘｽﾄ(4～3月)'!$D$5="工場間接",-G$68,0)) -> 59 | H72: =IF('内訳ﾘｽﾄ(4～3月)'!$D$5="製造",SUMIF('内訳ﾘｽﾄ(4～3月)'!$D$8:$D$15,$B72,'内訳ﾘｽﾄ(4～3月)'!K$8:K$15),IF('内訳ﾘｽﾄ(4～3月)'!$D$5="工場間接",-H$68,0)) -> 54.75 | I72: =IF('内訳ﾘｽﾄ(4～3月)'!$D$5="製造",SUMIF('内訳ﾘｽﾄ(4～3月)'!$D$8:$D$15,$B72,'内訳ﾘｽﾄ(4～3月)'!L$8:L$15),IF('内訳ﾘｽﾄ(4～3月)'!$D$5="工場間接",-I$68,0)) -> 65 | J72: =IF('内訳ﾘｽﾄ(4～3月)'!$D$5="製造",SUMIF('内訳ﾘｽﾄ(4～3月)'!$D$8:$D$15,$B72,'内訳ﾘｽﾄ(4～3月)'!M$8:M$15),IF('内訳ﾘｽﾄ(4～3月)'!$D$5="工場間接",-J$68,0)) -> 59.25 | ... N72: =IF('内訳ﾘｽﾄ(4～3月)'!$D$5="製造",SUMIF('内訳ﾘｽﾄ(4～3月)'!$D$8:$D$15,$B72,'内訳ﾘｽﾄ(4～3月)'!Q$8:Q$15),IF('内訳ﾘｽﾄ(4～3月)'!$D$5="工場間接",-N$68,0)) -> 60.5 | O72: =IF('内訳ﾘｽﾄ(4～3月)'!$D$5="工場間接",-SUM(O$68),IF('内訳ﾘｽﾄ(4～3月)'!$D$5="製造",SUMIF('内訳ﾘｽﾄ(4～3月)'!$D$8:$D$15,'採算表(VND)'!$B72,'内訳ﾘｽﾄ(4～3月)'!$R$8:$R$15),0)) -> 706
B73: 定時間合計 | C73: =SUM(C68:C72) -> 1402.5 | D73: =SUM(D68:D72) -> 1333.75 | E73: =SUM(E68:E72) -> 1475.75 | F73: =SUM(F68:F72) -> 1618.5 | G73: =SUM(G68:G72) -> 1405 | H73: =SUM(H68:H72) -> 1493.75 | I73: =SUM(I68:I72) -> 1815 | J73: =SUM(J68:J72) -> 1576.5 | ... N73: =SUM(N68:N72) -> 1578 | O73: =IF(ISBLANK(O4),"",SUM(O68:O72)) -> 18145.5
B74: 直接部門 | C74: =SUMIF('内訳ﾘｽﾄ(4～3月)'!$D$16:$D$23,'採算表(VND)'!$B74,'内訳ﾘｽﾄ(4～3月)'!F$16:F$23) -> 140 | D74: =SUMIF('内訳ﾘｽﾄ(4～3月)'!$D$16:$D$23,'採算表(VND)'!$B74,'内訳ﾘｽﾄ(4～3月)'!G$16:G$23) -> 138 | E74: =SUMIF('内訳ﾘｽﾄ(4～3月)'!$D$16:$D$23,'採算表(VND)'!$B74,'内訳ﾘｽﾄ(4～3月)'!H$16:H$23) -> 142 | F74: =SUMIF('内訳ﾘｽﾄ(4～3月)'!$D$16:$D$23,'採算表(VND)'!$B74,'内訳ﾘｽﾄ(4～3月)'!I$16:I$23) -> 146 | G74: =SUMIF('内訳ﾘｽﾄ(4～3月)'!$D$16:$D$23,'採算表(VND)'!$B74,'内訳ﾘｽﾄ(4～3月)'!J$16:J$23) -> 140 | H74: =SUMIF('内訳ﾘｽﾄ(4～3月)'!$D$16:$D$23,'採算表(VND)'!$B74,'内訳ﾘｽﾄ(4～3月)'!K$16:K$23) -> 138 | I74: =SUMIF('内訳ﾘｽﾄ(4～3月)'!$D$16:$D$23,'採算表(VND)'!$B74,'内訳ﾘｽﾄ(4～3月)'!L$16:L$23) -> 146 | J74: =SUMIF('内訳ﾘｽﾄ(4～3月)'!$D$16:$D$23,'採算表(VND)'!$B74,'内訳ﾘｽﾄ(4～3月)'!M$16:M$23) -> 140 | ... N74: =SUMIF('内訳ﾘｽﾄ(4～3月)'!$D$16:$D$23,'採算表(VND)'!$B74,'内訳ﾘｽﾄ(4～3月)'!Q$16:Q$23) -> 140 | O74: =SUMIF('内訳ﾘｽﾄ(4～3月)'!$D$16:$D$23,'採算表(VND)'!$B74,'内訳ﾘｽﾄ(4～3月)'!$R$16:$R$23) -> 1674
B75: 部内間接部門 | C75: =IF('内訳ﾘｽﾄ(4～3月)'!$D$5="製造",SUMIF('内訳ﾘｽﾄ(4～3月)'!$D$16:$D$23,$B75,'内訳ﾘｽﾄ(4～3月)'!F$16:F$23),IF('内訳ﾘｽﾄ(4～3月)'!$D$5="部内間接",-C$74,0)) -> 0 | D75: =IF('内訳ﾘｽﾄ(4～3月)'!$D$5="製造",SUMIF('内訳ﾘｽﾄ(4～3月)'!$D$16:$D$23,$B75,'内訳ﾘｽﾄ(4～3月)'!G$16:G$23),IF('内訳ﾘｽﾄ(4～3月)'!$D$5="部内間接",-D$74,0)) -> 0 | E75: =IF('内訳ﾘｽﾄ(4～3月)'!$D$5="製造",SUMIF('内訳ﾘｽﾄ(4～3月)'!$D$16:$D$23,$B75,'内訳ﾘｽﾄ(4～3月)'!H$16:H$23),IF('内訳ﾘｽﾄ(4～3月)'!$D$5="部内間接",-E$74,0)) -> 0 | F75: =IF('内訳ﾘｽﾄ(4～3月)'!$D$5="製造",SUMIF('内訳ﾘｽﾄ(4～3月)'!$D$16:$D$23,$B75,'内訳ﾘｽﾄ(4～3月)'!I$16:I$23),IF('内訳ﾘｽﾄ(4～3月)'!$D$5="部内間接",-F$74,0)) -> 0 | G75: =IF('内訳ﾘｽﾄ(4～3月)'!$D$5="製造",SUMIF('内訳ﾘｽﾄ(4～3月)'!$D$16:$D$23,$B75,'内訳ﾘｽﾄ(4～3月)'!J$16:J$23),IF('内訳ﾘｽﾄ(4～3月)'!$D$5="部内間接",-G$74,0)) -> 0 | H75: =IF('内訳ﾘｽﾄ(4～3月)'!$D$5="製造",SUMIF('内訳ﾘｽﾄ(4～3月)'!$D$16:$D$23,$B75,'内訳ﾘｽﾄ(4～3月)'!K$16:K$23),IF('内訳ﾘｽﾄ(4～3月)'!$D$5="部内間接",-H$74,0)) -> 0 | I75: =IF('内訳ﾘｽﾄ(4～3月)'!$D$5="製造",SUMIF('内訳ﾘｽﾄ(4～3月)'!$D$16:$D$23,$B75,'内訳ﾘｽﾄ(4～3月)'!L$16:L$23),IF('内訳ﾘｽﾄ(4～3月)'!$D$5="部内間接",-I$74,0)) -> 0 | J75: =IF('内訳ﾘｽﾄ(4～3月)'!$D$5="製造",SUMIF('内訳ﾘｽﾄ(4～3月)'!$D$16:$D$23,$B75,'内訳ﾘｽﾄ(4～3月)'!M$16:M$23),IF('内訳ﾘｽﾄ(4～3月)'!$D$5="部内間接",-J$74,0)) -> 0 | ... N75: =IF('内訳ﾘｽﾄ(4～3月)'!$D$5="製造",SUMIF('内訳ﾘｽﾄ(4～3月)'!$D$16:$D$23,$B75,'内訳ﾘｽﾄ(4～3月)'!Q$16:Q$23),IF('内訳ﾘｽﾄ(4～3月)'!$D$5="部内間接",-N$74,0)) -> 0 | O75: =IF('内訳ﾘｽﾄ(4～3月)'!$D$5="部内間接",-SUM(O$74),IF('内訳ﾘｽﾄ(4～3月)'!$D$5="製造",SUMIF('内訳ﾘｽﾄ(4～3月)'!$D$16:$D$23,'採算表(VND)'!$B75,'内訳ﾘｽﾄ(4～3月)'!$R$16:$R$23),0)) -> 0
B76: 部外間接部門1 | C76: =IF('内訳ﾘｽﾄ(4～3月)'!$D$5="製造",SUMIF('内訳ﾘｽﾄ(4～3月)'!$D$16:$D$23,$B76,'内訳ﾘｽﾄ(4～3月)'!F$16:F$23),IF('内訳ﾘｽﾄ(4～3月)'!$D$5="部外間接1",-C$74,0)) -> 0.5 | D76: =IF('内訳ﾘｽﾄ(4～3月)'!$D$5="製造",SUMIF('内訳ﾘｽﾄ(4～3月)'!$D$16:$D$23,$B76,'内訳ﾘｽﾄ(4～3月)'!G$16:G$23),IF('内訳ﾘｽﾄ(4～3月)'!$D$5="部外間接1",-D$74,0)) -> 0.5 | E76: =IF('内訳ﾘｽﾄ(4～3月)'!$D$5="製造",SUMIF('内訳ﾘｽﾄ(4～3月)'!$D$16:$D$23,$B76,'内訳ﾘｽﾄ(4～3月)'!H$16:H$23),IF('内訳ﾘｽﾄ(4～3月)'!$D$5="部外間接1",-E$74,0)) -> 0.5 | F76: =IF('内訳ﾘｽﾄ(4～3月)'!$D$5="製造",SUMIF('内訳ﾘｽﾄ(4～3月)'!$D$16:$D$23,$B76,'内訳ﾘｽﾄ(4～3月)'!I$16:I$23),IF('内訳ﾘｽﾄ(4～3月)'!$D$5="部外間接1",-F$74,0)) -> 0.5 | G76: =IF('内訳ﾘｽﾄ(4～3月)'!$D$5="製造",SUMIF('内訳ﾘｽﾄ(4～3月)'!$D$16:$D$23,$B76,'内訳ﾘｽﾄ(4～3月)'!J$16:J$23),IF('内訳ﾘｽﾄ(4～3月)'!$D$5="部外間接1",-G$74,0)) -> 0.5 | H76: =IF('内訳ﾘｽﾄ(4～3月)'!$D$5="製造",SUMIF('内訳ﾘｽﾄ(4～3月)'!$D$16:$D$23,$B76,'内訳ﾘｽﾄ(4～3月)'!K$16:K$23),IF('内訳ﾘｽﾄ(4～3月)'!$D$5="部外間接1",-H$74,0)) -> 0.5 | I76: =IF('内訳ﾘｽﾄ(4～3月)'!$D$5="製造",SUMIF('内訳ﾘｽﾄ(4～3月)'!$D$16:$D$23,$B76,'内訳ﾘｽﾄ(4～3月)'!L$16:L$23),IF('内訳ﾘｽﾄ(4～3月)'!$D$5="部外間接1",-I$74,0)) -> 0.5 | J76: =IF('内訳ﾘｽﾄ(4～3月)'!$D$5="製造",SUMIF('内訳ﾘｽﾄ(4～3月)'!$D$16:$D$23,$B76,'内訳ﾘｽﾄ(4～3月)'!M$16:M$23),IF('内訳ﾘｽﾄ(4～3月)'!$D$5="部外間接1",-J$74,0)) -> 0.5 | ... N76: =IF('内訳ﾘｽﾄ(4～3月)'!$D$5="製造",SUMIF('内訳ﾘｽﾄ(4～3月)'!$D$16:$D$23,$B76,'内訳ﾘｽﾄ(4～3月)'!Q$16:Q$23),IF('内訳ﾘｽﾄ(4～3月)'!$D$5="部外間接1",-N$74,0)) -> 0.5 | O76: =IF('内訳ﾘｽﾄ(4～3月)'!$D$5="部外間接1",-SUM(O$74),IF('内訳ﾘｽﾄ(4～3月)'!$D$5="製造",SUMIF('内訳ﾘｽﾄ(4～3月)'!$D$16:$D$23,'採算表(VND)'!$B76,'内訳ﾘｽﾄ(4～3月)'!$R$16:$R$23),0)) -> 5.75
B77: 部外間接部門2 | C77: =IF('内訳ﾘｽﾄ(4～3月)'!$D$5="製造",SUMIF('内訳ﾘｽﾄ(4～3月)'!$D$16:$D$23,$B77,'内訳ﾘｽﾄ(4～3月)'!F$16:F$23),IF('内訳ﾘｽﾄ(4～3月)'!$D$5="部外間接2",-C$74,0)) -> 1.25 | D77: =IF('内訳ﾘｽﾄ(4～3月)'!$D$5="製造",SUMIF('内訳ﾘｽﾄ(4～3月)'!$D$16:$D$23,$B77,'内訳ﾘｽﾄ(4～3月)'!G$16:G$23),IF('内訳ﾘｽﾄ(4～3月)'!$D$5="部外間接2",-D$74,0)) -> 1 | E77: =IF('内訳ﾘｽﾄ(4～3月)'!$D$5="製造",SUMIF('内訳ﾘｽﾄ(4～3月)'!$D$16:$D$23,$B77,'内訳ﾘｽﾄ(4～3月)'!H$16:H$23),IF('内訳ﾘｽﾄ(4～3月)'!$D$5="部外間接2",-E$74,0)) -> 1.25 | F77: =IF('内訳ﾘｽﾄ(4～3月)'!$D$5="製造",SUMIF('内訳ﾘｽﾄ(4～3月)'!$D$16:$D$23,$B77,'内訳ﾘｽﾄ(4～3月)'!I$16:I$23),IF('内訳ﾘｽﾄ(4～3月)'!$D$5="部外間接2",-F$74,0)) -> 1.25 | G77: =IF('内訳ﾘｽﾄ(4～3月)'!$D$5="製造",SUMIF('内訳ﾘｽﾄ(4～3月)'!$D$16:$D$23,$B77,'内訳ﾘｽﾄ(4～3月)'!J$16:J$23),IF('内訳ﾘｽﾄ(4～3月)'!$D$5="部外間接2",-G$74,0)) -> 1.25 | H77: =IF('内訳ﾘｽﾄ(4～3月)'!$D$5="製造",SUMIF('内訳ﾘｽﾄ(4～3月)'!$D$16:$D$23,$B77,'内訳ﾘｽﾄ(4～3月)'!K$16:K$23),IF('内訳ﾘｽﾄ(4～3月)'!$D$5="部外間接2",-H$74,0)) -> 1 | I77: =IF('内訳ﾘｽﾄ(4～3月)'!$D$5="製造",SUMIF('内訳ﾘｽﾄ(4～3月)'!$D$16:$D$23,$B77,'内訳ﾘｽﾄ(4～3月)'!L$16:L$23),IF('内訳ﾘｽﾄ(4～3月)'!$D$5="部外間接2",-I$74,0)) -> 1.25 | J77: =IF('内訳ﾘｽﾄ(4～3月)'!$D$5="製造",SUMIF('内訳ﾘｽﾄ(4～3月)'!$D$16:$D$23,$B77,'内訳ﾘｽﾄ(4～3月)'!M$16:M$23),IF('内訳ﾘｽﾄ(4～3月)'!$D$5="部外間接2",-J$74,0)) -> 1.25 | ... N77: =IF('内訳ﾘｽﾄ(4～3月)'!$D$5="製造",SUMIF('内訳ﾘｽﾄ(4～3月)'!$D$16:$D$23,$B77,'内訳ﾘｽﾄ(4～3月)'!Q$16:Q$23),IF('内訳ﾘｽﾄ(4～3月)'!$D$5="部外間接2",-N$74,0)) -> 1.5 | O77: =IF('内訳ﾘｽﾄ(4～3月)'!$D$5="部外間接2",-SUM(O$74),IF('内訳ﾘｽﾄ(4～3月)'!$D$5="製造",SUMIF('内訳ﾘｽﾄ(4～3月)'!$D$16:$D$23,'採算表(VND)'!$B77,'内訳ﾘｽﾄ(4～3月)'!$R$16:$R$23),0)) -> 14.25
B78: 工場間接部門 | C78: =IF('内訳ﾘｽﾄ(4～3月)'!$D$5="製造",SUMIF('内訳ﾘｽﾄ(4～3月)'!$D$16:$D$23,$B78,'内訳ﾘｽﾄ(4～3月)'!F$16:F$23),IF('内訳ﾘｽﾄ(4～3月)'!$D$5="工場間接",-C$74,0)) -> 3.25 | D78: =IF('内訳ﾘｽﾄ(4～3月)'!$D$5="製造",SUMIF('内訳ﾘｽﾄ(4～3月)'!$D$16:$D$23,$B78,'内訳ﾘｽﾄ(4～3月)'!G$16:G$23),IF('内訳ﾘｽﾄ(4～3月)'!$D$5="工場間接",-D$74,0)) -> 3.25 | E78: =IF('内訳ﾘｽﾄ(4～3月)'!$D$5="製造",SUMIF('内訳ﾘｽﾄ(4～3月)'!$D$16:$D$23,$B78,'内訳ﾘｽﾄ(4～3月)'!H$16:H$23),IF('内訳ﾘｽﾄ(4～3月)'!$D$5="工場間接",-E$74,0)) -> 2.75 | F78: =IF('内訳ﾘｽﾄ(4～3月)'!$D$5="製造",SUMIF('内訳ﾘｽﾄ(4～3月)'!$D$16:$D$23,$B78,'内訳ﾘｽﾄ(4～3月)'!I$16:I$23),IF('内訳ﾘｽﾄ(4～3月)'!$D$5="工場間接",-F$74,0)) -> 3 | G78: =IF('内訳ﾘｽﾄ(4～3月)'!$D$5="製造",SUMIF('内訳ﾘｽﾄ(4～3月)'!$D$16:$D$23,$B78,'内訳ﾘｽﾄ(4～3月)'!J$16:J$23),IF('内訳ﾘｽﾄ(4～3月)'!$D$5="工場間接",-G$74,0)) -> 2.75 | H78: =IF('内訳ﾘｽﾄ(4～3月)'!$D$5="製造",SUMIF('内訳ﾘｽﾄ(4～3月)'!$D$16:$D$23,$B78,'内訳ﾘｽﾄ(4～3月)'!K$16:K$23),IF('内訳ﾘｽﾄ(4～3月)'!$D$5="工場間接",-H$74,0)) -> 3.75 | I78: =IF('内訳ﾘｽﾄ(4～3月)'!$D$5="製造",SUMIF('内訳ﾘｽﾄ(4～3月)'!$D$16:$D$23,$B78,'内訳ﾘｽﾄ(4～3月)'!L$16:L$23),IF('内訳ﾘｽﾄ(4～3月)'!$D$5="工場間接",-I$74,0)) -> 3 | J78: =IF('内訳ﾘｽﾄ(4～3月)'!$D$5="製造",SUMIF('内訳ﾘｽﾄ(4～3月)'!$D$16:$D$23,$B78,'内訳ﾘｽﾄ(4～3月)'!M$16:M$23),IF('内訳ﾘｽﾄ(4～3月)'!$D$5="工場間接",-J$74,0)) -> 3 | ... N78: =IF('内訳ﾘｽﾄ(4～3月)'!$D$5="製造",SUMIF('内訳ﾘｽﾄ(4～3月)'!$D$16:$D$23,$B78,'内訳ﾘｽﾄ(4～3月)'!Q$16:Q$23),IF('内訳ﾘｽﾄ(4～3月)'!$D$5="工場間接",-N$74,0)) -> 2.75 | O78: =IF('内訳ﾘｽﾄ(4～3月)'!$D$5="工場間接",-SUM(O$74),IF('内訳ﾘｽﾄ(4～3月)'!$D$5="製造",SUMIF('内訳ﾘｽﾄ(4～3月)'!$D$16:$D$23,'採算表(VND)'!$B78,'内訳ﾘｽﾄ(4～3月)'!$R$16:$R$23),0)) -> 37
B79: 残業時間合計 | C79: =SUM(C74:C78) -> 145 | D79: =SUM(D74:D78) -> 142.75 | E79: =SUM(E74:E78) -> 146.5 | F79: =SUM(F74:F78) -> 150.75 | G79: =SUM(G74:G78) -> 144.5 | H79: =SUM(H74:H78) -> 143.25 | I79: =SUM(I74:I78) -> 150.75 | J79: =SUM(J74:J78) -> 144.75 | ... N79: =SUM(N74:N78) -> 144.75 | O79: =IF(ISBLANK(O10),"",SUM(O74:O78)) -> 1731
B80: 当月時間当り | C80: =IFERROR(ROUNDDOWN(C66/C67,0),0) -> -33652 | D80: =IFERROR(ROUNDDOWN(D66/D67,0),0) -> 611776 | E80: =IFERROR(ROUNDDOWN(E66/E67,0),0) -> 423800 | F80: =IFERROR(ROUNDDOWN(F66/F67,0),0) -> 507237 | G80: =IFERROR(ROUNDDOWN(G66/G67,0),0) -> 564717 | H80: =IFERROR(ROUNDDOWN(H66/H67,0),0) -> 528141 | I80: =IFERROR(ROUNDDOWN(I66/I67,0),0) -> 386499 | J80: =IFERROR(ROUNDDOWN(J66/J67,0),0) -> 656066 | ... O80: =IFERROR(ROUNDDOWN(O66/O67,0),0) -> 485856
B81: 時間当り生産高 | C81: =IFERROR(ROUNDDOWN(C12/C67,0),0) -> 0 | D81: =IFERROR(ROUNDDOWN(D12/D67,0),0) -> 666657 | E81: =IFERROR(ROUNDDOWN(E12/E67,0),0) -> 509474 | F81: =IFERROR(ROUNDDOWN(F12/F67,0),0) -> 540046 | G81: =IFERROR(ROUNDDOWN(G12/G67,0),0) -> 607085 | H81: =IFERROR(ROUNDDOWN(H12/H67,0),0) -> 612783 | I81: =IFERROR(ROUNDDOWN(I12/I67,0),0) -> 501005 | J81: =IFERROR(ROUNDDOWN(J12/J67,0),0) -> 680983 | ... O81: =IFERROR(ROUNDDOWN(O12/O67,0),0) -> 544794
B86: ■人員
B87: 出向社員(人) | C87: =SUMIF('内訳ﾘｽﾄ(4～3月)'!$D$24:$D$25,'採算表(VND)'!$B87,'内訳ﾘｽﾄ(4～3月)'!F$24:F$25) -> 1 | D87: =SUMIF('内訳ﾘｽﾄ(4～3月)'!$D$24:$D$25,'採算表(VND)'!$B87,'内訳ﾘｽﾄ(4～3月)'!G$24:G$25) -> 1 | E87: =SUMIF('内訳ﾘｽﾄ(4～3月)'!$D$24:$D$25,'採算表(VND)'!$B87,'内訳ﾘｽﾄ(4～3月)'!H$24:H$25) -> 1 | F87: =SUMIF('内訳ﾘｽﾄ(4～3月)'!$D$24:$D$25,'採算表(VND)'!$B87,'内訳ﾘｽﾄ(4～3月)'!I$24:I$25) -> 1 | G87: =SUMIF('内訳ﾘｽﾄ(4～3月)'!$D$24:$D$25,'採算表(VND)'!$B87,'内訳ﾘｽﾄ(4～3月)'!J$24:J$25) -> 1 | H87: =SUMIF('内訳ﾘｽﾄ(4～3月)'!$D$24:$D$25,'採算表(VND)'!$B87,'内訳ﾘｽﾄ(4～3月)'!K$24:K$25) -> 1 | I87: =SUMIF('内訳ﾘｽﾄ(4～3月)'!$D$24:$D$25,'採算表(VND)'!$B87,'内訳ﾘｽﾄ(4～3月)'!L$24:L$25) -> 1 | J87: =SUMIF('内訳ﾘｽﾄ(4～3月)'!$D$24:$D$25,'採算表(VND)'!$B87,'内訳ﾘｽﾄ(4～3月)'!M$24:M$25) -> 1 | ... O87: =SUMIF('内訳ﾘｽﾄ(4～3月)'!$D$24:$D$25,'採算表(VND)'!$B87,'内訳ﾘｽﾄ(4～3月)'!R$24:R$25) -> 1
B88: ローカル社員(人) | C88: =SUMIF('内訳ﾘｽﾄ(4～3月)'!$D$24:$D$25,'採算表(VND)'!$B88,'内訳ﾘｽﾄ(4～3月)'!F$24:F$25) -> 7 | D88: =SUMIF('内訳ﾘｽﾄ(4～3月)'!$D$24:$D$25,'採算表(VND)'!$B88,'内訳ﾘｽﾄ(4～3月)'!G$24:G$25) -> 7 | E88: =SUMIF('内訳ﾘｽﾄ(4～3月)'!$D$24:$D$25,'採算表(VND)'!$B88,'内訳ﾘｽﾄ(4～3月)'!H$24:H$25) -> 7 | F88: =SUMIF('内訳ﾘｽﾄ(4～3月)'!$D$24:$D$25,'採算表(VND)'!$B88,'内訳ﾘｽﾄ(4～3月)'!I$24:I$25) -> 7 | G88: =SUMIF('内訳ﾘｽﾄ(4～3月)'!$D$24:$D$25,'採算表(VND)'!$B88,'内訳ﾘｽﾄ(4～3月)'!J$24:J$25) -> 7 | H88: =SUMIF('内訳ﾘｽﾄ(4～3月)'!$D$24:$D$25,'採算表(VND)'!$B88,'内訳ﾘｽﾄ(4～3月)'!K$24:K$25) -> 8 | I88: =SUMIF('内訳ﾘｽﾄ(4～3月)'!$D$24:$D$25,'採算表(VND)'!$B88,'内訳ﾘｽﾄ(4～3月)'!L$24:L$25) -> 8 | J88: =SUMIF('内訳ﾘｽﾄ(4～3月)'!$D$24:$D$25,'採算表(VND)'!$B88,'内訳ﾘｽﾄ(4～3月)'!M$24:M$25) -> 8 | ... O88: =SUMIF('内訳ﾘｽﾄ(4～3月)'!$D$24:$D$25,'採算表(VND)'!$B88,'内訳ﾘｽﾄ(4～3月)'!R$24:R$25) -> 8
B89: 人員計 | C89: =C87+C88 -> 8 | D89: =D87+D88 -> 8 | E89: =E87+E88 -> 8 | F89: =F87+F88 -> 8 | G89: =G87+G88 -> 8 | H89: =H87+H88 -> 9 | I89: =I87+I88 -> 9 | J89: =J87+J88 -> 9 | ... O89: =O87+O88 -> 9
B91: ■定時間
B92: 出向社員定時 | C92: =SUMIF('内訳ﾘｽﾄ(4～3月)'!$B$8:$B$15,$B92,'内訳ﾘｽﾄ(4～3月)'!F$8:F$15) -> 170 | D92: =SUMIF('内訳ﾘｽﾄ(4～3月)'!$B$8:$B$15,$B92,'内訳ﾘｽﾄ(4～3月)'!G$8:G$15) -> 161.5 | E92: =SUMIF('内訳ﾘｽﾄ(4～3月)'!$B$8:$B$15,$B92,'内訳ﾘｽﾄ(4～3月)'!H$8:H$15) -> 178.5 | F92: =SUMIF('内訳ﾘｽﾄ(4～3月)'!$B$8:$B$15,$B92,'内訳ﾘｽﾄ(4～3月)'!I$8:I$15) -> 195.5 | G92: =SUMIF('内訳ﾘｽﾄ(4～3月)'!$B$8:$B$15,$B92,'内訳ﾘｽﾄ(4～3月)'!J$8:J$15) -> 170 | H92: =SUMIF('内訳ﾘｽﾄ(4～3月)'!$B$8:$B$15,$B92,'内訳ﾘｽﾄ(4～3月)'!K$8:K$15) -> 161.5 | I92: =SUMIF('内訳ﾘｽﾄ(4～3月)'!$B$8:$B$15,$B92,'内訳ﾘｽﾄ(4～3月)'!L$8:L$15) -> 195.5 | J92: =SUMIF('内訳ﾘｽﾄ(4～3月)'!$B$8:$B$15,$B92,'内訳ﾘｽﾄ(4～3月)'!M$8:M$15) -> 170 | ... O92: =SUMIF('内訳ﾘｽﾄ(4～3月)'!$B$8:$B$15,$B92,'内訳ﾘｽﾄ(4～3月)'!R$8:R$15) -> 2014.5
B93: ローカル社員定時 | C93: =SUMIF('内訳ﾘｽﾄ(4～3月)'!$B$8:$B$15,$B93,'内訳ﾘｽﾄ(4～3月)'!F$8:F$15) -> 1156 | D93: =SUMIF('内訳ﾘｽﾄ(4～3月)'!$B$8:$B$15,$B93,'内訳ﾘｽﾄ(4～3月)'!G$8:G$15) -> 1096.5 | E93: =SUMIF('内訳ﾘｽﾄ(4～3月)'!$B$8:$B$15,$B93,'内訳ﾘｽﾄ(4～3月)'!H$8:H$15) -> 1215.5 | F93: =SUMIF('内訳ﾘｽﾄ(4～3月)'!$B$8:$B$15,$B93,'内訳ﾘｽﾄ(4～3月)'!I$8:I$15) -> 1334.5 | G93: =SUMIF('内訳ﾘｽﾄ(4～3月)'!$B$8:$B$15,$B93,'内訳ﾘｽﾄ(4～3月)'!J$8:J$15) -> 1156 | H93: =SUMIF('内訳ﾘｽﾄ(4～3月)'!$B$8:$B$15,$B93,'内訳ﾘｽﾄ(4～3月)'!K$8:K$15) -> 1258 | I93: =SUMIF('内訳ﾘｽﾄ(4～3月)'!$B$8:$B$15,$B93,'内訳ﾘｽﾄ(4～3月)'!L$8:L$15) -> 1530 | J93: =SUMIF('内訳ﾘｽﾄ(4～3月)'!$B$8:$B$15,$B93,'内訳ﾘｽﾄ(4～3月)'!M$8:M$15) -> 1326 | ... O93: =SUMIF('内訳ﾘｽﾄ(4～3月)'!$B$8:$B$15,$B93,'内訳ﾘｽﾄ(4～3月)'!R$8:R$15) -> 15172.5
B94: 人員計 | C94: =C92+C93 -> 1326 | D94: =D92+D93 -> 1258 | E94: =E92+E93 -> 1394 | F94: =F92+F93 -> 1530 | G94: =G92+G93 -> 1326 | H94: =H92+H93 -> 1419.5 | I94: =I92+I93 -> 1725.5 | J94: =J92+J93 -> 1496 | ... O94: =O92+O93 -> 17187
B96: ■残業時間
B97: 出向社員残業 | C97: =SUMIF('内訳ﾘｽﾄ(4～3月)'!$B$16:$B$23,$B97,'内訳ﾘｽﾄ(4～3月)'!F$16:F$23) -> 40 | D97: =SUMIF('内訳ﾘｽﾄ(4～3月)'!$B$16:$B$23,$B97,'内訳ﾘｽﾄ(4～3月)'!G$16:G$23) -> 38 | E97: =SUMIF('内訳ﾘｽﾄ(4～3月)'!$B$16:$B$23,$B97,'内訳ﾘｽﾄ(4～3月)'!H$16:H$23) -> 42 | F97: =SUMIF('内訳ﾘｽﾄ(4～3月)'!$B$16:$B$23,$B97,'内訳ﾘｽﾄ(4～3月)'!I$16:I$23) -> 46 | G97: =SUMIF('内訳ﾘｽﾄ(4～3月)'!$B$16:$B$23,$B97,'内訳ﾘｽﾄ(4～3月)'!J$16:J$23) -> 40 | H97: =SUMIF('内訳ﾘｽﾄ(4～3月)'!$B$16:$B$23,$B97,'内訳ﾘｽﾄ(4～3月)'!K$16:K$23) -> 38 | I97: =SUMIF('内訳ﾘｽﾄ(4～3月)'!$B$16:$B$23,$B97,'内訳ﾘｽﾄ(4～3月)'!L$16:L$23) -> 46 | J97: =SUMIF('内訳ﾘｽﾄ(4～3月)'!$B$16:$B$23,$B97,'内訳ﾘｽﾄ(4～3月)'!M$16:M$23) -> 40 | ... O97: =SUMIF('内訳ﾘｽﾄ(4～3月)'!$B$16:$B$23,$B97,'内訳ﾘｽﾄ(4～3月)'!R$16:R$23) -> 474
B98: ローカル社員残業 | C98: =SUMIF('内訳ﾘｽﾄ(4～3月)'!$B$16:$B$23,$B98,'内訳ﾘｽﾄ(4～3月)'!F$16:F$23) -> 100 | D98: =SUMIF('内訳ﾘｽﾄ(4～3月)'!$B$16:$B$23,$B98,'内訳ﾘｽﾄ(4～3月)'!G$16:G$23) -> 100 | E98: =SUMIF('内訳ﾘｽﾄ(4～3月)'!$B$16:$B$23,$B98,'内訳ﾘｽﾄ(4～3月)'!H$16:H$23) -> 100 | F98: =SUMIF('内訳ﾘｽﾄ(4～3月)'!$B$16:$B$23,$B98,'内訳ﾘｽﾄ(4～3月)'!I$16:I$23) -> 100 | G98: =SUMIF('内訳ﾘｽﾄ(4～3月)'!$B$16:$B$23,$B98,'内訳ﾘｽﾄ(4～3月)'!J$16:J$23) -> 100 | H98: =SUMIF('内訳ﾘｽﾄ(4～3月)'!$B$16:$B$23,$B98,'内訳ﾘｽﾄ(4～3月)'!K$16:K$23) -> 100 | I98: =SUMIF('内訳ﾘｽﾄ(4～3月)'!$B$16:$B$23,$B98,'内訳ﾘｽﾄ(4～3月)'!L$16:L$23) -> 100 | J98: =SUMIF('内訳ﾘｽﾄ(4～3月)'!$B$16:$B$23,$B98,'内訳ﾘｽﾄ(4～3月)'!M$16:M$23) -> 100 | ... O98: =SUMIF('内訳ﾘｽﾄ(4～3月)'!$B$16:$B$23,$B98,'内訳ﾘｽﾄ(4～3月)'!R$16:R$23) -> 1200
B99: 人員計 | C99: =C97+C98 -> 140 | D99: =D97+D98 -> 138 | E99: =E97+E98 -> 142 | F99: =F97+F98 -> 146 | G99: =G97+G98 -> 140 | H99: =H97+H98 -> 138 | I99: =I97+I98 -> 146 | J99: =J97+J98 -> 140 | ... O99: =O97+O98 -> 1674

Sheet 内訳ﾘｽﾄ(4～3月)
A1: MP FY2026_各予定
B2: 25390 | E2: 稼働日数 | F2: =OFFSET(稼働日!$B$2,MATCH('内訳ﾘｽﾄ(4～3月)'!F4,稼働日!$A$3:$A$14,0),0) -> 20 | G2: =OFFSET(稼働日!$B$2,MATCH('内訳ﾘｽﾄ(4～3月)'!G4,稼働日!$A$3:$A$14,0),0) -> 19 | H2: =OFFSET(稼働日!$B$2,MATCH('内訳ﾘｽﾄ(4～3月)'!H4,稼働日!$A$3:$A$14,0),0) -> 21 | I2: =OFFSET(稼働日!$B$2,MATCH('内訳ﾘｽﾄ(4～3月)'!I4,稼働日!$A$3:$A$14,0),0) -> 23 | J2: =OFFSET(稼働日!$B$2,MATCH('内訳ﾘｽﾄ(4～3月)'!J4,稼働日!$A$3:$A$14,0),0) -> 20 | K2: =OFFSET(稼働日!$B$2,MATCH('内訳ﾘｽﾄ(4～3月)'!K4,稼働日!$A$3:$A$14,0),0) -> 19 | L2: =OFFSET(稼働日!$B$2,MATCH('内訳ﾘｽﾄ(4～3月)'!L4,稼働日!$A$3:$A$14,0),0) -> 23 | M2: =OFFSET(稼働日!$B$2,MATCH('内訳ﾘｽﾄ(4～3月)'!M4,稼働日!$A$3:$A$14,0),0) -> 20 | ... Q2: =OFFSET(稼働日!$B$2,MATCH('内訳ﾘｽﾄ(4～3月)'!Q4,稼働日!$A$3:$A$14,0),0) -> 20
E3: CHECK | F3: {=IF(SUM((F8:F25)-ROUNDDOWN((F8:F25)*4,0)/4)<>0,"時間➝0.25の倍数では無い",IF(SUM(ROUND((F26:F1000),0)-ROUND((F26:F1000),4))<>0,"経費➝小数点",IF(F5<>IF($D$5="製造",'採算表(VND)'!C13,-VLOOKUP($D$5&"経費",'採算表(VND)'!$B:$N,'採算表(VND)'!C3,0)),"経費➝NG","OK")))} -> OK | G3: {=IF(SUM((G8:G25)-ROUNDDOWN((G8:G25)*4,0)/4)<>0,"時間➝0.25の倍数では無い",IF(SUM(ROUND((G26:G1000),0)-ROUND((G26:G1000),4))<>0,"経費➝小数点",IF(G5<>IF($D$5="製造",'採算表(VND)'!D13,-VLOOKUP($D$5&"経費",'採算表(VND)'!$B:$N,'採算表(VND)'!D3,0)),"経費➝NG","OK")))} -> OK | H3: {=IF(SUM((H8:H25)-ROUNDDOWN((H8:H25)*4,0)/4)<>0,"時間➝0.25の倍数では無い",IF(SUM(ROUND((H26:H1000),0)-ROUND((H26:H1000),4))<>0,"経費➝小数点",IF(H5<>IF($D$5="製造",'採算表(VND)'!E13,-VLOOKUP($D$5&"経費",'採算表(VND)'!$B:$N,'採算表(VND)'!E3,0)),"経費➝NG","OK")))} -> OK | I3: {=IF(SUM((I8:I25)-ROUNDDOWN((I8:I25)*4,0)/4)<>0,"時間➝0.25の倍数では無い",IF(SUM(ROUND((I26:I1000),0)-ROUND((I26:I1000),4))<>0,"経費➝小数点",IF(I5<>IF($D$5="製造",'採算表(VND)'!F13,-VLOOKUP($D$5&"経費",'採算表(VND)'!$B:$N,'採算表(VND)'!F3,0)),"経費➝NG","OK")))} -> OK | J3: {=IF(SUM((J8:J25)-ROUNDDOWN((J8:J25)*4,0)/4)<>0,"時間➝0.25の倍数では無い",IF(SUM(ROUND((J26:J1000),0)-ROUND((J26:J1000),4))<>0,"経費➝小数点",IF(J5<>IF($D$5="製造",'採算表(VND)'!G13,-VLOOKUP($D$5&"経費",'採算表(VND)'!$B:$N,'採算表(VND)'!G3,0)),"経費➝NG","OK")))} -> OK | K3: {=IF(SUM((K8:K25)-ROUNDDOWN((K8:K25)*4,0)/4)<>0,"時間➝0.25の倍数では無い",IF(SUM(ROUND((K26:K1000),0)-ROUND((K26:K1000),4))<>0,"経費➝小数点",IF(K5<>IF($D$5="製造",'採算表(VND)'!H13,-VLOOKUP($D$5&"経費",'採算表(VND)'!$B:$N,'採算表(VND)'!H3,0)),"経費➝NG","OK")))} -> OK | L3: {=IF(SUM((L8:L25)-ROUNDDOWN((L8:L25)*4,0)/4)<>0,"時間➝0.25の倍数では無い",IF(SUM(ROUND((L26:L1000),0)-ROUND((L26:L1000),4))<>0,"経費➝小数点",IF(L5<>IF($D$5="製造",'採算表(VND)'!I13,-VLOOKUP($D$5&"経費",'採算表(VND)'!$B:$N,'採算表(VND)'!I3,0)),"経費➝NG","OK")))} -> OK | M3: {=IF(SUM((M8:M25)-ROUNDDOWN((M8:M25)*4,0)/4)<>0,"時間➝0.25の倍数では無い",IF(SUM(ROUND((M26:M1000),0)-ROUND((M26:M1000),4))<>0,"経費➝小数点",IF(M5<>IF($D$5="製造",'採算表(VND)'!J13,-VLOOKUP($D$5&"経費",'採算表(VND)'!$B:$N,'採算表(VND)'!J3,0)),"経費➝NG","OK")))} -> OK | ... Q3: {=IF(SUM((Q8:Q25)-ROUNDDOWN((Q8:Q25)*4,0)/4)<>0,"時間➝0.25の倍数では無い",IF(SUM(ROUND((Q26:Q1000),0)-ROUND((Q26:Q1000),4))<>0,"経費➝小数点",IF(Q5<>IF($D$5="製造",'採算表(VND)'!N13,-VLOOKUP($D$5&"経費",'採算表(VND)'!$B:$N,'採算表(VND)'!N3,0)),"経費➝NG","OK")))} -> OK
B4: 原価センター | C4: 組織名 | D4: 採算区分 | E4: 原価区分 | F4: 4 | G4: 5 | H4: 6 | I4: 7 | J4: 8 | K4: 9 | L4: 10 | M4: 11 | N4: 12 | O4: 1 | P4: 2 | Q4: 3 | R4: 合計 | S4: ※MEBIUS経費になると "V02V0800" は T列に 反映お願いします
B5: 1412000101 | C5: =VLOOKUP($B$5,原価センタ!$A:$E,2,0) -> EI2課 | D5: =VLOOKUP($B$5,原価センタ!$A:$E,4,0) -> 製造 | E5: =VLOOKUP($B$5,原価センタ!$A:$E,5,0) -> 製造 | F5: =SUM(F29:F1000) -> 52076543 | G5: =SUM(G29:G1000) -> 81031255 | H5: =SUM(H29:H1000) -> 138985384 | I5: =SUM(I29:I1000) -> 58046167 | J5: =SUM(J29:J1000) -> 65649208 | K5: =SUM(K29:K1000) -> 138559879 | L5: =SUM(L29:L1000) -> 225089418 | M5: =SUM(M29:M1000) -> 42889147 | ... R5: =SUM(R29:R1000) -> 1171488828
C7: 勘定科目名称 | D7: 採算科目 | E7: ﾃｰﾏｺｰﾄﾞ | F7: MP | G7: MP | H7: MP | I7: MP | J7: MP | K7: MP | L7: MP | M7: MP | N7: MP | O7: MP | P7: MP | Q7: MP | R7: MP | S7: 備考 | T7: WBS | BC7: WBS
B8: 出向社員定時 | C8: 定時間（日本社員） | D8: 直接部門 | F8: 170 | G8: 161.5 | H8: 178.5 | I8: 195.5 | J8: 170 | K8: 161.5 | L8: 195.5 | M8: 170 | N8: 187 | O8: 127.5 | P8: 127.5 | Q8: 170 | R8: =SUM(F8:Q8) -> 2014.5
B9: ローカル社員定時 | C9: 定時間（ベトナム社員） | D9: 直接部門 | F9: 1156 | G9: 1096.5 | H9: 1215.5 | I9: 1334.5 | J9: 1156 | K9: 1258 | L9: 1530 | M9: 1326 | N9: 1462 | O9: 1326 | P9: 986 | Q9: 1326 | R9: =SUM(F9:Q9) -> 15172.5
B10: 出向社員定時 | C10: 定時間（移動分日本社員） | D10: 直接部門 | R10: =SUM(F10:Q10) -> 0
B11: ローカル社員定時 | C11: 定時間（移動分ベトナム社員） | D11: 直接部門 | R11: =SUM(F11:Q11) -> 0
C12: 定時間（部内間接部門） | D12: 部内間接部門 | F12: 0 | G12: 0 | H12: 0 | I12: 0 | J12: 0 | K12: 0 | L12: 0 | M12: 0 | N12: 0 | O12: 0 | P12: 0 | Q12: 0 | R12: =SUM(F12:Q12) -> 0 | S12: この分には間接部門から直接部門に配賦された数字
C13: 定時間（部外間接部門1） | D13: 部外間接部門1 | F13: 6.75 | G13: 7 | H13: 7.75 | I13: 8.25 | J13: 7 | K13: 6.5 | L13: 8.25 | M13: 7.25 | N13: 8 | O13: 7.5 | P13: 5.5 | Q13: 7.5 | R13: =SUM(F13:Q13) -> 87.25 | S13: この分には間接部門から直接部門に配賦された数字
C14: 定時間（部外間接部門2） | D14: 部外間接部門2 | F14: 12.75 | G14: 12.25 | H14: 14 | I14: 15.5 | J14: 13 | K14: 13 | L14: 16.25 | M14: 14 | N14: 15.5 | O14: 14.25 | P14: 10.75 | Q14: 14 | R14: =SUM(F14:Q14) -> 165.25 | S14: この分には間接部門から直接部門に配賦された数字
C15: 定時間（工場間接部門） | D15: 工場間接部門 | F15: 57 | G15: 56.5 | H15: 60 | I15: 64.75 | J15: 59 | K15: 54.75 | L15: 65 | M15: 59.25 | N15: 63.75 | O15: 60.25 | P15: 45.25 | Q15: 60.5 | R15: =SUM(F15:Q15) -> 706 | S15: この分には間接部門から直接部門に配賦された数字
B16: 出向社員残業 | C16: 残業時間（日本社員） | D16: 直接部門 | F16: 40 | G16: 38 | H16: 42 | I16: 46 | J16: 40 | K16: 38 | L16: 46 | M16: 40 | N16: 44 | O16: 30 | P16: 30 | Q16: 40 | R16: =SUM(F16:Q16) -> 474
B17: ローカル社員残業 | C17: 残業時間（ベトナム社員） | D17: 直接部門 | F17: 100 | G17: 100 | H17: 100 | I17: 100 | J17: 100 | K17: 100 | L17: 100 | M17: 100 | N17: 100 | O17: 100 | P17: 100 | Q17: 100 | R17: =SUM(F17:Q17) -> 1200 | S17: =$R$362&S362 -> 0
B18: 出向社員残業 | C18: 残業時間（移動分日本社員） | D18: 直接部門 | R18: =SUM(F18:Q18) -> 0
B19: ローカル社員残業 | C19: 残業時間（移動分ベトナム社員） | D19: 直接部門 | R19: =SUM(F19:Q19) -> 0
C20: 残業時間（部内間接部門） | D20: 部内間接部門 | F20: 0 | G20: 0 | H20: 0 | I20: 0 | J20: 0 | K20: 0 | L20: 0 | M20: 0 | N20: 0 | O20: 0 | P20: 0 | Q20: 0 | R20: =SUM(F20:Q20) -> 0 | S20: この分には間接部門から直接部門に配賦された数字
C21: 残業時間（部外間接部門1） | D21: 部外間接部門1 | F21: 0.5 | G21: 0.5 | H21: 0.5 | I21: 0.5 | J21: 0.5 | K21: 0.5 | L21: 0.5 | M21: 0.5 | N21: 0.5 | O21: 0.5 | P21: 0.25 | Q21: 0.5 | R21: =SUM(F21:Q21) -> 5.75 | S21: この分には間接部門から直接部門に配賦された数字
C22: 残業時間（部外間接部門2） | D22: 部外間接部門2 | F22: 1.25 | G22: 1 | H22: 1.25 | I22: 1.25 | J22: 1.25 | K22: 1 | L22: 1.25 | M22: 1.25 | N22: 1.25 | O22: 1.5 | P22: 0.5 | Q22: 1.5 | R22: =SUM(F22:Q22) -> 14.25 | S22: この分には間接部門から直接部門に配賦された数字
C23: 残業時間（工場間接部門） | D23: 工場間接部門 | F23: 3.25 | G23: 3.25 | H23: 2.75 | I23: 3 | J23: 2.75 | K23: 3.75 | L23: 3 | M23: 3 | N23: 3 | O23: 2.75 | P23: 3.75 | Q23: 2.75 | R23: =SUM(F23:Q23) -> 37 | S23: この分には間接部門から直接部門に配賦された数字
B24: 出向社員(人) | C24: 出向社員(人) | D24: 出向社員(人) | F24: 1 | G24: 1 | H24: 1 | I24: 1 | J24: 1 | K24: 1 | L24: 1 | M24: 1 | N24: 1 | O24: 1 | P24: 1 | Q24: 1 | R24: =Q24 -> 1
B25: ローカル社員(人) | C25: ローカル社員(人) | D25: ローカル社員(人) | F25: 7 | G25: 7 | H25: 7 | I25: 7 | J25: 7 | K25: 8 | L25: 8 | M25: 8 | N25: 8 | O25: 8 | P25: 8 | Q25: 8 | R25: =Q25 -> 8 | V25: 4 | W25: 5 | X25: 6 | Y25: 7 | Z25: 8 | AA25: 9 | AB25: 10 | AC25: 11 | AD25: 12 | AE25: 1 | AF25: 2 | AG25: 3
B26: 9114120002 | C26: 社外出荷 | D26: 社外出荷 | F26: =ROUNDDOWN(V26*$B$2,0) -> 0 | G26: =ROUNDDOWN(W26*$B$2,0) -> 984319520 | H26: =ROUNDDOWN(X26*$B$2,0) -> 826495280 | I26: =ROUNDDOWN(Y26*$B$2,0) -> 955476480 | J26: =ROUNDDOWN(Z26*$B$2,0)+1 -> 940679442 | K26: =ROUNDDOWN(AA26*$B$2,0)+1 -> 1003126909 | L26: =ROUNDDOWN(AB26*$B$2,0)+1 -> 984850679 | M26: =ROUNDDOWN(AC26*$B$2,0)+1 -> 1172143061 | N26: =ROUNDDOWN(AD26*$B$2,0)+1 -> 991707757 | O26: =ROUNDDOWN(AE26*$B$2,0)+1 -> 1004452267 | P26: =ROUNDDOWN(AF26*$B$2,0)+1 -> 993069930 | Q26: =ROUNDDOWN(AG26*$B$2,0)+1 -> 972287961 | R26: =SUM(F26:Q26) -> 10828609286 | S26: 総生産情報 | V26: 0 | W26: 38768 | X26: 32552 | Y26: 37632 | Z26: 37049.21 | AA26: 39508.74 | AB26: 38788.92 | AC26: 46165.54 | AD26: 39058.99 | AE26: 39560.94 | AF26: 39112.64 | AG26: 38294.13
B27: 9114120004 | C27: 社内売 | D27: 社内売 | F27: 0 | G27: 0 | H27: 0 | I27: 0 | J27: 0 | K27: 0 | L27: 0 | M27: 0 | N27: 0 | O27: 0 | P27: 0 | Q27: 0 | R27: =SUM(F27:Q27) -> 0 | S27: 総生産情報
B28: 9114120014 | C28: 社内買 | D28: 社内買 | F28: 0 | G28: 0 | H28: 0 | I28: 0 | J28: 0 | K28: 0 | L28: 0 | M28: 0 | N28: 0 | O28: 0 | P28: 0 | Q28: 0 | R28: =SUM(F28:Q28) -> 0 | S28: 総生産情報
B29: 9114120006 | C29: 材料費(指図出庫） | D29: 材料費 | F29: 0 | G29: 0 | H29: 0 | I29: 0 | J29: 0 | K29: 0 | L29: 0 | M29: 0 | N29: 0 | O29: 0 | P29: 0 | Q29: 0 | R29: =SUM(F29:Q29) -> 0 | S29: 総生産情報
C30: =IFERROR(IF(VLOOKUP($B30,[1]勘定科目!$A:$H,HLOOKUP($E$5,[1]勘定科目!$F$1:$H$2,2,0),0)="","",VLOOKUP($B30,[1]勘定科目!$A:$E,2,0)),"") | D30: =IF(C30="","",VLOOKUP($B30,[1]勘定科目!$A:$E,4,0)) | R30: =SUM(F30:Q30) -> 0
B31: 9114120018 | C31: =IFERROR(IF(VLOOKUP($B31,[1]勘定科目!$A:$H,HLOOKUP($E$5,[1]勘定科目!$F$1:$H$2,2,0),0)="","",VLOOKUP($B31,[1]勘定科目!$A:$E,2,0)),"") -> 部内間接経費 | D31: =IF(C31="","",VLOOKUP($B31,[1]勘定科目!$A:$E,4,0)) -> 部内間接経費 | F31: 0 | G31: 0 | H31: 0 | I31: 0 | J31: 0 | K31: 0 | L31: 0 | M31: 0 | N31: 0 | O31: 0 | P31: 0 | Q31: 0 | R31: =SUM(F31:Q31) -> 0 | S31: この分には間接部門から直接部門に配賦された数字
B32: 9114120029 | C32: =IFERROR(IF(VLOOKUP($B32,[1]勘定科目!$A:$H,HLOOKUP($E$5,[1]勘定科目!$F$1:$H$2,2,0),0)="","",VLOOKUP($B32,[1]勘定科目!$A:$E,2,0)),"") -> 部外間接経費1 | D32: =IF(C32="","",VLOOKUP($B32,[1]勘定科目!$A:$E,4,0)) -> 部外間接経費1 | F32: 397747 | G32: 456533 | H32: 380030 | I32: 418678 | J32: 376428 | K32: 411955 | L32: 371559 | M32: 373981 | N32: 377739 | O32: 363365 | P32: 384659 | Q32: 367741 | R32: =SUM(F32:Q32) -> 4680415 | S32: この分には間接部門から直接部門に配賦された数字
B33: 9114120030 | C33: =IFERROR(IF(VLOOKUP($B33,[1]勘定科目!$A:$H,HLOOKUP($E$5,[1]勘定科目!$F$1:$H$2,2,0),0)="","",VLOOKUP($B33,[1]勘定科目!$A:$E,2,0)),"") -> 部外間接経費2 | D33: =IF(C33="","",VLOOKUP($B33,[1]勘定科目!$A:$E,4,0)) -> 部外間接経費2 | F33: 2428303 | G33: 829821 | H33: 594135 | I33: 640119 | J33: 574687 | K33: 516775 | L33: 646365 | M33: 664788 | N33: 642056 | O33: 502071 | P33: 525411 | Q33: 516392 | R33: =SUM(F33:Q33) -> 9080923 | S33: この分には間接部門から直接部門に配賦された数字
B34: 9114120021 | C34: =IFERROR(IF(VLOOKUP($B34,[1]勘定科目!$A:$H,HLOOKUP($E$5,[1]勘定科目!$F$1:$H$2,2,0),0)="","",VLOOKUP($B34,[1]勘定科目!$A:$E,2,0)),"") -> 工場間接経費 | D34: =IF(C34="","",VLOOKUP($B34,[1]勘定科目!$A:$E,4,0)) -> 工場間接経費 | F34: 28869303 | G34: 36883353 | H34: 27306721 | I34: 39335822 | J34: 21916820 | K34: 21422341 | L34: 27208206 | M34: 22922165 | N34: 22670431 | O34: 25237009 | P34: 17427491 | Q34: 17985040 | R34: =SUM(F34:Q34) -> 309184702 | S34: この分には間接部門から直接部門に配賦された数字
C35: =IFERROR(IF(VLOOKUP($B35,[1]勘定科目!$A:$H,HLOOKUP($E$5,[1]勘定科目!$F$1:$H$2,2,0),0)="","",VLOOKUP($B35,[1]勘定科目!$A:$E,2,0)),"") | D35: =IF(C35="","",VLOOKUP($B35,[1]勘定科目!$A:$E,4,0)) | R35: =SUM(F35:Q35) -> 0
B36: 9114120009 | C36: =IFERROR(IF(VLOOKUP($B36,[1]勘定科目!$A:$H,HLOOKUP($E$5,[1]勘定科目!$F$1:$H$2,2,0),0)="","",VLOOKUP($B36,[1]勘定科目!$A:$E,2,0)),"") -> 社内金利（在庫） | D36: =IF(C36="","",VLOOKUP($B36,[1]勘定科目!$A:$E,4,0)) -> 在庫金利 | F36: 0 | G36: 0 | H36: 0 | I36: 0 | J36: 0 | K36: 0 | L36: 0 | M36: 0 | N36: 0 | O36: 0 | P36: 0 | Q36: 0 | R36: =SUM(F36:Q36) -> 0 | S36: 経営管理にもらうデータ
C37: =IFERROR(IF(VLOOKUP($B37,[1]勘定科目!$A:$H,HLOOKUP($E$5,[1]勘定科目!$F$1:$H$2,2,0),0)="","",VLOOKUP($B37,[1]勘定科目!$A:$E,2,0)),"") | D37: =IF(C37="","",VLOOKUP($B37,[1]勘定科目!$A:$E,4,0)) | R37: =SUM(F37:Q37) -> 0
C38: =IFERROR(IF(VLOOKUP($B38,[1]勘定科目!$A:$H,HLOOKUP($E$5,[1]勘定科目!$F$1:$H$2,2,0),0)="","",VLOOKUP($B38,[1]勘定科目!$A:$E,2,0)),"") | D38: =IF(C38="","",VLOOKUP($B38,[1]勘定科目!$A:$E,4,0)) | R38: =SUM(F38:Q38) -> 0 | S38: 一般経費↓
B39: 5006016260 | C39: =IFERROR(IF(VLOOKUP($B39,[1]勘定科目!$A:$H,HLOOKUP($E$5,[1]勘定科目!$F$1:$H$2,2,0),0)="","",VLOOKUP($B39,[1]勘定科目!$A:$E,2,0)),"") -> 減価償却費配賦（製） 建物 | D39: =IF(C39="","",VLOOKUP($B39,[1]勘定科目!$A:$E,4,0)) -> 減価償却費 | F39: 3813451 | G39: 3813451 | H39: 3813451 | I39: 3813451 | J39: 3813451 | K39: 3813451 | L39: 3813451 | M39: 3813451 | N39: 3813451 | O39: 3813451 | P39: 3813451 | Q39: 3813451 | R39: =SUM(F39:Q39) -> 45761412 | S39: 減価償却費配賦 建物
B40: 5006016261 | C40: =IFERROR(IF(VLOOKUP($B40,[1]勘定科目!$A:$H,HLOOKUP($E$5,[1]勘定科目!$F$1:$H$2,2,0),0)="","",VLOOKUP($B40,[1]勘定科目!$A:$E,2,0)),"") -> 減価償却費配賦（製） 土地使用権 | D40: =IF(C40="","",VLOOKUP($B40,[1]勘定科目!$A:$E,4,0)) -> 減価償却費 | F40: 258089 | G40: 258089 | H40: 258089 | I40: 258089 | J40: 258089 | K40: 258089 | L40: 258089 | M40: 258089 | N40: 258089 | O40: 258089 | P40: 258089 | Q40: 258089 | R40: =SUM(F40:Q40) -> 3097068 | S40: 減価償却費配賦 土地使用権
B41: 9114120007 | C41: =IFERROR(IF(VLOOKUP($B41,[1]勘定科目!$A:$H,HLOOKUP($E$5,[1]勘定科目!$F$1:$H$2,2,0),0)="","",VLOOKUP($B41,[1]勘定科目!$A:$E,2,0)),"") -> 社内金利（固定資産） | D41: =IF(C41="","",VLOOKUP($B41,[1]勘定科目!$A:$E,4,0)) -> 固定資産金利 | F41: 1903107 | G41: 1903107 | H41: 1903107 | I41: 1903107 | J41: 1903107 | K41: 1903107 | L41: 1903107 | M41: 1903107 | N41: 1903107 | O41: 1903107 | P41: 1903107 | Q41: 1903107 | R41: =SUM(F41:Q41) -> 22837284 | S41: 固定資産金利 建物
B42: 9114120007 | C42: =IFERROR(IF(VLOOKUP($B42,[1]勘定科目!$A:$H,HLOOKUP($E$5,[1]勘定科目!$F$1:$H$2,2,0),0)="","",VLOOKUP($B42,[1]勘定科目!$A:$E,2,0)),"") -> 社内金利（固定資産） | D42: =IF(C42="","",VLOOKUP($B42,[1]勘定科目!$A:$E,4,0)) -> 固定資産金利 | F42: 226352 | G42: 226352 | H42: 226352 | I42: 226352 | J42: 226352 | K42: 226352 | L42: 226352 | M42: 226352 | N42: 226352 | O42: 226352 | P42: 226352 | Q42: 226352 | R42: =SUM(F42:Q42) -> 2716224 | S42: 固定資産金利 土地使用権
B43: 5005066281 | C43: =IFERROR(IF(VLOOKUP($B43,[1]勘定科目!$A:$H,HLOOKUP($E$5,[1]勘定科目!$F$1:$H$2,2,0),0)="","",VLOOKUP($B43,[1]勘定科目!$A:$E,2,0)),"") -> 電気代（製） | D43: =IF(C43="","",VLOOKUP($B43,[1]勘定科目!$A:$E,4,0)) -> 水道光熱費 | F43: 1271214 | G43: 1271214 | H43: 1271214 | I43: 1271214 | J43: 1271214 | K43: 1271214 | L43: 1271214 | M43: 1271214 | N43: 1271214 | O43: 1271214 | P43: 1271214 | Q43: 1271214 | R43: =SUM(F43:Q43) -> 15254568 | S43: 電気代
B44: 5005066282 | C44: =IFERROR(IF(VLOOKUP($B44,[1]勘定科目!$A:$H,HLOOKUP($E$5,[1]勘定科目!$F$1:$H$2,2,0),0)="","",VLOOKUP($B44,[1]勘定科目!$A:$E,2,0)),"") -> 水道代（製） | D44: =IF(C44="","",VLOOKUP($B44,[1]勘定科目!$A:$E,4,0)) -> 水道光熱費 | F44: 243403 | G44: 243403 | H44: 243403 | I44: 243403 | J44: 243403 | K44: 243403 | L44: 243403 | M44: 243403 | N44: 243403 | O44: 243403 | P44: 243403 | Q44: 243403 | R44: =SUM(F44:Q44) -> 2920836 | S44: 水道代
B45: 5005056281 | C45: =IFERROR(IF(VLOOKUP($B45,[1]勘定科目!$A:$H,HLOOKUP($E$5,[1]勘定科目!$F$1:$H$2,2,0),0)="","",VLOOKUP($B45,[1]勘定科目!$A:$E,2,0)),"") -> ガス代（製） | D45: =IF(C45="","",VLOOKUP($B45,[1]勘定科目!$A:$E,4,0)) -> 水道光熱費 | F45: 450850 | G45: 450850 | H45: 450850 | I45: 450850 | J45: 450850 | K45: 495935 | L45: 495935 | M45: 495935 | N45: 495935 | O45: 495935 | P45: 495935 | Q45: 495935 | R45: =SUM(F45:Q45) -> 5725795 | S45: ガス
B46: 5005016372 | C46: =IFERROR(IF(VLOOKUP($B46,[1]勘定科目!$A:$H,HLOOKUP($E$5,[1]勘定科目!$F$1:$H$2,2,0),0)="","",VLOOKUP($B46,[1]勘定科目!$A:$E,2,0)),"") -> その他消耗品（製） | D46: =IF(C46="","",VLOOKUP($B46,[1]勘定科目!$A:$E,4,0)) -> 消耗品費 | F46: 15200 | G46: 15200 | H46: 15200 | I46: 15200 | J46: 15200 | K46: 16720 | L46: 16720 | M46: 16720 | N46: 16720 | O46: 16720 | P46: 16720 | Q46: 16720 | R46: =SUM(F46:Q46) -> 193040 | S46: 手洗い洗剤
B47: 5005016372 | C47: =IFERROR(IF(VLOOKUP($B47,[1]勘定科目!$A:$H,HLOOKUP($E$5,[1]勘定科目!$F$1:$H$2,2,0),0)="","",VLOOKUP($B47,[1]勘定科目!$A:$E,2,0)),"") -> その他消耗品（製） | D47: =IF(C47="","",VLOOKUP($B47,[1]勘定科目!$A:$E,4,0)) -> 消耗品費 | F47: 179710 | G47: 179710 | H47: 179710 | I47: 179710 | J47: 179710 | K47: 197681 | L47: 197681 | M47: 197681 | N47: 197681 | O47: 197681 | P47: 197681 | Q47: 197681 | R47: =SUM(F47:Q47) -> 2282317 | S47: トイレットペーパー
B48: 5005016372 | C48: =IFERROR(IF(VLOOKUP($B48,[1]勘定科目!$A:$H,HLOOKUP($E$5,[1]勘定科目!$F$1:$H$2,2,0),0)="","",VLOOKUP($B48,[1]勘定科目!$A:$E,2,0)),"") -> その他消耗品（製） | D48: =IF(C48="","",VLOOKUP($B48,[1]勘定科目!$A:$E,4,0)) -> 消耗品費 | F48: 0 | G48: 0 | H48: 0 | I48: 0 | J48: 0 | K48: 0 | L48: 0 | M48: 0 | N48: 0 | O48: 0 | P48: 0 | Q48: 0 | R48: =SUM(F48:Q48) -> 0 | S48: アルコール 消毒
B49: 5005246286 | C49: =IFERROR(IF(VLOOKUP($B49,[1]勘定科目!$A:$H,HLOOKUP($E$5,[1]勘定科目!$F$1:$H$2,2,0),0)="","",VLOOKUP($B49,[1]勘定科目!$A:$E,2,0)),"") -> その他手数料（製） | D49: =IF(C49="","",VLOOKUP($B49,[1]勘定科目!$A:$E,4,0)) -> 手数料 | F49: 37670 | G49: 37670 | H49: 37670 | I49: 37670 | J49: 37670 | K49: 41437 | L49: 41437 | M49: 41437 | N49: 41437 | O49: 41437 | P49: 41437 | Q49: 41437 | R49: =SUM(F49:Q49) -> 478409 | S49: 清掃費
B50: 5004086291 | C50: =IFERROR(IF(VLOOKUP($B50,[1]勘定科目!$A:$H,HLOOKUP($E$5,[1]勘定科目!$F$1:$H$2,2,0),0)="","",VLOOKUP($B50,[1]勘定科目!$A:$E,2,0)),"") -> 福利厚生費（製） | D50: =IF(C50="","",VLOOKUP($B50,[1]勘定科目!$A:$E,4,0)) -> 福利厚生費 | F50: 1400000 | G50: 1400000 | H50: 1400000 | I50: 1400000 | J50: 1400000 | K50: 1400000 | L50: 1400000 | M50: 1400000 | N50: 1400000 | O50: 1400000 | P50: 1400000 | Q50: 1400000 | R50: =SUM(F50:Q50) -> 16800000 | S50: 出向者送迎費
B51: 5004086291 | C51: =IFERROR(IF(VLOOKUP($B51,[1]勘定科目!$A:$H,HLOOKUP($E$5,[1]勘定科目!$F$1:$H$2,2,0),0)="","",VLOOKUP($B51,[1]勘定科目!$A:$E,2,0)),"") -> 福利厚生費（製） | D51: =IF(C51="","",VLOOKUP($B51,[1]勘定科目!$A:$E,4,0)) -> 福利厚生費 | F51: 0 | G51: 0 | H51: 0 | I51: 0 | J51: 0 | K51: 0 | L51: 0 | M51: 0 | N51: 0 | O51: 0 | P51: 0 | Q51: 0 | R51: =SUM(F51:Q51) -> 0 | S51: ="Local Bus送迎費 (local Member 人員比率 "&X51&"で計算)" -> Local Bus送迎費 (local Member 人員比率 で計算)
B52: 5004086291 | C52: =IFERROR(IF(VLOOKUP($B52,[1]勘定科目!$A:$H,HLOOKUP($E$5,[1]勘定科目!$F$1:$H$2,2,0),0)="","",VLOOKUP($B52,[1]勘定科目!$A:$E,2,0)),"") -> 福利厚生費（製） | D52: =IF(C52="","",VLOOKUP($B52,[1]勘定科目!$A:$E,4,0)) -> 福利厚生費 | F52: 0 | G52: 0 | H52: 0 | I52: 0 | J52: 0 | K52: 0 | L52: 0 | M52: 0 | N52: 0 | O52: 0 | P52: 0 | Q52: 0 | R52: =SUM(F52:Q52) -> 0 | S52: 残業時のタクシー送迎費 (Local なし)
B53: 5004086291 | C53: =IFERROR(IF(VLOOKUP($B53,[1]勘定科目!$A:$H,HLOOKUP($E$5,[1]勘定科目!$F$1:$H$2,2,0),0)="","",VLOOKUP($B53,[1]勘定科目!$A:$E,2,0)),"") -> 福利厚生費（製） | D53: =IF(C53="","",VLOOKUP($B53,[1]勘定科目!$A:$E,4,0)) -> 福利厚生費 | R53: =SUM(F53:Q53) -> 0 | S53: 出向者 通勤タクシー費用 （140,000×16 固定 ＋α)
B54: 5004086291 | C54: =IFERROR(IF(VLOOKUP($B54,[1]勘定科目!$A:$H,HLOOKUP($E$5,[1]勘定科目!$F$1:$H$2,2,0),0)="","",VLOOKUP($B54,[1]勘定科目!$A:$E,2,0)),"") -> 福利厚生費（製） | D54: =IF(C54="","",VLOOKUP($B54,[1]勘定科目!$A:$E,4,0)) -> 福利厚生費 | F54: 0 | G54: 0 | H54: 0 | I54: 0 | J54: 0 | K54: 616000 | L54: 0 | M54: 0 | N54: 0 | O54: 0 | P54: 0 | Q54: 0 | R54: =SUM(F54:Q54) -> 616000 | S54: 月餅
B55: 5004086291 | C55: =IFERROR(IF(VLOOKUP($B55,[1]勘定科目!$A:$H,HLOOKUP($E$5,[1]勘定科目!$F$1:$H$2,2,0),0)="","",VLOOKUP($B55,[1]勘定科目!$A:$E,2,0)),"") -> 福利厚生費（製） | D55: =IF(C55="","",VLOOKUP($B55,[1]勘定科目!$A:$E,4,0)) -> 福利厚生費 | F55: 0 | G55: 0 | H55: 0 | I55: 0 | J55: 0 | K55: 0 | L55: 0 | M55: 0 | N55: 0 | O55: 0 | P55: 0 | Q55: 0 | R55: =SUM(F55:Q55) -> 0 | S55: 昼食代 (前月21日～当月20日を当月)
B56: 5004086291 | C56: =IFERROR(IF(VLOOKUP($B56,[1]勘定科目!$A:$H,HLOOKUP($E$5,[1]勘定科目!$F$1:$H$2,2,0),0)="","",VLOOKUP($B56,[1]勘定科目!$A:$E,2,0)),"") -> 福利厚生費（製） | D56: =IF(C56="","",VLOOKUP($B56,[1]勘定科目!$A:$E,4,0)) -> 福利厚生費 | F56: 0 | G56: 17500000 | H56: 0 | I56: 0 | J56: 0 | K56: 0 | L56: 0 | M56: 0 | N56: 0 | O56: 0 | P56: 0 | Q56: 0 | R56: =SUM(F56:Q56) -> 17500000 | S56: 社員旅行
B57: 5004086291 | C57: =IFERROR(IF(VLOOKUP($B57,[1]勘定科目!$A:$H,HLOOKUP($E$5,[1]勘定科目!$F$1:$H$2,2,0),0)="","",VLOOKUP($B57,[1]勘定科目!$A:$E,2,0)),"") -> 福利厚生費（製） | D57: =IF(C57="","",VLOOKUP($B57,[1]勘定科目!$A:$E,4,0)) -> 福利厚生費 | F57: 0 | G57: 0 | H57: 0 | I57: 0 | J57: 0 | K57: 1416250 | L57: 0 | M57: 0 | N57: 0 | O57: 0 | P57: 0 | Q57: 0 | R57: =SUM(F57:Q57) -> 1416250 | S57: kyoceraフェスティバル
B58: 5004086291 | C58: =IFERROR(IF(VLOOKUP($B58,[1]勘定科目!$A:$H,HLOOKUP($E$5,[1]勘定科目!$F$1:$H$2,2,0),0)="","",VLOOKUP($B58,[1]勘定科目!$A:$E,2,0)),"") -> 福利厚生費（製） | D58: =IF(C58="","",VLOOKUP($B58,[1]勘定科目!$A:$E,4,0)) -> 福利厚生費 | F58: 0 | G58: 0 | H58: 0 | I58: 0 | J58: 0 | K58: 0 | L58: 0 | M58: 1416800 | N58: 0 | O58: 0 | P58: 0 | Q58: 0 | R58: =SUM(F58:Q58) -> 1416800 | S58: 運動会
B59: 5004086291 | C59: =IFERROR(IF(VLOOKUP($B59,[1]勘定科目!$A:$H,HLOOKUP($E$5,[1]勘定科目!$F$1:$H$2,2,0),0)="","",VLOOKUP($B59,[1]勘定科目!$A:$E,2,0)),"") -> 福利厚生費（製） | D59: =IF(C59="","",VLOOKUP($B59,[1]勘定科目!$A:$E,4,0)) -> 福利厚生費 | F59: 0 | G59: 0 | H59: 0 | I59: 0 | J59: 0 | K59: 0 | L59: 0 | M59: 0 | N59: 0 | O59: 2200000 | P59: 0 | Q59: 0 | R59: =SUM(F59:Q59) -> 2200000 | S59: 忘年会補助金
B60: 5004086291 | C60: =IFERROR(IF(VLOOKUP($B60,[1]勘定科目!$A:$H,HLOOKUP($E$5,[1]勘定科目!$F$1:$H$2,2,0),0)="","",VLOOKUP($B60,[1]勘定科目!$A:$E,2,0)),"") -> 福利厚生費（製） | D60: =IF(C60="","",VLOOKUP($B60,[1]勘定科目!$A:$E,4,0)) -> 福利厚生費 | F60: 0 | G60: 0 | H60: 0 | I60: 0 | J60: 0 | K60: 0 | L60: 0 | M60: 0 | N60: 0 | O60: 0 | P60: 1100000 | Q60: 0 | R60: =SUM(F60:Q60) -> 1100000 | S60: お年玉
B61: 5004086291 | C61: =IFERROR(IF(VLOOKUP($B61,[1]勘定科目!$A:$H,HLOOKUP($E$5,[1]勘定科目!$F$1:$H$2,2,0),0)="","",VLOOKUP($B61,[1]勘定科目!$A:$E,2,0)),"") -> 福利厚生費（製） | D61: =IF(C61="","",VLOOKUP($B61,[1]勘定科目!$A:$E,4,0)) -> 福利厚生費 | F61: 0 | G61: 0 | H61: 0 | I61: 0 | J61: 0 | K61: 0 | L61: 0 | M61: 0 | N61: 0 | O61: 0 | P61: 0 | Q61: 0 | R61: =SUM(F61:Q61) -> 0 | S61: 誕生日会
C62: =IFERROR(IF(VLOOKUP($B62,[1]勘定科目!$A:$H,HLOOKUP($E$5,[1]勘定科目!$F$1:$H$2,2,0),0)="","",VLOOKUP($B62,[1]勘定科目!$A:$E,2,0)),"") | D62: =IF(C62="","",VLOOKUP($B62,[1]勘定科目!$A:$E,4,0)) | R62: =SUM(F62:Q62) -> 0 | S62: 決起コンパ
B63: 5005246281 | C63: =IFERROR(IF(VLOOKUP($B63,[1]勘定科目!$A:$H,HLOOKUP($E$5,[1]勘定科目!$F$1:$H$2,2,0),0)="","",VLOOKUP($B63,[1]勘定科目!$A:$E,2,0)),"") -> 図書印刷費（製） | D63: =IF(C63="","",VLOOKUP($B63,[1]勘定科目!$A:$E,4,0)) -> 図書及び事務費 | F63: 0 | G63: 0 | H63: 0 | I63: 0 | J63: 0 | K63: 0 | L63: 0 | M63: 16775 | N63: 0 | O63: 0 | P63: 0 | Q63: 0 | R63: =SUM(F63:Q63) -> 16775 | S63: ポケットカレンダー
B64: 5004086291 | C64: =IFERROR(IF(VLOOKUP($B64,[1]勘定科目!$A:$H,HLOOKUP($E$5,[1]勘定科目!$F$1:$H$2,2,0),0)="","",VLOOKUP($B64,[1]勘定科目!$A:$E,2,0)),"") -> 福利厚生費（製） | D64: =IF(C64="","",VLOOKUP($B64,[1]勘定科目!$A:$E,4,0)) -> 福利厚生費 | F64: 0 | G64: 0 | H64: 0 | I64: 200000 | J64: 0 | K64: 0 | L64: 0 | M64: 0 | N64: 0 | O64: 0 | P64: 0 | Q64: 0 | R64: =SUM(F64:Q64) -> 200000 | S64: フィロソフィ論文参加賞
B65: 5004086291 | C65: =IFERROR(IF(VLOOKUP($B65,[1]勘定科目!$A:$H,HLOOKUP($E$5,[1]勘定科目!$F$1:$H$2,2,0),0)="","",VLOOKUP($B65,[1]勘定科目!$A:$E,2,0)),"") -> 福利厚生費（製） | D65: =IF(C65="","",VLOOKUP($B65,[1]勘定科目!$A:$E,4,0)) -> 福利厚生費 | F65: 0 | G65: 0 | H65: 0 | I65: 0 | J65: 0 | K65: 0 | L65: 0 | M65: 0 | N65: 1260000 | O65: 0 | P65: 0 | Q65: 0 | R65: =SUM(F65:Q65) -> 1260000 | S65: 健康診断（ローカル）男性
B66: 5004086291 | C66: =IFERROR(IF(VLOOKUP($B66,[1]勘定科目!$A:$H,HLOOKUP($E$5,[1]勘定科目!$F$1:$H$2,2,0),0)="","",VLOOKUP($B66,[1]勘定科目!$A:$E,2,0)),"") -> 福利厚生費（製） | D66: =IF(C66="","",VLOOKUP($B66,[1]勘定科目!$A:$E,4,0)) -> 福利厚生費 | F66: 0 | G66: 0 | H66: 0 | I66: 0 | J66: 0 | K66: 0 | L66: 0 | M66: 0 | N66: 675000 | O66: 0 | P66: 0 | Q66: 0 | R66: =SUM(F66:Q66) -> 675000 | S66: 健康診断（ローカル）女性F
C67: =IFERROR(IF(VLOOKUP($B67,[1]勘定科目!$A:$H,HLOOKUP($E$5,[1]勘定科目!$F$1:$H$2,2,0),0)="","",VLOOKUP($B67,[1]勘定科目!$A:$E,2,0)),"") | D67: =IF(C67="","",VLOOKUP($B67,[1]勘定科目!$A:$E,4,0)) | R67: =SUM(F67:Q67) -> 0
C68: =IFERROR(IF(VLOOKUP($B68,[1]勘定科目!$A:$H,HLOOKUP($E$5,[1]勘定科目!$F$1:$H$2,2,0),0)="","",VLOOKUP($B68,[1]勘定科目!$A:$E,2,0)),"") | D68: =IF(C68="","",VLOOKUP($B68,[1]勘定科目!$A:$E,4,0)) | R68: =SUM(F68:Q68) -> 0 | S68: システム経費↓
B69: 5005246282 | C69: =IFERROR(IF(VLOOKUP($B69,[1]勘定科目!$A:$H,HLOOKUP($E$5,[1]勘定科目!$F$1:$H$2,2,0),0)="","",VLOOKUP($B69,[1]勘定科目!$A:$E,2,0)),"") -> ＫＤＣシステム使用料（製） | D69: =IF(C69="","",VLOOKUP($B69,[1]勘定科目!$A:$E,4,0)) -> 図書及び事務費 | F69: 1687104 | G69: 1847462 | H69: 1847462 | I69: 1847462 | J69: 1847462 | K69: 2032209 | L69: 2032209 | M69: 2032209 | N69: 2032209 | O69: 2032209 | P69: 2032209 | Q69: 2032209 | R69: =SUM(F69:Q69) -> 23302415 | S69: メール
B70: 5005246282 | C70: =IFERROR(IF(VLOOKUP($B70,[1]勘定科目!$A:$H,HLOOKUP($E$5,[1]勘定科目!$F$1:$H$2,2,0),0)="","",VLOOKUP($B70,[1]勘定科目!$A:$E,2,0)),"") -> ＫＤＣシステム使用料（製） | D70: =IF(C70="","",VLOOKUP($B70,[1]勘定科目!$A:$E,4,0)) -> 図書及び事務費 | R70: =SUM(F70:Q70) -> 0 | S70: R3
B71: 5005246282 | C71: =IFERROR(IF(VLOOKUP($B71,[1]勘定科目!$A:$H,HLOOKUP($E$5,[1]勘定科目!$F$1:$H$2,2,0),0)="","",VLOOKUP($B71,[1]勘定科目!$A:$E,2,0)),"") -> ＫＤＣシステム使用料（製） | D71: =IF(C71="","",VLOOKUP($B71,[1]勘定科目!$A:$E,4,0)) -> 図書及び事務費 | R71: =SUM(F71:Q71) -> 0 | S71: PLM 課金額アップ→MD4課に移動(52,254,413VND)
B72: 5005246282 | C72: =IFERROR(IF(VLOOKUP($B72,[1]勘定科目!$A:$H,HLOOKUP($E$5,[1]勘定科目!$F$1:$H$2,2,0),0)="","",VLOOKUP($B72,[1]勘定科目!$A:$E,2,0)),"") -> ＫＤＣシステム使用料（製） | D72: =IF(C72="","",VLOOKUP($B72,[1]勘定科目!$A:$E,4,0)) -> 図書及び事務費 | F72: 167040 | G72: 167040 | H72: 167040 | I72: 167040 | J72: 167040 | K72: 167040 | L72: 167040 | M72: 167040 | N72: 167040 | O72: 167040 | P72: 167040 | Q72: 167040 | R72: =SUM(F72:Q72) -> 2004480 | S72: VPN 出向者分
B73: 5005246282 | C73: =IFERROR(IF(VLOOKUP($B73,[1]勘定科目!$A:$H,HLOOKUP($E$5,[1]勘定科目!$F$1:$H$2,2,0),0)="","",VLOOKUP($B73,[1]勘定科目!$A:$E,2,0)),"") -> ＫＤＣシステム使用料（製） | D73: =IF(C73="","",VLOOKUP($B73,[1]勘定科目!$A:$E,4,0)) -> 図書及び事務費 | R73: =SUM(F73:Q73) -> 0 | S73: DemitasNX ライセンス 1本 ¥64,587/月 毎月KDCから振替請求
B74: 5005246282 | C74: =IFERROR(IF(VLOOKUP($B74,[1]勘定科目!$A:$H,HLOOKUP($E$5,[1]勘定科目!$F$1:$H$2,2,0),0)="","",VLOOKUP($B74,[1]勘定科目!$A:$E,2,0)),"") -> ＫＤＣシステム使用料（製） | D74: =IF(C74="","",VLOOKUP($B74,[1]勘定科目!$A:$E,4,0)) -> 図書及び事務費 | R74: =SUM(F74:Q74) -> 0 | S74: DemitasNX ライセンス 年間保守費用 ¥519,000/年 7月にKDCから振替請求
B75: 5005246282 | C75: =IFERROR(IF(VLOOKUP($B75,[1]勘定科目!$A:$H,HLOOKUP($E$5,[1]勘定科目!$F$1:$H$2,2,0),0)="","",VLOOKUP($B75,[1]勘定科目!$A:$E,2,0)),"") -> ＫＤＣシステム使用料（製） | D75: =IF(C75="","",VLOOKUP($B75,[1]勘定科目!$A:$E,4,0)) -> 図書及び事務費 | R75: =SUM(F75:Q75) -> 0 | S75: Finalcode管理者ライセンス \847/月 1本
B76: 5005046283 | C76: =IFERROR(IF(VLOOKUP($B76,[1]勘定科目!$A:$H,HLOOKUP($E$5,[1]勘定科目!$F$1:$H$2,2,0),0)="","",VLOOKUP($B76,[1]勘定科目!$A:$E,2,0)),"") -> 年間保守料（製） | D76: =IF(C76="","",VLOOKUP($B76,[1]勘定科目!$A:$E,4,0)) -> 修繕費 | R76: =SUM(F76:Q76) -> 0 | S76: E3 CAD 年間保守費用
C77: =IFERROR(IF(VLOOKUP($B77,[1]勘定科目!$A:$H,HLOOKUP($E$5,[1]勘定科目!$F$1:$H$2,2,0),0)="","",VLOOKUP($B77,[1]勘定科目!$A:$E,2,0)),"") | D77: =IF(C77="","",VLOOKUP($B77,[1]勘定科目!$A:$E,4,0)) | R77: =SUM(F77:Q77) -> 0
C78: =IFERROR(IF(VLOOKUP($B78,[1]勘定科目!$A:$H,HLOOKUP($E$5,[1]勘定科目!$F$1:$H$2,2,0),0)="","",VLOOKUP($B78,[1]勘定科目!$A:$E,2,0)),"") | D78: =IF(C78="","",VLOOKUP($B78,[1]勘定科目!$A:$E,4,0)) | R78: =SUM(F78:Q78) -> 0 | S78: 新入社員経費↓
B79: 5005246281 | C79: =IFERROR(IF(VLOOKUP($B79,[1]勘定科目!$A:$H,HLOOKUP($E$5,[1]勘定科目!$F$1:$H$2,2,0),0)="","",VLOOKUP($B79,[1]勘定科目!$A:$E,2,0)),"") -> 図書印刷費（製） | D79: =IF(C79="","",VLOOKUP($B79,[1]勘定科目!$A:$E,4,0)) -> 図書及び事務費 | I79: 0 | J79: 66500 | K79: 0 | L79: 0 | N79: 0 | O79: 0 | P79: 0 | Q79: 0 | R79: =SUM(F79:Q79) -> 66500 | S79: 新入社員 社員証 (7月Internship、8月 11期生)
B80: 5005246281 | C80: =IFERROR(IF(VLOOKUP($B80,[1]勘定科目!$A:$H,HLOOKUP($E$5,[1]勘定科目!$F$1:$H$2,2,0),0)="","",VLOOKUP($B80,[1]勘定科目!$A:$E,2,0)),"") -> 図書印刷費（製） | D80: =IF(C80="","",VLOOKUP($B80,[1]勘定科目!$A:$E,4,0)) -> 図書及び事務費 | I80: 0 | J80: 3400 | K80: 0 | L80: 0 | N80: 0 | O80: 0 | P80: 0 | Q80: 0 | R80: =SUM(F80:Q80) -> 3400 | S80: 新入社員 社員証ケース (7月Internship、8月 11期生)
B81: 5005246288 | C81: =IFERROR(IF(VLOOKUP($B81,[1]勘定科目!$A:$H,HLOOKUP($E$5,[1]勘定科目!$F$1:$H$2,2,0),0)="","",VLOOKUP($B81,[1]勘定科目!$A:$E,2,0)),"") -> 事務用品費（製） | D81: =IF(C81="","",VLOOKUP($B81,[1]勘定科目!$A:$E,4,0)) -> 図書及び事務費 | I81: 0 | J81: 2200 | K81: 0 | L81: 0 | N81: 0 | O81: 0 | P81: 0 | Q81: 0 | R81: =SUM(F81:Q81) -> 2200 | S81: 新入社員 Pen (7月Internship、8月 11期生)
B82: 5005246288 | C82: =IFERROR(IF(VLOOKUP($B82,[1]勘定科目!$A:$H,HLOOKUP($E$5,[1]勘定科目!$F$1:$H$2,2,0),0)="","",VLOOKUP($B82,[1]勘定科目!$A:$E,2,0)),"") -> 事務用品費（製） | D82: =IF(C82="","",VLOOKUP($B82,[1]勘定科目!$A:$E,4,0)) -> 図書及び事務費 | I82: 0 | J82: 9100 | K82: 0 | L82: 0 | N82: 0 | O82: 0 | P82: 0 | Q82: 0 | R82: =SUM(F82:Q82) -> 9100 | S82: 新入社員 Note (7月Internship、8月 11期生)
B83: 5005246281 | C83: =IFERROR(IF(VLOOKUP($B83,[1]勘定科目!$A:$H,HLOOKUP($E$5,[1]勘定科目!$F$1:$H$2,2,0),0)="","",VLOOKUP($B83,[1]勘定科目!$A:$E,2,0)),"") -> 図書印刷費（製） | D83: =IF(C83="","",VLOOKUP($B83,[1]勘定科目!$A:$E,4,0)) -> 図書及び事務費 | I83: 0 | J83: 12000 | K83: 0 | L83: 0 | N83: 0 | O83: 0 | P83: 0 | Q83: 0 | R83: =SUM(F83:Q83) -> 12000 | S83: 新入社員 フィロソフィ手帳 (7月Internship、8月 11期生)
B84: 5004086291 | C84: =IFERROR(IF(VLOOKUP($B84,[1]勘定科目!$A:$H,HLOOKUP($E$5,[1]勘定科目!$F$1:$H$2,2,0),0)="","",VLOOKUP($B84,[1]勘定科目!$A:$E,2,0)),"") -> 福利厚生費（製） | D84: =IF(C84="","",VLOOKUP($B84,[1]勘定科目!$A:$E,4,0)) -> 福利厚生費 | I84: 210000 | J84: 0 | N84: 0 | O84: 0 | P84: 0 | Q84: 0 | R84: =SUM(F84:Q84) -> 210000 | S84: 新入社員 採用時健康診断 （採用時）男性
B85: 5004086291 | C85: =IFERROR(IF(VLOOKUP($B85,[1]勘定科目!$A:$H,HLOOKUP($E$5,[1]勘定科目!$F$1:$H$2,2,0),0)="","",VLOOKUP($B85,[1]勘定科目!$A:$E,2,0)),"") -> 福利厚生費（製） | D85: =IF(C85="","",VLOOKUP($B85,[1]勘定科目!$A:$E,4,0)) -> 福利厚生費 | I85: 0 | R85: =SUM(F85:Q85) -> 0 | S85: 新入社員 採用時健康診断 （採用時）女性
B86: 5004086291 | C86: =IFERROR(IF(VLOOKUP($B86,[1]勘定科目!$A:$H,HLOOKUP($E$5,[1]勘定科目!$F$1:$H$2,2,0),0)="","",VLOOKUP($B86,[1]勘定科目!$A:$E,2,0)),"") -> 福利厚生費（製） | D86: =IF(C86="","",VLOOKUP($B86,[1]勘定科目!$A:$E,4,0)) -> 福利厚生費 | I86: 0 | J86: 37000 | K86: 0 | L86: 0 | N86: 0 | O86: 0 | P86: 0 | Q86: 0 | R86: =SUM(F86:Q86) -> 37000 | S86: 新入社員 帽子 (7月Internship、8月 11期生)
B87: 5004086291 | C87: =IFERROR(IF(VLOOKUP($B87,[1]勘定科目!$A:$H,HLOOKUP($E$5,[1]勘定科目!$F$1:$H$2,2,0),0)="","",VLOOKUP($B87,[1]勘定科目!$A:$E,2,0)),"") -> 福利厚生費（製） | D87: =IF(C87="","",VLOOKUP($B87,[1]勘定科目!$A:$E,4,0)) -> 福利厚生費 | F87: 3300000 | I87: 0 | J87: 330000 | K87: 0 | L87: 0 | N87: 0 | O87: 0 | P87: 0 | Q87: 0 | R87: =SUM(F87:Q87) -> 3630000 | S87: 新入社員 制服上着(夏服) x2枚/人 (7月Internship、8月 11期生)
B88: 5004086291 | C88: =IFERROR(IF(VLOOKUP($B88,[1]勘定科目!$A:$H,HLOOKUP($E$5,[1]勘定科目!$F$1:$H$2,2,0),0)="","",VLOOKUP($B88,[1]勘定科目!$A:$E,2,0)),"") -> 福利厚生費（製） | D88: =IF(C88="","",VLOOKUP($B88,[1]勘定科目!$A:$E,4,0)) -> 福利厚生費 | G88: 3500000 | I88: 0 | J88: 0 | K88: 0 | L88: 175000 | N88: 0 | O88: 0 | P88: 0 | Q88: 0 | R88: =SUM(F88:Q88) -> 3675000 | S88: 新入社員 制服上着(冬服) x2枚/人 (7月Internship、8月 11期生)
B89: 5004086291 | C89: =IFERROR(IF(VLOOKUP($B89,[1]勘定科目!$A:$H,HLOOKUP($E$5,[1]勘定科目!$F$1:$H$2,2,0),0)="","",VLOOKUP($B89,[1]勘定科目!$A:$E,2,0)),"") -> 福利厚生費（製） | D89: =IF(C89="","",VLOOKUP($B89,[1]勘定科目!$A:$E,4,0)) -> 福利厚生費 | I89: 0 | J89: 0 | K89: 0 | L89: 0 | N89: 0 | O89: 0 | P89: 0 | Q89: 0 | R89: =SUM(F89:Q89) -> 0 | S89: 新入社員 制服(ズボン) x2枚/人 (7月Internship、8月 11期生)
B90: 5004086291 | C90: =IFERROR(IF(VLOOKUP($B90,[1]勘定科目!$A:$H,HLOOKUP($E$5,[1]勘定科目!$F$1:$H$2,2,0),0)="","",VLOOKUP($B90,[1]勘定科目!$A:$E,2,0)),"") -> 福利厚生費（製） | D90: =IF(C90="","",VLOOKUP($B90,[1]勘定科目!$A:$E,4,0)) -> 福利厚生費 | I90: 0 | J90: 78000 | K90: 0 | L90: 0 | N90: 0 | O90: 0 | P90: 0 | Q90: 0 | R90: =SUM(F90:Q90) -> 78000 | S90: 新入社員 靴 男性
B91: 5004086291 | C91: =IFERROR(IF(VLOOKUP($B91,[1]勘定科目!$A:$H,HLOOKUP($E$5,[1]勘定科目!$F$1:$H$2,2,0),0)="","",VLOOKUP($B91,[1]勘定科目!$A:$E,2,0)),"") -> 福利厚生費（製） | D91: =IF(C91="","",VLOOKUP($B91,[1]勘定科目!$A:$E,4,0)) -> 福利厚生費 | R91: =SUM(F91:Q91) -> 0 | S91: 新入社員 靴 女性
B92: 5005246281 | C92: =IFERROR(IF(VLOOKUP($B92,[1]勘定科目!$A:$H,HLOOKUP($E$5,[1]勘定科目!$F$1:$H$2,2,0),0)="","",VLOOKUP($B92,[1]勘定科目!$A:$E,2,0)),"") -> 図書印刷費（製） | D92: =IF(C92="","",VLOOKUP($B92,[1]勘定科目!$A:$E,4,0)) -> 図書及び事務費 | I92: 0 | J92: 1525 | K92: 0 | L92: 0 | N92: 0 | O92: 0 | P92: 0 | Q92: 0 | R92: =SUM(F92:Q92) -> 1525 | S92: 新入社員 ポケットカレンダー (7月Internship、8月 11期生)
B93: 5005246281 | C93: =IFERROR(IF(VLOOKUP($B93,[1]勘定科目!$A:$H,HLOOKUP($E$5,[1]勘定科目!$F$1:$H$2,2,0),0)="","",VLOOKUP($B93,[1]勘定科目!$A:$E,2,0)),"") -> 図書印刷費（製） | D93: =IF(C93="","",VLOOKUP($B93,[1]勘定科目!$A:$E,4,0)) -> 図書及び事務費 | R93: =SUM(F93:Q93) -> 0 | S93: 新入社員 データ印
B94: 5005026371 | C94: =IFERROR(IF(VLOOKUP($B94,[1]勘定科目!$A:$H,HLOOKUP($E$5,[1]勘定科目!$F$1:$H$2,2,0),0)="","",VLOOKUP($B94,[1]勘定科目!$A:$E,2,0)),"") -> 消耗工具器具備品費（製） | D94: =IF(C94="","",VLOOKUP($B94,[1]勘定科目!$A:$E,4,0)) -> 消耗工具器具備品費 | J94: 20000000 | R94: =SUM(F94:Q94) -> 20000000 | S94: 新入社員 PC
B95: 5005026371 | C95: =IFERROR(IF(VLOOKUP($B95,[1]勘定科目!$A:$H,HLOOKUP($E$5,[1]勘定科目!$F$1:$H$2,2,0),0)="","",VLOOKUP($B95,[1]勘定科目!$A:$E,2,0)),"") -> 消耗工具器具備品費（製） | D95: =IF(C95="","",VLOOKUP($B95,[1]勘定科目!$A:$E,4,0)) -> 消耗工具器具備品費 | F95: 0 | G95: 0 | H95: 0 | I95: 0 | J95: 0 | K95: 0 | L95: 0 | M95: 0 | N95: 0 | O95: 0 | P95: 0 | Q95: 0 | R95: =SUM(F95:Q95) -> 0 | S95: 事務机
B96: 5005026371 | C96: =IFERROR(IF(VLOOKUP($B96,[1]勘定科目!$A:$H,HLOOKUP($E$5,[1]勘定科目!$F$1:$H$2,2,0),0)="","",VLOOKUP($B96,[1]勘定科目!$A:$E,2,0)),"") -> 消耗工具器具備品費（製） | D96: =IF(C96="","",VLOOKUP($B96,[1]勘定科目!$A:$E,4,0)) -> 消耗工具器具備品費 | F96: 0 | G96: 0 | H96: 0 | I96: 0 | J96: 0 | K96: 0 | L96: 0 | M96: 0 | N96: 0 | O96: 0 | P96: 0 | Q96: 0 | R96: =SUM(F96:Q96) -> 0 | S96: 事務机用椅子
C97: =IFERROR(IF(VLOOKUP($B97,[1]勘定科目!$A:$H,HLOOKUP($E$5,[1]勘定科目!$F$1:$H$2,2,0),0)="","",VLOOKUP($B97,[1]勘定科目!$A:$E,2,0)),"") | D97: =IF(C97="","",VLOOKUP($B97,[1]勘定科目!$A:$E,4,0)) | R97: =SUM(F97:Q97) -> 0 | S97: INTERNSHIP↓
B98: 5004046221 | C98: =IFERROR(IF(VLOOKUP($B98,[1]勘定科目!$A:$H,HLOOKUP($E$5,[1]勘定科目!$F$1:$H$2,2,0),0)="","",VLOOKUP($B98,[1]勘定科目!$A:$E,2,0)),"") -> 雑給（直製） | D98: =IF(C98="","",VLOOKUP($B98,[1]勘定科目!$A:$E,4,0)) -> 雑給 | F98: 0 | G98: 0 | H98: 0 | I98: 0 | J98: 0 | K98: 0 | L98: 0 | M98: 0 | N98: 0 | O98: 0 | P98: 0 | Q98: 0 | R98: =SUM(F98:Q98) -> 0 | S98: Intern Ship 雑給
B99: 5004086291 | C99: =IFERROR(IF(VLOOKUP($B99,[1]勘定科目!$A:$H,HLOOKUP($E$5,[1]勘定科目!$F$1:$H$2,2,0),0)="","",VLOOKUP($B99,[1]勘定科目!$A:$E,2,0)),"") -> 福利厚生費（製） | D99: =IF(C99="","",VLOOKUP($B99,[1]勘定科目!$A:$E,4,0)) -> 福利厚生費 | F99: 0 | G99: 0 | H99: 0 | I99: 0 | J99: 0 | K99: 0 | L99: 0 | M99: 0 | N99: 0 | O99: 0 | P99: 0 | Q99: 0 | R99: =SUM(F99:Q99) -> 0 | S99: Intern Ship 諸経費(支給品一式)
B100: 5004086291 | C100: =IFERROR(IF(VLOOKUP($B100,[1]勘定科目!$A:$H,HLOOKUP($E$5,[1]勘定科目!$F$1:$H$2,2,0),0)="","",VLOOKUP($B100,[1]勘定科目!$A:$E,2,0)),"") -> 福利厚生費（製） | D100: =IF(C100="","",VLOOKUP($B100,[1]勘定科目!$A:$E,4,0)) -> 福利厚生費 | F100: 0 | G100: 0 | H100: 0 | I100: 0 | J100: 0 | K100: 0 | L100: 0 | M100: 0 | N100: 0 | O100: 0 | P100: 0 | Q100: 0 | R100: =SUM(F100:Q100) -> 0 | S100: Intern Ship 寮費 (参加人数20%)
B101: 5005196373 | C101: =IFERROR(IF(VLOOKUP($B101,[1]勘定科目!$A:$H,HLOOKUP($E$5,[1]勘定科目!$F$1:$H$2,2,0),0)="","",VLOOKUP($B101,[1]勘定科目!$A:$E,2,0)),"") -> 試験研究用材料費 | D101: =IF(C101="","",VLOOKUP($B101,[1]勘定科目!$A:$E,4,0)) -> 試験研究費 | F101: 0 | G101: 0 | H101: 0 | I101: 0 | J101: 0 | K101: 0 | L101: 0 | M101: 0 | N101: 0 | O101: 0 | P101: 0 | Q101: 0 | R101: =SUM(F101:Q101) -> 0 | S101: Intern Ship 実習用部材費
...

Sheet 設備投資計画
B1: 設備投資金額一覧表 | D1: ='内訳ﾘｽﾄ(4～3月)'!C5 -> EI2課 | E1: (単位： VND)
B3: 部門ｺｰﾄﾞ | C3: 購入物品名 | D3: 目 的 | E3: 4 | F3: 5 | G3: 6 | H3: 7 | I3: 8 | J3: 9 | K3: 10 | L3: 11 | M3: 12 | N3: 1 | O3: 2 | P3: 3 | Q3: 償却期間 (ヶ月) | R3: 購入金額合計 | S3: WBS
R4: =SUM(E4:P4) -> 0
R5: =SUM(E5:P5) -> 0
R6: =SUM(E6:P6) -> 0
R7: =SUM(E7:P7) -> 0
R8: =SUM(E8:P8) -> 0
R9: =SUM(E9:P9) -> 0
R10: =SUM(E10:P10) -> 0
R11: =SUM(E11:P11) -> 0
R12: =SUM(E12:P12) -> 0
R13: =SUM(E13:P13) -> 0
R14: =SUM(E14:P14) -> 0
R15: =SUM(E15:P15) -> 0
... R49: =SUM(E49:P49) -> 0
D50: TOTAL | R50: =SUM(E50:P50) -> 0
B52: ＊設備投資は、30,000,000VND以上、且つ1年以上使用するものが対象となります。
B53: ＊建設仮勘定を含む、取得基準にて記入して下さい。
B54: ＊重複を避ける為、稟議起案部門にて記入して下さい。
B55: ＊リースによる設備投資を含めないで下さい。

Sheet 勘定科目
A1: Account_Code | B1: JPN (50cha) | C1: Tiếng Việt_Tên tài khoản kế toán | D1: JP_Name | E1: Tiếng Việt_Hạng mục lợi nhuận | F1: 製造 | G1: 一般 | H1: 販売 | I1: REMARK
F2: =COLUMNS($A$2:F2) -> 6 | G2: =COLUMNS($A$2:G2) -> 7 | H2: =COLUMNS($A$2:H2) -> 8
A3: 7001065118 | B3: 雑収入 | C3: Doanh thu khác | D3: 雑収入 | E3: Thu nhập khác | F3: 7001065118 | G3: 7001065118 | H3: 7001065118
A4: 7001075118 | B4: 雑収入（関係会社） | C4: Doanh thu khác | D4: 雑収入 | E4: Thu nhập khác | F4: 7001075118 | G4: 7001075118 | H4: 7001075118
A5: 7001065119 | B5: 固定資産売却勘定 | C5: Doanh thu khác | D5: 雑収入 | E5: Thu nhập khác | F5: 7001065119 | G5: 7001065119 | H5: 7001065119
A6: 5001016131 | B6: 材料仕入割戻高 | C6: Chi phí nguyên liệu, vật liệu trực tiếp | D6: 材料費 | E6: Chi phí nguyên vật liệu | F6: 5001016131 | I6: 2016年4月から追加する。
A7: 5001016134 | B7: リーフレット用材料 | C7: Chi phí nguyên liệu, vật liệu trực tiếp | D7: 材料費 | E7: Chi phí nguyên vật liệu | F7: 5001016134 | G7: 5001016134 | H7: 5001016134 | I7: 2017年1月変更。
A8: 5001016135 | B8: 不良部品材料費 | C8: Chi phí nguyên liệu, vật liệu trực tiếp | D8: 材料費 | E8: Chi phí nguyên vật liệu | F8: 5001016135 | G8: 5001016135 | H8: 5001016135
A9: 5001016136 | B9: 追加指図部品費 | C9: Chi phí nguyên liệu, vật liệu trực tiếp | D9: 材料費 | E9: Chi phí nguyên vật liệu | F9: 5001016136 | G9: 5001016136 | H9: 5001016136
A10: 5001016142 | B10: 加工中不良廃棄損 | C10: Chi phí nguyên liệu, vật liệu trực tiếp | D10: 仕掛仕損 | E10: Sản phẩm chưa hoàn thiện,hỏng | F10: 5001016142 | G10: 5001016142 | H10: 5001016142
A11: 5001016149 | B11: 金型材料仕入 | C11: Chi phí nguyên liệu, vật liệu trực tiếp | D11: 材料費 | E11: Chi phí nguyên vật liệu | F11: 5001016149 | G11: 5001016149 | H11: 5001016149 | I11: 2月から追加する。
A12: 5001016151 | B12: 生産用副資材 | C12: Chi phí nguyên liệu, vật liệu trực tiếp | D12: 材料費 | E12: Chi phí nguyên vật liệu | F12: 5001016151 | I12: 2017年1月追加。
A13: 5004046221 | B13: 雑給（直製） | C13: Chi phí nhân công trực tiếp | D13: 雑給 | E13: Chi phí nhân công trực tiếp | F13: 5004046221
A14: 5004046371 | B14: 雑給（間製） | C14: Chi phí nhân viên phân xưởng | D14: 雑給 | E14: Chi phí nhân công trực tiếp | F14: 5004046371
A15: 5005016371 | B15: 生産用消耗品費（製） | C15: Chi phí dụng cụ sản xuất | D15: 消耗品費 | E15: Chi phí hàng hóa tiêu hao | F15: 5005016371
A16: 5005016372 | B16: その他消耗品（製） | C16: Chi phí dụng cụ sản xuất | D16: 消耗品費 | E16: Chi phí hàng hóa tiêu hao | F16: 5005016372
A17: 5005016373 | B17: 生産用文房具（製造） | C17: Chi phí dụng cụ sản xuất | D17: 消耗品費 | E17: Chi phí hàng hóa tiêu hao | F17: 5005016373 | I17: 2017年1月追加。
A18: 5005026371 | B18: 消耗工具器具備品費（製） | C18: Chi phí dụng cụ sản xuất | D18: 消耗工具器具備品費 | E18: Chi phí sử dụng công cụ,đồ đạc | F18: 5005026371
A19: 5005026372 | B19: 消耗金型代（製） | C19: Chi phí dụng cụ sản xuất | D19: 消耗金型費 | E19: Chi phí tiêu hao khuôn | F19: 5005026372
A20: 5006016241 | B20: 減価償却費（製） 建物 | C20: Chi phí khấu hao TSCĐ | D20: 減価償却費 | E20: Chi phí khấu hao | F20: 5006016241
A21: 5006016242 | B21: 減価償却費（製） 機械装置 | C21: Chi phí khấu hao TSCĐ | D21: 減価償却費 | E21: Chi phí khấu hao | F21: 5006016242
A22: 5006016243 | B22: 減価償却費（製） 車輌運搬具 | C22: Chi phí khấu hao TSCĐ | D22: 減価償却費 | E22: Chi phí khấu hao | F22: 5006016243
A23: 5006016244 | B23: 減価償却費（製） 工具器具備品 | C23: Chi phí khấu hao TSCĐ | D23: 減価償却費 | E23: Chi phí khấu hao | F23: 5006016244
A24: 5006016245 | B24: 減価償却費（製） 構築物 | C24: Chi phí khấu hao TSCĐ | D24: 減価償却費 | E24: Chi phí khấu hao | F24: 5006016245
A25: 5005036246 | B25: 減価償却費（製） 金型 | C25: Chi phí khấu hao TSCĐ | D25: 金型償却費 | E25: Chi phí khấu hao khuôn | F25: 5005036246
A26: 5006016247 | B26: 減価償却費（製） その他有形固定資産 | C26: Chi phí khấu hao TSCĐ | D26: 減価償却費 | E26: Chi phí khấu hao | F26: 5006016247
A27: 5006016248 | B27: 減価償却費（製） リース建物 | C27: Chi phí khấu hao TSCĐ | D27: 減価償却費 | E27: Chi phí khấu hao | F27: 5006016248
A28: 5006016249 | B28: 減価償却費（製） リース機械装置 | C28: Chi phí khấu hao TSCĐ | D28: 減価償却費 | E28: Chi phí khấu hao | F28: 5006016249
A29: 5006016250 | B29: 減価償却費（製） リース車輌運搬具 | C29: Chi phí khấu hao TSCĐ | D29: 減価償却費 | E29: Chi phí khấu hao | F29: 5006016250
... A44: 5005046283 | B44: 年間保守料（製） | C44: Chi phi dịch vụ mua ngoài | D44: 修繕費 | E44: Chi phí sửa chữa | F44: 5005046283
A45: 5005046284 | B45: 金型修繕費（製造） | C45: Chi phi dịch vụ mua ngoài | D45: 修繕費 | E45: Chi phí sửa chữa | F45: 5005046284 | I45: 2017年1月追加。
A46: 5005066281 | B46: 電気代（製） | C46: Chi phi dịch vụ mua ngoài | D46: 水道光熱費 | E46: Chi phí Utilities(điện,nước..) | F46: 5005066281
A47: 5005066282 | B47: 水道代（製） | C47: Chi phi dịch vụ mua ngoài | D47: 水道光熱費 | E47: Chi phí Utilities(điện,nước..) | F47: 5005066282
A48: 5005056281 | B48: ガス代（製） | C48: Chi phi dịch vụ mua ngoài | D48: 水道光熱費 | E48: Chi phí Utilities(điện,nước..) | F48: 5005056281
A49: 5005076281 | B49: 通関申告費用（製） | C49: Chi phi dịch vụ mua ngoài | D49: 荷造運賃 | E49: Chi phí vận chuyển hàng hóa | F49: 5005076281
A50: 5005076282 | B50: 設備輸送費（製） | C50: Chi phi dịch vụ mua ngoài | D50: 荷造運賃 | E50: Chi phí vận chuyển hàng hóa | F50: 5005076282
A51: 5005076283 | B51: 輸入航空運賃（製） | C51: Chi phi dịch vụ mua ngoài | D51: 荷造運賃 | E51: Chi phí vận chuyển hàng hóa | F51: 5005076283
A52: 5005076284 | B52: 輸入海上運賃（製） | C52: Chi phi dịch vụ mua ngoài | D52: 荷造運賃 | E52: Chi phí vận chuyển hàng hóa | F52: 5005076284
A53: 5005076285 | B53: 空箱返却費用 | C53: Chi phi dịch vụ mua ngoài | D53: 荷造運賃 | E53: Chi phí vận chuyển hàng hóa | F53: 5005076285
A54: 5005076286 | B54: 部品集荷トラック代 | C54: Chi phi dịch vụ mua ngoài | D54: 荷造運賃 | E54: Chi phí vận chuyển hàng hóa | F54: 5005076286
A55: 5005076287 | B55: 物流保険料（製） | C55: Chi phi dịch vụ mua ngoài | D55: 荷造運賃 | E55: Chi phí vận chuyển hàng hóa | F55: 5005076287
A56: 5005076288 | B56: 梱包材料費（製） | C56: Chi phi dịch vụ mua ngoài | D56: 荷造用品費 | E56: Chi phí NVL dùng đóng gói hàng | F56: 5005076288
A57: 5005076289 | B57: クーリエ費用（製） | C57: Chi phi dịch vụ mua ngoài | D57: 荷造運賃 | E57: Chi phí vận chuyển hàng hóa | F57: 5005076289
A58: 5005076291 | B58: 外部倉庫 取扱手数料（製造） | C58: Chi phi dịch vụ mua ngoài | D58: 荷造運賃 | E58: Chi phí vận chuyển hàng hóa | F58: 5005076291 | I58: 2017年1月追加。
A59: 5005076292 | B59: 外部倉庫 保管料（製造） | C59: Chi phi dịch vụ mua ngoài | D59: 荷造運賃 | E59: Chi phí vận chuyển hàng hóa | F59: 5005076292 | I59: 2017年1月追加。
A60: 5005076293 | B60: 外部倉庫 輸送料（製造） | C60: Chi phi dịch vụ mua ngoài | D60: 荷造運賃 | E60: Chi phí vận chuyển hàng hóa | F60: 5005076293 | I60: 2017年1月追加。
A61: 5005076294 | B61: 外部物流業者 取扱手数料（製造） | C61: Chi phi dịch vụ mua ngoài | D61: 荷造運賃 | E61: Chi phí vận chuyển hàng hóa | F61: 5005076294 | I61: 2017年1月追加。
A62: 5005086281 | B62: 技術料（製） | C62: Chi phi dịch vụ mua ngoài | D62: 技術料 | E62: Phí kỹ thuật | F62: 5005086281
A63: 5005136281 | B63: 通信費（製） | C63: Chi phi dịch vụ mua ngoài | D63: 通信費 | E63: Chi phí điện thoại | F63: 5005136281
A64: 5005246281 | B64: 図書印刷費（製） | C64: Chi phi dịch vụ mua ngoài | D64: 図書及び事務費 | E64: Chi phí văn phòng | F64: 5005246281
A65: 5005246282 | B65: ＫＤＣシステム使用料（製） | C65: Chi phi dịch vụ mua ngoài | D65: 図書及び事務費 | E65: Chi phí văn phòng | F65: 5005246282
A66: 5005246283 | B66: ライセンス料（製） | C66: Chi phi dịch vụ mua ngoài | D66: 図書及び事務費 | E66: Chi phí văn phòng | F66: 5005246283
A67: 5005246284 | B67: 会費（製） | C67: Chi phi dịch vụ mua ngoài | D67: 会費及び会議費 | E67: Chi phí cuộc họp | F67: 5005246284
A68: 5005216281 | B68: 委嘱報酬・設計委託費（製） | C68: Chi phi dịch vụ mua ngoài | D68: 委嘱報酬 | E68: Thù lao ủy thác,phí hoa hồng | F68: 5005216281
A69: 5005226281 | B69: 保険料（製） | C69: Chi phi dịch vụ mua ngoài | D69: 保険料 | E69: Chi phí bảo hiểm | F69: 5005226281
A70: 5005236281 | B70: 事務所賃借料（製） | C70: Chi phi dịch vụ mua ngoài | D70: 賃借料 | E70: Chi phí thuê | F70: 5005236281
A71: 5005236282 | B71: 倉庫賃借料（製） | C71: Chi phi dịch vụ mua ngoài | D71: 賃借料 | E71: Chi phí thuê | F71: 5005236282
A72: 5005246285 | B72: 取扱手数料（製） | C72: Chi phi dịch vụ mua ngoài | D72: 手数料 | E72: Tiền dịch vụ,tiền lệ phí | F72: 5005246285
A73: 5005246286 | B73: その他手数料（製） | C73: Chi phi dịch vụ mua ngoài | D73: 手数料 | E73: Tiền dịch vụ,tiền lệ phí | F73: 5005246286
... A82: 5005186292 | B82: その他税金（製） | C82: Chi phí bằng tiền khác | D82: 公租公課 | E82: Thuế,phí công cộng | F82: 5005186292
A83: 5005196373 | B83: 試験研究用材料費 | C83: Chi phí dụng cụ sản xuất | D83: 試験研究費 | E83: Chi phí thử nghiệm,nghiên cứu | F83: 5005196373 | G83: 5005196373 | H83: 5005196373 | I83: 2月から追加する。
A84: 5005196277 | B84: 試験研究用役務費 | C84: Chi phi dịch vụ mua ngoài | D84: 試験研究費 | E84: Chi phí thử nghiệm,nghiên cứu | F84: 5005196277 | G84: 5005196277 | H84: 5005196277 | I84: 2月から追加する。
A85: 5005246291 | B85: 会議費（製） | C85: Chi phí bằng tiền khác | D85: 会費及び会議費 | E85: Chi phí cuộc họp | F85: 5005246291
A86: 5005246292 | B86: 雑費（製） | C86: Chi phí bằng tiền khác | D86: 雑費 | E86: Các loại chi phí bằng tiền khác | F86: 5005246292
A87: 5005246294 | B87: 開発費振替勘定（製） | C87: Chi phí bằng tiền khác | D87: 雑費 | E87: Các loại chi phí bằng tiền khác | F87: 5005246294 | I87: 2月から追加する→9/2015からｘから雑費になった
A88: 5005256291 | B88: 棚卸減耗費（製） | C88: Chi phí bằng tiền khác | D88: 棚卸減耗費 | E88: Chi phí hao hụt sau kiểm kê | F88: 5005256291
A89: 5101016174 | B89: 製商品仕入諸掛 | C89: Giá vốn hàng bán | D89: 仕入製商品費 | E89: Chi phí bán hàng | F89: 5101016174
A90: 5101016179 | B90: 製品品目外注加工費 | C90: Giá vốn hàng bán | D90: 外注加工費 | E90: Chi phí gia công ngoài | F90: 5101016179
A91: 5101016187 | B91: 製商品在庫廃棄損 | C91: Giá vốn hàng bán | D91: 雑損失 | E91: Tổn thất,lỗ khác | F91: 5101016187
A92: 5101016189 | B92: 金型製作収入 | C92: Doanh thu bán thành phẩm | D92: 雑収入 | E92: Thu nhập khác | F92: 5101016189 | I92: 2月から追加する。
A93: 6004046511 | B93: 雑給（販売） | C93: Chi phí nhân viên | D93: 雑給 | E93: Chi phí nhân công trực tiếp | H93: 6004046511
A94: 6003036412 | B94: 梱包材料費（販売） | C94: Chi phí vật liệu bao bì | D94: 荷造用品費 | E94: Chi phí NVL dùng đóng gói hàng | H94: 6003036412
A95: 6005016413 | B95: 消耗品費（販売） | C95: Chi phí dụng cụ đồ dùng | D95: 消耗品費 | E95: Chi phí hàng hóa tiêu hao | H95: 6005016413
A96: 6005016414 | B96: 消耗備品費（販売） | C96: Chi phí dụng cụ đồ dùng | D96: 消耗工具器具備品費 | E96: Chi phí sử dụng công cụ,đồ đạc | G96: 6005016414 | H96: 6005016414 | I96: 2017年1月追加。
A97: 6006016521 | B97: 減価償却費（販） 建物 | C97: Chi phí khấu hao TSCĐ | D97: 減価償却費 | E97: Chi phí khấu hao | H97: 6006016521
A98: 6006016522 | B98: 減価償却費（販） 機械装置 | C98: Chi phí khấu hao TSCĐ | D98: 減価償却費 | E98: Chi phí khấu hao | H98: 6006016522
A99: 6006016523 | B99: 減価償却費（販） 車輌運搬具 | C99: Chi phí khấu hao TSCĐ | D99: 減価償却費 | E99: Chi phí khấu hao | H99: 6006016523
A100: 6006016524 | B100: 減価償却費（販） 工具器具備品 | C100: Chi phí khấu hao TSCĐ | D100: 減価償却費 | E100: Chi phí khấu hao | H100: 6006016524
A101: 6006016525 | B101: 減価償却費（販） 構築物 | C101: Chi phí khấu hao TSCĐ | D101: 減価償却費 | E101: Chi phí khấu hao | H101: 6006016525
A102: 6006016526 | B102: 減価償却費（販） その他有形固定資産 | C102: Chi phí khấu hao TSCĐ | D102: 減価償却費 | E102: Chi phí khấu hao | H102: 6006016526
A103: 6006016527 | B103: 減価償却費（販） リース建物 | C103: Chi phí khấu hao TSCĐ | D103: 減価償却費 | E103: Chi phí khấu hao | H103: 6006016527
A104: 6006016528 | B104: 減価償却費（販） リース機械装置 | C104: Chi phí khấu hao TSCĐ | D104: 減価償却費 | E104: Chi phí khấu hao | H104: 6006016528
A105: 6006016529 | B105: 減価償却費（販） リース車輌運搬具 | C105: Chi phí khấu hao TSCĐ | D105: 減価償却費 | E105: Chi phí khấu hao | H105: 6006016529
A106: 6006016530 | B106: 減価償却費（販） リース工具器具備品 | C106: Chi phí khấu hao TSCĐ | D106: 減価償却費 | E106: Chi phí khấu hao | H106: 6006016530
A107: 6006016531 | B107: 減価償却費（販） リース構築物 | C107: Chi phí khấu hao TSCĐ | D107: 減価償却費 | E107: Chi phí khấu hao | H107: 6006016531
A108: 6006016532 | B108: 減価償却費（販） 土地使用権 | C108: Chi phí khấu hao TSCĐ | D108: 減価償却費 | E108: Chi phí khấu hao | H108: 6006016532
... A122: 6003036542 | B122: クーリエ費用（販売） | C122: Chi phí dịch vụ mua ngòai | D122: 荷造運賃 | E122: Chi phí vận chuyển hàng hóa | H122: 6003036542
A123: 6003036543 | B123: 輸出航空運賃（販売） | C123: Chi phí dịch vụ mua ngòai | D123: 荷造運賃 | E123: Chi phí vận chuyển hàng hóa | F123: 6003036543 | H123: 6003036543
A124: 6003036544 | B124: 輸出海上運賃（販売） | C124: Chi phí dịch vụ mua ngòai | D124: 荷造運賃 | E124: Chi phí vận chuyển hàng hóa | F124: 6003036544 | G124: 6003036544 | H124: 6003036544
A125: 6003036545 | B125: 保管延長費（販売） | C125: Chi phí dịch vụ mua ngòai | D125: 荷造運賃 | E125: Chi phí vận chuyển hàng hóa | H125: 6003036545
A126: 6003036546 | B126: 物流保険料（販売） | C126: Chi phí dịch vụ mua ngòai | D126: 荷造運賃 | E126: Chi phí vận chuyển hàng hóa | H126: 6003036546
A127: 6003036547 | B127: 梱包費用（販売） | C127: Chi phí dịch vụ mua ngòai | D127: 荷造運賃 | E127: Chi phí vận chuyển hàng hóa | H127: 6003036547
A128: 6003036548 | B128: 返品手数料（販売） | C128: Chi phí dịch vụ mua ngòai | D128: 荷造運賃 | E128: Chi phí vận chuyển hàng hóa | H128: 6003036548
A129: 6003036549 | B129: 保管料（販売） | C129: Chi phí dịch vụ mua ngòai | D129: 荷造運賃 | E129: Chi phí vận chuyển hàng hóa | H129: 6003036549
A130: 6003036550 | B130: オーバーナイト費（販売） | C130: Chi phí dịch vụ mua ngòai | D130: 荷造運賃 | E130: Chi phí vận chuyển hàng hóa | H130: 6003036550
A131: 6003036551 | B131: バンニング費（販売） | C131: Chi phí dịch vụ mua ngòai | D131: 荷造運賃 | E131: Chi phí vận chuyển hàng hóa | H131: 6003036551
A132: 6003036552 | B132: その他物流費（販売） | C132: Chi phí dịch vụ mua ngòai | D132: 荷造運賃 | E132: Chi phí vận chuyển hàng hóa | F132: 6003036552 | H132: 6003036552
A133: 6003036554 | B133: 外部倉庫 取扱手数料（販売） | C133: Chi phí dịch vụ mua ngòai | D133: 荷造運賃 | E133: Chi phí vận chuyển hàng hóa | F133: 6003036554 | G133: 6003036554 | H133: 6003036554 | I133: 2017年1月追加。
A134: 6003036555 | B134: 外部倉庫 保管料（販売） | C134: Chi phí dịch vụ mua ngòai | D134: 荷造運賃 | E134: Chi phí vận chuyển hàng hóa | F134: 6003036555 | G134: 6003036555 | H134: 6003036555 | I134: 2017年1月追加。
A135: 6003036556 | B135: 外部倉庫 輸送料（販売） | C135: Chi phí dịch vụ mua ngòai | D135: 荷造運賃 | E135: Chi phí vận chuyển hàng hóa | F135: 6003036556 | G135: 6003036556 | H135: 6003036556 | I135: 2017年1月追加。
...

Sheet 原価センタ
B1: 原価センタ | D1: 採算区分 | E1: 原価区分
A2: 1412000004 | B2: 機器製造1課 | C2: 01. | D2: 製造 | E2: 製造 | G2: V02XD800
A3: 1412000005 | B3: 機器製造2課 | C3: 02. | D3: 製造 | E3: 製造
A4: 1412000062 | B4: 機器製造管理課 | C4: 03. | D4: 部内間接 | E4: 製造
A5: 1412000034 | B5: トナー製造課 | C5: 04. | D5: 製造 | E5: 製造
A6: 1412000048 | B6: トナー生産技術課 | C6: 05. | D6: 部内間接 | E6: 製造
A7: 1412000055 | B7: トナー品質管理課 | C7: 06. | D7: 部内間接 | E7: 製造
A8: 1412000050 | B8: MD1課 | C8: 07. | D8: 製造 | E8: 製造
A9: 1412000077 | B9: MD2課 | C9: 08. | D9: 製造 | E9: 製造
A10: 1412000053 | B10: 工程品質管理1課 | C10: 09. | D10: 部内間接 | E10: 製造
A11: 1412000008 | B11: 生産管理課 | C11: 10. | D11: 部内間接 | E11: 製造
A12: 1412000010 | B12: 採算管理課 | C12: 11. | D12: 部外間接1 | E12: 製造
A13: 1412000054 | B13: マスター管理課 | C13: 12. | D13: 部外間接1 | E13: 製造
A14: 1412000036 | B14: 部品管理課 | C14: 13. | D14: 部内間接 | E14: 製造
... A58: 1412000099 | B58: MD4課 | C58: 65. | D58: 製造 | E58: 製造
A59: 1412000101 | B59: EI2課 | C59: 66 | D59: 製造 | E59: 製造

Sheet 稼働日
A2: FY2026 | B2: 稼働日
A3: 4 | B3: 20
A4: 5 | B4: 19
A5: 6 | B5: 21
A6: 7 | B6: 23
A7: 8 | B7: 20
A8: 9 | B8: 19
A9: 10 | B9: 23
A10: 11 | B10: 20
A11: 12 | B11: 22
A12: 1 | B12: 20
A13: 2 | B13: 15
A14: 3 | B14: 20
